Workbook

Sheet DEMANDA
A1: DEMANDA (unidades por año)
A3: Ref. | B3: Línea | C3: Producto | D3: 2026 | E3: 2027 | F3: 2028 | G3: 2029 | H3: 2030 | I3: 2031 | J3: 2032 | K3: 2033 | L3: 2034 | M3: 2035
A4: D01 | B4: RECARGAS | C4: Parte de la planta industrial | D4: =(PROY_INDEXADO!B63+PROY_INDEXADO!B65+PROY_INDEXADO!B66+PROY_INDEXADO!B67)/PROY_INDEXADO!B75 -> 0.28778641 | E4: =(PROY_INDEXADO!C63+PROY_INDEXADO!C65+PROY_INDEXADO!C66+PROY_INDEXADO!C67)/PROY_INDEXADO!C75 -> 0.28783937 | F4: =(PROY_INDEXADO!D63+PROY_INDEXADO!D65+PROY_INDEXADO!D66+PROY_INDEXADO!D67)/PROY_INDEXADO!D75 -> 0.28789154 | G4: =(PROY_INDEXADO!E63+PROY_INDEXADO!E65+PROY_INDEXADO!E66+PROY_INDEXADO!E67)/PROY_INDEXADO!E75 -> 0.28794305 | H4: =(PROY_INDEXADO!F63+PROY_INDEXADO!F65+PROY_INDEXADO!F66+PROY_INDEXADO!F67)/PROY_INDEXADO!F75 -> 0.2879932 | I4: =(PROY_INDEXADO!G63+PROY_INDEXADO!G65+PROY_INDEXADO!G66+PROY_INDEXADO!G67)/PROY_INDEXADO!G75 -> 0.28804275 | J4: =(PROY_INDEXADO!H63+PROY_INDEXADO!H65+PROY_INDEXADO!H66+PROY_INDEXADO!H67)/PROY_INDEXADO!H75 -> 0.28809088 | K4: =(PROY_INDEXADO!I63+PROY_INDEXADO!I65+PROY_INDEXADO!I66+PROY_INDEXADO!I67)/PROY_INDEXADO!I75 -> 0.28814012 | ... M4: =(PROY_INDEXADO!K63+PROY_INDEXADO!K65+PROY_INDEXADO!K66+PROY_INDEXADO!K67)/PROY_INDEXADO!K75 -> 0.28823651
A5: D02 | C5: % de unidades nuevas que van a CABA | D5: =(PROY_INDEXADO!B79+PROY_INDEXADO!B80+PROY_INDEXADO!B81+PROY_INDEXADO!B82)/PROY_INDEXADO!B93 -> 0.23315299 | E5: =(PROY_INDEXADO!C79+PROY_INDEXADO!C80+PROY_INDEXADO!C81+PROY_INDEXADO!C82)/PROY_INDEXADO!C93 -> 0.23306476 | F5: =(PROY_INDEXADO!D79+PROY_INDEXADO!D80+PROY_INDEXADO!D81+PROY_INDEXADO!D82)/PROY_INDEXADO!D93 -> 0.23305972 | G5: =(PROY_INDEXADO!E79+PROY_INDEXADO!E80+PROY_INDEXADO!E81+PROY_INDEXADO!E82)/PROY_INDEXADO!E93 -> 0.23312519 | H5: =(PROY_INDEXADO!F79+PROY_INDEXADO!F80+PROY_INDEXADO!F81+PROY_INDEXADO!F82)/PROY_INDEXADO!F93 -> 0.23328948 | I5: =(PROY_INDEXADO!G79+PROY_INDEXADO!G80+PROY_INDEXADO!G81+PROY_INDEXADO!G82)/PROY_INDEXADO!G93 -> 0.23356853 | J5: =(PROY_INDEXADO!H79+PROY_INDEXADO!H80+PROY_INDEXADO!H81+PROY_INDEXADO!H82)/PROY_INDEXADO!H93 -> 0.23398058 | K5: =(PROY_INDEXADO!I79+PROY_INDEXADO!I80+PROY_INDEXADO!I81+PROY_INDEXADO!I82)/PROY_INDEXADO!I93 -> 0.23454186 | ... M5: =(PROY_INDEXADO!K79+PROY_INDEXADO!K80+PROY_INDEXADO!K81+PROY_INDEXADO!K82)/PROY_INDEXADO!K93 -> 0.23621517
A6: D03 | B6: RECARGAS | C6: % de recargas de la planta industrial en CABA | D6: =PROY_INDEXADO!B63/(PROY_INDEXADO!B63+PROY_INDEXADO!B65+PROY_INDEXADO!B66+PROY_INDEXADO!B67) -> 0.21154491 | E6: =PROY_INDEXADO!C63/(PROY_INDEXADO!C63+PROY_INDEXADO!C65+PROY_INDEXADO!C66+PROY_INDEXADO!C67) -> 0.21080896 | F6: =PROY_INDEXADO!D63/(PROY_INDEXADO!D63+PROY_INDEXADO!D65+PROY_INDEXADO!D66+PROY_INDEXADO!D67) -> 0.21012352 | G6: =PROY_INDEXADO!E63/(PROY_INDEXADO!E63+PROY_INDEXADO!E65+PROY_INDEXADO!E66+PROY_INDEXADO!E67) -> 0.20949374 | H6: =PROY_INDEXADO!F63/(PROY_INDEXADO!F63+PROY_INDEXADO!F65+PROY_INDEXADO!F66+PROY_INDEXADO!F67) -> 0.20893171 | I6: =PROY_INDEXADO!G63/(PROY_INDEXADO!G63+PROY_INDEXADO!G65+PROY_INDEXADO!G66+PROY_INDEXADO!G67) -> 0.208444 | J6: =PROY_INDEXADO!H63/(PROY_INDEXADO!H63+PROY_INDEXADO!H65+PROY_INDEXADO!H66+PROY_INDEXADO!H67) -> 0.20804543 | K6: =PROY_INDEXADO!I63/(PROY_INDEXADO!I63+PROY_INDEXADO!I65+PROY_INDEXADO!I66+PROY_INDEXADO!I67) -> 0.20774816 | ... M6: =PROY_INDEXADO!K63/(PROY_INDEXADO!K63+PROY_INDEXADO!K65+PROY_INDEXADO!K66+PROY_INDEXADO!K67) -> 0.20752849
A7: D04 | B7: RECARGAS | C7: % de recargas de equipos usados | D7: =PROY_USADOS!$L$5 -> 0.047640139 | E7: =PROY_USADOS!$L$6 -> 0.047635883 | F7: =PROY_USADOS!$L$7 -> 0.047636541 | G7: =PROY_USADOS!$L$8 -> 0.047638627 | H7: =PROY_USADOS!$L$9 -> 0.047635501 | I7: =PROY_USADOS!$L$10 -> 0.047637147 | J7: =PROY_USADOS!$L$11 -> 0.047636246 | K7: =PROY_USADOS!$L$12 -> 0.047637525 | L7: =PROY_USADOS!$L$13 -> 0.047635817 | M7: =PROY_USADOS!$L$14 -> 0.047633261
A8: D05 | B8: MANUALES | C8: Matafuego ABC 1 kg | D8: =PROY_INDEXADO!B3 -> 4178.7365 | E8: =PROY_INDEXADO!C3 -> 5997.304 | F8: =PROY_INDEXADO!D3 -> 6851.7478 | G8: =PROY_INDEXADO!E3 -> 8467.1355 | H8: =PROY_INDEXADO!F3 -> 12680.633 | I8: =PROY_INDEXADO!G3 -> 15620.253 | J8: =PROY_INDEXADO!H3 -> 20332.553 | K8: =PROY_INDEXADO!I3 -> 25132.078 | ... M8: =PROY_INDEXADO!K3 -> 32072.639
A9: D06 | B9: MANUALES | C9: Matafuego ABC 2,5 kg | D9: =PROY_INDEXADO!B4 -> 295.03036 | E9: =PROY_INDEXADO!C4 -> 709.72745 | F9: =PROY_INDEXADO!D4 -> 986.86806 | G9: =PROY_INDEXADO!E4 -> 1500.6382 | H9: =PROY_INDEXADO!F4 -> 2312.6277 | I9: =PROY_INDEXADO!G4 -> 3252.8699 | J9: =PROY_INDEXADO!H4 -> 4102.3155 | K9: =PROY_INDEXADO!I4 -> 5104.3066 | ... M9: =PROY_INDEXADO!K4 -> 7424.8584
A10: D07 | B10: MANUALES | C10: Matafuego ABC 5 kg | D10: =PROY_INDEXADO!B5+PROY_RESERVAS!B30+PROY_RESERVAS!B69*$D$4 -> 2727.9036 | E10: =PROY_INDEXADO!C5+PROY_RESERVAS!C30+PROY_RESERVAS!C69*$D$4 -> 5488.9106 | F10: =PROY_INDEXADO!D5+PROY_RESERVAS!D30+PROY_RESERVAS!D69*$D$4 -> 7206.5855 | G10: =PROY_INDEXADO!E5+PROY_RESERVAS!E30+PROY_RESERVAS!E69*$D$4 -> 10420.908 | H10: =PROY_INDEXADO!F5+PROY_RESERVAS!F30+PROY_RESERVAS!F69*$D$4 -> 14495.071 | I10: =PROY_INDEXADO!G5+PROY_RESERVAS!G30+PROY_RESERVAS!G69*$D$4 -> 18737.061 | J10: =PROY_INDEXADO!H5+PROY_RESERVAS!H30+PROY_RESERVAS!H69*$D$4 -> 22634.482 | K10: =PROY_INDEXADO!I5+PROY_RESERVAS!I30+PROY_RESERVAS!I69*$D$4 -> 26002.338 | ... M10: =PROY_INDEXADO!K5+PROY_RESERVAS!K30+PROY_RESERVAS!K69*$D$4 -> 32428.771
A11: D08 | B11: MANUALES | C11: Matafuego ABC 10 kg | D11: =PROY_INDEXADO!B6+PROY_RESERVAS!B70*$D$4 -> 92.408754 | E11: =PROY_INDEXADO!C6+PROY_RESERVAS!C70*$D$4 -> 178.13943 | F11: =PROY_INDEXADO!D6+PROY_RESERVAS!D70*$D$4 -> 255.06523 | G11: =PROY_INDEXADO!E6+PROY_RESERVAS!E70*$D$4 -> 361.07103 | H11: =PROY_INDEXADO!F6+PROY_RESERVAS!F70*$D$4 -> 605.62479 | I11: =PROY_INDEXADO!G6+PROY_RESERVAS!G70*$D$4 -> 876.21675 | J11: =PROY_INDEXADO!H6+PROY_RESERVAS!H70*$D$4 -> 1130.355 | K11: =PROY_INDEXADO!I6+PROY_RESERVAS!I70*$D$4 -> 1397.6176 | ... M11: =PROY_INDEXADO!K6+PROY_RESERVAS!K70*$D$4 -> 1842.877
A12: D09 | B12: MANUALES | C12: Cilindro ABC 1 kg vacío | D12: =PROY_INDEXADO!B15 -> 0 | E12: =PROY_INDEXADO!C15 -> 0 | F12: =PROY_INDEXADO!D15 -> 7662.4 | G12: =PROY_INDEXADO!E15 -> 26694.8 | H12: =PROY_INDEXADO!F15 -> 49434.8 | I12: =PROY_INDEXADO!G15 -> 71680.2 | J12: =PROY_INDEXADO!H15 -> 101340.6 | K12: =PROY_INDEXADO!I15 -> 131001 | ... M12: =PROY_INDEXADO!K15 -> 170548
A13: D10 | B13: MANUALES | C13: Cilindro ABC 2,5 kg vacío | D13: =PROY_INDEXADO!B16 -> 0 | E13: =PROY_INDEXADO!C16 -> 0 | F13: =PROY_INDEXADO!D16 -> 299.6 | G13: =PROY_INDEXADO!E16 -> 1043.8 | H13: =PROY_INDEXADO!F16 -> 1933 | I13: =PROY_INDEXADO!G16 -> 2803 | J13: =PROY_INDEXADO!H16 -> 3963 | K13: =PROY_INDEXADO!I16 -> 5123 | ... M13: =PROY_INDEXADO!K16 -> 6669
A14: D11 | B14: MANUALES | C14: Cilindro ABC 5 kg vacío | D14: =PROY_INDEXADO!B17 -> 0 | E14: =PROY_INDEXADO!C17 -> 0 | F14: =PROY_INDEXADO!D17 -> 1478.8 | G14: =PROY_INDEXADO!E17 -> 5152 | H14: =PROY_INDEXADO!F17 -> 9540.8 | I14: =PROY_INDEXADO!G17 -> 13834.2 | J14: =PROY_INDEXADO!H17 -> 19558.6 | K14: =PROY_INDEXADO!I17 -> 25283 | ... M14: =PROY_INDEXADO!K17 -> 32915
A15: D12 | B15: MANUALES | C15: Cilindro ABC 10 kg vacío | D15: =PROY_INDEXADO!B18 -> 0 | E15: =PROY_INDEXADO!C18 -> 0 | F15: =PROY_INDEXADO!D18 -> 90.4 | G15: =PROY_INDEXADO!E18 -> 315 | H15: =PROY_INDEXADO!F18 -> 583.4 | I15: =PROY_INDEXADO!G18 -> 845.8 | J15: =PROY_INDEXADO!H18 -> 1195.4 | K15: =PROY_INDEXADO!I18 -> 1545 | ... M15: =PROY_INDEXADO!K18 -> 2011
A16: D13 | B16: RODANTES | C16: Matafuego ABC 25 kg | D16: =PROY_INDEXADO!B7 -> 34.051791 | E16: =PROY_INDEXADO!C7 -> 58.462147 | F16: =PROY_INDEXADO!D7 -> 75.20854 | G16: =PROY_INDEXADO!E7 -> 100.52985 | H16: =PROY_INDEXADO!F7 -> 155.876 | I16: =PROY_INDEXADO!G7 -> 211.93448 | J16: =PROY_INDEXADO!H7 -> 272.66823 | K16: =PROY_INDEXADO!I7 -> 337.84867 | ... M16: =PROY_INDEXADO!K7 -> 453.27053
A17: D14 | B17: RODANTES | C17: Matafuego ABC 50 kg | D17: =PROY_INDEXADO!B8+PROY_RESERVAS!B79*$D$4 -> 75.201727 | E17: =PROY_INDEXADO!C8+PROY_RESERVAS!C79*$D$4 -> 129.20669 | F17: =PROY_INDEXADO!D8+PROY_RESERVAS!D79*$D$4 -> 166.6531 | G17: =PROY_INDEXADO!E8+PROY_RESERVAS!E79*$D$4 -> 222.70533 | H17: =PROY_INDEXADO!F8+PROY_RESERVAS!F79*$D$4 -> 344.53881 | I17: =PROY_INDEXADO!G8+PROY_RESERVAS!G79*$D$4 -> 468.2272 | J17: =PROY_INDEXADO!H8+PROY_RESERVAS!H79*$D$4 -> 601.64 | K17: =PROY_INDEXADO!I8+PROY_RESERVAS!I79*$D$4 -> 744.53334 | ... M17: =PROY_INDEXADO!K8+PROY_RESERVAS!K79*$D$4 -> 998.25998
A18: D15 | B18: RODANTES | C18: Matafuego ABC 70 kg | D18: =PROY_INDEXADO!B9 -> 16.34486 | E18: =PROY_INDEXADO!C9 -> 28.061831 | F18: =PROY_INDEXADO!D9 -> 36.100099 | G18: =PROY_INDEXADO!E9 -> 48.254329 | H18: =PROY_INDEXADO!F9 -> 74.820482 | I18: =PROY_INDEXADO!G9 -> 101.72855 | J18: =PROY_INDEXADO!H9 -> 130.88075 | K18: =PROY_INDEXADO!I9 -> 162.16736 | ... M18: =PROY_INDEXADO!K9 -> 217.56986
A19: D16 | B19: RODANTES | C19: Matafuego ABC 100 kg | D19: =PROY_INDEXADO!B10+PROY_RESERVAS!B80*$D$4 -> 11.18436 | E19: =PROY_INDEXADO!C10+PROY_RESERVAS!C80*$D$4 -> 18.722277 | F19: =PROY_INDEXADO!D10+PROY_RESERVAS!D80*$D$4 -> 24.368909 | G19: =PROY_INDEXADO!E10+PROY_RESERVAS!E80*$D$4 -> 32.486118 | H19: =PROY_INDEXADO!F10+PROY_RESERVAS!F80*$D$4 -> 50.499062 | I19: =PROY_INDEXADO!G10+PROY_RESERVAS!G80*$D$4 -> 68.178767 | J19: =PROY_INDEXADO!H10+PROY_RESERVAS!H80*$D$4 -> 87.627957 | K19: =PROY_INDEXADO!I10+PROY_RESERVAS!I80*$D$4 -> 108.50009 | ... M19: =PROY_INDEXADO!K10+PROY_RESERVAS!K80*$D$4 -> 145.17607
A20: D17 | B20: RODANTES | C20: Cilindro ABC 25 kg vacío | D20: =PROY_INDEXADO!B19 -> 0 | E20: =PROY_INDEXADO!C19 -> 0 | F20: =PROY_INDEXADO!D19 -> 14.4 | G20: =PROY_INDEXADO!E19 -> 50.2 | H20: =PROY_INDEXADO!F19 -> 93 | I20: =PROY_INDEXADO!G19 -> 135 | J20: =PROY_INDEXADO!H19 -> 191 | K20: =PROY_INDEXADO!I19 -> 247 | ... M20: =PROY_INDEXADO!K19 -> 322
A21: D18 | B21: RODANTES | C21: Cilindro ABC 50 kg vacío | D21: =PROY_INDEXADO!B20 -> 0 | E21: =PROY_INDEXADO!C20 -> 0 | F21: =PROY_INDEXADO!D20 -> 31.8 | G21: =PROY_INDEXADO!E20 -> 110.8 | H21: =PROY_INDEXADO!F20 -> 205.2 | I21: =PROY_INDEXADO!G20 -> 297.6 | J21: =PROY_INDEXADO!H20 -> 420.8 | K21: =PROY_INDEXADO!I20 -> 544 | ... M21: =PROY_INDEXADO!K20 -> 708
A22: D19 | B22: RODANTES | C22: Cilindro ABC 70 kg vacío | D22: =PROY_INDEXADO!B21 -> 0 | E22: =PROY_INDEXADO!C21 -> 0 | F22: =PROY_INDEXADO!D21 -> 7 | G22: =PROY_INDEXADO!E21 -> 24.4 | H22: =PROY_INDEXADO!F21 -> 45.2 | I22: =PROY_INDEXADO!G21 -> 65.4 | J22: =PROY_INDEXADO!H21 -> 92.2 | K22: =PROY_INDEXADO!I21 -> 119 | ... M22: =PROY_INDEXADO!K21 -> 155
A23: D20 | B23: RODANTES | C23: Cilindro ABC 100 kg vacío | D23: =PROY_INDEXADO!B22 -> 0 | E23: =PROY_INDEXADO!C22 -> 0 | F23: =PROY_INDEXADO!D22 -> 4.6 | G23: =PROY_INDEXADO!E22 -> 16 | H23: =PROY_INDEXADO!F22 -> 29.6 | I23: =PROY_INDEXADO!G22 -> 42.8 | J23: =PROY_INDEXADO!H22 -> 60.4 | K23: =PROY_INDEXADO!I22 -> 78 | ... M23: =PROY_INDEXADO!K22 -> 102
A24: D21 | B24: RECARGAS | C24: Recarga ABC 1 kg | D24: =(PROY_INDEXADO!B27)*$D$4 -> 1000.7721 | E24: =(PROY_INDEXADO!C27)*$D$4 -> 4883.9039 | F24: =(PROY_INDEXADO!D27)*$D$4 -> 8790.7495 | G24: =(PROY_INDEXADO!E27)*$D$4 -> 16129.942 | H24: =(PROY_INDEXADO!F27)*$D$4 -> 24251.826 | I24: =(PROY_INDEXADO!G27)*$D$4 -> 33788.376 | J24: =(PROY_INDEXADO!H27)*$D$4 -> 42480.335 | K24: =(PROY_INDEXADO!I27)*$D$4 -> 49327.846 | ... M24: =(PROY_INDEXADO!K27)*$D$4 -> 56487.491
A25: D22 | B25: RECARGAS | C25: Recarga ABC 2,5 kg | D25: =(PROY_INDEXADO!B28)*$D$4 -> 94.968557 | E25: =(PROY_INDEXADO!C28)*$D$4 -> 370.50026 | F25: =(PROY_INDEXADO!D28)*$D$4 -> 848.15525 | G25: =(PROY_INDEXADO!E28)*$D$4 -> 1561.5415 | H25: =(PROY_INDEXADO!F28)*$D$4 -> 2259.3754 | I25: =(PROY_INDEXADO!G28)*$D$4 -> 2999.8693 | J25: =(PROY_INDEXADO!H28)*$D$4 -> 3686.5139 | K25: =(PROY_INDEXADO!I28)*$D$4 -> 4104.7172 | ... M25: =(PROY_INDEXADO!K28)*$D$4 -> 4783.2292
A26: D23 | B26: RECARGAS | C26: Recarga ABC 5 kg | D26: =(PROY_INDEXADO!B29+PROY_RESERVAS!B54)*$D$4 -> 579.42746 | E26: =(PROY_INDEXADO!C29+PROY_RESERVAS!C54)*$D$4 -> 2341.0327 | F26: =(PROY_INDEXADO!D29+PROY_RESERVAS!D54)*$D$4 -> 5274.796 | G26: =(PROY_INDEXADO!E29+PROY_RESERVAS!E54)*$D$4 -> 9966.207 | H26: =(PROY_INDEXADO!F29+PROY_RESERVAS!F54)*$D$4 -> 14367.038 | I26: =(PROY_INDEXADO!G29+PROY_RESERVAS!G54)*$D$4 -> 19107.591 | J26: =(PROY_INDEXADO!H29+PROY_RESERVAS!H54)*$D$4 -> 23397.064 | K26: =(PROY_INDEXADO!I29+PROY_RESERVAS!I54)*$D$4 -> 25952.927 | ... M26: =(PROY_INDEXADO!K29+PROY_RESERVAS!K54)*$D$4 -> 30068.838
A27: D24 | B27: RECARGAS | C27: Recarga ABC 10 kg | D27: =(PROY_INDEXADO!B30+PROY_RESERVAS!B55)*$D$4 -> 34.633262 | E27: =(PROY_INDEXADO!C30+PROY_RESERVAS!C55)*$D$4 -> 127.40782 | F27: =(PROY_INDEXADO!D30+PROY_RESERVAS!D55)*$D$4 -> 298.42726 | G27: =(PROY_INDEXADO!E30+PROY_RESERVAS!E55)*$D$4 -> 570.51062 | H27: =(PROY_INDEXADO!F30+PROY_RESERVAS!F55)*$D$4 -> 827.66705 | I27: =(PROY_INDEXADO!G30+PROY_RESERVAS!G55)*$D$4 -> 1108.6657 | J27: =(PROY_INDEXADO!H30+PROY_RESERVAS!H55)*$D$4 -> 1356.8203 | K27: =(PROY_INDEXADO!I30+PROY_RESERVAS!I55)*$D$4 -> 1502.3932 | ... M27: =(PROY_INDEXADO!K30+PROY_RESERVAS!K55)*$D$4 -> 1741.3814
A28: D25 | B28: RECARGAS | C28: Recarga Agua 10 l | D28: =(PROY_INDEXADO!B31+PROY_RESERVAS!B56)*$D$4 -> 46.422462 | E28: =(PROY_INDEXADO!C31+PROY_RESERVAS!C56)*$D$4 -> 187.18306 | F28: =(PROY_INDEXADO!D31+PROY_RESERVAS!D56)*$D$4 -> 428.90614 | G28: =(PROY_INDEXADO!E31+PROY_RESERVAS!E56)*$D$4 -> 804.78066 | H28: =(PROY_INDEXADO!F31+PROY_RESERVAS!F56)*$D$4 -> 1161.3521 | I28: =(PROY_INDEXADO!G31+PROY_RESERVAS!G56)*$D$4 -> 1552.2496 | J28: =(PROY_INDEXADO!H31+PROY_RESERVAS!H56)*$D$4 -> 1902.2563 | K28: =(PROY_INDEXADO!I31+PROY_RESERVAS!I56)*$D$4 -> 2114.8904 | ... M28: =(PROY_INDEXADO!K31+PROY_RESERVAS!K56)*$D$4 -> 2458.5058
A29: D26 | B29: RECARGAS | C29: Recarga AFFF 10 l | D29: =(PROY_INDEXADO!B32+PROY_RESERVAS!B57)*$D$4 -> 6.837342 | E29: =(PROY_INDEXADO!C32+PROY_RESERVAS!C57)*$D$4 -> 47.000054 | F29: =(PROY_INDEXADO!D32+PROY_RESERVAS!D57)*$D$4 -> 92.266417 | G29: =(PROY_INDEXADO!E32+PROY_RESERVAS!E57)*$D$4 -> 153.50372 | H29: =(PROY_INDEXADO!F32+PROY_RESERVAS!F57)*$D$4 -> 216.64243 | I29: =(PROY_INDEXADO!G32+PROY_RESERVAS!G57)*$D$4 -> 280.2678 | J29: =(PROY_INDEXADO!H32+PROY_RESERVAS!H57)*$D$4 -> 347.62935 | K29: =(PROY_INDEXADO!I32+PROY_RESERVAS!I57)*$D$4 -> 393.29385 | ... M29: =(PROY_INDEXADO!K32+PROY_RESERVAS!K57)*$D$4 -> 466.91659
A30: D27 | B30: RECARGAS | C30: Recarga AFFF 50 l | D30: =(PROY_INDEXADO!B33+PROY_RESERVAS!B58)*$D$4 -> 3.5625642 | E30: =(PROY_INDEXADO!C33+PROY_RESERVAS!C58)*$D$4 -> 24.238384 | F30: =(PROY_INDEXADO!D33+PROY_RESERVAS!D58)*$D$4 -> 47.906029 | G30: =(PROY_INDEXADO!E33+PROY_RESERVAS!E58)*$D$4 -> 82.117304 | H30: =(PROY_INDEXADO!F33+PROY_RESERVAS!F58)*$D$4 -> 116.23765 | I30: =(PROY_INDEXADO!G33+PROY_RESERVAS!G58)*$D$4 -> 149.80068 | J30: =(PROY_INDEXADO!H33+PROY_RESERVAS!H58)*$D$4 -> 183.05101 | K30: =(PROY_INDEXADO!I33+PROY_RESERVAS!I58)*$D$4 -> 206.96966 | ... M30: =(PROY_INDEXADO!K33+PROY_RESERVAS!K58)*$D$4 -> 243.56826
A31: D28 | B31: RECARGAS | C31: Recarga BC 5 kg | D31: =(PROY_INDEXADO!B34+PROY_RESERVAS!B59)*$D$4 -> 2.2526531 | E31: =(PROY_INDEXADO!C34+PROY_RESERVAS!C59)*$D$4 -> 13.834788 | F31: =(PROY_INDEXADO!D34+PROY_RESERVAS!D59)*$D$4 -> 25.869027 | G31: =(PROY_INDEXADO!E34+PROY_RESERVAS!E59)*$D$4 -> 46.478222 | H31: =(PROY_INDEXADO!F34+PROY_RESERVAS!F59)*$D$4 -> 64.117719 | I31: =(PROY_INDEXADO!G34+PROY_RESERVAS!G59)*$D$4 -> 85.147323 | J31: =(PROY_INDEXADO!H34+PROY_RESERVAS!H59)*$D$4 -> 107.29949 | K31: =(PROY_INDEXADO!I34+PROY_RESERVAS!I59)*$D$4 -> 118.97348 | ... M31: =(PROY_INDEXADO!K34+PROY_RESERVAS!K59)*$D$4 -> 140.86546
A32: D29 | B32: RECARGAS | C32: Recarga Clase K 6 l | D32: =(PROY_INDEXADO!B35+PROY_RESERVAS!B60)*$D$4 -> 23.866187 | E32: =(PROY_INDEXADO!C35+PROY_RESERVAS!C60)*$D$4 -> 97.674378 | F32: =(PROY_INDEXADO!D35+PROY_RESERVAS!D60)*$D$4 -> 217.45094 | G32: =(PROY_INDEXADO!E35+PROY_RESERVAS!E60)*$D$4 -> 395.3897 | H32: =(PROY_INDEXADO!F35+PROY_RESERVAS!F60)*$D$4 -> 570.71658 | I32: =(PROY_INDEXADO!G35+PROY_RESERVAS!G60)*$D$4 -> 756.17071 | J32: =(PROY_INDEXADO!H35+PROY_RESERVAS!H60)*$D$4 -> 930.20151 | K32: =(PROY_INDEXADO!I35+PROY_RESERVAS!I60)*$D$4 -> 1041.0787 | ... M32: =(PROY_INDEXADO!K35+PROY_RESERVAS!K60)*$D$4 -> 1212.3174
A33: D30 | B33: RECARGAS | C33: Recarga CO₂ 2 kg | D33: =(PROY_INDEXADO!B36)*$D$4 -> 129.6812 | E33: =(PROY_INDEXADO!C36)*$D$4 -> 488.42577 | F33: =(PROY_INDEXADO!D36)*$D$4 -> 1138.2519 | G33: =(PROY_INDEXADO!E36)*$D$4 -> 2176.028 | H33: =(PROY_INDEXADO!F36)*$D$4 -> 3142.6693 | I33: =(PROY_INDEXADO!G36)*$D$4 -> 4177.1867 | J33: =(PROY_INDEXADO!H36)*$D$4 -> 5107.2013 | K33: =(PROY_INDEXADO!I36)*$D$4 -> 5645.5652 | ... M33: =(PROY_INDEXADO!K36)*$D$4 -> 6542.6807
A34: D31 | B34: RECARGAS | C34: Recarga CO₂ 5 kg | D34: =(PROY_INDEXADO!B37+PROY_RESERVAS!B61)*$D$4 -> 38.037061 | E34: =(PROY_INDEXADO!C37+PROY_RESERVAS!C61)*$D$4 -> 192.71052 | F34: =(PROY_INDEXADO!D37+PROY_RESERVAS!D61)*$D$4 -> 412.57829 | G34: =(PROY_INDEXADO!E37+PROY_RESERVAS!E61)*$D$4 -> 739.4051 | H34: =(PROY_INDEXADO!F37+PROY_RESERVAS!F61)*$D$4 -> 1065.1717 | I34: =(PROY_INDEXADO!G37+PROY_RESERVAS!G61)*$D$4 -> 1419.2077 | J34: =(PROY_INDEXADO!H37+PROY_RESERVAS!H61)*$D$4 -> 1758.0599 | K34: =(PROY_INDEXADO!I37+PROY_RESERVAS!I61)*$D$4 -> 1983.2685 | ... M34: =(PROY_INDEXADO!K37+PROY_RESERVAS!K61)*$D$4 -> 2330.9482
A35: D32 | B35: RECARGAS | C35: Recarga HCFC 5 kg | D35: =(PROY_INDEXADO!B38+PROY_RESERVAS!B62)*$D$4 -> 5.5274309 | E35: =(PROY_INDEXADO!C38+PROY_RESERVAS!C62)*$D$4 -> 32.82927 | F35: =(PROY_INDEXADO!D38+PROY_RESERVAS!D62)*$D$4 -> 67.300015 | G35: =(PROY_INDEXADO!E38+PROY_RESERVAS!E62)*$D$4 -> 116.75936 | H35: =(PROY_INDEXADO!F38+PROY_RESERVAS!F62)*$D$4 -> 167.35004 | I35: =(PROY_INDEXADO!G38+PROY_RESERVAS!G62)*$D$4 -> 219.6805 | J35: =(PROY_INDEXADO!H38+PROY_RESERVAS!H62)*$D$4 -> 275.08031 | K35: =(PROY_INDEXADO!I38+PROY_RESERVAS!I62)*$D$4 -> 312.028 | ... M35: =(PROY_INDEXADO!K38+PROY_RESERVAS!K62)*$D$4 -> 370.07637
A36: D33 | B36: RECARGAS | C36: Recarga Clase D 9 l | D36: =(PROY_INDEXADO!B39+PROY_RESERVAS!B63)*$D$4 -> 2.2526531 | E36: =(PROY_INDEXADO!C39+PROY_RESERVAS!C63)*$D$4 -> 13.834788 | F36: =(PROY_INDEXADO!D39+PROY_RESERVAS!D63)*$D$4 -> 25.869027 | G36: =(PROY_INDEXADO!E39+PROY_RESERVAS!E63)*$D$4 -> 43.248307 | H36: =(PROY_INDEXADO!F39+PROY_RESERVAS!F63)*$D$4 -> 59.924629 | I36: =(PROY_INDEXADO!G39+PROY_RESERVAS!G63)*$D$4 -> 74.469092 | J36: =(PROY_INDEXADO!H39+PROY_RESERVAS!H63)*$D$4 -> 95.665355 | K36: =(PROY_INDEXADO!I39+PROY_RESERVAS!I63)*$D$4 -> 106.7423 | ... M36: =(PROY_INDEXADO!K39+PROY_RESERVAS!K63)*$D$4 -> 127.11145
A37: D34 | B37: RECARGAS | C37: Recarga ABC 25 kg | D37: =(PROY_INDEXADO!B40)*$D$4 -> 5.0759056 | E37: =(PROY_INDEXADO!C40)*$D$4 -> 24.746126 | F37: =(PROY_INDEXADO!D40)*$D$4 -> 53.778522 | G37: =(PROY_INDEXADO!E40)*$D$4 -> 96.864192 | H37: =(PROY_INDEXADO!F40)*$D$4 -> 139.32678 | I37: =(PROY_INDEXADO!G40)*$D$4 -> 185.11009 | J37: =(PROY_INDEXADO!H40)*$D$4 -> 228.05109 | K37: =(PROY_INDEXADO!I40)*$D$4 -> 256.03715 | ... M37: =(PROY_INDEXADO!K40)*$D$4 -> 299.85609
A38: D35 | B38: RECARGAS | C38: Recarga ABC 50 kg | D38: =(PROY_INDEXADO!B41+PROY_RESERVAS!B64)*$D$4 -> 11.454779 | E38: =(PROY_INDEXADO!C41+PROY_RESERVAS!C64)*$D$4 -> 55.304836 | F38: =(PROY_INDEXADO!D41+PROY_RESERVAS!D64)*$D$4 -> 120.32725 | G38: =(PROY_INDEXADO!E41+PROY_RESERVAS!E64)*$D$4 -> 216.55466 | H38: =(PROY_INDEXADO!F41+PROY_RESERVAS!F64)*$D$4 -> 311.41129 | I38: =(PROY_INDEXADO!G41+PROY_RESERVAS!G64)*$D$4 -> 413.86128 | J38: =(PROY_INDEXADO!H41+PROY_RESERVAS!H64)*$D$4 -> 509.77041 | K38: =(PROY_INDEXADO!I41+PROY_RESERVAS!I64)*$D$4 -> 572.20312 | ... M38: =(PROY_INDEXADO!K41+PROY_RESERVAS!K64)*$D$4 -> 670.0437
A39: D36 | B39: RECARGAS | C39: Recarga ABC 70 kg | D39: =(PROY_INDEXADO!B42)*$D$4 -> 2.4364347 | E39: =(PROY_INDEXADO!C42)*$D$4 -> 11.87814 | F39: =(PROY_INDEXADO!D42)*$D$4 -> 25.813691 | G39: =(PROY_INDEXADO!E42)*$D$4 -> 46.494812 | H39: =(PROY_INDEXADO!F42)*$D$4 -> 66.876856 | I39: =(PROY_INDEXADO!G42)*$D$4 -> 88.852841 | J39: =(PROY_INDEXADO!H42)*$D$4 -> 109.46452 | K39: =(PROY_INDEXADO!I42)*$D$4 -> 122.89783 | ... M39: =(PROY_INDEXADO!K42)*$D$4 -> 143.93092
A40: D37 | B40: RECARGAS | C40: Recarga ABC 100 kg | D40: =(PROY_INDEXADO!B43+PROY_RESERVAS!B65)*$D$4 -> 1.9120762 | E40: =(PROY_INDEXADO!C43+PROY_RESERVAS!C65)*$D$4 -> 8.2065467 | F40: =(PROY_INDEXADO!D43+PROY_RESERVAS!D65)*$D$4 -> 17.7847 | G40: =(PROY_INDEXADO!E43+PROY_RESERVAS!E65)*$D$4 -> 31.859901 | H40: =(PROY_INDEXADO!F43+PROY_RESERVAS!F65)*$D$4 -> 46.023503 | I40: =(PROY_INDEXADO!G43+PROY_RESERVAS!G65)*$D$4 -> 60.961946 | J40: =(PROY_INDEXADO!H43+PROY_RESERVAS!H65)*$D$4 -> 74.990853 | K40: =(PROY_INDEXADO!I43+PROY_RESERVAS!I65)*$D$4 -> 84.234181 | ... M40: =(PROY_INDEXADO!K43+PROY_RESERVAS!K65)*$D$4 -> 98.544026
A41: D38 | B41: RECARGAS | C41: Sustitutos nuevos (kit) | D41: =PROY_RESERVAS!B81*$D$4 -> 23.598486 | E41: =PROY_RESERVAS!C81*$D$4 -> 73.956311 | F41: =PROY_RESERVAS!D81*$D$4 -> 100.52859 | G41: =PROY_RESERVAS!E81*$D$4 -> 172.50877 | H41: =PROY_RESERVAS!F81*$D$4 -> 184.73969 | I41: =PROY_RESERVAS!G81*$D$4 -> 213.60946 | J41: =PROY_RESERVAS!H81*$D$4 -> 205.50348 | K41: =PROY_RESERVAS!I81*$D$4 -> 163.46268 | ... M41: =PROY_RESERVAS!K81*$D$4 -> 129.8924
A42: D39 | B42: REVENDIDOS | C42: Matafuego Agua 10 l | D42: =PROY_INDEXADO!B48+PROY_RESERVAS!B71*$D$4 -> 176.18353 | E42: =PROY_INDEXADO!C48+PROY_RESERVAS!C71*$D$4 -> 321.85832 | F42: =PROY_INDEXADO!D48+PROY_RESERVAS!D71*$D$4 -> 439.27958 | G42: =PROY_INDEXADO!E48+PROY_RESERVAS!E71*$D$4 -> 606.54581 | H42: =PROY_INDEXADO!F48+PROY_RESERVAS!F71*$D$4 -> 979.22006 | I42: =PROY_INDEXADO!G48+PROY_RESERVAS!G71*$D$4 -> 1374.7435 | J42: =PROY_INDEXADO!H48+PROY_RESERVAS!H71*$D$4 -> 1771.7592 | K42: =PROY_INDEXADO!I48+PROY_RESERVAS!I71*$D$4 -> 2191.7907 | ... M42: =PROY_INDEXADO!K48+PROY_RESERVAS!K71*$D$4 -> 2908.135
A43: D40 | B43: REVENDIDOS | C43: Matafuego AFFF 10 l | D43: =PROY_INDEXADO!B49+PROY_RESERVAS!B72*$D$4 -> 99.789572 | E43: =PROY_INDEXADO!C49+PROY_RESERVAS!C72*$D$4 -> 160.18902 | F43: =PROY_INDEXADO!D49+PROY_RESERVAS!D72*$D$4 -> 194.0195 | G43: =PROY_INDEXADO!E49+PROY_RESERVAS!E72*$D$4 -> 248.51536 | H43: =PROY_INDEXADO!F49+PROY_RESERVAS!F72*$D$4 -> 361.21734 | I43: =PROY_INDEXADO!G49+PROY_RESERVAS!G72*$D$4 -> 448.57469 | J43: =PROY_INDEXADO!H49+PROY_RESERVAS!H72*$D$4 -> 574.67983 | K43: =PROY_INDEXADO!I49+PROY_RESERVAS!I72*$D$4 -> 712.49398 | ... M43: =PROY_INDEXADO!K49+PROY_RESERVAS!K72*$D$4 -> 971.50993
A44: D41 | B44: REVENDIDOS | C44: Matafuego AFFF 50 l | D44: =PROY_INDEXADO!B50+PROY_RESERVAS!B73*$D$4 -> 42.931409 | E44: =PROY_INDEXADO!C50+PROY_RESERVAS!C73*$D$4 -> 68.537322 | F44: =PROY_INDEXADO!D50+PROY_RESERVAS!D73*$D$4 -> 83.194383 | G44: =PROY_INDEXADO!E50+PROY_RESERVAS!E73*$D$4 -> 106.83959 | H44: =PROY_INDEXADO!F50+PROY_RESERVAS!F73*$D$4 -> 154.74576 | I44: =PROY_INDEXADO!G50+PROY_RESERVAS!G73*$D$4 -> 192.30385 | J44: =PROY_INDEXADO!H50+PROY_RESERVAS!H73*$D$4 -> 246.35097 | K44: =PROY_INDEXADO!I50+PROY_RESERVAS!I73*$D$4 -> 305.41623 | ... M44: =PROY_INDEXADO!K50+PROY_RESERVAS!K73*$D$4 -> 416.43335
A45: D42 | B45: REVENDIDOS | C45: Matafuego BC 5 kg | D45: =PROY_INDEXADO!B51+PROY_RESERVAS!B74*$D$4 -> 28.716868 | E45: =PROY_INDEXADO!C51+PROY_RESERVAS!C74*$D$4 -> 45.696344 | F45: =PROY_INDEXADO!D51+PROY_RESERVAS!D74*$D$4 -> 55.275861 | G45: =PROY_INDEXADO!E51+PROY_RESERVAS!E74*$D$4 -> 71.125671 | H45: =PROY_INDEXADO!F51+PROY_RESERVAS!F74*$D$4 -> 103.25018 | I45: =PROY_INDEXADO!G51+PROY_RESERVAS!G74*$D$4 -> 128.2937 | J45: =PROY_INDEXADO!H51+PROY_RESERVAS!H74*$D$4 -> 164.04212 | K45: =PROY_INDEXADO!I51+PROY_RESERVAS!I74*$D$4 -> 203.69716 | ... M45: =PROY_INDEXADO!K51+PROY_RESERVAS!K74*$D$4 -> 277.70377
A46: D43 | B46: REVENDIDOS | C46: Matafuego Clase K 6 l | D46: =PROY_INDEXADO!B52+PROY_RESERVAS!B75*$D$4 -> 100.89892 | E46: =PROY_INDEXADO!C52+PROY_RESERVAS!C75*$D$4 -> 189.77498 | F46: =PROY_INDEXADO!D52+PROY_RESERVAS!D75*$D$4 -> 250.48567 | G46: =PROY_INDEXADO!E52+PROY_RESERVAS!E75*$D$4 -> 350.26997 | H46: =PROY_INDEXADO!F52+PROY_RESERVAS!F75*$D$4 -> 548.40703 | I46: =PROY_INDEXADO!G52+PROY_RESERVAS!G75*$D$4 -> 754.18915 | J46: =PROY_INDEXADO!H52+PROY_RESERVAS!H75*$D$4 -> 962.19113 | K46: =PROY_INDEXADO!I52+PROY_RESERVAS!I75*$D$4 -> 1193.0739 | ... M46: =PROY_INDEXADO!K52+PROY_RESERVAS!K75*$D$4 -> 1650.6033
A47: D44 | B47: REVENDIDOS | C47: Matafuego CO₂ 2 kg | D47: =PROY_INDEXADO!B53 -> 421.98437 | E47: =PROY_INDEXADO!C53 -> 772.32062 | F47: =PROY_INDEXADO!D53 -> 1066.3637 | G47: =PROY_INDEXADO!E53 -> 1474.9633 | H47: =PROY_INDEXADO!F53 -> 2394.6449 | I47: =PROY_INDEXADO!G53 -> 3311.5475 | J47: =PROY_INDEXADO!H53 -> 4274.1878 | K47: =PROY_INDEXADO!I53 -> 5292.3947 | ... M47: =PROY_INDEXADO!K53 -> 7005.2774
A48: D45 | B48: REVENDIDOS | C48: Matafuego CO₂ 5 kg | D48: =PROY_INDEXADO!B54+PROY_RESERVAS!B76*$D$4 -> 286.05401 | E48: =PROY_INDEXADO!C54+PROY_RESERVAS!C76*$D$4 -> 494.98807 | F48: =PROY_INDEXADO!D54+PROY_RESERVAS!D76*$D$4 -> 634.88919 | G48: =PROY_INDEXADO!E54+PROY_RESERVAS!E76*$D$4 -> 852.18536 | H48: =PROY_INDEXADO!F54+PROY_RESERVAS!F76*$D$4 -> 1303.7149 | I48: =PROY_INDEXADO!G54+PROY_RESERVAS!G76*$D$4 -> 1768.1971 | J48: =PROY_INDEXADO!H54+PROY_RESERVAS!H76*$D$4 -> 2265.7683 | K48: =PROY_INDEXADO!I54+PROY_RESERVAS!I76*$D$4 -> 2799.5636 | ... M48: =PROY_INDEXADO!K54+PROY_RESERVAS!K76*$D$4 -> 3776.0178
A49: D46 | B49: REVENDIDOS | C49: Matafuego HCFC 5 kg | D49: =PROY_INDEXADO!B55+PROY_RESERVAS!B77*$D$4 -> 59.14739 | E49: =PROY_INDEXADO!C55+PROY_RESERVAS!C77*$D$4 -> 100.56407 | F49: =PROY_INDEXADO!D55+PROY_RESERVAS!D77*$D$4 -> 126.84623 | G49: =PROY_INDEXADO!E55+PROY_RESERVAS!E77*$D$4 -> 168.43673 | H49: =PROY_INDEXADO!F55+PROY_RESERVAS!F77*$D$4 -> 257.23766 | I49: =PROY_INDEXADO!G55+PROY_RESERVAS!G77*$D$4 -> 346.79087 | J49: =PROY_INDEXADO!H55+PROY_RESERVAS!H77*$D$4 -> 445.40399 | K49: =PROY_INDEXADO!I55+PROY_RESERVAS!I77*$D$4 -> 551.60391 | ... M49: =PROY_INDEXADO!K55+PROY_RESERVAS!K77*$D$4 -> 744.12045
A50: D47 | B50: REVENDIDOS | C50: Matafuego Clase D 9 l | D50: =PROY_INDEXADO!B56+PROY_RESERVAS!B78*$D$4 -> 28.716868 | E50: =PROY_INDEXADO!C56+PROY_RESERVAS!C78*$D$4 -> 45.696344 | F50: =PROY_INDEXADO!D56+PROY_RESERVAS!D78*$D$4 -> 55.275861 | G50: =PROY_INDEXADO!E56+PROY_RESERVAS!E78*$D$4 -> 71.125671 | H50: =PROY_INDEXADO!F56+PROY_RESERVAS!F78*$D$4 -> 103.25018 | I50: =PROY_INDEXADO!G56+PROY_RESERVAS!G78*$D$4 -> 128.00591 | J50: =PROY_INDEXADO!H56+PROY_RESERVAS!H78*$D$4 -> 164.31552 | K50: =PROY_INDEXADO!I56+PROY_RESERVAS!I78*$D$4 -> 203.40937 | ... M50: =PROY_INDEXADO!K56+PROY_RESERVAS!K78*$D$4 -> 277.41598

Sheet ESTACIONALIDAD
A1: ESTACIONALIDAD: producción mensual del año 2035
A3: Ref. | B3: Perfil | C3: Ene | D3: Feb | E3: Mar | F3: Abr | G3: May | H3: Jun | I3: Jul | J3: Ago | K3: Sep | L3: Oct | M3: Nov | N3: Dic | O3: Total
A4: E01 | B4: Automovilístico (1 kg) | C4: 0.12 | D4: 0.09 | E4: 0.08 | F4: 0.075 | G4: 0.07 | H4: 0.07 | I4: 0.075 | J4: 0.075 | K4: 0.075 | L4: 0.075 | M4: 0.075 | N4: 0.12 | O4: =SUM(C4:N4) -> 1
A5: E02 | B5: Manual comercial (2,5 / 5 / 10 kg) | C5: 0.1 | D5: 0.08 | E5: 0.085 | F5: 0.085 | G5: 0.08 | H5: 0.075 | I5: 0.08 | J5: 0.08 | K5: 0.08 | L5: 0.075 | M5: 0.07 | N5: 0.11 | O5: =SUM(C5:N5) -> 1
A6: E03 | B6: Industrial s/ruedas (25 – 100 kg) | C6: 0.085 | D6: 0.075 | E6: 0.09 | F6: 0.09 | G6: 0.09 | H6: 0.08 | I6: 0.09 | J6: 0.09 | K6: 0.085 | L6: 0.075 | M6: 0.07 | N6: 0.08 | O6: =SUM(C6:N6) -> 1
A7: E04 | B7: Recargas (sin estacionalidad) | C7: 0.083333333 | D7: 0.083333333 | E7: 0.083333333 | F7: 0.083333333 | G7: 0.083333333 | H7: 0.083333333 | I7: 0.083333333 | J7: 0.083333333 | K7: 0.083333333 | L7: 0.083333333 | M7: 0.083333333 | N7: 0.083333333 | O7: =SUM(C7:N7) -> 1
A9: Línea | B9: Producto | C9: Ene | D9: Feb | E9: Mar | F9: Abr | G9: May | H9: Jun | I9: Jul | J9: Ago | K9: Sep | L9: Oct | M9: Nov | N9: Dic | O9: Total | P9: Mes pico del producto
A10: MANUALES | B10: =DEMANDA!C8 -> Matafuego ABC 1 kg | C10: =DEMANDA!$M$8*C$4 -> 3848.7167 | D10: =DEMANDA!$M$8*D$4 -> 2886.5375 | E10: =DEMANDA!$M$8*E$4 -> 2565.8111 | F10: =DEMANDA!$M$8*F$4 -> 2405.4479 | G10: =DEMANDA!$M$8*G$4 -> 2245.0847 | H10: =DEMANDA!$M$8*H$4 -> 2245.0847 | I10: =DEMANDA!$M$8*I$4 -> 2405.4479 | J10: =DEMANDA!$M$8*J$4 -> 2405.4479 | ... N10: =DEMANDA!$M$8*N$4 -> 3848.7167 | O10: =SUM(C10:N10) -> 32072.639 | P10: =MAX(C10:N10) -> 3848.7167
A11: MANUALES | B11: =DEMANDA!C9 -> Matafuego ABC 2,5 kg | C11: =DEMANDA!$M$9*C$5 -> 742.48584 | D11: =DEMANDA!$M$9*D$5 -> 593.98868 | E11: =DEMANDA!$M$9*E$5 -> 631.11297 | F11: =DEMANDA!$M$9*F$5 -> 631.11297 | G11: =DEMANDA!$M$9*G$5 -> 593.98868 | H11: =DEMANDA!$M$9*H$5 -> 556.86438 | I11: =DEMANDA!$M$9*I$5 -> 593.98868 | J11: =DEMANDA!$M$9*J$5 -> 593.98868 | ... N11: =DEMANDA!$M$9*N$5 -> 816.73443 | O11: =SUM(C11:N11) -> 7424.8584 | P11: =MAX(C11:N11) -> 816.73443
A12: MANUALES | B12: =DEMANDA!C10 -> Matafuego ABC 5 kg | C12: =DEMANDA!$M$10*C$5 -> 3242.8771 | D12: =DEMANDA!$M$10*D$5 -> 2594.3017 | E12: =DEMANDA!$M$10*E$5 -> 2756.4455 | F12: =DEMANDA!$M$10*F$5 -> 2756.4455 | G12: =DEMANDA!$M$10*G$5 -> 2594.3017 | H12: =DEMANDA!$M$10*H$5 -> 2432.1578 | I12: =DEMANDA!$M$10*I$5 -> 2594.3017 | J12: =DEMANDA!$M$10*J$5 -> 2594.3017 | ... N12: =DEMANDA!$M$10*N$5 -> 3567.1648 | O12: =SUM(C12:N12) -> 32428.771 | P12: =MAX(C12:N12) -> 3567.1648
A13: MANUALES | B13: =DEMANDA!C11 -> Matafuego ABC 10 kg | C13: =DEMANDA!$M$11*C$5 -> 184.2877 | D13: =DEMANDA!$M$11*D$5 -> 147.43016 | E13: =DEMANDA!$M$11*E$5 -> 156.64454 | F13: =DEMANDA!$M$11*F$5 -> 156.64454 | G13: =DEMANDA!$M$11*G$5 -> 147.43016 | H13: =DEMANDA!$M$11*H$5 -> 138.21577 | I13: =DEMANDA!$M$11*I$5 -> 147.43016 | J13: =DEMANDA!$M$11*J$5 -> 147.43016 | ... N13: =DEMANDA!$M$11*N$5 -> 202.71647 | O13: =SUM(C13:N13) -> 1842.877 | P13: =MAX(C13:N13) -> 202.71647
A14: MANUALES | B14: =DEMANDA!C12 -> Cilindro ABC 1 kg vacío | C14: =DEMANDA!$M$12*C$4 -> 20465.76 | D14: =DEMANDA!$M$12*D$4 -> 15349.32 | E14: =DEMANDA!$M$12*E$4 -> 13643.84 | F14: =DEMANDA!$M$12*F$4 -> 12791.1 | G14: =DEMANDA!$M$12*G$4 -> 11938.36 | H14: =DEMANDA!$M$12*H$4 -> 11938.36 | I14: =DEMANDA!$M$12*I$4 -> 12791.1 | J14: =DEMANDA!$M$12*J$4 -> 12791.1 | ... N14: =DEMANDA!$M$12*N$4 -> 20465.76 | O14: =SUM(C14:N14) -> 170548 | P14: =MAX(C14:N14) -> 20465.76
A15: MANUALES | B15: =DEMANDA!C13 -> Cilindro ABC 2,5 kg vacío | C15: =DEMANDA!$M$13*C$5 -> 666.9 | D15: =DEMANDA!$M$13*D$5 -> 533.52 | E15: =DEMANDA!$M$13*E$5 -> 566.865 | F15: =DEMANDA!$M$13*F$5 -> 566.865 | G15: =DEMANDA!$M$13*G$5 -> 533.52 | H15: =DEMANDA!$M$13*H$5 -> 500.175 | I15: =DEMANDA!$M$13*I$5 -> 533.52 | J15: =DEMANDA!$M$13*J$5 -> 533.52 | ... N15: =DEMANDA!$M$13*N$5 -> 733.59 | O15: =SUM(C15:N15) -> 6669 | P15: =MAX(C15:N15) -> 733.59
A16: MANUALES | B16: =DEMANDA!C14 -> Cilindro ABC 5 kg vacío | C16: =DEMANDA!$M$14*C$5 -> 3291.5 | D16: =DEMANDA!$M$14*D$5 -> 2633.2 | E16: =DEMANDA!$M$14*E$5 -> 2797.775 | F16: =DEMANDA!$M$14*F$5 -> 2797.775 | G16: =DEMANDA!$M$14*G$5 -> 2633.2 | H16: =DEMANDA!$M$14*H$5 -> 2468.625 | I16: =DEMANDA!$M$14*I$5 -> 2633.2 | J16: =DEMANDA!$M$14*J$5 -> 2633.2 | ... N16: =DEMANDA!$M$14*N$5 -> 3620.65 | O16: =SUM(C16:N16) -> 32915 | P16: =MAX(C16:N16) -> 3620.65
A17: MANUALES | B17: =DEMANDA!C15 -> Cilindro ABC 10 kg vacío | C17: =DEMANDA!$M$15*C$5 -> 201.1 | D17: =DEMANDA!$M$15*D$5 -> 160.88 | E17: =DEMANDA!$M$15*E$5 -> 170.935 | F17: =DEMANDA!$M$15*F$5 -> 170.935 | G17: =DEMANDA!$M$15*G$5 -> 160.88 | H17: =DEMANDA!$M$15*H$5 -> 150.825 | I17: =DEMANDA!$M$15*I$5 -> 160.88 | J17: =DEMANDA!$M$15*J$5 -> 160.88 | ... N17: =DEMANDA!$M$15*N$5 -> 221.21 | O17: =SUM(C17:N17) -> 2011 | P17: =MAX(C17:N17) -> 221.21
A18: MANUALES | B18: Total manuales | C18: =SUM(C10:C17) -> 32643.627 | D18: =SUM(D10:D17) -> 24899.178 | E18: =SUM(E10:E17) -> 23289.429 | F18: =SUM(F10:F17) -> 22276.326 | G18: =SUM(G10:G17) -> 20846.765 | H18: =SUM(H10:H17) -> 20430.308 | I18: =SUM(I10:I17) -> 21859.868 | J18: =SUM(J10:J17) -> 21859.868 | ... O18: =SUM(O10:O17) -> 285912.15
A19: RODANTES | B19: =DEMANDA!C16 -> Matafuego ABC 25 kg | C19: =DEMANDA!$M$16*C$6 -> 38.527995 | D19: =DEMANDA!$M$16*D$6 -> 33.99529 | E19: =DEMANDA!$M$16*E$6 -> 40.794348 | F19: =DEMANDA!$M$16*F$6 -> 40.794348 | G19: =DEMANDA!$M$16*G$6 -> 40.794348 | H19: =DEMANDA!$M$16*H$6 -> 36.261643 | I19: =DEMANDA!$M$16*I$6 -> 40.794348 | J19: =DEMANDA!$M$16*J$6 -> 40.794348 | ... N19: =DEMANDA!$M$16*N$6 -> 36.261643 | O19: =SUM(C19:N19) -> 453.27053 | P19: =MAX(C19:N19) -> 40.794348
A20: RODANTES | B20: =DEMANDA!C17 -> Matafuego ABC 50 kg | C20: =DEMANDA!$M$17*C$6 -> 84.852099 | D20: =DEMANDA!$M$17*D$6 -> 74.869499 | E20: =DEMANDA!$M$17*E$6 -> 89.843398 | F20: =DEMANDA!$M$17*F$6 -> 89.843398 | G20: =DEMANDA!$M$17*G$6 -> 89.843398 | H20: =DEMANDA!$M$17*H$6 -> 79.860799 | I20: =DEMANDA!$M$17*I$6 -> 89.843398 | J20: =DEMANDA!$M$17*J$6 -> 89.843398 | ... N20: =DEMANDA!$M$17*N$6 -> 79.860799 | O20: =SUM(C20:N20) -> 998.25998 | P20: =MAX(C20:N20) -> 89.843398
A21: RODANTES | B21: =DEMANDA!C18 -> Matafuego ABC 70 kg | C21: =DEMANDA!$M$18*C$6 -> 18.493438 | D21: =DEMANDA!$M$18*D$6 -> 16.317739 | E21: =DEMANDA!$M$18*E$6 -> 19.581287 | F21: =DEMANDA!$M$18*F$6 -> 19.581287 | G21: =DEMANDA!$M$18*G$6 -> 19.581287 | H21: =DEMANDA!$M$18*H$6 -> 17.405588 | I21: =DEMANDA!$M$18*I$6 -> 19.581287 | J21: =DEMANDA!$M$18*J$6 -> 19.581287 | ... N21: =DEMANDA!$M$18*N$6 -> 17.405588 | O21: =SUM(C21:N21) -> 217.56986 | P21: =MAX(C21:N21) -> 19.581287
A22: RODANTES | B22: =DEMANDA!C19 -> Matafuego ABC 100 kg | C22: =DEMANDA!$M$19*C$6 -> 12.339966 | D22: =DEMANDA!$M$19*D$6 -> 10.888206 | E22: =DEMANDA!$M$19*E$6 -> 13.065847 | F22: =DEMANDA!$M$19*F$6 -> 13.065847 | G22: =DEMANDA!$M$19*G$6 -> 13.065847 | H22: =DEMANDA!$M$19*H$6 -> 11.614086 | I22: =DEMANDA!$M$19*I$6 -> 13.065847 | J22: =DEMANDA!$M$19*J$6 -> 13.065847 | ... N22: =DEMANDA!$M$19*N$6 -> 11.614086 | O22: =SUM(C22:N22) -> 145.17607 | P22: =MAX(C22:N22) -> 13.065847
A23: RODANTES | B23: =DEMANDA!C20 -> Cilindro ABC 25 kg vacío | C23: =DEMANDA!$M$20*C$6 -> 27.37 | D23: =DEMANDA!$M$20*D$6 -> 24.15 | E23: =DEMANDA!$M$20*E$6 -> 28.98 | F23: =DEMANDA!$M$20*F$6 -> 28.98 | G23: =DEMANDA!$M$20*G$6 -> 28.98 | H23: =DEMANDA!$M$20*H$6 -> 25.76 | I23: =DEMANDA!$M$20*I$6 -> 28.98 | J23: =DEMANDA!$M$20*J$6 -> 28.98 | ... N23: =DEMANDA!$M$20*N$6 -> 25.76 | O23: =SUM(C23:N23) -> 322 | P23: =MAX(C23:N23) -> 28.98
A24: RODANTES | B24: =DEMANDA!C21 -> Cilindro ABC 50 kg vacío | C24: =DEMANDA!$M$21*C$6 -> 60.18 | D24: =DEMANDA!$M$21*D$6 -> 53.1 | E24: =DEMANDA!$M$21*E$6 -> 63.72 | F24: =DEMANDA!$M$21*F$6 -> 63.72 | G24: =DEMANDA!$M$21*G$6 -> 63.72 | H24: =DEMANDA!$M$21*H$6 -> 56.64 | I24: =DEMANDA!$M$21*I$6 -> 63.72 | J24: =DEMANDA!$M$21*J$6 -> 63.72 | ... N24: =DEMANDA!$M$21*N$6 -> 56.64 | O24: =SUM(C24:N24) -> 708 | P24: =MAX(C24:N24) -> 63.72
A25: RODANTES | B25: =DEMANDA!C22 -> Cilindro ABC 70 kg vacío | C25: =DEMANDA!$M$22*C$6 -> 13.175 | D25: =DEMANDA!$M$22*D$6 -> 11.625 | E25: =DEMANDA!$M$22*E$6 -> 13.95 | F25: =DEMANDA!$M$22*F$6 -> 13.95 | G25: =DEMANDA!$M$22*G$6 -> 13.95 | H25: =DEMANDA!$M$22*H$6 -> 12.4 | I25: =DEMANDA!$M$22*I$6 -> 13.95 | J25: =DEMANDA!$M$22*J$6 -> 13.95 | ... N25: =DEMANDA!$M$22*N$6 -> 12.4 | O25: =SUM(C25:N25) -> 155 | P25: =MAX(C25:N25) -> 13.95
A26: RODANTES | B26: =DEMANDA!C23 -> Cilindro ABC 100 kg vacío | C26: =DEMANDA!$M$23*C$6 -> 8.67 | D26: =DEMANDA!$M$23*D$6 -> 7.65 | E26: =DEMANDA!$M$23*E$6 -> 9.18 | F26: =DEMANDA!$M$23*F$6 -> 9.18 | G26: =DEMANDA!$M$23*G$6 -> 9.18 | H26: =DEMANDA!$M$23*H$6 -> 8.16 | I26: =DEMANDA!$M$23*I$6 -> 9.18 | J26: =DEMANDA!$M$23*J$6 -> 9.18 | ... N26: =DEMANDA!$M$23*N$6 -> 8.16 | O26: =SUM(C26:N26) -> 102 | P26: =MAX(C26:N26) -> 9.18
A27: RODANTES | B27: Total rodantes | C27: =SUM(C19:C26) -> 263.6085 | D27: =SUM(D19:D26) -> 232.59573 | E27: =SUM(E19:E26) -> 279.11488 | F27: =SUM(F19:F26) -> 279.11488 | G27: =SUM(G19:G26) -> 279.11488 | H27: =SUM(H19:H26) -> 248.10212 | I27: =SUM(I19:I26) -> 279.11488 | J27: =SUM(J19:J26) -> 279.11488 | ... O27: =SUM(O19:O26) -> 3101.2764
A28: RECARGAS | B28: =DEMANDA!C24 -> Recarga ABC 1 kg | C28: =DEMANDA!$M$24*C$7 -> 4707.2909 | D28: =DEMANDA!$M$24*D$7 -> 4707.2909 | E28: =DEMANDA!$M$24*E$7 -> 4707.2909 | F28: =DEMANDA!$M$24*F$7 -> 4707.2909 | G28: =DEMANDA!$M$24*G$7 -> 4707.2909 | H28: =DEMANDA!$M$24*H$7 -> 4707.2909 | I28: =DEMANDA!$M$24*I$7 -> 4707.2909 | J28: =DEMANDA!$M$24*J$7 -> 4707.2909 | ... N28: =DEMANDA!$M$24*N$7 -> 4707.2909 | O28: =SUM(C28:N28) -> 56487.491 | P28: =MAX(C28:N28) -> 4707.2909
A29: RECARGAS | B29: =DEMANDA!C25 -> Recarga ABC 2,5 kg | C29: =DEMANDA!$M$25*C$7 -> 398.60243 | D29: =DEMANDA!$M$25*D$7 -> 398.60243 | E29: =DEMANDA!$M$25*E$7 -> 398.60243 | F29: =DEMANDA!$M$25*F$7 -> 398.60243 | G29: =DEMANDA!$M$25*G$7 -> 398.60243 | H29: =DEMANDA!$M$25*H$7 -> 398.60243 | I29: =DEMANDA!$M$25*I$7 -> 398.60243 | J29: =DEMANDA!$M$25*J$7 -> 398.60243 | ... N29: =DEMANDA!$M$25*N$7 -> 398.60243 | O29: =SUM(C29:N29) -> 4783.2292 | P29: =MAX(C29:N29) -> 398.60243
A30: RECARGAS | B30: =DEMANDA!C26 -> Recarga ABC 5 kg | C30: =DEMANDA!$M$26*C$7 -> 2505.7365 | D30: =DEMANDA!$M$26*D$7 -> 2505.7365 | E30: =DEMANDA!$M$26*E$7 -> 2505.7365 | F30: =DEMANDA!$M$26*F$7 -> 2505.7365 | G30: =DEMANDA!$M$26*G$7 -> 2505.7365 | H30: =DEMANDA!$M$26*H$7 -> 2505.7365 | I30: =DEMANDA!$M$26*I$7 -> 2505.7365 | J30: =DEMANDA!$M$26*J$7 -> 2505.7365 | ... N30: =DEMANDA!$M$26*N$7 -> 2505.7365 | O30: =SUM(C30:N30) -> 30068.838 | P30: =MAX(C30:N30) -> 2505.7365
A31: RECARGAS | B31: =DEMANDA!C27 -> Recarga ABC 10 kg | C31: =DEMANDA!$M$27*C$7 -> 145.11512 | D31: =DEMANDA!$M$27*D$7 -> 145.11512 | E31: =DEMANDA!$M$27*E$7 -> 145.11512 | F31: =DEMANDA!$M$27*F$7 -> 145.11512 | G31: =DEMANDA!$M$27*G$7 -> 145.11512 | H31: =DEMANDA!$M$27*H$7 -> 145.11512 | I31: =DEMANDA!$M$27*I$7 -> 145.11512 | J31: =DEMANDA!$M$27*J$7 -> 145.11512 | ... N31: =DEMANDA!$M$27*N$7 -> 145.11512 | O31: =SUM(C31:N31) -> 1741.3814 | P31: =MAX(C31:N31) -> 145.11512
A32: RECARGAS | B32: =DEMANDA!C28 -> Recarga Agua 10 l | C32: =DEMANDA!$M$28*C$7 -> 204.87548 | D32: =DEMANDA!$M$28*D$7 -> 204.87548 | E32: =DEMANDA!$M$28*E$7 -> 204.87548 | F32: =DEMANDA!$M$28*F$7 -> 204.87548 | G32: =DEMANDA!$M$28*G$7 -> 204.87548 | H32: =DEMANDA!$M$28*H$7 -> 204.87548 | I32: =DEMANDA!$M$28*I$7 -> 204.87548 | J32: =DEMANDA!$M$28*J$7 -> 204.87548 | ... N32: =DEMANDA!$M$28*N$7 -> 204.87548 | O32: =SUM(C32:N32) -> 2458.5058 | P32: =MAX(C32:N32) -> 204.87548
A33: RECARGAS | B33: =DEMANDA!C29 -> Recarga AFFF 10 l | C33: =DEMANDA!$M$29*C$7 -> 38.909716 | D33: =DEMANDA!$M$29*D$7 -> 38.909716 | E33: =DEMANDA!$M$29*E$7 -> 38.909716 | F33: =DEMANDA!$M$29*F$7 -> 38.909716 | G33: =DEMANDA!$M$29*G$7 -> 38.909716 | H33: =DEMANDA!$M$29*H$7 -> 38.909716 | I33: =DEMANDA!$M$29*I$7 -> 38.909716 | J33: =DEMANDA!$M$29*J$7 -> 38.909716 | ... N33: =DEMANDA!$M$29*N$7 -> 38.909716 | O33: =SUM(C33:N33) -> 466.91659 | P33: =MAX(C33:N33) -> 38.909716
A34: RECARGAS | B34: =DEMANDA!C30 -> Recarga AFFF 50 l | C34: =DEMANDA!$M$30*C$7 -> 20.297355 | D34: =DEMANDA!$M$30*D$7 -> 20.297355 | E34: =DEMANDA!$M$30*E$7 -> 20.297355 | F34: =DEMANDA!$M$30*F$7 -> 20.297355 | G34: =DEMANDA!$M$30*G$7 -> 20.297355 | H34: =DEMANDA!$M$30*H$7 -> 20.297355 | I34: =DEMANDA!$M$30*I$7 -> 20.297355 | J34: =DEMANDA!$M$30*J$7 -> 20.297355 | ... N34: =DEMANDA!$M$30*N$7 -> 20.297355 | O34: =SUM(C34:N34) -> 243.56826 | P34: =MAX(C34:N34) -> 20.297355
A35: RECARGAS | B35: =DEMANDA!C31 -> Recarga BC 5 kg | C35: =DEMANDA!$M$31*C$7 -> 11.738789 | D35: =DEMANDA!$M$31*D$7 -> 11.738789 | E35: =DEMANDA!$M$31*E$7 -> 11.738789 | F35: =DEMANDA!$M$31*F$7 -> 11.738789 | G35: =DEMANDA!$M$31*G$7 -> 11.738789 | H35: =DEMANDA!$M$31*H$7 -> 11.738789 | I35: =DEMANDA!$M$31*I$7 -> 11.738789 | J35: =DEMANDA!$M$31*J$7 -> 11.738789 | ... N35: =DEMANDA!$M$31*N$7 -> 11.738789 | O35: =SUM(C35:N35) -> 140.86546 | P35: =MAX(C35:N35) -> 11.738789
A36: RECARGAS | B36: =DEMANDA!C32 -> Recarga Clase K 6 l | C36: =DEMANDA!$M$32*C$7 -> 101.02645 | D36: =DEMANDA!$M$32*D$7 -> 101.02645 | E36: =DEMANDA!$M$32*E$7 -> 101.02645 | F36: =DEMANDA!$M$32*F$7 -> 101.02645 | G36: =DEMANDA!$M$32*G$7 -> 101.02645 | H36: =DEMANDA!$M$32*H$7 -> 101.02645 | I36: =DEMANDA!$M$32*I$7 -> 101.02645 | J36: =DEMANDA!$M$32*J$7 -> 101.02645 | ... N36: =DEMANDA!$M$32*N$7 -> 101.02645 | O36: =SUM(C36:N36) -> 1212.3174 | P36: =MAX(C36:N36) -> 101.02645
A37: RECARGAS | B37: =DEMANDA!C33 -> Recarga CO₂ 2 kg | C37: =DEMANDA!$M$33*C$7 -> 545.22339 | D37: =DEMANDA!$M$33*D$7 -> 545.22339 | E37: =DEMANDA!$M$33*E$7 -> 545.22339 | F37: =DEMANDA!$M$33*F$7 -> 545.22339 | G37: =DEMANDA!$M$33*G$7 -> 545.22339 | H37: =DEMANDA!$M$33*H$7 -> 545.22339 | I37: =DEMANDA!$M$33*I$7 -> 545.22339 | J37: =DEMANDA!$M$33*J$7 -> 545.22339 | ... N37: =DEMANDA!$M$33*N$7 -> 545.22339 | O37: =SUM(C37:N37) -> 6542.6807 | P37: =MAX(C37:N37) -> 545.22339
A38: RECARGAS | B38: =DEMANDA!C34 -> Recarga CO₂ 5 kg | C38: =DEMANDA!$M$34*C$7 -> 194.24569 | D38: =DEMANDA!$M$34*D$7 -> 194.24569 | E38: =DEMANDA!$M$34*E$7 -> 194.24569 | F38: =DEMANDA!$M$34*F$7 -> 194.24569 | G38: =DEMANDA!$M$34*G$7 -> 194.24569 | H38: =DEMANDA!$M$34*H$7 -> 194.24569 | I38: =DEMANDA!$M$34*I$7 -> 194.24569 | J38: =DEMANDA!$M$34*J$7 -> 194.24569 | ... N38: =DEMANDA!$M$34*N$7 -> 194.24569 | O38: =SUM(C38:N38) -> 2330.9482 | P38: =MAX(C38:N38) -> 194.24569
A39: RECARGAS | B39: =DEMANDA!C35 -> Recarga HCFC 5 kg | C39: =DEMANDA!$M$35*C$7 -> 30.839698 | D39: =DEMANDA!$M$35*D$7 -> 30.839698 | E39: =DEMANDA!$M$35*E$7 -> 30.839698 | F39: =DEMANDA!$M$35*F$7 -> 30.839698 | G39: =DEMANDA!$M$35*G$7 -> 30.839698 | H39: =DEMANDA!$M$35*H$7 -> 30.839698 | I39: =DEMANDA!$M$35*I$7 -> 30.839698 | J39: =DEMANDA!$M$35*J$7 -> 30.839698 | ... N39: =DEMANDA!$M$35*N$7 -> 30.839698 | O39: =SUM(C39:N39) -> 370.07637 | P39: =MAX(C39:N39) -> 30.839698
A40: RECARGAS | B40: =DEMANDA!C36 -> Recarga Clase D 9 l | C40: =DEMANDA!$M$36*C$7 -> 10.592621 | D40: =DEMANDA!$M$36*D$7 -> 10.592621 | E40: =DEMANDA!$M$36*E$7 -> 10.592621 | F40: =DEMANDA!$M$36*F$7 -> 10.592621 | G40: =DEMANDA!$M$36*G$7 -> 10.592621 | H40: =DEMANDA!$M$36*H$7 -> 10.592621 | I40: =DEMANDA!$M$36*I$7 -> 10.592621 | J40: =DEMANDA!$M$36*J$7 -> 10.592621 | ... N40: =DEMANDA!$M$36*N$7 -> 10.592621 | O40: =SUM(C40:N40) -> 127.11145 | P40: =MAX(C40:N40) -> 10.592621
A41: RECARGAS | B41: =DEMANDA!C37 -> Recarga ABC 25 kg | C41: =DEMANDA!$M$37*C$7 -> 24.988007 | D41: =DEMANDA!$M$37*D$7 -> 24.988007 | E41: =DEMANDA!$M$37*E$7 -> 24.988007 | F41: =DEMANDA!$M$37*F$7 -> 24.988007 | G41: =DEMANDA!$M$37*G$7 -> 24.988007 | H41: =DEMANDA!$M$37*H$7 -> 24.988007 | I41: =DEMANDA!$M$37*I$7 -> 24.988007 | J41: =DEMANDA!$M$37*J$7 -> 24.988007 | ... N41: =DEMANDA!$M$37*N$7 -> 24.988007 | O41: =SUM(C41:N41) -> 299.85609 | P41: =MAX(C41:N41) -> 24.988007
A42: RECARGAS | B42: =DEMANDA!C38 -> Recarga ABC 50 kg | C42: =DEMANDA!$M$38*C$7 -> 55.836975 | D42: =DEMANDA!$M$38*D$7 -> 55.836975 | E42: =DEMANDA!$M$38*E$7 -> 55.836975 | F42: =DEMANDA!$M$38*F$7 -> 55.836975 | G42: =DEMANDA!$M$38*G$7 -> 55.836975 | H42: =DEMANDA!$M$38*H$7 -> 55.836975 | I42: =DEMANDA!$M$38*I$7 -> 55.836975 | J42: =DEMANDA!$M$38*J$7 -> 55.836975 | ... N42: =DEMANDA!$M$38*N$7 -> 55.836975 | O42: =SUM(C42:N42) -> 670.0437 | P42: =MAX(C42:N42) -> 55.836975
A43: RECARGAS | B43: =DEMANDA!C39 -> Recarga ABC 70 kg | C43: =DEMANDA!$M$39*C$7 -> 11.994243 | D43: =DEMANDA!$M$39*D$7 -> 11.994243 | E43: =DEMANDA!$M$39*E$7 -> 11.994243 | F43: =DEMANDA!$M$39*F$7 -> 11.994243 | G43: =DEMANDA!$M$39*G$7 -> 11.994243 | H43: =DEMANDA!$M$39*H$7 -> 11.994243 | I43: =DEMANDA!$M$39*I$7 -> 11.994243 | J43: =DEMANDA!$M$39*J$7 -> 11.994243 | ... N43: =DEMANDA!$M$39*N$7 -> 11.994243 | O43: =SUM(C43:N43) -> 143.93092 | P43: =MAX(C43:N43) -> 11.994243
A44: RECARGAS | B44: =DEMANDA!C40 -> Recarga ABC 100 kg | C44: =DEMANDA!$M$40*C$7 -> 8.2120021 | D44: =DEMANDA!$M$40*D$7 -> 8.2120021 | E44: =DEMANDA!$M$40*E$7 -> 8.2120021 | F44: =DEMANDA!$M$40*F$7 -> 8.2120021 | G44: =DEMANDA!$M$40*G$7 -> 8.2120021 | H44: =DEMANDA!$M$40*H$7 -> 8.2120021 | I44: =DEMANDA!$M$40*I$7 -> 8.2120021 | J44: =DEMANDA!$M$40*J$7 -> 8.2120021 | ... N44: =DEMANDA!$M$40*N$7 -> 8.2120021 | O44: =SUM(C44:N44) -> 98.544026 | P44: =MAX(C44:N44) -> 8.2120021
A45: RECARGAS | B45: Total recargas | C45: =SUM(C28:C44) -> 9015.5254 | D45: =SUM(D28:D44) -> 9015.5254 | E45: =SUM(E28:E44) -> 9015.5254 | F45: =SUM(F28:F44) -> 9015.5254 | G45: =SUM(G28:G44) -> 9015.5254 | H45: =SUM(H28:H44) -> 9015.5254 | I45: =SUM(I28:I44) -> 9015.5254 | J45: =SUM(J28:J44) -> 9015.5254 | ... O45: =SUM(O28:O44) -> 108186.3
A46: REVENDIDOS | B46: =DEMANDA!C42 -> Matafuego Agua 10 l | C46: =DEMANDA!$M$42*C$5 -> 290.8135 | D46: =DEMANDA!$M$42*D$5 -> 232.6508 | E46: =DEMANDA!$M$42*E$5 -> 247.19148 | F46: =DEMANDA!$M$42*F$5 -> 247.19148 | G46: =DEMANDA!$M$42*G$5 -> 232.6508 | H46: =DEMANDA!$M$42*H$5 -> 218.11013 | I46: =DEMANDA!$M$42*I$5 -> 232.6508 | J46: =DEMANDA!$M$42*J$5 -> 232.6508 | ... N46: =DEMANDA!$M$42*N$5 -> 319.89485 | O46: =SUM(C46:N46) -> 2908.135 | P46: =MAX(C46:N46) -> 319.89485
A47: REVENDIDOS | B47: =DEMANDA!C43 -> Matafuego AFFF 10 l | C47: =DEMANDA!$M$43*C$5 -> 97.150993 | D47: =DEMANDA!$M$43*D$5 -> 77.720795 | E47: =DEMANDA!$M$43*E$5 -> 82.578344 | F47: =DEMANDA!$M$43*F$5 -> 82.578344 | G47: =DEMANDA!$M$43*G$5 -> 77.720795 | H47: =DEMANDA!$M$43*H$5 -> 72.863245 | I47: =DEMANDA!$M$43*I$5 -> 77.720795 | J47: =DEMANDA!$M$43*J$5 -> 77.720795 | ... N47: =DEMANDA!$M$43*N$5 -> 106.86609 | O47: =SUM(C47:N47) -> 971.50993 | P47: =MAX(C47:N47) -> 106.86609
A48: REVENDIDOS | B48: =DEMANDA!C44 -> Matafuego AFFF 50 l | C48: =DEMANDA!$M$44*C$6 -> 35.396834 | D48: =DEMANDA!$M$44*D$6 -> 31.232501 | E48: =DEMANDA!$M$44*E$6 -> 37.479001 | F48: =DEMANDA!$M$44*F$6 -> 37.479001 | G48: =DEMANDA!$M$44*G$6 -> 37.479001 | H48: =DEMANDA!$M$44*H$6 -> 33.314668 | I48: =DEMANDA!$M$44*I$6 -> 37.479001 | J48: =DEMANDA!$M$44*J$6 -> 37.479001 | ... N48: =DEMANDA!$M$44*N$6 -> 33.314668 | O48: =SUM(C48:N48) -> 416.43335 | P48: =MAX(C48:N48) -> 37.479001
A49: REVENDIDOS | B49: =DEMANDA!C45 -> Matafuego BC 5 kg | C49: =DEMANDA!$M$45*C$5 -> 27.770377 | D49: =DEMANDA!$M$45*D$5 -> 22.216302 | E49: =DEMANDA!$M$45*E$5 -> 23.60482 | F49: =DEMANDA!$M$45*F$5 -> 23.60482 | G49: =DEMANDA!$M$45*G$5 -> 22.216302 | H49: =DEMANDA!$M$45*H$5 -> 20.827783 | I49: =DEMANDA!$M$45*I$5 -> 22.216302 | J49: =DEMANDA!$M$45*J$5 -> 22.216302 | ... N49: =DEMANDA!$M$45*N$5 -> 30.547415 | O49: =SUM(C49:N49) -> 277.70377 | P49: =MAX(C49:N49) -> 30.547415
A50: REVENDIDOS | B50: =DEMANDA!C46 -> Matafuego Clase K 6 l | C50: =DEMANDA!$M$46*C$5 -> 165.06033 | D50: =DEMANDA!$M$46*D$5 -> 132.04826 | E50: =DEMANDA!$M$46*E$5 -> 140.30128 | F50: =DEMANDA!$M$46*F$5 -> 140.30128 | G50: =DEMANDA!$M$46*G$5 -> 132.04826 | H50: =DEMANDA!$M$46*H$5 -> 123.79525 | I50: =DEMANDA!$M$46*I$5 -> 132.04826 | J50: =DEMANDA!$M$46*J$5 -> 132.04826 | ... N50: =DEMANDA!$M$46*N$5 -> 181.56636 | O50: =SUM(C50:N50) -> 1650.6033 | P50: =MAX(C50:N50) -> 181.56636
A51: REVENDIDOS | B51: =DEMANDA!C47 -> Matafuego CO₂ 2 kg | C51: =DEMANDA!$M$47*C$5 -> 700.52774 | D51: =DEMANDA!$M$47*D$5 -> 560.42219 | E51: =DEMANDA!$M$47*E$5 -> 595.44858 | F51: =DEMANDA!$M$47*F$5 -> 595.44858 | G51: =DEMANDA!$M$47*G$5 -> 560.42219 | H51: =DEMANDA!$M$47*H$5 -> 525.3958 | I51: =DEMANDA!$M$47*I$5 -> 560.42219 | J51: =DEMANDA!$M$47*J$5 -> 560.42219 | ... N51: =DEMANDA!$M$47*N$5 -> 770.58051 | O51: =SUM(C51:N51) -> 7005.2774 | P51: =MAX(C51:N51) -> 770.58051
A52: REVENDIDOS | B52: =DEMANDA!C48 -> Matafuego CO₂ 5 kg | C52: =DEMANDA!$M$48*C$5 -> 377.60178 | D52: =DEMANDA!$M$48*D$5 -> 302.08142 | E52: =DEMANDA!$M$48*E$5 -> 320.96151 | F52: =DEMANDA!$M$48*F$5 -> 320.96151 | G52: =DEMANDA!$M$48*G$5 -> 302.08142 | H52: =DEMANDA!$M$48*H$5 -> 283.20133 | I52: =DEMANDA!$M$48*I$5 -> 302.08142 | J52: =DEMANDA!$M$48*J$5 -> 302.08142 | ... N52: =DEMANDA!$M$48*N$5 -> 415.36195 | O52: =SUM(C52:N52) -> 3776.0178 | P52: =MAX(C52:N52) -> 415.36195
A53: REVENDIDOS | B53: =DEMANDA!C49 -> Matafuego HCFC 5 kg | C53: =DEMANDA!$M$49*C$5 -> 74.412045 | D53: =DEMANDA!$M$49*D$5 -> 59.529636 | E53: =DEMANDA!$M$49*E$5 -> 63.250239 | F53: =DEMANDA!$M$49*F$5 -> 63.250239 | G53: =DEMANDA!$M$49*G$5 -> 59.529636 | H53: =DEMANDA!$M$49*H$5 -> 55.809034 | I53: =DEMANDA!$M$49*I$5 -> 59.529636 | J53: =DEMANDA!$M$49*J$5 -> 59.529636 | ... N53: =DEMANDA!$M$49*N$5 -> 81.85325 | O53: =SUM(C53:N53) -> 744.12045 | P53: =MAX(C53:N53) -> 81.85325
A54: REVENDIDOS | B54: =DEMANDA!C50 -> Matafuego Clase D 9 l | C54: =DEMANDA!$M$50*C$5 -> 27.741598 | D54: =DEMANDA!$M$50*D$5 -> 22.193279 | E54: =DEMANDA!$M$50*E$5 -> 23.580359 | F54: =DEMANDA!$M$50*F$5 -> 23.580359 | G54: =DEMANDA!$M$50*G$5 -> 22.193279 | H54: =DEMANDA!$M$50*H$5 -> 20.806199 | I54: =DEMANDA!$M$50*I$5 -> 22.193279 | J54: =DEMANDA!$M$50*J$5 -> 22.193279 | ... N54: =DEMANDA!$M$50*N$5 -> 30.515758 | O54: =SUM(C54:N54) -> 277.41598 | P54: =MAX(C54:N54) -> 30.515758
A55: REVENDIDOS | B55: Total revendidos | C55: =SUM(C46:C54) -> 1796.4752 | D55: =SUM(D46:D54) -> 1440.0952 | E55: =SUM(E46:E54) -> 1534.3956 | F55: =SUM(F46:F54) -> 1534.3956 | G55: =SUM(G46:G54) -> 1446.3417 | H55: =SUM(H46:H54) -> 1354.1234 | I55: =SUM(I46:I54) -> 1446.3417 | J55: =SUM(J46:J54) -> 1446.3417 | ... O55: =SUM(O46:O54) -> 18027.217
A57: Ref. | B57: Línea | C57: Mes pico | D57: N.º de mes | E57: Unidades del mes pico | F57: Promedio mensual | G57: Factor de pico
A58: E05 | B58: MANUALES | C58: =INDEX($C$9:$N$9,D58) -> Dic | D58: =MATCH(MAX(C18:N18),C18:N18,0) -> 12 | E58: =INDEX(C18:N18,D58) -> 33476.542 | F58: =O18/12 -> 23826.012 | G58: =E58/F58 -> 1.4050418
A59: E06 | B59: RODANTES | C59: =INDEX($C$9:$N$9,D59) -> Mar | D59: =MATCH(MAX(C27:N27),C27:N27,0) -> 3 | E59: =INDEX(C27:N27,D59) -> 279.11488 | F59: =O27/12 -> 258.4397 | G59: =E59/F59 -> 1.08
A60: E07 | B60: RECARGAS | C60: =INDEX($C$9:$N$9,D60) -> Ene | D60: =MATCH(MAX(C45:N45),C45:N45,0) -> 1 | E60: =INDEX(C45:N45,D60) -> 9015.5254 | F60: =O45/12 -> 9015.5254 | G60: =E60/F60 -> 1
A61: E08 | B61: REVENDIDOS | C61: =INDEX($C$9:$N$9,D61) -> Dic | D61: =MATCH(MAX(C55:N55),C55:N55,0) -> 12 | E61: =INDEX(C55:N55,D61) -> 1970.5009 | F61: =O55/12 -> 1502.2681 | G61: =E61/F61 -> 1.3116839

Sheet MANUALES
A1: MANUALES: consumo por unidad de producto y lo que hay que comprar
A3: Ref. | B3: Código | C3: Material | D3: UM | E3: Destino | F3: ABC 1 kg | G3: ABC 2,5 kg | H3: ABC 5 kg | I3: ABC 10 kg | J3: Cilindro ABC 1 kg | K3: Cilindro ABC 2,5 kg | L3: Cilindro ABC 5 kg | M3: Cilindro ABC 10 kg | N3: 2026 | O3: 2027 | P3: 2028 | Q3: 2029 | R3: 2030 | S3: 2031 | T3: 2032 | U3: 2033 | V3: 2034 | W3: 2035 | X3: Mes pico 2035
C4: Demanda 2026 | F4: =DEMANDA!D8 -> 4178.7365 | G4: =DEMANDA!D9 -> 295.03036 | H4: =DEMANDA!D10 -> 2727.9036 | I4: =DEMANDA!D11 -> 92.408754 | J4: =DEMANDA!D12 -> 0 | K4: =DEMANDA!D13 -> 0 | L4: =DEMANDA!D14 -> 0 | M4: =DEMANDA!D15 -> 0
C5: Demanda 2027 | F5: =DEMANDA!E8 -> 5997.304 | G5: =DEMANDA!E9 -> 709.72745 | H5: =DEMANDA!E10 -> 5488.9106 | I5: =DEMANDA!E11 -> 178.13943 | J5: =DEMANDA!E12 -> 0 | K5: =DEMANDA!E13 -> 0 | L5: =DEMANDA!E14 -> 0 | M5: =DEMANDA!E15 -> 0
C6: Demanda 2028 | F6: =DEMANDA!F8 -> 6851.7478 | G6: =DEMANDA!F9 -> 986.86806 | H6: =DEMANDA!F10 -> 7206.5855 | I6: =DEMANDA!F11 -> 255.06523 | J6: =DEMANDA!F12 -> 7662.4 | K6: =DEMANDA!F13 -> 299.6 | L6: =DEMANDA!F14 -> 1478.8 | M6: =DEMANDA!F15 -> 90.4
C7: Demanda 2029 | F7: =DEMANDA!G8 -> 8467.1355 | G7: =DEMANDA!G9 -> 1500.6382 | H7: =DEMANDA!G10 -> 10420.908 | I7: =DEMANDA!G11 -> 361.07103 | J7: =DEMANDA!G12 -> 26694.8 | K7: =DEMANDA!G13 -> 1043.8 | L7: =DEMANDA!G14 -> 5152 | M7: =DEMANDA!G15 -> 315
C8: Demanda 2030 | F8: =DEMANDA!H8 -> 12680.633 | G8: =DEMANDA!H9 -> 2312.6277 | H8: =DEMANDA!H10 -> 14495.071 | I8: =DEMANDA!H11 -> 605.62479 | J8: =DEMANDA!H12 -> 49434.8 | K8: =DEMANDA!H13 -> 1933 | L8: =DEMANDA!H14 -> 9540.8 | M8: =DEMANDA!H15 -> 583.4
C9: Demanda 2031 | F9: =DEMANDA!I8 -> 15620.253 | G9: =DEMANDA!I9 -> 3252.8699 | H9: =DEMANDA!I10 -> 18737.061 | I9: =DEMANDA!I11 -> 876.21675 | J9: =DEMANDA!I12 -> 71680.2 | K9: =DEMANDA!I13 -> 2803 | L9: =DEMANDA!I14 -> 13834.2 | M9: =DEMANDA!I15 -> 845.8
C10: Demanda 2032 | F10: =DEMANDA!J8 -> 20332.553 | G10: =DEMANDA!J9 -> 4102.3155 | H10: =DEMANDA!J10 -> 22634.482 | I10: =DEMANDA!J11 -> 1130.355 | J10: =DEMANDA!J12 -> 101340.6 | K10: =DEMANDA!J13 -> 3963 | L10: =DEMANDA!J14 -> 19558.6 | M10: =DEMANDA!J15 -> 1195.4
C11: Demanda 2033 | F11: =DEMANDA!K8 -> 25132.078 | G11: =DEMANDA!K9 -> 5104.3066 | H11: =DEMANDA!K10 -> 26002.338 | I11: =DEMANDA!K11 -> 1397.6176 | J11: =DEMANDA!K12 -> 131001 | K11: =DEMANDA!K13 -> 5123 | L11: =DEMANDA!K14 -> 25283 | M11: =DEMANDA!K15 -> 1545
C12: Demanda 2034 | F12: =DEMANDA!L8 -> 28573.336 | G12: =DEMANDA!L9 -> 6195.1862 | H12: =DEMANDA!L10 -> 28613.4 | I12: =DEMANDA!L11 -> 1614.5948 | J12: =DEMANDA!L12 -> 146819.8 | K12: =DEMANDA!L13 -> 5741.4 | L12: =DEMANDA!L14 -> 28335.8 | M12: =DEMANDA!L15 -> 1731.4
C13: Demanda 2035 | F13: =DEMANDA!M8 -> 32072.639 | G13: =DEMANDA!M9 -> 7424.8584 | H13: =DEMANDA!M10 -> 32428.771 | I13: =DEMANDA!M11 -> 1842.877 | J13: =DEMANDA!M12 -> 170548 | K13: =DEMANDA!M13 -> 6669 | L13: =DEMANDA!M14 -> 32915 | M13: =DEMANDA!M15 -> 2011
C14: Producción del mes pico de cada producto, 2035 | F14: =ESTACIONALIDAD!P10 -> 3848.7167 | G14: =ESTACIONALIDAD!P11 -> 816.73443 | H14: =ESTACIONALIDAD!P12 -> 3567.1648 | I14: =ESTACIONALIDAD!P13 -> 202.71647 | J14: =ESTACIONALIDAD!P14 -> 20465.76 | K14: =ESTACIONALIDAD!P15 -> 733.59 | L14: =ESTACIONALIDAD!P16 -> 3620.65 | M14: =ESTACIONALIDAD!P17 -> 221.21
C15: CONSUMO POR UNIDAD (cantidad del material por cada producto)
A16: M01 | B16: MP-01 | C16: Caño c/costura Ø76,2 × 1,25 × 6 m (cuerpo 1 kg) | D16: barra | F16: =1/23 -> 0.043478261 | J16: =1/23 -> 0.043478261 | N16: =SUMPRODUCT($F16:$M16,$F$4:$M$4) -> 181.6842 | O16: =SUMPRODUCT($F16:$M16,$F$5:$M$5) -> 260.75235 | P16: =SUMPRODUCT($F16:$M16,$F$6:$M$6) -> 631.0499 | Q16: =SUMPRODUCT($F16:$M16,$F$7:$M$7) -> 1528.7798 | R16: =SUMPRODUCT($F16:$M16,$F$8:$M$8) -> 2700.671 | S16: =SUMPRODUCT($F16:$M16,$F$9:$M$9) -> 3795.6719 | T16: =SUMPRODUCT($F16:$M16,$F$10:$M$10) -> 5290.1371 | U16: =SUMPRODUCT($F16:$M16,$F$11:$M$11) -> 6788.3947 | V16: =SUMPRODUCT($F16:$M16,$F$12:$M$12) -> 7625.7885 | W16: =SUMPRODUCT($F16:$M16,$F$13:$M$13) -> 8809.593 | X16: =SUMPRODUCT($F16:$M16,$F$14:$M$14) -> 1057.1512
A17: M02 | B17: MP-02 | C17: Hoja LAF 1,25 × 1220 × 2440 mm | D17: hoja | G17: =1/27 -> 0.037037037 | K17: =1/27 -> 0.037037037 | N17: =SUMPRODUCT($F17:$M17,$F$4:$M$4) -> 10.92705 | O17: =SUMPRODUCT($F17:$M17,$F$5:$M$5) -> 26.286202 | P17: =SUMPRODUCT($F17:$M17,$F$6:$M$6) -> 47.646965 | Q17: =SUMPRODUCT($F17:$M17,$F$7:$M$7) -> 94.238451 | R17: =SUMPRODUCT($F17:$M17,$F$8:$M$8) -> 157.24547 | S17: =SUMPRODUCT($F17:$M17,$F$9:$M$9) -> 224.29148 | T17: =SUMPRODUCT($F17:$M17,$F$10:$M$10) -> 298.71539 | U17: =SUMPRODUCT($F17:$M17,$F$11:$M$11) -> 378.78913 | V17: =SUMPRODUCT($F17:$M17,$F$12:$M$12) -> 442.09579 | W17: =SUMPRODUCT($F17:$M17,$F$13:$M$13) -> 521.99476 | X17: =SUMPRODUCT($F17:$M17,$F$14:$M$14) -> 57.419423
A18: M03 | B18: MP-03 | C18: Hoja LAF 1,6 × 1000 × 2000 mm | D18: hoja | H18: =1/12 -> 0.083333333 | L18: =1/12 -> 0.083333333 | N18: =SUMPRODUCT($F18:$M18,$F$4:$M$4) -> 227.3253 | O18: =SUMPRODUCT($F18:$M18,$F$5:$M$5) -> 457.40922 | P18: =SUMPRODUCT($F18:$M18,$F$6:$M$6) -> 723.78212 | Q18: =SUMPRODUCT($F18:$M18,$F$7:$M$7) -> 1297.7423 | R18: =SUMPRODUCT($F18:$M18,$F$8:$M$8) -> 2002.9893 | S18: =SUMPRODUCT($F18:$M18,$F$9:$M$9) -> 2714.2717 | T18: =SUMPRODUCT($F18:$M18,$F$10:$M$10) -> 3516.0902 | U18: =SUMPRODUCT($F18:$M18,$F$11:$M$11) -> 4273.7782 | V18: =SUMPRODUCT($F18:$M18,$F$12:$M$12) -> 4745.7666 | W18: =SUMPRODUCT($F18:$M18,$F$13:$M$13) -> 5445.3142 | X18: =SUMPRODUCT($F18:$M18,$F$14:$M$14) -> 598.98456
A19: M04 | B19: MP-04 | C19: Hoja LAF 2,0 × 1500 × 3000 mm | D19: hoja | I19: =1/15 -> 0.066666667 | M19: =1/15 -> 0.066666667 | N19: =SUMPRODUCT($F19:$M19,$F$4:$M$4) -> 6.1605836 | O19: =SUMPRODUCT($F19:$M19,$F$5:$M$5) -> 11.875962 | P19: =SUMPRODUCT($F19:$M19,$F$6:$M$6) -> 23.031015 | Q19: =SUMPRODUCT($F19:$M19,$F$7:$M$7) -> 45.071402 | R19: =SUMPRODUCT($F19:$M19,$F$8:$M$8) -> 79.26832 | S19: =SUMPRODUCT($F19:$M19,$F$9:$M$9) -> 114.80112 | T19: =SUMPRODUCT($F19:$M19,$F$10:$M$10) -> 155.05033 | U19: =SUMPRODUCT($F19:$M19,$F$11:$M$11) -> 196.17451 | V19: =SUMPRODUCT($F19:$M19,$F$12:$M$12) -> 223.06632 | W19: =SUMPRODUCT($F19:$M19,$F$13:$M$13) -> 256.92513 | X19: =SUMPRODUCT($F19:$M19,$F$14:$M$14) -> 28.261764
A20: M05 | B20: MP-05 | C20: Fleje LAF 0,9 × 114 mm (cúpula 1 kg) | D20: kg | F20: =114*(95+3)*0.9*7.85/1000000 -> 0.07893018 | J20: =114*(95+3)*0.9*7.85/1000000 -> 0.07893018 | N20: =SUMPRODUCT($F20:$M20,$F$4:$M$4) -> 329.82843 | O20: =SUMPRODUCT($F20:$M20,$F$5:$M$5) -> 473.36828 | P20: =SUMPRODUCT($F20:$M20,$F$6:$M$6) -> 1145.6043 | Q20: =SUMPRODUCT($F20:$M20,$F$7:$M$7) -> 2775.3379 | R20: =SUMPRODUCT($F20:$M20,$F$8:$M$8) -> 4902.7823 | S20: =SUMPRODUCT($F20:$M20,$F$9:$M$9) -> 6890.6405 | T20: =SUMPRODUCT($F20:$M20,$F$10:$M$10) -> 9603.6839 | U20: =SUMPRODUCT($F20:$M20,$F$11:$M$11) -> 12323.612 | V20: =SUMPRODUCT($F20:$M20,$F$12:$M$12) -> 13843.812 | W20: =SUMPRODUCT($F20:$M20,$F$13:$M$13) -> 15992.884 | X20: =SUMPRODUCT($F20:$M20,$F$14:$M$14) -> 1919.146
A21: M06 | B21: MP-13 | C21: Fleje LAF 1,25 × 135 mm (fondo 1 kg) | D21: kg | F21: =135*(112+3)*1.25*7.85/1000000 -> 0.15233906 | J21: =135*(112+3)*1.25*7.85/1000000 -> 0.15233906 | N21: =SUMPRODUCT($F21:$M21,$F$4:$M$4) -> 636.58481 | O21: =SUMPRODUCT($F21:$M21,$F$5:$M$5) -> 913.62367 | P21: =SUMPRODUCT($F21:$M21,$F$6:$M$6) -> 2211.0717 | Q21: =SUMPRODUCT($F21:$M21,$F$7:$M$7) -> 5356.5363 | R21: =SUMPRODUCT($F21:$M21,$F$8:$M$8) -> 9462.6068 | S21: =SUMPRODUCT($F21:$M21,$F$9:$M$9) -> 13299.269 | T21: =SUMPRODUCT($F21:$M21,$F$10:$M$10) -> 18535.574 | U21: =SUMPRODUCT($F21:$M21,$F$11:$M$11) -> 23785.167 | V21: =SUMPRODUCT($F21:$M21,$F$12:$M$12) -> 26719.226 | W21: =SUMPRODUCT($F21:$M21,$F$13:$M$13) -> 30867.038 | X21: =SUMPRODUCT($F21:$M21,$F$14:$M$14) -> 3704.0446
A22: M07 | B22: MP-06 | C22: Fleje LAF 1,25 × 200 mm (cúpula y fondo 2,5 kg) | D22: kg | G22: =200*(179+3)*1.25*7.85/1000000+200*(148+3)*1.25*7.85/1000000 -> 0.6535125 | K22: =200*(179+3)*1.25*7.85/1000000+200*(148+3)*1.25*7.85/1000000 -> 0.6535125 | N22: =SUMPRODUCT($F22:$M22,$F$4:$M$4) -> 192.80603 | O22: =SUMPRODUCT($F22:$M22,$F$5:$M$5) -> 463.81576 | P22: =SUMPRODUCT($F22:$M22,$F$6:$M$6) -> 840.72296 | Q22: =SUMPRODUCT($F22:$M22,$F$7:$M$7) -> 1662.8222 | R22: =SUMPRODUCT($F22:$M22,$F$8:$M$8) -> 2774.5708 | S22: =SUMPRODUCT($F22:$M22,$F$9:$M$9) -> 3957.5867 | T22: =SUMPRODUCT($F22:$M22,$F$10:$M$10) -> 5270.7845 | U22: =SUMPRODUCT($F22:$M22,$F$11:$M$11) -> 6683.6727 | V22: =SUMPRODUCT($F22:$M22,$F$12:$M$12) -> 7800.7083 | W22: =SUMPRODUCT($F22:$M22,$F$13:$M$13) -> 9210.5127 | X22: =SUMPRODUCT($F22:$M22,$F$14:$M$14) -> 1013.1564
A23: M08 | B23: MP-07 | C23: Fleje LAF 1,6 × 250 mm (cúpula 5 kg) | D23: kg | H23: =250*(221+3)*1.6*7.85/1000000 -> 0.70336 | L23: =250*(221+3)*1.6*7.85/1000000 -> 0.70336 | N23: =SUMPRODUCT($F23:$M23,$F$4:$M$4) -> 1918.6983 | O23: =SUMPRODUCT($F23:$M23,$F$5:$M$5) -> 3860.6802 | P23: =SUMPRODUCT($F23:$M23,$F$6:$M$6) -> 6108.9527 | Q23: =SUMPRODUCT($F23:$M23,$F$7:$M$7) -> 10953.36 | R23: =SUMPRODUCT($F23:$M23,$F$8:$M$8) -> 16905.87 | S23: =SUMPRODUCT($F23:$M23,$F$9:$M$9) -> 22909.322 | T23: =SUMPRODUCT($F23:$M23,$F$10:$M$10) -> 29676.926 | U23: =SUMPRODUCT($F23:$M23,$F$11:$M$11) -> 36072.056 | V23: =SUMPRODUCT($F23:$M23,$F$12:$M$12) -> 40055.789 | W23: =SUMPRODUCT($F23:$M23,$F$13:$M$13) -> 45960.195 | X23: =SUMPRODUCT($F23:$M23,$F$14:$M$14) -> 5055.6214
A24: M09 | B24: MP-08 | C24: Fleje LAF 1,6 × 200 mm (fondo 5 kg) | D24: kg | H24: =200*(177+3)*1.6*7.85/1000000 -> 0.45216 | L24: =200*(177+3)*1.6*7.85/1000000 -> 0.45216 | N24: =SUMPRODUCT($F24:$M24,$F$4:$M$4) -> 1233.4489 | O24: =SUMPRODUCT($F24:$M24,$F$5:$M$5) -> 2481.8658 | P24: =SUMPRODUCT($F24:$M24,$F$6:$M$6) -> 3927.1839 | Q24: =SUMPRODUCT($F24:$M24,$F$7:$M$7) -> 7041.446 | R24: =SUMPRODUCT($F24:$M24,$F$8:$M$8) -> 10868.06 | S24: =SUMPRODUCT($F24:$M24,$F$9:$M$9) -> 14727.421 | T24: =SUMPRODUCT($F24:$M24,$F$10:$M$10) -> 19078.024 | U24: =SUMPRODUCT($F24:$M24,$F$11:$M$11) -> 23189.179 | V24: =SUMPRODUCT($F24:$M24,$F$12:$M$12) -> 25750.15 | W24: =SUMPRODUCT($F24:$M24,$F$13:$M$13) -> 29545.839 | X24: =SUMPRODUCT($F24:$M24,$F$14:$M$14) -> 3250.0423
A25: M10 | B25: MP-09 | C25: Fleje LAF 1,6 × 300 mm (cúpula 10 kg) | D25: kg | I25: =300*(258+3)*1.6*7.85/1000000 -> 0.983448 | M25: =300*(258+3)*1.6*7.85/1000000 -> 0.983448 | N25: =SUMPRODUCT($F25:$M25,$F$4:$M$4) -> 90.879205 | O25: =SUMPRODUCT($F25:$M25,$F$5:$M$5) -> 175.19087 | P25: =SUMPRODUCT($F25:$M25,$F$6:$M$6) -> 339.74709 | Q25: =SUMPRODUCT($F25:$M25,$F$7:$M$7) -> 664.8807 | R25: =SUMPRODUCT($F25:$M25,$F$8:$M$8) -> 1169.3441 | S25: =SUMPRODUCT($F25:$M25,$F$9:$M$9) -> 1693.5139 | T25: =SUMPRODUCT($F25:$M25,$F$10:$M$10) -> 2287.2591 | U25: =SUMPRODUCT($F25:$M25,$F$11:$M$11) -> 2893.9114 | V25: =SUMPRODUCT($F25:$M25,$F$12:$M$12) -> 3290.6119 | W25: =SUMPRODUCT($F25:$M25,$F$13:$M$13) -> 3790.0876 | X25: =SUMPRODUCT($F25:$M25,$F$14:$M$14) -> 416.90964
A26: M11 | B26: MP-10 | C26: Fleje LAF 2,0 × 249 mm (fondo 10 kg) | D26: kg | I26: =249*(205+3)*2*7.85/1000000 -> 0.8131344 | M26: =249*(205+3)*2*7.85/1000000 -> 0.8131344 | N26: =SUMPRODUCT($F26:$M26,$F$4:$M$4) -> 75.140737 | O26: =SUMPRODUCT($F26:$M26,$F$5:$M$5) -> 144.8513 | P26: =SUMPRODUCT($F26:$M26,$F$6:$M$6) -> 280.90966 | Q26: =SUMPRODUCT($F26:$M26,$F$7:$M$7) -> 549.73661 | R26: =SUMPRODUCT($F26:$M26,$F$8:$M$8) -> 966.83696 | S26: =SUMPRODUCT($F26:$M26,$F$9:$M$9) -> 1400.2311 | T26: =SUMPRODUCT($F26:$M26,$F$10:$M$10) -> 1891.1514 | U26: =SUMPRODUCT($F26:$M26,$F$11:$M$11) -> 2392.7436 | V26: =SUMPRODUCT($F26:$M26,$F$12:$M$12) -> 2720.7435 | W26: =SUMPRODUCT($F26:$M26,$F$13:$M$13) -> 3133.7199 | X26: =SUMPRODUCT($F26:$M26,$F$14:$M$14) -> 344.70919
A27: M12 | B27: MP-18 | C27: Asiento de válvula M22 × 1,5 (1 kg) | D27: u | F27: 1 | J27: 1 | N27: =SUMPRODUCT($F27:$M27,$F$4:$M$4) -> 4178.7365 | O27: =SUMPRODUCT($F27:$M27,$F$5:$M$5) -> 5997.304 | P27: =SUMPRODUCT($F27:$M27,$F$6:$M$6) -> 14514.148 | Q27: =SUMPRODUCT($F27:$M27,$F$7:$M$7) -> 35161.936 | R27: =SUMPRODUCT($F27:$M27,$F$8:$M$8) -> 62115.433 | S27: =SUMPRODUCT($F27:$M27,$F$9:$M$9) -> 87300.453 | T27: =SUMPRODUCT($F27:$M27,$F$10:$M$10) -> 121673.15 | U27: =SUMPRODUCT($F27:$M27,$F$11:$M$11) -> 156133.08 | V27: =SUMPRODUCT($F27:$M27,$F$12:$M$12) -> 175393.14 | W27: =SUMPRODUCT($F27:$M27,$F$13:$M$13) -> 202620.64 | X27: =SUMPRODUCT($F27:$M27,$F$14:$M$14) -> 24314.477
A28: M13 | B28: MP-19 | C28: Asiento de válvula M30 × 1,5 (2,5 a 10 kg) | D28: u | G28: 1 | H28: 1 | I28: 1 | K28: 1 | L28: 1 | M28: 1 | N28: =SUMPRODUCT($F28:$M28,$F$4:$M$4) -> 3115.3427 | O28: =SUMPRODUCT($F28:$M28,$F$5:$M$5) -> 6376.7775 | P28: =SUMPRODUCT($F28:$M28,$F$6:$M$6) -> 10317.319 | Q28: =SUMPRODUCT($F28:$M28,$F$7:$M$7) -> 18793.417 | R28: =SUMPRODUCT($F28:$M28,$F$8:$M$8) -> 29470.524 | S28: =SUMPRODUCT($F28:$M28,$F$9:$M$9) -> 40349.148 | T28: =SUMPRODUCT($F28:$M28,$F$10:$M$10) -> 52584.153 | U28: =SUMPRODUCT($F28:$M28,$F$11:$M$11) -> 64455.263 | V28: =SUMPRODUCT($F28:$M28,$F$12:$M$12) -> 72231.781 | W28: =SUMPRODUCT($F28:$M28,$F$13:$M$13) -> 83291.506 | X28: =SUMPRODUCT($F28:$M28,$F$14:$M$14) -> 9162.0657
A29: M14 | B29: MP-23 | C29: Alambre MAG ER70S-6 Ø0,9 mm (manuales) | D29: kg | F29: 0.01499 | G29: 0.0304 | H29: 0.03675 | I29: 0.04575 | J29: 0.01499 | K29: 0.0304 | L29: 0.03675 | M29: 0.04575 | N29: =SUMPRODUCT($F29:$M29,$F$4:$M$4) -> 176.08634 | O29: =SUMPRODUCT($F29:$M29,$F$5:$M$5) -> 321.34265 | P29: =SUMPRODUCT($F29:$M29,$F$6:$M$6) -> 591.66866 | Q29: =SUMPRODUCT($F29:$M29,$F$7:$M$7) -> 1207.6629 | R29: =SUMPRODUCT($F29:$M29,$F$8:$M$8) -> 1997.8936 | S29: =SUMPRODUCT($F29:$M29,$F$9:$M$9) -> 2768.5083 | T29: =SUMPRODUCT($F29:$M29,$F$10:$M$10) -> 3726.0652 | U29: =SUMPRODUCT($F29:$M29,$F$11:$M$11) -> 4670.7059 | V29: =SUMPRODUCT($F29:$M29,$F$12:$M$12) -> 5237.9777 | W29: =SUMPRODUCT($F29:$M29,$F$13:$M$13) -> 6043.4351 | X29: =SUMPRODUCT($F29:$M29,$F$14:$M$14) -> 695.1507
A30: M15 | B30: MP-25 | C30: Gas MAG Ar + 8 % CO₂ (Arcal 21) | D30: m³ | F30: =0.01671*48/(1216*0.01671+99*0.03388+446*0.04096+27*0.051) -> 0.018515817 | G30: =0.03388*48/(1216*0.01671+99*0.03388+446*0.04096+27*0.051) -> 0.037541345 | H30: =0.04096*48/(1216*0.01671+99*0.03388+446*0.04096+27*0.051) -> 0.045386466 | I30: =0.051*48/(1216*0.01671+99*0.03388+446*0.04096+27*0.051) -> 0.056511469 | J30: =0.01671*48/(1216*0.01671+99*0.03388+446*0.04096+27*0.051) -> 0.018515817 | K30: =0.03388*48/(1216*0.01671+99*0.03388+446*0.04096+27*0.051) -> 0.037541345 | L30: =0.04096*48/(1216*0.01671+99*0.03388+446*0.04096+27*0.051) -> 0.045386466 | M30: =0.051*48/(1216*0.01671+99*0.03388+446*0.04096+27*0.051) -> 0.056511469 | N30: =SUMPRODUCT($F30:$M30,$F$4:$M$4) -> 217.48061 | O30: =SUMPRODUCT($F30:$M30,$F$5:$M$5) -> 396.87828 | P30: =SUMPRODUCT($F30:$M30,$F$6:$M$6) -> 730.75875 | Q30: =SUMPRODUCT($F30:$M30,$F$7:$M$7) -> 1491.5786 | R30: =SUMPRODUCT($F30:$M30,$F$8:$M$8) -> 2467.6013 | S30: =SUMPRODUCT($F30:$M30,$F$9:$M$9) -> 3419.3928 | T30: =SUMPRODUCT($F30:$M30,$F$10:$M$10) -> 4602.0873 | U30: =SUMPRODUCT($F30:$M30,$F$11:$M$11) -> 5768.8302 | V30: =SUMPRODUCT($F30:$M30,$F$12:$M$12) -> 6469.4727 | W30: =SUMPRODUCT($F30:$M30,$F$13:$M$13) -> 7464.3001 | X30: =SUMPRODUCT($F30:$M30,$F$14:$M$14) -> 858.58988
A31: M16 | B31: MP-28 | C31: Granalla de acero S330 / S390 | D31: kg | F31: 0.08 | G31: 0.08 | H31: 0.08 | I31: 0.08 | J31: 0.08 | K31: 0.08 | L31: 0.08 | M31: 0.08 | N31: =SUMPRODUCT($F31:$M31,$F$4:$M$4) -> 583.52634 | O31: =SUMPRODUCT($F31:$M31,$F$5:$M$5) -> 989.92652 | P31: =SUMPRODUCT($F31:$M31,$F$6:$M$6) -> 1986.5173 | Q31: =SUMPRODUCT($F31:$M31,$F$7:$M$7) -> 4316.4282 | R31: =SUMPRODUCT($F31:$M31,$F$8:$M$8) -> 7326.8765 | S31: =SUMPRODUCT($F31:$M31,$F$9:$M$9) -> 10211.968 | T31: =SUMPRODUCT($F31:$M31,$F$10:$M$10) -> 13940.584 | U31: =SUMPRODUCT($F31:$M31,$F$11:$M$11) -> 17647.067 | V31: =SUMPRODUCT($F31:$M31,$F$12:$M$12) -> 19809.993 | W31: =SUMPRODUCT($F31:$M31,$F$13:$M$13) -> 22872.972 | X31: =SUMPRODUCT($F31:$M31,$F$14:$M$14) -> 2678.1234
A32: M17 | B32: MP-31 | C32: Pintura en polvo poliéster rojo 03-1-050 | D32: kg | F32: =0.0764/9.46/0.95 -> 0.0085011684 | G32: =0.1375/9.46/0.95 -> 0.015299878 | H32: =0.2091/9.46/0.95 -> 0.023266941 | I32: =0.351/9.46/0.95 -> 0.039056415 | J32: =0.0764/9.46/0.95 -> 0.0085011684 | K32: =0.1375/9.46/0.95 -> 0.015299878 | L32: =0.2091/9.46/0.95 -> 0.023266941 | M32: =0.351/9.46/0.95 -> 0.039056415 | N32: =SUMPRODUCT($F32:$M32,$F$4:$M$4) -> 107.1172 | O32: =SUMPRODUCT($F32:$M32,$F$5:$M$5) -> 196.51048 | P32: =SUMPRODUCT($F32:$M32,$F$6:$M$6) -> 358.645 | Q32: =SUMPRODUCT($F32:$M32,$F$7:$M$7) -> 726.58597 | R32: =SUMPRODUCT($F32:$M32,$F$8:$M$8) -> 1198.6916 | S32: =SUMPRODUCT($F32:$M32,$F$9:$M$9) -> 1659.8993 | T32: =SUMPRODUCT($F32:$M32,$F$10:$M$10) -> 2230.3019 | U32: =SUMPRODUCT($F32:$M32,$F$11:$M$11) -> 2791.9712 | V32: =SUMPRODUCT($F32:$M32,$F$12:$M$12) -> 3129.3911 | W32: =SUMPRODUCT($F32:$M32,$F$13:$M$13) -> 3609.0148 | X32: =SUMPRODUCT($F32:$M32,$F$14:$M$14) -> 414.21675
A33: M18 | B33: MP-33 | C33: Polvo ABC 60 (manuales y sus recargas) | D33: kg | F33: 1.05 | G33: 2.55 | H33: 5.15 | I33: 10.15 | N33: =SUMPRODUCT($F33:$M33,$F$4:$M$4) -> 20126.653 | O33: =SUMPRODUCT($F33:$M33,$F$5:$M$5) -> 38182.979 | P33: =SUMPRODUCT($F33:$M33,$F$6:$M$6) -> 49413.676 | Q33: =SUMPRODUCT($F33:$M33,$F$7:$M$7) -> 70049.666 | R33: =SUMPRODUCT($F33:$M33,$F$8:$M$8) -> 100008.57 | S33: =SUMPRODUCT($F33:$M33,$F$9:$M$9) -> 130085.55 | T33: =SUMPRODUCT($F33:$M33,$F$10:$M$10) -> 159850.77 | U33: =SUMPRODUCT($F33:$M33,$F$11:$M$11) -> 187502.53 | V33: =SUMPRODUCT($F33:$M33,$F$12:$M$12) -> 209546.87 | W33: =SUMPRODUCT($F33:$M33,$F$13:$M$13) -> 238323.03 | X33: =SUMPRODUCT($F33:$M33,$F$14:$M$14) -> 26552.296
A34: M19 | B34: MP-34 | C34: Nitrógeno seco | D34: m³ | F34: =1.18/3*14/1000 -> 0.0055066667 | G34: =3.5/3*14/1000 -> 0.016333333 | H34: =6/3*14/1000 -> 0.028 | I34: =12.5/3*14/1000 -> 0.058333333 | N34: =SUMPRODUCT($F34:$M34,$F$4:$M$4) -> 109.60155 | O34: =SUMPRODUCT($F34:$M34,$F$5:$M$5) -> 208.69833 | P34: =SUMPRODUCT($F34:$M34,$F$6:$M$6) -> 270.51233 | Q34: =SUMPRODUCT($F34:$M34,$F$7:$M$7) -> 383.98401 | R34: =SUMPRODUCT($F34:$M34,$F$8:$M$8) -> 548.79105 | S34: =SUMPRODUCT($F34:$M34,$F$9:$M$9) -> 714.89609 | T34: =SUMPRODUCT($F34:$M34,$F$10:$M$10) -> 878.67196 | U34: =SUMPRODUCT($F34:$M34,$F$11:$M$11) -> 1031.3575 | V34: =SUMPRODUCT($F34:$M34,$F$12:$M$12) -> 1153.8918 | W34: =SUMPRODUCT($F34:$M34,$F$13:$M$13) -> 1313.3928 | X34: =SUMPRODUCT($F34:$M34,$F$14:$M$14) -> 146.23934
A35: M20 | B35: MP-42 | C35: Válvula HZ M-22 con tubo de pesca (1 kg) | D35: u | F35: 1 | N35: =SUMPRODUCT($F35:$M35,$F$4:$M$4) -> 4178.7365 | O35: =SUMPRODUCT($F35:$M35,$F$5:$M$5) -> 5997.304 | P35: =SUMPRODUCT($F35:$M35,$F$6:$M$6) -> 6851.7478 | Q35: =SUMPRODUCT($F35:$M35,$F$7:$M$7) -> 8467.1355 | R35: =SUMPRODUCT($F35:$M35,$F$8:$M$8) -> 12680.633 | S35: =SUMPRODUCT($F35:$M35,$F$9:$M$9) -> 15620.253 | T35: =SUMPRODUCT($F35:$M35,$F$10:$M$10) -> 20332.553 | U35: =SUMPRODUCT($F35:$M35,$F$11:$M$11) -> 25132.078 | V35: =SUMPRODUCT($F35:$M35,$F$12:$M$12) -> 28573.336 | W35: =SUMPRODUCT($F35:$M35,$F$13:$M$13) -> 32072.639 | X35: =SUMPRODUCT($F35:$M35,$F$14:$M$14) -> 3848.7167
A36: M21 | B36: MP-43 | C36: Válvula HZ M-30 con resorte, sin tubo pescante (2,5 a 10 kg) | D36: u | G36: 1 | H36: 1 | I36: 1 | N36: =SUMPRODUCT($F36:$M36,$F$4:$M$4) -> 3115.3427 | O36: =SUMPRODUCT($F36:$M36,$F$5:$M$5) -> 6376.7775 | P36: =SUMPRODUCT($F36:$M36,$F$6:$M$6) -> 8448.5188 | Q36: =SUMPRODUCT($F36:$M36,$F$7:$M$7) -> 12282.617 | R36: =SUMPRODUCT($F36:$M36,$F$8:$M$8) -> 17413.324 | S36: =SUMPRODUCT($F36:$M36,$F$9:$M$9) -> 22866.148 | T36: =SUMPRODUCT($F36:$M36,$F$10:$M$10) -> 27867.153 | U36: =SUMPRODUCT($F36:$M36,$F$11:$M$11) -> 32504.263 | V36: =SUMPRODUCT($F36:$M36,$F$12:$M$12) -> 36423.181 | W36: =SUMPRODUCT($F36:$M36,$F$13:$M$13) -> 41696.506 | X36: =SUMPRODUCT($F36:$M36,$F$14:$M$14) -> 4586.6157
A37: M22 | B37: MP-45 | C37: Manómetro 1,4 MPa | D37: u | F37: 1 | G37: 1 | H37: 1 | I37: 1 | N37: =SUMPRODUCT($F37:$M37,$F$4:$M$4) -> 7294.0792 | O37: =SUMPRODUCT($F37:$M37,$F$5:$M$5) -> 12374.081 | P37: =SUMPRODUCT($F37:$M37,$F$6:$M$6) -> 15300.267 | Q37: =SUMPRODUCT($F37:$M37,$F$7:$M$7) -> 20749.753 | R37: =SUMPRODUCT($F37:$M37,$F$8:$M$8) -> 30093.957 | S37: =SUMPRODUCT($F37:$M37,$F$9:$M$9) -> 38486.401 | T37: =SUMPRODUCT($F37:$M37,$F$10:$M$10) -> 48199.706 | U37: =SUMPRODUCT($F37:$M37,$F$11:$M$11) -> 57636.341 | V37: =SUMPRODUCT($F37:$M37,$F$12:$M$12) -> 64996.517 | W37: =SUMPRODUCT($F37:$M37,$F$13:$M$13) -> 73769.145 | X37: =SUMPRODUCT($F37:$M37,$F$14:$M$14) -> 8435.3324
A38: M23 | B38: MP-46/ABC2.5 | C38: Tubo pescante de PVC rígido, ABC 2,5 kg | D38: u | G38: 1 | N38: =SUMPRODUCT($F38:$M38,$F$4:$M$4) -> 295.03036 | O38: =SUMPRODUCT($F38:$M38,$F$5:$M$5) -> 709.72745 | P38: =SUMPRODUCT($F38:$M38,$F$6:$M$6) -> 986.86806 | Q38: =SUMPRODUCT($F38:$M38,$F$7:$M$7) -> 1500.6382 | R38: =SUMPRODUCT($F38:$M38,$F$8:$M$8) -> 2312.6277 | S38: =SUMPRODUCT($F38:$M38,$F$9:$M$9) -> 3252.8699 | T38: =SUMPRODUCT($F38:$M38,$F$10:$M$10) -> 4102.3155 | U38: =SUMPRODUCT($F38:$M38,$F$11:$M$11) -> 5104.3066 | V38: =SUMPRODUCT($F38:$M38,$F$12:$M$12) -> 6195.1862 | W38: =SUMPRODUCT($F38:$M38,$F$13:$M$13) -> 7424.8584 | X38: =SUMPRODUCT($F38:$M38,$F$14:$M$14) -> 816.73443
A39: M24 | B39: MP-46/ABC5 | C39: Tubo pescante de PVC rígido, ABC 5 kg | D39: u | H39: 1 | N39: =SUMPRODUCT($F39:$M39,$F$4:$M$4) -> 2727.9036 | O39: =SUMPRODUCT($F39:$M39,$F$5:$M$5) -> 5488.9106 | P39: =SUMPRODUCT($F39:$M39,$F$6:$M$6) -> 7206.5855 | Q39: =SUMPRODUCT($F39:$M39,$F$7:$M$7) -> 10420.908 | R39: =SUMPRODUCT($F39:$M39,$F$8:$M$8) -> 14495.071 | S39: =SUMPRODUCT($F39:$M39,$F$9:$M$9) -> 18737.061 | T39: =SUMPRODUCT($F39:$M39,$F$10:$M$10) -> 22634.482 | U39: =SUMPRODUCT($F39:$M39,$F$11:$M$11) -> 26002.338 | V39: =SUMPRODUCT($F39:$M39,$F$12:$M$12) -> 28613.4 | W39: =SUMPRODUCT($F39:$M39,$F$13:$M$13) -> 32428.771 | X39: =SUMPRODUCT($F39:$M39,$F$14:$M$14) -> 3567.1648
A40: M25 | B40: MP-46/ABC10 | C40: Tubo pescante de PVC rígido, ABC 10 kg | D40: u | I40: 1 | N40: =SUMPRODUCT($F40:$M40,$F$4:$M$4) -> 92.408754 | O40: =SUMPRODUCT($F40:$M40,$F$5:$M$5) -> 178.13943 | P40: =SUMPRODUCT($F40:$M40,$F$6:$M$6) -> 255.06523 | Q40: =SUMPRODUCT($F40:$M40,$F$7:$M$7) -> 361.07103 | R40: =SUMPRODUCT($F40:$M40,$F$8:$M$8) -> 605.62479 | S40: =SUMPRODUCT($F40:$M40,$F$9:$M$9) -> 876.21675 | T40: =SUMPRODUCT($F40:$M40,$F$10:$M$10) -> 1130.355 | U40: =SUMPRODUCT($F40:$M40,$F$11:$M$11) -> 1397.6176 | V40: =SUMPRODUCT($F40:$M40,$F$12:$M$12) -> 1614.5948 | W40: =SUMPRODUCT($F40:$M40,$F$13:$M$13) -> 1842.877 | X40: =SUMPRODUCT($F40:$M40,$F$14:$M$14) -> 202.71647
A41: M26 | B41: MP-48/ABC1 | C41: Tobera ABC 1 kg | D41: u | F41: 1 | N41: =SUMPRODUCT($F41:$M41,$F$4:$M$4) -> 4178.7365 | O41: =SUMPRODUCT($F41:$M41,$F$5:$M$5) -> 5997.304 | P41: =SUMPRODUCT($F41:$M41,$F$6:$M$6) -> 6851.7478 | Q41: =SUMPRODUCT($F41:$M41,$F$7:$M$7) -> 8467.1355 | R41: =SUMPRODUCT($F41:$M41,$F$8:$M$8) -> 12680.633 | S41: =SUMPRODUCT($F41:$M41,$F$9:$M$9) -> 15620.253 | T41: =SUMPRODUCT($F41:$M41,$F$10:$M$10) -> 20332.553 | U41: =SUMPRODUCT($F41:$M41,$F$11:$M$11) -> 25132.078 | V41: =SUMPRODUCT($F41:$M41,$F$12:$M$12) -> 28573.336 | W41: =SUMPRODUCT($F41:$M41,$F$13:$M$13) -> 32072.639 | X41: =SUMPRODUCT($F41:$M41,$F$14:$M$14) -> 3848.7167
A42: M27 | B42: MP-48/ABC2.5 | C42: Manguera con tobera ABC 2,5 kg | D42: u | G42: 1 | N42: =SUMPRODUCT($F42:$M42,$F$4:$M$4) -> 295.03036 | O42: =SUMPRODUCT($F42:$M42,$F$5:$M$5) -> 709.72745 | P42: =SUMPRODUCT($F42:$M42,$F$6:$M$6) -> 986.86806 | Q42: =SUMPRODUCT($F42:$M42,$F$7:$M$7) -> 1500.6382 | R42: =SUMPRODUCT($F42:$M42,$F$8:$M$8) -> 2312.6277 | S42: =SUMPRODUCT($F42:$M42,$F$9:$M$9) -> 3252.8699 | T42: =SUMPRODUCT($F42:$M42,$F$10:$M$10) -> 4102.3155 | U42: =SUMPRODUCT($F42:$M42,$F$11:$M$11) -> 5104.3066 | V42: =SUMPRODUCT($F42:$M42,$F$12:$M$12) -> 6195.1862 | W42: =SUMPRODUCT($F42:$M42,$F$13:$M$13) -> 7424.8584 | X42: =SUMPRODUCT($F42:$M42,$F$14:$M$14) -> 816.73443
A43: M28 | B43: MP-48/ABC5 | C43: Manguera con tobera ABC 5 kg | D43: u | H43: 1 | N43: =SUMPRODUCT($F43:$M43,$F$4:$M$4) -> 2727.9036 | O43: =SUMPRODUCT($F43:$M43,$F$5:$M$5) -> 5488.9106 | P43: =SUMPRODUCT($F43:$M43,$F$6:$M$6) -> 7206.5855 | Q43: =SUMPRODUCT($F43:$M43,$F$7:$M$7) -> 10420.908 | R43: =SUMPRODUCT($F43:$M43,$F$8:$M$8) -> 14495.071 | S43: =SUMPRODUCT($F43:$M43,$F$9:$M$9) -> 18737.061 | T43: =SUMPRODUCT($F43:$M43,$F$10:$M$10) -> 22634.482 | U43: =SUMPRODUCT($F43:$M43,$F$11:$M$11) -> 26002.338 | V43: =SUMPRODUCT($F43:$M43,$F$12:$M$12) -> 28613.4 | W43: =SUMPRODUCT($F43:$M43,$F$13:$M$13) -> 32428.771 | X43: =SUMPRODUCT($F43:$M43,$F$14:$M$14) -> 3567.1648
A44: M29 | B44: MP-48/ABC10 | C44: Manguera con tobera ABC 10 kg | D44: u | I44: 1 | N44: =SUMPRODUCT($F44:$M44,$F$4:$M$4) -> 92.408754 | O44: =SUMPRODUCT($F44:$M44,$F$5:$M$5) -> 178.13943 | P44: =SUMPRODUCT($F44:$M44,$F$6:$M$6) -> 255.06523 | Q44: =SUMPRODUCT($F44:$M44,$F$7:$M$7) -> 361.07103 | R44: =SUMPRODUCT($F44:$M44,$F$8:$M$8) -> 605.62479 | S44: =SUMPRODUCT($F44:$M44,$F$9:$M$9) -> 876.21675 | T44: =SUMPRODUCT($F44:$M44,$F$10:$M$10) -> 1130.355 | U44: =SUMPRODUCT($F44:$M44,$F$11:$M$11) -> 1397.6176 | V44: =SUMPRODUCT($F44:$M44,$F$12:$M$12) -> 1614.5948 | W44: =SUMPRODUCT($F44:$M44,$F$13:$M$13) -> 1842.877 | X44: =SUMPRODUCT($F44:$M44,$F$14:$M$14) -> 202.71647
A45: M30 | B45: MP-50/M22 | C45: Junta tórica del cuello M22 | D45: u | F45: 1 | N45: =SUMPRODUCT($F45:$M45,$F$4:$M$4) -> 4178.7365 | O45: =SUMPRODUCT($F45:$M45,$F$5:$M$5) -> 5997.304 | P45: =SUMPRODUCT($F45:$M45,$F$6:$M$6) -> 6851.7478 | Q45: =SUMPRODUCT($F45:$M45,$F$7:$M$7) -> 8467.1355 | R45: =SUMPRODUCT($F45:$M45,$F$8:$M$8) -> 12680.633 | S45: =SUMPRODUCT($F45:$M45,$F$9:$M$9) -> 15620.253 | T45: =SUMPRODUCT($F45:$M45,$F$10:$M$10) -> 20332.553 | U45: =SUMPRODUCT($F45:$M45,$F$11:$M$11) -> 25132.078 | V45: =SUMPRODUCT($F45:$M45,$F$12:$M$12) -> 28573.336 | W45: =SUMPRODUCT($F45:$M45,$F$13:$M$13) -> 32072.639 | X45: =SUMPRODUCT($F45:$M45,$F$14:$M$14) -> 3848.7167
A46: M31 | B46: MP-50/M30 | C46: Junta tórica del cuello M30 | D46: u | G46: 1 | H46: 1 | I46: 1 | N46: =SUMPRODUCT($F46:$M46,$F$4:$M$4) -> 3115.3427 | O46: =SUMPRODUCT($F46:$M46,$F$5:$M$5) -> 6376.7775 | P46: =SUMPRODUCT($F46:$M46,$F$6:$M$6) -> 8448.5188 | Q46: =SUMPRODUCT($F46:$M46,$F$7:$M$7) -> 12282.617 | R46: =SUMPRODUCT($F46:$M46,$F$8:$M$8) -> 17413.324 | S46: =SUMPRODUCT($F46:$M46,$F$9:$M$9) -> 22866.148 | T46: =SUMPRODUCT($F46:$M46,$F$10:$M$10) -> 27867.153 | U46: =SUMPRODUCT($F46:$M46,$F$11:$M$11) -> 32504.263 | V46: =SUMPRODUCT($F46:$M46,$F$12:$M$12) -> 36423.181 | W46: =SUMPRODUCT($F46:$M46,$F$13:$M$13) -> 41696.506 | X46: =SUMPRODUCT($F46:$M46,$F$14:$M$14) -> 4586.6157
A47: M32 | B47: MP-52/ABC2.5 | C47: Soporte de pared ABC 2,5 kg | D47: u | G47: 1 | N47: =SUMPRODUCT($F47:$M47,$F$4:$M$4) -> 295.03036 | O47: =SUMPRODUCT($F47:$M47,$F$5:$M$5) -> 709.72745 | P47: =SUMPRODUCT($F47:$M47,$F$6:$M$6) -> 986.86806 | Q47: =SUMPRODUCT($F47:$M47,$F$7:$M$7) -> 1500.6382 | R47: =SUMPRODUCT($F47:$M47,$F$8:$M$8) -> 2312.6277 | S47: =SUMPRODUCT($F47:$M47,$F$9:$M$9) -> 3252.8699 | T47: =SUMPRODUCT($F47:$M47,$F$10:$M$10) -> 4102.3155 | U47: =SUMPRODUCT($F47:$M47,$F$11:$M$11) -> 5104.3066 | V47: =SUMPRODUCT($F47:$M47,$F$12:$M$12) -> 6195.1862 | W47: =SUMPRODUCT($F47:$M47,$F$13:$M$13) -> 7424.8584 | X47: =SUMPRODUCT($F47:$M47,$F$14:$M$14) -> 816.73443
A48: M33 | B48: MP-52/ABC5 | C48: Soporte de pared ABC 5 kg | D48: u | H48: 1 | N48: =SUMPRODUCT($F48:$M48,$F$4:$M$4) -> 2727.9036 | O48: =SUMPRODUCT($F48:$M48,$F$5:$M$5) -> 5488.9106 | P48: =SUMPRODUCT($F48:$M48,$F$6:$M$6) -> 7206.5855 | Q48: =SUMPRODUCT($F48:$M48,$F$7:$M$7) -> 10420.908 | R48: =SUMPRODUCT($F48:$M48,$F$8:$M$8) -> 14495.071 | S48: =SUMPRODUCT($F48:$M48,$F$9:$M$9) -> 18737.061 | T48: =SUMPRODUCT($F48:$M48,$F$10:$M$10) -> 22634.482 | U48: =SUMPRODUCT($F48:$M48,$F$11:$M$11) -> 26002.338 | V48: =SUMPRODUCT($F48:$M48,$F$12:$M$12) -> 28613.4 | W48: =SUMPRODUCT($F48:$M48,$F$13:$M$13) -> 32428.771 | X48: =SUMPRODUCT($F48:$M48,$F$14:$M$14) -> 3567.1648
A49: M34 | B49: MP-52/ABC10 | C49: Soporte de pared ABC 10 kg | D49: u | I49: 1 | N49: =SUMPRODUCT($F49:$M49,$F$4:$M$4) -> 92.408754 | O49: =SUMPRODUCT($F49:$M49,$F$5:$M$5) -> 178.13943 | P49: =SUMPRODUCT($F49:$M49,$F$6:$M$6) -> 255.06523 | Q49: =SUMPRODUCT($F49:$M49,$F$7:$M$7) -> 361.07103 | R49: =SUMPRODUCT($F49:$M49,$F$8:$M$8) -> 605.62479 | S49: =SUMPRODUCT($F49:$M49,$F$9:$M$9) -> 876.21675 | T49: =SUMPRODUCT($F49:$M49,$F$10:$M$10) -> 1130.355 | U49: =SUMPRODUCT($F49:$M49,$F$11:$M$11) -> 1397.6176 | V49: =SUMPRODUCT($F49:$M49,$F$12:$M$12) -> 1614.5948 | W49: =SUMPRODUCT($F49:$M49,$F$13:$M$13) -> 1842.877 | X49: =SUMPRODUCT($F49:$M49,$F$14:$M$14) -> 202.71647
A50: M35 | B50: MP-87 | C50: Soporte vehicular (1 kg) | D50: u | F50: 1 | N50: =SUMPRODUCT($F50:$M50,$F$4:$M$4) -> 4178.7365 | O50: =SUMPRODUCT($F50:$M50,$F$5:$M$5) -> 5997.304 | P50: =SUMPRODUCT($F50:$M50,$F$6:$M$6) -> 6851.7478 | Q50: =SUMPRODUCT($F50:$M50,$F$7:$M$7) -> 8467.1355 | R50: =SUMPRODUCT($F50:$M50,$F$8:$M$8) -> 12680.633 | S50: =SUMPRODUCT($F50:$M50,$F$9:$M$9) -> 15620.253 | T50: =SUMPRODUCT($F50:$M50,$F$10:$M$10) -> 20332.553 | U50: =SUMPRODUCT($F50:$M50,$F$11:$M$11) -> 25132.078 | V50: =SUMPRODUCT($F50:$M50,$F$12:$M$12) -> 28573.336 | W50: =SUMPRODUCT($F50:$M50,$F$13:$M$13) -> 32072.639 | X50: =SUMPRODUCT($F50:$M50,$F$14:$M$14) -> 3848.7167
A51: M36 | B51: MP-86 | C51: Tornillo y tarugo de fijación | D51: u | G51: 2 | H51: 2 | I51: 2 | N51: =SUMPRODUCT($F51:$M51,$F$4:$M$4) -> 6230.6854 | O51: =SUMPRODUCT($F51:$M51,$F$5:$M$5) -> 12753.555 | P51: =SUMPRODUCT($F51:$M51,$F$6:$M$6) -> 16897.038 | Q51: =SUMPRODUCT($F51:$M51,$F$7:$M$7) -> 24565.234 | R51: =SUMPRODUCT($F51:$M51,$F$8:$M$8) -> 34826.648 | S51: =SUMPRODUCT($F51:$M51,$F$9:$M$9) -> 45732.295 | T51: =SUMPRODUCT($F51:$M51,$F$10:$M$10) -> 55734.305 | U51: =SUMPRODUCT($F51:$M51,$F$11:$M$11) -> 65008.525 | V51: =SUMPRODUCT($F51:$M51,$F$12:$M$12) -> 72846.362 | W51: =SUMPRODUCT($F51:$M51,$F$13:$M$13) -> 83393.012 | X51: =SUMPRODUCT($F51:$M51,$F$14:$M$14) -> 9173.2313
A52: M37 | B52: MP-56/ABC1 | C52: Etiqueta de características ABC 1 kg | D52: u | F52: 1 | N52: =SUMPRODUCT($F52:$M52,$F$4:$M$4) -> 4178.7365 | O52: =SUMPRODUCT($F52:$M52,$F$5:$M$5) -> 5997.304 | P52: =SUMPRODUCT($F52:$M52,$F$6:$M$6) -> 6851.7478 | Q52: =SUMPRODUCT($F52:$M52,$F$7:$M$7) -> 8467.1355 | R52: =SUMPRODUCT($F52:$M52,$F$8:$M$8) -> 12680.633 | S52: =SUMPRODUCT($F52:$M52,$F$9:$M$9) -> 15620.253 | T52: =SUMPRODUCT($F52:$M52,$F$10:$M$10) -> 20332.553 | U52: =SUMPRODUCT($F52:$M52,$F$11:$M$11) -> 25132.078 | V52: =SUMPRODUCT($F52:$M52,$F$12:$M$12) -> 28573.336 | W52: =SUMPRODUCT($F52:$M52,$F$13:$M$13) -> 32072.639 | X52: =SUMPRODUCT($F52:$M52,$F$14:$M$14) -> 3848.7167
A53: M38 | B53: MP-56/ABC2.5 | C53: Etiqueta de características ABC 2,5 kg | D53: u | G53: 1 | N53: =SUMPRODUCT($F53:$M53,$F$4:$M$4) -> 295.03036 | O53: =SUMPRODUCT($F53:$M53,$F$5:$M$5) -> 709.72745 | P53: =SUMPRODUCT($F53:$M53,$F$6:$M$6) -> 986.86806 | Q53: =SUMPRODUCT($F53:$M53,$F$7:$M$7) -> 1500.6382 | R53: =SUMPRODUCT($F53:$M53,$F$8:$M$8) -> 2312.6277 | S53: =SUMPRODUCT($F53:$M53,$F$9:$M$9) -> 3252.8699 | T53: =SUMPRODUCT($F53:$M53,$F$10:$M$10) -> 4102.3155 | U53: =SUMPRODUCT($F53:$M53,$F$11:$M$11) -> 5104.3066 | V53: =SUMPRODUCT($F53:$M53,$F$12:$M$12) -> 6195.1862 | W53: =SUMPRODUCT($F53:$M53,$F$13:$M$13) -> 7424.8584 | X53: =SUMPRODUCT($F53:$M53,$F$14:$M$14) -> 816.73443
A54: M39 | B54: MP-56/ABC5 | C54: Etiqueta de características ABC 5 kg | D54: u | H54: 1 | N54: =SUMPRODUCT($F54:$M54,$F$4:$M$4) -> 2727.9036 | O54: =SUMPRODUCT($F54:$M54,$F$5:$M$5) -> 5488.9106 | P54: =SUMPRODUCT($F54:$M54,$F$6:$M$6) -> 7206.5855 | Q54: =SUMPRODUCT($F54:$M54,$F$7:$M$7) -> 10420.908 | R54: =SUMPRODUCT($F54:$M54,$F$8:$M$8) -> 14495.071 | S54: =SUMPRODUCT($F54:$M54,$F$9:$M$9) -> 18737.061 | T54: =SUMPRODUCT($F54:$M54,$F$10:$M$10) -> 22634.482 | U54: =SUMPRODUCT($F54:$M54,$F$11:$M$11) -> 26002.338 | V54: =SUMPRODUCT($F54:$M54,$F$12:$M$12) -> 28613.4 | W54: =SUMPRODUCT($F54:$M54,$F$13:$M$13) -> 32428.771 | X54: =SUMPRODUCT($F54:$M54,$F$14:$M$14) -> 3567.1648
A55: M40 | B55: MP-56/ABC10 | C55: Etiqueta de características ABC 10 kg | D55: u | I55: 1 | N55: =SUMPRODUCT($F55:$M55,$F$4:$M$4) -> 92.408754 | O55: =SUMPRODUCT($F55:$M55,$F$5:$M$5) -> 178.13943 | P55: =SUMPRODUCT($F55:$M55,$F$6:$M$6) -> 255.06523 | Q55: =SUMPRODUCT($F55:$M55,$F$7:$M$7) -> 361.07103 | R55: =SUMPRODUCT($F55:$M55,$F$8:$M$8) -> 605.62479 | S55: =SUMPRODUCT($F55:$M55,$F$9:$M$9) -> 876.21675 | T55: =SUMPRODUCT($F55:$M55,$F$10:$M$10) -> 1130.355 | U55: =SUMPRODUCT($F55:$M55,$F$11:$M$11) -> 1397.6176 | V55: =SUMPRODUCT($F55:$M55,$F$12:$M$12) -> 1614.5948 | W55: =SUMPRODUCT($F55:$M55,$F$13:$M$13) -> 1842.877 | X55: =SUMPRODUCT($F55:$M55,$F$14:$M$14) -> 202.71647
A56: M41 | B56: MP-78 | C56: Oblea de fabricación (PBA) | D56: u | E56: PBA | F56: 1 | G56: 1 | H56: 1 | I56: 1 | N56: =SUMPRODUCT($F56:$M56,$F$4:$M$4)*(1-DEMANDA!D$5) -> 5593.4428 | O56: =SUMPRODUCT($F56:$M56,$F$5:$M$5)*(1-DEMANDA!E$5) -> 9490.1192 | P56: =SUMPRODUCT($F56:$M56,$F$6:$M$6)*(1-DEMANDA!F$5) -> 11734.391 | Q56: =SUMPRODUCT($F56:$M56,$F$7:$M$7)*(1-DEMANDA!G$5) -> 15912.462 | R56: =SUMPRODUCT($F56:$M56,$F$8:$M$8)*(1-DEMANDA!H$5) -> 23073.353 | S56: =SUMPRODUCT($F56:$M56,$F$9:$M$9)*(1-DEMANDA!I$5) -> 29497.189 | T56: =SUMPRODUCT($F56:$M56,$F$10:$M$10)*(1-DEMANDA!J$5) -> 36921.911 | U56: =SUMPRODUCT($F56:$M56,$F$11:$M$11)*(1-DEMANDA!K$5) -> 44118.206 | V56: =SUMPRODUCT($F56:$M56,$F$12:$M$12)*(1-DEMANDA!L$5) -> 49704.474 | W56: =SUMPRODUCT($F56:$M56,$F$13:$M$13)*(1-DEMANDA!M$5) -> 56343.754 | X56: =SUMPRODUCT($F56:$M56,$F$14:$M$14)*(1-DEMANDA!M$5) -> 6442.7789
A57: M42 | B57: MP-79 | C57: Estampilla IRAM de conformidad | D57: u | F57: 1 | G57: 1 | H57: 1 | I57: 1 | N57: =SUMPRODUCT($F57:$M57,$F$4:$M$4) -> 7294.0792 | O57: =SUMPRODUCT($F57:$M57,$F$5:$M$5) -> 12374.081 | P57: =SUMPRODUCT($F57:$M57,$F$6:$M$6) -> 15300.267 | Q57: =SUMPRODUCT($F57:$M57,$F$7:$M$7) -> 20749.753 | R57: =SUMPRODUCT($F57:$M57,$F$8:$M$8) -> 30093.957 | S57: =SUMPRODUCT($F57:$M57,$F$9:$M$9) -> 38486.401 | T57: =SUMPRODUCT($F57:$M57,$F$10:$M$10) -> 48199.706 | U57: =SUMPRODUCT($F57:$M57,$F$11:$M$11) -> 57636.341 | V57: =SUMPRODUCT($F57:$M57,$F$12:$M$12) -> 64996.517 | W57: =SUMPRODUCT($F57:$M57,$F$13:$M$13) -> 73769.145 | X57: =SUMPRODUCT($F57:$M57,$F$14:$M$14) -> 8435.3324
A58: M43 | B58: MP-77 | C58: Tarjeta de identificación AGC (CABA) | D58: u | E58: CABA | G58: 1 | H58: 1 | I58: 1 | N58: =SUMPRODUCT($F58:$M58,$F$4:$M$4)*DEMANDA!D$5 -> 726.35146 | O58: =SUMPRODUCT($F58:$M58,$F$5:$M$5)*DEMANDA!E$5 -> 1486.2021 | P58: =SUMPRODUCT($F58:$M58,$F$6:$M$6)*DEMANDA!F$5 -> 1969.0094 | Q58: =SUMPRODUCT($F58:$M58,$F$7:$M$7)*DEMANDA!G$5 -> 2863.3875 | R58: =SUMPRODUCT($F58:$M58,$F$8:$M$8)*DEMANDA!H$5 -> 4062.3453 | S58: =SUMPRODUCT($F58:$M58,$F$9:$M$9)*DEMANDA!I$5 -> 5340.8125 | T58: =SUMPRODUCT($F58:$M58,$F$10:$M$10)*DEMANDA!J$5 -> 6520.3724 | U58: =SUMPRODUCT($F58:$M58,$F$11:$M$11)*DEMANDA!K$5 -> 7623.6102 | V58: =SUMPRODUCT($F58:$M58,$F$12:$M$12)*DEMANDA!L$5 -> 8569.457 | W58: =SUMPRODUCT($F58:$M58,$F$13:$M$13)*DEMANDA!M$5 -> 9849.3472 | X58: =SUMPRODUCT($F58:$M58,$F$14:$M$14)*DEMANDA!M$5 -> 1083.4282
A59: M44 | B59: MP-80 | C59: Etiqueta de n° de serie GS1 | D59: u | F59: 1 | G59: 1 | H59: 1 | I59: 1 | N59: =SUMPRODUCT($F59:$M59,$F$4:$M$4) -> 7294.0792 | O59: =SUMPRODUCT($F59:$M59,$F$5:$M$5) -> 12374.081 | P59: =SUMPRODUCT($F59:$M59,$F$6:$M$6) -> 15300.267 | Q59: =SUMPRODUCT($F59:$M59,$F$7:$M$7) -> 20749.753 | R59: =SUMPRODUCT($F59:$M59,$F$8:$M$8) -> 30093.957 | S59: =SUMPRODUCT($F59:$M59,$F$9:$M$9) -> 38486.401 | T59: =SUMPRODUCT($F59:$M59,$F$10:$M$10) -> 48199.706 | U59: =SUMPRODUCT($F59:$M59,$F$11:$M$11) -> 57636.341 | V59: =SUMPRODUCT($F59:$M59,$F$12:$M$12) -> 64996.517 | W59: =SUMPRODUCT($F59:$M59,$F$13:$M$13) -> 73769.145 | X59: =SUMPRODUCT($F59:$M59,$F$14:$M$14) -> 8435.3324
A60: M45 | B60: MP-81 | C60: Faja de garantía válvula-cuello | D60: u | F60: 1 | G60: 1 | H60: 1 | I60: 1 | N60: =SUMPRODUCT($F60:$M60,$F$4:$M$4) -> 7294.0792 | O60: =SUMPRODUCT($F60:$M60,$F$5:$M$5) -> 12374.081 | P60: =SUMPRODUCT($F60:$M60,$F$6:$M$6) -> 15300.267 | Q60: =SUMPRODUCT($F60:$M60,$F$7:$M$7) -> 20749.753 | R60: =SUMPRODUCT($F60:$M60,$F$8:$M$8) -> 30093.957 | S60: =SUMPRODUCT($F60:$M60,$F$9:$M$9) -> 38486.401 | T60: =SUMPRODUCT($F60:$M60,$F$10:$M$10) -> 48199.706 | U60: =SUMPRODUCT($F60:$M60,$F$11:$M$11) -> 57636.341 | V60: =SUMPRODUCT($F60:$M60,$F$12:$M$12) -> 64996.517 | W60: =SUMPRODUCT($F60:$M60,$F$13:$M$13) -> 73769.145 | X60: =SUMPRODUCT($F60:$M60,$F$14:$M$14) -> 8435.3324
A61: M46 | B61: MP-51 | C61: Precinto de fábrica | D61: u | F61: 1 | G61: 1 | H61: 1 | I61: 1 | N61: =SUMPRODUCT($F61:$M61,$F$4:$M$4) -> 7294.0792 | O61: =SUMPRODUCT($F61:$M61,$F$5:$M$5) -> 12374.081 | P61: =SUMPRODUCT($F61:$M61,$F$6:$M$6) -> 15300.267 | Q61: =SUMPRODUCT($F61:$M61,$F$7:$M$7) -> 20749.753 | R61: =SUMPRODUCT($F61:$M61,$F$8:$M$8) -> 30093.957 | S61: =SUMPRODUCT($F61:$M61,$F$9:$M$9) -> 38486.401 | T61: =SUMPRODUCT($F61:$M61,$F$10:$M$10) -> 48199.706 | U61: =SUMPRODUCT($F61:$M61,$F$11:$M$11) -> 57636.341 | V61: =SUMPRODUCT($F61:$M61,$F$12:$M$12) -> 64996.517 | W61: =SUMPRODUCT($F61:$M61,$F$13:$M$13) -> 73769.145 | X61: =SUMPRODUCT($F61:$M61,$F$14:$M$14) -> 8435.3324
A62: M47 | B62: MP-88 | C62: Etiqueta del cilindro suelto | D62: u | J62: 1 | K62: 1 | L62: 1 | M62: 1 | N62: =SUMPRODUCT($F62:$M62,$F$4:$M$4) -> 0 | O62: =SUMPRODUCT($F62:$M62,$F$5:$M$5) -> 0 | P62: =SUMPRODUCT($F62:$M62,$F$6:$M$6) -> 9531.2 | Q62: =SUMPRODUCT($F62:$M62,$F$7:$M$7) -> 33205.6 | R62: =SUMPRODUCT($F62:$M62,$F$8:$M$8) -> 61492 | S62: =SUMPRODUCT($F62:$M62,$F$9:$M$9) -> 89163.2 | T62: =SUMPRODUCT($F62:$M62,$F$10:$M$10) -> 126057.6 | U62: =SUMPRODUCT($F62:$M62,$F$11:$M$11) -> 162952 | V62: =SUMPRODUCT($F62:$M62,$F$12:$M$12) -> 182628.4 | W62: =SUMPRODUCT($F62:$M62,$F$13:$M$13) -> 212143 | X62: =SUMPRODUCT($F62:$M62,$F$14:$M$14) -> 25041.21
A63: M48 | B63: MP-62/M22 | C63: Tapón protector de rosca M22 | D63: u | J63: 1 | N63: =SUMPRODUCT($F63:$M63,$F$4:$M$4) -> 0 | O63: =SUMPRODUCT($F63:$M63,$F$5:$M$5) -> 0 | P63: =SUMPRODUCT($F63:$M63,$F$6:$M$6) -> 7662.4 | Q63: =SUMPRODUCT($F63:$M63,$F$7:$M$7) -> 26694.8 | R63: =SUMPRODUCT($F63:$M63,$F$8:$M$8) -> 49434.8 | S63: =SUMPRODUCT($F63:$M63,$F$9:$M$9) -> 71680.2 | T63: =SUMPRODUCT($F63:$M63,$F$10:$M$10) -> 101340.6 | U63: =SUMPRODUCT($F63:$M63,$F$11:$M$11) -> 131001 | V63: =SUMPRODUCT($F63:$M63,$F$12:$M$12) -> 146819.8 | W63: =SUMPRODUCT($F63:$M63,$F$13:$M$13) -> 170548 | X63: =SUMPRODUCT($F63:$M63,$F$14:$M$14) -> 20465.76
A64: M49 | B64: MP-62/M30 | C64: Tapón protector de rosca M30 | D64: u | K64: 1 | L64: 1 | M64: 1 | N64: =SUMPRODUCT($F64:$M64,$F$4:$M$4) -> 0 | O64: =SUMPRODUCT($F64:$M64,$F$5:$M$5) -> 0 | P64: =SUMPRODUCT($F64:$M64,$F$6:$M$6) -> 1868.8 | Q64: =SUMPRODUCT($F64:$M64,$F$7:$M$7) -> 6510.8 | R64: =SUMPRODUCT($F64:$M64,$F$8:$M$8) -> 12057.2 | S64: =SUMPRODUCT($F64:$M64,$F$9:$M$9) -> 17483 | T64: =SUMPRODUCT($F64:$M64,$F$10:$M$10) -> 24717 | U64: =SUMPRODUCT($F64:$M64,$F$11:$M$11) -> 31951 | V64: =SUMPRODUCT($F64:$M64,$F$12:$M$12) -> 35808.6 | W64: =SUMPRODUCT($F64:$M64,$F$13:$M$13) -> 41595 | X64: =SUMPRODUCT($F64:$M64,$F$14:$M$14) -> 4575.45
A65: M50 | B65: MP-85 | C65: Impresos (protocolo de ensayo, remito de préstamo) | D65: u | J65: 1 | K65: 1 | L65: 1 | M65: 1 | N65: =SUMPRODUCT($F65:$M65,$F$4:$M$4) -> 0 | O65: =SUMPRODUCT($F65:$M65,$F$5:$M$5) -> 0 | P65: =SUMPRODUCT($F65:$M65,$F$6:$M$6) -> 9531.2 | Q65: =SUMPRODUCT($F65:$M65,$F$7:$M$7) -> 33205.6 | R65: =SUMPRODUCT($F65:$M65,$F$8:$M$8) -> 61492 | S65: =SUMPRODUCT($F65:$M65,$F$9:$M$9) -> 89163.2 | T65: =SUMPRODUCT($F65:$M65,$F$10:$M$10) -> 126057.6 | U65: =SUMPRODUCT($F65:$M65,$F$11:$M$11) -> 162952 | V65: =SUMPRODUCT($F65:$M65,$F$12:$M$12) -> 182628.4 | W65: =SUMPRODUCT($F65:$M65,$F$13:$M$13) -> 212143 | X65: =SUMPRODUCT($F65:$M65,$F$14:$M$14) -> 25041.21
A66: M51 | B66: MP-59/ABC1 | C66: Caja de cartón simple ABC 1 kg | D66: u | F66: 1 | J66: 1 | N66: =SUMPRODUCT($F66:$M66,$F$4:$M$4) -> 4178.7365 | O66: =SUMPRODUCT($F66:$M66,$F$5:$M$5) -> 5997.304 | P66: =SUMPRODUCT($F66:$M66,$F$6:$M$6) -> 14514.148 | Q66: =SUMPRODUCT($F66:$M66,$F$7:$M$7) -> 35161.936 | R66: =SUMPRODUCT($F66:$M66,$F$8:$M$8) -> 62115.433 | S66: =SUMPRODUCT($F66:$M66,$F$9:$M$9) -> 87300.453 | T66: =SUMPRODUCT($F66:$M66,$F$10:$M$10) -> 121673.15 | U66: =SUMPRODUCT($F66:$M66,$F$11:$M$11) -> 156133.08 | V66: =SUMPRODUCT($F66:$M66,$F$12:$M$12) -> 175393.14 | W66: =SUMPRODUCT($F66:$M66,$F$13:$M$13) -> 202620.64 | X66: =SUMPRODUCT($F66:$M66,$F$14:$M$14) -> 24314.477
A67: M52 | B67: MP-59/ABC2.5 | C67: Caja de cartón simple ABC 2,5 kg | D67: u | G67: 1 | K67: 1 | N67: =SUMPRODUCT($F67:$M67,$F$4:$M$4) -> 295.03036 | O67: =SUMPRODUCT($F67:$M67,$F$5:$M$5) -> 709.72745 | P67: =SUMPRODUCT($F67:$M67,$F$6:$M$6) -> 1286.4681 | Q67: =SUMPRODUCT($F67:$M67,$F$7:$M$7) -> 2544.4382 | R67: =SUMPRODUCT($F67:$M67,$F$8:$M$8) -> 4245.6277 | S67: =SUMPRODUCT($F67:$M67,$F$9:$M$9) -> 6055.8699 | T67: =SUMPRODUCT($F67:$M67,$F$10:$M$10) -> 8065.3155 | U67: =SUMPRODUCT($F67:$M67,$F$11:$M$11) -> 10227.307 | V67: =SUMPRODUCT($F67:$M67,$F$12:$M$12) -> 11936.586 | W67: =SUMPRODUCT($F67:$M67,$F$13:$M$13) -> 14093.858 | X67: =SUMPRODUCT($F67:$M67,$F$14:$M$14) -> 1550.3244
A68: M53 | B68: MP-59/ABC5 | C68: Caja de cartón simple ABC 5 kg | D68: u | H68: 1 | L68: 1 | N68: =SUMPRODUCT($F68:$M68,$F$4:$M$4) -> 2727.9036 | O68: =SUMPRODUCT($F68:$M68,$F$5:$M$5) -> 5488.9106 | P68: =SUMPRODUCT($F68:$M68,$F$6:$M$6) -> 8685.3855 | Q68: =SUMPRODUCT($F68:$M68,$F$7:$M$7) -> 15572.908 | R68: =SUMPRODUCT($F68:$M68,$F$8:$M$8) -> 24035.871 | S68: =SUMPRODUCT($F68:$M68,$F$9:$M$9) -> 32571.261 | T68: =SUMPRODUCT($F68:$M68,$F$10:$M$10) -> 42193.082 | U68: =SUMPRODUCT($F68:$M68,$F$11:$M$11) -> 51285.338 | V68: =SUMPRODUCT($F68:$M68,$F$12:$M$12) -> 56949.2 | W68: =SUMPRODUCT($F68:$M68,$F$13:$M$13) -> 65343.771 | X68: =SUMPRODUCT($F68:$M68,$F$14:$M$14) -> 7187.8148
A69: M54 | B69: MP-59/ABC10 | C69: Caja de cartón doble ABC 10 kg | D69: u | I69: 1 | M69: 1 | N69: =SUMPRODUCT($F69:$M69,$F$4:$M$4) -> 92.408754 | O69: =SUMPRODUCT($F69:$M69,$F$5:$M$5) -> 178.13943 | P69: =SUMPRODUCT($F69:$M69,$F$6:$M$6) -> 345.46523 | Q69: =SUMPRODUCT($F69:$M69,$F$7:$M$7) -> 676.07103 | R69: =SUMPRODUCT($F69:$M69,$F$8:$M$8) -> 1189.0248 | S69: =SUMPRODUCT($F69:$M69,$F$9:$M$9) -> 1722.0168 | T69: =SUMPRODUCT($F69:$M69,$F$10:$M$10) -> 2325.755 | U69: =SUMPRODUCT($F69:$M69,$F$11:$M$11) -> 2942.6176 | V69: =SUMPRODUCT($F69:$M69,$F$12:$M$12) -> 3345.9948 | W69: =SUMPRODUCT($F69:$M69,$F$13:$M$13) -> 3853.877 | X69: =SUMPRODUCT($F69:$M69,$F$14:$M$14) -> 423.92647
A70: M55 | B70: MP-89 | C70: Etiqueta de caja | D70: u | F70: 1 | G70: 1 | H70: 1 | I70: 1 | J70: 1 | K70: 1 | L70: 1 | M70: 1 | N70: =SUMPRODUCT($F70:$M70,$F$4:$M$4) -> 7294.0792 | O70: =SUMPRODUCT($F70:$M70,$F$5:$M$5) -> 12374.081 | P70: =SUMPRODUCT($F70:$M70,$F$6:$M$6) -> 24831.467 | Q70: =SUMPRODUCT($F70:$M70,$F$7:$M$7) -> 53955.353 | R70: =SUMPRODUCT($F70:$M70,$F$8:$M$8) -> 91585.957 | S70: =SUMPRODUCT($F70:$M70,$F$9:$M$9) -> 127649.6 | T70: =SUMPRODUCT($F70:$M70,$F$10:$M$10) -> 174257.31 | U70: =SUMPRODUCT($F70:$M70,$F$11:$M$11) -> 220588.34 | V70: =SUMPRODUCT($F70:$M70,$F$12:$M$12) -> 247624.92 | W70: =SUMPRODUCT($F70:$M70,$F$13:$M$13) -> 285912.15 | X70: =SUMPRODUCT($F70:$M70,$F$14:$M$14) -> 33476.542
A71: M56 | B71: MP-60 | C71: Pallet de madera 1200 × 1000 | D71: u | F71: =1/400 -> 0.0025 | G71: =1/167 -> 0.005988024 | H71: =1/90 -> 0.011111111 | I71: =1/40 -> 0.025 | J71: =1/400 -> 0.0025 | K71: =1/167 -> 0.005988024 | L71: =1/90 -> 0.011111111 | M71: =1/40 -> 0.025 | N71: =SUMPRODUCT($F71:$M71,$F$4:$M$4) -> 44.833749 | O71: =SUMPRODUCT($F71:$M71,$F$5:$M$5) -> 84.684507 | P71: =SUMPRODUCT($F71:$M71,$F$6:$M$6) -> 149.12969 | Q71: =SUMPRODUCT($F71:$M71,$F$7:$M$7) -> 293.07508 | R71: =SUMPRODUCT($F71:$M71,$F$8:$M$8) -> 477.50236 | S71: =SUMPRODUCT($F71:$M71,$F$9:$M$9) -> 659.46714 | T71: =SUMPRODUCT($F71:$M71,$F$10:$M$10) -> 879.43408 | U71: =SUMPRODUCT($F71:$M71,$F$11:$M$11) -> 1094.9766 | V71: =SUMPRODUCT($F71:$M71,$F$12:$M$12) -> 1226.3782 | W71: =SUMPRODUCT($F71:$M71,$F$13:$M$13) -> 1413.3348 | X71: =SUMPRODUCT($F71:$M71,$F$14:$M$14) -> 160.53234
A72: M57 | B72: MP-90 | C72: Etiqueta de pallet | D72: u | F72: =1/400 -> 0.0025 | G72: =1/167 -> 0.005988024 | H72: =1/90 -> 0.011111111 | I72: =1/40 -> 0.025 | J72: =1/400 -> 0.0025 | K72: =1/167 -> 0.005988024 | L72: =1/90 -> 0.011111111 | M72: =1/40 -> 0.025 | N72: =SUMPRODUCT($F72:$M72,$F$4:$M$4) -> 44.833749 | O72: =SUMPRODUCT($F72:$M72,$F$5:$M$5) -> 84.684507 | P72: =SUMPRODUCT($F72:$M72,$F$6:$M$6) -> 149.12969 | Q72: =SUMPRODUCT($F72:$M72,$F$7:$M$7) -> 293.07508 | R72: =SUMPRODUCT($F72:$M72,$F$8:$M$8) -> 477.50236 | S72: =SUMPRODUCT($F72:$M72,$F$9:$M$9) -> 659.46714 | T72: =SUMPRODUCT($F72:$M72,$F$10:$M$10) -> 879.43408 | U72: =SUMPRODUCT($F72:$M72,$F$11:$M$11) -> 1094.9766 | V72: =SUMPRODUCT($F72:$M72,$F$12:$M$12) -> 1226.3782 | W72: =SUMPRODUCT($F72:$M72,$F$13:$M$13) -> 1413.3348 | X72: =SUMPRODUCT($F72:$M72,$F$14:$M$14) -> 160.53234

Sheet RODANTES
A1: RODANTES: consumo por unidad de producto y lo que hay que comprar
A3: Ref. | B3: Código | C3: Material | D3: UM | E3: Destino | F3: ABC 25 kg | G3: ABC 50 kg | H3: ABC 70 kg | I3: ABC 100 kg | J3: Cilindro ABC 25 kg | K3: Cilindro ABC 50 kg | L3: Cilindro ABC 70 kg | M3: Cilindro ABC 100 kg | N3: 2026 | O3: 2027 | P3: 2028 | Q3: 2029 | R3: 2030 | S3: 2031 | T3: 2032 | U3: 2033 | V3: 2034 | W3: 2035 | X3: Mes pico 2035
C4: Demanda 2026 | F4: =DEMANDA!D16 -> 34.051791 | G4: =DEMANDA!D17 -> 75.201727 | H4: =DEMANDA!D18 -> 16.34486 | I4: =DEMANDA!D19 -> 11.18436 | J4: =DEMANDA!D20 -> 0 | K4: =DEMANDA!D21 -> 0 | L4: =DEMANDA!D22 -> 0 | M4: =DEMANDA!D23 -> 0
C5: Demanda 2027 | F5: =DEMANDA!E16 -> 58.462147 | G5: =DEMANDA!E17 -> 129.20669 | H5: =DEMANDA!E18 -> 28.061831 | I5: =DEMANDA!E19 -> 18.722277 | J5: =DEMANDA!E20 -> 0 | K5: =DEMANDA!E21 -> 0 | L5: =DEMANDA!E22 -> 0 | M5: =DEMANDA!E23 -> 0
C6: Demanda 2028 | F6: =DEMANDA!F16 -> 75.20854 | G6: =DEMANDA!F17 -> 166.6531 | H6: =DEMANDA!F18 -> 36.100099 | I6: =DEMANDA!F19 -> 24.368909 | J6: =DEMANDA!F20 -> 14.4 | K6: =DEMANDA!F21 -> 31.8 | L6: =DEMANDA!F22 -> 7 | M6: =DEMANDA!F23 -> 4.6
C7: Demanda 2029 | F7: =DEMANDA!G16 -> 100.52985 | G7: =DEMANDA!G17 -> 222.70533 | H7: =DEMANDA!G18 -> 48.254329 | I7: =DEMANDA!G19 -> 32.486118 | J7: =DEMANDA!G20 -> 50.2 | K7: =DEMANDA!G21 -> 110.8 | L7: =DEMANDA!G22 -> 24.4 | M7: =DEMANDA!G23 -> 16
C8: Demanda 2030 | F8: =DEMANDA!H16 -> 155.876 | G8: =DEMANDA!H17 -> 344.53881 | H8: =DEMANDA!H18 -> 74.820482 | I8: =DEMANDA!H19 -> 50.499062 | J8: =DEMANDA!H20 -> 93 | K8: =DEMANDA!H21 -> 205.2 | L8: =DEMANDA!H22 -> 45.2 | M8: =DEMANDA!H23 -> 29.6
C9: Demanda 2031 | F9: =DEMANDA!I16 -> 211.93448 | G9: =DEMANDA!I17 -> 468.2272 | H9: =DEMANDA!I18 -> 101.72855 | I9: =DEMANDA!I19 -> 68.178767 | J9: =DEMANDA!I20 -> 135 | K9: =DEMANDA!I21 -> 297.6 | L9: =DEMANDA!I22 -> 65.4 | M9: =DEMANDA!I23 -> 42.8
C10: Demanda 2032 | F10: =DEMANDA!J16 -> 272.66823 | G10: =DEMANDA!J17 -> 601.64 | H10: =DEMANDA!J18 -> 130.88075 | I10: =DEMANDA!J19 -> 87.627957 | J10: =DEMANDA!J20 -> 191 | K10: =DEMANDA!J21 -> 420.8 | L10: =DEMANDA!J22 -> 92.2 | M10: =DEMANDA!J23 -> 60.4
C11: Demanda 2033 | F11: =DEMANDA!K16 -> 337.84867 | G11: =DEMANDA!K17 -> 744.53334 | H11: =DEMANDA!K18 -> 162.16736 | I11: =DEMANDA!K19 -> 108.50009 | J11: =DEMANDA!K20 -> 247 | K11: =DEMANDA!K21 -> 544 | L11: =DEMANDA!K22 -> 119 | M11: =DEMANDA!K23 -> 78
C12: Demanda 2034 | F12: =DEMANDA!L16 -> 393.62742 | G12: =DEMANDA!L17 -> 867.28974 | H12: =DEMANDA!L18 -> 188.94116 | I12: =DEMANDA!L19 -> 126.36367 | J12: =DEMANDA!L20 -> 277 | K12: =DEMANDA!L21 -> 609.6 | L12: =DEMANDA!L22 -> 133.4 | M12: =DEMANDA!L23 -> 87.6
C13: Demanda 2035 | F13: =DEMANDA!M16 -> 453.27053 | G13: =DEMANDA!M17 -> 998.25998 | H13: =DEMANDA!M18 -> 217.56986 | I13: =DEMANDA!M19 -> 145.17607 | J13: =DEMANDA!M20 -> 322 | K13: =DEMANDA!M21 -> 708 | L13: =DEMANDA!M22 -> 155 | M13: =DEMANDA!M23 -> 102
C14: Producción del mes pico de cada producto, 2035 | F14: =ESTACIONALIDAD!P19 -> 40.794348 | G14: =ESTACIONALIDAD!P20 -> 89.843398 | H14: =ESTACIONALIDAD!P21 -> 19.581287 | I14: =ESTACIONALIDAD!P22 -> 13.065847 | J14: =ESTACIONALIDAD!P23 -> 28.98 | K14: =ESTACIONALIDAD!P24 -> 63.72 | L14: =ESTACIONALIDAD!P25 -> 13.95 | M14: =ESTACIONALIDAD!P26 -> 9.18
C15: CONSUMO POR UNIDAD (cantidad del material por cada producto)
A16: R01 | B16: MP-11 | C16: Hoja LAC 3,2 × 1500 × 3000 mm | D16: hoja | F16: =1/9 -> 0.11111111 | G16: =1/6 -> 0.16666667 | J16: =1/9 -> 0.11111111 | K16: =1/6 -> 0.16666667 | N16: =SUMPRODUCT($F16:$M16,$F$4:$M$4) -> 16.317154 | O16: =SUMPRODUCT($F16:$M16,$F$5:$M$5) -> 28.030242 | P16: =SUMPRODUCT($F16:$M16,$F$6:$M$6) -> 43.032021 | Q16: =SUMPRODUCT($F16:$M16,$F$7:$M$7) -> 72.331984 | R16: =SUMPRODUCT($F16:$M16,$F$8:$M$8) -> 119.27602 | S16: =SUMPRODUCT($F16:$M16,$F$9:$M$9) -> 166.18614 | T16: =SUMPRODUCT($F16:$M16,$F$10:$M$10) -> 221.92536 | U16: =SUMPRODUCT($F16:$M16,$F$11:$M$11) -> 279.73874 | V16: =SUMPRODUCT($F16:$M16,$F$12:$M$12) -> 320.66245 | W16: =SUMPRODUCT($F16:$M16,$F$13:$M$13) -> 370.51783 | X16: =SUMPRODUCT($F16:$M16,$F$14:$M$14) -> 33.346605
A17: R02 | B17: MP-12 | C17: Hoja LAC 4,75 × 1500 × 3000 mm | D17: hoja | H17: =2/9 -> 0.22222222 | I17: =1/3 -> 0.33333333 | L17: =2/9 -> 0.22222222 | M17: =1/3 -> 0.33333333 | N17: =SUMPRODUCT($F17:$M17,$F$4:$M$4) -> 7.360311 | O17: =SUMPRODUCT($F17:$M17,$F$5:$M$5) -> 12.476721 | P17: =SUMPRODUCT($F17:$M17,$F$6:$M$6) -> 19.234103 | Q17: =SUMPRODUCT($F17:$M17,$F$7:$M$7) -> 32.307446 | R17: =SUMPRODUCT($F17:$M17,$F$8:$M$8) -> 53.370905 | S17: =SUMPRODUCT($F17:$M17,$F$9:$M$9) -> 74.132601 | T17: =SUMPRODUCT($F17:$M17,$F$10:$M$10) -> 98.916153 | U17: =SUMPRODUCT($F17:$M17,$F$11:$M$11) -> 124.64833 | V17: =SUMPRODUCT($F17:$M17,$F$12:$M$12) -> 142.95259 | W17: =SUMPRODUCT($F17:$M17,$F$13:$M$13) -> 165.18533 | X17: =SUMPRODUCT($F17:$M17,$F$14:$M$14) -> 14.866679
A18: R03 | B18: MP-15 | C18: Casquete 10" × 3,2 mm (carro 25 kg) | D18: u | F18: 2 | J18: 2 | N18: =SUMPRODUCT($F18:$M18,$F$4:$M$4) -> 68.103583 | O18: =SUMPRODUCT($F18:$M18,$F$5:$M$5) -> 116.92429 | P18: =SUMPRODUCT($F18:$M18,$F$6:$M$6) -> 179.21708 | Q18: =SUMPRODUCT($F18:$M18,$F$7:$M$7) -> 301.45971 | R18: =SUMPRODUCT($F18:$M18,$F$8:$M$8) -> 497.75201 | S18: =SUMPRODUCT($F18:$M18,$F$9:$M$9) -> 693.86897 | T18: =SUMPRODUCT($F18:$M18,$F$10:$M$10) -> 927.33647 | U18: =SUMPRODUCT($F18:$M18,$F$11:$M$11) -> 1169.6973 | V18: =SUMPRODUCT($F18:$M18,$F$12:$M$12) -> 1341.2548 | W18: =SUMPRODUCT($F18:$M18,$F$13:$M$13) -> 1550.5411 | X18: =SUMPRODUCT($F18:$M18,$F$14:$M$14) -> 139.5487
A19: R04 | B19: MP-16 | C19: Casquete 12" × 3,2 mm (carro 50 kg) | D19: u | G19: 2 | K19: 2 | N19: =SUMPRODUCT($F19:$M19,$F$4:$M$4) -> 150.40345 | O19: =SUMPRODUCT($F19:$M19,$F$5:$M$5) -> 258.41337 | P19: =SUMPRODUCT($F19:$M19,$F$6:$M$6) -> 396.9062 | Q19: =SUMPRODUCT($F19:$M19,$F$7:$M$7) -> 667.01067 | R19: =SUMPRODUCT($F19:$M19,$F$8:$M$8) -> 1099.4776 | S19: =SUMPRODUCT($F19:$M19,$F$9:$M$9) -> 1531.6544 | T19: =SUMPRODUCT($F19:$M19,$F$10:$M$10) -> 2044.88 | U19: =SUMPRODUCT($F19:$M19,$F$11:$M$11) -> 2577.0667 | V19: =SUMPRODUCT($F19:$M19,$F$12:$M$12) -> 2953.7795 | W19: =SUMPRODUCT($F19:$M19,$F$13:$M$13) -> 3412.52 | X19: =SUMPRODUCT($F19:$M19,$F$14:$M$14) -> 307.1268
A20: R05 | B20: MP-17 | C20: Casquete 15" × 4,75 mm (carros 70 y 100 kg) | D20: u | H20: 2 | I20: 2 | L20: 2 | M20: 2 | N20: =SUMPRODUCT($F20:$M20,$F$4:$M$4) -> 55.058439 | O20: =SUMPRODUCT($F20:$M20,$F$5:$M$5) -> 93.568215 | P20: =SUMPRODUCT($F20:$M20,$F$6:$M$6) -> 144.13802 | Q20: =SUMPRODUCT($F20:$M20,$F$7:$M$7) -> 242.28089 | R20: =SUMPRODUCT($F20:$M20,$F$8:$M$8) -> 400.23909 | S20: =SUMPRODUCT($F20:$M20,$F$9:$M$9) -> 556.21464 | T20: =SUMPRODUCT($F20:$M20,$F$10:$M$10) -> 742.21742 | U20: =SUMPRODUCT($F20:$M20,$F$11:$M$11) -> 935.3349 | V20: =SUMPRODUCT($F20:$M20,$F$12:$M$12) -> 1072.6097 | W20: =SUMPRODUCT($F20:$M20,$F$13:$M$13) -> 1239.4919 | X20: =SUMPRODUCT($F20:$M20,$F$14:$M$14) -> 111.55427
A21: R06 | B21: MP-20 | C21: Cupla M30 × 1,5 (carros 25 y 50 kg) | D21: u | F21: 1 | G21: 1 | J21: 1 | K21: 1 | N21: =SUMPRODUCT($F21:$M21,$F$4:$M$4) -> 109.25352 | O21: =SUMPRODUCT($F21:$M21,$F$5:$M$5) -> 187.66883 | P21: =SUMPRODUCT($F21:$M21,$F$6:$M$6) -> 288.06164 | Q21: =SUMPRODUCT($F21:$M21,$F$7:$M$7) -> 484.23519 | R21: =SUMPRODUCT($F21:$M21,$F$8:$M$8) -> 798.61482 | S21: =SUMPRODUCT($F21:$M21,$F$9:$M$9) -> 1112.7617 | T21: =SUMPRODUCT($F21:$M21,$F$10:$M$10) -> 1486.1082 | U21: =SUMPRODUCT($F21:$M21,$F$11:$M$11) -> 1873.382 | V21: =SUMPRODUCT($F21:$M21,$F$12:$M$12) -> 2147.5172 | W21: =SUMPRODUCT($F21:$M21,$F$13:$M$13) -> 2481.5305 | X21: =SUMPRODUCT($F21:$M21,$F$14:$M$14) -> 223.33775
A22: R07 | B22: MP-21 | C22: Cupla 2½" BSP (carros 70 y 100 kg) | D22: u | H22: 1 | I22: 1 | L22: 1 | M22: 1 | N22: =SUMPRODUCT($F22:$M22,$F$4:$M$4) -> 27.52922 | O22: =SUMPRODUCT($F22:$M22,$F$5:$M$5) -> 46.784107 | P22: =SUMPRODUCT($F22:$M22,$F$6:$M$6) -> 72.069008 | Q22: =SUMPRODUCT($F22:$M22,$F$7:$M$7) -> 121.14045 | R22: =SUMPRODUCT($F22:$M22,$F$8:$M$8) -> 200.11954 | S22: =SUMPRODUCT($F22:$M22,$F$9:$M$9) -> 278.10732 | T22: =SUMPRODUCT($F22:$M22,$F$10:$M$10) -> 371.10871 | U22: =SUMPRODUCT($F22:$M22,$F$11:$M$11) -> 467.66745 | V22: =SUMPRODUCT($F22:$M22,$F$12:$M$12) -> 536.30483 | W22: =SUMPRODUCT($F22:$M22,$F$13:$M$13) -> 619.74593 | X22: =SUMPRODUCT($F22:$M22,$F$14:$M$14) -> 55.777134
A23: R08 | B23: MP-66 | C23: Caño SAE 1010 1" × 2,0 × 6 m (manija; caño del eje 25 kg) | D23: barra | F23: =1440/6000/0.95+354/6000/0.95 -> 0.31473684 | G23: =1520/6000/0.95 -> 0.26666667 | H23: =1590/6000/0.95 -> 0.27894737 | I23: =1590/6000/0.95 -> 0.27894737 | N23: =SUMPRODUCT($F23:$M23,$F$4:$M$4) -> 38.450351 | O23: =SUMPRODUCT($F23:$M23,$F$5:$M$5) -> 65.905612 | P23: =SUMPRODUCT($F23:$M23,$F$6:$M$6) -> 84.979396 | Q23: =SUMPRODUCT($F23:$M23,$F$7:$M$7) -> 113.55087 | R23: =SUMPRODUCT($F23:$M23,$F$8:$M$8) -> 175.89449 | S23: =SUMPRODUCT($F23:$M23,$F$9:$M$9) -> 238.95938 | T23: =SUMPRODUCT($F23:$M23,$F$10:$M$10) -> 307.2085 | U23: =SUMPRODUCT($F23:$M23,$F$11:$M$11) -> 380.37762 | V23: =SUMPRODUCT($F23:$M23,$F$12:$M$12) -> 443.11977 | W23: =SUMPRODUCT($F23:$M23,$F$13:$M$13) -> 510.05062 | X23: =SUMPRODUCT($F23:$M23,$F$14:$M$14) -> 45.904556
A24: R09 | B24: MP-67 | C24: Caño SAE 1010 1¼" × 2,0 × 6 m (caño del eje 50 a 100 kg) | D24: barra | G24: =354/6000/0.95 -> 0.062105263 | H24: =434/6000/0.95 -> 0.076140351 | I24: =434/6000/0.95 -> 0.076140351 | N24: =SUMPRODUCT($F24:$M24,$F$4:$M$4) -> 6.7665075 | O24: =SUMPRODUCT($F24:$M24,$F$5:$M$5) -> 11.586574 | P24: =SUMPRODUCT($F24:$M24,$F$6:$M$6) -> 14.954166 | Q24: =SUMPRODUCT($F24:$M24,$F$7:$M$7) -> 19.978779 | R24: =SUMPRODUCT($F24:$M24,$F$8:$M$8) -> 30.939548 | S24: =SUMPRODUCT($F24:$M24,$F$9:$M$9) -> 42.016176 | T24: =SUMPRODUCT($F24:$M24,$F$10:$M$10) -> 54.00234 | U24: =SUMPRODUCT($F24:$M24,$F$11:$M$11) -> 66.848153 | V24: =SUMPRODUCT($F24:$M24,$F$12:$M$12) -> 77.870678 | W24: =SUMPRODUCT($F24:$M24,$F$13:$M$13) -> 89.616801 | X24: =SUMPRODUCT($F24:$M24,$F$14:$M$14) -> 8.0655121
A25: R10 | B25: MP-68 | C25: Barra trefilada SAE 1045 3/4" × 4 m (eje 25 kg) | D25: barra | F25: =1/INT(4000/490) -> 0.125 | N25: =SUMPRODUCT($F25:$M25,$F$4:$M$4) -> 4.2564739 | O25: =SUMPRODUCT($F25:$M25,$F$5:$M$5) -> 7.3077684 | P25: =SUMPRODUCT($F25:$M25,$F$6:$M$6) -> 9.4010675 | Q25: =SUMPRODUCT($F25:$M25,$F$7:$M$7) -> 12.566232 | R25: =SUMPRODUCT($F25:$M25,$F$8:$M$8) -> 19.4845 | S25: =SUMPRODUCT($F25:$M25,$F$9:$M$9) -> 26.49181 | T25: =SUMPRODUCT($F25:$M25,$F$10:$M$10) -> 34.083529 | U25: =SUMPRODUCT($F25:$M25,$F$11:$M$11) -> 42.231084 | V25: =SUMPRODUCT($F25:$M25,$F$12:$M$12) -> 49.203427 | W25: =SUMPRODUCT($F25:$M25,$F$13:$M$13) -> 56.658817 | X25: =SUMPRODUCT($F25:$M25,$F$14:$M$14) -> 5.0992935
A26: R11 | B26: MP-69 | C26: Barra trefilada SAE 1045 1" × 6 m (eje 50 a 100 kg) | D26: barra | G26: =1/INT(6000/510) -> 0.090909091 | H26: =1/INT(6000/590) -> 0.1 | I26: =1/INT(6000/590) -> 0.1 | N26: =SUMPRODUCT($F26:$M26,$F$4:$M$4) -> 9.5894426 | O26: =SUMPRODUCT($F26:$M26,$F$5:$M$5) -> 16.424473 | P26: =SUMPRODUCT($F26:$M26,$F$6:$M$6) -> 21.197183 | Q26: =SUMPRODUCT($F26:$M26,$F$7:$M$7) -> 28.319984 | R26: =SUMPRODUCT($F26:$M26,$F$8:$M$8) -> 43.853665 | S26: =SUMPRODUCT($F26:$M26,$F$9:$M$9) -> 59.556841 | T26: =SUMPRODUCT($F26:$M26,$F$10:$M$10) -> 76.545416 | U26: =SUMPRODUCT($F26:$M26,$F$11:$M$11) -> 94.751594 | V26: =SUMPRODUCT($F26:$M26,$F$12:$M$12) -> 110.37501 | W26: =SUMPRODUCT($F26:$M26,$F$13:$M$13) -> 127.0255 | X26: =SUMPRODUCT($F26:$M26,$F$14:$M$14) -> 11.432295
A27: R12 | B27: MP-24 | C27: Alambre MAG ER70S-6 Ø1,0 mm (carros) | D27: kg | F27: =(6+48+10.5+190+141)/1000 -> 0.3955 | G27: =(7.2+63+10.5+218+146)/1000 -> 0.4447 | H27: =(16.8+120+29+463+199)/1000 -> 0.8278 | I27: =(18+158+29+463+199)/1000 -> 0.867 | J27: =(6+48+10.5+190)/1000 -> 0.2545 | K27: =(7.2+63+10.5+218)/1000 -> 0.2987 | L27: =(16.8+120+29+463)/1000 -> 0.6288 | M27: =(18+158+29+463)/1000 -> 0.668 | N27: =SUMPRODUCT($F27:$M27,$F$4:$M$4) -> 70.136806 | O27: =SUMPRODUCT($F27:$M27,$F$5:$M$5) -> 120.04179 | P27: =SUMPRODUCT($F27:$M27,$F$6:$M$6) -> 175.50498 | Q27: =SUMPRODUCT($F27:$M27,$F$7:$M$7) -> 278.8096 | R27: =SUMPRODUCT($F27:$M27,$F$8:$M$8) -> 453.74075 | S27: =SUMPRODUCT($F27:$M27,$F$9:$M$9) -> 628.32715 | T27: =SUMPRODUCT($F27:$M27,$F$10:$M$10) -> 832.33114 | U27: =SUMPRODUCT($F27:$M27,$F$11:$M$11) -> 1045.3103 | V27: =SUMPRODUCT($F27:$M27,$F$12:$M$12) -> 1202.3089 | W27: =SUMPRODUCT($F27:$M27,$F$13:$M$13) -> 1388.1953 | X27: =SUMPRODUCT($F27:$M27,$F$14:$M$14) -> 124.93758
A28: R13 | B28: MP-25 | C28: Gas MAG Ar + 8 % CO₂ (Arcal 21) | D28: m³ | F28: =(3.4+18+10+66+96)/1000 -> 0.1934 | G28: =(4.1+22+10+75+98)/1000 -> 0.2091 | H28: =(9.5+32+17+122+109)/1000 -> 0.2895 | I28: =(10.2+42+17+122+109)/1000 -> 0.3002 | J28: =(3.4+18+10+66)/1000 -> 0.0974 | K28: =(4.1+22+10+75)/1000 -> 0.1111 | L28: =(9.5+32+17+122)/1000 -> 0.1805 | M28: =(10.2+42+17+122)/1000 -> 0.1912 | N28: =SUMPRODUCT($F28:$M28,$F$4:$M$4) -> 30.399679 | O28: =SUMPRODUCT($F28:$M28,$F$5:$M$5) -> 52.068025 | P28: =SUMPRODUCT($F28:$M28,$F$6:$M$6) -> 74.23758 | Q28: =SUMPRODUCT($F28:$M28,$F$7:$M$7) -> 114.39488 | R28: =SUMPRODUCT($F28:$M28,$F$8:$M$8) -> 184.68387 | S28: =SUMPRODUCT($F28:$M28,$F$9:$M$9) -> 255.01254 | T28: =SUMPRODUCT($F28:$M28,$F$10:$M$10) -> 336.27771 | U28: =SUMPRODUCT($F28:$M28,$F$11:$M$11) -> 421.43033 | V28: =SUMPRODUCT($F28:$M28,$F$12:$M$12) -> 485.64485 | W28: =SUMPRODUCT($F28:$M28,$F$13:$M$13) -> 560.46851 | X28: =SUMPRODUCT($F28:$M28,$F$14:$M$14) -> 50.442166
A29: R14 | B29: MP-92 | C29: Disco de sensitiva 355 mm | D29: u | F29: =3/200 -> 0.015 | G29: =3/200 -> 0.015 | H29: =3/200 -> 0.015 | I29: =3/200 -> 0.015 | N29: =SUMPRODUCT($F29:$M29,$F$4:$M$4) -> 2.0517411 | O29: =SUMPRODUCT($F29:$M29,$F$5:$M$5) -> 3.5167941 | P29: =SUMPRODUCT($F29:$M29,$F$6:$M$6) -> 4.5349597 | Q29: =SUMPRODUCT($F29:$M29,$F$7:$M$7) -> 6.0596345 | R29: =SUMPRODUCT($F29:$M29,$F$8:$M$8) -> 9.3860154 | S29: =SUMPRODUCT($F29:$M29,$F$9:$M$9) -> 12.751035 | T29: =SUMPRODUCT($F29:$M29,$F$10:$M$10) -> 16.392254 | U29: =SUMPRODUCT($F29:$M29,$F$11:$M$11) -> 20.295742 | V29: =SUMPRODUCT($F29:$M29,$F$12:$M$12) -> 23.64333 | W29: =SUMPRODUCT($F29:$M29,$F$13:$M$13) -> 27.214147 | X29: =SUMPRODUCT($F29:$M29,$F$14:$M$14) -> 2.4492732
A30: R15 | B30: MP-27 | C30: Disco de corte 115 × 1,0 mm | D30: u | F30: =1/40 -> 0.025 | G30: =1/40 -> 0.025 | H30: =1/40+7/80 -> 0.1125 | I30: =1/40+7/80 -> 0.1125 | L30: =7/80 -> 0.0875 | M30: =7/80 -> 0.0875 | N30: =SUMPRODUCT($F30:$M30,$F$4:$M$4) -> 5.8283752 | O30: =SUMPRODUCT($F30:$M30,$F$5:$M$5) -> 9.9549329 | P30: =SUMPRODUCT($F30:$M30,$F$6:$M$6) -> 13.864304 | Q30: =SUMPRODUCT($F30:$M30,$F$7:$M$7) -> 20.69918 | R30: =SUMPRODUCT($F30:$M30,$F$8:$M$8) -> 33.153819 | S30: =SUMPRODUCT($F30:$M30,$F$9:$M$9) -> 45.586115 | T30: =SUMPRODUCT($F30:$M30,$F$10:$M$10) -> 59.792436 | U30: =SUMPRODUCT($F30:$M30,$F$11:$M$11) -> 74.747138 | V30: =SUMPRODUCT($F30:$M30,$F$12:$M$12) -> 86.332223 | W30: =SUMPRODUCT($F30:$M30,$F$13:$M$13) -> 99.58468 | X30: =SUMPRODUCT($F30:$M30,$F$14:$M$14) -> 8.9626212
A31: R16 | B31: MP-93 | C31: Disco flap 115 mm grano 60 | D31: u | F31: =2/400 -> 0.005 | G31: =2/400 -> 0.005 | H31: =2/400+7/4/80 -> 0.026875 | I31: =2/400+7/4/80 -> 0.026875 | L31: =7/4/80 -> 0.021875 | M31: =7/4/80 -> 0.021875 | N31: =SUMPRODUCT($F31:$M31,$F$4:$M$4) -> 1.2861154 | O31: =SUMPRODUCT($F31:$M31,$F$5:$M$5) -> 2.1956671 | P31: =SUMPRODUCT($F31:$M31,$F$6:$M$6) -> 3.0881628 | Q31: =SUMPRODUCT($F31:$M31,$F$7:$M$7) -> 4.6698255 | R31: =SUMPRODUCT($F31:$M31,$F$8:$M$8) -> 7.5062868 | S31: =SUMPRODUCT($F31:$M31,$F$9:$M$9) -> 10.333943 | T31: =SUMPRODUCT($F31:$M31,$F$10:$M$10) -> 13.582088 | U31: =SUMPRODUCT($F31:$M31,$F$11:$M$11) -> 16.995473 | V31: =SUMPRODUCT($F31:$M31,$F$12:$M$12) -> 19.612778 | W31: =SUMPRODUCT($F31:$M31,$F$13:$M$13) -> 22.628324 | X31: =SUMPRODUCT($F31:$M31,$F$14:$M$14) -> 2.0365492
A32: R17 | B32: MP-94 | C32: Mecha de acero rápido 4,5 mm | D32: u | F32: =2/200 -> 0.01 | G32: =2/200 -> 0.01 | H32: =2/200 -> 0.01 | I32: =2/200 -> 0.01 | N32: =SUMPRODUCT($F32:$M32,$F$4:$M$4) -> 1.3678274 | O32: =SUMPRODUCT($F32:$M32,$F$5:$M$5) -> 2.3445294 | P32: =SUMPRODUCT($F32:$M32,$F$6:$M$6) -> 3.0233065 | Q32: =SUMPRODUCT($F32:$M32,$F$7:$M$7) -> 4.0397563 | R32: =SUMPRODUCT($F32:$M32,$F$8:$M$8) -> 6.2573436 | S32: =SUMPRODUCT($F32:$M32,$F$9:$M$9) -> 8.50069 | T32: =SUMPRODUCT($F32:$M32,$F$10:$M$10) -> 10.928169 | U32: =SUMPRODUCT($F32:$M32,$F$11:$M$11) -> 13.530495 | V32: =SUMPRODUCT($F32:$M32,$F$12:$M$12) -> 15.76222 | W32: =SUMPRODUCT($F32:$M32,$F$13:$M$13) -> 18.142764 | X32: =SUMPRODUCT($F32:$M32,$F$14:$M$14) -> 1.6328488
A33: R18 | B33: MP-95 | C33: Spray antiproyecciones 400 ml | D33: u | F33: =1/400 -> 0.0025 | G33: =1/400 -> 0.0025 | H33: =1/400 -> 0.0025 | I33: =1/400 -> 0.0025 | J33: =1/400 -> 0.0025 | K33: =1/400 -> 0.0025 | L33: =1/400 -> 0.0025 | M33: =1/400 -> 0.0025 | N33: =SUMPRODUCT($F33:$M33,$F$4:$M$4) -> 0.34195685 | O33: =SUMPRODUCT($F33:$M33,$F$5:$M$5) -> 0.58613235 | P33: =SUMPRODUCT($F33:$M33,$F$6:$M$6) -> 0.90032662 | Q33: =SUMPRODUCT($F33:$M33,$F$7:$M$7) -> 1.5134391 | R33: =SUMPRODUCT($F33:$M33,$F$8:$M$8) -> 2.4968359 | S33: =SUMPRODUCT($F33:$M33,$F$9:$M$9) -> 3.4771725 | T33: =SUMPRODUCT($F33:$M33,$F$10:$M$10) -> 4.6430424 | U33: =SUMPRODUCT($F33:$M33,$F$11:$M$11) -> 5.8526236 | V33: =SUMPRODUCT($F33:$M33,$F$12:$M$12) -> 6.709555 | W33: =SUMPRODUCT($F33:$M33,$F$13:$M$13) -> 7.7531911 | X33: =SUMPRODUCT($F33:$M33,$F$14:$M$14) -> 0.6977872
A34: R19 | B34: MP-96/ABC25 | C34: Servicio de pintura, carro 25 kg (tercerizado) | D34: u | F34: 1 | J34: 1 | N34: =SUMPRODUCT($F34:$M34,$F$4:$M$4) -> 34.051791 | O34: =SUMPRODUCT($F34:$M34,$F$5:$M$5) -> 58.462147 | P34: =SUMPRODUCT($F34:$M34,$F$6:$M$6) -> 89.60854 | Q34: =SUMPRODUCT($F34:$M34,$F$7:$M$7) -> 150.72985 | R34: =SUMPRODUCT($F34:$M34,$F$8:$M$8) -> 248.876 | S34: =SUMPRODUCT($F34:$M34,$F$9:$M$9) -> 346.93448 | T34: =SUMPRODUCT($F34:$M34,$F$10:$M$10) -> 463.66823 | U34: =SUMPRODUCT($F34:$M34,$F$11:$M$11) -> 584.84867 | V34: =SUMPRODUCT($F34:$M34,$F$12:$M$12) -> 670.62742 | W34: =SUMPRODUCT($F34:$M34,$F$13:$M$13) -> 775.27053 | X34: =SUMPRODUCT($F34:$M34,$F$14:$M$14) -> 69.774348
A35: R20 | B35: MP-96/ABC50 | C35: Servicio de pintura, carro 50 kg (tercerizado) | D35: u | G35: 1 | K35: 1 | N35: =SUMPRODUCT($F35:$M35,$F$4:$M$4) -> 75.201727 | O35: =SUMPRODUCT($F35:$M35,$F$5:$M$5) -> 129.20669 | P35: =SUMPRODUCT($F35:$M35,$F$6:$M$6) -> 198.4531 | Q35: =SUMPRODUCT($F35:$M35,$F$7:$M$7) -> 333.50533 | R35: =SUMPRODUCT($F35:$M35,$F$8:$M$8) -> 549.73881 | S35: =SUMPRODUCT($F35:$M35,$F$9:$M$9) -> 765.8272 | T35: =SUMPRODUCT($F35:$M35,$F$10:$M$10) -> 1022.44 | U35: =SUMPRODUCT($F35:$M35,$F$11:$M$11) -> 1288.5333 | V35: =SUMPRODUCT($F35:$M35,$F$12:$M$12) -> 1476.8897 | W35: =SUMPRODUCT($F35:$M35,$F$13:$M$13) -> 1706.26 | X35: =SUMPRODUCT($F35:$M35,$F$14:$M$14) -> 153.5634
A36: R21 | B36: MP-96/ABC70 | C36: Servicio de pintura, carro 70 kg (tercerizado) | D36: u | H36: 1 | L36: 1 | N36: =SUMPRODUCT($F36:$M36,$F$4:$M$4) -> 16.34486 | O36: =SUMPRODUCT($F36:$M36,$F$5:$M$5) -> 28.061831 | P36: =SUMPRODUCT($F36:$M36,$F$6:$M$6) -> 43.100099 | Q36: =SUMPRODUCT($F36:$M36,$F$7:$M$7) -> 72.654329 | R36: =SUMPRODUCT($F36:$M36,$F$8:$M$8) -> 120.02048 | S36: =SUMPRODUCT($F36:$M36,$F$9:$M$9) -> 167.12855 | T36: =SUMPRODUCT($F36:$M36,$F$10:$M$10) -> 223.08075 | U36: =SUMPRODUCT($F36:$M36,$F$11:$M$11) -> 281.16736 | V36: =SUMPRODUCT($F36:$M36,$F$12:$M$12) -> 322.34116 | W36: =SUMPRODUCT($F36:$M36,$F$13:$M$13) -> 372.56986 | X36: =SUMPRODUCT($F36:$M36,$F$14:$M$14) -> 33.531287
A37: R22 | B37: MP-96/ABC100 | C37: Servicio de pintura, carro 100 kg (tercerizado) | D37: u | I37: 1 | M37: 1 | N37: =SUMPRODUCT($F37:$M37,$F$4:$M$4) -> 11.18436 | O37: =SUMPRODUCT($F37:$M37,$F$5:$M$5) -> 18.722277 | P37: =SUMPRODUCT($F37:$M37,$F$6:$M$6) -> 28.968909 | Q37: =SUMPRODUCT($F37:$M37,$F$7:$M$7) -> 48.486118 | R37: =SUMPRODUCT($F37:$M37,$F$8:$M$8) -> 80.099062 | S37: =SUMPRODUCT($F37:$M37,$F$9:$M$9) -> 110.97877 | T37: =SUMPRODUCT($F37:$M37,$F$10:$M$10) -> 148.02796 | U37: =SUMPRODUCT($F37:$M37,$F$11:$M$11) -> 186.50009 | V37: =SUMPRODUCT($F37:$M37,$F$12:$M$12) -> 213.96367 | W37: =SUMPRODUCT($F37:$M37,$F$13:$M$13) -> 247.17607 | X37: =SUMPRODUCT($F37:$M37,$F$14:$M$14) -> 22.245847
A38: R23 | B38: MP-33B | C38: Polvo ABC 90 (carros y sus recargas) | D38: kg | F38: =25*1.01 -> 25.25 | G38: =50*1.01 -> 50.5 | H38: =70*1.01 -> 70.7 | I38: =100*1.01 -> 101 | N38: =SUMPRODUCT($F38:$M38,$F$4:$M$4) -> 6942.6969 | O38: =SUMPRODUCT($F38:$M38,$F$5:$M$5) -> 11876.028 | P38: =SUMPRODUCT($F38:$M38,$F$6:$M$6) -> 15328.534 | Q38: =SUMPRODUCT($F38:$M38,$F$7:$M$7) -> 20477.677 | R38: =SUMPRODUCT($F38:$M38,$F$8:$M$8) -> 31725.292 | S38: =SUMPRODUCT($F38:$M38,$F$9:$M$9) -> 43075.083 | T38: =SUMPRODUCT($F38:$M38,$F$10:$M$10) -> 55371.386 | U38: =SUMPRODUCT($F38:$M38,$F$11:$M$11) -> 68553.354 | V38: =SUMPRODUCT($F38:$M38,$F$12:$M$12) -> 79858.095 | W38: =SUMPRODUCT($F38:$M38,$F$13:$M$13) -> 91902.182 | X38: =SUMPRODUCT($F38:$M38,$F$14:$M$14) -> 8271.1964
A39: R24 | B39: MP-34 | C39: Nitrógeno seco | D39: m³ | F39: =34.4/3*14/1000 -> 0.16053333 | G39: =61.8/3*14/1000 -> 0.2884 | H39: =96/3*14/1000 -> 0.448 | I39: =121/3*14/1000 -> 0.56466667 | N39: =SUMPRODUCT($F39:$M39,$F$4:$M$4) -> 40.792558 | O39: =SUMPRODUCT($F39:$M39,$F$5:$M$5) -> 69.791877 | P39: =SUMPRODUCT($F39:$M39,$F$6:$M$6) -> 90.069387 | Q39: =SUMPRODUCT($F39:$M39,$F$7:$M$7) -> 120.32838 | R39: =SUMPRODUCT($F39:$M39,$F$8:$M$8) -> 186.423 | S39: =SUMPRODUCT($F39:$M39,$F$9:$M$9) -> 253.13194 | T39: =SUMPRODUCT($F39:$M39,$F$10:$M$10) -> 325.40048 | U39: =SUMPRODUCT($F39:$M39,$F$11:$M$11) -> 402.87675 | V39: =SUMPRODUCT($F39:$M39,$F$12:$M$12) -> 469.31568 | W39: =SUMPRODUCT($F39:$M39,$F$13:$M$13) -> 540.11059 | X39: =SUMPRODUCT($F39:$M39,$F$14:$M$14) -> 48.609953
A40: R25 | B40: MP-70 | C40: Arandela de tope del eje | D40: u | F40: 4 | G40: 4 | H40: 4 | I40: 4 | N40: =SUMPRODUCT($F40:$M40,$F$4:$M$4) -> 547.13095 | O40: =SUMPRODUCT($F40:$M40,$F$5:$M$5) -> 937.81177 | P40: =SUMPRODUCT($F40:$M40,$F$6:$M$6) -> 1209.3226 | Q40: =SUMPRODUCT($F40:$M40,$F$7:$M$7) -> 1615.9025 | R40: =SUMPRODUCT($F40:$M40,$F$8:$M$8) -> 2502.9374 | S40: =SUMPRODUCT($F40:$M40,$F$9:$M$9) -> 3400.276 | T40: =SUMPRODUCT($F40:$M40,$F$10:$M$10) -> 4371.2678 | U40: =SUMPRODUCT($F40:$M40,$F$11:$M$11) -> 5412.1978 | V40: =SUMPRODUCT($F40:$M40,$F$12:$M$12) -> 6304.888 | W40: =SUMPRODUCT($F40:$M40,$F$13:$M$13) -> 7257.1058 | X40: =SUMPRODUCT($F40:$M40,$F$14:$M$14) -> 653.13952
A41: R26 | B41: MP-71 | C41: Pasador partido del eje | D41: u | F41: 2 | G41: 2 | H41: 2 | I41: 2 | N41: =SUMPRODUCT($F41:$M41,$F$4:$M$4) -> 273.56548 | O41: =SUMPRODUCT($F41:$M41,$F$5:$M$5) -> 468.90588 | P41: =SUMPRODUCT($F41:$M41,$F$6:$M$6) -> 604.6613 | Q41: =SUMPRODUCT($F41:$M41,$F$7:$M$7) -> 807.95127 | R41: =SUMPRODUCT($F41:$M41,$F$8:$M$8) -> 1251.4687 | S41: =SUMPRODUCT($F41:$M41,$F$9:$M$9) -> 1700.138 | T41: =SUMPRODUCT($F41:$M41,$F$10:$M$10) -> 2185.6339 | U41: =SUMPRODUCT($F41:$M41,$F$11:$M$11) -> 2706.0989 | V41: =SUMPRODUCT($F41:$M41,$F$12:$M$12) -> 3152.444 | W41: =SUMPRODUCT($F41:$M41,$F$13:$M$13) -> 3628.5529 | X41: =SUMPRODUCT($F41:$M41,$F$14:$M$14) -> 326.56976
A42: R27 | B42: MP-54/300 | C42: Rueda Ø300 × 50, buje 3/4" (carro 25 kg) | D42: u | F42: 2 | N42: =SUMPRODUCT($F42:$M42,$F$4:$M$4) -> 68.103583 | O42: =SUMPRODUCT($F42:$M42,$F$5:$M$5) -> 116.92429 | P42: =SUMPRODUCT($F42:$M42,$F$6:$M$6) -> 150.41708 | Q42: =SUMPRODUCT($F42:$M42,$F$7:$M$7) -> 201.05971 | R42: =SUMPRODUCT($F42:$M42,$F$8:$M$8) -> 311.75201 | S42: =SUMPRODUCT($F42:$M42,$F$9:$M$9) -> 423.86897 | T42: =SUMPRODUCT($F42:$M42,$F$10:$M$10) -> 545.33647 | U42: =SUMPRODUCT($F42:$M42,$F$11:$M$11) -> 675.69734 | V42: =SUMPRODUCT($F42:$M42,$F$12:$M$12) -> 787.25483 | W42: =SUMPRODUCT($F42:$M42,$F$13:$M$13) -> 906.54107 | X42: =SUMPRODUCT($F42:$M42,$F$14:$M$14) -> 81.588696
A43: R28 | B43: MP-54/350 | C43: Rueda Ø350 × 60, buje 1" (carro 50 kg) | D43: u | G43: 2 | N43: =SUMPRODUCT($F43:$M43,$F$4:$M$4) -> 150.40345 | O43: =SUMPRODUCT($F43:$M43,$F$5:$M$5) -> 258.41337 | P43: =SUMPRODUCT($F43:$M43,$F$6:$M$6) -> 333.3062 | Q43: =SUMPRODUCT($F43:$M43,$F$7:$M$7) -> 445.41067 | R43: =SUMPRODUCT($F43:$M43,$F$8:$M$8) -> 689.07762 | S43: =SUMPRODUCT($F43:$M43,$F$9:$M$9) -> 936.4544 | T43: =SUMPRODUCT($F43:$M43,$F$10:$M$10) -> 1203.28 | U43: =SUMPRODUCT($F43:$M43,$F$11:$M$11) -> 1489.0667 | V43: =SUMPRODUCT($F43:$M43,$F$12:$M$12) -> 1734.5795 | W43: =SUMPRODUCT($F43:$M43,$F$13:$M$13) -> 1996.52 | X43: =SUMPRODUCT($F43:$M43,$F$14:$M$14) -> 179.6868
A44: R29 | B44: MP-54/400 | C44: Rueda Ø400 × 60, buje 1" (carros 70 y 100 kg) | D44: u | H44: 2 | I44: 2 | N44: =SUMPRODUCT($F44:$M44,$F$4:$M$4) -> 55.058439 | O44: =SUMPRODUCT($F44:$M44,$F$5:$M$5) -> 93.568215 | P44: =SUMPRODUCT($F44:$M44,$F$6:$M$6) -> 120.93802 | Q44: =SUMPRODUCT($F44:$M44,$F$7:$M$7) -> 161.48089 | R44: =SUMPRODUCT($F44:$M44,$F$8:$M$8) -> 250.63909 | S44: =SUMPRODUCT($F44:$M44,$F$9:$M$9) -> 339.81464 | T44: =SUMPRODUCT($F44:$M44,$F$10:$M$10) -> 437.01742 | U44: =SUMPRODUCT($F44:$M44,$F$11:$M$11) -> 541.3349 | V44: =SUMPRODUCT($F44:$M44,$F$12:$M$12) -> 630.60967 | W44: =SUMPRODUCT($F44:$M44,$F$13:$M$13) -> 725.49186 | X44: =SUMPRODUCT($F44:$M44,$F$14:$M$14) -> 65.294267
A45: R30 | B45: MP-44/25 | C45: Válvula HZ de carro 25 kg, sin tubo pescante | D45: u | F45: 1 | N45: =SUMPRODUCT($F45:$M45,$F$4:$M$4) -> 34.051791 | O45: =SUMPRODUCT($F45:$M45,$F$5:$M$5) -> 58.462147 | P45: =SUMPRODUCT($F45:$M45,$F$6:$M$6) -> 75.20854 | Q45: =SUMPRODUCT($F45:$M45,$F$7:$M$7) -> 100.52985 | R45: =SUMPRODUCT($F45:$M45,$F$8:$M$8) -> 155.876 | S45: =SUMPRODUCT($F45:$M45,$F$9:$M$9) -> 211.93448 | T45: =SUMPRODUCT($F45:$M45,$F$10:$M$10) -> 272.66823 | U45: =SUMPRODUCT($F45:$M45,$F$11:$M$11) -> 337.84867 | V45: =SUMPRODUCT($F45:$M45,$F$12:$M$12) -> 393.62742 | W45: =SUMPRODUCT($F45:$M45,$F$13:$M$13) -> 453.27053 | X45: =SUMPRODUCT($F45:$M45,$F$14:$M$14) -> 40.794348
A46: R31 | B46: MP-44/50 | C46: Válvula HZ de carro 50-70-100 kg, sin tubo pescante | D46: u | G46: 1 | H46: 1 | I46: 1 | N46: =SUMPRODUCT($F46:$M46,$F$4:$M$4) -> 102.73095 | O46: =SUMPRODUCT($F46:$M46,$F$5:$M$5) -> 175.99079 | P46: =SUMPRODUCT($F46:$M46,$F$6:$M$6) -> 227.12211 | Q46: =SUMPRODUCT($F46:$M46,$F$7:$M$7) -> 303.44578 | R46: =SUMPRODUCT($F46:$M46,$F$8:$M$8) -> 469.85836 | S46: =SUMPRODUCT($F46:$M46,$F$9:$M$9) -> 638.13452 | T46: =SUMPRODUCT($F46:$M46,$F$10:$M$10) -> 820.14871 | U46: =SUMPRODUCT($F46:$M46,$F$11:$M$11) -> 1015.2008 | V46: =SUMPRODUCT($F46:$M46,$F$12:$M$12) -> 1182.5946 | W46: =SUMPRODUCT($F46:$M46,$F$13:$M$13) -> 1361.0059 | X46: =SUMPRODUCT($F46:$M46,$F$14:$M$14) -> 122.49053
A47: R32 | B47: MP-45 | C47: Manómetro 1,4 MPa | D47: u | F47: 1 | G47: 1 | H47: 1 | I47: 1 | N47: =SUMPRODUCT($F47:$M47,$F$4:$M$4) -> 136.78274 | O47: =SUMPRODUCT($F47:$M47,$F$5:$M$5) -> 234.45294 | P47: =SUMPRODUCT($F47:$M47,$F$6:$M$6) -> 302.33065 | Q47: =SUMPRODUCT($F47:$M47,$F$7:$M$7) -> 403.97563 | R47: =SUMPRODUCT($F47:$M47,$F$8:$M$8) -> 625.73436 | S47: =SUMPRODUCT($F47:$M47,$F$9:$M$9) -> 850.069 | T47: =SUMPRODUCT($F47:$M47,$F$10:$M$10) -> 1092.8169 | U47: =SUMPRODUCT($F47:$M47,$F$11:$M$11) -> 1353.0495 | V47: =SUMPRODUCT($F47:$M47,$F$12:$M$12) -> 1576.222 | W47: =SUMPRODUCT($F47:$M47,$F$13:$M$13) -> 1814.2764 | X47: =SUMPRODUCT($F47:$M47,$F$14:$M$14) -> 163.28488
A48: R33 | B48: MP-47/ABC25 | C48: Tubo pescante de acero SAE 1010, carro 25 kg | D48: u | F48: 1 | N48: =SUMPRODUCT($F48:$M48,$F$4:$M$4) -> 34.051791 | O48: =SUMPRODUCT($F48:$M48,$F$5:$M$5) -> 58.462147 | P48: =SUMPRODUCT($F48:$M48,$F$6:$M$6) -> 75.20854 | Q48: =SUMPRODUCT($F48:$M48,$F$7:$M$7) -> 100.52985 | R48: =SUMPRODUCT($F48:$M48,$F$8:$M$8) -> 155.876 | S48: =SUMPRODUCT($F48:$M48,$F$9:$M$9) -> 211.93448 | T48: =SUMPRODUCT($F48:$M48,$F$10:$M$10) -> 272.66823 | U48: =SUMPRODUCT($F48:$M48,$F$11:$M$11) -> 337.84867 | V48: =SUMPRODUCT($F48:$M48,$F$12:$M$12) -> 393.62742 | W48: =SUMPRODUCT($F48:$M48,$F$13:$M$13) -> 453.27053 | X48: =SUMPRODUCT($F48:$M48,$F$14:$M$14) -> 40.794348
A49: R34 | B49: MP-47/ABC50 | C49: Tubo pescante de acero SAE 1010, carro 50 kg | D49: u | G49: 1 | N49: =SUMPRODUCT($F49:$M49,$F$4:$M$4) -> 75.201727 | O49: =SUMPRODUCT($F49:$M49,$F$5:$M$5) -> 129.20669 | P49: =SUMPRODUCT($F49:$M49,$F$6:$M$6) -> 166.6531 | Q49: =SUMPRODUCT($F49:$M49,$F$7:$M$7) -> 222.70533 | R49: =SUMPRODUCT($F49:$M49,$F$8:$M$8) -> 344.53881 | S49: =SUMPRODUCT($F49:$M49,$F$9:$M$9) -> 468.2272 | T49: =SUMPRODUCT($F49:$M49,$F$10:$M$10) -> 601.64 | U49: =SUMPRODUCT($F49:$M49,$F$11:$M$11) -> 744.53334 | V49: =SUMPRODUCT($F49:$M49,$F$12:$M$12) -> 867.28974 | W49: =SUMPRODUCT($F49:$M49,$F$13:$M$13) -> 998.25998 | X49: =SUMPRODUCT($F49:$M49,$F$14:$M$14) -> 89.843398
A50: R35 | B50: MP-47/ABC70 | C50: Tubo pescante de acero SAE 1010, carro 70 kg | D50: u | H50: 1 | N50: =SUMPRODUCT($F50:$M50,$F$4:$M$4) -> 16.34486 | O50: =SUMPRODUCT($F50:$M50,$F$5:$M$5) -> 28.061831 | P50: =SUMPRODUCT($F50:$M50,$F$6:$M$6) -> 36.100099 | Q50: =SUMPRODUCT($F50:$M50,$F$7:$M$7) -> 48.254329 | R50: =SUMPRODUCT($F50:$M50,$F$8:$M$8) -> 74.820482 | S50: =SUMPRODUCT($F50:$M50,$F$9:$M$9) -> 101.72855 | T50: =SUMPRODUCT($F50:$M50,$F$10:$M$10) -> 130.88075 | U50: =SUMPRODUCT($F50:$M50,$F$11:$M$11) -> 162.16736 | V50: =SUMPRODUCT($F50:$M50,$F$12:$M$12) -> 188.94116 | W50: =SUMPRODUCT($F50:$M50,$F$13:$M$13) -> 217.56986 | X50: =SUMPRODUCT($F50:$M50,$F$14:$M$14) -> 19.581287
A51: R36 | B51: MP-47/ABC100 | C51: Tubo pescante de acero SAE 1010, carro 100 kg | D51: u | I51: 1 | N51: =SUMPRODUCT($F51:$M51,$F$4:$M$4) -> 11.18436 | O51: =SUMPRODUCT($F51:$M51,$F$5:$M$5) -> 18.722277 | P51: =SUMPRODUCT($F51:$M51,$F$6:$M$6) -> 24.368909 | Q51: =SUMPRODUCT($F51:$M51,$F$7:$M$7) -> 32.486118 | R51: =SUMPRODUCT($F51:$M51,$F$8:$M$8) -> 50.499062 | S51: =SUMPRODUCT($F51:$M51,$F$9:$M$9) -> 68.178767 | T51: =SUMPRODUCT($F51:$M51,$F$10:$M$10) -> 87.627957 | U51: =SUMPRODUCT($F51:$M51,$F$11:$M$11) -> 108.50009 | V51: =SUMPRODUCT($F51:$M51,$F$12:$M$12) -> 126.36367 | W51: =SUMPRODUCT($F51:$M51,$F$13:$M$13) -> 145.17607 | X51: =SUMPRODUCT($F51:$M51,$F$14:$M$14) -> 13.065847
A52: R37 | B52: MP-49/ABC25 | C52: Manguera con válvula esférica y tobera, carro 25 kg | D52: u | F52: 1 | N52: =SUMPRODUCT($F52:$M52,$F$4:$M$4) -> 34.051791 | O52: =SUMPRODUCT($F52:$M52,$F$5:$M$5) -> 58.462147 | P52: =SUMPRODUCT($F52:$M52,$F$6:$M$6) -> 75.20854 | Q52: =SUMPRODUCT($F52:$M52,$F$7:$M$7) -> 100.52985 | R52: =SUMPRODUCT($F52:$M52,$F$8:$M$8) -> 155.876 | S52: =SUMPRODUCT($F52:$M52,$F$9:$M$9) -> 211.93448 | T52: =SUMPRODUCT($F52:$M52,$F$10:$M$10) -> 272.66823 | U52: =SUMPRODUCT($F52:$M52,$F$11:$M$11) -> 337.84867 | V52: =SUMPRODUCT($F52:$M52,$F$12:$M$12) -> 393.62742 | W52: =SUMPRODUCT($F52:$M52,$F$13:$M$13) -> 453.27053 | X52: =SUMPRODUCT($F52:$M52,$F$14:$M$14) -> 40.794348
A53: R38 | B53: MP-49/ABC50 | C53: Manguera con válvula esférica y tobera, carro 50 kg | D53: u | G53: 1 | N53: =SUMPRODUCT($F53:$M53,$F$4:$M$4) -> 75.201727 | O53: =SUMPRODUCT($F53:$M53,$F$5:$M$5) -> 129.20669 | P53: =SUMPRODUCT($F53:$M53,$F$6:$M$6) -> 166.6531 | Q53: =SUMPRODUCT($F53:$M53,$F$7:$M$7) -> 222.70533 | R53: =SUMPRODUCT($F53:$M53,$F$8:$M$8) -> 344.53881 | S53: =SUMPRODUCT($F53:$M53,$F$9:$M$9) -> 468.2272 | T53: =SUMPRODUCT($F53:$M53,$F$10:$M$10) -> 601.64 | U53: =SUMPRODUCT($F53:$M53,$F$11:$M$11) -> 744.53334 | V53: =SUMPRODUCT($F53:$M53,$F$12:$M$12) -> 867.28974 | W53: =SUMPRODUCT($F53:$M53,$F$13:$M$13) -> 998.25998 | X53: =SUMPRODUCT($F53:$M53,$F$14:$M$14) -> 89.843398
A54: R39 | B54: MP-49/ABC70 | C54: Manguera con válvula esférica y tobera, carro 70 kg | D54: u | H54: 1 | N54: =SUMPRODUCT($F54:$M54,$F$4:$M$4) -> 16.34486 | O54: =SUMPRODUCT($F54:$M54,$F$5:$M$5) -> 28.061831 | P54: =SUMPRODUCT($F54:$M54,$F$6:$M$6) -> 36.100099 | Q54: =SUMPRODUCT($F54:$M54,$F$7:$M$7) -> 48.254329 | R54: =SUMPRODUCT($F54:$M54,$F$8:$M$8) -> 74.820482 | S54: =SUMPRODUCT($F54:$M54,$F$9:$M$9) -> 101.72855 | T54: =SUMPRODUCT($F54:$M54,$F$10:$M$10) -> 130.88075 | U54: =SUMPRODUCT($F54:$M54,$F$11:$M$11) -> 162.16736 | V54: =SUMPRODUCT($F54:$M54,$F$12:$M$12) -> 188.94116 | W54: =SUMPRODUCT($F54:$M54,$F$13:$M$13) -> 217.56986 | X54: =SUMPRODUCT($F54:$M54,$F$14:$M$14) -> 19.581287
A55: R40 | B55: MP-49/ABC100 | C55: Manguera con válvula esférica y tobera, carro 100 kg | D55: u | I55: 1 | N55: =SUMPRODUCT($F55:$M55,$F$4:$M$4) -> 11.18436 | O55: =SUMPRODUCT($F55:$M55,$F$5:$M$5) -> 18.722277 | P55: =SUMPRODUCT($F55:$M55,$F$6:$M$6) -> 24.368909 | Q55: =SUMPRODUCT($F55:$M55,$F$7:$M$7) -> 32.486118 | R55: =SUMPRODUCT($F55:$M55,$F$8:$M$8) -> 50.499062 | S55: =SUMPRODUCT($F55:$M55,$F$9:$M$9) -> 68.178767 | T55: =SUMPRODUCT($F55:$M55,$F$10:$M$10) -> 87.627957 | U55: =SUMPRODUCT($F55:$M55,$F$11:$M$11) -> 108.50009 | V55: =SUMPRODUCT($F55:$M55,$F$12:$M$12) -> 126.36367 | W55: =SUMPRODUCT($F55:$M55,$F$13:$M$13) -> 145.17607 | X55: =SUMPRODUCT($F55:$M55,$F$14:$M$14) -> 13.065847
A56: R41 | B56: MP-50/M30 | C56: Junta tórica del cuello M30 | D56: u | F56: 1 | G56: 1 | N56: =SUMPRODUCT($F56:$M56,$F$4:$M$4) -> 109.25352 | O56: =SUMPRODUCT($F56:$M56,$F$5:$M$5) -> 187.66883 | P56: =SUMPRODUCT($F56:$M56,$F$6:$M$6) -> 241.86164 | Q56: =SUMPRODUCT($F56:$M56,$F$7:$M$7) -> 323.23519 | R56: =SUMPRODUCT($F56:$M56,$F$8:$M$8) -> 500.41482 | S56: =SUMPRODUCT($F56:$M56,$F$9:$M$9) -> 680.16168 | T56: =SUMPRODUCT($F56:$M56,$F$10:$M$10) -> 874.30823 | U56: =SUMPRODUCT($F56:$M56,$F$11:$M$11) -> 1082.382 | V56: =SUMPRODUCT($F56:$M56,$F$12:$M$12) -> 1260.9172 | W56: =SUMPRODUCT($F56:$M56,$F$13:$M$13) -> 1451.5305 | X56: =SUMPRODUCT($F56:$M56,$F$14:$M$14) -> 130.63775
A57: R42 | B57: MP-50/2½ | C57: Junta tórica del cuello 2½" | D57: u | H57: 1 | I57: 1 | N57: =SUMPRODUCT($F57:$M57,$F$4:$M$4) -> 27.52922 | O57: =SUMPRODUCT($F57:$M57,$F$5:$M$5) -> 46.784107 | P57: =SUMPRODUCT($F57:$M57,$F$6:$M$6) -> 60.469008 | Q57: =SUMPRODUCT($F57:$M57,$F$7:$M$7) -> 80.740447 | R57: =SUMPRODUCT($F57:$M57,$F$8:$M$8) -> 125.31954 | S57: =SUMPRODUCT($F57:$M57,$F$9:$M$9) -> 169.90732 | T57: =SUMPRODUCT($F57:$M57,$F$10:$M$10) -> 218.50871 | U57: =SUMPRODUCT($F57:$M57,$F$11:$M$11) -> 270.66745 | V57: =SUMPRODUCT($F57:$M57,$F$12:$M$12) -> 315.30483 | W57: =SUMPRODUCT($F57:$M57,$F$13:$M$13) -> 362.74593 | X57: =SUMPRODUCT($F57:$M57,$F$14:$M$14) -> 32.647134
A58: R43 | B58: MP-56/ABC25 | C58: Etiqueta de características ABC 25 kg | D58: u | F58: 1 | N58: =SUMPRODUCT($F58:$M58,$F$4:$M$4) -> 34.051791 | O58: =SUMPRODUCT($F58:$M58,$F$5:$M$5) -> 58.462147 | P58: =SUMPRODUCT($F58:$M58,$F$6:$M$6) -> 75.20854 | Q58: =SUMPRODUCT($F58:$M58,$F$7:$M$7) -> 100.52985 | R58: =SUMPRODUCT($F58:$M58,$F$8:$M$8) -> 155.876 | S58: =SUMPRODUCT($F58:$M58,$F$9:$M$9) -> 211.93448 | T58: =SUMPRODUCT($F58:$M58,$F$10:$M$10) -> 272.66823 | U58: =SUMPRODUCT($F58:$M58,$F$11:$M$11) -> 337.84867 | V58: =SUMPRODUCT($F58:$M58,$F$12:$M$12) -> 393.62742 | W58: =SUMPRODUCT($F58:$M58,$F$13:$M$13) -> 453.27053 | X58: =SUMPRODUCT($F58:$M58,$F$14:$M$14) -> 40.794348
A59: R44 | B59: MP-56/ABC50 | C59: Etiqueta de características ABC 50 kg | D59: u | G59: 1 | N59: =SUMPRODUCT($F59:$M59,$F$4:$M$4) -> 75.201727 | O59: =SUMPRODUCT($F59:$M59,$F$5:$M$5) -> 129.20669 | P59: =SUMPRODUCT($F59:$M59,$F$6:$M$6) -> 166.6531 | Q59: =SUMPRODUCT($F59:$M59,$F$7:$M$7) -> 222.70533 | R59: =SUMPRODUCT($F59:$M59,$F$8:$M$8) -> 344.53881 | S59: =SUMPRODUCT($F59:$M59,$F$9:$M$9) -> 468.2272 | T59: =SUMPRODUCT($F59:$M59,$F$10:$M$10) -> 601.64 | U59: =SUMPRODUCT($F59:$M59,$F$11:$M$11) -> 744.53334 | V59: =SUMPRODUCT($F59:$M59,$F$12:$M$12) -> 867.28974 | W59: =SUMPRODUCT($F59:$M59,$F$13:$M$13) -> 998.25998 | X59: =SUMPRODUCT($F59:$M59,$F$14:$M$14) -> 89.843398
A60: R45 | B60: MP-56/ABC70 | C60: Etiqueta de características ABC 70 kg | D60: u | H60: 1 | N60: =SUMPRODUCT($F60:$M60,$F$4:$M$4) -> 16.34486 | O60: =SUMPRODUCT($F60:$M60,$F$5:$M$5) -> 28.061831 | P60: =SUMPRODUCT($F60:$M60,$F$6:$M$6) -> 36.100099 | Q60: =SUMPRODUCT($F60:$M60,$F$7:$M$7) -> 48.254329 | R60: =SUMPRODUCT($F60:$M60,$F$8:$M$8) -> 74.820482 | S60: =SUMPRODUCT($F60:$M60,$F$9:$M$9) -> 101.72855 | T60: =SUMPRODUCT($F60:$M60,$F$10:$M$10) -> 130.88075 | U60: =SUMPRODUCT($F60:$M60,$F$11:$M$11) -> 162.16736 | V60: =SUMPRODUCT($F60:$M60,$F$12:$M$12) -> 188.94116 | W60: =SUMPRODUCT($F60:$M60,$F$13:$M$13) -> 217.56986 | X60: =SUMPRODUCT($F60:$M60,$F$14:$M$14) -> 19.581287
A61: R46 | B61: MP-56/ABC100 | C61: Etiqueta de características ABC 100 kg | D61: u | I61: 1 | N61: =SUMPRODUCT($F61:$M61,$F$4:$M$4) -> 11.18436 | O61: =SUMPRODUCT($F61:$M61,$F$5:$M$5) -> 18.722277 | P61: =SUMPRODUCT($F61:$M61,$F$6:$M$6) -> 24.368909 | Q61: =SUMPRODUCT($F61:$M61,$F$7:$M$7) -> 32.486118 | R61: =SUMPRODUCT($F61:$M61,$F$8:$M$8) -> 50.499062 | S61: =SUMPRODUCT($F61:$M61,$F$9:$M$9) -> 68.178767 | T61: =SUMPRODUCT($F61:$M61,$F$10:$M$10) -> 87.627957 | U61: =SUMPRODUCT($F61:$M61,$F$11:$M$11) -> 108.50009 | V61: =SUMPRODUCT($F61:$M61,$F$12:$M$12) -> 126.36367 | W61: =SUMPRODUCT($F61:$M61,$F$13:$M$13) -> 145.17607 | X61: =SUMPRODUCT($F61:$M61,$F$14:$M$14) -> 13.065847
A62: R47 | B62: MP-78 | C62: Oblea de fabricación (PBA) | D62: u | E62: PBA | F62: 1 | G62: 1 | H62: 1 | I62: 1 | N62: =SUMPRODUCT($F62:$M62,$F$4:$M$4)*(1-DEMANDA!D$5) -> 104.89143 | O62: =SUMPRODUCT($F62:$M62,$F$5:$M$5)*(1-DEMANDA!E$5) -> 179.81022 | P62: =SUMPRODUCT($F62:$M62,$F$6:$M$6)*(1-DEMANDA!F$5) -> 231.86955 | Q62: =SUMPRODUCT($F62:$M62,$F$7:$M$7)*(1-DEMANDA!G$5) -> 309.79874 | R62: =SUMPRODUCT($F62:$M62,$F$8:$M$8)*(1-DEMANDA!H$5) -> 479.75711 | S62: =SUMPRODUCT($F62:$M62,$F$9:$M$9)*(1-DEMANDA!I$5) -> 651.51963 | T62: =SUMPRODUCT($F62:$M62,$F$10:$M$10)*(1-DEMANDA!J$5) -> 837.119 | U62: =SUMPRODUCT($F62:$M62,$F$11:$M$11)*(1-DEMANDA!K$5) -> 1035.7027 | V62: =SUMPRODUCT($F62:$M62,$F$12:$M$12)*(1-DEMANDA!L$5) -> 1205.3767 | W62: =SUMPRODUCT($F62:$M62,$F$13:$M$13)*(1-DEMANDA!M$5) -> 1385.7168 | X62: =SUMPRODUCT($F62:$M62,$F$14:$M$14)*(1-DEMANDA!M$5) -> 124.71451
A63: R48 | B63: MP-79 | C63: Estampilla IRAM de conformidad | D63: u | F63: 1 | G63: 1 | H63: 1 | I63: 1 | N63: =SUMPRODUCT($F63:$M63,$F$4:$M$4) -> 136.78274 | O63: =SUMPRODUCT($F63:$M63,$F$5:$M$5) -> 234.45294 | P63: =SUMPRODUCT($F63:$M63,$F$6:$M$6) -> 302.33065 | Q63: =SUMPRODUCT($F63:$M63,$F$7:$M$7) -> 403.97563 | R63: =SUMPRODUCT($F63:$M63,$F$8:$M$8) -> 625.73436 | S63: =SUMPRODUCT($F63:$M63,$F$9:$M$9) -> 850.069 | T63: =SUMPRODUCT($F63:$M63,$F$10:$M$10) -> 1092.8169 | U63: =SUMPRODUCT($F63:$M63,$F$11:$M$11) -> 1353.0495 | V63: =SUMPRODUCT($F63:$M63,$F$12:$M$12) -> 1576.222 | W63: =SUMPRODUCT($F63:$M63,$F$13:$M$13) -> 1814.2764 | X63: =SUMPRODUCT($F63:$M63,$F$14:$M$14) -> 163.28488
A64: R49 | B64: MP-77 | C64: Tarjeta de identificación AGC (CABA) | D64: u | E64: CABA | F64: 1 | G64: 1 | H64: 1 | I64: 1 | N64: =SUMPRODUCT($F64:$M64,$F$4:$M$4)*DEMANDA!D$5 -> 31.891304 | O64: =SUMPRODUCT($F64:$M64,$F$5:$M$5)*DEMANDA!E$5 -> 54.642718 | P64: =SUMPRODUCT($F64:$M64,$F$6:$M$6)*DEMANDA!F$5 -> 70.461095 | Q64: =SUMPRODUCT($F64:$M64,$F$7:$M$7)*DEMANDA!G$5 -> 94.176898 | R64: =SUMPRODUCT($F64:$M64,$F$8:$M$8)*DEMANDA!H$5 -> 145.97725 | S64: =SUMPRODUCT($F64:$M64,$F$9:$M$9)*DEMANDA!I$5 -> 198.54937 | T64: =SUMPRODUCT($F64:$M64,$F$10:$M$10)*DEMANDA!J$5 -> 255.69794 | U64: =SUMPRODUCT($F64:$M64,$F$11:$M$11)*DEMANDA!K$5 -> 317.34674 | V64: =SUMPRODUCT($F64:$M64,$F$12:$M$12)*DEMANDA!L$5 -> 370.84533 | W64: =SUMPRODUCT($F64:$M64,$F$13:$M$13)*DEMANDA!M$5 -> 428.55961 | X64: =SUMPRODUCT($F64:$M64,$F$14:$M$14)*DEMANDA!M$5 -> 38.570365
A65: R50 | B65: MP-80 | C65: Etiqueta de n° de serie GS1 | D65: u | F65: 1 | G65: 1 | H65: 1 | I65: 1 | N65: =SUMPRODUCT($F65:$M65,$F$4:$M$4) -> 136.78274 | O65: =SUMPRODUCT($F65:$M65,$F$5:$M$5) -> 234.45294 | P65: =SUMPRODUCT($F65:$M65,$F$6:$M$6) -> 302.33065 | Q65: =SUMPRODUCT($F65:$M65,$F$7:$M$7) -> 403.97563 | R65: =SUMPRODUCT($F65:$M65,$F$8:$M$8) -> 625.73436 | S65: =SUMPRODUCT($F65:$M65,$F$9:$M$9) -> 850.069 | T65: =SUMPRODUCT($F65:$M65,$F$10:$M$10) -> 1092.8169 | U65: =SUMPRODUCT($F65:$M65,$F$11:$M$11) -> 1353.0495 | V65: =SUMPRODUCT($F65:$M65,$F$12:$M$12) -> 1576.222 | W65: =SUMPRODUCT($F65:$M65,$F$13:$M$13) -> 1814.2764 | X65: =SUMPRODUCT($F65:$M65,$F$14:$M$14) -> 163.28488
A66: R51 | B66: MP-81 | C66: Faja de garantía válvula-cuello | D66: u | F66: 1 | G66: 1 | H66: 1 | I66: 1 | N66: =SUMPRODUCT($F66:$M66,$F$4:$M$4) -> 136.78274 | O66: =SUMPRODUCT($F66:$M66,$F$5:$M$5) -> 234.45294 | P66: =SUMPRODUCT($F66:$M66,$F$6:$M$6) -> 302.33065 | Q66: =SUMPRODUCT($F66:$M66,$F$7:$M$7) -> 403.97563 | R66: =SUMPRODUCT($F66:$M66,$F$8:$M$8) -> 625.73436 | S66: =SUMPRODUCT($F66:$M66,$F$9:$M$9) -> 850.069 | T66: =SUMPRODUCT($F66:$M66,$F$10:$M$10) -> 1092.8169 | U66: =SUMPRODUCT($F66:$M66,$F$11:$M$11) -> 1353.0495 | V66: =SUMPRODUCT($F66:$M66,$F$12:$M$12) -> 1576.222 | W66: =SUMPRODUCT($F66:$M66,$F$13:$M$13) -> 1814.2764 | X66: =SUMPRODUCT($F66:$M66,$F$14:$M$14) -> 163.28488
A67: R52 | B67: MP-51 | C67: Precinto de fábrica | D67: u | F67: 1 | G67: 1 | H67: 1 | I67: 1 | N67: =SUMPRODUCT($F67:$M67,$F$4:$M$4) -> 136.78274 | O67: =SUMPRODUCT($F67:$M67,$F$5:$M$5) -> 234.45294 | P67: =SUMPRODUCT($F67:$M67,$F$6:$M$6) -> 302.33065 | Q67: =SUMPRODUCT($F67:$M67,$F$7:$M$7) -> 403.97563 | R67: =SUMPRODUCT($F67:$M67,$F$8:$M$8) -> 625.73436 | S67: =SUMPRODUCT($F67:$M67,$F$9:$M$9) -> 850.069 | T67: =SUMPRODUCT($F67:$M67,$F$10:$M$10) -> 1092.8169 | U67: =SUMPRODUCT($F67:$M67,$F$11:$M$11) -> 1353.0495 | V67: =SUMPRODUCT($F67:$M67,$F$12:$M$12) -> 1576.222 | W67: =SUMPRODUCT($F67:$M67,$F$13:$M$13) -> 1814.2764 | X67: =SUMPRODUCT($F67:$M67,$F$14:$M$14) -> 163.28488
A68: R53 | B68: MP-88 | C68: Etiqueta del cilindro suelto | D68: u | J68: 1 | K68: 1 | L68: 1 | M68: 1 | N68: =SUMPRODUCT($F68:$M68,$F$4:$M$4) -> 0 | O68: =SUMPRODUCT($F68:$M68,$F$5:$M$5) -> 0 | P68: =SUMPRODUCT($F68:$M68,$F$6:$M$6) -> 57.8 | Q68: =SUMPRODUCT($F68:$M68,$F$7:$M$7) -> 201.4 | R68: =SUMPRODUCT($F68:$M68,$F$8:$M$8) -> 373 | S68: =SUMPRODUCT($F68:$M68,$F$9:$M$9) -> 540.8 | T68: =SUMPRODUCT($F68:$M68,$F$10:$M$10) -> 764.4 | U68: =SUMPRODUCT($F68:$M68,$F$11:$M$11) -> 988 | V68: =SUMPRODUCT($F68:$M68,$F$12:$M$12) -> 1107.6 | W68: =SUMPRODUCT($F68:$M68,$F$13:$M$13) -> 1287 | X68: =SUMPRODUCT($F68:$M68,$F$14:$M$14) -> 115.83
A69: R54 | B69: MP-62/M30 | C69: Tapón protector de rosca M30 | D69: u | J69: 1 | K69: 1 | N69: =SUMPRODUCT($F69:$M69,$F$4:$M$4) -> 0 | O69: =SUMPRODUCT($F69:$M69,$F$5:$M$5) -> 0 | P69: =SUMPRODUCT($F69:$M69,$F$6:$M$6) -> 46.2 | Q69: =SUMPRODUCT($F69:$M69,$F$7:$M$7) -> 161 | R69: =SUMPRODUCT($F69:$M69,$F$8:$M$8) -> 298.2 | S69: =SUMPRODUCT($F69:$M69,$F$9:$M$9) -> 432.6 | T69: =SUMPRODUCT($F69:$M69,$F$10:$M$10) -> 611.8 | U69: =SUMPRODUCT($F69:$M69,$F$11:$M$11) -> 791 | V69: =SUMPRODUCT($F69:$M69,$F$12:$M$12) -> 886.6 | W69: =SUMPRODUCT($F69:$M69,$F$13:$M$13) -> 1030 | X69: =SUMPRODUCT($F69:$M69,$F$14:$M$14) -> 92.7
A70: R55 | B70: MP-62/2½ | C70: Tapón protector de rosca 2½" | D70: u | L70: 1 | M70: 1 | N70: =SUMPRODUCT($F70:$M70,$F$4:$M$4) -> 0 | O70: =SUMPRODUCT($F70:$M70,$F$5:$M$5) -> 0 | P70: =SUMPRODUCT($F70:$M70,$F$6:$M$6) -> 11.6 | Q70: =SUMPRODUCT($F70:$M70,$F$7:$M$7) -> 40.4 | R70: =SUMPRODUCT($F70:$M70,$F$8:$M$8) -> 74.8 | S70: =SUMPRODUCT($F70:$M70,$F$9:$M$9) -> 108.2 | T70: =SUMPRODUCT($F70:$M70,$F$10:$M$10) -> 152.6 | U70: =SUMPRODUCT($F70:$M70,$F$11:$M$11) -> 197 | V70: =SUMPRODUCT($F70:$M70,$F$12:$M$12) -> 221 | W70: =SUMPRODUCT($F70:$M70,$F$13:$M$13) -> 257 | X70: =SUMPRODUCT($F70:$M70,$F$14:$M$14) -> 23.13
A71: R56 | B71: MP-60 | C71: Pallet de madera 1200 × 1000 | D71: u | J71: =1/24 -> 0.041666667 | K71: =1/9 -> 0.11111111 | L71: =1/6 -> 0.16666667 | M71: =1/6 -> 0.16666667 | N71: =SUMPRODUCT($F71:$M71,$F$4:$M$4) -> 0 | O71: =SUMPRODUCT($F71:$M71,$F$5:$M$5) -> 0 | P71: =SUMPRODUCT($F71:$M71,$F$6:$M$6) -> 6.0666667 | Q71: =SUMPRODUCT($F71:$M71,$F$7:$M$7) -> 21.136111 | R71: =SUMPRODUCT($F71:$M71,$F$8:$M$8) -> 39.141667 | S71: =SUMPRODUCT($F71:$M71,$F$9:$M$9) -> 56.725 | T71: =SUMPRODUCT($F71:$M71,$F$10:$M$10) -> 80.147222 | U71: =SUMPRODUCT($F71:$M71,$F$11:$M$11) -> 103.56944 | V71: =SUMPRODUCT($F71:$M71,$F$12:$M$12) -> 116.10833 | W71: =SUMPRODUCT($F71:$M71,$F$13:$M$13) -> 134.91667 | X71: =SUMPRODUCT($F71:$M71,$F$14:$M$14) -> 12.1425
A72: R57 | B72: MP-90 | C72: Etiqueta de pallet | D72: u | J72: =1/24 -> 0.041666667 | K72: =1/9 -> 0.11111111 | L72: =1/6 -> 0.16666667 | M72: =1/6 -> 0.16666667 | N72: =SUMPRODUCT($F72:$M72,$F$4:$M$4) -> 0 | O72: =SUMPRODUCT($F72:$M72,$F$5:$M$5) -> 0 | P72: =SUMPRODUCT($F72:$M72,$F$6:$M$6) -> 6.0666667 | Q72: =SUMPRODUCT($F72:$M72,$F$7:$M$7) -> 21.136111 | R72: =SUMPRODUCT($F72:$M72,$F$8:$M$8) -> 39.141667 | S72: =SUMPRODUCT($F72:$M72,$F$9:$M$9) -> 56.725 | T72: =SUMPRODUCT($F72:$M72,$F$10:$M$10) -> 80.147222 | U72: =SUMPRODUCT($F72:$M72,$F$11:$M$11) -> 103.56944 | V72: =SUMPRODUCT($F72:$M72,$F$12:$M$12) -> 116.10833 | W72: =SUMPRODUCT($F72:$M72,$F$13:$M$13) -> 134.91667 | X72: =SUMPRODUCT($F72:$M72,$F$14:$M$14) -> 12.1425

Sheet RECARGAS
A1: RECARGAS: consumo por unidad de producto y lo que hay que comprar
A3: Ref. | B3: Código | C3: Material | D3: UM | E3: Destino | F3: Recarga ABC 1 kg | G3: Recarga ABC 2,5 kg | H3: Recarga ABC 5 kg | I3: Recarga ABC 10 kg | J3: Recarga Agua 10 l | K3: Recarga AFFF 10 l | L3: Recarga AFFF 50 l | M3: Recarga BC 5 kg | N3: Recarga Clase K 6 l | O3: Recarga CO₂ 2 kg | P3: Recarga CO₂ 5 kg | Q3: Recarga HCFC 5 kg | R3: Recarga Clase D 9 l | S3: Recarga ABC 25 kg | T3: Recarga ABC 50 kg | U3: Recarga ABC 70 kg | V3: Recarga ABC 100 kg | W3: Sustituto nuevo (kit) | X3: 2026 | Y3: 2027 | Z3: 2028 | AA3: 2029 | AB3: 2030 | AC3: 2031 | AD3: 2032 | AE3: 2033 | AF3: 2034 | AG3: 2035 | AH3: Mes pico 2035
C4: Demanda 2026 | F4: =DEMANDA!D24 -> 1000.7721 | G4: =DEMANDA!D25 -> 94.968557 | H4: =DEMANDA!D26 -> 579.42746 | I4: =DEMANDA!D27 -> 34.633262 | J4: =DEMANDA!D28 -> 46.422462 | K4: =DEMANDA!D29 -> 6.837342 | L4: =DEMANDA!D30 -> 3.5625642 | M4: =DEMANDA!D31 -> 2.2526531 | N4: =DEMANDA!D32 -> 23.866187 | O4: =DEMANDA!D33 -> 129.6812 | P4: =DEMANDA!D34 -> 38.037061 | Q4: =DEMANDA!D35 -> 5.5274309 | R4: =DEMANDA!D36 -> 2.2526531 | S4: =DEMANDA!D37 -> 5.0759056 | T4: =DEMANDA!D38 -> 11.454779 | U4: =DEMANDA!D39 -> 2.4364347 | V4: =DEMANDA!D40 -> 1.9120762 | W4: =DEMANDA!D41 -> 23.598486
C5: Demanda 2027 | F5: =DEMANDA!E24 -> 4883.9039 | G5: =DEMANDA!E25 -> 370.50026 | H5: =DEMANDA!E26 -> 2341.0327 | I5: =DEMANDA!E27 -> 127.40782 | J5: =DEMANDA!E28 -> 187.18306 | K5: =DEMANDA!E29 -> 47.000054 | L5: =DEMANDA!E30 -> 24.238384 | M5: =DEMANDA!E31 -> 13.834788 | N5: =DEMANDA!E32 -> 97.674378 | O5: =DEMANDA!E33 -> 488.42577 | P5: =DEMANDA!E34 -> 192.71052 | Q5: =DEMANDA!E35 -> 32.82927 | R5: =DEMANDA!E36 -> 13.834788 | S5: =DEMANDA!E37 -> 24.746126 | T5: =DEMANDA!E38 -> 55.304836 | U5: =DEMANDA!E39 -> 11.87814 | V5: =DEMANDA!E40 -> 8.2065467 | W5: =DEMANDA!E41 -> 73.956311
C6: Demanda 2028 | F6: =DEMANDA!F24 -> 8790.7495 | G6: =DEMANDA!F25 -> 848.15525 | H6: =DEMANDA!F26 -> 5274.796 | I6: =DEMANDA!F27 -> 298.42726 | J6: =DEMANDA!F28 -> 428.90614 | K6: =DEMANDA!F29 -> 92.266417 | L6: =DEMANDA!F30 -> 47.906029 | M6: =DEMANDA!F31 -> 25.869027 | N6: =DEMANDA!F32 -> 217.45094 | O6: =DEMANDA!F33 -> 1138.2519 | P6: =DEMANDA!F34 -> 412.57829 | Q6: =DEMANDA!F35 -> 67.300015 | R6: =DEMANDA!F36 -> 25.869027 | S6: =DEMANDA!F37 -> 53.778522 | T6: =DEMANDA!F38 -> 120.32725 | U6: =DEMANDA!F39 -> 25.813691 | V6: =DEMANDA!F40 -> 17.7847 | W6: =DEMANDA!F41 -> 100.52859
C7: Demanda 2029 | F7: =DEMANDA!G24 -> 16129.942 | G7: =DEMANDA!G25 -> 1561.5415 | H7: =DEMANDA!G26 -> 9966.207 | I7: =DEMANDA!G27 -> 570.51062 | J7: =DEMANDA!G28 -> 804.78066 | K7: =DEMANDA!G29 -> 153.50372 | L7: =DEMANDA!G30 -> 82.117304 | M7: =DEMANDA!G31 -> 46.478222 | N7: =DEMANDA!G32 -> 395.3897 | O7: =DEMANDA!G33 -> 2176.028 | P7: =DEMANDA!G34 -> 739.4051 | Q7: =DEMANDA!G35 -> 116.75936 | R7: =DEMANDA!G36 -> 43.248307 | S7: =DEMANDA!G37 -> 96.864192 | T7: =DEMANDA!G38 -> 216.55466 | U7: =DEMANDA!G39 -> 46.494812 | V7: =DEMANDA!G40 -> 31.859901 | W7: =DEMANDA!G41 -> 172.50877
C8: Demanda 2030 | F8: =DEMANDA!H24 -> 24251.826 | G8: =DEMANDA!H25 -> 2259.3754 | H8: =DEMANDA!H26 -> 14367.038 | I8: =DEMANDA!H27 -> 827.66705 | J8: =DEMANDA!H28 -> 1161.3521 | K8: =DEMANDA!H29 -> 216.64243 | L8: =DEMANDA!H30 -> 116.23765 | M8: =DEMANDA!H31 -> 64.117719 | N8: =DEMANDA!H32 -> 570.71658 | O8: =DEMANDA!H33 -> 3142.6693 | P8: =DEMANDA!H34 -> 1065.1717 | Q8: =DEMANDA!H35 -> 167.35004 | R8: =DEMANDA!H36 -> 59.924629 | S8: =DEMANDA!H37 -> 139.32678 | T8: =DEMANDA!H38 -> 311.41129 | U8: =DEMANDA!H39 -> 66.876856 | V8: =DEMANDA!H40 -> 46.023503 | W8: =DEMANDA!H41 -> 184.73969
C9: Demanda 2031 | F9: =DEMANDA!I24 -> 33788.376 | G9: =DEMANDA!I25 -> 2999.8693 | H9: =DEMANDA!I26 -> 19107.591 | I9: =DEMANDA!I27 -> 1108.6657 | J9: =DEMANDA!I28 -> 1552.2496 | K9: =DEMANDA!I29 -> 280.2678 | L9: =DEMANDA!I30 -> 149.80068 | M9: =DEMANDA!I31 -> 85.147323 | N9: =DEMANDA!I32 -> 756.17071 | O9: =DEMANDA!I33 -> 4177.1867 | P9: =DEMANDA!I34 -> 1419.2077 | Q9: =DEMANDA!I35 -> 219.6805 | R9: =DEMANDA!I36 -> 74.469092 | S9: =DEMANDA!I37 -> 185.11009 | T9: =DEMANDA!I38 -> 413.86128 | U9: =DEMANDA!I39 -> 88.852841 | V9: =DEMANDA!I40 -> 60.961946 | W9: =DEMANDA!I41 -> 213.60946
C10: Demanda 2032 | F10: =DEMANDA!J24 -> 42480.335 | G10: =DEMANDA!J25 -> 3686.5139 | H10: =DEMANDA!J26 -> 23397.064 | I10: =DEMANDA!J27 -> 1356.8203 | J10: =DEMANDA!J28 -> 1902.2563 | K10: =DEMANDA!J29 -> 347.62935 | L10: =DEMANDA!J30 -> 183.05101 | M10: =DEMANDA!J31 -> 107.29949 | N10: =DEMANDA!J32 -> 930.20151 | O10: =DEMANDA!J33 -> 5107.2013 | P10: =DEMANDA!J34 -> 1758.0599 | Q10: =DEMANDA!J35 -> 275.08031 | R10: =DEMANDA!J36 -> 95.665355 | S10: =DEMANDA!J37 -> 228.05109 | T10: =DEMANDA!J38 -> 509.77041 | U10: =DEMANDA!J39 -> 109.46452 | V10: =DEMANDA!J40 -> 74.990853 | W10: =DEMANDA!J41 -> 205.50348
C11: Demanda 2033 | F11: =DEMANDA!K24 -> 49327.846 | G11: =DEMANDA!K25 -> 4104.7172 | H11: =DEMANDA!K26 -> 25952.927 | I11: =DEMANDA!K27 -> 1502.3932 | J11: =DEMANDA!K28 -> 2114.8904 | K11: =DEMANDA!K29 -> 393.29385 | L11: =DEMANDA!K30 -> 206.96966 | M11: =DEMANDA!K31 -> 118.97348 | N11: =DEMANDA!K32 -> 1041.0787 | O11: =DEMANDA!K33 -> 5645.5652 | P11: =DEMANDA!K34 -> 1983.2685 | Q11: =DEMANDA!K35 -> 312.028 | R11: =DEMANDA!K36 -> 106.7423 | S11: =DEMANDA!K37 -> 256.03715 | T11: =DEMANDA!K38 -> 572.20312 | U11: =DEMANDA!K39 -> 122.89783 | V11: =DEMANDA!K40 -> 84.234181 | W11: =DEMANDA!K41 -> 163.46268
C12: Demanda 2034 | F12: =DEMANDA!L24 -> 52863.649 | G12: =DEMANDA!L25 -> 4441.3702 | H12: =DEMANDA!L26 -> 27992.313 | I12: =DEMANDA!L27 -> 1620.9697 | J12: =DEMANDA!L28 -> 2285.1511 | K12: =DEMANDA!L29 -> 429.82307 | L12: =DEMANDA!L30 -> 225.16725 | M12: =DEMANDA!L31 -> 129.72892 | N12: =DEMANDA!L32 -> 1126.0357 | O12: =DEMANDA!L33 -> 6090.0803 | P12: =DEMANDA!L34 -> 2156.0119 | Q12: =DEMANDA!L35 -> 340.93934 | R12: =DEMANDA!L36 -> 117.03747 | S12: =DEMANDA!L37 -> 277.80342 | T12: =DEMANDA!L38 -> 620.95226 | U12: =DEMANDA!L39 -> 133.34564 | V12: =DEMANDA!L40 -> 91.487172 | W12: =DEMANDA!L41 -> 125.0384
C13: Demanda 2035 | F13: =DEMANDA!M24 -> 56487.491 | G13: =DEMANDA!M25 -> 4783.2292 | H13: =DEMANDA!M26 -> 30068.838 | I13: =DEMANDA!M27 -> 1741.3814 | J13: =DEMANDA!M28 -> 2458.5058 | K13: =DEMANDA!M29 -> 466.91659 | L13: =DEMANDA!M30 -> 243.56826 | M13: =DEMANDA!M31 -> 140.86546 | N13: =DEMANDA!M32 -> 1212.3174 | O13: =DEMANDA!M33 -> 6542.6807 | P13: =DEMANDA!M34 -> 2330.9482 | Q13: =DEMANDA!M35 -> 370.07637 | R13: =DEMANDA!M36 -> 127.11145 | S13: =DEMANDA!M37 -> 299.85609 | T13: =DEMANDA!M38 -> 670.0437 | U13: =DEMANDA!M39 -> 143.93092 | V13: =DEMANDA!M40 -> 98.544026 | W13: =DEMANDA!M41 -> 129.8924
C14: Producción del mes pico de cada producto, 2035 | F14: =ESTACIONALIDAD!P28 -> 4707.2909 | G14: =ESTACIONALIDAD!P29 -> 398.60243 | H14: =ESTACIONALIDAD!P30 -> 2505.7365 | I14: =ESTACIONALIDAD!P31 -> 145.11512 | J14: =ESTACIONALIDAD!P32 -> 204.87548 | K14: =ESTACIONALIDAD!P33 -> 38.909716 | L14: =ESTACIONALIDAD!P34 -> 20.297355 | M14: =ESTACIONALIDAD!P35 -> 11.738789 | N14: =ESTACIONALIDAD!P36 -> 101.02645 | O14: =ESTACIONALIDAD!P37 -> 545.22339 | P14: =ESTACIONALIDAD!P38 -> 194.24569 | Q14: =ESTACIONALIDAD!P39 -> 30.839698 | R14: =ESTACIONALIDAD!P40 -> 10.592621 | S14: =ESTACIONALIDAD!P41 -> 24.988007 | T14: =ESTACIONALIDAD!P42 -> 55.836975 | U14: =ESTACIONALIDAD!P43 -> 11.994243 | V14: =ESTACIONALIDAD!P44 -> 8.2120021 | W14: =DEMANDA!M41/12 -> 10.824366
C15: CONSUMO POR UNIDAD (cantidad del material por cada producto)
A16: K01 | B16: MP-33 | C16: Polvo ABC 60 (manuales y sus recargas) | D16: kg | F16: =1.05*(0.1+DEMANDA!$M$7)+(1-0.1-DEMANDA!$M$7)*0.05 -> 0.19763326 | G16: =2.55*(0.1+DEMANDA!$M$7)+(1-0.1-DEMANDA!$M$7)*0.0499999999999998 -> 0.41908315 | H16: =5.15*(0.1+DEMANDA!$M$7)+(1-0.1-DEMANDA!$M$7)*0.15 -> 0.8881663 | I16: =10.15*(0.1+DEMANDA!$M$7)+(1-0.1-DEMANDA!$M$7)*0.15 -> 1.6263326 | X16: =SUMPRODUCT($F16:$W16,$F$4:$W$4) -> 808.53872 | Y16: =SUMPRODUCT($F16:$W16,$F$5:$W$5) -> 3406.9261 | Z16: =SUMPRODUCT($F16:$W16,$F$6:$W$6) -> 7263.0301 | AA16: =SUMPRODUCT($F16:$W16,$F$7:$W$7) -> 13621.718 | AB16: =SUMPRODUCT($F16:$W16,$F$8:$W$8) -> 19846.214 | AC16: =SUMPRODUCT($F16:$W16,$F$9:$W$9) -> 26708.679 | AD16: =SUMPRODUCT($F16:$W16,$F$10:$W$10) -> 32927.608 | AE16: =SUMPRODUCT($F16:$W16,$F$11:$W$11) -> 36962.947 | AF16: =SUMPRODUCT($F16:$W16,$F$12:$W$12) -> 39806.984 | AG16: =SUMPRODUCT($F16:$W16,$F$13:$W$13) -> 42706.572 | AH16: =SUMPRODUCT($F16:$W16,$F$14:$W$14) -> 3558.881
A17: K02 | B17: MP-33B | C17: Polvo ABC 90 (carros y sus recargas) | D17: kg | S17: =25*(0.1+DEMANDA!$M$7)+(1-0.1-DEMANDA!$M$7)*0.75 -> 4.3301066 | T17: =50*(0.1+DEMANDA!$M$7)+(1-0.1-DEMANDA!$M$7)*1.5 -> 8.6602131 | U17: =70*(0.1+DEMANDA!$M$7)+(1-0.1-DEMANDA!$M$7)*2.09999999999999 -> 12.124298 | V17: =100*(0.1+DEMANDA!$M$7)+(1-0.1-DEMANDA!$M$7)*3 -> 17.320426 | X17: =SUMPRODUCT($F17:$W17,$F$4:$W$4) -> 183.83807 | Y17: =SUMPRODUCT($F17:$W17,$F$5:$W$5) -> 872.26004 | Z17: =SUMPRODUCT($F17:$W17,$F$6:$W$6) -> 1895.9379 | AA17: =SUMPRODUCT($F17:$W17,$F$7:$W$7) -> 3410.3858 | AB17: =SUMPRODUCT($F17:$W17,$F$8:$W$8) -> 4908.1696 | AC17: =SUMPRODUCT($F17:$W17,$F$9:$W$9) -> 6518.8385 | AD17: =SUMPRODUCT($F17:$W17,$F$10:$W$10) -> 8028.26 | AE17: =SUMPRODUCT($F17:$W17,$F$11:$W$11) -> 9013.091 | AF17: =SUMPRODUCT($F17:$W17,$F$12:$W$12) -> 9781.8165 | AG17: =SUMPRODUCT($F17:$W17,$F$13:$W$13) -> 10553.016 | AH17: =SUMPRODUCT($F17:$W17,$F$14:$W$14) -> 879.41801
A18: K03 | B18: MP-35 | C18: Polvo BC (recargas) | D18: kg | M18: 5.15 | X18: =SUMPRODUCT($F18:$W18,$F$4:$W$4) -> 11.601163 | Y18: =SUMPRODUCT($F18:$W18,$F$5:$W$5) -> 71.24916 | Z18: =SUMPRODUCT($F18:$W18,$F$6:$W$6) -> 133.22549 | AA18: =SUMPRODUCT($F18:$W18,$F$7:$W$7) -> 239.36284 | AB18: =SUMPRODUCT($F18:$W18,$F$8:$W$8) -> 330.20625 | AC18: =SUMPRODUCT($F18:$W18,$F$9:$W$9) -> 438.50871 | AD18: =SUMPRODUCT($F18:$W18,$F$10:$W$10) -> 552.59235 | AE18: =SUMPRODUCT($F18:$W18,$F$11:$W$11) -> 612.71342 | AF18: =SUMPRODUCT($F18:$W18,$F$12:$W$12) -> 668.10393 | AG18: =SUMPRODUCT($F18:$W18,$F$13:$W$13) -> 725.45714 | AH18: =SUMPRODUCT($F18:$W18,$F$14:$W$14) -> 60.454761
A19: K04 | B19: MP-36 | C19: Polvo clase D (recargas) | D19: kg | R19: 9.15 | X19: =SUMPRODUCT($F19:$W19,$F$4:$W$4) -> 20.611776 | Y19: =SUMPRODUCT($F19:$W19,$F$5:$W$5) -> 126.58831 | Z19: =SUMPRODUCT($F19:$W19,$F$6:$W$6) -> 236.7016 | AA19: =SUMPRODUCT($F19:$W19,$F$7:$W$7) -> 395.722 | AB19: =SUMPRODUCT($F19:$W19,$F$8:$W$8) -> 548.31035 | AC19: =SUMPRODUCT($F19:$W19,$F$9:$W$9) -> 681.3922 | AD19: =SUMPRODUCT($F19:$W19,$F$10:$W$10) -> 875.338 | AE19: =SUMPRODUCT($F19:$W19,$F$11:$W$11) -> 976.69207 | AF19: =SUMPRODUCT($F19:$W19,$F$12:$W$12) -> 1070.8928 | AG19: =SUMPRODUCT($F19:$W19,$F$13:$W$13) -> 1163.0698 | AH19: =SUMPRODUCT($F19:$W19,$F$14:$W$14) -> 96.922484
A20: K05 | B20: MP-37 | C20: CO₂ líquido (recargas) | D20: kg | O20: =2*0.1 -> 0.2 | P20: =5*0.1 -> 0.5 | X20: =SUMPRODUCT($F20:$W20,$F$4:$W$4) -> 44.954771 | Y20: =SUMPRODUCT($F20:$W20,$F$5:$W$5) -> 194.04041 | Z20: =SUMPRODUCT($F20:$W20,$F$6:$W$6) -> 433.93953 | AA20: =SUMPRODUCT($F20:$W20,$F$7:$W$7) -> 804.90814 | AB20: =SUMPRODUCT($F20:$W20,$F$8:$W$8) -> 1161.1197 | AC20: =SUMPRODUCT($F20:$W20,$F$9:$W$9) -> 1545.0412 | AD20: =SUMPRODUCT($F20:$W20,$F$10:$W$10) -> 1900.4702 | AE20: =SUMPRODUCT($F20:$W20,$F$11:$W$11) -> 2120.7473 | AF20: =SUMPRODUCT($F20:$W20,$F$12:$W$12) -> 2296.022 | AG20: =SUMPRODUCT($F20:$W20,$F$13:$W$13) -> 2474.0102 | AH20: =SUMPRODUCT($F20:$W20,$F$14:$W$14) -> 206.16752
A21: K06 | B21: MP-38 | C21: Agente limpio HCFC-123 (recargas) | D21: kg | Q21: =5*0.1 -> 0.5 | X21: =SUMPRODUCT($F21:$W21,$F$4:$W$4) -> 2.7637155 | Y21: =SUMPRODUCT($F21:$W21,$F$5:$W$5) -> 16.414635 | Z21: =SUMPRODUCT($F21:$W21,$F$6:$W$6) -> 33.650008 | AA21: =SUMPRODUCT($F21:$W21,$F$7:$W$7) -> 58.37968 | AB21: =SUMPRODUCT($F21:$W21,$F$8:$W$8) -> 83.67502 | AC21: =SUMPRODUCT($F21:$W21,$F$9:$W$9) -> 109.84025 | AD21: =SUMPRODUCT($F21:$W21,$F$10:$W$10) -> 137.54015 | AE21: =SUMPRODUCT($F21:$W21,$F$11:$W$11) -> 156.014 | AF21: =SUMPRODUCT($F21:$W21,$F$12:$W$12) -> 170.46967 | AG21: =SUMPRODUCT($F21:$W21,$F$13:$W$13) -> 185.03819 | AH21: =SUMPRODUCT($F21:$W21,$F$14:$W$14) -> 15.419849
A22: K07 | B22: MP-40 | C22: Concentrado AFFF 3 % (recargas) | D22: L | K22: =10*0.03 -> 0.3 | L22: =50*0.03 -> 1.5 | X22: =SUMPRODUCT($F22:$W22,$F$4:$W$4) -> 7.3950489 | Y22: =SUMPRODUCT($F22:$W22,$F$5:$W$5) -> 50.457593 | Z22: =SUMPRODUCT($F22:$W22,$F$6:$W$6) -> 99.538969 | AA22: =SUMPRODUCT($F22:$W22,$F$7:$W$7) -> 169.22707 | AB22: =SUMPRODUCT($F22:$W22,$F$8:$W$8) -> 239.34921 | AC22: =SUMPRODUCT($F22:$W22,$F$9:$W$9) -> 308.78136 | AD22: =SUMPRODUCT($F22:$W22,$F$10:$W$10) -> 378.86532 | AE22: =SUMPRODUCT($F22:$W22,$F$11:$W$11) -> 428.44265 | AF22: =SUMPRODUCT($F22:$W22,$F$12:$W$12) -> 466.69779 | AG22: =SUMPRODUCT($F22:$W22,$F$13:$W$13) -> 505.42737 | AH22: =SUMPRODUCT($F22:$W22,$F$14:$W$14) -> 42.118947
A23: K08 | B23: MP-41 | C23: Acetato de potasio Gastro K (recargas) | D23: L | N23: 6.09 | X23: =SUMPRODUCT($F23:$W23,$F$4:$W$4) -> 145.34508 | Y23: =SUMPRODUCT($F23:$W23,$F$5:$W$5) -> 594.83696 | Z23: =SUMPRODUCT($F23:$W23,$F$6:$W$6) -> 1324.2762 | AA23: =SUMPRODUCT($F23:$W23,$F$7:$W$7) -> 2407.9233 | AB23: =SUMPRODUCT($F23:$W23,$F$8:$W$8) -> 3475.664 | AC23: =SUMPRODUCT($F23:$W23,$F$9:$W$9) -> 4605.0796 | AD23: =SUMPRODUCT($F23:$W23,$F$10:$W$10) -> 5664.9272 | AE23: =SUMPRODUCT($F23:$W23,$F$11:$W$11) -> 6340.1693 | AF23: =SUMPRODUCT($F23:$W23,$F$12:$W$12) -> 6857.5574 | AG23: =SUMPRODUCT($F23:$W23,$F$13:$W$13) -> 7383.0131 | AH23: =SUMPRODUCT($F23:$W23,$F$14:$W$14) -> 615.25109
A24: K09 | B24: MP-34 | C24: Nitrógeno seco | D24: m³ | F24: =1.18/3*14/1000 -> 0.0055066667 | G24: =3.5/3*14/1000 -> 0.016333333 | H24: =6/3*14/1000 -> 0.028 | I24: =12.5/3*14/1000 -> 0.058333333 | J24: =32.99/1000 -> 0.03299 | K24: =32.99/1000 -> 0.03299 | L24: =97.81/1000 -> 0.09781 | M24: =3.835/1000 -> 0.003835 | N24: =23.789/1000 -> 0.023789 | Q24: =21.731/1000*0.35 -> 0.00760585 | R24: =46.253/1000 -> 0.046253 | S24: =34.4/3*14/1000 -> 0.16053333 | T24: =61.8/3*14/1000 -> 0.2884 | U24: =96/3*14/1000 -> 0.448 | V24: =121/3*14/1000 -> 0.56466667 | X24: =SUMPRODUCT($F24:$W24,$F$4:$W$4) -> 34.424052 | Y24: =SUMPRODUCT($F24:$W24,$F$5:$W$5) -> 149.16712 | Z24: =SUMPRODUCT($F24:$W24,$F$6:$W$6) -> 321.16577 | AA24: =SUMPRODUCT($F24:$W24,$F$7:$W$7) -> 595.60345 | AB24: =SUMPRODUCT($F24:$W24,$F$8:$W$8) -> 863.83031 | AC24: =SUMPRODUCT($F24:$W24,$F$9:$W$9) -> 1156.5842 | AD24: =SUMPRODUCT($F24:$W24,$F$10:$W$10) -> 1424.6013 | AE24: =SUMPRODUCT($F24:$W24,$F$11:$W$11) -> 1597.2672 | AF24: =SUMPRODUCT($F24:$W24,$F$12:$W$12) -> 1723.946 | AG24: =SUMPRODUCT($F24:$W24,$F$13:$W$13) -> 1852.6022 | AH24: =SUMPRODUCT($F24:$W24,$F$14:$W$14) -> 154.38351
A25: K10 | B25: MP-50/OT | C25: Junta tórica del cuello (recargas, surtido por medida) | D25: u | F25: 1 | G25: 1 | H25: 1 | I25: 1 | J25: 1 | K25: 1 | L25: 1 | M25: 1 | N25: 1 | O25: 0.35 | P25: 0.35 | Q25: 0.35 | R25: 1 | S25: 1 | T25: 1 | U25: 1 | V25: 1 | X25: =SUMPRODUCT($F25:$W25,$F$4:$W$4) -> 1876.5104 | Y25: =SUMPRODUCT($F25:$W25,$F$5:$W$5) -> 8456.6337 | Z25: =SUMPRODUCT($F25:$W25,$F$6:$W$6) -> 16834.445 | AA25: =SUMPRODUCT($F25:$W25,$F$7:$W$7) -> 31206.76 | AB25: =SUMPRODUCT($F25:$W25,$F$8:$W$8) -> 45989.852 | AC25: =SUMPRODUCT($F25:$W25,$F$9:$W$9) -> 62687.02 | AD25: =SUMPRODUCT($F25:$W25,$F$10:$W$10) -> 77908.233 | AE25: =SUMPRODUCT($F25:$W25,$F$11:$W$11) -> 88684.506 | AF25: =SUMPRODUCT($F25:$W25,$F$12:$W$12) -> 95360.295 | AG25: =SUMPRODUCT($F25:$W25,$F$13:$W$13) -> 102177.9 | AH25: =SUMPRODUCT($F25:$W25,$F$14:$W$14) -> 8514.8247
A26: K11 | B26: MP-55 | C26: Conjunto de seguridad de CO₂ (recargas) | D26: u | O26: 0.35 | P26: 0.35 | X26: =SUMPRODUCT($F26:$W26,$F$4:$W$4) -> 58.701392 | Y26: =SUMPRODUCT($F26:$W26,$F$5:$W$5) -> 238.3977 | Z26: =SUMPRODUCT($F26:$W26,$F$6:$W$6) -> 542.79057 | AA26: =SUMPRODUCT($F26:$W26,$F$7:$W$7) -> 1020.4016 | AB26: =SUMPRODUCT($F26:$W26,$F$8:$W$8) -> 1472.7443 | AC26: =SUMPRODUCT($F26:$W26,$F$9:$W$9) -> 1958.738 | AD26: =SUMPRODUCT($F26:$W26,$F$10:$W$10) -> 2402.8414 | AE26: =SUMPRODUCT($F26:$W26,$F$11:$W$11) -> 2670.0918 | AF26: =SUMPRODUCT($F26:$W26,$F$12:$W$12) -> 2886.1322 | AG26: =SUMPRODUCT($F26:$W26,$F$13:$W$13) -> 3105.7701 | AH26: =SUMPRODUCT($F26:$W26,$F$14:$W$14) -> 258.81418
A27: K12 | B27: MP-57 | C27: Marbete del año | D27: u | F27: 1 | G27: 1 | H27: 1 | I27: 1 | J27: 1 | K27: 1 | L27: 1 | M27: 1 | N27: 1 | O27: 1 | P27: 1 | Q27: 1 | R27: 1 | S27: 1 | T27: 1 | U27: 1 | V27: 1 | X27: =SUMPRODUCT($F27:$W27,$F$4:$W$4) -> 1989.1201 | Y27: =SUMPRODUCT($F27:$W27,$F$5:$W$5) -> 8920.7113 | Z27: =SUMPRODUCT($F27:$W27,$F$6:$W$6) -> 17886.23 | AA27: =SUMPRODUCT($F27:$W27,$F$7:$W$7) -> 33177.685 | AB27: =SUMPRODUCT($F27:$W27,$F$8:$W$8) -> 48833.727 | AC27: =SUMPRODUCT($F27:$W27,$F$9:$W$9) -> 66467.468 | AD27: =SUMPRODUCT($F27:$W27,$F$10:$W$10) -> 82549.455 | AE27: =SUMPRODUCT($F27:$W27,$F$11:$W$11) -> 93846.066 | AF27: =SUMPRODUCT($F27:$W27,$F$12:$W$12) -> 100941.87 | AG27: =SUMPRODUCT($F27:$W27,$F$13:$W$13) -> 108186.3 | AH27: =SUMPRODUCT($F27:$W27,$F$14:$W$14) -> 9015.5254
A28: K13 | B28: MP-97 | C28: Precinto del recargador | D28: u | F28: 1 | G28: 1 | H28: 1 | I28: 1 | J28: 1 | K28: 1 | L28: 1 | M28: 1 | N28: 1 | O28: 1 | P28: 1 | Q28: 1 | R28: 1 | S28: 1 | T28: 1 | U28: 1 | V28: 1 | X28: =SUMPRODUCT($F28:$W28,$F$4:$W$4) -> 1989.1201 | Y28: =SUMPRODUCT($F28:$W28,$F$5:$W$5) -> 8920.7113 | Z28: =SUMPRODUCT($F28:$W28,$F$6:$W$6) -> 17886.23 | AA28: =SUMPRODUCT($F28:$W28,$F$7:$W$7) -> 33177.685 | AB28: =SUMPRODUCT($F28:$W28,$F$8:$W$8) -> 48833.727 | AC28: =SUMPRODUCT($F28:$W28,$F$9:$W$9) -> 66467.468 | AD28: =SUMPRODUCT($F28:$W28,$F$10:$W$10) -> 82549.455 | AE28: =SUMPRODUCT($F28:$W28,$F$11:$W$11) -> 93846.066 | AF28: =SUMPRODUCT($F28:$W28,$F$12:$W$12) -> 100941.87 | AG28: =SUMPRODUCT($F28:$W28,$F$13:$W$13) -> 108186.3 | AH28: =SUMPRODUCT($F28:$W28,$F$14:$W$14) -> 9015.5254
A29: K14 | B29: MP-72 | C29: Etiqueta de servicio | D29: u | F29: 1 | G29: 1 | H29: 1 | I29: 1 | J29: 1 | K29: 1 | L29: 1 | M29: 1 | N29: 1 | O29: 1 | P29: 1 | Q29: 1 | R29: 1 | S29: 1 | T29: 1 | U29: 1 | V29: 1 | X29: =SUMPRODUCT($F29:$W29,$F$4:$W$4) -> 1989.1201 | Y29: =SUMPRODUCT($F29:$W29,$F$5:$W$5) -> 8920.7113 | Z29: =SUMPRODUCT($F29:$W29,$F$6:$W$6) -> 17886.23 | AA29: =SUMPRODUCT($F29:$W29,$F$7:$W$7) -> 33177.685 | AB29: =SUMPRODUCT($F29:$W29,$F$8:$W$8) -> 48833.727 | AC29: =SUMPRODUCT($F29:$W29,$F$9:$W$9) -> 66467.468 | AD29: =SUMPRODUCT($F29:$W29,$F$10:$W$10) -> 82549.455 | AE29: =SUMPRODUCT($F29:$W29,$F$11:$W$11) -> 93846.066 | AF29: =SUMPRODUCT($F29:$W29,$F$12:$W$12) -> 100941.87 | AG29: =SUMPRODUCT($F29:$W29,$F$13:$W$13) -> 108186.3 | AH29: =SUMPRODUCT($F29:$W29,$F$14:$W$14) -> 9015.5254
A30: K15 | B30: MP-75 | C30: Estampilla y oblea de recarga (PBA) | D30: u | E30: PBA | F30: 1 | G30: 1 | H30: 1 | I30: 1 | J30: 1 | K30: 1 | L30: 1 | M30: 1 | N30: 1 | O30: 1 | P30: 1 | Q30: 1 | R30: 1 | S30: 1 | T30: 1 | U30: 1 | V30: 1 | X30: =SUMPRODUCT($F30:$W30,$F$4:$W$4)*(1-DEMANDA!D$6) -> 1568.3319 | Y30: =SUMPRODUCT($F30:$W30,$F$5:$W$5)*(1-DEMANDA!E$6) -> 7040.1455 | Z30: =SUMPRODUCT($F30:$W30,$F$6:$W$6)*(1-DEMANDA!F$6) -> 14127.912 | AA30: =SUMPRODUCT($F30:$W30,$F$7:$W$7)*(1-DEMANDA!G$6) -> 26227.168 | AB30: =SUMPRODUCT($F30:$W30,$F$8:$W$8)*(1-DEMANDA!H$6) -> 38630.813 | AC30: =SUMPRODUCT($F30:$W30,$F$9:$W$9)*(1-DEMANDA!I$6) -> 52612.724 | AD30: =SUMPRODUCT($F30:$W30,$F$10:$W$10)*(1-DEMANDA!J$6) -> 65375.418 | AE30: =SUMPRODUCT($F30:$W30,$F$11:$W$11)*(1-DEMANDA!K$6) -> 74349.719 | AF30: =SUMPRODUCT($F30:$W30,$F$12:$W$12)*(1-DEMANDA!L$6) -> 79989.429 | AG30: =SUMPRODUCT($F30:$W30,$F$13:$W$13)*(1-DEMANDA!M$6) -> 85734.565 | AH30: =SUMPRODUCT($F30:$W30,$F$14:$W$14)*(1-DEMANDA!M$6) -> 7144.5471
A31: K16 | B31: MP-76 | C31: Tarjeta de identificación DPS (PBA) | D31: u | E31: PBA | F31: 1 | G31: 1 | H31: 1 | I31: 1 | J31: 1 | K31: 1 | L31: 1 | M31: 1 | N31: 1 | O31: 1 | P31: 1 | Q31: 1 | R31: 1 | S31: 1 | T31: 1 | U31: 1 | V31: 1 | X31: =SUMPRODUCT($F31:$W31,$F$4:$W$4)*(1-DEMANDA!D$6) -> 1568.3319 | Y31: =SUMPRODUCT($F31:$W31,$F$5:$W$5)*(1-DEMANDA!E$6) -> 7040.1455 | Z31: =SUMPRODUCT($F31:$W31,$F$6:$W$6)*(1-DEMANDA!F$6) -> 14127.912 | AA31: =SUMPRODUCT($F31:$W31,$F$7:$W$7)*(1-DEMANDA!G$6) -> 26227.168 | AB31: =SUMPRODUCT($F31:$W31,$F$8:$W$8)*(1-DEMANDA!H$6) -> 38630.813 | AC31: =SUMPRODUCT($F31:$W31,$F$9:$W$9)*(1-DEMANDA!I$6) -> 52612.724 | AD31: =SUMPRODUCT($F31:$W31,$F$10:$W$10)*(1-DEMANDA!J$6) -> 65375.418 | AE31: =SUMPRODUCT($F31:$W31,$F$11:$W$11)*(1-DEMANDA!K$6) -> 74349.719 | AF31: =SUMPRODUCT($F31:$W31,$F$12:$W$12)*(1-DEMANDA!L$6) -> 79989.429 | AG31: =SUMPRODUCT($F31:$W31,$F$13:$W$13)*(1-DEMANDA!M$6) -> 85734.565 | AH31: =SUMPRODUCT($F31:$W31,$F$14:$W$14)*(1-DEMANDA!M$6) -> 7144.5471
A32: K17 | B32: MP-77 | C32: Tarjeta de identificación AGC (CABA) | D32: u | E32: CABA | F32: 1 | G32: 1 | H32: 1 | I32: 1 | J32: 1 | K32: 1 | L32: 1 | M32: 1 | N32: 1 | O32: 1 | P32: 1 | Q32: 1 | R32: 1 | S32: 1 | T32: 1 | U32: 1 | V32: 1 | X32: =SUMPRODUCT($F32:$W32,$F$4:$W$4)*DEMANDA!D$6 -> 420.78823 | Y32: =SUMPRODUCT($F32:$W32,$F$5:$W$5)*DEMANDA!E$6 -> 1880.5658 | Z32: =SUMPRODUCT($F32:$W32,$F$6:$W$6)*DEMANDA!F$6 -> 3758.3176 | AA32: =SUMPRODUCT($F32:$W32,$F$7:$W$7)*DEMANDA!G$6 -> 6950.5174 | AB32: =SUMPRODUCT($F32:$W32,$F$8:$W$8)*DEMANDA!H$6 -> 10202.914 | AC32: =SUMPRODUCT($F32:$W32,$F$9:$W$9)*DEMANDA!I$6 -> 13854.745 | AD32: =SUMPRODUCT($F32:$W32,$F$10:$W$10)*DEMANDA!J$6 -> 17174.037 | AE32: =SUMPRODUCT($F32:$W32,$F$11:$W$11)*DEMANDA!K$6 -> 19496.348 | AF32: =SUMPRODUCT($F32:$W32,$F$12:$W$12)*DEMANDA!L$6 -> 20952.436 | AG32: =SUMPRODUCT($F32:$W32,$F$13:$W$13)*DEMANDA!M$6 -> 22451.74 | AH32: =SUMPRODUCT($F32:$W32,$F$14:$W$14)*DEMANDA!M$6 -> 1870.9784
A33: K18 | B33: MP-65 | C33: Esmalte sintético rojo RAL 3000 (recargas) | D33: L | F33: =0.15*0.0764/8.8 -> 0.0013022727 | G33: =0.15*0.1375/8.8 -> 0.00234375 | H33: =0.15*0.2091/8.8 -> 0.0035642045 | I33: =0.15*0.351/8.8 -> 0.0059829545 | J33: =0.15*0.3646/8.8 -> 0.0062147727 | K33: =0.15*0.3646/8.8 -> 0.0062147727 | L33: =0.15*0.9064/8.8 -> 0.01545 | M33: =0.15*0.2091/8.8 -> 0.0035642045 | N33: =0.15*0.2577/8.8 -> 0.0043926136 | O33: =0.15*0.1366/8.8 -> 0.0023284091 | P33: =0.15*0.2824/8.8 -> 0.0048136364 | Q33: =0.15*0.2091/8.8 -> 0.0035642045 | R33: =0.15*0.351/8.8 -> 0.0059829545 | S33: =0.15*0.626/8.8 -> 0.010670455 | T33: =0.15*0.9064/8.8 -> 0.01545 | U33: =0.15*1.2326/8.8 -> 0.021010227 | V33: =0.15*1.4989/8.8 -> 0.025549432 | X33: =SUMPRODUCT($F33:$W33,$F$4:$W$4) -> 5.146578 | Y33: =SUMPRODUCT($F33:$W33,$F$5:$W$5) -> 22.485387 | Z33: =SUMPRODUCT($F33:$W33,$F$6:$W$6) -> 47.508843 | AA33: =SUMPRODUCT($F33:$W33,$F$7:$W$7) -> 88.198111 | AB33: =SUMPRODUCT($F33:$W33,$F$8:$W$8) -> 128.41084 | AC33: =SUMPRODUCT($F33:$W33,$F$9:$W$9) -> 172.67724 | AD33: =SUMPRODUCT($F33:$W33,$F$10:$W$10) -> 213.18241 | AE33: =SUMPRODUCT($F33:$W33,$F$11:$W$11) -> 239.88111 | AF33: =SUMPRODUCT($F33:$W33,$F$12:$W$12) -> 258.6522 | AG33: =SUMPRODUCT($F33:$W33,$F$13:$W$13) -> 277.76163 | AH33: =SUMPRODUCT($F33:$W33,$F$14:$W$14) -> 23.146803
A34: K19 | B34: MP-82 | C34: Faja amarilla de sustituto | D34: u | W34: 1 | X34: =SUMPRODUCT($F34:$W34,$F$4:$W$4) -> 23.598486 | Y34: =SUMPRODUCT($F34:$W34,$F$5:$W$5) -> 73.956311 | Z34: =SUMPRODUCT($F34:$W34,$F$6:$W$6) -> 100.52859 | AA34: =SUMPRODUCT($F34:$W34,$F$7:$W$7) -> 172.50877 | AB34: =SUMPRODUCT($F34:$W34,$F$8:$W$8) -> 184.73969 | AC34: =SUMPRODUCT($F34:$W34,$F$9:$W$9) -> 213.60946 | AD34: =SUMPRODUCT($F34:$W34,$F$10:$W$10) -> 205.50348 | AE34: =SUMPRODUCT($F34:$W34,$F$11:$W$11) -> 163.46268 | AF34: =SUMPRODUCT($F34:$W34,$F$12:$W$12) -> 125.0384 | AG34: =SUMPRODUCT($F34:$W34,$F$13:$W$13) -> 129.8924 | AH34: =SUMPRODUCT($F34:$W34,$F$14:$W$14) -> 10.824366
A35: K20 | B35: MP-83 | C35: Tarjeta DPS «sustituto habilitado» | D35: u | E35: PBA | W35: 1 | X35: =SUMPRODUCT($F35:$W35,$F$4:$W$4)*(1-DEMANDA!D$6) -> 18.606346 | Y35: =SUMPRODUCT($F35:$W35,$F$5:$W$5)*(1-DEMANDA!E$6) -> 58.365658 | Z35: =SUMPRODUCT($F35:$W35,$F$6:$W$6)*(1-DEMANDA!F$6) -> 79.405169 | AA35: =SUMPRODUCT($F35:$W35,$F$7:$W$7)*(1-DEMANDA!G$6) -> 136.36926 | AB35: =SUMPRODUCT($F35:$W35,$F$8:$W$8)*(1-DEMANDA!H$6) -> 146.14171 | AC35: =SUMPRODUCT($F35:$W35,$F$9:$W$9)*(1-DEMANDA!I$6) -> 169.08385 | AD35: =SUMPRODUCT($F35:$W35,$F$10:$W$10)*(1-DEMANDA!J$6) -> 162.74942 | AE35: =SUMPRODUCT($F35:$W35,$F$11:$W$11)*(1-DEMANDA!K$6) -> 129.50361 | AF35: =SUMPRODUCT($F35:$W35,$F$12:$W$12)*(1-DEMANDA!L$6) -> 99.084261 | AG35: =SUMPRODUCT($F35:$W35,$F$13:$W$13)*(1-DEMANDA!M$6) -> 102.93602 | AH35: =SUMPRODUCT($F35:$W35,$F$14:$W$14)*(1-DEMANDA!M$6) -> 8.578002
A36: K21 | B36: MP-84 | C36: Tarjeta AGC «es sustituto» | D36: u | E36: CABA | W36: 1 | X36: =SUMPRODUCT($F36:$W36,$F$4:$W$4)*DEMANDA!D$6 -> 4.9921394 | Y36: =SUMPRODUCT($F36:$W36,$F$5:$W$5)*DEMANDA!E$6 -> 15.590653 | Z36: =SUMPRODUCT($F36:$W36,$F$6:$W$6)*DEMANDA!F$6 -> 21.123421 | AA36: =SUMPRODUCT($F36:$W36,$F$7:$W$7)*DEMANDA!G$6 -> 36.139507 | AB36: =SUMPRODUCT($F36:$W36,$F$8:$W$8)*DEMANDA!H$6 -> 38.59798 | AC36: =SUMPRODUCT($F36:$W36,$F$9:$W$9)*DEMANDA!I$6 -> 44.52561 | AD36: =SUMPRODUCT($F36:$W36,$F$10:$W$10)*DEMANDA!J$6 -> 42.75406 | AE36: =SUMPRODUCT($F36:$W36,$F$11:$W$11)*DEMANDA!K$6 -> 33.959071 | AF36: =SUMPRODUCT($F36:$W36,$F$12:$W$12)*DEMANDA!L$6 -> 25.954138 | AG36: =SUMPRODUCT($F36:$W36,$F$13:$W$13)*DEMANDA!M$6 -> 26.956373 | AH36: =SUMPRODUCT($F36:$W36,$F$14:$W$14)*DEMANDA!M$6 -> 2.2463644
A37: K22 | B37: MP-85 | C37: Impresos (protocolo de ensayo, remito de préstamo) | D37: u | W37: 1 | X37: =SUMPRODUCT($F37:$W37,$F$4:$W$4) -> 23.598486 | Y37: =SUMPRODUCT($F37:$W37,$F$5:$W$5) -> 73.956311 | Z37: =SUMPRODUCT($F37:$W37,$F$6:$W$6) -> 100.52859 | AA37: =SUMPRODUCT($F37:$W37,$F$7:$W$7) -> 172.50877 | AB37: =SUMPRODUCT($F37:$W37,$F$8:$W$8) -> 184.73969 | AC37: =SUMPRODUCT($F37:$W37,$F$9:$W$9) -> 213.60946 | AD37: =SUMPRODUCT($F37:$W37,$F$10:$W$10) -> 205.50348 | AE37: =SUMPRODUCT($F37:$W37,$F$11:$W$11) -> 163.46268 | AF37: =SUMPRODUCT($F37:$W37,$F$12:$W$12) -> 125.0384 | AG37: =SUMPRODUCT($F37:$W37,$F$13:$W$13) -> 129.8924 | AH37: =SUMPRODUCT($F37:$W37,$F$14:$W$14) -> 10.824366

Sheet REVENDIDOS
A1: REVENDIDOS: consumo por unidad de producto y lo que hay que comprar
A3: Ref. | B3: Código | C3: Material | D3: UM | E3: Destino | F3: Agua 10 l | G3: AFFF 10 l | H3: AFFF 50 l | I3: BC 5 kg | J3: Clase K 6 l | K3: CO₂ 2 kg | L3: CO₂ 5 kg | M3: HCFC 5 kg | N3: Clase D 9 l | O3: 2026 | P3: 2027 | Q3: 2028 | R3: 2029 | S3: 2030 | T3: 2031 | U3: 2032 | V3: 2033 | W3: 2034 | X3: 2035 | Y3: Mes pico 2035
C4: Demanda 2026 | F4: =DEMANDA!D42 -> 176.18353 | G4: =DEMANDA!D43 -> 99.789572 | H4: =DEMANDA!D44 -> 42.931409 | I4: =DEMANDA!D45 -> 28.716868 | J4: =DEMANDA!D46 -> 100.89892 | K4: =DEMANDA!D47 -> 421.98437 | L4: =DEMANDA!D48 -> 286.05401 | M4: =DEMANDA!D49 -> 59.14739 | N4: =DEMANDA!D50 -> 28.716868
C5: Demanda 2027 | F5: =DEMANDA!E42 -> 321.85832 | G5: =DEMANDA!E43 -> 160.18902 | H5: =DEMANDA!E44 -> 68.537322 | I5: =DEMANDA!E45 -> 45.696344 | J5: =DEMANDA!E46 -> 189.77498 | K5: =DEMANDA!E47 -> 772.32062 | L5: =DEMANDA!E48 -> 494.98807 | M5: =DEMANDA!E49 -> 100.56407 | N5: =DEMANDA!E50 -> 45.696344
C6: Demanda 2028 | F6: =DEMANDA!F42 -> 439.27958 | G6: =DEMANDA!F43 -> 194.0195 | H6: =DEMANDA!F44 -> 83.194383 | I6: =DEMANDA!F45 -> 55.275861 | J6: =DEMANDA!F46 -> 250.48567 | K6: =DEMANDA!F47 -> 1066.3637 | L6: =DEMANDA!F48 -> 634.88919 | M6: =DEMANDA!F49 -> 126.84623 | N6: =DEMANDA!F50 -> 55.275861
C7: Demanda 2029 | F7: =DEMANDA!G42 -> 606.54581 | G7: =DEMANDA!G43 -> 248.51536 | H7: =DEMANDA!G44 -> 106.83959 | I7: =DEMANDA!G45 -> 71.125671 | J7: =DEMANDA!G46 -> 350.26997 | K7: =DEMANDA!G47 -> 1474.9633 | L7: =DEMANDA!G48 -> 852.18536 | M7: =DEMANDA!G49 -> 168.43673 | N7: =DEMANDA!G50 -> 71.125671
C8: Demanda 2030 | F8: =DEMANDA!H42 -> 979.22006 | G8: =DEMANDA!H43 -> 361.21734 | H8: =DEMANDA!H44 -> 154.74576 | I8: =DEMANDA!H45 -> 103.25018 | J8: =DEMANDA!H46 -> 548.40703 | K8: =DEMANDA!H47 -> 2394.6449 | L8: =DEMANDA!H48 -> 1303.7149 | M8: =DEMANDA!H49 -> 257.23766 | N8: =DEMANDA!H50 -> 103.25018
C9: Demanda 2031 | F9: =DEMANDA!I42 -> 1374.7435 | G9: =DEMANDA!I43 -> 448.57469 | H9: =DEMANDA!I44 -> 192.30385 | I9: =DEMANDA!I45 -> 128.2937 | J9: =DEMANDA!I46 -> 754.18915 | K9: =DEMANDA!I47 -> 3311.5475 | L9: =DEMANDA!I48 -> 1768.1971 | M9: =DEMANDA!I49 -> 346.79087 | N9: =DEMANDA!I50 -> 128.00591
C10: Demanda 2032 | F10: =DEMANDA!J42 -> 1771.7592 | G10: =DEMANDA!J43 -> 574.67983 | H10: =DEMANDA!J44 -> 246.35097 | I10: =DEMANDA!J45 -> 164.04212 | J10: =DEMANDA!J46 -> 962.19113 | K10: =DEMANDA!J47 -> 4274.1878 | L10: =DEMANDA!J48 -> 2265.7683 | M10: =DEMANDA!J49 -> 445.40399 | N10: =DEMANDA!J50 -> 164.31552
C11: Demanda 2033 | F11: =DEMANDA!K42 -> 2191.7907 | G11: =DEMANDA!K43 -> 712.49398 | H11: =DEMANDA!K44 -> 305.41623 | I11: =DEMANDA!K45 -> 203.69716 | J11: =DEMANDA!K46 -> 1193.0739 | K11: =DEMANDA!K47 -> 5292.3947 | L11: =DEMANDA!K48 -> 2799.5636 | M11: =DEMANDA!K49 -> 551.60391 | N11: =DEMANDA!K50 -> 203.40937
C12: Demanda 2034 | F12: =DEMANDA!L42 -> 2539.2067 | G12: =DEMANDA!L43 -> 836.54819 | H12: =DEMANDA!L44 -> 358.70771 | I12: =DEMANDA!L45 -> 238.94182 | J12: =DEMANDA!L46 -> 1411.3549 | K12: =DEMANDA!L47 -> 6125.2048 | L12: =DEMANDA!L48 -> 3269.3087 | M12: =DEMANDA!L49 -> 644.41787 | N12: =DEMANDA!L50 -> 239.21522
C13: Demanda 2035 | F13: =DEMANDA!M42 -> 2908.135 | G13: =DEMANDA!M43 -> 971.50993 | H13: =DEMANDA!M44 -> 416.43335 | I13: =DEMANDA!M45 -> 277.70377 | J13: =DEMANDA!M46 -> 1650.6033 | K13: =DEMANDA!M47 -> 7005.2774 | L13: =DEMANDA!M48 -> 3776.0178 | M13: =DEMANDA!M49 -> 744.12045 | N13: =DEMANDA!M50 -> 277.41598
C14: Producción del mes pico de cada producto, 2035 | F14: =ESTACIONALIDAD!P46 -> 319.89485 | G14: =ESTACIONALIDAD!P47 -> 106.86609 | H14: =ESTACIONALIDAD!P48 -> 37.479001 | I14: =ESTACIONALIDAD!P49 -> 30.547415 | J14: =ESTACIONALIDAD!P50 -> 181.56636 | K14: =ESTACIONALIDAD!P51 -> 770.58051 | L14: =ESTACIONALIDAD!P52 -> 415.36195 | M14: =ESTACIONALIDAD!P53 -> 81.85325 | N14: =ESTACIONALIDAD!P54 -> 30.515758
C15: CONSUMO POR UNIDAD (cantidad del material por cada producto)
A16: V01 | B16: RV-AGUA_10l | C16: Matafuego Agua 10 l (reventa) | D16: u | F16: 1 | O16: =SUMPRODUCT($F16:$N16,$F$4:$N$4) -> 176.18353 | P16: =SUMPRODUCT($F16:$N16,$F$5:$N$5) -> 321.85832 | Q16: =SUMPRODUCT($F16:$N16,$F$6:$N$6) -> 439.27958 | R16: =SUMPRODUCT($F16:$N16,$F$7:$N$7) -> 606.54581 | S16: =SUMPRODUCT($F16:$N16,$F$8:$N$8) -> 979.22006 | T16: =SUMPRODUCT($F16:$N16,$F$9:$N$9) -> 1374.7435 | U16: =SUMPRODUCT($F16:$N16,$F$10:$N$10) -> 1771.7592 | V16: =SUMPRODUCT($F16:$N16,$F$11:$N$11) -> 2191.7907 | W16: =SUMPRODUCT($F16:$N16,$F$12:$N$12) -> 2539.2067 | X16: =SUMPRODUCT($F16:$N16,$F$13:$N$13) -> 2908.135 | Y16: =SUMPRODUCT($F16:$N16,$F$14:$N$14) -> 319.89485
A17: V02 | B17: RV-AFFF_10l | C17: Matafuego AFFF 10 l (reventa) | D17: u | G17: 1 | O17: =SUMPRODUCT($F17:$N17,$F$4:$N$4) -> 99.789572 | P17: =SUMPRODUCT($F17:$N17,$F$5:$N$5) -> 160.18902 | Q17: =SUMPRODUCT($F17:$N17,$F$6:$N$6) -> 194.0195 | R17: =SUMPRODUCT($F17:$N17,$F$7:$N$7) -> 248.51536 | S17: =SUMPRODUCT($F17:$N17,$F$8:$N$8) -> 361.21734 | T17: =SUMPRODUCT($F17:$N17,$F$9:$N$9) -> 448.57469 | U17: =SUMPRODUCT($F17:$N17,$F$10:$N$10) -> 574.67983 | V17: =SUMPRODUCT($F17:$N17,$F$11:$N$11) -> 712.49398 | W17: =SUMPRODUCT($F17:$N17,$F$12:$N$12) -> 836.54819 | X17: =SUMPRODUCT($F17:$N17,$F$13:$N$13) -> 971.50993 | Y17: =SUMPRODUCT($F17:$N17,$F$14:$N$14) -> 106.86609
A18: V03 | B18: RV-AFFF_50l | C18: Matafuego AFFF 50 l (reventa) | D18: u | H18: 1 | O18: =SUMPRODUCT($F18:$N18,$F$4:$N$4) -> 42.931409 | P18: =SUMPRODUCT($F18:$N18,$F$5:$N$5) -> 68.537322 | Q18: =SUMPRODUCT($F18:$N18,$F$6:$N$6) -> 83.194383 | R18: =SUMPRODUCT($F18:$N18,$F$7:$N$7) -> 106.83959 | S18: =SUMPRODUCT($F18:$N18,$F$8:$N$8) -> 154.74576 | T18: =SUMPRODUCT($F18:$N18,$F$9:$N$9) -> 192.30385 | U18: =SUMPRODUCT($F18:$N18,$F$10:$N$10) -> 246.35097 | V18: =SUMPRODUCT($F18:$N18,$F$11:$N$11) -> 305.41623 | W18: =SUMPRODUCT($F18:$N18,$F$12:$N$12) -> 358.70771 | X18: =SUMPRODUCT($F18:$N18,$F$13:$N$13) -> 416.43335 | Y18: =SUMPRODUCT($F18:$N18,$F$14:$N$14) -> 37.479001
A19: V04 | B19: RV-BC_5kg | C19: Matafuego BC 5 kg (reventa) | D19: u | I19: 1 | O19: =SUMPRODUCT($F19:$N19,$F$4:$N$4) -> 28.716868 | P19: =SUMPRODUCT($F19:$N19,$F$5:$N$5) -> 45.696344 | Q19: =SUMPRODUCT($F19:$N19,$F$6:$N$6) -> 55.275861 | R19: =SUMPRODUCT($F19:$N19,$F$7:$N$7) -> 71.125671 | S19: =SUMPRODUCT($F19:$N19,$F$8:$N$8) -> 103.25018 | T19: =SUMPRODUCT($F19:$N19,$F$9:$N$9) -> 128.2937 | U19: =SUMPRODUCT($F19:$N19,$F$10:$N$10) -> 164.04212 | V19: =SUMPRODUCT($F19:$N19,$F$11:$N$11) -> 203.69716 | W19: =SUMPRODUCT($F19:$N19,$F$12:$N$12) -> 238.94182 | X19: =SUMPRODUCT($F19:$N19,$F$13:$N$13) -> 277.70377 | Y19: =SUMPRODUCT($F19:$N19,$F$14:$N$14) -> 30.547415
A20: V05 | B20: RV-SALESK_6l | C20: Matafuego Clase K 6 l (reventa) | D20: u | J20: 1 | O20: =SUMPRODUCT($F20:$N20,$F$4:$N$4) -> 100.89892 | P20: =SUMPRODUCT($F20:$N20,$F$5:$N$5) -> 189.77498 | Q20: =SUMPRODUCT($F20:$N20,$F$6:$N$6) -> 250.48567 | R20: =SUMPRODUCT($F20:$N20,$F$7:$N$7) -> 350.26997 | S20: =SUMPRODUCT($F20:$N20,$F$8:$N$8) -> 548.40703 | T20: =SUMPRODUCT($F20:$N20,$F$9:$N$9) -> 754.18915 | U20: =SUMPRODUCT($F20:$N20,$F$10:$N$10) -> 962.19113 | V20: =SUMPRODUCT($F20:$N20,$F$11:$N$11) -> 1193.0739 | W20: =SUMPRODUCT($F20:$N20,$F$12:$N$12) -> 1411.3549 | X20: =SUMPRODUCT($F20:$N20,$F$13:$N$13) -> 1650.6033 | Y20: =SUMPRODUCT($F20:$N20,$F$14:$N$14) -> 181.56636
A21: V06 | B21: RV-CO2_2kg | C21: Matafuego CO₂ 2 kg (reventa) | D21: u | K21: 1 | O21: =SUMPRODUCT($F21:$N21,$F$4:$N$4) -> 421.98437 | P21: =SUMPRODUCT($F21:$N21,$F$5:$N$5) -> 772.32062 | Q21: =SUMPRODUCT($F21:$N21,$F$6:$N$6) -> 1066.3637 | R21: =SUMPRODUCT($F21:$N21,$F$7:$N$7) -> 1474.9633 | S21: =SUMPRODUCT($F21:$N21,$F$8:$N$8) -> 2394.6449 | T21: =SUMPRODUCT($F21:$N21,$F$9:$N$9) -> 3311.5475 | U21: =SUMPRODUCT($F21:$N21,$F$10:$N$10) -> 4274.1878 | V21: =SUMPRODUCT($F21:$N21,$F$11:$N$11) -> 5292.3947 | W21: =SUMPRODUCT($F21:$N21,$F$12:$N$12) -> 6125.2048 | X21: =SUMPRODUCT($F21:$N21,$F$13:$N$13) -> 7005.2774 | Y21: =SUMPRODUCT($F21:$N21,$F$14:$N$14) -> 770.58051
A22: V07 | B22: RV-CO2_5kg | C22: Matafuego CO₂ 5 kg (reventa) | D22: u | L22: 1 | O22: =SUMPRODUCT($F22:$N22,$F$4:$N$4) -> 286.05401 | P22: =SUMPRODUCT($F22:$N22,$F$5:$N$5) -> 494.98807 | Q22: =SUMPRODUCT($F22:$N22,$F$6:$N$6) -> 634.88919 | R22: =SUMPRODUCT($F22:$N22,$F$7:$N$7) -> 852.18536 | S22: =SUMPRODUCT($F22:$N22,$F$8:$N$8) -> 1303.7149 | T22: =SUMPRODUCT($F22:$N22,$F$9:$N$9) -> 1768.1971 | U22: =SUMPRODUCT($F22:$N22,$F$10:$N$10) -> 2265.7683 | V22: =SUMPRODUCT($F22:$N22,$F$11:$N$11) -> 2799.5636 | W22: =SUMPRODUCT($F22:$N22,$F$12:$N$12) -> 3269.3087 | X22: =SUMPRODUCT($F22:$N22,$F$13:$N$13) -> 3776.0178 | Y22: =SUMPRODUCT($F22:$N22,$F$14:$N$14) -> 415.36195
A23: V08 | B23: RV-HCFC-HFC_5kg | C23: Matafuego HCFC 5 kg (reventa) | D23: u | M23: 1 | O23: =SUMPRODUCT($F23:$N23,$F$4:$N$4) -> 59.14739 | P23: =SUMPRODUCT($F23:$N23,$F$5:$N$5) -> 100.56407 | Q23: =SUMPRODUCT($F23:$N23,$F$6:$N$6) -> 126.84623 | R23: =SUMPRODUCT($F23:$N23,$F$7:$N$7) -> 168.43673 | S23: =SUMPRODUCT($F23:$N23,$F$8:$N$8) -> 257.23766 | T23: =SUMPRODUCT($F23:$N23,$F$9:$N$9) -> 346.79087 | U23: =SUMPRODUCT($F23:$N23,$F$10:$N$10) -> 445.40399 | V23: =SUMPRODUCT($F23:$N23,$F$11:$N$11) -> 551.60391 | W23: =SUMPRODUCT($F23:$N23,$F$12:$N$12) -> 644.41787 | X23: =SUMPRODUCT($F23:$N23,$F$13:$N$13) -> 744.12045 | Y23: =SUMPRODUCT($F23:$N23,$F$14:$N$14) -> 81.85325
A24: V09 | B24: RV-CLASED_9l | C24: Matafuego Clase D 9 l (reventa) | D24: u | N24: 1 | O24: =SUMPRODUCT($F24:$N24,$F$4:$N$4) -> 28.716868 | P24: =SUMPRODUCT($F24:$N24,$F$5:$N$5) -> 45.696344 | Q24: =SUMPRODUCT($F24:$N24,$F$6:$N$6) -> 55.275861 | R24: =SUMPRODUCT($F24:$N24,$F$7:$N$7) -> 71.125671 | S24: =SUMPRODUCT($F24:$N24,$F$8:$N$8) -> 103.25018 | T24: =SUMPRODUCT($F24:$N24,$F$9:$N$9) -> 128.00591 | U24: =SUMPRODUCT($F24:$N24,$F$10:$N$10) -> 164.31552 | V24: =SUMPRODUCT($F24:$N24,$F$11:$N$11) -> 203.40937 | W24: =SUMPRODUCT($F24:$N24,$F$12:$N$12) -> 239.21522 | X24: =SUMPRODUCT($F24:$N24,$F$13:$N$13) -> 277.41598 | Y24: =SUMPRODUCT($F24:$N24,$F$14:$N$14) -> 30.515758
A25: V10 | B25: MP-77 | C25: Tarjeta de identificación AGC (CABA) | D25: u | E25: CABA | F25: 1 | G25: 1 | H25: 1 | I25: 1 | J25: 1 | K25: 1 | L25: 1 | M25: 1 | N25: 1 | O25: =SUMPRODUCT($F25:$N25,$F$4:$N$4)*DEMANDA!D$5 -> 290.14093 | P25: =SUMPRODUCT($F25:$N25,$F$5:$N$5)*DEMANDA!E$5 -> 512.65509 | Q25: =SUMPRODUCT($F25:$N25,$F$6:$N$6)*DEMANDA!F$5 -> 677.1853 | R25: =SUMPRODUCT($F25:$N25,$F$7:$N$7)*DEMANDA!G$5 -> 920.84627 | S25: =SUMPRODUCT($F25:$N25,$F$8:$N$8)*DEMANDA!H$5 -> 1447.7217 | T25: =SUMPRODUCT($F25:$N25,$F$9:$N$9)*DEMANDA!I$5 -> 1974.2722 | U25: =SUMPRODUCT($F25:$N25,$F$10:$N$10)*DEMANDA!J$5 -> 2543.0644 | V25: =SUMPRODUCT($F25:$N25,$F$11:$N$11)*DEMANDA!K$5 -> 3155.3957 | W25: =SUMPRODUCT($F25:$N25,$F$12:$N$12)*DEMANDA!L$5 -> 3685.0873 | X25: =SUMPRODUCT($F25:$N25,$F$13:$N$13)*DEMANDA!M$5 -> 4258.3021 | Y25: =SUMPRODUCT($F25:$N25,$F$14:$N$14)*DEMANDA!M$5 -> 466.44587

Sheet CONSOLIDADO
A1: CONSOLIDADO: lo que hay que comprar de cada material (las cuatro líneas)
A3: Código | B3: Material | C3: UM | D3: Manuales 2035 | E3: Rodantes 2035 | F3: Recargas 2035 | G3: Revendidos 2035 | H3: 2026 | I3: 2027 | J3: 2028 | K3: 2029 | L3: 2030 | M3: 2031 | N3: 2032 | O3: 2033 | P3: 2034 | Q3: 2035 | R3: Mes pico 2035
A4: MP-01 | B4: Caño c/costura Ø76,2 × 1,25 × 6 m (cuerpo 1 kg) | C4: barra | D4: =SUMIF(MANUALES!$B$16:$B$72,$A4,MANUALES!W$16:W$72) -> 8809.593 | E4: =SUMIF(RODANTES!$B$16:$B$72,$A4,RODANTES!W$16:W$72) -> 0 | F4: =SUMIF(RECARGAS!$B$16:$B$37,$A4,RECARGAS!AG$16:AG$37) -> 0 | G4: =SUMIF(REVENDIDOS!$B$16:$B$25,$A4,REVENDIDOS!X$16:X$25) -> 0 | H4: =SUMIF(MANUALES!$B$16:$B$72,$A4,MANUALES!N$16:N$72)+SUMIF(RODANTES!$B$16:$B$72,$A4,RODANTES!N$16:N$72)+SUMIF(RECARGAS!$B$16:$B$37,$A4,RECARGAS!X$16:X$37)+SUMIF(REVENDIDOS!$B$16:$B$25,$A4,REVENDIDOS!O$16:O$25) -> 181.6842 | I4: =SUMIF(MANUALES!$B$16:$B$72,$A4,MANUALES!O$16:O$72)+SUMIF(RODANTES!$B$16:$B$72,$A4,RODANTES!O$16:O$72)+SUMIF(RECARGAS!$B$16:$B$37,$A4,RECARGAS!Y$16:Y$37)+SUMIF(REVENDIDOS!$B$16:$B$25,$A4,REVENDIDOS!P$16:P$25) -> 260.75235 | J4: =SUMIF(MANUALES!$B$16:$B$72,$A4,MANUALES!P$16:P$72)+SUMIF(RODANTES!$B$16:$B$72,$A4,RODANTES!P$16:P$72)+SUMIF(RECARGAS!$B$16:$B$37,$A4,RECARGAS!Z$16:Z$37)+SUMIF(REVENDIDOS!$B$16:$B$25,$A4,REVENDIDOS!Q$16:Q$25) -> 631.0499 | K4: =SUMIF(MANUALES!$B$16:$B$72,$A4,MANUALES!Q$16:Q$72)+SUMIF(RODANTES!$B$16:$B$72,$A4,RODANTES!Q$16:Q$72)+SUMIF(RECARGAS!$B$16:$B$37,$A4,RECARGAS!AA$16:AA$37)+SUMIF(REVENDIDOS!$B$16:$B$25,$A4,REVENDIDOS!R$16:R$25) -> 1528.7798 | L4: =SUMIF(MANUALES!$B$16:$B$72,$A4,MANUALES!R$16:R$72)+SUMIF(RODANTES!$B$16:$B$72,$A4,RODANTES!R$16:R$72)+SUMIF(RECARGAS!$B$16:$B$37,$A4,RECARGAS!AB$16:AB$37)+SUMIF(REVENDIDOS!$B$16:$B$25,$A4,REVENDIDOS!S$16:S$25) -> 2700.671 | M4: =SUMIF(MANUALES!$B$16:$B$72,$A4,MANUALES!S$16:S$72)+SUMIF(RODANTES!$B$16:$B$72,$A4,RODANTES!S$16:S$72)+SUMIF(RECARGAS!$B$16:$B$37,$A4,RECARGAS!AC$16:AC$37)+SUMIF(REVENDIDOS!$B$16:$B$25,$A4,REVENDIDOS!T$16:T$25) -> 3795.6719 | N4: =SUMIF(MANUALES!$B$16:$B$72,$A4,MANUALES!T$16:T$72)+SUMIF(RODANTES!$B$16:$B$72,$A4,RODANTES!T$16:T$72)+SUMIF(RECARGAS!$B$16:$B$37,$A4,RECARGAS!AD$16:AD$37)+SUMIF(REVENDIDOS!$B$16:$B$25,$A4,REVENDIDOS!U$16:U$25) -> 5290.1371 | O4: =SUMIF(MANUALES!$B$16:$B$72,$A4,MANUALES!U$16:U$72)+SUMIF(RODANTES!$B$16:$B$72,$A4,RODANTES!U$16:U$72)+SUMIF(RECARGAS!$B$16:$B$37,$A4,RECARGAS!AE$16:AE$37)+SUMIF(REVENDIDOS!$B$16:$B$25,$A4,REVENDIDOS!V$16:V$25) -> 6788.3947 | ... R4: =SUMIF(MANUALES!$B$16:$B$72,$A4,MANUALES!X$16:X$72)+SUMIF(RODANTES!$B$16:$B$72,$A4,RODANTES!X$16:X$72)+SUMIF(RECARGAS!$B$16:$B$37,$A4,RECARGAS!AH$16:AH$37)+SUMIF(REVENDIDOS!$B$16:$B$25,$A4,REVENDIDOS!Y$16:Y$25) -> 1057.1512
A5: MP-02 | B5: Hoja LAF 1,25 × 1220 × 2440 mm | C5: hoja | D5: =SUMIF(MANUALES!$B$16:$B$72,$A5,MANUALES!W$16:W$72) -> 521.99476 | E5: =SUMIF(RODANTES!$B$16:$B$72,$A5,RODANTES!W$16:W$72) -> 0 | F5: =SUMIF(RECARGAS!$B$16:$B$37,$A5,RECARGAS!AG$16:AG$37) -> 0 | G5: =SUMIF(REVENDIDOS!$B$16:$B$25,$A5,REVENDIDOS!X$16:X$25) -> 0 | H5: =SUMIF(MANUALES!$B$16:$B$72,$A5,MANUALES!N$16:N$72)+SUMIF(RODANTES!$B$16:$B$72,$A5,RODANTES!N$16:N$72)+SUMIF(RECARGAS!$B$16:$B$37,$A5,RECARGAS!X$16:X$37)+SUMIF(REVENDIDOS!$B$16:$B$25,$A5,REVENDIDOS!O$16:O$25) -> 10.92705 | I5: =SUMIF(MANUALES!$B$16:$B$72,$A5,MANUALES!O$16:O$72)+SUMIF(RODANTES!$B$16:$B$72,$A5,RODANTES!O$16:O$72)+SUMIF(RECARGAS!$B$16:$B$37,$A5,RECARGAS!Y$16:Y$37)+SUMIF(REVENDIDOS!$B$16:$B$25,$A5,REVENDIDOS!P$16:P$25) -> 26.286202 | J5: =SUMIF(MANUALES!$B$16:$B$72,$A5,MANUALES!P$16:P$72)+SUMIF(RODANTES!$B$16:$B$72,$A5,RODANTES!P$16:P$72)+SUMIF(RECARGAS!$B$16:$B$37,$A5,RECARGAS!Z$16:Z$37)+SUMIF(REVENDIDOS!$B$16:$B$25,$A5,REVENDIDOS!Q$16:Q$25) -> 47.646965 | K5: =SUMIF(MANUALES!$B$16:$B$72,$A5,MANUALES!Q$16:Q$72)+SUMIF(RODANTES!$B$16:$B$72,$A5,RODANTES!Q$16:Q$72)+SUMIF(RECARGAS!$B$16:$B$37,$A5,RECARGAS!AA$16:AA$37)+SUMIF(REVENDIDOS!$B$16:$B$25,$A5,REVENDIDOS!R$16:R$25) -> 94.238451 | L5: =SUMIF(MANUALES!$B$16:$B$72,$A5,MANUALES!R$16:R$72)+SUMIF(RODANTES!$B$16:$B$72,$A5,RODANTES!R$16:R$72)+SUMIF(RECARGAS!$B$16:$B$37,$A5,RECARGAS!AB$16:AB$37)+SUMIF(REVENDIDOS!$B$16:$B$25,$A5,REVENDIDOS!S$16:S$25) -> 157.24547 | M5: =SUMIF(MANUALES!$B$16:$B$72,$A5,MANUALES!S$16:S$72)+SUMIF(RODANTES!$B$16:$B$72,$A5,RODANTES!S$16:S$72)+SUMIF(RECARGAS!$B$16:$B$37,$A5,RECARGAS!AC$16:AC$37)+SUMIF(REVENDIDOS!$B$16:$B$25,$A5,REVENDIDOS!T$16:T$25) -> 224.29148 | N5: =SUMIF(MANUALES!$B$16:$B$72,$A5,MANUALES!T$16:T$72)+SUMIF(RODANTES!$B$16:$B$72,$A5,RODANTES!T$16:T$72)+SUMIF(RECARGAS!$B$16:$B$37,$A5,RECARGAS!AD$16:AD$37)+SUMIF(REVENDIDOS!$B$16:$B$25,$A5,REVENDIDOS!U$16:U$25) -> 298.71539 | O5: =SUMIF(MANUALES!$B$16:$B$72,$A5,MANUALES!U$16:U$72)+SUMIF(RODANTES!$B$16:$B$72,$A5,RODANTES!U$16:U$72)+SUMIF(RECARGAS!$B$16:$B$37,$A5,RECARGAS!AE$16:AE$37)+SUMIF(REVENDIDOS!$B$16:$B$25,$A5,REVENDIDOS!V$16:V$25) -> 378.78913 | ... R5: =SUMIF(MANUALES!$B$16:$B$72,$A5,MANUALES!X$16:X$72)+SUMIF(RODANTES!$B$16:$B$72,$A5,RODANTES!X$16:X$72)+SUMIF(RECARGAS!$B$16:$B$37,$A5,RECARGAS!AH$16:AH$37)+SUMIF(REVENDIDOS!$B$16:$B$25,$A5,REVENDIDOS!Y$16:Y$25) -> 57.419423
A6: MP-03 | B6: Hoja LAF 1,6 × 1000 × 2000 mm | C6: hoja | D6: =SUMIF(MANUALES!$B$16:$B$72,$A6,MANUALES!W$16:W$72) -> 5445.3142 | E6: =SUMIF(RODANTES!$B$16:$B$72,$A6,RODANTES!W$16:W$72) -> 0 | F6: =SUMIF(RECARGAS!$B$16:$B$37,$A6,RECARGAS!AG$16:AG$37) -> 0 | G6: =SUMIF(REVENDIDOS!$B$16:$B$25,$A6,REVENDIDOS!X$16:X$25) -> 0 | H6: =SUMIF(MANUALES!$B$16:$B$72,$A6,MANUALES!N$16:N$72)+SUMIF(RODANTES!$B$16:$B$72,$A6,RODANTES!N$16:N$72)+SUMIF(RECARGAS!$B$16:$B$37,$A6,RECARGAS!X$16:X$37)+SUMIF(REVENDIDOS!$B$16:$B$25,$A6,REVENDIDOS!O$16:O$25) -> 227.3253 | I6: =SUMIF(MANUALES!$B$16:$B$72,$A6,MANUALES!O$16:O$72)+SUMIF(RODANTES!$B$16:$B$72,$A6,RODANTES!O$16:O$72)+SUMIF(RECARGAS!$B$16:$B$37,$A6,RECARGAS!Y$16:Y$37)+SUMIF(REVENDIDOS!$B$16:$B$25,$A6,REVENDIDOS!P$16:P$25) -> 457.40922 | J6: =SUMIF(MANUALES!$B$16:$B$72,$A6,MANUALES!P$16:P$72)+SUMIF(RODANTES!$B$16:$B$72,$A6,RODANTES!P$16:P$72)+SUMIF(RECARGAS!$B$16:$B$37,$A6,RECARGAS!Z$16:Z$37)+SUMIF(REVENDIDOS!$B$16:$B$25,$A6,REVENDIDOS!Q$16:Q$25) -> 723.78212 | K6: =SUMIF(MANUALES!$B$16:$B$72,$A6,MANUALES!Q$16:Q$72)+SUMIF(RODANTES!$B$16:$B$72,$A6,RODANTES!Q$16:Q$72)+SUMIF(RECARGAS!$B$16:$B$37,$A6,RECARGAS!AA$16:AA$37)+SUMIF(REVENDIDOS!$B$16:$B$25,$A6,REVENDIDOS!R$16:R$25) -> 1297.7423 | L6: =SUMIF(MANUALES!$B$16:$B$72,$A6,MANUALES!R$16:R$72)+SUMIF(RODANTES!$B$16:$B$72,$A6,RODANTES!R$16:R$72)+SUMIF(RECARGAS!$B$16:$B$37,$A6,RECARGAS!AB$16:AB$37)+SUMIF(REVENDIDOS!$B$16:$B$25,$A6,REVENDIDOS!S$16:S$25) -> 2002.9893 | M6: =SUMIF(MANUALES!$B$16:$B$72,$A6,MANUALES!S$16:S$72)+SUMIF(RODANTES!$B$16:$B$72,$A6,RODANTES!S$16:S$72)+SUMIF(RECARGAS!$B$16:$B$37,$A6,RECARGAS!AC$16:AC$37)+SUMIF(REVENDIDOS!$B$16:$B$25,$A6,REVENDIDOS!T$16:T$25) -> 2714.2717 | N6: =SUMIF(MANUALES!$B$16:$B$72,$A6,MANUALES!T$16:T$72)+SUMIF(RODANTES!$B$16:$B$72,$A6,RODANTES!T$16:T$72)+SUMIF(RECARGAS!$B$16:$B$37,$A6,RECARGAS!AD$16:AD$37)+SUMIF(REVENDIDOS!$B$16:$B$25,$A6,REVENDIDOS!U$16:U$25) -> 3516.0902 | O6: =SUMIF(MANUALES!$B$16:$B$72,$A6,MANUALES!U$16:U$72)+SUMIF(RODANTES!$B$16:$B$72,$A6,RODANTES!U$16:U$72)+SUMIF(RECARGAS!$B$16:$B$37,$A6,RECARGAS!AE$16:AE$37)+SUMIF(REVENDIDOS!$B$16:$B$25,$A6,REVENDIDOS!V$16:V$25) -> 4273.7782 | ... R6: =SUMIF(MANUALES!$B$16:$B$72,$A6,MANUALES!X$16:X$72)+SUMIF(RODANTES!$B$16:$B$72,$A6,RODANTES!X$16:X$72)+SUMIF(RECARGAS!$B$16:$B$37,$A6,RECARGAS!AH$16:AH$37)+SUMIF(REVENDIDOS!$B$16:$B$25,$A6,REVENDIDOS!Y$16:Y$25) -> 598.98456
A7: MP-04 | B7: Hoja LAF 2,0 × 1500 × 3000 mm | C7: hoja | D7: =SUMIF(MANUALES!$B$16:$B$72,$A7,MANUALES!W$16:W$72) -> 256.92513 | E7: =SUMIF(RODANTES!$B$16:$B$72,$A7,RODANTES!W$16:W$72) -> 0 | F7: =SUMIF(RECARGAS!$B$16:$B$37,$A7,RECARGAS!AG$16:AG$37) -> 0 | G7: =SUMIF(REVENDIDOS!$B$16:$B$25,$A7,REVENDIDOS!X$16:X$25) -> 0 | H7: =SUMIF(MANUALES!$B$16:$B$72,$A7,MANUALES!N$16:N$72)+SUMIF(RODANTES!$B$16:$B$72,$A7,RODANTES!N$16:N$72)+SUMIF(RECARGAS!$B$16:$B$37,$A7,RECARGAS!X$16:X$37)+SUMIF(REVENDIDOS!$B$16:$B$25,$A7,REVENDIDOS!O$16:O$25) -> 6.1605836 | I7: =SUMIF(MANUALES!$B$16:$B$72,$A7,MANUALES!O$16:O$72)+SUMIF(RODANTES!$B$16:$B$72,$A7,RODANTES!O$16:O$72)+SUMIF(RECARGAS!$B$16:$B$37,$A7,RECARGAS!Y$16:Y$37)+SUMIF(REVENDIDOS!$B$16:$B$25,$A7,REVENDIDOS!P$16:P$25) -> 11.875962 | J7: =SUMIF(MANUALES!$B$16:$B$72,$A7,MANUALES!P$16:P$72)+SUMIF(RODANTES!$B$16:$B$72,$A7,RODANTES!P$16:P$72)+SUMIF(RECARGAS!$B$16:$B$37,$A7,RECARGAS!Z$16:Z$37)+SUMIF(REVENDIDOS!$B$16:$B$25,$A7,REVENDIDOS!Q$16:Q$25) -> 23.031015 | K7: =SUMIF(MANUALES!$B$16:$B$72,$A7,MANUALES!Q$16:Q$72)+SUMIF(RODANTES!$B$16:$B$72,$A7,RODANTES!Q$16:Q$72)+SUMIF(RECARGAS!$B$16:$B$37,$A7,RECARGAS!AA$16:AA$37)+SUMIF(REVENDIDOS!$B$16:$B$25,$A7,REVENDIDOS!R$16:R$25) -> 45.071402 | L7: =SUMIF(MANUALES!$B$16:$B$72,$A7,MANUALES!R$16:R$72)+SUMIF(RODANTES!$B$16:$B$72,$A7,RODANTES!R$16:R$72)+SUMIF(RECARGAS!$B$16:$B$37,$A7,RECARGAS!AB$16:AB$37)+SUMIF(REVENDIDOS!$B$16:$B$25,$A7,REVENDIDOS!S$16:S$25) -> 79.26832 | M7: =SUMIF(MANUALES!$B$16:$B$72,$A7,MANUALES!S$16:S$72)+SUMIF(RODANTES!$B$16:$B$72,$A7,RODANTES!S$16:S$72)+SUMIF(RECARGAS!$B$16:$B$37,$A7,RECARGAS!AC$16:AC$37)+SUMIF(REVENDIDOS!$B$16:$B$25,$A7,REVENDIDOS!T$16:T$25) -> 114.80112 | N7: =SUMIF(MANUALES!$B$16:$B$72,$A7,MANUALES!T$16:T$72)+SUMIF(RODANTES!$B$16:$B$72,$A7,RODANTES!T$16:T$72)+SUMIF(RECARGAS!$B$16:$B$37,$A7,RECARGAS!AD$16:AD$37)+SUMIF(REVENDIDOS!$B$16:$B$25,$A7,REVENDIDOS!U$16:U$25) -> 155.05033 | O7: =SUMIF(MANUALES!$B$16:$B$72,$A7,MANUALES!U$16:U$72)+SUMIF(RODANTES!$B$16:$B$72,$A7,RODANTES!U$16:U$72)+SUMIF(RECARGAS!$B$16:$B$37,$A7,RECARGAS!AE$16:AE$37)+SUMIF(REVENDIDOS!$B$16:$B$25,$A7,REVENDIDOS!V$16:V$25) -> 196.17451 | ... R7: =SUMIF(MANUALES!$B$16:$B$72,$A7,MANUALES!X$16:X$72)+SUMIF(RODANTES!$B$16:$B$72,$A7,RODANTES!X$16:X$72)+SUMIF(RECARGAS!$B$16:$B$37,$A7,RECARGAS!AH$16:AH$37)+SUMIF(REVENDIDOS!$B$16:$B$25,$A7,REVENDIDOS!Y$16:Y$25) -> 28.261764
A8: MP-05 | B8: Fleje LAF 0,9 × 114 mm (cúpula 1 kg) | C8: kg | D8: =SUMIF(MANUALES!$B$16:$B$72,$A8,MANUALES!W$16:W$72) -> 15992.884 | E8: =SUMIF(RODANTES!$B$16:$B$72,$A8,RODANTES!W$16:W$72) -> 0 | F8: =SUMIF(RECARGAS!$B$16:$B$37,$A8,RECARGAS!AG$16:AG$37) -> 0 | G8: =SUMIF(REVENDIDOS!$B$16:$B$25,$A8,REVENDIDOS!X$16:X$25) -> 0 | H8: =SUMIF(MANUALES!$B$16:$B$72,$A8,MANUALES!N$16:N$72)+SUMIF(RODANTES!$B$16:$B$72,$A8,RODANTES!N$16:N$72)+SUMIF(RECARGAS!$B$16:$B$37,$A8,RECARGAS!X$16:X$37)+SUMIF(REVENDIDOS!$B$16:$B$25,$A8,REVENDIDOS!O$16:O$25) -> 329.82843 | I8: =SUMIF(MANUALES!$B$16:$B$72,$A8,MANUALES!O$16:O$72)+SUMIF(RODANTES!$B$16:$B$72,$A8,RODANTES!O$16:O$72)+SUMIF(RECARGAS!$B$16:$B$37,$A8,RECARGAS!Y$16:Y$37)+SUMIF(REVENDIDOS!$B$16:$B$25,$A8,REVENDIDOS!P$16:P$25) -> 473.36828 | J8: =SUMIF(MANUALES!$B$16:$B$72,$A8,MANUALES!P$16:P$72)+SUMIF(RODANTES!$B$16:$B$72,$A8,RODANTES!P$16:P$72)+SUMIF(RECARGAS!$B$16:$B$37,$A8,RECARGAS!Z$16:Z$37)+SUMIF(REVENDIDOS!$B$16:$B$25,$A8,REVENDIDOS!Q$16:Q$25) -> 1145.6043 | K8: =SUMIF(MANUALES!$B$16:$B$72,$A8,MANUALES!Q$16:Q$72)+SUMIF(RODANTES!$B$16:$B$72,$A8,RODANTES!Q$16:Q$72)+SUMIF(RECARGAS!$B$16:$B$37,$A8,RECARGAS!AA$16:AA$37)+SUMIF(REVENDIDOS!$B$16:$B$25,$A8,REVENDIDOS!R$16:R$25) -> 2775.3379 | L8: =SUMIF(MANUALES!$B$16:$B$72,$A8,MANUALES!R$16:R$72)+SUMIF(RODANTES!$B$16:$B$72,$A8,RODANTES!R$16:R$72)+SUMIF(RECARGAS!$B$16:$B$37,$A8,RECARGAS!AB$16:AB$37)+SUMIF(REVENDIDOS!$B$16:$B$25,$A8,REVENDIDOS!S$16:S$25) -> 4902.7823 | M8: =SUMIF(MANUALES!$B$16:$B$72,$A8,MANUALES!S$16:S$72)+SUMIF(RODANTES!$B$16:$B$72,$A8,RODANTES!S$16:S$72)+SUMIF(RECARGAS!$B$16:$B$37,$A8,RECARGAS!AC$16:AC$37)+SUMIF(REVENDIDOS!$B$16:$B$25,$A8,REVENDIDOS!T$16:T$25) -> 6890.6405 | N8: =SUMIF(MANUALES!$B$16:$B$72,$A8,MANUALES!T$16:T$72)+SUMIF(RODANTES!$B$16:$B$72,$A8,RODANTES!T$16:T$72)+SUMIF(RECARGAS!$B$16:$B$37,$A8,RECARGAS!AD$16:AD$37)+SUMIF(REVENDIDOS!$B$16:$B$25,$A8,REVENDIDOS!U$16:U$25) -> 9603.6839 | O8: =SUMIF(MANUALES!$B$16:$B$72,$A8,MANUALES!U$16:U$72)+SUMIF(RODANTES!$B$16:$B$72,$A8,RODANTES!U$16:U$72)+SUMIF(RECARGAS!$B$16:$B$37,$A8,RECARGAS!AE$16:AE$37)+SUMIF(REVENDIDOS!$B$16:$B$25,$A8,REVENDIDOS!V$16:V$25) -> 12323.612 | ... R8: =SUMIF(MANUALES!$B$16:$B$72,$A8,MANUALES!X$16:X$72)+SUMIF(RODANTES!$B$16:$B$72,$A8,RODANTES!X$16:X$72)+SUMIF(RECARGAS!$B$16:$B$37,$A8,RECARGAS!AH$16:AH$37)+SUMIF(REVENDIDOS!$B$16:$B$25,$A8,REVENDIDOS!Y$16:Y$25) -> 1919.146
A9: MP-13 | B9: Fleje LAF 1,25 × 135 mm (fondo 1 kg) | C9: kg | D9: =SUMIF(MANUALES!$B$16:$B$72,$A9,MANUALES!W$16:W$72) -> 30867.038 | E9: =SUMIF(RODANTES!$B$16:$B$72,$A9,RODANTES!W$16:W$72) -> 0 | F9: =SUMIF(RECARGAS!$B$16:$B$37,$A9,RECARGAS!AG$16:AG$37) -> 0 | G9: =SUMIF(REVENDIDOS!$B$16:$B$25,$A9,REVENDIDOS!X$16:X$25) -> 0 | H9: =SUMIF(MANUALES!$B$16:$B$72,$A9,MANUALES!N$16:N$72)+SUMIF(RODANTES!$B$16:$B$72,$A9,RODANTES!N$16:N$72)+SUMIF(RECARGAS!$B$16:$B$37,$A9,RECARGAS!X$16:X$37)+SUMIF(REVENDIDOS!$B$16:$B$25,$A9,REVENDIDOS!O$16:O$25) -> 636.58481 | I9: =SUMIF(MANUALES!$B$16:$B$72,$A9,MANUALES!O$16:O$72)+SUMIF(RODANTES!$B$16:$B$72,$A9,RODANTES!O$16:O$72)+SUMIF(RECARGAS!$B$16:$B$37,$A9,RECARGAS!Y$16:Y$37)+SUMIF(REVENDIDOS!$B$16:$B$25,$A9,REVENDIDOS!P$16:P$25) -> 913.62367 | J9: =SUMIF(MANUALES!$B$16:$B$72,$A9,MANUALES!P$16:P$72)+SUMIF(RODANTES!$B$16:$B$72,$A9,RODANTES!P$16:P$72)+SUMIF(RECARGAS!$B$16:$B$37,$A9,RECARGAS!Z$16:Z$37)+SUMIF(REVENDIDOS!$B$16:$B$25,$A9,REVENDIDOS!Q$16:Q$25) -> 2211.0717 | K9: =SUMIF(MANUALES!$B$16:$B$72,$A9,MANUALES!Q$16:Q$72)+SUMIF(RODANTES!$B$16:$B$72,$A9,RODANTES!Q$16:Q$72)+SUMIF(RECARGAS!$B$16:$B$37,$A9,RECARGAS!AA$16:AA$37)+SUMIF(REVENDIDOS!$B$16:$B$25,$A9,REVENDIDOS!R$16:R$25) -> 5356.5363 | L9: =SUMIF(MANUALES!$B$16:$B$72,$A9,MANUALES!R$16:R$72)+SUMIF(RODANTES!$B$16:$B$72,$A9,RODANTES!R$16:R$72)+SUMIF(RECARGAS!$B$16:$B$37,$A9,RECARGAS!AB$16:AB$37)+SUMIF(REVENDIDOS!$B$16:$B$25,$A9,REVENDIDOS!S$16:S$25) -> 9462.6068 | M9: =SUMIF(MANUALES!$B$16:$B$72,$A9,MANUALES!S$16:S$72)+SUMIF(RODANTES!$B$16:$B$72,$A9,RODANTES!S$16:S$72)+SUMIF(RECARGAS!$B$16:$B$37,$A9,RECARGAS!AC$16:AC$37)+SUMIF(REVENDIDOS!$B$16:$B$25,$A9,REVENDIDOS!T$16:T$25) -> 13299.269 | N9: =SUMIF(MANUALES!$B$16:$B$72,$A9,MANUALES!T$16:T$72)+SUMIF(RODANTES!$B$16:$B$72,$A9,RODANTES!T$16:T$72)+SUMIF(RECARGAS!$B$16:$B$37,$A9,RECARGAS!AD$16:AD$37)+SUMIF(REVENDIDOS!$B$16:$B$25,$A9,REVENDIDOS!U$16:U$25) -> 18535.574 | O9: =SUMIF(MANUALES!$B$16:$B$72,$A9,MANUALES!U$16:U$72)+SUMIF(RODANTES!$B$16:$B$72,$A9,RODANTES!U$16:U$72)+SUMIF(RECARGAS!$B$16:$B$37,$A9,RECARGAS!AE$16:AE$37)+SUMIF(REVENDIDOS!$B$16:$B$25,$A9,REVENDIDOS!V$16:V$25) -> 23785.167 | ... R9: =SUMIF(MANUALES!$B$16:$B$72,$A9,MANUALES!X$16:X$72)+SUMIF(RODANTES!$B$16:$B$72,$A9,RODANTES!X$16:X$72)+SUMIF(RECARGAS!$B$16:$B$37,$A9,RECARGAS!AH$16:AH$37)+SUMIF(REVENDIDOS!$B$16:$B$25,$A9,REVENDIDOS!Y$16:Y$25) -> 3704.0446
A10: MP-06 | B10: Fleje LAF 1,25 × 200 mm (cúpula y fondo 2,5 kg) | C10: kg | D10: =SUMIF(MANUALES!$B$16:$B$72,$A10,MANUALES!W$16:W$72) -> 9210.5127 | E10: =SUMIF(RODANTES!$B$16:$B$72,$A10,RODANTES!W$16:W$72) -> 0 | F10: =SUMIF(RECARGAS!$B$16:$B$37,$A10,RECARGAS!AG$16:AG$37) -> 0 | G10: =SUMIF(REVENDIDOS!$B$16:$B$25,$A10,REVENDIDOS!X$16:X$25) -> 0 | H10: =SUMIF(MANUALES!$B$16:$B$72,$A10,MANUALES!N$16:N$72)+SUMIF(RODANTES!$B$16:$B$72,$A10,RODANTES!N$16:N$72)+SUMIF(RECARGAS!$B$16:$B$37,$A10,RECARGAS!X$16:X$37)+SUMIF(REVENDIDOS!$B$16:$B$25,$A10,REVENDIDOS!O$16:O$25) -> 192.80603 | I10: =SUMIF(MANUALES!$B$16:$B$72,$A10,MANUALES!O$16:O$72)+SUMIF(RODANTES!$B$16:$B$72,$A10,RODANTES!O$16:O$72)+SUMIF(RECARGAS!$B$16:$B$37,$A10,RECARGAS!Y$16:Y$37)+SUMIF(REVENDIDOS!$B$16:$B$25,$A10,REVENDIDOS!P$16:P$25) -> 463.81576 | J10: =SUMIF(MANUALES!$B$16:$B$72,$A10,MANUALES!P$16:P$72)+SUMIF(RODANTES!$B$16:$B$72,$A10,RODANTES!P$16:P$72)+SUMIF(RECARGAS!$B$16:$B$37,$A10,RECARGAS!Z$16:Z$37)+SUMIF(REVENDIDOS!$B$16:$B$25,$A10,REVENDIDOS!Q$16:Q$25) -> 840.72296 | K10: =SUMIF(MANUALES!$B$16:$B$72,$A10,MANUALES!Q$16:Q$72)+SUMIF(RODANTES!$B$16:$B$72,$A10,RODANTES!Q$16:Q$72)+SUMIF(RECARGAS!$B$16:$B$37,$A10,RECARGAS!AA$16:AA$37)+SUMIF(REVENDIDOS!$B$16:$B$25,$A10,REVENDIDOS!R$16:R$25) -> 1662.8222 | L10: =SUMIF(MANUALES!$B$16:$B$72,$A10,MANUALES!R$16:R$72)+SUMIF(RODANTES!$B$16:$B$72,$A10,RODANTES!R$16:R$72)+SUMIF(RECARGAS!$B$16:$B$37,$A10,RECARGAS!AB$16:AB$37)+SUMIF(REVENDIDOS!$B$16:$B$25,$A10,REVENDIDOS!S$16:S$25) -> 2774.5708 | M10: =SUMIF(MANUALES!$B$16:$B$72,$A10,MANUALES!S$16:S$72)+SUMIF(RODANTES!$B$16:$B$72,$A10,RODANTES!S$16:S$72)+SUMIF(RECARGAS!$B$16:$B$37,$A10,RECARGAS!AC$16:AC$37)+SUMIF(REVENDIDOS!$B$16:$B$25,$A10,REVENDIDOS!T$16:T$25) -> 3957.5867 | N10: =SUMIF(MANUALES!$B$16:$B$72,$A10,MANUALES!T$16:T$72)+SUMIF(RODANTES!$B$16:$B$72,$A10,RODANTES!T$16:T$72)+SUMIF(RECARGAS!$B$16:$B$37,$A10,RECARGAS!AD$16:AD$37)+SUMIF(REVENDIDOS!$B$16:$B$25,$A10,REVENDIDOS!U$16:U$25) -> 5270.7845 | O10: =SUMIF(MANUALES!$B$16:$B$72,$A10,MANUALES!U$16:U$72)+SUMIF(RODANTES!$B$16:$B$72,$A10,RODANTES!U$16:U$72)+SUMIF(RECARGAS!$B$16:$B$37,$A10,RECARGAS!AE$16:AE$37)+SUMIF(REVENDIDOS!$B$16:$B$25,$A10,REVENDIDOS!V$16:V$25) -> 6683.6727 | ... R10: =SUMIF(MANUALES!$B$16:$B$72,$A10,MANUALES!X$16:X$72)+SUMIF(RODANTES!$B$16:$B$72,$A10,RODANTES!X$16:X$72)+SUMIF(RECARGAS!$B$16:$B$37,$A10,RECARGAS!AH$16:AH$37)+SUMIF(REVENDIDOS!$B$16:$B$25,$A10,REVENDIDOS!Y$16:Y$25) -> 1013.1564
A11: MP-07 | B11: Fleje LAF 1,6 × 250 mm (cúpula 5 kg) | C11: kg | D11: =SUMIF(MANUALES!$B$16:$B$72,$A11,MANUALES!W$16:W$72) -> 45960.195 | E11: =SUMIF(RODANTES!$B$16:$B$72,$A11,RODANTES!W$16:W$72) -> 0 | F11: =SUMIF(RECARGAS!$B$16:$B$37,$A11,RECARGAS!AG$16:AG$37) -> 0 | G11: =SUMIF(REVENDIDOS!$B$16:$B$25,$A11,REVENDIDOS!X$16:X$25) -> 0 | H11: =SUMIF(MANUALES!$B$16:$B$72,$A11,MANUALES!N$16:N$72)+SUMIF(RODANTES!$B$16:$B$72,$A11,RODANTES!N$16:N$72)+SUMIF(RECARGAS!$B$16:$B$37,$A11,RECARGAS!X$16:X$37)+SUMIF(REVENDIDOS!$B$16:$B$25,$A11,REVENDIDOS!O$16:O$25) -> 1918.6983 | I11: =SUMIF(MANUALES!$B$16:$B$72,$A11,MANUALES!O$16:O$72)+SUMIF(RODANTES!$B$16:$B$72,$A11,RODANTES!O$16:O$72)+SUMIF(RECARGAS!$B$16:$B$37,$A11,RECARGAS!Y$16:Y$37)+SUMIF(REVENDIDOS!$B$16:$B$25,$A11,REVENDIDOS!P$16:P$25) -> 3860.6802 | J11: =SUMIF(MANUALES!$B$16:$B$72,$A11,MANUALES!P$16:P$72)+SUMIF(RODANTES!$B$16:$B$72,$A11,RODANTES!P$16:P$72)+SUMIF(RECARGAS!$B$16:$B$37,$A11,RECARGAS!Z$16:Z$37)+SUMIF(REVENDIDOS!$B$16:$B$25,$A11,REVENDIDOS!Q$16:Q$25) -> 6108.9527 | K11: =SUMIF(MANUALES!$B$16:$B$72,$A11,MANUALES!Q$16:Q$72)+SUMIF(RODANTES!$B$16:$B$72,$A11,RODANTES!Q$16:Q$72)+SUMIF(RECARGAS!$B$16:$B$37,$A11,RECARGAS!AA$16:AA$37)+SUMIF(REVENDIDOS!$B$16:$B$25,$A11,REVENDIDOS!R$16:R$25) -> 10953.36 | L11: =SUMIF(MANUALES!$B$16:$B$72,$A11,MANUALES!R$16:R$72)+SUMIF(RODANTES!$B$16:$B$72,$A11,RODANTES!R$16:R$72)+SUMIF(RECARGAS!$B$16:$B$37,$A11,RECARGAS!AB$16:AB$37)+SUMIF(REVENDIDOS!$B$16:$B$25,$A11,REVENDIDOS!S$16:S$25) -> 16905.87 | M11: =SUMIF(MANUALES!$B$16:$B$72,$A11,MANUALES!S$16:S$72)+SUMIF(RODANTES!$B$16:$B$72,$A11,RODANTES!S$16:S$72)+SUMIF(RECARGAS!$B$16:$B$37,$A11,RECARGAS!AC$16:AC$37)+SUMIF(REVENDIDOS!$B$16:$B$25,$A11,REVENDIDOS!T$16:T$25) -> 22909.322 | N11: =SUMIF(MANUALES!$B$16:$B$72,$A11,MANUALES!T$16:T$72)+SUMIF(RODANTES!$B$16:$B$72,$A11,RODANTES!T$16:T$72)+SUMIF(RECARGAS!$B$16:$B$37,$A11,RECARGAS!AD$16:AD$37)+SUMIF(REVENDIDOS!$B$16:$B$25,$A11,REVENDIDOS!U$16:U$25) -> 29676.926 | O11: =SUMIF(MANUALES!$B$16:$B$72,$A11,MANUALES!U$16:U$72)+SUMIF(RODANTES!$B$16:$B$72,$A11,RODANTES!U$16:U$72)+SUMIF(RECARGAS!$B$16:$B$37,$A11,RECARGAS!AE$16:AE$37)+SUMIF(REVENDIDOS!$B$16:$B$25,$A11,REVENDIDOS!V$16:V$25) -> 36072.056 | ... R11: =SUMIF(MANUALES!$B$16:$B$72,$A11,MANUALES!X$16:X$72)+SUMIF(RODANTES!$B$16:$B$72,$A11,RODANTES!X$16:X$72)+SUMIF(RECARGAS!$B$16:$B$37,$A11,RECARGAS!AH$16:AH$37)+SUMIF(REVENDIDOS!$B$16:$B$25,$A11,REVENDIDOS!Y$16:Y$25) -> 5055.6214
A12: MP-08 | B12: Fleje LAF 1,6 × 200 mm (fondo 5 kg) | C12: kg | D12: =SUMIF(MANUALES!$B$16:$B$72,$A12,MANUALES!W$16:W$72) -> 29545.839 | E12: =SUMIF(RODANTES!$B$16:$B$72,$A12,RODANTES!W$16:W$72) -> 0 | F12: =SUMIF(RECARGAS!$B$16:$B$37,$A12,RECARGAS!AG$16:AG$37) -> 0 | G12: =SUMIF(REVENDIDOS!$B$16:$B$25,$A12,REVENDIDOS!X$16:X$25) -> 0 | H12: =SUMIF(MANUALES!$B$16:$B$72,$A12,MANUALES!N$16:N$72)+SUMIF(RODANTES!$B$16:$B$72,$A12,RODANTES!N$16:N$72)+SUMIF(RECARGAS!$B$16:$B$37,$A12,RECARGAS!X$16:X$37)+SUMIF(REVENDIDOS!$B$16:$B$25,$A12,REVENDIDOS!O$16:O$25) -> 1233.4489 | I12: =SUMIF(MANUALES!$B$16:$B$72,$A12,MANUALES!O$16:O$72)+SUMIF(RODANTES!$B$16:$B$72,$A12,RODANTES!O$16:O$72)+SUMIF(RECARGAS!$B$16:$B$37,$A12,RECARGAS!Y$16:Y$37)+SUMIF(REVENDIDOS!$B$16:$B$25,$A12,REVENDIDOS!P$16:P$25) -> 2481.8658 | J12: =SUMIF(MANUALES!$B$16:$B$72,$A12,MANUALES!P$16:P$72)+SUMIF(RODANTES!$B$16:$B$72,$A12,RODANTES!P$16:P$72)+SUMIF(RECARGAS!$B$16:$B$37,$A12,RECARGAS!Z$16:Z$37)+SUMIF(REVENDIDOS!$B$16:$B$25,$A12,REVENDIDOS!Q$16:Q$25) -> 3927.1839 | K12: =SUMIF(MANUALES!$B$16:$B$72,$A12,MANUALES!Q$16:Q$72)+SUMIF(RODANTES!$B$16:$B$72,$A12,RODANTES!Q$16:Q$72)+SUMIF(RECARGAS!$B$16:$B$37,$A12,RECARGAS!AA$16:AA$37)+SUMIF(REVENDIDOS!$B$16:$B$25,$A12,REVENDIDOS!R$16:R$25) -> 7041.446 | L12: =SUMIF(MANUALES!$B$16:$B$72,$A12,MANUALES!R$16:R$72)+SUMIF(RODANTES!$B$16:$B$72,$A12,RODANTES!R$16:R$72)+SUMIF(RECARGAS!$B$16:$B$37,$A12,RECARGAS!AB$16:AB$37)+SUMIF(REVENDIDOS!$B$16:$B$25,$A12,REVENDIDOS!S$16:S$25) -> 10868.06 | M12: =SUMIF(MANUALES!$B$16:$B$72,$A12,MANUALES!S$16:S$72)+SUMIF(RODANTES!$B$16:$B$72,$A12,RODANTES!S$16:S$72)+SUMIF(RECARGAS!$B$16:$B$37,$A12,RECARGAS!AC$16:AC$37)+SUMIF(REVENDIDOS!$B$16:$B$25,$A12,REVENDIDOS!T$16:T$25) -> 14727.421 | N12: =SUMIF(MANUALES!$B$16:$B$72,$A12,MANUALES!T$16:T$72)+SUMIF(RODANTES!$B$16:$B$72,$A12,RODANTES!T$16:T$72)+SUMIF(RECARGAS!$B$16:$B$37,$A12,RECARGAS!AD$16:AD$37)+SUMIF(REVENDIDOS!$B$16:$B$25,$A12,REVENDIDOS!U$16:U$25) -> 19078.024 | O12: =SUMIF(MANUALES!$B$16:$B$72,$A12,MANUALES!U$16:U$72)+SUMIF(RODANTES!$B$16:$B$72,$A12,RODANTES!U$16:U$72)+SUMIF(RECARGAS!$B$16:$B$37,$A12,RECARGAS!AE$16:AE$37)+SUMIF(REVENDIDOS!$B$16:$B$25,$A12,REVENDIDOS!V$16:V$25) -> 23189.179 | ... R12: =SUMIF(MANUALES!$B$16:$B$72,$A12,MANUALES!X$16:X$72)+SUMIF(RODANTES!$B$16:$B$72,$A12,RODANTES!X$16:X$72)+SUMIF(RECARGAS!$B$16:$B$37,$A12,RECARGAS!AH$16:AH$37)+SUMIF(REVENDIDOS!$B$16:$B$25,$A12,REVENDIDOS!Y$16:Y$25) -> 3250.0423
