Workbook

Sheet Indexado Dim Técnico
A1: PRODUCCION DE MATAFUEGOS TERMINADOS
A2: Demanda | B2: 2026 | C2: 2027 | D2: 2028 | E2: 2029 | F2: 2030 | G2: 2031 | H2: 2032 | I2: 2033 | J2: 2034 | K2: 2035 | L2: %
A3: ABC 1 kg | B3: 4178.7365 | C3: 5997.304 | D3: 6851.7478 | E3: 8467.1355 | F3: 12680.633 | G3: 15620.253 | H3: 20332.553 | I3: 25132.078 | J3: 28573.336 | K3: 32072.639 | L3: 0.43398757
A4: ABC 2,5 kg | B4: 295.03036 | C4: 709.72745 | D4: 986.86806 | E4: 1500.6382 | F4: 2312.6277 | G4: 3252.8699 | H4: 4102.3155 | I4: 5104.3066 | J4: 6195.1862 | K4: 7424.8584 | L4: 0.1004687
A5: ABC 5 kg | B5: 2255.773 | C5: 3846.9789 | D5: 5093.5376 | E5: 6823.1153 | F5: 10819.307 | G5: 14605.964 | H5: 18877.76 | I5: 23368.186 | J5: 26967.725 | K5: 30750.779 | L5: 0.41610096
A6: ABC 10 kg | B6: 91.833182 | C6: 177.2473 | D6: 252.97878 | E6: 358.02049 | F6: 602.71815 | G6: 872.60503 | H6: 1127.1605 | I6: 1395.4448 | J6: 1612.3501 | K6: 1840.8481 | L6: 0.024909244
A7: ABC 25 kg s/ruedas | B7: 34.051791 | C7: 58.462147 | D7: 75.20854 | E7: 100.52985 | F7: 155.876 | G7: 211.93448 | H7: 272.66823 | I7: 337.84867 | J7: 393.62742 | K7: 453.27053 | L7: 0.0061333829
A8: ABC 50 kg s/ruedas | B8: 74.913941 | C8: 128.61672 | D8: 165.45879 | E8: 221.16568 | F8: 342.92721 | G8: 466.25586 | H8: 599.87011 | I8: 743.26708 | J8: 865.98031 | K8: 997.19517 | L8: 0.013493442
A9: ABC 70 kg s/ruedas | B9: 16.34486 | C9: 28.061831 | D9: 36.100099 | E9: 48.254329 | F9: 74.820482 | G9: 101.72855 | H9: 130.88075 | I9: 162.16736 | J9: 188.94116 | K9: 217.56986 | L9: 0.0029440238
A10: ABC 100 kg s/ruedas | B10: 10.896573 | C10: 18.707887 | D10: 24.066733 | E10: 32.169553 | F10: 49.880321 | G10: 67.819034 | H10: 87.253835 | I10: 108.11157 | J10: 125.96077 | K10: 145.04657 | L10: 0.0019626825
A11: TOTAL | B11: 6957.5803 | C11: 10965.106 | D11: 13485.966 | E11: 17551.029 | F11: 27038.79 | G11: 35199.43 | H11: 45530.462 | I11: 56351.411 | J11: 64923.107 | K11: 73902.207 | L11: 1
A13: PRODUCCION DE CILINDROS
A14: Demanda | B14: 2026 | C14: 2027 | D14: 2028 | E14: 2029 | F14: 2030 | G14: 2031 | H14: 2032 | I14: 2033 | J14: 2034 | K14: 2035 | L14: %
A15: Cilindros ABC 1 kg | B15: 0 | C15: 0 | D15: 7662.4 | E15: 26694.8 | F15: 49434.8 | G15: 71680.2 | H15: 101340.6 | I15: 131001 | J15: 146819.8 | K15: 170548 | L15: 0.79908167
A16: Cilindros ABC 2,5 kg | B16: 0 | C16: 0 | D16: 299.6 | E16: 1043.8 | F16: 1933 | G16: 2803 | H16: 3963 | I16: 5123 | J16: 5741.4 | K16: 6669 | L16: 0.031246779
A17: Cilindros ABC 5 kg | B17: 0 | C17: 0 | D17: 1478.8 | E17: 5152 | F17: 9540.8 | G17: 13834.2 | H17: 19558.6 | I17: 25283 | J17: 28335.8 | K17: 32915 | L17: 0.15421918
A18: Cilindros ABC 10 kg | B18: 0 | C18: 0 | D18: 90.4 | E18: 315 | F18: 583.4 | G18: 845.8 | H18: 1195.4 | I18: 1545 | J18: 1731.4 | K18: 2011 | L18: 0.009422293
A19: Cilindros ABC 25 kg | B19: 0 | C19: 0 | D19: 14.4 | E19: 50.2 | F19: 93 | G19: 135 | H19: 191 | I19: 247 | J19: 277 | K19: 322 | L19: 0.0015086914
A20: Cilindros ABC 50 kg | B20: 0 | C20: 0 | D20: 31.8 | E20: 110.8 | F20: 205.2 | G20: 297.6 | H20: 420.8 | I20: 544 | J20: 609.6 | K20: 708 | L20: 0.0033172469
A21: Cilindros ABC 70 kg | B21: 0 | C21: 0 | D21: 7 | E21: 24.4 | F21: 45.2 | G21: 65.4 | H21: 92.2 | I21: 119 | J21: 133.4 | K21: 155 | L21: 0.00072623343
A22: Cilindros ABC 100 kg | B22: 0 | C22: 0 | D22: 4.6 | E22: 16 | F22: 29.6 | G22: 42.8 | H22: 60.4 | I22: 78 | J22: 87.6 | K22: 102 | L22: 0.00047790845
A23: Cilindros Total | B23: 0 | C23: 0 | D23: 9589 | E23: 33407 | F23: 61865 | G23: 89704 | H23: 126822 | I23: 163940 | J23: 183736 | K23: 213430 | L23: 1
A25: RECARGAS
A26: Demanda | B26: 2026 | C26: 2027 | D26: 2028 | E26: 2029 | F26: 2030 | G26: 2031 | H26: 2032 | I26: 2033 | J26: 2034 | K26: 2035 | L26: %
A27: ABC 1 kg | B27: 3477.4821 | C27: 16970.586 | D27: 30546.09 | E27: 56048.311 | F27: 84270.226 | G27: 117407.82 | H27: 147610.64 | I27: 171404.36 | J27: 183690.57 | K27: 196282.69 | L27: 0.52777261
A28: ABC 2,5 kg | B28: 329.99667 | C28: 1287.414 | D28: 2947.1692 | E28: 5426.0433 | F28: 7850.8758 | G28: 10423.944 | H28: 12809.896 | I28: 14263.068 | J28: 15432.87 | K28: 16620.761 | L28: 0.044690555
A29: ABC 5 kg | B29: 1950.3941 | C29: 7852.6185 | D29: 17775.857 | E29: 33605.568 | F29: 48407.572 | G29: 64323.043 | H29: 78721.1 | I29: 87237.212 | J29: 94103.668 | K29: 101095.18 | L29: 0.27182868
A30: ABC 10 kg | B30: 118.34363 | C30: 437.71658 | D30: 1024.9748 | E30: 1960.4099 | F30: 2844.9768 | G30: 3810.3906 | H30: 4663.6781 | I30: 5164.5146 | J30: 5571.5443 | K30: 5985.9509 | L30: 0.01609526
A31: Agua 10 l | B31: 159.30874 | C31: 643.42354 | D31: 1474.3627 | E31: 2766.4512 | F31: 3991.4652 | G31: 5335.7558 | H31: 6538.9589 | I31: 7269.8197 | J31: 7855.4414 | K31: 8450.8141 | L31: 0.022722881
A32: AFFF 10 l | B32: 22.758391 | C32: 161.31575 | D32: 316.60728 | E32: 527.39462 | F32: 743.78895 | G32: 962.87434 | H32: 1194.9422 | I32: 1351.6172 | J32: 1477.5489 | K32: 1604.4414 | L32: 0.0043140851
A33: AFFF 50 l s/ruedas | B33: 11.379195 | C33: 83.22352 | D33: 164.46383 | E33: 281.34115 | F33: 398.90251 | G33: 514.52728 | H33: 629.06551 | I33: 711.17802 | J33: 773.41098 | K33: 836.35081 | L33: 0.0022488129
A34: BC 5 kg | B34: 6.8275173 | C34: 47.073112 | D34: 88.889676 | E34: 159.50249 | F34: 219.7962 | G34: 291.86985 | H34: 368.84417 | I34: 408.40895 | J34: 445.78194 | K34: 483.4792 | L34: 0.0012999979
A35: Sales K 6 l | B35: 81.930207 | C35: 335.39886 | D35: 746.59835 | E35: 1358.8998 | F35: 1961.1255 | G35: 2598.5414 | H35: 3197.2635 | I35: 3578.5395 | J35: 3870.748 | K35: 4167.5596 | L35: 0.011205898
A36: CO₂ 2 kg | B36: 450.61614 | C36: 1697.1815 | D36: 3955.1969 | E36: 7561.2603 | F36: 10920.145 | G36: 14514.885 | H36: 17746.499 | I36: 19617.205 | J36: 21161.806 | K36: 22734.502 | L36: 0.061129421
A37: CO₂ 5 kg | B37: 125.17115 | C37: 643.63037 | D37: 1375.6267 | E37: 2460.2843 | F37: 3545.2577 | G37: 4723.4618 | H37: 5853.9052 | I37: 6608.4599 | J37: 7185.7084 | K37: 7769.5771 | L37: 0.020891144
A38: HCFC/HFC 5 kg | B38: 18.206713 | C38: 112.07512 | D38: 230.85404 | E38: 400.71533 | F38: 574.50779 | G38: 754.34562 | H38: 944.84884 | I38: 1072.2347 | J38: 1171.6958 | K38: 1271.9411 | L38: 0.0034200452
... A44: Recargas Total | B44: 6829.7931 | C44: 30662.681 | D44: 61483.058 | E44: 114050.8 | F44: 167870.4 | G44: 228490.11 | H44: 283777.78 | I44: 322612.24 | J44: 347003.72 | K44: 371907.69 | L44: 1
A46: MATAFUEGOS TERCIARIZADOS VENDIDOS
A47: Demanda | B47: 2026 | C47: 2027 | D47: 2028 | E47: 2029 | F47: 2030 | G47: 2031 | H47: 2032 | I47: 2033 | J47: 2034 | K47: 2035 | L47: %
A48: Agua 10 l | B48: 175.60796 | C48: 320.39061 | D48: 436.58878 | E48: 602.28658 | F48: 974.75938 | G48: 1370.0813 | H48: 1767.1834 | I48: 2188.4667 | J48: 2536.3433 | K48: 2904.8974 | L48: 0.16128875
A49: AFFF 10 l | B49: 99.501785 | C49: 159.88684 | D49: 193.41515 | E49: 247.88223 | F49: 360.26764 | G49: 447.86961 | H49: 573.94598 | I49: 711.73135 | J49: 836.04456 | K49: 970.70413 | L49: 0.053896449
A50: AFFF 50 l s/ruedas | B50: 42.643622 | C50: 68.522932 | D50: 82.892207 | E50: 106.23524 | F50: 154.40042 | G50: 191.94412 | H50: 245.97685 | I50: 305.02772 | J50: 358.30481 | K50: 416.01606 | L50: 0.023098478
A51: BC 5 kg | B51: 28.429082 | C51: 45.681955 | D51: 55.261471 | E51: 70.823495 | F51: 102.93361 | G51: 127.96275 | H51: 163.98457 | I51: 203.35181 | J51: 238.86987 | K51: 277.34404 | L51: 0.015398985
A52: Sales K 6 l | B52: 100.61113 | C52: 188.89723 | D52: 248.98918 | E52: 348.41375 | F52: 546.17668 | G52: 751.85808 | H52: 960.04713 | I52: 1191.4191 | J52: 1409.9304 | K52: 1649.1356 | L52: 0.091565029
A53: CO₂ 2 kg | B53: 421.98437 | C53: 772.32062 | D53: 1066.3637 | E53: 1474.9633 | F53: 2394.6449 | G53: 3311.5475 | H53: 4274.1878 | I53: 5292.3947 | J53: 6125.2048 | K53: 7005.2774 | L53: 0.38895433
A54: CO₂ 5 kg | B54: 284.03951 | C54: 489.45297 | D54: 625.43061 | E54: 836.95187 | F54: 1289.1433 | G54: 1751.7357 | H54: 2250.2471 | I54: 2789.0594 | J54: 3259.9748 | K54: 3766.1755 | L54: 0.20910953
A55: HCFC/HFC 5 kg | B55: 58.859604 | C55: 100.2619 | D55: 126.52966 | E55: 167.81799 | F55: 256.59014 | G55: 346.11458 | H55: 444.69891 | I55: 551.15784 | J55: 643.95742 | K55: 743.64561 | L55: 0.041289468
A56: Clase D 9 l | B56: 28.429082 | C56: 45.681955 | D56: 55.261471 | E56: 70.823495 | F56: 102.93361 | G56: 127.96275 | H56: 163.98457 | I56: 203.35181 | J56: 238.86987 | K56: 277.34404 | L56: 0.015398985
A57: Revendidos Total | B57: 1240.1061 | C57: 2191.097 | D57: 2890.7323 | E57: 3926.198 | F57: 6181.8497 | G57: 8427.0764 | H57: 10844.256 | I57: 13435.96 | J57: 15647.5 | K57: 18010.54 | L57: 1
A59: DISTRIBUCIÓN DE RECARGAS POR ZONA
A60: ZONA | B60: 2026 | C60: 2027 | D60: 2028 | E60: 2029 | F60: 2030 | G60: 2031 | H60: 2032 | I60: 2033 | J60: 2034 | K60: 2035 | L60: % ZONAL AÑO 2026 | M60: % ZONAL AÑO 2027 | N60: % ZONAL AÑO 2028 | O60: % ZONAL AÑO 2029 | P60: % ZONAL AÑO 2030 | Q60: % ZONAL AÑO 2031 | R60: % ZONAL AÑO 2032 | S60: % ZONAL AÑO 2033 | T60: % ZONAL AÑO 2034 | U60: % ZONAL AÑO 2035 | V60: Ratio de cobertura año 10 planta comercial
A61: CABA Norte | B61: 372.55787 | C61: 1662.2427 | D61: 3313.0494 | E61: 6110.2769 | F61: 8944.5644 | G61: 12112.066 | H61: 14971.759 | I61: 16948.142 | J61: 18162.044 | K61: 19406.047 | L61: 0.054548924 | M61: 0.054210612 | N61: 0.053885566 | O61: 0.053575048 | P61: 0.05328256 | Q61: 0.053009146 | R61: 0.052758741 | S61: 0.052534095 | T61: 0.052339623 | U61: 0.05217974 | V61: 0.38488863
A62: CABA Este | B62: 528.02642 | C62: 2376.8206 | D62: 4779.1843 | E62: 8891.8427 | F62: 13129.922 | G62: 17933.548 | H62: 22357.662 | I62: 25523.281 | J62: 27579.272 | K62: 29709.331 | L62: 0.077312214 | M62: 0.077515094 | N62: 0.077731728 | O62: 0.077963882 | P62: 0.078214635 | Q62: 0.078487198 | R62: 0.078785807 | S62: 0.079114422 | T62: 0.079478318 | U62: 0.079883616 | V62: Ratio de cobertura año 10 planta industrial
A63: CABA Sur | B63: 415.79609 | C63: 1860.5844 | D63: 3719.2814 | E63: 6879.8024 | F63: 10100.915 | G63: 13718.725 | H63: 17008.503 | I63: 19311.755 | J63: 20757.435 | K63: 22246.509 | L63: 0.060879749 | M63: 0.060679118 | N63: 0.060492784 | O63: 0.060322265 | P63: 0.060170912 | Q63: 0.060040783 | R63: 0.059935991 | S63: 0.059860579 | T63: 0.059819057 | U63: 0.059817286 | V63: 0.61511137
A64: CABA Oeste | B64: 441.44772 | C64: 1978.435 | D64: 3960.26 | E64: 7334.1015 | F64: 10777.7 | G64: 14647.079 | H64: 18164.614 | I64: 20621.868 | J64: 22152.695 | K64: 23714.72 | L64: 0.064635591 | M64: 0.06452257 | N64: 0.064412215 | O64: 0.064305571 | P64: 0.064202504 | Q64: 0.064103778 | R64: 0.064009992 | S64: 0.06392153 | T64: 0.063839936 | U64: 0.063765071
A65: PBA Sur 1er (Avellaneda) | B65: 458.70777 | C65: 2061.9328 | D65: 4139.2991 | E65: 7686.8125 | F65: 11325.46 | G65: 15429.107 | H65: 19177.457 | I65: 21816.328 | J65: 23477.646 | K65: 25170.766 | L65: 0.067162763 | M65: 0.06724568 | N65: 0.067324222 | O65: 0.067398149 | P65: 0.067465498 | Q65: 0.067526368 | R65: 0.067579135 | S65: 0.067623994 | T65: 0.067658198 | U65: 0.067680145
A66: PBA Sur 2do cordón | B66: 636.38851 | C66: 2858.3024 | D66: 5733.3155 | E66: 10638.22 | F66: 15661.318 | G66: 21318.849 | H66: 26476.854 | I66: 30095.909 | J66: 32361.717 | K66: 34668.23 | L66: 0.093178299 | M66: 0.093217627 | N66: 0.09325033 | O66: 0.093276161 | P66: 0.093294104 | Q66: 0.093303157 | R66: 0.093301364 | S66: 0.09328818 | T66: 0.093260434 | U66: 0.093217299
A67: PBA Sur 3er cordón | B67: 454.62927 | C67: 2045.1072 | D67: 4108.5565 | E67: 7635.2983 | F67: 11257.839 | G67: 15348.239 | H67: 19090.976 | I67: 21733.536 | J67: 23405.616 | K67: 25111.868 | L67: 0.0665656 | M67: 0.066696948 | N67: 0.066824205 | O67: 0.066946471 | P67: 0.067062685 | Q67: 0.067172445 | R67: 0.067274387 | S67: 0.067367363 | T67: 0.067450621 | U67: 0.067521776
A68: PBA Norte 1er cordón | B68: 359.94876 | C68: 1618.8619 | D68: 3251.5478 | E68: 6041.287 | F68: 8905.6314 | G68: 12138.705 | H68: 15095.516 | I68: 17181.354 | J68: 18499.256 | K68: 19843.463 | L68: 0.052702733 | M68: 0.052795837 | N68: 0.052885265 | O68: 0.052970143 | P68: 0.053050637 | Q68: 0.053125736 | R68: 0.053194849 | S68: 0.05325698 | T68: 0.053311406 | U68: 0.053355883
A69: PBA Norte 2do cordón | B69: 597.34162 | C69: 2686.6674 | D69: 5396.5219 | E69: 10027.099 | F69: 14781.808 | G69: 20148.821 | H69: 25057.429 | I69: 28520.161 | J69: 30707.696 | K69: 32939.196 | L69: 0.087461159 | M69: 0.087620108 | N69: 0.087772503 | O69: 0.087917831 | P69: 0.088054881 | Q69: 0.088182465 | R69: 0.088299473 | S69: 0.088403842 | T69: 0.088493853 | U69: 0.088568205
A70: PBA Norte 3er cordón | B70: 319.12323 | C70: 1434.6624 | D70: 2880.3809 | E70: 5349.5436 | F70: 7882.7595 | G70: 10740.345 | H70: 13351.329 | I70: 15190.192 | J70: 16349.032 | K70: 17530.282 | L70: 0.046725168 | M70: 0.04678855 | N70: 0.046848368 | O70: 0.046904922 | P70: 0.046957413 | Q70: 0.047005734 | R70: 0.047048536 | S70: 0.047084984 | T70: 0.04711486 | U70: 0.047136111
A71: PBA Oeste 1er cordón | B71: 584.10992 | C71: 2621.1571 | D71: 5253.0024 | E71: 9738.3999 | F71: 14324.084 | G71: 19481.486 | H71: 24173.961 | I71: 27454.478 | J71: 29496.089 | K71: 31571.268 | L71: 0.085523809 | M71: 0.085483625 | N71: 0.085438209 | O71: 0.085386515 | P71: 0.085328229 | Q71: 0.085261836 | R71: 0.085186237 | S71: 0.085100547 | T71: 0.085002228 | U71: 0.084890066
A72: PBA Oeste 2do cordón | B72: 456.24081 | C72: 2050.7139 | D72: 4116.4881 | E72: 7643.8612 | F72: 11261.277 | G72: 15340.4 | H72: 19065.605 | I72: 21686.688 | J72: 23335.732 | K72: 25016.111 | L72: 0.066801557 | M72: 0.066879798 | N72: 0.06695321 | O72: 0.067021551 | P72: 0.067083164 | Q72: 0.067138137 | R72: 0.06718498 | S72: 0.067222148 | T72: 0.067249229 | U72: 0.067264302
A73: PBA Oeste 3er cordón | B73: 117.08802 | C73: 527.01426 | D73: 1059.3619 | E73: 1969.8448 | F73: 2906.0051 | G73: 3964.0864 | H73: 4933.5361 | I73: 5619.4239 | J73: 6054.9028 | K73: 6499.7354 | L73: 0.017143715 | M73: 0.017187482 | N73: 0.017230143 | O73: 0.017271644 | P73: 0.017311004 | Q73: 0.01734905 | R73: 0.017385209 | S73: 0.017418508 | T73: 0.017449101 | U73: 0.017476744
A74: PBA Interior | B74: 1088.3871 | C74: 4880.1788 | D74: 9772.809 | E74: 18104.406 | F74: 26611.113 | G74: 36168.651 | H74: 44852.582 | I74: 50909.123 | J74: 54664.583 | K74: 58480.162 | L74: 0.15935872 | M74: 0.15915695 | N74: 0.15895125 | O74: 0.15873985 | P74: 0.15852178 | Q74: 0.15829417 | R74: 0.1580553 | S74: 0.15780283 | T74: 0.15753314 | U74: 0.15724376
A75: SUBTOTAL CABA + PBA | B75: 6829.7931 | C75: 30662.681 | D75: 61483.058 | E75: 114050.8 | F75: 167870.4 | G75: 228490.11 | H75: 283777.78 | I75: 322612.24 | J75: 347003.72 | K75: 371907.69 | L75: 1 | M75: 1 | N75: 1 | O75: 1 | P75: 1 | Q75: 1 | R75: 1 | S75: 1 | T75: 1 | U75: 1
A77: DISTRIBUCIÓN DE UNIDADES NUEVAS REVENDIDAS POR ZONA – TODOS LOS AÑOS
A78: ZONA | B78: 2026 | C78: 2027 | D78: 2028 | E78: 2029 | F78: 2030 | G78: 2031 | H78: 2032 | I78: 2033 | J78: 2034 | K78: 2035 | L78: % ZONAL AÑO 2026 | M78: % ZONAL AÑO 2027 | N78: % ZONAL AÑO 2028 | O78: % ZONAL AÑO 2029 | P78: % ZONAL AÑO 2030 | Q78: % ZONAL AÑO 2031 | R78: % ZONAL AÑO 2032 | S78: % ZONAL AÑO 2033 | T78: % ZONAL AÑO 2034 | U78: % ZONAL AÑO 2035 | V78: Ratio de cobertura año 10 planta comercial
A79: CABA Norte | B79: 44.572325 | C79: 78.37283 | D79: 102.94721 | E79: 139.31219 | F79: 218.74611 | G79: 297.63245 | H79: 382.64303 | I79: 474.37826 | J79: 553.52314 | K79: 639.3736 | L79: 0.035942347 | M79: 0.035768763 | N79: 0.035612849 | O79: 0.035482721 | P79: 0.03538522 | Q79: 0.035318589 | R79: 0.035285318 | S79: 0.035306613 | T79: 0.035374542 | U79: 0.035499969 | V79: 0.3873481
A80: CABA Este | B80: 104.58609 | C80: 185.28962 | D80: 245.18827 | E80: 334.12367 | F80: 527.96032 | G80: 722.6195 | H80: 934.11047 | I80: 1163.2119 | J80: 1362.3677 | K80: 1578.1861 | L80: 0.084336404 | M80: 0.08456477 | N80: 0.08481874 | O80: 0.085101075 | P80: 0.085404911 | Q80: 0.085749727 | R80: 0.086138731 | S80: 0.086574522 | T80: 0.08706616 | U80: 0.0876257 | V80: Ratio de cobertura año 10 planta industrial
A81: CABA Sur | B81: 64.372731 | C81: 113.56542 | D81: 149.69314 | E81: 203.20713 | F81: 320.02148 | G81: 436.61298 | H81: 562.84 | I81: 699.15986 | J81: 817.24156 | K81: 945.39621 | L81: 0.051909049 | M81: 0.051830394 | N81: 0.051783814 | O81: 0.05175672 | P81: 0.051767916 | Q81: 0.05181073 | R81: 0.05190213 | S81: 0.052036463 | T81: 0.052228252 | U81: 0.052491276 | V81: 0.6126519
A82: CABA Oeste | B82: 75.603308 | C82: 133.43963 | D82: 175.88462 | E82: 238.65268 | F82: 375.43261 | G82: 511.43493 | H82: 657.75183 | I82: 814.54519 | J82: 948.33018 | K82: 1091.4067 | L82: 0.060965191 | M82: 0.060900829 | N82: 0.060844313 | O82: 0.060784678 | P82: 0.060731437 | Q82: 0.060689485 | R82: 0.060654397 | S82: 0.060624262 | T82: 0.06060586 | U82: 0.060598222
A83: PBA Sur 1er (Avellaneda) | B83: 87.619343 | C83: 154.89326 | D83: 204.42833 | E83: 277.74315 | F83: 437.38296 | G83: 596.2238 | H83: 767.10333 | I83: 950.09227 | J83: 1105.8178 | K83: 1271.6659 | L83: 0.070654712 | M83: 0.070692107 | N83: 0.070718529 | O83: 0.070740994 | P83: 0.070752766 | Q83: 0.070750966 | R83: 0.070738215 | S83: 0.070712643 | T83: 0.070670575 | U83: 0.070606764
A84: PBA Sur 2do cordón | B84: 118.21021 | C84: 208.85183 | D84: 275.50468 | E84: 374.09343 | F84: 588.79353 | G84: 802.26807 | H84: 1031.6291 | I84: 1277.0427 | J84: 1485.5612 | K84: 1707.5471 | L84: 0.095322656 | M84: 0.095318385 | N84: 0.095306189 | O84: 0.095281347 | P84: 0.095245526 | Q84: 0.095201233 | R84: 0.095131388 | S84: 0.095046625 | T84: 0.094939204 | U84: 0.094808216
A85: PBA Sur 3er cordón | B85: 91.964659 | C85: 162.65214 | D85: 214.78699 | E85: 291.95836 | F85: 460.00377 | G85: 627.41483 | H85: 807.61472 | I85: 1000.7494 | J85: 1165.3452 | K85: 1340.8214 | L85: 0.074158699 | M85: 0.0742332 | N85: 0.07430193 | O85: 0.074361598 | P85: 0.074411996 | Q85: 0.074452253 | R85: 0.074473961 | S85: 0.074482905 | T85: 0.074474851 | U85: 0.074446489
A86: PBA Norte 1er cordón | B86: 68.844295 | C86: 121.72948 | D86: 160.71825 | E86: 218.40255 | F86: 344.05381 | G86: 469.12763 | H86: 603.77238 | I86: 747.97733 | J86: 870.81304 | K86: 1001.6998 | L86: 0.05551484 | M86: 0.05555641 | N86: 0.055597763 | O86: 0.055626982 | P86: 0.05565548 | Q86: 0.055669085 | R86: 0.055676698 | S86: 0.055669807 | T86: 0.055651897 | U86: 0.055617422
A87: PBA Norte 2do cordón | B87: 120.71376 | C87: 213.48596 | D87: 281.87423 | E87: 383.10684 | F87: 603.5282 | G87: 823.03953 | H87: 1059.3188 | I87: 1312.4763 | J87: 1528.0608 | K87: 1757.8681 | L87: 0.097341478 | M87: 0.097433368 | N87: 0.097509629 | O87: 0.097577055 | P87: 0.097629065 | Q87: 0.097666082 | R87: 0.097684782 | S87: 0.097683847 | T87: 0.09765527 | U87: 0.097602191
A88: PBA Norte 3er cordón | B88: 62.482723 | C88: 110.47268 | D88: 145.81971 | E88: 198.13605 | F88: 312.07187 | G88: 425.4389 | H88: 547.4474 | I88: 678.0753 | J88: 789.34453 | K88: 907.81398 | L88: 0.05038498 | M88: 0.050418892 | N88: 0.050443866 | O88: 0.050465118 | P88: 0.050481958 | Q88: 0.050484756 | R88: 0.050482706 | S88: 0.0504672 | T88: 0.050445409 | U88: 0.050404596
A89: PBA Oeste 1er cordón | B89: 100.40118 | C89: 177.25115 | D89: 233.63765 | E89: 317.00887 | F89: 498.57382 | G89: 678.79379 | H89: 872.24148 | I89: 1078.9737 | J89: 1254.2663 | K89: 1440.6388 | L89: 0.08096176 | M89: 0.080896075 | N89: 0.080822998 | O89: 0.080741948 | P89: 0.080651237 | Q89: 0.080549144 | R89: 0.0804335 | S89: 0.080304917 | T89: 0.08015762 | U89: 0.079988653
A90: PBA Oeste 2do cordón | B90: 90.027687 | C90: 159.14938 | D90: 210.04307 | E90: 285.37102 | F90: 449.37153 | G90: 612.55049 | H90: 788.14134 | I90: 976.08346 | J90: 1136.0179 | K90: 1306.3659 | L90: 0.072596759 | M90: 0.072634567 | N90: 0.072660852 | O90: 0.072683807 | P90: 0.072692082 | Q90: 0.072688376 | R90: 0.072678229 | S90: 0.072647092 | T90: 0.072600603 | U90: 0.072533411
A91: PBA Oeste 3er cordón | B91: 24.64854 | C91: 43.605949 | D91: 57.6079 | E91: 78.33168 | F91: 123.45049 | G91: 168.46047 | H91: 216.91593 | I91: 268.89363 | J91: 313.15588 | K91: 360.44099 | L91: 0.019876153 | M91: 0.019901423 | N91: 0.01992848 | O91: 0.019951026 | P91: 0.01996983 | Q91: 0.019990381 | R91: 0.020002841 | S91: 0.020012982 | T91: 0.020013158 | U91: 0.020012781
A92: PBA Interior | B92: 186.05929 | C92: 328.33768 | D92: 432.59822 | E92: 586.75038 | F92: 922.45917 | G92: 1255.459 | H92: 1612.7264 | I92: 1994.3013 | J92: 2317.6545 | K92: 2661.3149 | L92: 0.15003497 | M92: 0.14985082 | N92: 0.14965005 | O92: 0.14944493 | P92: 0.14922058 | Q92: 0.14897919 | R92: 0.1487171 | S92: 0.14843012 | T92: 0.1481166 | U92: 0.14776431
A93: SUBTOTAL CABA + PBA | B93: 1240.1061 | C93: 2191.097 | D93: 2890.7323 | E93: 3926.198 | F93: 6181.8497 | G93: 8427.0764 | H93: 10844.256 | I93: 13435.96 | J93: 15647.5 | K93: 18010.54 | L93: 1 | M93: 1 | N93: 1 | O93: 1 | P93: 1 | Q93: 1 | R93: 1 | S93: 1 | T93: 1 | U93: 1

Sheet Reservas y Sustitutos
A1: Reserva del cliente (IRAM 3517-2:2020 5.3) y extintores sustitutos (9.4.5) — FLAMA
A2: 5.3: «Esta dotación no debe ser menor al 10% de la dotación mínima requerida» · «Si fuera heterogénea, la de reserva debe ser de extintores tipo ABC de 5 kg» · «Las propiedades que tengan menos de 5 extintores pueden no tener dotación de reserva».
A3: 9.4.5: «Los extintores fuera de servicio por mantenimiento o recarga deben ser sustituidos por equipos sustitutos que tengan igual clasificación y por lo menos igual capacidad» · se cubre «con extintores de reserva (ver 5.3) o requiriendo al prestador responsable del servicio su provisión temporaria».
A5: PARÁMETROS (celdas amarillas: completar con datos de planta)
A6: Días hábiles por año (DH) | B6: 260 | E6: menor a 5 matafuegos sin reserva obligatoria | L6: Dato de planta
A7: Ciclo de recarga en planta (días: retiro + recarga + devolución) | B7: 3 | L7: Dato de planta (dimensionamiento técnico de la línea de recarga)
A8: Reserva mínima de la norma | B8: 0.1 | L8: IRAM 3517-2:2020 5.3 (10 %)
A9: Vida útil extintor (años) | B9: 20 | L9: Res. 349/07 PBA art. 26
A10: Vida útil CO₂ (años) | B10: 30 | L10: Res. 349/07 PBA art. 26
A12: Año | B12: 2026 | C12: 2027 | D12: 2028 | E12: 2029 | F12: 2030 | G12: 2031 | H12: 2032 | I12: 2033 | J12: 2034 | K12: 2035
A14: A. PARQUE INSTALADO POR SEGMENTO
A15: Supermercados | B15: 39725 | C15: 39940 | D15: 40154 | E15: 40369 | F15: 40593 | G15: 40811 | H15: 41042 | I15: 41258 | J15: 41486 | K15: 41707
A16: Salud | B16: 3393423 | C16: 3525669 | D16: 3663072 | E16: 3805830 | F16: 3954150 | G16: 4108248 | H16: 4268358 | I16: 4434705 | J16: 4607532 | K16: 4787100
A17: Educación | B17: 703633 | C17: 704099 | D17: 704578 | E17: 705077 | F17: 705582 | G17: 706103 | H17: 706636 | I17: 707181 | J17: 707746 | K17: 708321
A18: Automotor | B18: 12094003 | C18: 12355237 | D18: 12622105 | E18: 12894744 | F18: 13173268 | G18: 13457809 | H18: 13748498 | I18: 14045462 | J18: 14348845 | K18: 14658783
A19: Industrias / almacenes | B19: 480202 | C19: 491487 | D19: 503046 | E19: 514886 | F19: 527016 | G19: 539450 | H19: 552192 | I19: 565246 | J19: 578626 | K19: 592334
A20: Edificios | B20: 18972632 | C20: 19153968 | D20: 19337280 | E20: 19522464 | F20: 19709624 | G20: 19898792 | H20: 20089920 | I20: 20283056 | J20: 20478312 | K20: 20675608
A21: Hoteles | B21: 327007 | C21: 330622 | D21: 334864 | E21: 339841 | F21: 345690 | G21: 352567 | H21: 360658 | I21: 370183 | J21: 381402 | K21: 394627
A22: Parque total | B22: 36010625 | C22: 36601022 | D22: 37205099 | E22: 37823211 | F22: 38455923 | G22: 39103780 | H22: 39767304 | I22: 40447091 | J22: 41143949 | K22: 41858480
A23: Parque con reserva obligatoria (sin Automotor) | B23: 23916622 | C23: 24245785 | D23: 24582994 | E23: 24928467 | F23: 25282655 | G23: 25645971 | H23: 26018806 | I23: 26401629 | J23: 26795104 | K23: 27199697
A24: % del parque con reserva obligatoria | B24: 0.66415459 | C24: 0.66243464 | D24: 0.6607426 | E24: 0.65907855 | F24: 0.65744502 | G24: 0.65584378 | H24: 0.65427634 | I24: 0.65274482 | J24: 0.65125261 | K24: 0.64980135 | L24: 5.3: propiedades con < 5 extintores exentas; en el Excel el único segmento así es Automotor
A26: B. RESERVA DEL CLIENTE (5.3)
A27: Recargas del año (mantenimiento anual) | B27: 6829.7931 | C27: 30662.681 | D27: 61483.058 | E27: 114050.8 | F27: 167870.4 | G27: 228490.11 | H27: 283777.78 | I27: 322612.24 | J27: 347003.72 | K27: 371907.69 | L27: Indexado Dim Técnico fila 44
A28: Parque de reserva obligatoria | B28: 4536.0385 | C28: 20312.022 | D28: 40624.476 | E28: 75168.433 | F28: 110365.56 | G28: 149853.82 | H28: 185669.09 | I28: 210583.47 | J28: 225987.07 | K28: 241666.12
A29: Reserva requerida en clientes | B29: 454 | C29: 2032 | D29: 4063 | E29: 7517 | F29: 11037 | G29: 14986 | H29: 18567 | I29: 21059 | J29: 22599 | K29: 24167 | L29: 5.3: ≥ 10 % de la dotación
A30: VENTA de reserva | B30: 454 | C30: 1578 | D30: 2031 | E30: 3454 | F30: 3520 | G30: 3949 | H30: 3581 | I30: 2492 | J30: 1540 | K30: 1568
A32: C. EXTINTORES SUSTITUTOS (9.4.5) — STOCK
A33: Fracción de retiros cubierta por la reserva del cliente | B33: 0.066473463 | C33: 0.066269483 | D33: 0.066083245 | E33: 0.065909229 | F33: 0.065747149 | G33: 0.065587084 | H33: 0.065427955 | I33: 0.065276507 | J33: 0.065126104 | K33: 0.064981179 | L33: La reserva (10 %) cubre como máximo esa fracción de lo que se retira
A34: Necesidad por tipo = recargas / DH × ciclo × (1 − cobertura)
A35: ABC 1 kg | B35: 37.45756 | C35: 182.83793 | D35: 329.16352 | E35: 604.08704 | F35: 908.4196 | G35: 1265.8545 | H35: 1591.7628 | I35: 1848.6425 | J35: 1981.4713 | K35: 2117.6309
A36: ABC 2,5 kg | B36: 3.5545459 | C36: 13.870359 | D36: 31.758585 | E36: 58.481734 | F36: 84.63119 | G36: 112.3877 | H36: 138.13581 | I36: 153.83106 | J36: 166.47447 | K36: 179.31605
A37: ABC 5 kg | B37: 21.008592 | C37: 84.602649 | D37: 191.55197 | E37: 362.19982 | F37: 521.82591 | G37: 693.51095 | H37: 848.89084 | I37: 940.87698 | J37: 1015.0969 | K37: 1090.6834
A38: ABC 10 kg | B38: 1.2747337 | C38: 4.7158768 | D38: 11.04509 | E38: 21.12924 | F38: 30.668397 | G38: 41.082441 | H38: 50.290883 | I38: 55.70069 | J38: 60.100285 | K38: 64.580501
A39: Agua 10 l | B39: 1.7159877 | C39: 6.9321253 | D39: 15.887678 | E39: 29.816729 | F39: 43.027359 | G39: 57.528451 | H39: 70.513017 | I39: 78.406976 | J39: 84.736697 | K39: 91.173118
A40: AFFF 10 l | B40: 0.2451411 | C40: 1.7379858 | D40: 3.4117482 | E40: 5.6842436 | F40: 8.0179263 | G40: 10.38141 | H40: 12.885687 | I40: 14.577558 | J40: 15.938329 | K40: 17.309803
A41: AFFF 50 l s/ruedas | B41: 0.12257055 | C41: 0.89663469 | D41: 1.7722561 | E41: 3.0322865 | F41: 4.3001055 | G41: 5.5474724 | H41: 6.7835427 | I41: 7.6702478 | J41: 8.3427893 | K41: 9.0231201
A42: BC 5 kg | B42: 0.073542329 | C42: 0.50715694 | D42: 0.95787182 | E42: 1.7191131 | F42: 2.369368 | G42: 3.1468495 | H42: 3.9774398 | I42: 4.4048013 | J42: 4.8086527 | K42: 5.2161018
A43: Sales K 6 l | B43: 0.88250795 | C43: 3.6135248 | D43: 8.0453159 | E43: 14.646182 | F43: 21.14062 | G43: 28.016661 | H43: 34.477766 | I43: 38.595518 | J43: 41.753784 | K43: 44.962462
A44: CO₂ 2 kg | B44: 4.8537937 | C44: 18.285117 | D44: 42.621053 | E44: 81.49504 | F44: 117.71742 | G44: 156.49496 | H44: 191.36979 | I44: 211.57688 | J44: 228.27254 | K44: 245.27523
A45: CO₂ 5 kg | B45: 1.348276 | C45: 6.9343537 | D45: 14.823702 | E45: 26.516871 | F45: 38.217313 | G45: 50.926889 | H45: 63.125725 | I45: 71.274032 | J45: 77.512283 | K45: 83.823471
A46: HCFC/HFC 5 kg | B46: 0.19611288 | C46: 1.2074765 | D46: 2.4876745 | E46: 4.318898 | F46: 6.1931024 | G46: 8.1331188 | H46: 10.1888 | I46: 11.564342 | J46: 12.63909 | K46: 13.722564
... A51: ABC 100 kg s/ruedas | B51: 0.060794992 | C51: 0.29645336 | D51: 0.64438383 | E51: 1.1608603 | F51: 1.6700391 | G51: 2.2192004 | H51: 2.734466 | I51: 3.0705329 | J51: 3.3321015 | K51: 3.5971689
A53: STOCK DE SUSTITUTOS (siempre igual capacidad de extinción o mayor para sustituir)
A54: ABC 5 kg (cubre ABC 1; 2,5 y 5 kg) | B54: 63 | C54: 282 | D54: 553 | E54: 1025 | F54: 1515 | G54: 2072 | H54: 2579 | I54: 2944 | J54: 3164 | K54: 3388
A55: ABC 10 kg | B55: 2 | C55: 5 | D55: 12 | E55: 22 | F55: 31 | G55: 42 | H55: 51 | I55: 56 | J55: 61 | K55: 65
A56: Agua 10 l | B56: 2 | C56: 7 | D56: 16 | E56: 30 | F56: 44 | G56: 58 | H56: 71 | I56: 79 | J56: 85 | K56: 92
A57: AFFF 10 l | B57: 1 | C57: 2 | D57: 4 | E57: 6 | F57: 9 | G57: 11 | H57: 13 | I57: 15 | J57: 16 | K57: 18
A58: AFFF 50 l s/ruedas | B58: 1 | C58: 1 | D58: 2 | E58: 4 | F58: 5 | G58: 6 | H58: 7 | I58: 8 | J58: 9 | K58: 10
A59: BC 5 kg | B59: 1 | C59: 1 | D59: 1 | E59: 2 | F59: 3 | G59: 4 | H59: 4 | I59: 5 | J59: 5 | K59: 6
A60: Sales K 6 l | B60: 1 | C60: 4 | D60: 9 | E60: 15 | F60: 22 | G60: 29 | H60: 35 | I60: 39 | J60: 42 | K60: 45
A61: CO₂ 5 kg (cubre CO₂ 2 y 5 kg) | B61: 7 | C61: 26 | D61: 58 | E61: 109 | F61: 156 | G61: 208 | H61: 255 | I61: 283 | J61: 306 | K61: 330
A62: HCFC/HFC 5 kg | B62: 1 | C62: 2 | D62: 3 | E62: 5 | F62: 7 | G62: 9 | H62: 11 | I62: 12 | J62: 13 | K62: 14
A63: Clase D 9 l | B63: 1 | C63: 1 | D63: 1 | E63: 2 | F63: 3 | G63: 3 | H63: 4 | I63: 4 | J63: 5 | K63: 5
A64: ABC 50 kg s/ruedas (cubre 25 y 50 kg) | B64: 1 | C64: 3 | D64: 7 | E64: 12 | F64: 17 | G64: 23 | H64: 28 | I64: 31 | J64: 34 | K64: 36
A65: ABC 100 kg s/ruedas (cubre 70 y 100 kg) | B65: 1 | C65: 1 | D65: 2 | E65: 3 | F65: 5 | G65: 6 | H65: 7 | I65: 8 | J65: 9 | K65: 9
A66: Total stock de sustitutos | B66: 82 | C66: 335 | D66: 668 | E66: 1235 | F66: 1817 | G66: 2471 | H66: 3065 | I66: 3484 | J66: 3749 | K66: 4018
A68: ALTA ANUAL DE SUSTITUTOS
A69: ABC 5 kg (cubre ABC 1; 2,5 y 5 kg) | B69: 63 | C69: 222.15 | D69: 285.1 | E69: 499.65 | F69: 541.25 | G69: 632.75 | H69: 610.6 | I69: 493.95 | J69: 367.2 | K69: 382.2
A70: ABC 10 kg | B70: 2 | C70: 3.1 | D70: 7.25 | E70: 10.6 | F70: 10.1 | G70: 12.55 | H70: 11.1 | I70: 7.55 | J70: 7.8 | K70: 7.05
A71: Agua 10 l | B71: 2 | C71: 5.1 | D71: 9.35 | E71: 14.8 | F71: 15.5 | G71: 16.2 | H71: 15.9 | I71: 11.55 | J71: 9.95 | K71: 11.25
A72: AFFF 10 l | B72: 1 | C72: 1.05 | D72: 2.1 | E72: 2.2 | F72: 3.3 | G72: 2.45 | H72: 2.55 | I72: 2.65 | J72: 1.75 | K72: 2.8
A73: AFFF 50 l s/ruedas | B73: 1 | C73: 0.05 | D73: 1.05 | E73: 2.1 | F73: 1.2 | G73: 1.25 | H73: 1.3 | I73: 1.35 | J73: 1.4 | K73: 1.45
A74: BC 5 kg | B74: 1 | C74: 0.05 | D74: 0.05 | E74: 1.05 | F74: 1.1 | G74: 1.15 | H74: 0.2 | I74: 1.2 | J74: 0.25 | K74: 1.25
A75: Sales K 6 l | B75: 1 | C75: 3.05 | D75: 5.2 | E75: 6.45 | F75: 7.75 | G75: 8.1 | H75: 7.45 | I75: 5.75 | J75: 4.95 | K75: 5.1
A76: CO₂ 5 kg (cubre CO₂ 2 y 5 kg) | B76: 7 | C76: 19.233333 | D76: 32.866667 | E76: 52.933333 | F76: 50.633333 | G76: 57.2 | H76: 53.933333 | I76: 36.5 | J76: 32.433333 | K76: 34.2
A77: HCFC/HFC 5 kg | B77: 1 | C77: 1.05 | D77: 1.1 | E77: 2.15 | F77: 2.25 | G77: 2.35 | H77: 2.45 | I77: 1.55 | J77: 1.6 | K77: 1.65
A78: Clase D 9 l | B78: 1 | C78: 0.05 | D78: 0.05 | E78: 1.05 | F78: 1.1 | G78: 0.15 | H78: 1.15 | I78: 0.2 | J78: 1.2 | K78: 0.25
A79: ABC 50 kg s/ruedas (cubre 25 y 50 kg) | B79: 1 | C79: 2.05 | D79: 4.15 | E79: 5.35 | F79: 5.6 | G79: 6.85 | H79: 6.15 | I79: 4.4 | J79: 4.55 | K79: 3.7
A80: ABC 100 kg s/ruedas (cubre 70 y 100 kg) | B80: 1 | C80: 0.05 | D80: 1.05 | E80: 1.1 | F80: 2.15 | G80: 1.25 | H80: 1.3 | I80: 1.35 | J80: 1.4 | K80: 0.45
... A82: Recargas de los sustitutos (= stock: se mantienen cada año, 9.4.5) | B82: 82 | C82: 335 | D82: 668 | E82: 1235 | F82: 1817 | G82: 2471 | H82: 3065 | I82: 3484 | J82: 3749 | K82: 4018

Sheet Parametros
A1: Parámetros del MRP
A3: Fracción de recargas con agente 100 % nuevo (equipo accionado) | B3: 1 | C3: IRAM 3517-2:2020 9.9.1.4: el polvo de un extintor accionado no se reutiliza. 100 % = cota superior. El resto de las recargas usa el caso B del BOM (recuperado + reposición de mermas). Ajustar con el dato real de la planta de recargas.
A6: Año | B6: ='Indexado Dim Técnico'!B26 | C6: ='Indexado Dim Técnico'!C26 | D6: ='Indexado Dim Técnico'!D26 | E6: ='Indexado Dim Técnico'!E26 | F6: ='Indexado Dim Técnico'!F26 | G6: ='Indexado Dim Técnico'!G26 | H6: ='Indexado Dim Técnico'!H26 | I6: ='Indexado Dim Técnico'!I26 | ... K6: ='Indexado Dim Técnico'!K26
A7: % destino CABA — unidades nuevas (zonal de revendidos, filas 79-82) | B7: ='Indexado Dim Técnico'!L79+'Indexado Dim Técnico'!L80+'Indexado Dim Técnico'!L81+'Indexado Dim Técnico'!L82 | C7: ='Indexado Dim Técnico'!M79+'Indexado Dim Técnico'!M80+'Indexado Dim Técnico'!M81+'Indexado Dim Técnico'!M82 | D7: ='Indexado Dim Técnico'!N79+'Indexado Dim Técnico'!N80+'Indexado Dim Técnico'!N81+'Indexado Dim Técnico'!N82 | E7: ='Indexado Dim Técnico'!O79+'Indexado Dim Técnico'!O80+'Indexado Dim Técnico'!O81+'Indexado Dim Técnico'!O82 | F7: ='Indexado Dim Técnico'!P79+'Indexado Dim Técnico'!P80+'Indexado Dim Técnico'!P81+'Indexado Dim Técnico'!P82 | G7: ='Indexado Dim Técnico'!Q79+'Indexado Dim Técnico'!Q80+'Indexado Dim Técnico'!Q81+'Indexado Dim Técnico'!Q82 | H7: ='Indexado Dim Técnico'!R79+'Indexado Dim Técnico'!R80+'Indexado Dim Técnico'!R81+'Indexado Dim Técnico'!R82 | I7: ='Indexado Dim Técnico'!S79+'Indexado Dim Técnico'!S80+'Indexado Dim Técnico'!S81+'Indexado Dim Técnico'!S82 | ... K7: ='Indexado Dim Técnico'!U79+'Indexado Dim Técnico'!U80+'Indexado Dim Técnico'!U81+'Indexado Dim Técnico'!U82
A8: % destino CABA — recargas (zonal de recargas, filas 61-64) | B8: ='Indexado Dim Técnico'!L61+'Indexado Dim Técnico'!L62+'Indexado Dim Técnico'!L63+'Indexado Dim Técnico'!L64 | C8: ='Indexado Dim Técnico'!M61+'Indexado Dim Técnico'!M62+'Indexado Dim Técnico'!M63+'Indexado Dim Técnico'!M64 | D8: ='Indexado Dim Técnico'!N61+'Indexado Dim Técnico'!N62+'Indexado Dim Técnico'!N63+'Indexado Dim Técnico'!N64 | E8: ='Indexado Dim Técnico'!O61+'Indexado Dim Técnico'!O62+'Indexado Dim Técnico'!O63+'Indexado Dim Técnico'!O64 | F8: ='Indexado Dim Técnico'!P61+'Indexado Dim Técnico'!P62+'Indexado Dim Técnico'!P63+'Indexado Dim Técnico'!P64 | G8: ='Indexado Dim Técnico'!Q61+'Indexado Dim Técnico'!Q62+'Indexado Dim Técnico'!Q63+'Indexado Dim Técnico'!Q64 | H8: ='Indexado Dim Técnico'!R61+'Indexado Dim Técnico'!R62+'Indexado Dim Técnico'!R63+'Indexado Dim Técnico'!R64 | I8: ='Indexado Dim Técnico'!S61+'Indexado Dim Técnico'!S62+'Indexado Dim Técnico'!S63+'Indexado Dim Técnico'!S64 | ... K8: ='Indexado Dim Técnico'!U61+'Indexado Dim Técnico'!U62+'Indexado Dim Técnico'!U63+'Indexado Dim Técnico'!U64
A9: % recargas planta COMERCIAL (zonas de Indexado V60: CABA N/E/O, PBA Norte 1°-3°) | B9: ='Indexado Dim Técnico'!L61+'Indexado Dim Técnico'!L62+'Indexado Dim Técnico'!L64+'Indexado Dim Técnico'!L68+'Indexado Dim Técnico'!L69+'Indexado Dim Técnico'!L70 | C9: ='Indexado Dim Técnico'!M61+'Indexado Dim Técnico'!M62+'Indexado Dim Técnico'!M64+'Indexado Dim Técnico'!M68+'Indexado Dim Técnico'!M69+'Indexado Dim Técnico'!M70 | D9: ='Indexado Dim Técnico'!N61+'Indexado Dim Técnico'!N62+'Indexado Dim Técnico'!N64+'Indexado Dim Técnico'!N68+'Indexado Dim Técnico'!N69+'Indexado Dim Técnico'!N70 | E9: ='Indexado Dim Técnico'!O61+'Indexado Dim Técnico'!O62+'Indexado Dim Técnico'!O64+'Indexado Dim Técnico'!O68+'Indexado Dim Técnico'!O69+'Indexado Dim Técnico'!O70 | F9: ='Indexado Dim Técnico'!P61+'Indexado Dim Técnico'!P62+'Indexado Dim Técnico'!P64+'Indexado Dim Técnico'!P68+'Indexado Dim Técnico'!P69+'Indexado Dim Técnico'!P70 | G9: ='Indexado Dim Técnico'!Q61+'Indexado Dim Técnico'!Q62+'Indexado Dim Técnico'!Q64+'Indexado Dim Técnico'!Q68+'Indexado Dim Técnico'!Q69+'Indexado Dim Técnico'!Q70 | H9: ='Indexado Dim Técnico'!R61+'Indexado Dim Técnico'!R62+'Indexado Dim Técnico'!R64+'Indexado Dim Técnico'!R68+'Indexado Dim Técnico'!R69+'Indexado Dim Técnico'!R70 | I9: ='Indexado Dim Técnico'!S61+'Indexado Dim Técnico'!S62+'Indexado Dim Técnico'!S64+'Indexado Dim Técnico'!S68+'Indexado Dim Técnico'!S69+'Indexado Dim Técnico'!S70 | ... K9: ='Indexado Dim Técnico'!U61+'Indexado Dim Técnico'!U62+'Indexado Dim Técnico'!U64+'Indexado Dim Técnico'!U68+'Indexado Dim Técnico'!U69+'Indexado Dim Técnico'!U70
A10: % recargas planta INDUSTRIAL (CABA Sur, PBA Sur 1°-3°, PBA Oeste 1°-3°, Interior) | B10: =1-B9 | C10: =1-C9 | D10: =1-D9 | E10: =1-E9 | F10: =1-F9 | G10: =1-G9 | H10: =1-H9 | I10: =1-I9 | ... K10: =1-K9
A12: Destino: lo que exige una norma de PBA (oblea Res. 522/07, tarjeta DPS Res. 349/07) se aplica a la proporción PBA; lo de CABA (tarjeta AGC, Ord. 40.473) a la proporción CABA. Para unidades nuevas se usa la distribución zonal de revendidos (única de unidades nuevas en el Indexado).

Sheet Demanda
A1: Demanda por producto (unidades/año) — fórmulas sobre las dos primeras hojas
A3: Producto | B3: ='Indexado Dim Técnico'!B26 | C3: ='Indexado Dim Técnico'!C26 | D3: ='Indexado Dim Técnico'!D26 | E3: ='Indexado Dim Técnico'!E26 | F3: ='Indexado Dim Técnico'!F26 | G3: ='Indexado Dim Técnico'!G26 | H3: ='Indexado Dim Técnico'!H26 | I3: ='Indexado Dim Técnico'!I26 | ... K3: ='Indexado Dim Técnico'!K26 | L3: Origen
A5: MATAFUEGOS FABRICADOS (unidades nuevas + venta de reserva + alta de sustitutos)
A6: FL_MAT_ABC_1kg | B6: ='Indexado Dim Técnico'!B3 | C6: ='Indexado Dim Técnico'!C3 | D6: ='Indexado Dim Técnico'!D3 | E6: ='Indexado Dim Técnico'!E3 | F6: ='Indexado Dim Técnico'!F3 | G6: ='Indexado Dim Técnico'!G3 | H6: ='Indexado Dim Técnico'!H3 | I6: ='Indexado Dim Técnico'!I3 | ... K6: ='Indexado Dim Técnico'!K3 | L6: Indexado fila 3
A7: FL_MAT_ABC_2.5kg | B7: ='Indexado Dim Técnico'!B4 | C7: ='Indexado Dim Técnico'!C4 | D7: ='Indexado Dim Técnico'!D4 | E7: ='Indexado Dim Técnico'!E4 | F7: ='Indexado Dim Técnico'!F4 | G7: ='Indexado Dim Técnico'!G4 | H7: ='Indexado Dim Técnico'!H4 | I7: ='Indexado Dim Técnico'!I4 | ... K7: ='Indexado Dim Técnico'!K4 | L7: Indexado fila 4
A8: FL_MAT_ABC_5kg | B8: ='Indexado Dim Técnico'!B5+'Reservas y Sustitutos'!B30+'Reservas y Sustitutos'!B69 | C8: ='Indexado Dim Técnico'!C5+'Reservas y Sustitutos'!C30+'Reservas y Sustitutos'!C69 | D8: ='Indexado Dim Técnico'!D5+'Reservas y Sustitutos'!D30+'Reservas y Sustitutos'!D69 | E8: ='Indexado Dim Técnico'!E5+'Reservas y Sustitutos'!E30+'Reservas y Sustitutos'!E69 | F8: ='Indexado Dim Técnico'!F5+'Reservas y Sustitutos'!F30+'Reservas y Sustitutos'!F69 | G8: ='Indexado Dim Técnico'!G5+'Reservas y Sustitutos'!G30+'Reservas y Sustitutos'!G69 | H8: ='Indexado Dim Técnico'!H5+'Reservas y Sustitutos'!H30+'Reservas y Sustitutos'!H69 | I8: ='Indexado Dim Técnico'!I5+'Reservas y Sustitutos'!I30+'Reservas y Sustitutos'!I69 | ... K8: ='Indexado Dim Técnico'!K5+'Reservas y Sustitutos'!K30+'Reservas y Sustitutos'!K69 | L8: Indexado fila 5 + Reservas fila 30 + Reservas fila 69
A9: FL_MAT_ABC_10kg | B9: ='Indexado Dim Técnico'!B6+'Reservas y Sustitutos'!B70 | C9: ='Indexado Dim Técnico'!C6+'Reservas y Sustitutos'!C70 | D9: ='Indexado Dim Técnico'!D6+'Reservas y Sustitutos'!D70 | E9: ='Indexado Dim Técnico'!E6+'Reservas y Sustitutos'!E70 | F9: ='Indexado Dim Técnico'!F6+'Reservas y Sustitutos'!F70 | G9: ='Indexado Dim Técnico'!G6+'Reservas y Sustitutos'!G70 | H9: ='Indexado Dim Técnico'!H6+'Reservas y Sustitutos'!H70 | I9: ='Indexado Dim Técnico'!I6+'Reservas y Sustitutos'!I70 | ... K9: ='Indexado Dim Técnico'!K6+'Reservas y Sustitutos'!K70 | L9: Indexado fila 6 + Reservas fila 70
A10: FL_MAT_ABC_25kg | B10: ='Indexado Dim Técnico'!B7 | C10: ='Indexado Dim Técnico'!C7 | D10: ='Indexado Dim Técnico'!D7 | E10: ='Indexado Dim Técnico'!E7 | F10: ='Indexado Dim Técnico'!F7 | G10: ='Indexado Dim Técnico'!G7 | H10: ='Indexado Dim Técnico'!H7 | I10: ='Indexado Dim Técnico'!I7 | ... K10: ='Indexado Dim Técnico'!K7 | L10: Indexado fila 7
A11: FL_MAT_ABC_50kg | B11: ='Indexado Dim Técnico'!B8+'Reservas y Sustitutos'!B79 | C11: ='Indexado Dim Técnico'!C8+'Reservas y Sustitutos'!C79 | D11: ='Indexado Dim Técnico'!D8+'Reservas y Sustitutos'!D79 | E11: ='Indexado Dim Técnico'!E8+'Reservas y Sustitutos'!E79 | F11: ='Indexado Dim Técnico'!F8+'Reservas y Sustitutos'!F79 | G11: ='Indexado Dim Técnico'!G8+'Reservas y Sustitutos'!G79 | H11: ='Indexado Dim Técnico'!H8+'Reservas y Sustitutos'!H79 | I11: ='Indexado Dim Técnico'!I8+'Reservas y Sustitutos'!I79 | ... K11: ='Indexado Dim Técnico'!K8+'Reservas y Sustitutos'!K79 | L11: Indexado fila 8 + Reservas fila 79
A12: FL_MAT_ABC_70kg | B12: ='Indexado Dim Técnico'!B9 | C12: ='Indexado Dim Técnico'!C9 | D12: ='Indexado Dim Técnico'!D9 | E12: ='Indexado Dim Técnico'!E9 | F12: ='Indexado Dim Técnico'!F9 | G12: ='Indexado Dim Técnico'!G9 | H12: ='Indexado Dim Técnico'!H9 | I12: ='Indexado Dim Técnico'!I9 | ... K12: ='Indexado Dim Técnico'!K9 | L12: Indexado fila 9
A13: FL_MAT_ABC_100kg | B13: ='Indexado Dim Técnico'!B10+'Reservas y Sustitutos'!B80 | C13: ='Indexado Dim Técnico'!C10+'Reservas y Sustitutos'!C80 | D13: ='Indexado Dim Técnico'!D10+'Reservas y Sustitutos'!D80 | E13: ='Indexado Dim Técnico'!E10+'Reservas y Sustitutos'!E80 | F13: ='Indexado Dim Técnico'!F10+'Reservas y Sustitutos'!F80 | G13: ='Indexado Dim Técnico'!G10+'Reservas y Sustitutos'!G80 | H13: ='Indexado Dim Técnico'!H10+'Reservas y Sustitutos'!H80 | I13: ='Indexado Dim Técnico'!I10+'Reservas y Sustitutos'!I80 | ... K13: ='Indexado Dim Técnico'!K10+'Reservas y Sustitutos'!K80 | L13: Indexado fila 10 + Reservas fila 80
A15: MATAFUEGOS REVENDIDOS (compra de unidades nuevas + alta de sustitutos)
A16: FL_MAT_AGUA_10l | B16: ='Indexado Dim Técnico'!B48+'Reservas y Sustitutos'!B71 | C16: ='Indexado Dim Técnico'!C48+'Reservas y Sustitutos'!C71 | D16: ='Indexado Dim Técnico'!D48+'Reservas y Sustitutos'!D71 | E16: ='Indexado Dim Técnico'!E48+'Reservas y Sustitutos'!E71 | F16: ='Indexado Dim Técnico'!F48+'Reservas y Sustitutos'!F71 | G16: ='Indexado Dim Técnico'!G48+'Reservas y Sustitutos'!G71 | H16: ='Indexado Dim Técnico'!H48+'Reservas y Sustitutos'!H71 | I16: ='Indexado Dim Técnico'!I48+'Reservas y Sustitutos'!I71 | ... K16: ='Indexado Dim Técnico'!K48+'Reservas y Sustitutos'!K71 | L16: Indexado fila 48 + Reservas fila 71
A17: FL_MAT_AFFF_10l | B17: ='Indexado Dim Técnico'!B49+'Reservas y Sustitutos'!B72 | C17: ='Indexado Dim Técnico'!C49+'Reservas y Sustitutos'!C72 | D17: ='Indexado Dim Técnico'!D49+'Reservas y Sustitutos'!D72 | E17: ='Indexado Dim Técnico'!E49+'Reservas y Sustitutos'!E72 | F17: ='Indexado Dim Técnico'!F49+'Reservas y Sustitutos'!F72 | G17: ='Indexado Dim Técnico'!G49+'Reservas y Sustitutos'!G72 | H17: ='Indexado Dim Técnico'!H49+'Reservas y Sustitutos'!H72 | I17: ='Indexado Dim Técnico'!I49+'Reservas y Sustitutos'!I72 | ... K17: ='Indexado Dim Técnico'!K49+'Reservas y Sustitutos'!K72 | L17: Indexado fila 49 + Reservas fila 72
A18: FL_MAT_AFFF_50l | B18: ='Indexado Dim Técnico'!B50+'Reservas y Sustitutos'!B73 | C18: ='Indexado Dim Técnico'!C50+'Reservas y Sustitutos'!C73 | D18: ='Indexado Dim Técnico'!D50+'Reservas y Sustitutos'!D73 | E18: ='Indexado Dim Técnico'!E50+'Reservas y Sustitutos'!E73 | F18: ='Indexado Dim Técnico'!F50+'Reservas y Sustitutos'!F73 | G18: ='Indexado Dim Técnico'!G50+'Reservas y Sustitutos'!G73 | H18: ='Indexado Dim Técnico'!H50+'Reservas y Sustitutos'!H73 | I18: ='Indexado Dim Técnico'!I50+'Reservas y Sustitutos'!I73 | ... K18: ='Indexado Dim Técnico'!K50+'Reservas y Sustitutos'!K73 | L18: Indexado fila 50 + Reservas fila 73
A19: FL_MAT_BC_5kg | B19: ='Indexado Dim Técnico'!B51+'Reservas y Sustitutos'!B74 | C19: ='Indexado Dim Técnico'!C51+'Reservas y Sustitutos'!C74 | D19: ='Indexado Dim Técnico'!D51+'Reservas y Sustitutos'!D74 | E19: ='Indexado Dim Técnico'!E51+'Reservas y Sustitutos'!E74 | F19: ='Indexado Dim Técnico'!F51+'Reservas y Sustitutos'!F74 | G19: ='Indexado Dim Técnico'!G51+'Reservas y Sustitutos'!G74 | H19: ='Indexado Dim Técnico'!H51+'Reservas y Sustitutos'!H74 | I19: ='Indexado Dim Técnico'!I51+'Reservas y Sustitutos'!I74 | ... K19: ='Indexado Dim Técnico'!K51+'Reservas y Sustitutos'!K74 | L19: Indexado fila 51 + Reservas fila 74
A20: FL_MAT_SALESK_6l | B20: ='Indexado Dim Técnico'!B52+'Reservas y Sustitutos'!B75 | C20: ='Indexado Dim Técnico'!C52+'Reservas y Sustitutos'!C75 | D20: ='Indexado Dim Técnico'!D52+'Reservas y Sustitutos'!D75 | E20: ='Indexado Dim Técnico'!E52+'Reservas y Sustitutos'!E75 | F20: ='Indexado Dim Técnico'!F52+'Reservas y Sustitutos'!F75 | G20: ='Indexado Dim Técnico'!G52+'Reservas y Sustitutos'!G75 | H20: ='Indexado Dim Técnico'!H52+'Reservas y Sustitutos'!H75 | I20: ='Indexado Dim Técnico'!I52+'Reservas y Sustitutos'!I75 | ... K20: ='Indexado Dim Técnico'!K52+'Reservas y Sustitutos'!K75 | L20: Indexado fila 52 + Reservas fila 75
A21: FL_MAT_CO2_2kg | B21: ='Indexado Dim Técnico'!B53 | C21: ='Indexado Dim Técnico'!C53 | D21: ='Indexado Dim Técnico'!D53 | E21: ='Indexado Dim Técnico'!E53 | F21: ='Indexado Dim Técnico'!F53 | G21: ='Indexado Dim Técnico'!G53 | H21: ='Indexado Dim Técnico'!H53 | I21: ='Indexado Dim Técnico'!I53 | ... K21: ='Indexado Dim Técnico'!K53 | L21: Indexado fila 53
A22: FL_MAT_CO2_5kg | B22: ='Indexado Dim Técnico'!B54+'Reservas y Sustitutos'!B76 | C22: ='Indexado Dim Técnico'!C54+'Reservas y Sustitutos'!C76 | D22: ='Indexado Dim Técnico'!D54+'Reservas y Sustitutos'!D76 | E22: ='Indexado Dim Técnico'!E54+'Reservas y Sustitutos'!E76 | F22: ='Indexado Dim Técnico'!F54+'Reservas y Sustitutos'!F76 | G22: ='Indexado Dim Técnico'!G54+'Reservas y Sustitutos'!G76 | H22: ='Indexado Dim Técnico'!H54+'Reservas y Sustitutos'!H76 | I22: ='Indexado Dim Técnico'!I54+'Reservas y Sustitutos'!I76 | ... K22: ='Indexado Dim Técnico'!K54+'Reservas y Sustitutos'!K76 | L22: Indexado fila 54 + Reservas fila 76
A23: FL_MAT_HCFC-HFC_5kg | B23: ='Indexado Dim Técnico'!B55+'Reservas y Sustitutos'!B77 | C23: ='Indexado Dim Técnico'!C55+'Reservas y Sustitutos'!C77 | D23: ='Indexado Dim Técnico'!D55+'Reservas y Sustitutos'!D77 | E23: ='Indexado Dim Técnico'!E55+'Reservas y Sustitutos'!E77 | F23: ='Indexado Dim Técnico'!F55+'Reservas y Sustitutos'!F77 | G23: ='Indexado Dim Técnico'!G55+'Reservas y Sustitutos'!G77 | H23: ='Indexado Dim Técnico'!H55+'Reservas y Sustitutos'!H77 | I23: ='Indexado Dim Técnico'!I55+'Reservas y Sustitutos'!I77 | ... K23: ='Indexado Dim Técnico'!K55+'Reservas y Sustitutos'!K77 | L23: Indexado fila 55 + Reservas fila 77
A24: FL_MAT_CLASED_9l | B24: ='Indexado Dim Técnico'!B56+'Reservas y Sustitutos'!B78 | C24: ='Indexado Dim Técnico'!C56+'Reservas y Sustitutos'!C78 | D24: ='Indexado Dim Técnico'!D56+'Reservas y Sustitutos'!D78 | E24: ='Indexado Dim Técnico'!E56+'Reservas y Sustitutos'!E78 | F24: ='Indexado Dim Técnico'!F56+'Reservas y Sustitutos'!F78 | G24: ='Indexado Dim Técnico'!G56+'Reservas y Sustitutos'!G78 | H24: ='Indexado Dim Técnico'!H56+'Reservas y Sustitutos'!H78 | I24: ='Indexado Dim Técnico'!I56+'Reservas y Sustitutos'!I78 | ... K24: ='Indexado Dim Técnico'!K56+'Reservas y Sustitutos'!K78 | L24: Indexado fila 56 + Reservas fila 78
A26: CILINDROS SUELTOS (venta)
A27: FL_REC_ABC_1kg | B27: ='Indexado Dim Técnico'!B15 | C27: ='Indexado Dim Técnico'!C15 | D27: ='Indexado Dim Técnico'!D15 | E27: ='Indexado Dim Técnico'!E15 | F27: ='Indexado Dim Técnico'!F15 | G27: ='Indexado Dim Técnico'!G15 | H27: ='Indexado Dim Técnico'!H15 | I27: ='Indexado Dim Técnico'!I15 | ... K27: ='Indexado Dim Técnico'!K15 | L27: Indexado fila 15
A28: FL_REC_ABC_2.5kg | B28: ='Indexado Dim Técnico'!B16 | C28: ='Indexado Dim Técnico'!C16 | D28: ='Indexado Dim Técnico'!D16 | E28: ='Indexado Dim Técnico'!E16 | F28: ='Indexado Dim Técnico'!F16 | G28: ='Indexado Dim Técnico'!G16 | H28: ='Indexado Dim Técnico'!H16 | I28: ='Indexado Dim Técnico'!I16 | ... K28: ='Indexado Dim Técnico'!K16 | L28: Indexado fila 16
A29: FL_REC_ABC_5kg | B29: ='Indexado Dim Técnico'!B17 | C29: ='Indexado Dim Técnico'!C17 | D29: ='Indexado Dim Técnico'!D17 | E29: ='Indexado Dim Técnico'!E17 | F29: ='Indexado Dim Técnico'!F17 | G29: ='Indexado Dim Técnico'!G17 | H29: ='Indexado Dim Técnico'!H17 | I29: ='Indexado Dim Técnico'!I17 | ... K29: ='Indexado Dim Técnico'!K17 | L29: Indexado fila 17
A30: FL_REC_ABC_10kg | B30: ='Indexado Dim Técnico'!B18 | C30: ='Indexado Dim Técnico'!C18 | D30: ='Indexado Dim Técnico'!D18 | E30: ='Indexado Dim Técnico'!E18 | F30: ='Indexado Dim Técnico'!F18 | G30: ='Indexado Dim Técnico'!G18 | H30: ='Indexado Dim Técnico'!H18 | I30: ='Indexado Dim Técnico'!I18 | ... K30: ='Indexado Dim Técnico'!K18 | L30: Indexado fila 18
A31: FL_REC_ABC_25kg | B31: ='Indexado Dim Técnico'!B19 | C31: ='Indexado Dim Técnico'!C19 | D31: ='Indexado Dim Técnico'!D19 | E31: ='Indexado Dim Técnico'!E19 | F31: ='Indexado Dim Técnico'!F19 | G31: ='Indexado Dim Técnico'!G19 | H31: ='Indexado Dim Técnico'!H19 | I31: ='Indexado Dim Técnico'!I19 | ... K31: ='Indexado Dim Técnico'!K19 | L31: Indexado fila 19
A32: FL_REC_ABC_50kg | B32: ='Indexado Dim Técnico'!B20 | C32: ='Indexado Dim Técnico'!C20 | D32: ='Indexado Dim Técnico'!D20 | E32: ='Indexado Dim Técnico'!E20 | F32: ='Indexado Dim Técnico'!F20 | G32: ='Indexado Dim Técnico'!G20 | H32: ='Indexado Dim Técnico'!H20 | I32: ='Indexado Dim Técnico'!I20 | ... K32: ='Indexado Dim Técnico'!K20 | L32: Indexado fila 20
A33: FL_REC_ABC_70kg | B33: ='Indexado Dim Técnico'!B21 | C33: ='Indexado Dim Técnico'!C21 | D33: ='Indexado Dim Técnico'!D21 | E33: ='Indexado Dim Técnico'!E21 | F33: ='Indexado Dim Técnico'!F21 | G33: ='Indexado Dim Técnico'!G21 | H33: ='Indexado Dim Técnico'!H21 | I33: ='Indexado Dim Técnico'!I21 | ... K33: ='Indexado Dim Técnico'!K21 | L33: Indexado fila 21
A34: FL_REC_ABC_100kg | B34: ='Indexado Dim Técnico'!B22 | C34: ='Indexado Dim Técnico'!C22 | D34: ='Indexado Dim Técnico'!D22 | E34: ='Indexado Dim Técnico'!E22 | F34: ='Indexado Dim Técnico'!F22 | G34: ='Indexado Dim Técnico'!G22 | H34: ='Indexado Dim Técnico'!H22 | I34: ='Indexado Dim Técnico'!I22 | ... K34: ='Indexado Dim Técnico'!K22 | L34: Indexado fila 22
A36: KITS DE SUSTITUTO (alta anual de sustitutos por pool)
A37: FL_SUS_ABC_5kg | B37: ='Reservas y Sustitutos'!B69 | C37: ='Reservas y Sustitutos'!C69 | D37: ='Reservas y Sustitutos'!D69 | E37: ='Reservas y Sustitutos'!E69 | F37: ='Reservas y Sustitutos'!F69 | G37: ='Reservas y Sustitutos'!G69 | H37: ='Reservas y Sustitutos'!H69 | I37: ='Reservas y Sustitutos'!I69 | ... K37: ='Reservas y Sustitutos'!K69 | L37: Reservas fila 69
A38: FL_SUS_ABC_10kg | B38: ='Reservas y Sustitutos'!B70 | C38: ='Reservas y Sustitutos'!C70 | D38: ='Reservas y Sustitutos'!D70 | E38: ='Reservas y Sustitutos'!E70 | F38: ='Reservas y Sustitutos'!F70 | G38: ='Reservas y Sustitutos'!G70 | H38: ='Reservas y Sustitutos'!H70 | I38: ='Reservas y Sustitutos'!I70 | ... K38: ='Reservas y Sustitutos'!K70 | L38: Reservas fila 70
A39: FL_SUS_AGUA_10l | B39: ='Reservas y Sustitutos'!B71 | C39: ='Reservas y Sustitutos'!C71 | D39: ='Reservas y Sustitutos'!D71 | E39: ='Reservas y Sustitutos'!E71 | F39: ='Reservas y Sustitutos'!F71 | G39: ='Reservas y Sustitutos'!G71 | H39: ='Reservas y Sustitutos'!H71 | I39: ='Reservas y Sustitutos'!I71 | ... K39: ='Reservas y Sustitutos'!K71 | L39: Reservas fila 71
A40: FL_SUS_AFFF_10l | B40: ='Reservas y Sustitutos'!B72 | C40: ='Reservas y Sustitutos'!C72 | D40: ='Reservas y Sustitutos'!D72 | E40: ='Reservas y Sustitutos'!E72 | F40: ='Reservas y Sustitutos'!F72 | G40: ='Reservas y Sustitutos'!G72 | H40: ='Reservas y Sustitutos'!H72 | I40: ='Reservas y Sustitutos'!I72 | ... K40: ='Reservas y Sustitutos'!K72 | L40: Reservas fila 72
A41: FL_SUS_AFFF_50l | B41: ='Reservas y Sustitutos'!B73 | C41: ='Reservas y Sustitutos'!C73 | D41: ='Reservas y Sustitutos'!D73 | E41: ='Reservas y Sustitutos'!E73 | F41: ='Reservas y Sustitutos'!F73 | G41: ='Reservas y Sustitutos'!G73 | H41: ='Reservas y Sustitutos'!H73 | I41: ='Reservas y Sustitutos'!I73 | ... K41: ='Reservas y Sustitutos'!K73 | L41: Reservas fila 73
A42: FL_SUS_BC_5kg | B42: ='Reservas y Sustitutos'!B74 | C42: ='Reservas y Sustitutos'!C74 | D42: ='Reservas y Sustitutos'!D74 | E42: ='Reservas y Sustitutos'!E74 | F42: ='Reservas y Sustitutos'!F74 | G42: ='Reservas y Sustitutos'!G74 | H42: ='Reservas y Sustitutos'!H74 | I42: ='Reservas y Sustitutos'!I74 | ... K42: ='Reservas y Sustitutos'!K74 | L42: Reservas fila 74
A43: FL_SUS_SALESK_6l | B43: ='Reservas y Sustitutos'!B75 | C43: ='Reservas y Sustitutos'!C75 | D43: ='Reservas y Sustitutos'!D75 | E43: ='Reservas y Sustitutos'!E75 | F43: ='Reservas y Sustitutos'!F75 | G43: ='Reservas y Sustitutos'!G75 | H43: ='Reservas y Sustitutos'!H75 | I43: ='Reservas y Sustitutos'!I75 | ... K43: ='Reservas y Sustitutos'!K75 | L43: Reservas fila 75
A44: FL_SUS_CO2_5kg | B44: ='Reservas y Sustitutos'!B76 | C44: ='Reservas y Sustitutos'!C76 | D44: ='Reservas y Sustitutos'!D76 | E44: ='Reservas y Sustitutos'!E76 | F44: ='Reservas y Sustitutos'!F76 | G44: ='Reservas y Sustitutos'!G76 | H44: ='Reservas y Sustitutos'!H76 | I44: ='Reservas y Sustitutos'!I76 | ... K44: ='Reservas y Sustitutos'!K76 | L44: Reservas fila 76
A45: FL_SUS_HCFC-HFC_5kg | B45: ='Reservas y Sustitutos'!B77 | C45: ='Reservas y Sustitutos'!C77 | D45: ='Reservas y Sustitutos'!D77 | E45: ='Reservas y Sustitutos'!E77 | F45: ='Reservas y Sustitutos'!F77 | G45: ='Reservas y Sustitutos'!G77 | H45: ='Reservas y Sustitutos'!H77 | I45: ='Reservas y Sustitutos'!I77 | ... K45: ='Reservas y Sustitutos'!K77 | L45: Reservas fila 77
A46: FL_SUS_CLASED_9l | B46: ='Reservas y Sustitutos'!B78 | C46: ='Reservas y Sustitutos'!C78 | D46: ='Reservas y Sustitutos'!D78 | E46: ='Reservas y Sustitutos'!E78 | F46: ='Reservas y Sustitutos'!F78 | G46: ='Reservas y Sustitutos'!G78 | H46: ='Reservas y Sustitutos'!H78 | I46: ='Reservas y Sustitutos'!I78 | ... K46: ='Reservas y Sustitutos'!K78 | L46: Reservas fila 78
A47: FL_SUS_ABC_50kg | B47: ='Reservas y Sustitutos'!B79 | C47: ='Reservas y Sustitutos'!C79 | D47: ='Reservas y Sustitutos'!D79 | E47: ='Reservas y Sustitutos'!E79 | F47: ='Reservas y Sustitutos'!F79 | G47: ='Reservas y Sustitutos'!G79 | H47: ='Reservas y Sustitutos'!H79 | I47: ='Reservas y Sustitutos'!I79 | ... K47: ='Reservas y Sustitutos'!K79 | L47: Reservas fila 79
A48: FL_SUS_ABC_100kg | B48: ='Reservas y Sustitutos'!B80 | C48: ='Reservas y Sustitutos'!C80 | D48: ='Reservas y Sustitutos'!D80 | E48: ='Reservas y Sustitutos'!E80 | F48: ='Reservas y Sustitutos'!F80 | G48: ='Reservas y Sustitutos'!G80 | H48: ='Reservas y Sustitutos'!H80 | I48: ='Reservas y Sustitutos'!I80 | ... K48: ='Reservas y Sustitutos'!K80 | L48: Reservas fila 80
A50: RECARGAS (Indexado + mantenimiento anual del stock de sustitutos)
A51: FL_MAT_ABC_1kg | B51: ='Indexado Dim Técnico'!B27 | C51: ='Indexado Dim Técnico'!C27 | D51: ='Indexado Dim Técnico'!D27 | E51: ='Indexado Dim Técnico'!E27 | F51: ='Indexado Dim Técnico'!F27 | G51: ='Indexado Dim Técnico'!G27 | H51: ='Indexado Dim Técnico'!H27 | I51: ='Indexado Dim Técnico'!I27 | ... K51: ='Indexado Dim Técnico'!K27 | L51: Indexado fila 27
A52: FL_MAT_ABC_2.5kg | B52: ='Indexado Dim Técnico'!B28 | C52: ='Indexado Dim Técnico'!C28 | D52: ='Indexado Dim Técnico'!D28 | E52: ='Indexado Dim Técnico'!E28 | F52: ='Indexado Dim Técnico'!F28 | G52: ='Indexado Dim Técnico'!G28 | H52: ='Indexado Dim Técnico'!H28 | I52: ='Indexado Dim Técnico'!I28 | ... K52: ='Indexado Dim Técnico'!K28 | L52: Indexado fila 28
A53: FL_MAT_ABC_5kg | B53: ='Indexado Dim Técnico'!B29+'Reservas y Sustitutos'!B54 | C53: ='Indexado Dim Técnico'!C29+'Reservas y Sustitutos'!C54 | D53: ='Indexado Dim Técnico'!D29+'Reservas y Sustitutos'!D54 | E53: ='Indexado Dim Técnico'!E29+'Reservas y Sustitutos'!E54 | F53: ='Indexado Dim Técnico'!F29+'Reservas y Sustitutos'!F54 | G53: ='Indexado Dim Técnico'!G29+'Reservas y Sustitutos'!G54 | H53: ='Indexado Dim Técnico'!H29+'Reservas y Sustitutos'!H54 | I53: ='Indexado Dim Técnico'!I29+'Reservas y Sustitutos'!I54 | ... K53: ='Indexado Dim Técnico'!K29+'Reservas y Sustitutos'!K54 | L53: Indexado fila 29 + Reservas fila 54
A54: FL_MAT_ABC_10kg | B54: ='Indexado Dim Técnico'!B30+'Reservas y Sustitutos'!B55 | C54: ='Indexado Dim Técnico'!C30+'Reservas y Sustitutos'!C55 | D54: ='Indexado Dim Técnico'!D30+'Reservas y Sustitutos'!D55 | E54: ='Indexado Dim Técnico'!E30+'Reservas y Sustitutos'!E55 | F54: ='Indexado Dim Técnico'!F30+'Reservas y Sustitutos'!F55 | G54: ='Indexado Dim Técnico'!G30+'Reservas y Sustitutos'!G55 | H54: ='Indexado Dim Técnico'!H30+'Reservas y Sustitutos'!H55 | I54: ='Indexado Dim Técnico'!I30+'Reservas y Sustitutos'!I55 | ... K54: ='Indexado Dim Técnico'!K30+'Reservas y Sustitutos'!K55 | L54: Indexado fila 30 + Reservas fila 55
A55: FL_MAT_AGUA_10l | B55: ='Indexado Dim Técnico'!B31+'Reservas y Sustitutos'!B56 | C55: ='Indexado Dim Técnico'!C31+'Reservas y Sustitutos'!C56 | D55: ='Indexado Dim Técnico'!D31+'Reservas y Sustitutos'!D56 | E55: ='Indexado Dim Técnico'!E31+'Reservas y Sustitutos'!E56 | F55: ='Indexado Dim Técnico'!F31+'Reservas y Sustitutos'!F56 | G55: ='Indexado Dim Técnico'!G31+'Reservas y Sustitutos'!G56 | H55: ='Indexado Dim Técnico'!H31+'Reservas y Sustitutos'!H56 | I55: ='Indexado Dim Técnico'!I31+'Reservas y Sustitutos'!I56 | ... K55: ='Indexado Dim Técnico'!K31+'Reservas y Sustitutos'!K56 | L55: Indexado fila 31 + Reservas fila 56
A56: FL_MAT_AFFF_10l | B56: ='Indexado Dim Técnico'!B32+'Reservas y Sustitutos'!B57 | C56: ='Indexado Dim Técnico'!C32+'Reservas y Sustitutos'!C57 | D56: ='Indexado Dim Técnico'!D32+'Reservas y Sustitutos'!D57 | E56: ='Indexado Dim Técnico'!E32+'Reservas y Sustitutos'!E57 | F56: ='Indexado Dim Técnico'!F32+'Reservas y Sustitutos'!F57 | G56: ='Indexado Dim Técnico'!G32+'Reservas y Sustitutos'!G57 | H56: ='Indexado Dim Técnico'!H32+'Reservas y Sustitutos'!H57 | I56: ='Indexado Dim Técnico'!I32+'Reservas y Sustitutos'!I57 | ... K56: ='Indexado Dim Técnico'!K32+'Reservas y Sustitutos'!K57 | L56: Indexado fila 32 + Reservas fila 57
A57: FL_MAT_AFFF_50l | B57: ='Indexado Dim Técnico'!B33+'Reservas y Sustitutos'!B58 | C57: ='Indexado Dim Técnico'!C33+'Reservas y Sustitutos'!C58 | D57: ='Indexado Dim Técnico'!D33+'Reservas y Sustitutos'!D58 | E57: ='Indexado Dim Técnico'!E33+'Reservas y Sustitutos'!E58 | F57: ='Indexado Dim Técnico'!F33+'Reservas y Sustitutos'!F58 | G57: ='Indexado Dim Técnico'!G33+'Reservas y Sustitutos'!G58 | H57: ='Indexado Dim Técnico'!H33+'Reservas y Sustitutos'!H58 | I57: ='Indexado Dim Técnico'!I33+'Reservas y Sustitutos'!I58 | ... K57: ='Indexado Dim Técnico'!K33+'Reservas y Sustitutos'!K58 | L57: Indexado fila 33 + Reservas fila 58
A58: FL_MAT_BC_5kg | B58: ='Indexado Dim Técnico'!B34+'Reservas y Sustitutos'!B59 | C58: ='Indexado Dim Técnico'!C34+'Reservas y Sustitutos'!C59 | D58: ='Indexado Dim Técnico'!D34+'Reservas y Sustitutos'!D59 | E58: ='Indexado Dim Técnico'!E34+'Reservas y Sustitutos'!E59 | F58: ='Indexado Dim Técnico'!F34+'Reservas y Sustitutos'!F59 | G58: ='Indexado Dim Técnico'!G34+'Reservas y Sustitutos'!G59 | H58: ='Indexado Dim Técnico'!H34+'Reservas y Sustitutos'!H59 | I58: ='Indexado Dim Técnico'!I34+'Reservas y Sustitutos'!I59 | ... K58: ='Indexado Dim Técnico'!K34+'Reservas y Sustitutos'!K59 | L58: Indexado fila 34 + Reservas fila 59
A59: FL_MAT_SALESK_6l | B59: ='Indexado Dim Técnico'!B35+'Reservas y Sustitutos'!B60 | C59: ='Indexado Dim Técnico'!C35+'Reservas y Sustitutos'!C60 | D59: ='Indexado Dim Técnico'!D35+'Reservas y Sustitutos'!D60 | E59: ='Indexado Dim Técnico'!E35+'Reservas y Sustitutos'!E60 | F59: ='Indexado Dim Técnico'!F35+'Reservas y Sustitutos'!F60 | G59: ='Indexado Dim Técnico'!G35+'Reservas y Sustitutos'!G60 | H59: ='Indexado Dim Técnico'!H35+'Reservas y Sustitutos'!H60 | I59: ='Indexado Dim Técnico'!I35+'Reservas y Sustitutos'!I60 | ... K59: ='Indexado Dim Técnico'!K35+'Reservas y Sustitutos'!K60 | L59: Indexado fila 35 + Reservas fila 60
A60: FL_MAT_CO2_2kg | B60: ='Indexado Dim Técnico'!B36 | C60: ='Indexado Dim Técnico'!C36 | D60: ='Indexado Dim Técnico'!D36 | E60: ='Indexado Dim Técnico'!E36 | F60: ='Indexado Dim Técnico'!F36 | G60: ='Indexado Dim Técnico'!G36 | H60: ='Indexado Dim Técnico'!H36 | I60: ='Indexado Dim Técnico'!I36 | ... K60: ='Indexado Dim Técnico'!K36 | L60: Indexado fila 36
A61: FL_MAT_CO2_5kg | B61: ='Indexado Dim Técnico'!B37+'Reservas y Sustitutos'!B61 | C61: ='Indexado Dim Técnico'!C37+'Reservas y Sustitutos'!C61 | D61: ='Indexado Dim Técnico'!D37+'Reservas y Sustitutos'!D61 | E61: ='Indexado Dim Técnico'!E37+'Reservas y Sustitutos'!E61 | F61: ='Indexado Dim Técnico'!F37+'Reservas y Sustitutos'!F61 | G61: ='Indexado Dim Técnico'!G37+'Reservas y Sustitutos'!G61 | H61: ='Indexado Dim Técnico'!H37+'Reservas y Sustitutos'!H61 | I61: ='Indexado Dim Técnico'!I37+'Reservas y Sustitutos'!I61 | ... K61: ='Indexado Dim Técnico'!K37+'Reservas y Sustitutos'!K61 | L61: Indexado fila 37 + Reservas fila 61
A62: FL_MAT_HCFC-HFC_5kg | B62: ='Indexado Dim Técnico'!B38+'Reservas y Sustitutos'!B62 | C62: ='Indexado Dim Técnico'!C38+'Reservas y Sustitutos'!C62 | D62: ='Indexado Dim Técnico'!D38+'Reservas y Sustitutos'!D62 | E62: ='Indexado Dim Técnico'!E38+'Reservas y Sustitutos'!E62 | F62: ='Indexado Dim Técnico'!F38+'Reservas y Sustitutos'!F62 | G62: ='Indexado Dim Técnico'!G38+'Reservas y Sustitutos'!G62 | H62: ='Indexado Dim Técnico'!H38+'Reservas y Sustitutos'!H62 | I62: ='Indexado Dim Técnico'!I38+'Reservas y Sustitutos'!I62 | ... K62: ='Indexado Dim Técnico'!K38+'Reservas y Sustitutos'!K62 | L62: Indexado fila 38 + Reservas fila 62
A63: FL_MAT_CLASED_9l | B63: ='Indexado Dim Técnico'!B39+'Reservas y Sustitutos'!B63 | C63: ='Indexado Dim Técnico'!C39+'Reservas y Sustitutos'!C63 | D63: ='Indexado Dim Técnico'!D39+'Reservas y Sustitutos'!D63 | E63: ='Indexado Dim Técnico'!E39+'Reservas y Sustitutos'!E63 | F63: ='Indexado Dim Técnico'!F39+'Reservas y Sustitutos'!F63 | G63: ='Indexado Dim Técnico'!G39+'Reservas y Sustitutos'!G63 | H63: ='Indexado Dim Técnico'!H39+'Reservas y Sustitutos'!H63 | I63: ='Indexado Dim Técnico'!I39+'Reservas y Sustitutos'!I63 | ... K63: ='Indexado Dim Técnico'!K39+'Reservas y Sustitutos'!K63 | L63: Indexado fila 39 + Reservas fila 63
A64: FL_MAT_ABC_25kg | B64: ='Indexado Dim Técnico'!B40 | C64: ='Indexado Dim Técnico'!C40 | D64: ='Indexado Dim Técnico'!D40 | E64: ='Indexado Dim Técnico'!E40 | F64: ='Indexado Dim Técnico'!F40 | G64: ='Indexado Dim Técnico'!G40 | H64: ='Indexado Dim Técnico'!H40 | I64: ='Indexado Dim Técnico'!I40 | ... K64: ='Indexado Dim Técnico'!K40 | L64: Indexado fila 40
A65: FL_MAT_ABC_50kg | B65: ='Indexado Dim Técnico'!B41+'Reservas y Sustitutos'!B64 | C65: ='Indexado Dim Técnico'!C41+'Reservas y Sustitutos'!C64 | D65: ='Indexado Dim Técnico'!D41+'Reservas y Sustitutos'!D64 | E65: ='Indexado Dim Técnico'!E41+'Reservas y Sustitutos'!E64 | F65: ='Indexado Dim Técnico'!F41+'Reservas y Sustitutos'!F64 | G65: ='Indexado Dim Técnico'!G41+'Reservas y Sustitutos'!G64 | H65: ='Indexado Dim Técnico'!H41+'Reservas y Sustitutos'!H64 | I65: ='Indexado Dim Técnico'!I41+'Reservas y Sustitutos'!I64 | ... K65: ='Indexado Dim Técnico'!K41+'Reservas y Sustitutos'!K64 | L65: Indexado fila 41 + Reservas fila 64
A66: FL_MAT_ABC_70kg | B66: ='Indexado Dim Técnico'!B42 | C66: ='Indexado Dim Técnico'!C42 | D66: ='Indexado Dim Técnico'!D42 | E66: ='Indexado Dim Técnico'!E42 | F66: ='Indexado Dim Técnico'!F42 | G66: ='Indexado Dim Técnico'!G42 | H66: ='Indexado Dim Técnico'!H42 | I66: ='Indexado Dim Técnico'!I42 | ... K66: ='Indexado Dim Técnico'!K42 | L66: Indexado fila 42
A67: FL_MAT_ABC_100kg | B67: ='Indexado Dim Técnico'!B43+'Reservas y Sustitutos'!B65 | C67: ='Indexado Dim Técnico'!C43+'Reservas y Sustitutos'!C65 | D67: ='Indexado Dim Técnico'!D43+'Reservas y Sustitutos'!D65 | E67: ='Indexado Dim Técnico'!E43+'Reservas y Sustitutos'!E65 | F67: ='Indexado Dim Técnico'!F43+'Reservas y Sustitutos'!F65 | G67: ='Indexado Dim Técnico'!G43+'Reservas y Sustitutos'!G65 | H67: ='Indexado Dim Técnico'!H43+'Reservas y Sustitutos'!H65 | I67: ='Indexado Dim Técnico'!I43+'Reservas y Sustitutos'!I65 | ... K67: ='Indexado Dim Técnico'!K43+'Reservas y Sustitutos'!K65 | L67: Indexado fila 43 + Reservas fila 65

Sheet MP_MATAFUEGOS_FABRICADOS
A1: Requerimiento de MP — matafuegos fabricados (ABC 1 a 100 kg)
A2: Demanda = unidades nuevas + venta de reserva ABC 5 kg + alta de sustitutos. Coeficientes del BOM (azul). Destino CABA/PBA según % zonal (Parametros fila 7).
AJ4: Demanda (u) → | AK4: ABC_1kg | AL4: ABC_2.5kg | AM4: ABC_5kg | AN4: ABC_10kg | AO4: ABC_25kg | AP4: ABC_50kg | AQ4: ABC_70kg | AR4: ABC_100kg
AJ5: ='Demanda'!B3 | AK5: ='Demanda'!B6 | AL5: ='Demanda'!B7 | AM5: ='Demanda'!B8 | AN5: ='Demanda'!B9 | AO5: ='Demanda'!B10 | AP5: ='Demanda'!B11 | AQ5: ='Demanda'!B12 | AR5: ='Demanda'!B13
AJ6: ='Demanda'!C3 | AK6: ='Demanda'!C6 | AL6: ='Demanda'!C7 | AM6: ='Demanda'!C8 | AN6: ='Demanda'!C9 | AO6: ='Demanda'!C10 | AP6: ='Demanda'!C11 | AQ6: ='Demanda'!C12 | AR6: ='Demanda'!C13
AJ7: ='Demanda'!D3 | AK7: ='Demanda'!D6 | AL7: ='Demanda'!D7 | AM7: ='Demanda'!D8 | AN7: ='Demanda'!D9 | AO7: ='Demanda'!D10 | AP7: ='Demanda'!D11 | AQ7: ='Demanda'!D12 | AR7: ='Demanda'!D13
AJ8: ='Demanda'!E3 | AK8: ='Demanda'!E6 | AL8: ='Demanda'!E7 | AM8: ='Demanda'!E8 | AN8: ='Demanda'!E9 | AO8: ='Demanda'!E10 | AP8: ='Demanda'!E11 | AQ8: ='Demanda'!E12 | AR8: ='Demanda'!E13
AJ9: ='Demanda'!F3 | AK9: ='Demanda'!F6 | AL9: ='Demanda'!F7 | AM9: ='Demanda'!F8 | AN9: ='Demanda'!F9 | AO9: ='Demanda'!F10 | AP9: ='Demanda'!F11 | AQ9: ='Demanda'!F12 | AR9: ='Demanda'!F13
AJ10: ='Demanda'!G3 | AK10: ='Demanda'!G6 | AL10: ='Demanda'!G7 | AM10: ='Demanda'!G8 | AN10: ='Demanda'!G9 | AO10: ='Demanda'!G10 | AP10: ='Demanda'!G11 | AQ10: ='Demanda'!G12 | AR10: ='Demanda'!G13
AJ11: ='Demanda'!H3 | AK11: ='Demanda'!H6 | AL11: ='Demanda'!H7 | AM11: ='Demanda'!H8 | AN11: ='Demanda'!H9 | AO11: ='Demanda'!H10 | AP11: ='Demanda'!H11 | AQ11: ='Demanda'!H12 | AR11: ='Demanda'!H13
AJ12: ='Demanda'!I3 | AK12: ='Demanda'!I6 | AL12: ='Demanda'!I7 | AM12: ='Demanda'!I8 | AN12: ='Demanda'!I9 | AO12: ='Demanda'!I10 | AP12: ='Demanda'!I11 | AQ12: ='Demanda'!I12 | AR12: ='Demanda'!I13
AJ13: ='Demanda'!J3 | AK13: ='Demanda'!J6 | AL13: ='Demanda'!J7 | AM13: ='Demanda'!J8 | AN13: ='Demanda'!J9 | AO13: ='Demanda'!J10 | AP13: ='Demanda'!J11 | AQ13: ='Demanda'!J12 | AR13: ='Demanda'!J13
AJ14: ='Demanda'!K3 | AK14: ='Demanda'!K6 | AL14: ='Demanda'!K7 | AM14: ='Demanda'!K8 | AN14: ='Demanda'!K9 | AO14: ='Demanda'!K10 | AP14: ='Demanda'!K11 | AQ14: ='Demanda'!K12 | AR14: ='Demanda'!K13
A16: Ítem | B16: UM | C16: Rubro | D16: Proveedor principal | E16: Destino | F16: ='Demanda'!B3 | G16: ='Demanda'!C3 | H16: ='Demanda'!D3 | I16: ='Demanda'!E3 | J16: ='Demanda'!F3 | K16: ='Demanda'!G3 | L16: ='Demanda'!H3 | M16: ='Demanda'!I3 | ... O16: ='Demanda'!K3 | AK16: coef. ABC_1kg | AL16: coef. ABC_2.5kg | AM16: coef. ABC_5kg | AN16: coef. ABC_10kg | AO16: coef. ABC_25kg | AP16: coef. ABC_50kg | AQ16: coef. ABC_70kg | AR16: coef. ABC_100kg
A17: Caño SAE 1010 Ø25,4 × 1,6 | B17: barra 6 m | C17: Materia prima | D17: Metalpri / Prilux | E17: Todos | F17: =SUMPRODUCT($AK17:$AR17,$AK$5:$AR$5)*IF($E17="CABA",'Parametros'!B$7,IF($E17="PBA",1-'Parametros'!B$7,1)) | G17: =SUMPRODUCT($AK17:$AR17,$AK$6:$AR$6)*IF($E17="CABA",'Parametros'!C$7,IF($E17="PBA",1-'Parametros'!C$7,1)) | H17: =SUMPRODUCT($AK17:$AR17,$AK$7:$AR$7)*IF($E17="CABA",'Parametros'!D$7,IF($E17="PBA",1-'Parametros'!D$7,1)) | I17: =SUMPRODUCT($AK17:$AR17,$AK$8:$AR$8)*IF($E17="CABA",'Parametros'!E$7,IF($E17="PBA",1-'Parametros'!E$7,1)) | J17: =SUMPRODUCT($AK17:$AR17,$AK$9:$AR$9)*IF($E17="CABA",'Parametros'!F$7,IF($E17="PBA",1-'Parametros'!F$7,1)) | K17: =SUMPRODUCT($AK17:$AR17,$AK$10:$AR$10)*IF($E17="CABA",'Parametros'!G$7,IF($E17="PBA",1-'Parametros'!G$7,1)) | L17: =SUMPRODUCT($AK17:$AR17,$AK$11:$AR$11)*IF($E17="CABA",'Parametros'!H$7,IF($E17="PBA",1-'Parametros'!H$7,1)) | M17: =SUMPRODUCT($AK17:$AR17,$AK$12:$AR$12)*IF($E17="CABA",'Parametros'!I$7,IF($E17="PBA",1-'Parametros'!I$7,1)) | N17: =SUMPRODUCT($AK17:$AR17,$AK$13:$AR$13)*IF($E17="CABA",'Parametros'!J$7,IF($E17="PBA",1-'Parametros'!J$7,1)) | O17: =SUMPRODUCT($AK17:$AR17,$AK$14:$AR$14)*IF($E17="CABA",'Parametros'!K$7,IF($E17="PBA",1-'Parametros'!K$7,1)) | AO17: 0.2774 | AP17: 0.2767 | AQ17: 0.3162 | AR17: 0.2998
A18: Caño Ø76,2 × 1,25 | B18: barra 6 m | C18: Materia prima | D18: Metalpri / Prilux | E18: Todos | F18: =SUMPRODUCT($AK18:$AR18,$AK$5:$AR$5)*IF($E18="CABA",'Parametros'!B$7,IF($E18="PBA",1-'Parametros'!B$7,1)) | G18: =SUMPRODUCT($AK18:$AR18,$AK$6:$AR$6)*IF($E18="CABA",'Parametros'!C$7,IF($E18="PBA",1-'Parametros'!C$7,1)) | H18: =SUMPRODUCT($AK18:$AR18,$AK$7:$AR$7)*IF($E18="CABA",'Parametros'!D$7,IF($E18="PBA",1-'Parametros'!D$7,1)) | I18: =SUMPRODUCT($AK18:$AR18,$AK$8:$AR$8)*IF($E18="CABA",'Parametros'!E$7,IF($E18="PBA",1-'Parametros'!E$7,1)) | J18: =SUMPRODUCT($AK18:$AR18,$AK$9:$AR$9)*IF($E18="CABA",'Parametros'!F$7,IF($E18="PBA",1-'Parametros'!F$7,1)) | K18: =SUMPRODUCT($AK18:$AR18,$AK$10:$AR$10)*IF($E18="CABA",'Parametros'!G$7,IF($E18="PBA",1-'Parametros'!G$7,1)) | L18: =SUMPRODUCT($AK18:$AR18,$AK$11:$AR$11)*IF($E18="CABA",'Parametros'!H$7,IF($E18="PBA",1-'Parametros'!H$7,1)) | M18: =SUMPRODUCT($AK18:$AR18,$AK$12:$AR$12)*IF($E18="CABA",'Parametros'!I$7,IF($E18="PBA",1-'Parametros'!I$7,1)) | N18: =SUMPRODUCT($AK18:$AR18,$AK$13:$AR$13)*IF($E18="CABA",'Parametros'!J$7,IF($E18="PBA",1-'Parametros'!J$7,1)) | O18: =SUMPRODUCT($AK18:$AR18,$AK$14:$AR$14)*IF($E18="CABA",'Parametros'!K$7,IF($E18="PBA",1-'Parametros'!K$7,1)) | AK18: 0.0435
A19: Chapa LAC 1500 × 3000 e=3,2 | B19: kg | C19: Materia prima | D19: Pradecon S.A. | E19: Todos | F19: =SUMPRODUCT($AK19:$AR19,$AK$5:$AR$5)*IF($E19="CABA",'Parametros'!B$7,IF($E19="PBA",1-'Parametros'!B$7,1)) | G19: =SUMPRODUCT($AK19:$AR19,$AK$6:$AR$6)*IF($E19="CABA",'Parametros'!C$7,IF($E19="PBA",1-'Parametros'!C$7,1)) | H19: =SUMPRODUCT($AK19:$AR19,$AK$7:$AR$7)*IF($E19="CABA",'Parametros'!D$7,IF($E19="PBA",1-'Parametros'!D$7,1)) | I19: =SUMPRODUCT($AK19:$AR19,$AK$8:$AR$8)*IF($E19="CABA",'Parametros'!E$7,IF($E19="PBA",1-'Parametros'!E$7,1)) | J19: =SUMPRODUCT($AK19:$AR19,$AK$9:$AR$9)*IF($E19="CABA",'Parametros'!F$7,IF($E19="PBA",1-'Parametros'!F$7,1)) | K19: =SUMPRODUCT($AK19:$AR19,$AK$10:$AR$10)*IF($E19="CABA",'Parametros'!G$7,IF($E19="PBA",1-'Parametros'!G$7,1)) | L19: =SUMPRODUCT($AK19:$AR19,$AK$11:$AR$11)*IF($E19="CABA",'Parametros'!H$7,IF($E19="PBA",1-'Parametros'!H$7,1)) | M19: =SUMPRODUCT($AK19:$AR19,$AK$12:$AR$12)*IF($E19="CABA",'Parametros'!I$7,IF($E19="PBA",1-'Parametros'!I$7,1)) | N19: =SUMPRODUCT($AK19:$AR19,$AK$13:$AR$13)*IF($E19="CABA",'Parametros'!J$7,IF($E19="PBA",1-'Parametros'!J$7,1)) | O19: =SUMPRODUCT($AK19:$AR19,$AK$14:$AR$14)*IF($E19="CABA",'Parametros'!K$7,IF($E19="PBA",1-'Parametros'!K$7,1)) | AO19: 12.558 | AP19: 18.845
A20: Chapa LAC 1500 × 3000 e=4,75 | B20: kg | C20: Materia prima | D20: Pradecon S.A. | E20: Todos | F20: =SUMPRODUCT($AK20:$AR20,$AK$5:$AR$5)*IF($E20="CABA",'Parametros'!B$7,IF($E20="PBA",1-'Parametros'!B$7,1)) | G20: =SUMPRODUCT($AK20:$AR20,$AK$6:$AR$6)*IF($E20="CABA",'Parametros'!C$7,IF($E20="PBA",1-'Parametros'!C$7,1)) | H20: =SUMPRODUCT($AK20:$AR20,$AK$7:$AR$7)*IF($E20="CABA",'Parametros'!D$7,IF($E20="PBA",1-'Parametros'!D$7,1)) | I20: =SUMPRODUCT($AK20:$AR20,$AK$8:$AR$8)*IF($E20="CABA",'Parametros'!E$7,IF($E20="PBA",1-'Parametros'!E$7,1)) | J20: =SUMPRODUCT($AK20:$AR20,$AK$9:$AR$9)*IF($E20="CABA",'Parametros'!F$7,IF($E20="PBA",1-'Parametros'!F$7,1)) | K20: =SUMPRODUCT($AK20:$AR20,$AK$10:$AR$10)*IF($E20="CABA",'Parametros'!G$7,IF($E20="PBA",1-'Parametros'!G$7,1)) | L20: =SUMPRODUCT($AK20:$AR20,$AK$11:$AR$11)*IF($E20="CABA",'Parametros'!H$7,IF($E20="PBA",1-'Parametros'!H$7,1)) | M20: =SUMPRODUCT($AK20:$AR20,$AK$12:$AR$12)*IF($E20="CABA",'Parametros'!I$7,IF($E20="PBA",1-'Parametros'!I$7,1)) | N20: =SUMPRODUCT($AK20:$AR20,$AK$13:$AR$13)*IF($E20="CABA",'Parametros'!J$7,IF($E20="PBA",1-'Parametros'!J$7,1)) | O20: =SUMPRODUCT($AK20:$AR20,$AK$14:$AR$14)*IF($E20="CABA",'Parametros'!K$7,IF($E20="PBA",1-'Parametros'!K$7,1)) | AQ20: 38.802 | AR20: 51.355
A21: Chapa LAF 1000 × 2000 e=1,6 | B21: kg | C21: Materia prima | D21: Pradecon S.A. | E21: Todos | F21: =SUMPRODUCT($AK21:$AR21,$AK$5:$AR$5)*IF($E21="CABA",'Parametros'!B$7,IF($E21="PBA",1-'Parametros'!B$7,1)) | G21: =SUMPRODUCT($AK21:$AR21,$AK$6:$AR$6)*IF($E21="CABA",'Parametros'!C$7,IF($E21="PBA",1-'Parametros'!C$7,1)) | H21: =SUMPRODUCT($AK21:$AR21,$AK$7:$AR$7)*IF($E21="CABA",'Parametros'!D$7,IF($E21="PBA",1-'Parametros'!D$7,1)) | I21: =SUMPRODUCT($AK21:$AR21,$AK$8:$AR$8)*IF($E21="CABA",'Parametros'!E$7,IF($E21="PBA",1-'Parametros'!E$7,1)) | J21: =SUMPRODUCT($AK21:$AR21,$AK$9:$AR$9)*IF($E21="CABA",'Parametros'!F$7,IF($E21="PBA",1-'Parametros'!F$7,1)) | K21: =SUMPRODUCT($AK21:$AR21,$AK$10:$AR$10)*IF($E21="CABA",'Parametros'!G$7,IF($E21="PBA",1-'Parametros'!G$7,1)) | L21: =SUMPRODUCT($AK21:$AR21,$AK$11:$AR$11)*IF($E21="CABA",'Parametros'!H$7,IF($E21="PBA",1-'Parametros'!H$7,1)) | M21: =SUMPRODUCT($AK21:$AR21,$AK$12:$AR$12)*IF($E21="CABA",'Parametros'!I$7,IF($E21="PBA",1-'Parametros'!I$7,1)) | N21: =SUMPRODUCT($AK21:$AR21,$AK$13:$AR$13)*IF($E21="CABA",'Parametros'!J$7,IF($E21="PBA",1-'Parametros'!J$7,1)) | O21: =SUMPRODUCT($AK21:$AR21,$AK$14:$AR$14)*IF($E21="CABA",'Parametros'!K$7,IF($E21="PBA",1-'Parametros'!K$7,1)) | AM21: 2.092
A22: Chapa LAF 1220 × 2440 e=1,25 | B22: kg | C22: Materia prima | D22: Pradecon S.A. | E22: Todos | F22: =SUMPRODUCT($AK22:$AR22,$AK$5:$AR$5)*IF($E22="CABA",'Parametros'!B$7,IF($E22="PBA",1-'Parametros'!B$7,1)) | G22: =SUMPRODUCT($AK22:$AR22,$AK$6:$AR$6)*IF($E22="CABA",'Parametros'!C$7,IF($E22="PBA",1-'Parametros'!C$7,1)) | H22: =SUMPRODUCT($AK22:$AR22,$AK$7:$AR$7)*IF($E22="CABA",'Parametros'!D$7,IF($E22="PBA",1-'Parametros'!D$7,1)) | I22: =SUMPRODUCT($AK22:$AR22,$AK$8:$AR$8)*IF($E22="CABA",'Parametros'!E$7,IF($E22="PBA",1-'Parametros'!E$7,1)) | J22: =SUMPRODUCT($AK22:$AR22,$AK$9:$AR$9)*IF($E22="CABA",'Parametros'!F$7,IF($E22="PBA",1-'Parametros'!F$7,1)) | K22: =SUMPRODUCT($AK22:$AR22,$AK$10:$AR$10)*IF($E22="CABA",'Parametros'!G$7,IF($E22="PBA",1-'Parametros'!G$7,1)) | L22: =SUMPRODUCT($AK22:$AR22,$AK$11:$AR$11)*IF($E22="CABA",'Parametros'!H$7,IF($E22="PBA",1-'Parametros'!H$7,1)) | M22: =SUMPRODUCT($AK22:$AR22,$AK$12:$AR$12)*IF($E22="CABA",'Parametros'!I$7,IF($E22="PBA",1-'Parametros'!I$7,1)) | N22: =SUMPRODUCT($AK22:$AR22,$AK$13:$AR$13)*IF($E22="CABA",'Parametros'!J$7,IF($E22="PBA",1-'Parametros'!J$7,1)) | O22: =SUMPRODUCT($AK22:$AR22,$AK$14:$AR$14)*IF($E22="CABA",'Parametros'!K$7,IF($E22="PBA",1-'Parametros'!K$7,1)) | AL22: 1.082
A23: Chapa LAF 1500 × 3000 e=2 | B23: kg | C23: Materia prima | D23: Pradecon S.A. | E23: Todos | F23: =SUMPRODUCT($AK23:$AR23,$AK$5:$AR$5)*IF($E23="CABA",'Parametros'!B$7,IF($E23="PBA",1-'Parametros'!B$7,1)) | G23: =SUMPRODUCT($AK23:$AR23,$AK$6:$AR$6)*IF($E23="CABA",'Parametros'!C$7,IF($E23="PBA",1-'Parametros'!C$7,1)) | H23: =SUMPRODUCT($AK23:$AR23,$AK$7:$AR$7)*IF($E23="CABA",'Parametros'!D$7,IF($E23="PBA",1-'Parametros'!D$7,1)) | I23: =SUMPRODUCT($AK23:$AR23,$AK$8:$AR$8)*IF($E23="CABA",'Parametros'!E$7,IF($E23="PBA",1-'Parametros'!E$7,1)) | J23: =SUMPRODUCT($AK23:$AR23,$AK$9:$AR$9)*IF($E23="CABA",'Parametros'!F$7,IF($E23="PBA",1-'Parametros'!F$7,1)) | K23: =SUMPRODUCT($AK23:$AR23,$AK$10:$AR$10)*IF($E23="CABA",'Parametros'!G$7,IF($E23="PBA",1-'Parametros'!G$7,1)) | L23: =SUMPRODUCT($AK23:$AR23,$AK$11:$AR$11)*IF($E23="CABA",'Parametros'!H$7,IF($E23="PBA",1-'Parametros'!H$7,1)) | M23: =SUMPRODUCT($AK23:$AR23,$AK$12:$AR$12)*IF($E23="CABA",'Parametros'!I$7,IF($E23="PBA",1-'Parametros'!I$7,1)) | N23: =SUMPRODUCT($AK23:$AR23,$AK$13:$AR$13)*IF($E23="CABA",'Parametros'!J$7,IF($E23="PBA",1-'Parametros'!J$7,1)) | O23: =SUMPRODUCT($AK23:$AR23,$AK$14:$AR$14)*IF($E23="CABA",'Parametros'!K$7,IF($E23="PBA",1-'Parametros'!K$7,1)) | AN23: 4.71
A24: Fleje e=0,9 × 114 | B24: m | C24: Materia prima | D24: Pacheco Chapas | E24: Todos | F24: =SUMPRODUCT($AK24:$AR24,$AK$5:$AR$5)*IF($E24="CABA",'Parametros'!B$7,IF($E24="PBA",1-'Parametros'!B$7,1)) | G24: =SUMPRODUCT($AK24:$AR24,$AK$6:$AR$6)*IF($E24="CABA",'Parametros'!C$7,IF($E24="PBA",1-'Parametros'!C$7,1)) | H24: =SUMPRODUCT($AK24:$AR24,$AK$7:$AR$7)*IF($E24="CABA",'Parametros'!D$7,IF($E24="PBA",1-'Parametros'!D$7,1)) | I24: =SUMPRODUCT($AK24:$AR24,$AK$8:$AR$8)*IF($E24="CABA",'Parametros'!E$7,IF($E24="PBA",1-'Parametros'!E$7,1)) | J24: =SUMPRODUCT($AK24:$AR24,$AK$9:$AR$9)*IF($E24="CABA",'Parametros'!F$7,IF($E24="PBA",1-'Parametros'!F$7,1)) | K24: =SUMPRODUCT($AK24:$AR24,$AK$10:$AR$10)*IF($E24="CABA",'Parametros'!G$7,IF($E24="PBA",1-'Parametros'!G$7,1)) | L24: =SUMPRODUCT($AK24:$AR24,$AK$11:$AR$11)*IF($E24="CABA",'Parametros'!H$7,IF($E24="PBA",1-'Parametros'!H$7,1)) | M24: =SUMPRODUCT($AK24:$AR24,$AK$12:$AR$12)*IF($E24="CABA",'Parametros'!I$7,IF($E24="PBA",1-'Parametros'!I$7,1)) | N24: =SUMPRODUCT($AK24:$AR24,$AK$13:$AR$13)*IF($E24="CABA",'Parametros'!J$7,IF($E24="PBA",1-'Parametros'!J$7,1)) | O24: =SUMPRODUCT($AK24:$AR24,$AK$14:$AR$14)*IF($E24="CABA",'Parametros'!K$7,IF($E24="PBA",1-'Parametros'!K$7,1)) | AK24: 0.111
A25: Fleje e=1,25 × 106 | B25: m | C25: Materia prima | D25: Pacheco Chapas | E25: Todos | F25: =SUMPRODUCT($AK25:$AR25,$AK$5:$AR$5)*IF($E25="CABA",'Parametros'!B$7,IF($E25="PBA",1-'Parametros'!B$7,1)) | G25: =SUMPRODUCT($AK25:$AR25,$AK$6:$AR$6)*IF($E25="CABA",'Parametros'!C$7,IF($E25="PBA",1-'Parametros'!C$7,1)) | H25: =SUMPRODUCT($AK25:$AR25,$AK$7:$AR$7)*IF($E25="CABA",'Parametros'!D$7,IF($E25="PBA",1-'Parametros'!D$7,1)) | I25: =SUMPRODUCT($AK25:$AR25,$AK$8:$AR$8)*IF($E25="CABA",'Parametros'!E$7,IF($E25="PBA",1-'Parametros'!E$7,1)) | J25: =SUMPRODUCT($AK25:$AR25,$AK$9:$AR$9)*IF($E25="CABA",'Parametros'!F$7,IF($E25="PBA",1-'Parametros'!F$7,1)) | K25: =SUMPRODUCT($AK25:$AR25,$AK$10:$AR$10)*IF($E25="CABA",'Parametros'!G$7,IF($E25="PBA",1-'Parametros'!G$7,1)) | L25: =SUMPRODUCT($AK25:$AR25,$AK$11:$AR$11)*IF($E25="CABA",'Parametros'!H$7,IF($E25="PBA",1-'Parametros'!H$7,1)) | M25: =SUMPRODUCT($AK25:$AR25,$AK$12:$AR$12)*IF($E25="CABA",'Parametros'!I$7,IF($E25="PBA",1-'Parametros'!I$7,1)) | N25: =SUMPRODUCT($AK25:$AR25,$AK$13:$AR$13)*IF($E25="CABA",'Parametros'!J$7,IF($E25="PBA",1-'Parametros'!J$7,1)) | O25: =SUMPRODUCT($AK25:$AR25,$AK$14:$AR$14)*IF($E25="CABA",'Parametros'!K$7,IF($E25="PBA",1-'Parametros'!K$7,1)) | AK25: 0.103
A26: Fleje e=1,25 × 200 | B26: m | C26: Materia prima | D26: Pacheco Chapas | E26: Todos | F26: =SUMPRODUCT($AK26:$AR26,$AK$5:$AR$5)*IF($E26="CABA",'Parametros'!B$7,IF($E26="PBA",1-'Parametros'!B$7,1)) | G26: =SUMPRODUCT($AK26:$AR26,$AK$6:$AR$6)*IF($E26="CABA",'Parametros'!C$7,IF($E26="PBA",1-'Parametros'!C$7,1)) | H26: =SUMPRODUCT($AK26:$AR26,$AK$7:$AR$7)*IF($E26="CABA",'Parametros'!D$7,IF($E26="PBA",1-'Parametros'!D$7,1)) | I26: =SUMPRODUCT($AK26:$AR26,$AK$8:$AR$8)*IF($E26="CABA",'Parametros'!E$7,IF($E26="PBA",1-'Parametros'!E$7,1)) | J26: =SUMPRODUCT($AK26:$AR26,$AK$9:$AR$9)*IF($E26="CABA",'Parametros'!F$7,IF($E26="PBA",1-'Parametros'!F$7,1)) | K26: =SUMPRODUCT($AK26:$AR26,$AK$10:$AR$10)*IF($E26="CABA",'Parametros'!G$7,IF($E26="PBA",1-'Parametros'!G$7,1)) | L26: =SUMPRODUCT($AK26:$AR26,$AK$11:$AR$11)*IF($E26="CABA",'Parametros'!H$7,IF($E26="PBA",1-'Parametros'!H$7,1)) | M26: =SUMPRODUCT($AK26:$AR26,$AK$12:$AR$12)*IF($E26="CABA",'Parametros'!I$7,IF($E26="PBA",1-'Parametros'!I$7,1)) | N26: =SUMPRODUCT($AK26:$AR26,$AK$13:$AR$13)*IF($E26="CABA",'Parametros'!J$7,IF($E26="PBA",1-'Parametros'!J$7,1)) | O26: =SUMPRODUCT($AK26:$AR26,$AK$14:$AR$14)*IF($E26="CABA",'Parametros'!K$7,IF($E26="PBA",1-'Parametros'!K$7,1)) | AL26: 0.333
A27: Fleje e=1,6 × 200 | B27: m | C27: Materia prima | D27: Pacheco Chapas | E27: Todos | F27: =SUMPRODUCT($AK27:$AR27,$AK$5:$AR$5)*IF($E27="CABA",'Parametros'!B$7,IF($E27="PBA",1-'Parametros'!B$7,1)) | G27: =SUMPRODUCT($AK27:$AR27,$AK$6:$AR$6)*IF($E27="CABA",'Parametros'!C$7,IF($E27="PBA",1-'Parametros'!C$7,1)) | H27: =SUMPRODUCT($AK27:$AR27,$AK$7:$AR$7)*IF($E27="CABA",'Parametros'!D$7,IF($E27="PBA",1-'Parametros'!D$7,1)) | I27: =SUMPRODUCT($AK27:$AR27,$AK$8:$AR$8)*IF($E27="CABA",'Parametros'!E$7,IF($E27="PBA",1-'Parametros'!E$7,1)) | J27: =SUMPRODUCT($AK27:$AR27,$AK$9:$AR$9)*IF($E27="CABA",'Parametros'!F$7,IF($E27="PBA",1-'Parametros'!F$7,1)) | K27: =SUMPRODUCT($AK27:$AR27,$AK$10:$AR$10)*IF($E27="CABA",'Parametros'!G$7,IF($E27="PBA",1-'Parametros'!G$7,1)) | L27: =SUMPRODUCT($AK27:$AR27,$AK$11:$AR$11)*IF($E27="CABA",'Parametros'!H$7,IF($E27="PBA",1-'Parametros'!H$7,1)) | M27: =SUMPRODUCT($AK27:$AR27,$AK$12:$AR$12)*IF($E27="CABA",'Parametros'!I$7,IF($E27="PBA",1-'Parametros'!I$7,1)) | N27: =SUMPRODUCT($AK27:$AR27,$AK$13:$AR$13)*IF($E27="CABA",'Parametros'!J$7,IF($E27="PBA",1-'Parametros'!J$7,1)) | O27: =SUMPRODUCT($AK27:$AR27,$AK$14:$AR$14)*IF($E27="CABA",'Parametros'!K$7,IF($E27="PBA",1-'Parametros'!K$7,1)) | AM27: 0.18
A28: Fleje e=1,6 × 250 | B28: m | C28: Materia prima | D28: Pacheco Chapas | E28: Todos | F28: =SUMPRODUCT($AK28:$AR28,$AK$5:$AR$5)*IF($E28="CABA",'Parametros'!B$7,IF($E28="PBA",1-'Parametros'!B$7,1)) | G28: =SUMPRODUCT($AK28:$AR28,$AK$6:$AR$6)*IF($E28="CABA",'Parametros'!C$7,IF($E28="PBA",1-'Parametros'!C$7,1)) | H28: =SUMPRODUCT($AK28:$AR28,$AK$7:$AR$7)*IF($E28="CABA",'Parametros'!D$7,IF($E28="PBA",1-'Parametros'!D$7,1)) | I28: =SUMPRODUCT($AK28:$AR28,$AK$8:$AR$8)*IF($E28="CABA",'Parametros'!E$7,IF($E28="PBA",1-'Parametros'!E$7,1)) | J28: =SUMPRODUCT($AK28:$AR28,$AK$9:$AR$9)*IF($E28="CABA",'Parametros'!F$7,IF($E28="PBA",1-'Parametros'!F$7,1)) | K28: =SUMPRODUCT($AK28:$AR28,$AK$10:$AR$10)*IF($E28="CABA",'Parametros'!G$7,IF($E28="PBA",1-'Parametros'!G$7,1)) | L28: =SUMPRODUCT($AK28:$AR28,$AK$11:$AR$11)*IF($E28="CABA",'Parametros'!H$7,IF($E28="PBA",1-'Parametros'!H$7,1)) | M28: =SUMPRODUCT($AK28:$AR28,$AK$12:$AR$12)*IF($E28="CABA",'Parametros'!I$7,IF($E28="PBA",1-'Parametros'!I$7,1)) | N28: =SUMPRODUCT($AK28:$AR28,$AK$13:$AR$13)*IF($E28="CABA",'Parametros'!J$7,IF($E28="PBA",1-'Parametros'!J$7,1)) | O28: =SUMPRODUCT($AK28:$AR28,$AK$14:$AR$14)*IF($E28="CABA",'Parametros'!K$7,IF($E28="PBA",1-'Parametros'!K$7,1)) | AM28: 0.224
A29: Fleje e=1,6 × 300 | B29: m | C29: Materia prima | D29: Pacheco Chapas | E29: Todos | F29: =SUMPRODUCT($AK29:$AR29,$AK$5:$AR$5)*IF($E29="CABA",'Parametros'!B$7,IF($E29="PBA",1-'Parametros'!B$7,1)) | G29: =SUMPRODUCT($AK29:$AR29,$AK$6:$AR$6)*IF($E29="CABA",'Parametros'!C$7,IF($E29="PBA",1-'Parametros'!C$7,1)) | H29: =SUMPRODUCT($AK29:$AR29,$AK$7:$AR$7)*IF($E29="CABA",'Parametros'!D$7,IF($E29="PBA",1-'Parametros'!D$7,1)) | I29: =SUMPRODUCT($AK29:$AR29,$AK$8:$AR$8)*IF($E29="CABA",'Parametros'!E$7,IF($E29="PBA",1-'Parametros'!E$7,1)) | J29: =SUMPRODUCT($AK29:$AR29,$AK$9:$AR$9)*IF($E29="CABA",'Parametros'!F$7,IF($E29="PBA",1-'Parametros'!F$7,1)) | K29: =SUMPRODUCT($AK29:$AR29,$AK$10:$AR$10)*IF($E29="CABA",'Parametros'!G$7,IF($E29="PBA",1-'Parametros'!G$7,1)) | L29: =SUMPRODUCT($AK29:$AR29,$AK$11:$AR$11)*IF($E29="CABA",'Parametros'!H$7,IF($E29="PBA",1-'Parametros'!H$7,1)) | M29: =SUMPRODUCT($AK29:$AR29,$AK$12:$AR$12)*IF($E29="CABA",'Parametros'!I$7,IF($E29="PBA",1-'Parametros'!I$7,1)) | N29: =SUMPRODUCT($AK29:$AR29,$AK$13:$AR$13)*IF($E29="CABA",'Parametros'!J$7,IF($E29="PBA",1-'Parametros'!J$7,1)) | O29: =SUMPRODUCT($AK29:$AR29,$AK$14:$AR$14)*IF($E29="CABA",'Parametros'!K$7,IF($E29="PBA",1-'Parametros'!K$7,1)) | AN29: 0.261
A30: Fleje e=2 × 249 | B30: m | C30: Materia prima | D30: Pacheco Chapas | E30: Todos | F30: =SUMPRODUCT($AK30:$AR30,$AK$5:$AR$5)*IF($E30="CABA",'Parametros'!B$7,IF($E30="PBA",1-'Parametros'!B$7,1)) | G30: =SUMPRODUCT($AK30:$AR30,$AK$6:$AR$6)*IF($E30="CABA",'Parametros'!C$7,IF($E30="PBA",1-'Parametros'!C$7,1)) | H30: =SUMPRODUCT($AK30:$AR30,$AK$7:$AR$7)*IF($E30="CABA",'Parametros'!D$7,IF($E30="PBA",1-'Parametros'!D$7,1)) | I30: =SUMPRODUCT($AK30:$AR30,$AK$8:$AR$8)*IF($E30="CABA",'Parametros'!E$7,IF($E30="PBA",1-'Parametros'!E$7,1)) | J30: =SUMPRODUCT($AK30:$AR30,$AK$9:$AR$9)*IF($E30="CABA",'Parametros'!F$7,IF($E30="PBA",1-'Parametros'!F$7,1)) | K30: =SUMPRODUCT($AK30:$AR30,$AK$10:$AR$10)*IF($E30="CABA",'Parametros'!G$7,IF($E30="PBA",1-'Parametros'!G$7,1)) | L30: =SUMPRODUCT($AK30:$AR30,$AK$11:$AR$11)*IF($E30="CABA",'Parametros'!H$7,IF($E30="PBA",1-'Parametros'!H$7,1)) | M30: =SUMPRODUCT($AK30:$AR30,$AK$12:$AR$12)*IF($E30="CABA",'Parametros'!I$7,IF($E30="PBA",1-'Parametros'!I$7,1)) | N30: =SUMPRODUCT($AK30:$AR30,$AK$13:$AR$13)*IF($E30="CABA",'Parametros'!J$7,IF($E30="PBA",1-'Parametros'!J$7,1)) | O30: =SUMPRODUCT($AK30:$AR30,$AK$14:$AR$14)*IF($E30="CABA",'Parametros'!K$7,IF($E30="PBA",1-'Parametros'!K$7,1)) | AN30: 0.208
A31: Redondo SAE 1045 Ø25 | B31: barra 6 m | C31: Materia prima | D31: Hierros Parrotta | E31: Todos | F31: =SUMPRODUCT($AK31:$AR31,$AK$5:$AR$5)*IF($E31="CABA",'Parametros'!B$7,IF($E31="PBA",1-'Parametros'!B$7,1)) | G31: =SUMPRODUCT($AK31:$AR31,$AK$6:$AR$6)*IF($E31="CABA",'Parametros'!C$7,IF($E31="PBA",1-'Parametros'!C$7,1)) | H31: =SUMPRODUCT($AK31:$AR31,$AK$7:$AR$7)*IF($E31="CABA",'Parametros'!D$7,IF($E31="PBA",1-'Parametros'!D$7,1)) | I31: =SUMPRODUCT($AK31:$AR31,$AK$8:$AR$8)*IF($E31="CABA",'Parametros'!E$7,IF($E31="PBA",1-'Parametros'!E$7,1)) | J31: =SUMPRODUCT($AK31:$AR31,$AK$9:$AR$9)*IF($E31="CABA",'Parametros'!F$7,IF($E31="PBA",1-'Parametros'!F$7,1)) | K31: =SUMPRODUCT($AK31:$AR31,$AK$10:$AR$10)*IF($E31="CABA",'Parametros'!G$7,IF($E31="PBA",1-'Parametros'!G$7,1)) | L31: =SUMPRODUCT($AK31:$AR31,$AK$11:$AR$11)*IF($E31="CABA",'Parametros'!H$7,IF($E31="PBA",1-'Parametros'!H$7,1)) | M31: =SUMPRODUCT($AK31:$AR31,$AK$12:$AR$12)*IF($E31="CABA",'Parametros'!I$7,IF($E31="PBA",1-'Parametros'!I$7,1)) | N31: =SUMPRODUCT($AK31:$AR31,$AK$13:$AR$13)*IF($E31="CABA",'Parametros'!J$7,IF($E31="PBA",1-'Parametros'!J$7,1)) | O31: =SUMPRODUCT($AK31:$AR31,$AK$14:$AR$14)*IF($E31="CABA",'Parametros'!K$7,IF($E31="PBA",1-'Parametros'!K$7,1)) | AO31: 0.0758 | AP31: 0.0777 | AQ31: 0.0958 | AR31: 0.105
A32: Cuello roscado — Ø29 × 12,5 de alto, rosca M22x1,5, asiento Ø26 | B32: u | C32: Semielaborado comprado | D32: Eli-Met | E32: Todos | F32: =SUMPRODUCT($AK32:$AR32,$AK$5:$AR$5)*IF($E32="CABA",'Parametros'!B$7,IF($E32="PBA",1-'Parametros'!B$7,1)) | G32: =SUMPRODUCT($AK32:$AR32,$AK$6:$AR$6)*IF($E32="CABA",'Parametros'!C$7,IF($E32="PBA",1-'Parametros'!C$7,1)) | H32: =SUMPRODUCT($AK32:$AR32,$AK$7:$AR$7)*IF($E32="CABA",'Parametros'!D$7,IF($E32="PBA",1-'Parametros'!D$7,1)) | I32: =SUMPRODUCT($AK32:$AR32,$AK$8:$AR$8)*IF($E32="CABA",'Parametros'!E$7,IF($E32="PBA",1-'Parametros'!E$7,1)) | J32: =SUMPRODUCT($AK32:$AR32,$AK$9:$AR$9)*IF($E32="CABA",'Parametros'!F$7,IF($E32="PBA",1-'Parametros'!F$7,1)) | K32: =SUMPRODUCT($AK32:$AR32,$AK$10:$AR$10)*IF($E32="CABA",'Parametros'!G$7,IF($E32="PBA",1-'Parametros'!G$7,1)) | L32: =SUMPRODUCT($AK32:$AR32,$AK$11:$AR$11)*IF($E32="CABA",'Parametros'!H$7,IF($E32="PBA",1-'Parametros'!H$7,1)) | M32: =SUMPRODUCT($AK32:$AR32,$AK$12:$AR$12)*IF($E32="CABA",'Parametros'!I$7,IF($E32="PBA",1-'Parametros'!I$7,1)) | N32: =SUMPRODUCT($AK32:$AR32,$AK$13:$AR$13)*IF($E32="CABA",'Parametros'!J$7,IF($E32="PBA",1-'Parametros'!J$7,1)) | O32: =SUMPRODUCT($AK32:$AR32,$AK$14:$AR$14)*IF($E32="CABA",'Parametros'!K$7,IF($E32="PBA",1-'Parametros'!K$7,1)) | AK32: 1
A33: Cuello roscado — Ø36,8 × 14 de alto, rosca M30x1,5, asiento Ø35 | B33: u | C33: Semielaborado comprado | D33: Eli-Met | E33: Todos | F33: =SUMPRODUCT($AK33:$AR33,$AK$5:$AR$5)*IF($E33="CABA",'Parametros'!B$7,IF($E33="PBA",1-'Parametros'!B$7,1)) | G33: =SUMPRODUCT($AK33:$AR33,$AK$6:$AR$6)*IF($E33="CABA",'Parametros'!C$7,IF($E33="PBA",1-'Parametros'!C$7,1)) | H33: =SUMPRODUCT($AK33:$AR33,$AK$7:$AR$7)*IF($E33="CABA",'Parametros'!D$7,IF($E33="PBA",1-'Parametros'!D$7,1)) | I33: =SUMPRODUCT($AK33:$AR33,$AK$8:$AR$8)*IF($E33="CABA",'Parametros'!E$7,IF($E33="PBA",1-'Parametros'!E$7,1)) | J33: =SUMPRODUCT($AK33:$AR33,$AK$9:$AR$9)*IF($E33="CABA",'Parametros'!F$7,IF($E33="PBA",1-'Parametros'!F$7,1)) | K33: =SUMPRODUCT($AK33:$AR33,$AK$10:$AR$10)*IF($E33="CABA",'Parametros'!G$7,IF($E33="PBA",1-'Parametros'!G$7,1)) | L33: =SUMPRODUCT($AK33:$AR33,$AK$11:$AR$11)*IF($E33="CABA",'Parametros'!H$7,IF($E33="PBA",1-'Parametros'!H$7,1)) | M33: =SUMPRODUCT($AK33:$AR33,$AK$12:$AR$12)*IF($E33="CABA",'Parametros'!I$7,IF($E33="PBA",1-'Parametros'!I$7,1)) | N33: =SUMPRODUCT($AK33:$AR33,$AK$13:$AR$13)*IF($E33="CABA",'Parametros'!J$7,IF($E33="PBA",1-'Parametros'!J$7,1)) | O33: =SUMPRODUCT($AK33:$AR33,$AK$14:$AR$14)*IF($E33="CABA",'Parametros'!K$7,IF($E33="PBA",1-'Parametros'!K$7,1)) | AN33: 1
A34: Cuello roscado — Ø37 × 14 de alto, rosca M30x1,5, asiento Ø35 | B34: u | C34: Semielaborado comprado | D34: Eli-Met | E34: Todos | F34: =SUMPRODUCT($AK34:$AR34,$AK$5:$AR$5)*IF($E34="CABA",'Parametros'!B$7,IF($E34="PBA",1-'Parametros'!B$7,1)) | G34: =SUMPRODUCT($AK34:$AR34,$AK$6:$AR$6)*IF($E34="CABA",'Parametros'!C$7,IF($E34="PBA",1-'Parametros'!C$7,1)) | H34: =SUMPRODUCT($AK34:$AR34,$AK$7:$AR$7)*IF($E34="CABA",'Parametros'!D$7,IF($E34="PBA",1-'Parametros'!D$7,1)) | I34: =SUMPRODUCT($AK34:$AR34,$AK$8:$AR$8)*IF($E34="CABA",'Parametros'!E$7,IF($E34="PBA",1-'Parametros'!E$7,1)) | J34: =SUMPRODUCT($AK34:$AR34,$AK$9:$AR$9)*IF($E34="CABA",'Parametros'!F$7,IF($E34="PBA",1-'Parametros'!F$7,1)) | K34: =SUMPRODUCT($AK34:$AR34,$AK$10:$AR$10)*IF($E34="CABA",'Parametros'!G$7,IF($E34="PBA",1-'Parametros'!G$7,1)) | L34: =SUMPRODUCT($AK34:$AR34,$AK$11:$AR$11)*IF($E34="CABA",'Parametros'!H$7,IF($E34="PBA",1-'Parametros'!H$7,1)) | M34: =SUMPRODUCT($AK34:$AR34,$AK$12:$AR$12)*IF($E34="CABA",'Parametros'!I$7,IF($E34="PBA",1-'Parametros'!I$7,1)) | N34: =SUMPRODUCT($AK34:$AR34,$AK$13:$AR$13)*IF($E34="CABA",'Parametros'!J$7,IF($E34="PBA",1-'Parametros'!J$7,1)) | O34: =SUMPRODUCT($AK34:$AR34,$AK$14:$AR$14)*IF($E34="CABA",'Parametros'!K$7,IF($E34="PBA",1-'Parametros'!K$7,1)) | AL34: 1
A35: Cuello roscado — Ø37 × 15 de alto, rosca M30x1,5, asiento Ø35 | B35: u | C35: Semielaborado comprado | D35: Eli-Met | E35: Todos | F35: =SUMPRODUCT($AK35:$AR35,$AK$5:$AR$5)*IF($E35="CABA",'Parametros'!B$7,IF($E35="PBA",1-'Parametros'!B$7,1)) | G35: =SUMPRODUCT($AK35:$AR35,$AK$6:$AR$6)*IF($E35="CABA",'Parametros'!C$7,IF($E35="PBA",1-'Parametros'!C$7,1)) | H35: =SUMPRODUCT($AK35:$AR35,$AK$7:$AR$7)*IF($E35="CABA",'Parametros'!D$7,IF($E35="PBA",1-'Parametros'!D$7,1)) | I35: =SUMPRODUCT($AK35:$AR35,$AK$8:$AR$8)*IF($E35="CABA",'Parametros'!E$7,IF($E35="PBA",1-'Parametros'!E$7,1)) | J35: =SUMPRODUCT($AK35:$AR35,$AK$9:$AR$9)*IF($E35="CABA",'Parametros'!F$7,IF($E35="PBA",1-'Parametros'!F$7,1)) | K35: =SUMPRODUCT($AK35:$AR35,$AK$10:$AR$10)*IF($E35="CABA",'Parametros'!G$7,IF($E35="PBA",1-'Parametros'!G$7,1)) | L35: =SUMPRODUCT($AK35:$AR35,$AK$11:$AR$11)*IF($E35="CABA",'Parametros'!H$7,IF($E35="PBA",1-'Parametros'!H$7,1)) | M35: =SUMPRODUCT($AK35:$AR35,$AK$12:$AR$12)*IF($E35="CABA",'Parametros'!I$7,IF($E35="PBA",1-'Parametros'!I$7,1)) | N35: =SUMPRODUCT($AK35:$AR35,$AK$13:$AR$13)*IF($E35="CABA",'Parametros'!J$7,IF($E35="PBA",1-'Parametros'!J$7,1)) | O35: =SUMPRODUCT($AK35:$AR35,$AK$14:$AR$14)*IF($E35="CABA",'Parametros'!K$7,IF($E35="PBA",1-'Parametros'!K$7,1)) | AM35: 1
A36: Cuello roscado — Ø37 × 35 de alto, rosca M30x1,5, asiento Ø35 | B36: u | C36: Semielaborado comprado | D36: Eli-Met | E36: Todos | F36: =SUMPRODUCT($AK36:$AR36,$AK$5:$AR$5)*IF($E36="CABA",'Parametros'!B$7,IF($E36="PBA",1-'Parametros'!B$7,1)) | G36: =SUMPRODUCT($AK36:$AR36,$AK$6:$AR$6)*IF($E36="CABA",'Parametros'!C$7,IF($E36="PBA",1-'Parametros'!C$7,1)) | H36: =SUMPRODUCT($AK36:$AR36,$AK$7:$AR$7)*IF($E36="CABA",'Parametros'!D$7,IF($E36="PBA",1-'Parametros'!D$7,1)) | I36: =SUMPRODUCT($AK36:$AR36,$AK$8:$AR$8)*IF($E36="CABA",'Parametros'!E$7,IF($E36="PBA",1-'Parametros'!E$7,1)) | J36: =SUMPRODUCT($AK36:$AR36,$AK$9:$AR$9)*IF($E36="CABA",'Parametros'!F$7,IF($E36="PBA",1-'Parametros'!F$7,1)) | K36: =SUMPRODUCT($AK36:$AR36,$AK$10:$AR$10)*IF($E36="CABA",'Parametros'!G$7,IF($E36="PBA",1-'Parametros'!G$7,1)) | L36: =SUMPRODUCT($AK36:$AR36,$AK$11:$AR$11)*IF($E36="CABA",'Parametros'!H$7,IF($E36="PBA",1-'Parametros'!H$7,1)) | M36: =SUMPRODUCT($AK36:$AR36,$AK$12:$AR$12)*IF($E36="CABA",'Parametros'!I$7,IF($E36="PBA",1-'Parametros'!I$7,1)) | N36: =SUMPRODUCT($AK36:$AR36,$AK$13:$AR$13)*IF($E36="CABA",'Parametros'!J$7,IF($E36="PBA",1-'Parametros'!J$7,1)) | O36: =SUMPRODUCT($AK36:$AR36,$AK$14:$AR$14)*IF($E36="CABA",'Parametros'!K$7,IF($E36="PBA",1-'Parametros'!K$7,1)) | AO36: 1
A37: Cuello roscado — Ø88 × 37 de alto, rosca RBSP 2 1/2"-11 h, asiento Ø80 | B37: u | C37: Semielaborado comprado | D37: Eli-Met | E37: Todos | F37: =SUMPRODUCT($AK37:$AR37,$AK$5:$AR$5)*IF($E37="CABA",'Parametros'!B$7,IF($E37="PBA",1-'Parametros'!B$7,1)) | G37: =SUMPRODUCT($AK37:$AR37,$AK$6:$AR$6)*IF($E37="CABA",'Parametros'!C$7,IF($E37="PBA",1-'Parametros'!C$7,1)) | H37: =SUMPRODUCT($AK37:$AR37,$AK$7:$AR$7)*IF($E37="CABA",'Parametros'!D$7,IF($E37="PBA",1-'Parametros'!D$7,1)) | I37: =SUMPRODUCT($AK37:$AR37,$AK$8:$AR$8)*IF($E37="CABA",'Parametros'!E$7,IF($E37="PBA",1-'Parametros'!E$7,1)) | J37: =SUMPRODUCT($AK37:$AR37,$AK$9:$AR$9)*IF($E37="CABA",'Parametros'!F$7,IF($E37="PBA",1-'Parametros'!F$7,1)) | K37: =SUMPRODUCT($AK37:$AR37,$AK$10:$AR$10)*IF($E37="CABA",'Parametros'!G$7,IF($E37="PBA",1-'Parametros'!G$7,1)) | L37: =SUMPRODUCT($AK37:$AR37,$AK$11:$AR$11)*IF($E37="CABA",'Parametros'!H$7,IF($E37="PBA",1-'Parametros'!H$7,1)) | M37: =SUMPRODUCT($AK37:$AR37,$AK$12:$AR$12)*IF($E37="CABA",'Parametros'!I$7,IF($E37="PBA",1-'Parametros'!I$7,1)) | N37: =SUMPRODUCT($AK37:$AR37,$AK$13:$AR$13)*IF($E37="CABA",'Parametros'!J$7,IF($E37="PBA",1-'Parametros'!J$7,1)) | O37: =SUMPRODUCT($AK37:$AR37,$AK$14:$AR$14)*IF($E37="CABA",'Parametros'!K$7,IF($E37="PBA",1-'Parametros'!K$7,1)) | AP37: 1 | AQ37: 1 | AR37: 1
A38: Cúpula — Ø276,5 × e3,2 × 94,4 de alto; disco Ø358,3 | B38: u | C38: Semielaborado comprado | D38: Gockel Ingeniería S.R.L. | E38: Todos | F38: =SUMPRODUCT($AK38:$AR38,$AK$5:$AR$5)*IF($E38="CABA",'Parametros'!B$7,IF($E38="PBA",1-'Parametros'!B$7,1)) | G38: =SUMPRODUCT($AK38:$AR38,$AK$6:$AR$6)*IF($E38="CABA",'Parametros'!C$7,IF($E38="PBA",1-'Parametros'!C$7,1)) | H38: =SUMPRODUCT($AK38:$AR38,$AK$7:$AR$7)*IF($E38="CABA",'Parametros'!D$7,IF($E38="PBA",1-'Parametros'!D$7,1)) | I38: =SUMPRODUCT($AK38:$AR38,$AK$8:$AR$8)*IF($E38="CABA",'Parametros'!E$7,IF($E38="PBA",1-'Parametros'!E$7,1)) | J38: =SUMPRODUCT($AK38:$AR38,$AK$9:$AR$9)*IF($E38="CABA",'Parametros'!F$7,IF($E38="PBA",1-'Parametros'!F$7,1)) | K38: =SUMPRODUCT($AK38:$AR38,$AK$10:$AR$10)*IF($E38="CABA",'Parametros'!G$7,IF($E38="PBA",1-'Parametros'!G$7,1)) | L38: =SUMPRODUCT($AK38:$AR38,$AK$11:$AR$11)*IF($E38="CABA",'Parametros'!H$7,IF($E38="PBA",1-'Parametros'!H$7,1)) | M38: =SUMPRODUCT($AK38:$AR38,$AK$12:$AR$12)*IF($E38="CABA",'Parametros'!I$7,IF($E38="PBA",1-'Parametros'!I$7,1)) | N38: =SUMPRODUCT($AK38:$AR38,$AK$13:$AR$13)*IF($E38="CABA",'Parametros'!J$7,IF($E38="PBA",1-'Parametros'!J$7,1)) | O38: =SUMPRODUCT($AK38:$AR38,$AK$14:$AR$14)*IF($E38="CABA",'Parametros'!K$7,IF($E38="PBA",1-'Parametros'!K$7,1)) | AO38: 1
A39: Cúpula — Ø320 × e3,2 × 109,9 de alto; disco Ø410,8 | B39: u | C39: Semielaborado comprado | D39: Gockel Ingeniería S.R.L. | E39: Todos | F39: =SUMPRODUCT($AK39:$AR39,$AK$5:$AR$5)*IF($E39="CABA",'Parametros'!B$7,IF($E39="PBA",1-'Parametros'!B$7,1)) | G39: =SUMPRODUCT($AK39:$AR39,$AK$6:$AR$6)*IF($E39="CABA",'Parametros'!C$7,IF($E39="PBA",1-'Parametros'!C$7,1)) | H39: =SUMPRODUCT($AK39:$AR39,$AK$7:$AR$7)*IF($E39="CABA",'Parametros'!D$7,IF($E39="PBA",1-'Parametros'!D$7,1)) | I39: =SUMPRODUCT($AK39:$AR39,$AK$8:$AR$8)*IF($E39="CABA",'Parametros'!E$7,IF($E39="PBA",1-'Parametros'!E$7,1)) | J39: =SUMPRODUCT($AK39:$AR39,$AK$9:$AR$9)*IF($E39="CABA",'Parametros'!F$7,IF($E39="PBA",1-'Parametros'!F$7,1)) | K39: =SUMPRODUCT($AK39:$AR39,$AK$10:$AR$10)*IF($E39="CABA",'Parametros'!G$7,IF($E39="PBA",1-'Parametros'!G$7,1)) | L39: =SUMPRODUCT($AK39:$AR39,$AK$11:$AR$11)*IF($E39="CABA",'Parametros'!H$7,IF($E39="PBA",1-'Parametros'!H$7,1)) | M39: =SUMPRODUCT($AK39:$AR39,$AK$12:$AR$12)*IF($E39="CABA",'Parametros'!I$7,IF($E39="PBA",1-'Parametros'!I$7,1)) | N39: =SUMPRODUCT($AK39:$AR39,$AK$13:$AR$13)*IF($E39="CABA",'Parametros'!J$7,IF($E39="PBA",1-'Parametros'!J$7,1)) | O39: =SUMPRODUCT($AK39:$AR39,$AK$14:$AR$14)*IF($E39="CABA",'Parametros'!K$7,IF($E39="PBA",1-'Parametros'!K$7,1)) | AP39: 1
A40: Cúpula — Ø390 × e4,75 × 137,3 de alto; disco Ø507,3 | B40: u | C40: Semielaborado comprado | D40: Gockel Ingeniería S.R.L. | E40: Todos | F40: =SUMPRODUCT($AK40:$AR40,$AK$5:$AR$5)*IF($E40="CABA",'Parametros'!B$7,IF($E40="PBA",1-'Parametros'!B$7,1)) | G40: =SUMPRODUCT($AK40:$AR40,$AK$6:$AR$6)*IF($E40="CABA",'Parametros'!C$7,IF($E40="PBA",1-'Parametros'!C$7,1)) | H40: =SUMPRODUCT($AK40:$AR40,$AK$7:$AR$7)*IF($E40="CABA",'Parametros'!D$7,IF($E40="PBA",1-'Parametros'!D$7,1)) | I40: =SUMPRODUCT($AK40:$AR40,$AK$8:$AR$8)*IF($E40="CABA",'Parametros'!E$7,IF($E40="PBA",1-'Parametros'!E$7,1)) | J40: =SUMPRODUCT($AK40:$AR40,$AK$9:$AR$9)*IF($E40="CABA",'Parametros'!F$7,IF($E40="PBA",1-'Parametros'!F$7,1)) | K40: =SUMPRODUCT($AK40:$AR40,$AK$10:$AR$10)*IF($E40="CABA",'Parametros'!G$7,IF($E40="PBA",1-'Parametros'!G$7,1)) | L40: =SUMPRODUCT($AK40:$AR40,$AK$11:$AR$11)*IF($E40="CABA",'Parametros'!H$7,IF($E40="PBA",1-'Parametros'!H$7,1)) | M40: =SUMPRODUCT($AK40:$AR40,$AK$12:$AR$12)*IF($E40="CABA",'Parametros'!I$7,IF($E40="PBA",1-'Parametros'!I$7,1)) | N40: =SUMPRODUCT($AK40:$AR40,$AK$13:$AR$13)*IF($E40="CABA",'Parametros'!J$7,IF($E40="PBA",1-'Parametros'!J$7,1)) | O40: =SUMPRODUCT($AK40:$AR40,$AK$14:$AR$14)*IF($E40="CABA",'Parametros'!K$7,IF($E40="PBA",1-'Parametros'!K$7,1)) | AQ40: 1 | AR40: 1
A41: Fondo — Ø276,5 × e3,2 × 95 de alto; disco Ø362,5 | B41: u | C41: Semielaborado comprado | D41: Gockel Ingeniería S.R.L. | E41: Todos | F41: =SUMPRODUCT($AK41:$AR41,$AK$5:$AR$5)*IF($E41="CABA",'Parametros'!B$7,IF($E41="PBA",1-'Parametros'!B$7,1)) | G41: =SUMPRODUCT($AK41:$AR41,$AK$6:$AR$6)*IF($E41="CABA",'Parametros'!C$7,IF($E41="PBA",1-'Parametros'!C$7,1)) | H41: =SUMPRODUCT($AK41:$AR41,$AK$7:$AR$7)*IF($E41="CABA",'Parametros'!D$7,IF($E41="PBA",1-'Parametros'!D$7,1)) | I41: =SUMPRODUCT($AK41:$AR41,$AK$8:$AR$8)*IF($E41="CABA",'Parametros'!E$7,IF($E41="PBA",1-'Parametros'!E$7,1)) | J41: =SUMPRODUCT($AK41:$AR41,$AK$9:$AR$9)*IF($E41="CABA",'Parametros'!F$7,IF($E41="PBA",1-'Parametros'!F$7,1)) | K41: =SUMPRODUCT($AK41:$AR41,$AK$10:$AR$10)*IF($E41="CABA",'Parametros'!G$7,IF($E41="PBA",1-'Parametros'!G$7,1)) | L41: =SUMPRODUCT($AK41:$AR41,$AK$11:$AR$11)*IF($E41="CABA",'Parametros'!H$7,IF($E41="PBA",1-'Parametros'!H$7,1)) | M41: =SUMPRODUCT($AK41:$AR41,$AK$12:$AR$12)*IF($E41="CABA",'Parametros'!I$7,IF($E41="PBA",1-'Parametros'!I$7,1)) | N41: =SUMPRODUCT($AK41:$AR41,$AK$13:$AR$13)*IF($E41="CABA",'Parametros'!J$7,IF($E41="PBA",1-'Parametros'!J$7,1)) | O41: =SUMPRODUCT($AK41:$AR41,$AK$14:$AR$14)*IF($E41="CABA",'Parametros'!K$7,IF($E41="PBA",1-'Parametros'!K$7,1)) | AO41: 1
A42: Fondo — Ø320 × e3,2 × 113 de alto; disco Ø423,5 | B42: u | C42: Semielaborado comprado | D42: Gockel Ingeniería S.R.L. | E42: Todos | F42: =SUMPRODUCT($AK42:$AR42,$AK$5:$AR$5)*IF($E42="CABA",'Parametros'!B$7,IF($E42="PBA",1-'Parametros'!B$7,1)) | G42: =SUMPRODUCT($AK42:$AR42,$AK$6:$AR$6)*IF($E42="CABA",'Parametros'!C$7,IF($E42="PBA",1-'Parametros'!C$7,1)) | H42: =SUMPRODUCT($AK42:$AR42,$AK$7:$AR$7)*IF($E42="CABA",'Parametros'!D$7,IF($E42="PBA",1-'Parametros'!D$7,1)) | I42: =SUMPRODUCT($AK42:$AR42,$AK$8:$AR$8)*IF($E42="CABA",'Parametros'!E$7,IF($E42="PBA",1-'Parametros'!E$7,1)) | J42: =SUMPRODUCT($AK42:$AR42,$AK$9:$AR$9)*IF($E42="CABA",'Parametros'!F$7,IF($E42="PBA",1-'Parametros'!F$7,1)) | K42: =SUMPRODUCT($AK42:$AR42,$AK$10:$AR$10)*IF($E42="CABA",'Parametros'!G$7,IF($E42="PBA",1-'Parametros'!G$7,1)) | L42: =SUMPRODUCT($AK42:$AR42,$AK$11:$AR$11)*IF($E42="CABA",'Parametros'!H$7,IF($E42="PBA",1-'Parametros'!H$7,1)) | M42: =SUMPRODUCT($AK42:$AR42,$AK$12:$AR$12)*IF($E42="CABA",'Parametros'!I$7,IF($E42="PBA",1-'Parametros'!I$7,1)) | N42: =SUMPRODUCT($AK42:$AR42,$AK$13:$AR$13)*IF($E42="CABA",'Parametros'!J$7,IF($E42="PBA",1-'Parametros'!J$7,1)) | O42: =SUMPRODUCT($AK42:$AR42,$AK$14:$AR$14)*IF($E42="CABA",'Parametros'!K$7,IF($E42="PBA",1-'Parametros'!K$7,1)) | AP42: 1
A43: Fondo — Ø390 × e4,75 × 139,8 de alto; disco Ø518,1 | B43: u | C43: Semielaborado comprado | D43: Gockel Ingeniería S.R.L. | E43: Todos | F43: =SUMPRODUCT($AK43:$AR43,$AK$5:$AR$5)*IF($E43="CABA",'Parametros'!B$7,IF($E43="PBA",1-'Parametros'!B$7,1)) | G43: =SUMPRODUCT($AK43:$AR43,$AK$6:$AR$6)*IF($E43="CABA",'Parametros'!C$7,IF($E43="PBA",1-'Parametros'!C$7,1)) | H43: =SUMPRODUCT($AK43:$AR43,$AK$7:$AR$7)*IF($E43="CABA",'Parametros'!D$7,IF($E43="PBA",1-'Parametros'!D$7,1)) | I43: =SUMPRODUCT($AK43:$AR43,$AK$8:$AR$8)*IF($E43="CABA",'Parametros'!E$7,IF($E43="PBA",1-'Parametros'!E$7,1)) | J43: =SUMPRODUCT($AK43:$AR43,$AK$9:$AR$9)*IF($E43="CABA",'Parametros'!F$7,IF($E43="PBA",1-'Parametros'!F$7,1)) | K43: =SUMPRODUCT($AK43:$AR43,$AK$10:$AR$10)*IF($E43="CABA",'Parametros'!G$7,IF($E43="PBA",1-'Parametros'!G$7,1)) | L43: =SUMPRODUCT($AK43:$AR43,$AK$11:$AR$11)*IF($E43="CABA",'Parametros'!H$7,IF($E43="PBA",1-'Parametros'!H$7,1)) | M43: =SUMPRODUCT($AK43:$AR43,$AK$12:$AR$12)*IF($E43="CABA",'Parametros'!I$7,IF($E43="PBA",1-'Parametros'!I$7,1)) | N43: =SUMPRODUCT($AK43:$AR43,$AK$13:$AR$13)*IF($E43="CABA",'Parametros'!J$7,IF($E43="PBA",1-'Parametros'!J$7,1)) | O43: =SUMPRODUCT($AK43:$AR43,$AK$14:$AR$14)*IF($E43="CABA",'Parametros'!K$7,IF($E43="PBA",1-'Parametros'!K$7,1)) | AQ43: 1 | AR43: 1
A44: Arandelas de tope (4) — 4 × Ø40 × Ø26 × 4 | B44: u | C44: Componente comprado | D44: Hierros Parrotta | E44: Todos | F44: =SUMPRODUCT($AK44:$AR44,$AK$5:$AR$5)*IF($E44="CABA",'Parametros'!B$7,IF($E44="PBA",1-'Parametros'!B$7,1)) | G44: =SUMPRODUCT($AK44:$AR44,$AK$6:$AR$6)*IF($E44="CABA",'Parametros'!C$7,IF($E44="PBA",1-'Parametros'!C$7,1)) | H44: =SUMPRODUCT($AK44:$AR44,$AK$7:$AR$7)*IF($E44="CABA",'Parametros'!D$7,IF($E44="PBA",1-'Parametros'!D$7,1)) | I44: =SUMPRODUCT($AK44:$AR44,$AK$8:$AR$8)*IF($E44="CABA",'Parametros'!E$7,IF($E44="PBA",1-'Parametros'!E$7,1)) | J44: =SUMPRODUCT($AK44:$AR44,$AK$9:$AR$9)*IF($E44="CABA",'Parametros'!F$7,IF($E44="PBA",1-'Parametros'!F$7,1)) | K44: =SUMPRODUCT($AK44:$AR44,$AK$10:$AR$10)*IF($E44="CABA",'Parametros'!G$7,IF($E44="PBA",1-'Parametros'!G$7,1)) | L44: =SUMPRODUCT($AK44:$AR44,$AK$11:$AR$11)*IF($E44="CABA",'Parametros'!H$7,IF($E44="PBA",1-'Parametros'!H$7,1)) | M44: =SUMPRODUCT($AK44:$AR44,$AK$12:$AR$12)*IF($E44="CABA",'Parametros'!I$7,IF($E44="PBA",1-'Parametros'!I$7,1)) | N44: =SUMPRODUCT($AK44:$AR44,$AK$13:$AR$13)*IF($E44="CABA",'Parametros'!J$7,IF($E44="PBA",1-'Parametros'!J$7,1)) | O44: =SUMPRODUCT($AK44:$AR44,$AK$14:$AR$14)*IF($E44="CABA",'Parametros'!K$7,IF($E44="PBA",1-'Parametros'!K$7,1)) | AO44: 1 | AP44: 1 | AQ44: 1 | AR44: 1
A45: Junta tórica de asiento — Ø24 ext. × cordón 3 | B45: u | C45: Componente comprado | D45: Argensold | E45: Todos | F45: =SUMPRODUCT($AK45:$AR45,$AK$5:$AR$5)*IF($E45="CABA",'Parametros'!B$7,IF($E45="PBA",1-'Parametros'!B$7,1)) | G45: =SUMPRODUCT($AK45:$AR45,$AK$6:$AR$6)*IF($E45="CABA",'Parametros'!C$7,IF($E45="PBA",1-'Parametros'!C$7,1)) | H45: =SUMPRODUCT($AK45:$AR45,$AK$7:$AR$7)*IF($E45="CABA",'Parametros'!D$7,IF($E45="PBA",1-'Parametros'!D$7,1)) | I45: =SUMPRODUCT($AK45:$AR45,$AK$8:$AR$8)*IF($E45="CABA",'Parametros'!E$7,IF($E45="PBA",1-'Parametros'!E$7,1)) | J45: =SUMPRODUCT($AK45:$AR45,$AK$9:$AR$9)*IF($E45="CABA",'Parametros'!F$7,IF($E45="PBA",1-'Parametros'!F$7,1)) | K45: =SUMPRODUCT($AK45:$AR45,$AK$10:$AR$10)*IF($E45="CABA",'Parametros'!G$7,IF($E45="PBA",1-'Parametros'!G$7,1)) | L45: =SUMPRODUCT($AK45:$AR45,$AK$11:$AR$11)*IF($E45="CABA",'Parametros'!H$7,IF($E45="PBA",1-'Parametros'!H$7,1)) | M45: =SUMPRODUCT($AK45:$AR45,$AK$12:$AR$12)*IF($E45="CABA",'Parametros'!I$7,IF($E45="PBA",1-'Parametros'!I$7,1)) | N45: =SUMPRODUCT($AK45:$AR45,$AK$13:$AR$13)*IF($E45="CABA",'Parametros'!J$7,IF($E45="PBA",1-'Parametros'!J$7,1)) | O45: =SUMPRODUCT($AK45:$AR45,$AK$14:$AR$14)*IF($E45="CABA",'Parametros'!K$7,IF($E45="PBA",1-'Parametros'!K$7,1)) | AK45: 1
A46: Junta tórica de asiento — Ø32,8 ext. × cordón 3 | B46: u | C46: Componente comprado | D46: Argensold | E46: Todos | F46: =SUMPRODUCT($AK46:$AR46,$AK$5:$AR$5)*IF($E46="CABA",'Parametros'!B$7,IF($E46="PBA",1-'Parametros'!B$7,1)) | G46: =SUMPRODUCT($AK46:$AR46,$AK$6:$AR$6)*IF($E46="CABA",'Parametros'!C$7,IF($E46="PBA",1-'Parametros'!C$7,1)) | H46: =SUMPRODUCT($AK46:$AR46,$AK$7:$AR$7)*IF($E46="CABA",'Parametros'!D$7,IF($E46="PBA",1-'Parametros'!D$7,1)) | I46: =SUMPRODUCT($AK46:$AR46,$AK$8:$AR$8)*IF($E46="CABA",'Parametros'!E$7,IF($E46="PBA",1-'Parametros'!E$7,1)) | J46: =SUMPRODUCT($AK46:$AR46,$AK$9:$AR$9)*IF($E46="CABA",'Parametros'!F$7,IF($E46="PBA",1-'Parametros'!F$7,1)) | K46: =SUMPRODUCT($AK46:$AR46,$AK$10:$AR$10)*IF($E46="CABA",'Parametros'!G$7,IF($E46="PBA",1-'Parametros'!G$7,1)) | L46: =SUMPRODUCT($AK46:$AR46,$AK$11:$AR$11)*IF($E46="CABA",'Parametros'!H$7,IF($E46="PBA",1-'Parametros'!H$7,1)) | M46: =SUMPRODUCT($AK46:$AR46,$AK$12:$AR$12)*IF($E46="CABA",'Parametros'!I$7,IF($E46="PBA",1-'Parametros'!I$7,1)) | N46: =SUMPRODUCT($AK46:$AR46,$AK$13:$AR$13)*IF($E46="CABA",'Parametros'!J$7,IF($E46="PBA",1-'Parametros'!J$7,1)) | O46: =SUMPRODUCT($AK46:$AR46,$AK$14:$AR$14)*IF($E46="CABA",'Parametros'!K$7,IF($E46="PBA",1-'Parametros'!K$7,1)) | AL46: 1 | AM46: 1 | AN46: 1 | AO46: 1
A47: Junta tórica de asiento — Ø78 ext. × cordón 3 | B47: u | C47: Componente comprado | D47: Argensold | E47: Todos | F47: =SUMPRODUCT($AK47:$AR47,$AK$5:$AR$5)*IF($E47="CABA",'Parametros'!B$7,IF($E47="PBA",1-'Parametros'!B$7,1)) | G47: =SUMPRODUCT($AK47:$AR47,$AK$6:$AR$6)*IF($E47="CABA",'Parametros'!C$7,IF($E47="PBA",1-'Parametros'!C$7,1)) | H47: =SUMPRODUCT($AK47:$AR47,$AK$7:$AR$7)*IF($E47="CABA",'Parametros'!D$7,IF($E47="PBA",1-'Parametros'!D$7,1)) | I47: =SUMPRODUCT($AK47:$AR47,$AK$8:$AR$8)*IF($E47="CABA",'Parametros'!E$7,IF($E47="PBA",1-'Parametros'!E$7,1)) | J47: =SUMPRODUCT($AK47:$AR47,$AK$9:$AR$9)*IF($E47="CABA",'Parametros'!F$7,IF($E47="PBA",1-'Parametros'!F$7,1)) | K47: =SUMPRODUCT($AK47:$AR47,$AK$10:$AR$10)*IF($E47="CABA",'Parametros'!G$7,IF($E47="PBA",1-'Parametros'!G$7,1)) | L47: =SUMPRODUCT($AK47:$AR47,$AK$11:$AR$11)*IF($E47="CABA",'Parametros'!H$7,IF($E47="PBA",1-'Parametros'!H$7,1)) | M47: =SUMPRODUCT($AK47:$AR47,$AK$12:$AR$12)*IF($E47="CABA",'Parametros'!I$7,IF($E47="PBA",1-'Parametros'!I$7,1)) | N47: =SUMPRODUCT($AK47:$AR47,$AK$13:$AR$13)*IF($E47="CABA",'Parametros'!J$7,IF($E47="PBA",1-'Parametros'!J$7,1)) | O47: =SUMPRODUCT($AK47:$AR47,$AK$14:$AR$14)*IF($E47="CABA",'Parametros'!K$7,IF($E47="PBA",1-'Parametros'!K$7,1)) | AP47: 1 | AQ47: 1 | AR47: 1
A48: Manguera (tramo enrollado) — Ø25 × 1.219 de largo desarrollado | B48: u | C48: Componente comprado | D48: Yukon / MatafuegosYa S.R.L. | E48: Todos | F48: =SUMPRODUCT($AK48:$AR48,$AK$5:$AR$5)*IF($E48="CABA",'Parametros'!B$7,IF($E48="PBA",1-'Parametros'!B$7,1)) | G48: =SUMPRODUCT($AK48:$AR48,$AK$6:$AR$6)*IF($E48="CABA",'Parametros'!C$7,IF($E48="PBA",1-'Parametros'!C$7,1)) | H48: =SUMPRODUCT($AK48:$AR48,$AK$7:$AR$7)*IF($E48="CABA",'Parametros'!D$7,IF($E48="PBA",1-'Parametros'!D$7,1)) | I48: =SUMPRODUCT($AK48:$AR48,$AK$8:$AR$8)*IF($E48="CABA",'Parametros'!E$7,IF($E48="PBA",1-'Parametros'!E$7,1)) | J48: =SUMPRODUCT($AK48:$AR48,$AK$9:$AR$9)*IF($E48="CABA",'Parametros'!F$7,IF($E48="PBA",1-'Parametros'!F$7,1)) | K48: =SUMPRODUCT($AK48:$AR48,$AK$10:$AR$10)*IF($E48="CABA",'Parametros'!G$7,IF($E48="PBA",1-'Parametros'!G$7,1)) | L48: =SUMPRODUCT($AK48:$AR48,$AK$11:$AR$11)*IF($E48="CABA",'Parametros'!H$7,IF($E48="PBA",1-'Parametros'!H$7,1)) | M48: =SUMPRODUCT($AK48:$AR48,$AK$12:$AR$12)*IF($E48="CABA",'Parametros'!I$7,IF($E48="PBA",1-'Parametros'!I$7,1)) | N48: =SUMPRODUCT($AK48:$AR48,$AK$13:$AR$13)*IF($E48="CABA",'Parametros'!J$7,IF($E48="PBA",1-'Parametros'!J$7,1)) | O48: =SUMPRODUCT($AK48:$AR48,$AK$14:$AR$14)*IF($E48="CABA",'Parametros'!K$7,IF($E48="PBA",1-'Parametros'!K$7,1)) | AP48: 1
A49: Manguera (tramo enrollado) — Ø25 × 1.321 de largo desarrollado | B49: u | C49: Componente comprado | D49: Yukon / MatafuegosYa S.R.L. | E49: Todos | F49: =SUMPRODUCT($AK49:$AR49,$AK$5:$AR$5)*IF($E49="CABA",'Parametros'!B$7,IF($E49="PBA",1-'Parametros'!B$7,1)) | G49: =SUMPRODUCT($AK49:$AR49,$AK$6:$AR$6)*IF($E49="CABA",'Parametros'!C$7,IF($E49="PBA",1-'Parametros'!C$7,1)) | H49: =SUMPRODUCT($AK49:$AR49,$AK$7:$AR$7)*IF($E49="CABA",'Parametros'!D$7,IF($E49="PBA",1-'Parametros'!D$7,1)) | I49: =SUMPRODUCT($AK49:$AR49,$AK$8:$AR$8)*IF($E49="CABA",'Parametros'!E$7,IF($E49="PBA",1-'Parametros'!E$7,1)) | J49: =SUMPRODUCT($AK49:$AR49,$AK$9:$AR$9)*IF($E49="CABA",'Parametros'!F$7,IF($E49="PBA",1-'Parametros'!F$7,1)) | K49: =SUMPRODUCT($AK49:$AR49,$AK$10:$AR$10)*IF($E49="CABA",'Parametros'!G$7,IF($E49="PBA",1-'Parametros'!G$7,1)) | L49: =SUMPRODUCT($AK49:$AR49,$AK$11:$AR$11)*IF($E49="CABA",'Parametros'!H$7,IF($E49="PBA",1-'Parametros'!H$7,1)) | M49: =SUMPRODUCT($AK49:$AR49,$AK$12:$AR$12)*IF($E49="CABA",'Parametros'!I$7,IF($E49="PBA",1-'Parametros'!I$7,1)) | N49: =SUMPRODUCT($AK49:$AR49,$AK$13:$AR$13)*IF($E49="CABA",'Parametros'!J$7,IF($E49="PBA",1-'Parametros'!J$7,1)) | O49: =SUMPRODUCT($AK49:$AR49,$AK$14:$AR$14)*IF($E49="CABA",'Parametros'!K$7,IF($E49="PBA",1-'Parametros'!K$7,1)) | AQ49: 1
A50: Manguera (tramo enrollado) — Ø25 × 1.664 de largo desarrollado | B50: u | C50: Componente comprado | D50: Yukon / MatafuegosYa S.R.L. | E50: Todos | F50: =SUMPRODUCT($AK50:$AR50,$AK$5:$AR$5)*IF($E50="CABA",'Parametros'!B$7,IF($E50="PBA",1-'Parametros'!B$7,1)) | G50: =SUMPRODUCT($AK50:$AR50,$AK$6:$AR$6)*IF($E50="CABA",'Parametros'!C$7,IF($E50="PBA",1-'Parametros'!C$7,1)) | H50: =SUMPRODUCT($AK50:$AR50,$AK$7:$AR$7)*IF($E50="CABA",'Parametros'!D$7,IF($E50="PBA",1-'Parametros'!D$7,1)) | I50: =SUMPRODUCT($AK50:$AR50,$AK$8:$AR$8)*IF($E50="CABA",'Parametros'!E$7,IF($E50="PBA",1-'Parametros'!E$7,1)) | J50: =SUMPRODUCT($AK50:$AR50,$AK$9:$AR$9)*IF($E50="CABA",'Parametros'!F$7,IF($E50="PBA",1-'Parametros'!F$7,1)) | K50: =SUMPRODUCT($AK50:$AR50,$AK$10:$AR$10)*IF($E50="CABA",'Parametros'!G$7,IF($E50="PBA",1-'Parametros'!G$7,1)) | L50: =SUMPRODUCT($AK50:$AR50,$AK$11:$AR$11)*IF($E50="CABA",'Parametros'!H$7,IF($E50="PBA",1-'Parametros'!H$7,1)) | M50: =SUMPRODUCT($AK50:$AR50,$AK$12:$AR$12)*IF($E50="CABA",'Parametros'!I$7,IF($E50="PBA",1-'Parametros'!I$7,1)) | N50: =SUMPRODUCT($AK50:$AR50,$AK$13:$AR$13)*IF($E50="CABA",'Parametros'!J$7,IF($E50="PBA",1-'Parametros'!J$7,1)) | O50: =SUMPRODUCT($AK50:$AR50,$AK$14:$AR$14)*IF($E50="CABA",'Parametros'!K$7,IF($E50="PBA",1-'Parametros'!K$7,1)) | AR50: 1
A51: Manguera (tramo enrollado) — Ø25 × 968 de largo desarrollado | B51: u | C51: Componente comprado | D51: Yukon / MatafuegosYa S.R.L. | E51: Todos | F51: =SUMPRODUCT($AK51:$AR51,$AK$5:$AR$5)*IF($E51="CABA",'Parametros'!B$7,IF($E51="PBA",1-'Parametros'!B$7,1)) | G51: =SUMPRODUCT($AK51:$AR51,$AK$6:$AR$6)*IF($E51="CABA",'Parametros'!C$7,IF($E51="PBA",1-'Parametros'!C$7,1)) | H51: =SUMPRODUCT($AK51:$AR51,$AK$7:$AR$7)*IF($E51="CABA",'Parametros'!D$7,IF($E51="PBA",1-'Parametros'!D$7,1)) | I51: =SUMPRODUCT($AK51:$AR51,$AK$8:$AR$8)*IF($E51="CABA",'Parametros'!E$7,IF($E51="PBA",1-'Parametros'!E$7,1)) | J51: =SUMPRODUCT($AK51:$AR51,$AK$9:$AR$9)*IF($E51="CABA",'Parametros'!F$7,IF($E51="PBA",1-'Parametros'!F$7,1)) | K51: =SUMPRODUCT($AK51:$AR51,$AK$10:$AR$10)*IF($E51="CABA",'Parametros'!G$7,IF($E51="PBA",1-'Parametros'!G$7,1)) | L51: =SUMPRODUCT($AK51:$AR51,$AK$11:$AR$11)*IF($E51="CABA",'Parametros'!H$7,IF($E51="PBA",1-'Parametros'!H$7,1)) | M51: =SUMPRODUCT($AK51:$AR51,$AK$12:$AR$12)*IF($E51="CABA",'Parametros'!I$7,IF($E51="PBA",1-'Parametros'!I$7,1)) | N51: =SUMPRODUCT($AK51:$AR51,$AK$13:$AR$13)*IF($E51="CABA",'Parametros'!J$7,IF($E51="PBA",1-'Parametros'!J$7,1)) | O51: =SUMPRODUCT($AK51:$AR51,$AK$14:$AR$14)*IF($E51="CABA",'Parametros'!K$7,IF($E51="PBA",1-'Parametros'!K$7,1)) | AO51: 1
A52: Manguera — Ø16 × 1.053 de largo desarrollado | B52: u | C52: Componente comprado | D52: Yukon / MatafuegosYa S.R.L. | E52: Todos | F52: =SUMPRODUCT($AK52:$AR52,$AK$5:$AR$5)*IF($E52="CABA",'Parametros'!B$7,IF($E52="PBA",1-'Parametros'!B$7,1)) | G52: =SUMPRODUCT($AK52:$AR52,$AK$6:$AR$6)*IF($E52="CABA",'Parametros'!C$7,IF($E52="PBA",1-'Parametros'!C$7,1)) | H52: =SUMPRODUCT($AK52:$AR52,$AK$7:$AR$7)*IF($E52="CABA",'Parametros'!D$7,IF($E52="PBA",1-'Parametros'!D$7,1)) | I52: =SUMPRODUCT($AK52:$AR52,$AK$8:$AR$8)*IF($E52="CABA",'Parametros'!E$7,IF($E52="PBA",1-'Parametros'!E$7,1)) | J52: =SUMPRODUCT($AK52:$AR52,$AK$9:$AR$9)*IF($E52="CABA",'Parametros'!F$7,IF($E52="PBA",1-'Parametros'!F$7,1)) | K52: =SUMPRODUCT($AK52:$AR52,$AK$10:$AR$10)*IF($E52="CABA",'Parametros'!G$7,IF($E52="PBA",1-'Parametros'!G$7,1)) | L52: =SUMPRODUCT($AK52:$AR52,$AK$11:$AR$11)*IF($E52="CABA",'Parametros'!H$7,IF($E52="PBA",1-'Parametros'!H$7,1)) | M52: =SUMPRODUCT($AK52:$AR52,$AK$12:$AR$12)*IF($E52="CABA",'Parametros'!I$7,IF($E52="PBA",1-'Parametros'!I$7,1)) | N52: =SUMPRODUCT($AK52:$AR52,$AK$13:$AR$13)*IF($E52="CABA",'Parametros'!J$7,IF($E52="PBA",1-'Parametros'!J$7,1)) | O52: =SUMPRODUCT($AK52:$AR52,$AK$14:$AR$14)*IF($E52="CABA",'Parametros'!K$7,IF($E52="PBA",1-'Parametros'!K$7,1)) | AR52: 1
A53: Manguera — Ø16 × 238 de largo desarrollado | B53: u | C53: Componente comprado | D53: Yukon / MatafuegosYa S.R.L. | E53: Todos | F53: =SUMPRODUCT($AK53:$AR53,$AK$5:$AR$5)*IF($E53="CABA",'Parametros'!B$7,IF($E53="PBA",1-'Parametros'!B$7,1)) | G53: =SUMPRODUCT($AK53:$AR53,$AK$6:$AR$6)*IF($E53="CABA",'Parametros'!C$7,IF($E53="PBA",1-'Parametros'!C$7,1)) | H53: =SUMPRODUCT($AK53:$AR53,$AK$7:$AR$7)*IF($E53="CABA",'Parametros'!D$7,IF($E53="PBA",1-'Parametros'!D$7,1)) | I53: =SUMPRODUCT($AK53:$AR53,$AK$8:$AR$8)*IF($E53="CABA",'Parametros'!E$7,IF($E53="PBA",1-'Parametros'!E$7,1)) | J53: =SUMPRODUCT($AK53:$AR53,$AK$9:$AR$9)*IF($E53="CABA",'Parametros'!F$7,IF($E53="PBA",1-'Parametros'!F$7,1)) | K53: =SUMPRODUCT($AK53:$AR53,$AK$10:$AR$10)*IF($E53="CABA",'Parametros'!G$7,IF($E53="PBA",1-'Parametros'!G$7,1)) | L53: =SUMPRODUCT($AK53:$AR53,$AK$11:$AR$11)*IF($E53="CABA",'Parametros'!H$7,IF($E53="PBA",1-'Parametros'!H$7,1)) | M53: =SUMPRODUCT($AK53:$AR53,$AK$12:$AR$12)*IF($E53="CABA",'Parametros'!I$7,IF($E53="PBA",1-'Parametros'!I$7,1)) | N53: =SUMPRODUCT($AK53:$AR53,$AK$13:$AR$13)*IF($E53="CABA",'Parametros'!J$7,IF($E53="PBA",1-'Parametros'!J$7,1)) | O53: =SUMPRODUCT($AK53:$AR53,$AK$14:$AR$14)*IF($E53="CABA",'Parametros'!K$7,IF($E53="PBA",1-'Parametros'!K$7,1)) | AL53: 1
A54: Manguera — Ø16 × 328 de largo desarrollado | B54: u | C54: Componente comprado | D54: Yukon / MatafuegosYa S.R.L. | E54: Todos | F54: =SUMPRODUCT($AK54:$AR54,$AK$5:$AR$5)*IF($E54="CABA",'Parametros'!B$7,IF($E54="PBA",1-'Parametros'!B$7,1)) | G54: =SUMPRODUCT($AK54:$AR54,$AK$6:$AR$6)*IF($E54="CABA",'Parametros'!C$7,IF($E54="PBA",1-'Parametros'!C$7,1)) | H54: =SUMPRODUCT($AK54:$AR54,$AK$7:$AR$7)*IF($E54="CABA",'Parametros'!D$7,IF($E54="PBA",1-'Parametros'!D$7,1)) | I54: =SUMPRODUCT($AK54:$AR54,$AK$8:$AR$8)*IF($E54="CABA",'Parametros'!E$7,IF($E54="PBA",1-'Parametros'!E$7,1)) | J54: =SUMPRODUCT($AK54:$AR54,$AK$9:$AR$9)*IF($E54="CABA",'Parametros'!F$7,IF($E54="PBA",1-'Parametros'!F$7,1)) | K54: =SUMPRODUCT($AK54:$AR54,$AK$10:$AR$10)*IF($E54="CABA",'Parametros'!G$7,IF($E54="PBA",1-'Parametros'!G$7,1)) | L54: =SUMPRODUCT($AK54:$AR54,$AK$11:$AR$11)*IF($E54="CABA",'Parametros'!H$7,IF($E54="PBA",1-'Parametros'!H$7,1)) | M54: =SUMPRODUCT($AK54:$AR54,$AK$12:$AR$12)*IF($E54="CABA",'Parametros'!I$7,IF($E54="PBA",1-'Parametros'!I$7,1)) | N54: =SUMPRODUCT($AK54:$AR54,$AK$13:$AR$13)*IF($E54="CABA",'Parametros'!J$7,IF($E54="PBA",1-'Parametros'!J$7,1)) | O54: =SUMPRODUCT($AK54:$AR54,$AK$14:$AR$14)*IF($E54="CABA",'Parametros'!K$7,IF($E54="PBA",1-'Parametros'!K$7,1)) | AM54: 1
A55: Manguera — Ø16 × 517 de largo desarrollado | B55: u | C55: Componente comprado | D55: Yukon / MatafuegosYa S.R.L. | E55: Todos | F55: =SUMPRODUCT($AK55:$AR55,$AK$5:$AR$5)*IF($E55="CABA",'Parametros'!B$7,IF($E55="PBA",1-'Parametros'!B$7,1)) | G55: =SUMPRODUCT($AK55:$AR55,$AK$6:$AR$6)*IF($E55="CABA",'Parametros'!C$7,IF($E55="PBA",1-'Parametros'!C$7,1)) | H55: =SUMPRODUCT($AK55:$AR55,$AK$7:$AR$7)*IF($E55="CABA",'Parametros'!D$7,IF($E55="PBA",1-'Parametros'!D$7,1)) | I55: =SUMPRODUCT($AK55:$AR55,$AK$8:$AR$8)*IF($E55="CABA",'Parametros'!E$7,IF($E55="PBA",1-'Parametros'!E$7,1)) | J55: =SUMPRODUCT($AK55:$AR55,$AK$9:$AR$9)*IF($E55="CABA",'Parametros'!F$7,IF($E55="PBA",1-'Parametros'!F$7,1)) | K55: =SUMPRODUCT($AK55:$AR55,$AK$10:$AR$10)*IF($E55="CABA",'Parametros'!G$7,IF($E55="PBA",1-'Parametros'!G$7,1)) | L55: =SUMPRODUCT($AK55:$AR55,$AK$11:$AR$11)*IF($E55="CABA",'Parametros'!H$7,IF($E55="PBA",1-'Parametros'!H$7,1)) | M55: =SUMPRODUCT($AK55:$AR55,$AK$12:$AR$12)*IF($E55="CABA",'Parametros'!I$7,IF($E55="PBA",1-'Parametros'!I$7,1)) | N55: =SUMPRODUCT($AK55:$AR55,$AK$13:$AR$13)*IF($E55="CABA",'Parametros'!J$7,IF($E55="PBA",1-'Parametros'!J$7,1)) | O55: =SUMPRODUCT($AK55:$AR55,$AK$14:$AR$14)*IF($E55="CABA",'Parametros'!K$7,IF($E55="PBA",1-'Parametros'!K$7,1)) | AN55: 1
A56: Manguera — Ø16 × 656 de largo desarrollado | B56: u | C56: Componente comprado | D56: Yukon / MatafuegosYa S.R.L. | E56: Todos | F56: =SUMPRODUCT($AK56:$AR56,$AK$5:$AR$5)*IF($E56="CABA",'Parametros'!B$7,IF($E56="PBA",1-'Parametros'!B$7,1)) | G56: =SUMPRODUCT($AK56:$AR56,$AK$6:$AR$6)*IF($E56="CABA",'Parametros'!C$7,IF($E56="PBA",1-'Parametros'!C$7,1)) | H56: =SUMPRODUCT($AK56:$AR56,$AK$7:$AR$7)*IF($E56="CABA",'Parametros'!D$7,IF($E56="PBA",1-'Parametros'!D$7,1)) | I56: =SUMPRODUCT($AK56:$AR56,$AK$8:$AR$8)*IF($E56="CABA",'Parametros'!E$7,IF($E56="PBA",1-'Parametros'!E$7,1)) | J56: =SUMPRODUCT($AK56:$AR56,$AK$9:$AR$9)*IF($E56="CABA",'Parametros'!F$7,IF($E56="PBA",1-'Parametros'!F$7,1)) | K56: =SUMPRODUCT($AK56:$AR56,$AK$10:$AR$10)*IF($E56="CABA",'Parametros'!G$7,IF($E56="PBA",1-'Parametros'!G$7,1)) | L56: =SUMPRODUCT($AK56:$AR56,$AK$11:$AR$11)*IF($E56="CABA",'Parametros'!H$7,IF($E56="PBA",1-'Parametros'!H$7,1)) | M56: =SUMPRODUCT($AK56:$AR56,$AK$12:$AR$12)*IF($E56="CABA",'Parametros'!I$7,IF($E56="PBA",1-'Parametros'!I$7,1)) | N56: =SUMPRODUCT($AK56:$AR56,$AK$13:$AR$13)*IF($E56="CABA",'Parametros'!J$7,IF($E56="PBA",1-'Parametros'!J$7,1)) | O56: =SUMPRODUCT($AK56:$AR56,$AK$14:$AR$14)*IF($E56="CABA",'Parametros'!K$7,IF($E56="PBA",1-'Parametros'!K$7,1)) | AO56: 1
A57: Manguera — Ø16 × 848 de largo desarrollado | B57: u | C57: Componente comprado | D57: Yukon / MatafuegosYa S.R.L. | E57: Todos | F57: =SUMPRODUCT($AK57:$AR57,$AK$5:$AR$5)*IF($E57="CABA",'Parametros'!B$7,IF($E57="PBA",1-'Parametros'!B$7,1)) | G57: =SUMPRODUCT($AK57:$AR57,$AK$6:$AR$6)*IF($E57="CABA",'Parametros'!C$7,IF($E57="PBA",1-'Parametros'!C$7,1)) | H57: =SUMPRODUCT($AK57:$AR57,$AK$7:$AR$7)*IF($E57="CABA",'Parametros'!D$7,IF($E57="PBA",1-'Parametros'!D$7,1)) | I57: =SUMPRODUCT($AK57:$AR57,$AK$8:$AR$8)*IF($E57="CABA",'Parametros'!E$7,IF($E57="PBA",1-'Parametros'!E$7,1)) | J57: =SUMPRODUCT($AK57:$AR57,$AK$9:$AR$9)*IF($E57="CABA",'Parametros'!F$7,IF($E57="PBA",1-'Parametros'!F$7,1)) | K57: =SUMPRODUCT($AK57:$AR57,$AK$10:$AR$10)*IF($E57="CABA",'Parametros'!G$7,IF($E57="PBA",1-'Parametros'!G$7,1)) | L57: =SUMPRODUCT($AK57:$AR57,$AK$11:$AR$11)*IF($E57="CABA",'Parametros'!H$7,IF($E57="PBA",1-'Parametros'!H$7,1)) | M57: =SUMPRODUCT($AK57:$AR57,$AK$12:$AR$12)*IF($E57="CABA",'Parametros'!I$7,IF($E57="PBA",1-'Parametros'!I$7,1)) | N57: =SUMPRODUCT($AK57:$AR57,$AK$13:$AR$13)*IF($E57="CABA",'Parametros'!J$7,IF($E57="PBA",1-'Parametros'!J$7,1)) | O57: =SUMPRODUCT($AK57:$AR57,$AK$14:$AR$14)*IF($E57="CABA",'Parametros'!K$7,IF($E57="PBA",1-'Parametros'!K$7,1)) | AP57: 1
A58: Manguera — Ø16 × 999 de largo desarrollado | B58: u | C58: Componente comprado | D58: Yukon / MatafuegosYa S.R.L. | E58: Todos | F58: =SUMPRODUCT($AK58:$AR58,$AK$5:$AR$5)*IF($E58="CABA",'Parametros'!B$7,IF($E58="PBA",1-'Parametros'!B$7,1)) | G58: =SUMPRODUCT($AK58:$AR58,$AK$6:$AR$6)*IF($E58="CABA",'Parametros'!C$7,IF($E58="PBA",1-'Parametros'!C$7,1)) | H58: =SUMPRODUCT($AK58:$AR58,$AK$7:$AR$7)*IF($E58="CABA",'Parametros'!D$7,IF($E58="PBA",1-'Parametros'!D$7,1)) | I58: =SUMPRODUCT($AK58:$AR58,$AK$8:$AR$8)*IF($E58="CABA",'Parametros'!E$7,IF($E58="PBA",1-'Parametros'!E$7,1)) | J58: =SUMPRODUCT($AK58:$AR58,$AK$9:$AR$9)*IF($E58="CABA",'Parametros'!F$7,IF($E58="PBA",1-'Parametros'!F$7,1)) | K58: =SUMPRODUCT($AK58:$AR58,$AK$10:$AR$10)*IF($E58="CABA",'Parametros'!G$7,IF($E58="PBA",1-'Parametros'!G$7,1)) | L58: =SUMPRODUCT($AK58:$AR58,$AK$11:$AR$11)*IF($E58="CABA",'Parametros'!H$7,IF($E58="PBA",1-'Parametros'!H$7,1)) | M58: =SUMPRODUCT($AK58:$AR58,$AK$12:$AR$12)*IF($E58="CABA",'Parametros'!I$7,IF($E58="PBA",1-'Parametros'!I$7,1)) | N58: =SUMPRODUCT($AK58:$AR58,$AK$13:$AR$13)*IF($E58="CABA",'Parametros'!J$7,IF($E58="PBA",1-'Parametros'!J$7,1)) | O58: =SUMPRODUCT($AK58:$AR58,$AK$14:$AR$14)*IF($E58="CABA",'Parametros'!K$7,IF($E58="PBA",1-'Parametros'!K$7,1)) | AQ58: 1
A59: Manómetro — Ø36 esfera, rango 0-3,5 MPa, sector verde en 1,4 | B59: u | C59: Componente comprado | D59: Yukon / MatafuegosYa S.R.L. | E59: Todos | F59: =SUMPRODUCT($AK59:$AR59,$AK$5:$AR$5)*IF($E59="CABA",'Parametros'!B$7,IF($E59="PBA",1-'Parametros'!B$7,1)) | G59: =SUMPRODUCT($AK59:$AR59,$AK$6:$AR$6)*IF($E59="CABA",'Parametros'!C$7,IF($E59="PBA",1-'Parametros'!C$7,1)) | H59: =SUMPRODUCT($AK59:$AR59,$AK$7:$AR$7)*IF($E59="CABA",'Parametros'!D$7,IF($E59="PBA",1-'Parametros'!D$7,1)) | I59: =SUMPRODUCT($AK59:$AR59,$AK$8:$AR$8)*IF($E59="CABA",'Parametros'!E$7,IF($E59="PBA",1-'Parametros'!E$7,1)) | J59: =SUMPRODUCT($AK59:$AR59,$AK$9:$AR$9)*IF($E59="CABA",'Parametros'!F$7,IF($E59="PBA",1-'Parametros'!F$7,1)) | K59: =SUMPRODUCT($AK59:$AR59,$AK$10:$AR$10)*IF($E59="CABA",'Parametros'!G$7,IF($E59="PBA",1-'Parametros'!G$7,1)) | L59: =SUMPRODUCT($AK59:$AR59,$AK$11:$AR$11)*IF($E59="CABA",'Parametros'!H$7,IF($E59="PBA",1-'Parametros'!H$7,1)) | M59: =SUMPRODUCT($AK59:$AR59,$AK$12:$AR$12)*IF($E59="CABA",'Parametros'!I$7,IF($E59="PBA",1-'Parametros'!I$7,1)) | N59: =SUMPRODUCT($AK59:$AR59,$AK$13:$AR$13)*IF($E59="CABA",'Parametros'!J$7,IF($E59="PBA",1-'Parametros'!J$7,1)) | O59: =SUMPRODUCT($AK59:$AR59,$AK$14:$AR$14)*IF($E59="CABA",'Parametros'!K$7,IF($E59="PBA",1-'Parametros'!K$7,1)) | AK59: 1 | AL59: 1 | AM59: 1 | AN59: 1
A60: Manómetro — Ø47 esfera, rango 0-3,5 MPa, sector verde en 1,4 | B60: u | C60: Componente comprado | D60: Yukon / MatafuegosYa S.R.L. | E60: Todos | F60: =SUMPRODUCT($AK60:$AR60,$AK$5:$AR$5)*IF($E60="CABA",'Parametros'!B$7,IF($E60="PBA",1-'Parametros'!B$7,1)) | G60: =SUMPRODUCT($AK60:$AR60,$AK$6:$AR$6)*IF($E60="CABA",'Parametros'!C$7,IF($E60="PBA",1-'Parametros'!C$7,1)) | H60: =SUMPRODUCT($AK60:$AR60,$AK$7:$AR$7)*IF($E60="CABA",'Parametros'!D$7,IF($E60="PBA",1-'Parametros'!D$7,1)) | I60: =SUMPRODUCT($AK60:$AR60,$AK$8:$AR$8)*IF($E60="CABA",'Parametros'!E$7,IF($E60="PBA",1-'Parametros'!E$7,1)) | J60: =SUMPRODUCT($AK60:$AR60,$AK$9:$AR$9)*IF($E60="CABA",'Parametros'!F$7,IF($E60="PBA",1-'Parametros'!F$7,1)) | K60: =SUMPRODUCT($AK60:$AR60,$AK$10:$AR$10)*IF($E60="CABA",'Parametros'!G$7,IF($E60="PBA",1-'Parametros'!G$7,1)) | L60: =SUMPRODUCT($AK60:$AR60,$AK$11:$AR$11)*IF($E60="CABA",'Parametros'!H$7,IF($E60="PBA",1-'Parametros'!H$7,1)) | M60: =SUMPRODUCT($AK60:$AR60,$AK$12:$AR$12)*IF($E60="CABA",'Parametros'!I$7,IF($E60="PBA",1-'Parametros'!I$7,1)) | N60: =SUMPRODUCT($AK60:$AR60,$AK$13:$AR$13)*IF($E60="CABA",'Parametros'!J$7,IF($E60="PBA",1-'Parametros'!J$7,1)) | O60: =SUMPRODUCT($AK60:$AR60,$AK$14:$AR$14)*IF($E60="CABA",'Parametros'!K$7,IF($E60="PBA",1-'Parametros'!K$7,1)) | AO60: 1 | AP60: 1 | AQ60: 1 | AR60: 1
A61: Neumático macizo — Ø300 × 49 de ancho | B61: u | C61: Componente comprado | D61: Ruedar | E61: Todos | F61: =SUMPRODUCT($AK61:$AR61,$AK$5:$AR$5)*IF($E61="CABA",'Parametros'!B$7,IF($E61="PBA",1-'Parametros'!B$7,1)) | G61: =SUMPRODUCT($AK61:$AR61,$AK$6:$AR$6)*IF($E61="CABA",'Parametros'!C$7,IF($E61="PBA",1-'Parametros'!C$7,1)) | H61: =SUMPRODUCT($AK61:$AR61,$AK$7:$AR$7)*IF($E61="CABA",'Parametros'!D$7,IF($E61="PBA",1-'Parametros'!D$7,1)) | I61: =SUMPRODUCT($AK61:$AR61,$AK$8:$AR$8)*IF($E61="CABA",'Parametros'!E$7,IF($E61="PBA",1-'Parametros'!E$7,1)) | J61: =SUMPRODUCT($AK61:$AR61,$AK$9:$AR$9)*IF($E61="CABA",'Parametros'!F$7,IF($E61="PBA",1-'Parametros'!F$7,1)) | K61: =SUMPRODUCT($AK61:$AR61,$AK$10:$AR$10)*IF($E61="CABA",'Parametros'!G$7,IF($E61="PBA",1-'Parametros'!G$7,1)) | L61: =SUMPRODUCT($AK61:$AR61,$AK$11:$AR$11)*IF($E61="CABA",'Parametros'!H$7,IF($E61="PBA",1-'Parametros'!H$7,1)) | M61: =SUMPRODUCT($AK61:$AR61,$AK$12:$AR$12)*IF($E61="CABA",'Parametros'!I$7,IF($E61="PBA",1-'Parametros'!I$7,1)) | N61: =SUMPRODUCT($AK61:$AR61,$AK$13:$AR$13)*IF($E61="CABA",'Parametros'!J$7,IF($E61="PBA",1-'Parametros'!J$7,1)) | O61: =SUMPRODUCT($AK61:$AR61,$AK$14:$AR$14)*IF($E61="CABA",'Parametros'!K$7,IF($E61="PBA",1-'Parametros'!K$7,1)) | AO61: 2
A62: Neumático macizo — Ø350 × 49 de ancho | B62: u | C62: Componente comprado | D62: Ruedar | E62: Todos | F62: =SUMPRODUCT($AK62:$AR62,$AK$5:$AR$5)*IF($E62="CABA",'Parametros'!B$7,IF($E62="PBA",1-'Parametros'!B$7,1)) | G62: =SUMPRODUCT($AK62:$AR62,$AK$6:$AR$6)*IF($E62="CABA",'Parametros'!C$7,IF($E62="PBA",1-'Parametros'!C$7,1)) | H62: =SUMPRODUCT($AK62:$AR62,$AK$7:$AR$7)*IF($E62="CABA",'Parametros'!D$7,IF($E62="PBA",1-'Parametros'!D$7,1)) | I62: =SUMPRODUCT($AK62:$AR62,$AK$8:$AR$8)*IF($E62="CABA",'Parametros'!E$7,IF($E62="PBA",1-'Parametros'!E$7,1)) | J62: =SUMPRODUCT($AK62:$AR62,$AK$9:$AR$9)*IF($E62="CABA",'Parametros'!F$7,IF($E62="PBA",1-'Parametros'!F$7,1)) | K62: =SUMPRODUCT($AK62:$AR62,$AK$10:$AR$10)*IF($E62="CABA",'Parametros'!G$7,IF($E62="PBA",1-'Parametros'!G$7,1)) | L62: =SUMPRODUCT($AK62:$AR62,$AK$11:$AR$11)*IF($E62="CABA",'Parametros'!H$7,IF($E62="PBA",1-'Parametros'!H$7,1)) | M62: =SUMPRODUCT($AK62:$AR62,$AK$12:$AR$12)*IF($E62="CABA",'Parametros'!I$7,IF($E62="PBA",1-'Parametros'!I$7,1)) | N62: =SUMPRODUCT($AK62:$AR62,$AK$13:$AR$13)*IF($E62="CABA",'Parametros'!J$7,IF($E62="PBA",1-'Parametros'!J$7,1)) | O62: =SUMPRODUCT($AK62:$AR62,$AK$14:$AR$14)*IF($E62="CABA",'Parametros'!K$7,IF($E62="PBA",1-'Parametros'!K$7,1)) | AP62: 2 | AQ62: 2
A63: Neumático macizo — Ø400 × 76 de ancho | B63: u | C63: Componente comprado | D63: Ruedar | E63: Todos | F63: =SUMPRODUCT($AK63:$AR63,$AK$5:$AR$5)*IF($E63="CABA",'Parametros'!B$7,IF($E63="PBA",1-'Parametros'!B$7,1)) | G63: =SUMPRODUCT($AK63:$AR63,$AK$6:$AR$6)*IF($E63="CABA",'Parametros'!C$7,IF($E63="PBA",1-'Parametros'!C$7,1)) | H63: =SUMPRODUCT($AK63:$AR63,$AK$7:$AR$7)*IF($E63="CABA",'Parametros'!D$7,IF($E63="PBA",1-'Parametros'!D$7,1)) | I63: =SUMPRODUCT($AK63:$AR63,$AK$8:$AR$8)*IF($E63="CABA",'Parametros'!E$7,IF($E63="PBA",1-'Parametros'!E$7,1)) | J63: =SUMPRODUCT($AK63:$AR63,$AK$9:$AR$9)*IF($E63="CABA",'Parametros'!F$7,IF($E63="PBA",1-'Parametros'!F$7,1)) | K63: =SUMPRODUCT($AK63:$AR63,$AK$10:$AR$10)*IF($E63="CABA",'Parametros'!G$7,IF($E63="PBA",1-'Parametros'!G$7,1)) | L63: =SUMPRODUCT($AK63:$AR63,$AK$11:$AR$11)*IF($E63="CABA",'Parametros'!H$7,IF($E63="PBA",1-'Parametros'!H$7,1)) | M63: =SUMPRODUCT($AK63:$AR63,$AK$12:$AR$12)*IF($E63="CABA",'Parametros'!I$7,IF($E63="PBA",1-'Parametros'!I$7,1)) | N63: =SUMPRODUCT($AK63:$AR63,$AK$13:$AR$13)*IF($E63="CABA",'Parametros'!J$7,IF($E63="PBA",1-'Parametros'!J$7,1)) | O63: =SUMPRODUCT($AK63:$AR63,$AK$14:$AR$14)*IF($E63="CABA",'Parametros'!K$7,IF($E63="PBA",1-'Parametros'!K$7,1)) | AR63: 2
A64: Racor de manguera — 19,4 × 18,8 × 18,8 | B64: u | C64: Componente comprado | D64: Yukon / MatafuegosYa S.R.L. | E64: Todos | F64: =SUMPRODUCT($AK64:$AR64,$AK$5:$AR$5)*IF($E64="CABA",'Parametros'!B$7,IF($E64="PBA",1-'Parametros'!B$7,1)) | G64: =SUMPRODUCT($AK64:$AR64,$AK$6:$AR$6)*IF($E64="CABA",'Parametros'!C$7,IF($E64="PBA",1-'Parametros'!C$7,1)) | H64: =SUMPRODUCT($AK64:$AR64,$AK$7:$AR$7)*IF($E64="CABA",'Parametros'!D$7,IF($E64="PBA",1-'Parametros'!D$7,1)) | I64: =SUMPRODUCT($AK64:$AR64,$AK$8:$AR$8)*IF($E64="CABA",'Parametros'!E$7,IF($E64="PBA",1-'Parametros'!E$7,1)) | J64: =SUMPRODUCT($AK64:$AR64,$AK$9:$AR$9)*IF($E64="CABA",'Parametros'!F$7,IF($E64="PBA",1-'Parametros'!F$7,1)) | K64: =SUMPRODUCT($AK64:$AR64,$AK$10:$AR$10)*IF($E64="CABA",'Parametros'!G$7,IF($E64="PBA",1-'Parametros'!G$7,1)) | L64: =SUMPRODUCT($AK64:$AR64,$AK$11:$AR$11)*IF($E64="CABA",'Parametros'!H$7,IF($E64="PBA",1-'Parametros'!H$7,1)) | M64: =SUMPRODUCT($AK64:$AR64,$AK$12:$AR$12)*IF($E64="CABA",'Parametros'!I$7,IF($E64="PBA",1-'Parametros'!I$7,1)) | N64: =SUMPRODUCT($AK64:$AR64,$AK$13:$AR$13)*IF($E64="CABA",'Parametros'!J$7,IF($E64="PBA",1-'Parametros'!J$7,1)) | O64: =SUMPRODUCT($AK64:$AR64,$AK$14:$AR$14)*IF($E64="CABA",'Parametros'!K$7,IF($E64="PBA",1-'Parametros'!K$7,1)) | AL64: 1 | AM64: 1 | AN64: 1
A65: Racor de manguera — 24 × 24 × 16 | B65: u | C65: Componente comprado | D65: Yukon / MatafuegosYa S.R.L. | E65: Todos | F65: =SUMPRODUCT($AK65:$AR65,$AK$5:$AR$5)*IF($E65="CABA",'Parametros'!B$7,IF($E65="PBA",1-'Parametros'!B$7,1)) | G65: =SUMPRODUCT($AK65:$AR65,$AK$6:$AR$6)*IF($E65="CABA",'Parametros'!C$7,IF($E65="PBA",1-'Parametros'!C$7,1)) | H65: =SUMPRODUCT($AK65:$AR65,$AK$7:$AR$7)*IF($E65="CABA",'Parametros'!D$7,IF($E65="PBA",1-'Parametros'!D$7,1)) | I65: =SUMPRODUCT($AK65:$AR65,$AK$8:$AR$8)*IF($E65="CABA",'Parametros'!E$7,IF($E65="PBA",1-'Parametros'!E$7,1)) | J65: =SUMPRODUCT($AK65:$AR65,$AK$9:$AR$9)*IF($E65="CABA",'Parametros'!F$7,IF($E65="PBA",1-'Parametros'!F$7,1)) | K65: =SUMPRODUCT($AK65:$AR65,$AK$10:$AR$10)*IF($E65="CABA",'Parametros'!G$7,IF($E65="PBA",1-'Parametros'!G$7,1)) | L65: =SUMPRODUCT($AK65:$AR65,$AK$11:$AR$11)*IF($E65="CABA",'Parametros'!H$7,IF($E65="PBA",1-'Parametros'!H$7,1)) | M65: =SUMPRODUCT($AK65:$AR65,$AK$12:$AR$12)*IF($E65="CABA",'Parametros'!I$7,IF($E65="PBA",1-'Parametros'!I$7,1)) | N65: =SUMPRODUCT($AK65:$AR65,$AK$13:$AR$13)*IF($E65="CABA",'Parametros'!J$7,IF($E65="PBA",1-'Parametros'!J$7,1)) | O65: =SUMPRODUCT($AK65:$AR65,$AK$14:$AR$14)*IF($E65="CABA",'Parametros'!K$7,IF($E65="PBA",1-'Parametros'!K$7,1)) | AO65: 1 | AP65: 1 | AQ65: 1 | AR65: 1
A66: Suncho portatobera — 137,3 × 127 × 14,4 | B66: u | C66: Componente comprado | D66: Yukon / MatafuegosYa S.R.L. | E66: Todos | F66: =SUMPRODUCT($AK66:$AR66,$AK$5:$AR$5)*IF($E66="CABA",'Parametros'!B$7,IF($E66="PBA",1-'Parametros'!B$7,1)) | G66: =SUMPRODUCT($AK66:$AR66,$AK$6:$AR$6)*IF($E66="CABA",'Parametros'!C$7,IF($E66="PBA",1-'Parametros'!C$7,1)) | H66: =SUMPRODUCT($AK66:$AR66,$AK$7:$AR$7)*IF($E66="CABA",'Parametros'!D$7,IF($E66="PBA",1-'Parametros'!D$7,1)) | I66: =SUMPRODUCT($AK66:$AR66,$AK$8:$AR$8)*IF($E66="CABA",'Parametros'!E$7,IF($E66="PBA",1-'Parametros'!E$7,1)) | J66: =SUMPRODUCT($AK66:$AR66,$AK$9:$AR$9)*IF($E66="CABA",'Parametros'!F$7,IF($E66="PBA",1-'Parametros'!F$7,1)) | K66: =SUMPRODUCT($AK66:$AR66,$AK$10:$AR$10)*IF($E66="CABA",'Parametros'!G$7,IF($E66="PBA",1-'Parametros'!G$7,1)) | L66: =SUMPRODUCT($AK66:$AR66,$AK$11:$AR$11)*IF($E66="CABA",'Parametros'!H$7,IF($E66="PBA",1-'Parametros'!H$7,1)) | M66: =SUMPRODUCT($AK66:$AR66,$AK$12:$AR$12)*IF($E66="CABA",'Parametros'!I$7,IF($E66="PBA",1-'Parametros'!I$7,1)) | N66: =SUMPRODUCT($AK66:$AR66,$AK$13:$AR$13)*IF($E66="CABA",'Parametros'!J$7,IF($E66="PBA",1-'Parametros'!J$7,1)) | O66: =SUMPRODUCT($AK66:$AR66,$AK$14:$AR$14)*IF($E66="CABA",'Parametros'!K$7,IF($E66="PBA",1-'Parametros'!K$7,1)) | AL66: 1
A67: Suncho portatobera — 166,3 × 156 × 14,4 | B67: u | C67: Componente comprado | D67: Yukon / MatafuegosYa S.R.L. | E67: Todos | F67: =SUMPRODUCT($AK67:$AR67,$AK$5:$AR$5)*IF($E67="CABA",'Parametros'!B$7,IF($E67="PBA",1-'Parametros'!B$7,1)) | G67: =SUMPRODUCT($AK67:$AR67,$AK$6:$AR$6)*IF($E67="CABA",'Parametros'!C$7,IF($E67="PBA",1-'Parametros'!C$7,1)) | H67: =SUMPRODUCT($AK67:$AR67,$AK$7:$AR$7)*IF($E67="CABA",'Parametros'!D$7,IF($E67="PBA",1-'Parametros'!D$7,1)) | I67: =SUMPRODUCT($AK67:$AR67,$AK$8:$AR$8)*IF($E67="CABA",'Parametros'!E$7,IF($E67="PBA",1-'Parametros'!E$7,1)) | J67: =SUMPRODUCT($AK67:$AR67,$AK$9:$AR$9)*IF($E67="CABA",'Parametros'!F$7,IF($E67="PBA",1-'Parametros'!F$7,1)) | K67: =SUMPRODUCT($AK67:$AR67,$AK$10:$AR$10)*IF($E67="CABA",'Parametros'!G$7,IF($E67="PBA",1-'Parametros'!G$7,1)) | L67: =SUMPRODUCT($AK67:$AR67,$AK$11:$AR$11)*IF($E67="CABA",'Parametros'!H$7,IF($E67="PBA",1-'Parametros'!H$7,1)) | M67: =SUMPRODUCT($AK67:$AR67,$AK$12:$AR$12)*IF($E67="CABA",'Parametros'!I$7,IF($E67="PBA",1-'Parametros'!I$7,1)) | N67: =SUMPRODUCT($AK67:$AR67,$AK$13:$AR$13)*IF($E67="CABA",'Parametros'!J$7,IF($E67="PBA",1-'Parametros'!J$7,1)) | O67: =SUMPRODUCT($AK67:$AR67,$AK$14:$AR$14)*IF($E67="CABA",'Parametros'!K$7,IF($E67="PBA",1-'Parametros'!K$7,1)) | AM67: 1
A68: Suncho portatobera — 194,8 × 184,5 × 14,4 | B68: u | C68: Componente comprado | D68: Yukon / MatafuegosYa S.R.L. | E68: Todos | F68: =SUMPRODUCT($AK68:$AR68,$AK$5:$AR$5)*IF($E68="CABA",'Parametros'!B$7,IF($E68="PBA",1-'Parametros'!B$7,1)) | G68: =SUMPRODUCT($AK68:$AR68,$AK$6:$AR$6)*IF($E68="CABA",'Parametros'!C$7,IF($E68="PBA",1-'Parametros'!C$7,1)) | H68: =SUMPRODUCT($AK68:$AR68,$AK$7:$AR$7)*IF($E68="CABA",'Parametros'!D$7,IF($E68="PBA",1-'Parametros'!D$7,1)) | I68: =SUMPRODUCT($AK68:$AR68,$AK$8:$AR$8)*IF($E68="CABA",'Parametros'!E$7,IF($E68="PBA",1-'Parametros'!E$7,1)) | J68: =SUMPRODUCT($AK68:$AR68,$AK$9:$AR$9)*IF($E68="CABA",'Parametros'!F$7,IF($E68="PBA",1-'Parametros'!F$7,1)) | K68: =SUMPRODUCT($AK68:$AR68,$AK$10:$AR$10)*IF($E68="CABA",'Parametros'!G$7,IF($E68="PBA",1-'Parametros'!G$7,1)) | L68: =SUMPRODUCT($AK68:$AR68,$AK$11:$AR$11)*IF($E68="CABA",'Parametros'!H$7,IF($E68="PBA",1-'Parametros'!H$7,1)) | M68: =SUMPRODUCT($AK68:$AR68,$AK$12:$AR$12)*IF($E68="CABA",'Parametros'!I$7,IF($E68="PBA",1-'Parametros'!I$7,1)) | N68: =SUMPRODUCT($AK68:$AR68,$AK$13:$AR$13)*IF($E68="CABA",'Parametros'!J$7,IF($E68="PBA",1-'Parametros'!J$7,1)) | O68: =SUMPRODUCT($AK68:$AR68,$AK$14:$AR$14)*IF($E68="CABA",'Parametros'!K$7,IF($E68="PBA",1-'Parametros'!K$7,1)) | AN68: 1
A69: Tobera campana — 200 × 68 × 68 | B69: u | C69: Componente comprado | D69: Yukon / MatafuegosYa S.R.L. | E69: Todos | F69: =SUMPRODUCT($AK69:$AR69,$AK$5:$AR$5)*IF($E69="CABA",'Parametros'!B$7,IF($E69="PBA",1-'Parametros'!B$7,1)) | G69: =SUMPRODUCT($AK69:$AR69,$AK$6:$AR$6)*IF($E69="CABA",'Parametros'!C$7,IF($E69="PBA",1-'Parametros'!C$7,1)) | H69: =SUMPRODUCT($AK69:$AR69,$AK$7:$AR$7)*IF($E69="CABA",'Parametros'!D$7,IF($E69="PBA",1-'Parametros'!D$7,1)) | I69: =SUMPRODUCT($AK69:$AR69,$AK$8:$AR$8)*IF($E69="CABA",'Parametros'!E$7,IF($E69="PBA",1-'Parametros'!E$7,1)) | J69: =SUMPRODUCT($AK69:$AR69,$AK$9:$AR$9)*IF($E69="CABA",'Parametros'!F$7,IF($E69="PBA",1-'Parametros'!F$7,1)) | K69: =SUMPRODUCT($AK69:$AR69,$AK$10:$AR$10)*IF($E69="CABA",'Parametros'!G$7,IF($E69="PBA",1-'Parametros'!G$7,1)) | L69: =SUMPRODUCT($AK69:$AR69,$AK$11:$AR$11)*IF($E69="CABA",'Parametros'!H$7,IF($E69="PBA",1-'Parametros'!H$7,1)) | M69: =SUMPRODUCT($AK69:$AR69,$AK$12:$AR$12)*IF($E69="CABA",'Parametros'!I$7,IF($E69="PBA",1-'Parametros'!I$7,1)) | N69: =SUMPRODUCT($AK69:$AR69,$AK$13:$AR$13)*IF($E69="CABA",'Parametros'!J$7,IF($E69="PBA",1-'Parametros'!J$7,1)) | O69: =SUMPRODUCT($AK69:$AR69,$AK$14:$AR$14)*IF($E69="CABA",'Parametros'!K$7,IF($E69="PBA",1-'Parametros'!K$7,1)) | AO69: 1 | AP69: 1 | AQ69: 1 | AR69: 1
A70: Tobera con portatobera — 73,5 × 19,9 × 19,9 | B70: u | C70: Componente comprado | D70: Yukon / MatafuegosYa S.R.L. | E70: Todos | F70: =SUMPRODUCT($AK70:$AR70,$AK$5:$AR$5)*IF($E70="CABA",'Parametros'!B$7,IF($E70="PBA",1-'Parametros'!B$7,1)) | G70: =SUMPRODUCT($AK70:$AR70,$AK$6:$AR$6)*IF($E70="CABA",'Parametros'!C$7,IF($E70="PBA",1-'Parametros'!C$7,1)) | H70: =SUMPRODUCT($AK70:$AR70,$AK$7:$AR$7)*IF($E70="CABA",'Parametros'!D$7,IF($E70="PBA",1-'Parametros'!D$7,1)) | I70: =SUMPRODUCT($AK70:$AR70,$AK$8:$AR$8)*IF($E70="CABA",'Parametros'!E$7,IF($E70="PBA",1-'Parametros'!E$7,1)) | J70: =SUMPRODUCT($AK70:$AR70,$AK$9:$AR$9)*IF($E70="CABA",'Parametros'!F$7,IF($E70="PBA",1-'Parametros'!F$7,1)) | K70: =SUMPRODUCT($AK70:$AR70,$AK$10:$AR$10)*IF($E70="CABA",'Parametros'!G$7,IF($E70="PBA",1-'Parametros'!G$7,1)) | L70: =SUMPRODUCT($AK70:$AR70,$AK$11:$AR$11)*IF($E70="CABA",'Parametros'!H$7,IF($E70="PBA",1-'Parametros'!H$7,1)) | M70: =SUMPRODUCT($AK70:$AR70,$AK$12:$AR$12)*IF($E70="CABA",'Parametros'!I$7,IF($E70="PBA",1-'Parametros'!I$7,1)) | N70: =SUMPRODUCT($AK70:$AR70,$AK$13:$AR$13)*IF($E70="CABA",'Parametros'!J$7,IF($E70="PBA",1-'Parametros'!J$7,1)) | O70: =SUMPRODUCT($AK70:$AR70,$AK$14:$AR$14)*IF($E70="CABA",'Parametros'!K$7,IF($E70="PBA",1-'Parametros'!K$7,1)) | AL70: 1 | AM70: 1 | AN70: 1
A71: Tobera — 12 × 12 × 10 | B71: u | C71: Componente comprado | D71: Yukon / MatafuegosYa S.R.L. | E71: Todos | F71: =SUMPRODUCT($AK71:$AR71,$AK$5:$AR$5)*IF($E71="CABA",'Parametros'!B$7,IF($E71="PBA",1-'Parametros'!B$7,1)) | G71: =SUMPRODUCT($AK71:$AR71,$AK$6:$AR$6)*IF($E71="CABA",'Parametros'!C$7,IF($E71="PBA",1-'Parametros'!C$7,1)) | H71: =SUMPRODUCT($AK71:$AR71,$AK$7:$AR$7)*IF($E71="CABA",'Parametros'!D$7,IF($E71="PBA",1-'Parametros'!D$7,1)) | I71: =SUMPRODUCT($AK71:$AR71,$AK$8:$AR$8)*IF($E71="CABA",'Parametros'!E$7,IF($E71="PBA",1-'Parametros'!E$7,1)) | J71: =SUMPRODUCT($AK71:$AR71,$AK$9:$AR$9)*IF($E71="CABA",'Parametros'!F$7,IF($E71="PBA",1-'Parametros'!F$7,1)) | K71: =SUMPRODUCT($AK71:$AR71,$AK$10:$AR$10)*IF($E71="CABA",'Parametros'!G$7,IF($E71="PBA",1-'Parametros'!G$7,1)) | L71: =SUMPRODUCT($AK71:$AR71,$AK$11:$AR$11)*IF($E71="CABA",'Parametros'!H$7,IF($E71="PBA",1-'Parametros'!H$7,1)) | M71: =SUMPRODUCT($AK71:$AR71,$AK$12:$AR$12)*IF($E71="CABA",'Parametros'!I$7,IF($E71="PBA",1-'Parametros'!I$7,1)) | N71: =SUMPRODUCT($AK71:$AR71,$AK$13:$AR$13)*IF($E71="CABA",'Parametros'!J$7,IF($E71="PBA",1-'Parametros'!J$7,1)) | O71: =SUMPRODUCT($AK71:$AR71,$AK$14:$AR$14)*IF($E71="CABA",'Parametros'!K$7,IF($E71="PBA",1-'Parametros'!K$7,1)) | AK71: 1
A72: Válvula HZ armada M-22 1 kg c/tubo de pesca plástico | B72: u | C72: Componente comprado | D72: Polvex S.R.L. / Sancibrao | E72: Todos | F72: =SUMPRODUCT($AK72:$AR72,$AK$5:$AR$5)*IF($E72="CABA",'Parametros'!B$7,IF($E72="PBA",1-'Parametros'!B$7,1)) | G72: =SUMPRODUCT($AK72:$AR72,$AK$6:$AR$6)*IF($E72="CABA",'Parametros'!C$7,IF($E72="PBA",1-'Parametros'!C$7,1)) | H72: =SUMPRODUCT($AK72:$AR72,$AK$7:$AR$7)*IF($E72="CABA",'Parametros'!D$7,IF($E72="PBA",1-'Parametros'!D$7,1)) | I72: =SUMPRODUCT($AK72:$AR72,$AK$8:$AR$8)*IF($E72="CABA",'Parametros'!E$7,IF($E72="PBA",1-'Parametros'!E$7,1)) | J72: =SUMPRODUCT($AK72:$AR72,$AK$9:$AR$9)*IF($E72="CABA",'Parametros'!F$7,IF($E72="PBA",1-'Parametros'!F$7,1)) | K72: =SUMPRODUCT($AK72:$AR72,$AK$10:$AR$10)*IF($E72="CABA",'Parametros'!G$7,IF($E72="PBA",1-'Parametros'!G$7,1)) | L72: =SUMPRODUCT($AK72:$AR72,$AK$11:$AR$11)*IF($E72="CABA",'Parametros'!H$7,IF($E72="PBA",1-'Parametros'!H$7,1)) | M72: =SUMPRODUCT($AK72:$AR72,$AK$12:$AR$12)*IF($E72="CABA",'Parametros'!I$7,IF($E72="PBA",1-'Parametros'!I$7,1)) | N72: =SUMPRODUCT($AK72:$AR72,$AK$13:$AR$13)*IF($E72="CABA",'Parametros'!J$7,IF($E72="PBA",1-'Parametros'!J$7,1)) | O72: =SUMPRODUCT($AK72:$AR72,$AK$14:$AR$14)*IF($E72="CABA",'Parametros'!K$7,IF($E72="PBA",1-'Parametros'!K$7,1)) | AK72: 1
A73: Válvula HZ armada M-30 c/resorte y tubo 7/8 | B73: u | C73: Componente comprado | D73: Polvex S.R.L. / Sancibrao | E73: Todos | F73: =SUMPRODUCT($AK73:$AR73,$AK$5:$AR$5)*IF($E73="CABA",'Parametros'!B$7,IF($E73="PBA",1-'Parametros'!B$7,1)) | G73: =SUMPRODUCT($AK73:$AR73,$AK$6:$AR$6)*IF($E73="CABA",'Parametros'!C$7,IF($E73="PBA",1-'Parametros'!C$7,1)) | H73: =SUMPRODUCT($AK73:$AR73,$AK$7:$AR$7)*IF($E73="CABA",'Parametros'!D$7,IF($E73="PBA",1-'Parametros'!D$7,1)) | I73: =SUMPRODUCT($AK73:$AR73,$AK$8:$AR$8)*IF($E73="CABA",'Parametros'!E$7,IF($E73="PBA",1-'Parametros'!E$7,1)) | J73: =SUMPRODUCT($AK73:$AR73,$AK$9:$AR$9)*IF($E73="CABA",'Parametros'!F$7,IF($E73="PBA",1-'Parametros'!F$7,1)) | K73: =SUMPRODUCT($AK73:$AR73,$AK$10:$AR$10)*IF($E73="CABA",'Parametros'!G$7,IF($E73="PBA",1-'Parametros'!G$7,1)) | L73: =SUMPRODUCT($AK73:$AR73,$AK$11:$AR$11)*IF($E73="CABA",'Parametros'!H$7,IF($E73="PBA",1-'Parametros'!H$7,1)) | M73: =SUMPRODUCT($AK73:$AR73,$AK$12:$AR$12)*IF($E73="CABA",'Parametros'!I$7,IF($E73="PBA",1-'Parametros'!I$7,1)) | N73: =SUMPRODUCT($AK73:$AR73,$AK$13:$AR$13)*IF($E73="CABA",'Parametros'!J$7,IF($E73="PBA",1-'Parametros'!J$7,1)) | O73: =SUMPRODUCT($AK73:$AR73,$AK$14:$AR$14)*IF($E73="CABA",'Parametros'!K$7,IF($E73="PBA",1-'Parametros'!K$7,1)) | AL73: 1 | AM73: 1 | AN73: 1
A74: Válvula HZ armada de carro 25 kg c/traba, manija y resorte | B74: u | C74: Componente comprado | D74: Polvex S.R.L. / Sancibrao | E74: Todos | F74: =SUMPRODUCT($AK74:$AR74,$AK$5:$AR$5)*IF($E74="CABA",'Parametros'!B$7,IF($E74="PBA",1-'Parametros'!B$7,1)) | G74: =SUMPRODUCT($AK74:$AR74,$AK$6:$AR$6)*IF($E74="CABA",'Parametros'!C$7,IF($E74="PBA",1-'Parametros'!C$7,1)) | H74: =SUMPRODUCT($AK74:$AR74,$AK$7:$AR$7)*IF($E74="CABA",'Parametros'!D$7,IF($E74="PBA",1-'Parametros'!D$7,1)) | I74: =SUMPRODUCT($AK74:$AR74,$AK$8:$AR$8)*IF($E74="CABA",'Parametros'!E$7,IF($E74="PBA",1-'Parametros'!E$7,1)) | J74: =SUMPRODUCT($AK74:$AR74,$AK$9:$AR$9)*IF($E74="CABA",'Parametros'!F$7,IF($E74="PBA",1-'Parametros'!F$7,1)) | K74: =SUMPRODUCT($AK74:$AR74,$AK$10:$AR$10)*IF($E74="CABA",'Parametros'!G$7,IF($E74="PBA",1-'Parametros'!G$7,1)) | L74: =SUMPRODUCT($AK74:$AR74,$AK$11:$AR$11)*IF($E74="CABA",'Parametros'!H$7,IF($E74="PBA",1-'Parametros'!H$7,1)) | M74: =SUMPRODUCT($AK74:$AR74,$AK$12:$AR$12)*IF($E74="CABA",'Parametros'!I$7,IF($E74="PBA",1-'Parametros'!I$7,1)) | N74: =SUMPRODUCT($AK74:$AR74,$AK$13:$AR$13)*IF($E74="CABA",'Parametros'!J$7,IF($E74="PBA",1-'Parametros'!J$7,1)) | O74: =SUMPRODUCT($AK74:$AR74,$AK$14:$AR$14)*IF($E74="CABA",'Parametros'!K$7,IF($E74="PBA",1-'Parametros'!K$7,1)) | AO74: 1
A75: Válvula HZ armada de carro 50-70-100 kg | B75: u | C75: Componente comprado | D75: Polvex S.R.L. / Sancibrao | E75: Todos | F75: =SUMPRODUCT($AK75:$AR75,$AK$5:$AR$5)*IF($E75="CABA",'Parametros'!B$7,IF($E75="PBA",1-'Parametros'!B$7,1)) | G75: =SUMPRODUCT($AK75:$AR75,$AK$6:$AR$6)*IF($E75="CABA",'Parametros'!C$7,IF($E75="PBA",1-'Parametros'!C$7,1)) | H75: =SUMPRODUCT($AK75:$AR75,$AK$7:$AR$7)*IF($E75="CABA",'Parametros'!D$7,IF($E75="PBA",1-'Parametros'!D$7,1)) | I75: =SUMPRODUCT($AK75:$AR75,$AK$8:$AR$8)*IF($E75="CABA",'Parametros'!E$7,IF($E75="PBA",1-'Parametros'!E$7,1)) | J75: =SUMPRODUCT($AK75:$AR75,$AK$9:$AR$9)*IF($E75="CABA",'Parametros'!F$7,IF($E75="PBA",1-'Parametros'!F$7,1)) | K75: =SUMPRODUCT($AK75:$AR75,$AK$10:$AR$10)*IF($E75="CABA",'Parametros'!G$7,IF($E75="PBA",1-'Parametros'!G$7,1)) | L75: =SUMPRODUCT($AK75:$AR75,$AK$11:$AR$11)*IF($E75="CABA",'Parametros'!H$7,IF($E75="PBA",1-'Parametros'!H$7,1)) | M75: =SUMPRODUCT($AK75:$AR75,$AK$12:$AR$12)*IF($E75="CABA",'Parametros'!I$7,IF($E75="PBA",1-'Parametros'!I$7,1)) | N75: =SUMPRODUCT($AK75:$AR75,$AK$13:$AR$13)*IF($E75="CABA",'Parametros'!J$7,IF($E75="PBA",1-'Parametros'!J$7,1)) | O75: =SUMPRODUCT($AK75:$AR75,$AK$14:$AR$14)*IF($E75="CABA",'Parametros'!K$7,IF($E75="PBA",1-'Parametros'!K$7,1)) | AP75: 1 | AQ75: 1 | AR75: 1
A76: Válvula esférica — 110 × 60 × 40 | B76: u | C76: Componente comprado | D76: Yukon / MatafuegosYa S.R.L. | E76: Todos | F76: =SUMPRODUCT($AK76:$AR76,$AK$5:$AR$5)*IF($E76="CABA",'Parametros'!B$7,IF($E76="PBA",1-'Parametros'!B$7,1)) | G76: =SUMPRODUCT($AK76:$AR76,$AK$6:$AR$6)*IF($E76="CABA",'Parametros'!C$7,IF($E76="PBA",1-'Parametros'!C$7,1)) | H76: =SUMPRODUCT($AK76:$AR76,$AK$7:$AR$7)*IF($E76="CABA",'Parametros'!D$7,IF($E76="PBA",1-'Parametros'!D$7,1)) | I76: =SUMPRODUCT($AK76:$AR76,$AK$8:$AR$8)*IF($E76="CABA",'Parametros'!E$7,IF($E76="PBA",1-'Parametros'!E$7,1)) | J76: =SUMPRODUCT($AK76:$AR76,$AK$9:$AR$9)*IF($E76="CABA",'Parametros'!F$7,IF($E76="PBA",1-'Parametros'!F$7,1)) | K76: =SUMPRODUCT($AK76:$AR76,$AK$10:$AR$10)*IF($E76="CABA",'Parametros'!G$7,IF($E76="PBA",1-'Parametros'!G$7,1)) | L76: =SUMPRODUCT($AK76:$AR76,$AK$11:$AR$11)*IF($E76="CABA",'Parametros'!H$7,IF($E76="PBA",1-'Parametros'!H$7,1)) | M76: =SUMPRODUCT($AK76:$AR76,$AK$12:$AR$12)*IF($E76="CABA",'Parametros'!I$7,IF($E76="PBA",1-'Parametros'!I$7,1)) | N76: =SUMPRODUCT($AK76:$AR76,$AK$13:$AR$13)*IF($E76="CABA",'Parametros'!J$7,IF($E76="PBA",1-'Parametros'!J$7,1)) | O76: =SUMPRODUCT($AK76:$AR76,$AK$14:$AR$14)*IF($E76="CABA",'Parametros'!K$7,IF($E76="PBA",1-'Parametros'!K$7,1)) | AO76: 1 | AP76: 1 | AQ76: 1 | AR76: 1
A77: Alambre MAG ER70S-6 Ø0,9 (AWS A5.18) | B77: kg | C77: Consumible de proceso | D77: Conarco (ESAB Argentina) | E77: Todos | F77: =SUMPRODUCT($AK77:$AR77,$AK$5:$AR$5)*IF($E77="CABA",'Parametros'!B$7,IF($E77="PBA",1-'Parametros'!B$7,1)) | G77: =SUMPRODUCT($AK77:$AR77,$AK$6:$AR$6)*IF($E77="CABA",'Parametros'!C$7,IF($E77="PBA",1-'Parametros'!C$7,1)) | H77: =SUMPRODUCT($AK77:$AR77,$AK$7:$AR$7)*IF($E77="CABA",'Parametros'!D$7,IF($E77="PBA",1-'Parametros'!D$7,1)) | I77: =SUMPRODUCT($AK77:$AR77,$AK$8:$AR$8)*IF($E77="CABA",'Parametros'!E$7,IF($E77="PBA",1-'Parametros'!E$7,1)) | J77: =SUMPRODUCT($AK77:$AR77,$AK$9:$AR$9)*IF($E77="CABA",'Parametros'!F$7,IF($E77="PBA",1-'Parametros'!F$7,1)) | K77: =SUMPRODUCT($AK77:$AR77,$AK$10:$AR$10)*IF($E77="CABA",'Parametros'!G$7,IF($E77="PBA",1-'Parametros'!G$7,1)) | L77: =SUMPRODUCT($AK77:$AR77,$AK$11:$AR$11)*IF($E77="CABA",'Parametros'!H$7,IF($E77="PBA",1-'Parametros'!H$7,1)) | M77: =SUMPRODUCT($AK77:$AR77,$AK$12:$AR$12)*IF($E77="CABA",'Parametros'!I$7,IF($E77="PBA",1-'Parametros'!I$7,1)) | N77: =SUMPRODUCT($AK77:$AR77,$AK$13:$AR$13)*IF($E77="CABA",'Parametros'!J$7,IF($E77="PBA",1-'Parametros'!J$7,1)) | O77: =SUMPRODUCT($AK77:$AR77,$AK$14:$AR$14)*IF($E77="CABA",'Parametros'!K$7,IF($E77="PBA",1-'Parametros'!K$7,1)) | AK77: 0.0146 | AL77: 0.0292 | AM77: 0.0551 | AN77: 0.0985
A78: Alambre MAG ER70S-6 Ø1,2 (AWS A5.18) | B78: kg | C78: Consumible de proceso | D78: Conarco (ESAB Argentina) | E78: Todos | F78: =SUMPRODUCT($AK78:$AR78,$AK$5:$AR$5)*IF($E78="CABA",'Parametros'!B$7,IF($E78="PBA",1-'Parametros'!B$7,1)) | G78: =SUMPRODUCT($AK78:$AR78,$AK$6:$AR$6)*IF($E78="CABA",'Parametros'!C$7,IF($E78="PBA",1-'Parametros'!C$7,1)) | H78: =SUMPRODUCT($AK78:$AR78,$AK$7:$AR$7)*IF($E78="CABA",'Parametros'!D$7,IF($E78="PBA",1-'Parametros'!D$7,1)) | I78: =SUMPRODUCT($AK78:$AR78,$AK$8:$AR$8)*IF($E78="CABA",'Parametros'!E$7,IF($E78="PBA",1-'Parametros'!E$7,1)) | J78: =SUMPRODUCT($AK78:$AR78,$AK$9:$AR$9)*IF($E78="CABA",'Parametros'!F$7,IF($E78="PBA",1-'Parametros'!F$7,1)) | K78: =SUMPRODUCT($AK78:$AR78,$AK$10:$AR$10)*IF($E78="CABA",'Parametros'!G$7,IF($E78="PBA",1-'Parametros'!G$7,1)) | L78: =SUMPRODUCT($AK78:$AR78,$AK$11:$AR$11)*IF($E78="CABA",'Parametros'!H$7,IF($E78="PBA",1-'Parametros'!H$7,1)) | M78: =SUMPRODUCT($AK78:$AR78,$AK$12:$AR$12)*IF($E78="CABA",'Parametros'!I$7,IF($E78="PBA",1-'Parametros'!I$7,1)) | N78: =SUMPRODUCT($AK78:$AR78,$AK$13:$AR$13)*IF($E78="CABA",'Parametros'!J$7,IF($E78="PBA",1-'Parametros'!J$7,1)) | O78: =SUMPRODUCT($AK78:$AR78,$AK$14:$AR$14)*IF($E78="CABA",'Parametros'!K$7,IF($E78="PBA",1-'Parametros'!K$7,1)) | AO78: 0.3431 | AP78: 0.4262 | AQ78: 1.0749 | AR78: 1.0956
A79: Gas de protección MAG Arcal 21 / ARCAL Speed (Ar + 8 % CO₂, M20) | B79: L | C79: Consumible de proceso | D79: Air Liquide Argentina - sucursal Piñeyro | E79: Todos | F79: =SUMPRODUCT($AK79:$AR79,$AK$5:$AR$5)*IF($E79="CABA",'Parametros'!B$7,IF($E79="PBA",1-'Parametros'!B$7,1)) | G79: =SUMPRODUCT($AK79:$AR79,$AK$6:$AR$6)*IF($E79="CABA",'Parametros'!C$7,IF($E79="PBA",1-'Parametros'!C$7,1)) | H79: =SUMPRODUCT($AK79:$AR79,$AK$7:$AR$7)*IF($E79="CABA",'Parametros'!D$7,IF($E79="PBA",1-'Parametros'!D$7,1)) | I79: =SUMPRODUCT($AK79:$AR79,$AK$8:$AR$8)*IF($E79="CABA",'Parametros'!E$7,IF($E79="PBA",1-'Parametros'!E$7,1)) | J79: =SUMPRODUCT($AK79:$AR79,$AK$9:$AR$9)*IF($E79="CABA",'Parametros'!F$7,IF($E79="PBA",1-'Parametros'!F$7,1)) | K79: =SUMPRODUCT($AK79:$AR79,$AK$10:$AR$10)*IF($E79="CABA",'Parametros'!G$7,IF($E79="PBA",1-'Parametros'!G$7,1)) | L79: =SUMPRODUCT($AK79:$AR79,$AK$11:$AR$11)*IF($E79="CABA",'Parametros'!H$7,IF($E79="PBA",1-'Parametros'!H$7,1)) | M79: =SUMPRODUCT($AK79:$AR79,$AK$12:$AR$12)*IF($E79="CABA",'Parametros'!I$7,IF($E79="PBA",1-'Parametros'!I$7,1)) | N79: =SUMPRODUCT($AK79:$AR79,$AK$13:$AR$13)*IF($E79="CABA",'Parametros'!J$7,IF($E79="PBA",1-'Parametros'!J$7,1)) | O79: =SUMPRODUCT($AK79:$AR79,$AK$14:$AR$14)*IF($E79="CABA",'Parametros'!K$7,IF($E79="PBA",1-'Parametros'!K$7,1)) | AK79: 13.3 | AL79: 27.1 | AM79: 32.8 | AN79: 40.8 | AO79: 54.8 | AP79: 68.3 | AQ79: 79.5 | AR79: 84.6
A80: Granalla de acero S330 / S390 (ISO 11124-3, SAE J444) | B80: kg | C80: Consumible de proceso | D80: CyM Materiales | E80: Todos | F80: =SUMPRODUCT($AK80:$AR80,$AK$5:$AR$5)*IF($E80="CABA",'Parametros'!B$7,IF($E80="PBA",1-'Parametros'!B$7,1)) | G80: =SUMPRODUCT($AK80:$AR80,$AK$6:$AR$6)*IF($E80="CABA",'Parametros'!C$7,IF($E80="PBA",1-'Parametros'!C$7,1)) | H80: =SUMPRODUCT($AK80:$AR80,$AK$7:$AR$7)*IF($E80="CABA",'Parametros'!D$7,IF($E80="PBA",1-'Parametros'!D$7,1)) | I80: =SUMPRODUCT($AK80:$AR80,$AK$8:$AR$8)*IF($E80="CABA",'Parametros'!E$7,IF($E80="PBA",1-'Parametros'!E$7,1)) | J80: =SUMPRODUCT($AK80:$AR80,$AK$9:$AR$9)*IF($E80="CABA",'Parametros'!F$7,IF($E80="PBA",1-'Parametros'!F$7,1)) | K80: =SUMPRODUCT($AK80:$AR80,$AK$10:$AR$10)*IF($E80="CABA",'Parametros'!G$7,IF($E80="PBA",1-'Parametros'!G$7,1)) | L80: =SUMPRODUCT($AK80:$AR80,$AK$11:$AR$11)*IF($E80="CABA",'Parametros'!H$7,IF($E80="PBA",1-'Parametros'!H$7,1)) | M80: =SUMPRODUCT($AK80:$AR80,$AK$12:$AR$12)*IF($E80="CABA",'Parametros'!I$7,IF($E80="PBA",1-'Parametros'!I$7,1)) | N80: =SUMPRODUCT($AK80:$AR80,$AK$13:$AR$13)*IF($E80="CABA",'Parametros'!J$7,IF($E80="PBA",1-'Parametros'!J$7,1)) | O80: =SUMPRODUCT($AK80:$AR80,$AK$14:$AR$14)*IF($E80="CABA",'Parametros'!K$7,IF($E80="PBA",1-'Parametros'!K$7,1)) | AK80: 0.08 | AL80: 0.08 | AM80: 0.08 | AN80: 0.08
A81: Servicio de pintura en polvo al horno, rojo 03-1-050 | B81: u | C81: Servicio | D81: Prymax | E81: Todos | F81: =SUMPRODUCT($AK81:$AR81,$AK$5:$AR$5)*IF($E81="CABA",'Parametros'!B$7,IF($E81="PBA",1-'Parametros'!B$7,1)) | G81: =SUMPRODUCT($AK81:$AR81,$AK$6:$AR$6)*IF($E81="CABA",'Parametros'!C$7,IF($E81="PBA",1-'Parametros'!C$7,1)) | H81: =SUMPRODUCT($AK81:$AR81,$AK$7:$AR$7)*IF($E81="CABA",'Parametros'!D$7,IF($E81="PBA",1-'Parametros'!D$7,1)) | I81: =SUMPRODUCT($AK81:$AR81,$AK$8:$AR$8)*IF($E81="CABA",'Parametros'!E$7,IF($E81="PBA",1-'Parametros'!E$7,1)) | J81: =SUMPRODUCT($AK81:$AR81,$AK$9:$AR$9)*IF($E81="CABA",'Parametros'!F$7,IF($E81="PBA",1-'Parametros'!F$7,1)) | K81: =SUMPRODUCT($AK81:$AR81,$AK$10:$AR$10)*IF($E81="CABA",'Parametros'!G$7,IF($E81="PBA",1-'Parametros'!G$7,1)) | L81: =SUMPRODUCT($AK81:$AR81,$AK$11:$AR$11)*IF($E81="CABA",'Parametros'!H$7,IF($E81="PBA",1-'Parametros'!H$7,1)) | M81: =SUMPRODUCT($AK81:$AR81,$AK$12:$AR$12)*IF($E81="CABA",'Parametros'!I$7,IF($E81="PBA",1-'Parametros'!I$7,1)) | N81: =SUMPRODUCT($AK81:$AR81,$AK$13:$AR$13)*IF($E81="CABA",'Parametros'!J$7,IF($E81="PBA",1-'Parametros'!J$7,1)) | O81: =SUMPRODUCT($AK81:$AR81,$AK$14:$AR$14)*IF($E81="CABA",'Parametros'!K$7,IF($E81="PBA",1-'Parametros'!K$7,1)) | AK81: 1 | AL81: 1 | AM81: 1 | AN81: 1
A82: Servicio de pintura en polvo al horno, rojo 03-1-050 (con preparación por quemado) | B82: u | C82: Servicio | D82: Pintor de carros (cotización por mensaje) | E82: Todos | F82: =SUMPRODUCT($AK82:$AR82,$AK$5:$AR$5)*IF($E82="CABA",'Parametros'!B$7,IF($E82="PBA",1-'Parametros'!B$7,1)) | G82: =SUMPRODUCT($AK82:$AR82,$AK$6:$AR$6)*IF($E82="CABA",'Parametros'!C$7,IF($E82="PBA",1-'Parametros'!C$7,1)) | H82: =SUMPRODUCT($AK82:$AR82,$AK$7:$AR$7)*IF($E82="CABA",'Parametros'!D$7,IF($E82="PBA",1-'Parametros'!D$7,1)) | I82: =SUMPRODUCT($AK82:$AR82,$AK$8:$AR$8)*IF($E82="CABA",'Parametros'!E$7,IF($E82="PBA",1-'Parametros'!E$7,1)) | J82: =SUMPRODUCT($AK82:$AR82,$AK$9:$AR$9)*IF($E82="CABA",'Parametros'!F$7,IF($E82="PBA",1-'Parametros'!F$7,1)) | K82: =SUMPRODUCT($AK82:$AR82,$AK$10:$AR$10)*IF($E82="CABA",'Parametros'!G$7,IF($E82="PBA",1-'Parametros'!G$7,1)) | L82: =SUMPRODUCT($AK82:$AR82,$AK$11:$AR$11)*IF($E82="CABA",'Parametros'!H$7,IF($E82="PBA",1-'Parametros'!H$7,1)) | M82: =SUMPRODUCT($AK82:$AR82,$AK$12:$AR$12)*IF($E82="CABA",'Parametros'!I$7,IF($E82="PBA",1-'Parametros'!I$7,1)) | N82: =SUMPRODUCT($AK82:$AR82,$AK$13:$AR$13)*IF($E82="CABA",'Parametros'!J$7,IF($E82="PBA",1-'Parametros'!J$7,1)) | O82: =SUMPRODUCT($AK82:$AR82,$AK$14:$AR$14)*IF($E82="CABA",'Parametros'!K$7,IF($E82="PBA",1-'Parametros'!K$7,1)) | AO82: 1 | AP82: 1 | AQ82: 1 | AR82: 1
A83: Gas impulsor: N₂ | B83: kg | C83: Carga (agente y gas) | D83: Air Liquide Argentina - sucursal Piñeyro | E83: Todos | F83: =SUMPRODUCT($AK83:$AR83,$AK$5:$AR$5)*IF($E83="CABA",'Parametros'!B$7,IF($E83="PBA",1-'Parametros'!B$7,1)) | G83: =SUMPRODUCT($AK83:$AR83,$AK$6:$AR$6)*IF($E83="CABA",'Parametros'!C$7,IF($E83="PBA",1-'Parametros'!C$7,1)) | H83: =SUMPRODUCT($AK83:$AR83,$AK$7:$AR$7)*IF($E83="CABA",'Parametros'!D$7,IF($E83="PBA",1-'Parametros'!D$7,1)) | I83: =SUMPRODUCT($AK83:$AR83,$AK$8:$AR$8)*IF($E83="CABA",'Parametros'!E$7,IF($E83="PBA",1-'Parametros'!E$7,1)) | J83: =SUMPRODUCT($AK83:$AR83,$AK$9:$AR$9)*IF($E83="CABA",'Parametros'!F$7,IF($E83="PBA",1-'Parametros'!F$7,1)) | K83: =SUMPRODUCT($AK83:$AR83,$AK$10:$AR$10)*IF($E83="CABA",'Parametros'!G$7,IF($E83="PBA",1-'Parametros'!G$7,1)) | L83: =SUMPRODUCT($AK83:$AR83,$AK$11:$AR$11)*IF($E83="CABA",'Parametros'!H$7,IF($E83="PBA",1-'Parametros'!H$7,1)) | M83: =SUMPRODUCT($AK83:$AR83,$AK$12:$AR$12)*IF($E83="CABA",'Parametros'!I$7,IF($E83="PBA",1-'Parametros'!I$7,1)) | N83: =SUMPRODUCT($AK83:$AR83,$AK$13:$AR$13)*IF($E83="CABA",'Parametros'!J$7,IF($E83="PBA",1-'Parametros'!J$7,1)) | O83: =SUMPRODUCT($AK83:$AR83,$AK$14:$AR$14)*IF($E83="CABA",'Parametros'!K$7,IF($E83="PBA",1-'Parametros'!K$7,1)) | AK83: 0.0047 | AL83: 0.0212 | AM83: 0.0251 | AN83: 0.0588 | AO83: 0.2013 | AP83: 0.2819 | AQ83: 0.5581 | AR83: 0.5189
A84: Polvo químico seco ABC 60 (Sello IRAM 3569) | B84: kg | C84: Carga (agente y gas) | D84: DEM S.A. (DEMSA) | E84: Todos | F84: =SUMPRODUCT($AK84:$AR84,$AK$5:$AR$5)*IF($E84="CABA",'Parametros'!B$7,IF($E84="PBA",1-'Parametros'!B$7,1)) | G84: =SUMPRODUCT($AK84:$AR84,$AK$6:$AR$6)*IF($E84="CABA",'Parametros'!C$7,IF($E84="PBA",1-'Parametros'!C$7,1)) | H84: =SUMPRODUCT($AK84:$AR84,$AK$7:$AR$7)*IF($E84="CABA",'Parametros'!D$7,IF($E84="PBA",1-'Parametros'!D$7,1)) | I84: =SUMPRODUCT($AK84:$AR84,$AK$8:$AR$8)*IF($E84="CABA",'Parametros'!E$7,IF($E84="PBA",1-'Parametros'!E$7,1)) | J84: =SUMPRODUCT($AK84:$AR84,$AK$9:$AR$9)*IF($E84="CABA",'Parametros'!F$7,IF($E84="PBA",1-'Parametros'!F$7,1)) | K84: =SUMPRODUCT($AK84:$AR84,$AK$10:$AR$10)*IF($E84="CABA",'Parametros'!G$7,IF($E84="PBA",1-'Parametros'!G$7,1)) | L84: =SUMPRODUCT($AK84:$AR84,$AK$11:$AR$11)*IF($E84="CABA",'Parametros'!H$7,IF($E84="PBA",1-'Parametros'!H$7,1)) | M84: =SUMPRODUCT($AK84:$AR84,$AK$12:$AR$12)*IF($E84="CABA",'Parametros'!I$7,IF($E84="PBA",1-'Parametros'!I$7,1)) | N84: =SUMPRODUCT($AK84:$AR84,$AK$13:$AR$13)*IF($E84="CABA",'Parametros'!J$7,IF($E84="PBA",1-'Parametros'!J$7,1)) | O84: =SUMPRODUCT($AK84:$AR84,$AK$14:$AR$14)*IF($E84="CABA",'Parametros'!K$7,IF($E84="PBA",1-'Parametros'!K$7,1)) | AK84: 1.05 | AL84: 2.55 | AM84: 5.15 | AN84: 10.15
A85: Polvo químico seco ABC 90 (Sello IRAM 3569) | B85: kg | C85: Carga (agente y gas) | D85: DEM S.A. (DEMSA) | E85: Todos | F85: =SUMPRODUCT($AK85:$AR85,$AK$5:$AR$5)*IF($E85="CABA",'Parametros'!B$7,IF($E85="PBA",1-'Parametros'!B$7,1)) | G85: =SUMPRODUCT($AK85:$AR85,$AK$6:$AR$6)*IF($E85="CABA",'Parametros'!C$7,IF($E85="PBA",1-'Parametros'!C$7,1)) | H85: =SUMPRODUCT($AK85:$AR85,$AK$7:$AR$7)*IF($E85="CABA",'Parametros'!D$7,IF($E85="PBA",1-'Parametros'!D$7,1)) | I85: =SUMPRODUCT($AK85:$AR85,$AK$8:$AR$8)*IF($E85="CABA",'Parametros'!E$7,IF($E85="PBA",1-'Parametros'!E$7,1)) | J85: =SUMPRODUCT($AK85:$AR85,$AK$9:$AR$9)*IF($E85="CABA",'Parametros'!F$7,IF($E85="PBA",1-'Parametros'!F$7,1)) | K85: =SUMPRODUCT($AK85:$AR85,$AK$10:$AR$10)*IF($E85="CABA",'Parametros'!G$7,IF($E85="PBA",1-'Parametros'!G$7,1)) | L85: =SUMPRODUCT($AK85:$AR85,$AK$11:$AR$11)*IF($E85="CABA",'Parametros'!H$7,IF($E85="PBA",1-'Parametros'!H$7,1)) | M85: =SUMPRODUCT($AK85:$AR85,$AK$12:$AR$12)*IF($E85="CABA",'Parametros'!I$7,IF($E85="PBA",1-'Parametros'!I$7,1)) | N85: =SUMPRODUCT($AK85:$AR85,$AK$13:$AR$13)*IF($E85="CABA",'Parametros'!J$7,IF($E85="PBA",1-'Parametros'!J$7,1)) | O85: =SUMPRODUCT($AK85:$AR85,$AK$14:$AR$14)*IF($E85="CABA",'Parametros'!K$7,IF($E85="PBA",1-'Parametros'!K$7,1)) | AO85: 25 | AP85: 50 | AQ85: 70 | AR85: 100
A86: Estampilla IRAM de conformidad — 60 × 40 | B86: u | C86: Identificación | D86: IRAM - Instituto Argentino de Normalización | E86: Todos | F86: =SUMPRODUCT($AK86:$AR86,$AK$5:$AR$5)*IF($E86="CABA",'Parametros'!B$7,IF($E86="PBA",1-'Parametros'!B$7,1)) | G86: =SUMPRODUCT($AK86:$AR86,$AK$6:$AR$6)*IF($E86="CABA",'Parametros'!C$7,IF($E86="PBA",1-'Parametros'!C$7,1)) | H86: =SUMPRODUCT($AK86:$AR86,$AK$7:$AR$7)*IF($E86="CABA",'Parametros'!D$7,IF($E86="PBA",1-'Parametros'!D$7,1)) | I86: =SUMPRODUCT($AK86:$AR86,$AK$8:$AR$8)*IF($E86="CABA",'Parametros'!E$7,IF($E86="PBA",1-'Parametros'!E$7,1)) | J86: =SUMPRODUCT($AK86:$AR86,$AK$9:$AR$9)*IF($E86="CABA",'Parametros'!F$7,IF($E86="PBA",1-'Parametros'!F$7,1)) | K86: =SUMPRODUCT($AK86:$AR86,$AK$10:$AR$10)*IF($E86="CABA",'Parametros'!G$7,IF($E86="PBA",1-'Parametros'!G$7,1)) | L86: =SUMPRODUCT($AK86:$AR86,$AK$11:$AR$11)*IF($E86="CABA",'Parametros'!H$7,IF($E86="PBA",1-'Parametros'!H$7,1)) | M86: =SUMPRODUCT($AK86:$AR86,$AK$12:$AR$12)*IF($E86="CABA",'Parametros'!I$7,IF($E86="PBA",1-'Parametros'!I$7,1)) | N86: =SUMPRODUCT($AK86:$AR86,$AK$13:$AR$13)*IF($E86="CABA",'Parametros'!J$7,IF($E86="PBA",1-'Parametros'!J$7,1)) | O86: =SUMPRODUCT($AK86:$AR86,$AK$14:$AR$14)*IF($E86="CABA",'Parametros'!K$7,IF($E86="PBA",1-'Parametros'!K$7,1)) | AK86: 1 | AL86: 1 | AM86: 1 | AN86: 1 | AO86: 1 | AP86: 1 | AQ86: 1 | AR86: 1
A87: Etiqueta / placa de características — 168 × 136 (desarrollo × alto: panel central 108° + 2 alas laterales), e ≈ 0,3, laminado UV | B87: u | C87: Identificación | D87: Astuprint | E87: Todos | F87: =SUMPRODUCT($AK87:$AR87,$AK$5:$AR$5)*IF($E87="CABA",'Parametros'!B$7,IF($E87="PBA",1-'Parametros'!B$7,1)) | G87: =SUMPRODUCT($AK87:$AR87,$AK$6:$AR$6)*IF($E87="CABA",'Parametros'!C$7,IF($E87="PBA",1-'Parametros'!C$7,1)) | H87: =SUMPRODUCT($AK87:$AR87,$AK$7:$AR$7)*IF($E87="CABA",'Parametros'!D$7,IF($E87="PBA",1-'Parametros'!D$7,1)) | I87: =SUMPRODUCT($AK87:$AR87,$AK$8:$AR$8)*IF($E87="CABA",'Parametros'!E$7,IF($E87="PBA",1-'Parametros'!E$7,1)) | J87: =SUMPRODUCT($AK87:$AR87,$AK$9:$AR$9)*IF($E87="CABA",'Parametros'!F$7,IF($E87="PBA",1-'Parametros'!F$7,1)) | K87: =SUMPRODUCT($AK87:$AR87,$AK$10:$AR$10)*IF($E87="CABA",'Parametros'!G$7,IF($E87="PBA",1-'Parametros'!G$7,1)) | L87: =SUMPRODUCT($AK87:$AR87,$AK$11:$AR$11)*IF($E87="CABA",'Parametros'!H$7,IF($E87="PBA",1-'Parametros'!H$7,1)) | M87: =SUMPRODUCT($AK87:$AR87,$AK$12:$AR$12)*IF($E87="CABA",'Parametros'!I$7,IF($E87="PBA",1-'Parametros'!I$7,1)) | N87: =SUMPRODUCT($AK87:$AR87,$AK$13:$AR$13)*IF($E87="CABA",'Parametros'!J$7,IF($E87="PBA",1-'Parametros'!J$7,1)) | O87: =SUMPRODUCT($AK87:$AR87,$AK$14:$AR$14)*IF($E87="CABA",'Parametros'!K$7,IF($E87="PBA",1-'Parametros'!K$7,1)) | AK87: 1
A88: Etiqueta / placa de características — 234 × 151 (desarrollo × alto: panel central 108° + 2 alas laterales), e ≈ 0,3, laminado UV | B88: u | C88: Identificación | D88: Astuprint | E88: Todos | F88: =SUMPRODUCT($AK88:$AR88,$AK$5:$AR$5)*IF($E88="CABA",'Parametros'!B$7,IF($E88="PBA",1-'Parametros'!B$7,1)) | G88: =SUMPRODUCT($AK88:$AR88,$AK$6:$AR$6)*IF($E88="CABA",'Parametros'!C$7,IF($E88="PBA",1-'Parametros'!C$7,1)) | H88: =SUMPRODUCT($AK88:$AR88,$AK$7:$AR$7)*IF($E88="CABA",'Parametros'!D$7,IF($E88="PBA",1-'Parametros'!D$7,1)) | I88: =SUMPRODUCT($AK88:$AR88,$AK$8:$AR$8)*IF($E88="CABA",'Parametros'!E$7,IF($E88="PBA",1-'Parametros'!E$7,1)) | J88: =SUMPRODUCT($AK88:$AR88,$AK$9:$AR$9)*IF($E88="CABA",'Parametros'!F$7,IF($E88="PBA",1-'Parametros'!F$7,1)) | K88: =SUMPRODUCT($AK88:$AR88,$AK$10:$AR$10)*IF($E88="CABA",'Parametros'!G$7,IF($E88="PBA",1-'Parametros'!G$7,1)) | L88: =SUMPRODUCT($AK88:$AR88,$AK$11:$AR$11)*IF($E88="CABA",'Parametros'!H$7,IF($E88="PBA",1-'Parametros'!H$7,1)) | M88: =SUMPRODUCT($AK88:$AR88,$AK$12:$AR$12)*IF($E88="CABA",'Parametros'!I$7,IF($E88="PBA",1-'Parametros'!I$7,1)) | N88: =SUMPRODUCT($AK88:$AR88,$AK$13:$AR$13)*IF($E88="CABA",'Parametros'!J$7,IF($E88="PBA",1-'Parametros'!J$7,1)) | O88: =SUMPRODUCT($AK88:$AR88,$AK$14:$AR$14)*IF($E88="CABA",'Parametros'!K$7,IF($E88="PBA",1-'Parametros'!K$7,1)) | AL88: 1
A89: Etiqueta / placa de características — 289 × 142 (desarrollo × alto: panel central 108° + 2 alas laterales), e ≈ 0,3, laminado UV | B89: u | C89: Identificación | D89: Astuprint | E89: Todos | F89: =SUMPRODUCT($AK89:$AR89,$AK$5:$AR$5)*IF($E89="CABA",'Parametros'!B$7,IF($E89="PBA",1-'Parametros'!B$7,1)) | G89: =SUMPRODUCT($AK89:$AR89,$AK$6:$AR$6)*IF($E89="CABA",'Parametros'!C$7,IF($E89="PBA",1-'Parametros'!C$7,1)) | H89: =SUMPRODUCT($AK89:$AR89,$AK$7:$AR$7)*IF($E89="CABA",'Parametros'!D$7,IF($E89="PBA",1-'Parametros'!D$7,1)) | I89: =SUMPRODUCT($AK89:$AR89,$AK$8:$AR$8)*IF($E89="CABA",'Parametros'!E$7,IF($E89="PBA",1-'Parametros'!E$7,1)) | J89: =SUMPRODUCT($AK89:$AR89,$AK$9:$AR$9)*IF($E89="CABA",'Parametros'!F$7,IF($E89="PBA",1-'Parametros'!F$7,1)) | K89: =SUMPRODUCT($AK89:$AR89,$AK$10:$AR$10)*IF($E89="CABA",'Parametros'!G$7,IF($E89="PBA",1-'Parametros'!G$7,1)) | L89: =SUMPRODUCT($AK89:$AR89,$AK$11:$AR$11)*IF($E89="CABA",'Parametros'!H$7,IF($E89="PBA",1-'Parametros'!H$7,1)) | M89: =SUMPRODUCT($AK89:$AR89,$AK$12:$AR$12)*IF($E89="CABA",'Parametros'!I$7,IF($E89="PBA",1-'Parametros'!I$7,1)) | N89: =SUMPRODUCT($AK89:$AR89,$AK$13:$AR$13)*IF($E89="CABA",'Parametros'!J$7,IF($E89="PBA",1-'Parametros'!J$7,1)) | O89: =SUMPRODUCT($AK89:$AR89,$AK$14:$AR$14)*IF($E89="CABA",'Parametros'!K$7,IF($E89="PBA",1-'Parametros'!K$7,1)) | AM89: 1
A90: Etiqueta / placa de características — 343 × 221 (desarrollo × alto: panel central 108° + 2 alas laterales), e ≈ 0,3, laminado UV | B90: u | C90: Identificación | D90: Astuprint | E90: Todos | F90: =SUMPRODUCT($AK90:$AR90,$AK$5:$AR$5)*IF($E90="CABA",'Parametros'!B$7,IF($E90="PBA",1-'Parametros'!B$7,1)) | G90: =SUMPRODUCT($AK90:$AR90,$AK$6:$AR$6)*IF($E90="CABA",'Parametros'!C$7,IF($E90="PBA",1-'Parametros'!C$7,1)) | H90: =SUMPRODUCT($AK90:$AR90,$AK$7:$AR$7)*IF($E90="CABA",'Parametros'!D$7,IF($E90="PBA",1-'Parametros'!D$7,1)) | I90: =SUMPRODUCT($AK90:$AR90,$AK$8:$AR$8)*IF($E90="CABA",'Parametros'!E$7,IF($E90="PBA",1-'Parametros'!E$7,1)) | J90: =SUMPRODUCT($AK90:$AR90,$AK$9:$AR$9)*IF($E90="CABA",'Parametros'!F$7,IF($E90="PBA",1-'Parametros'!F$7,1)) | K90: =SUMPRODUCT($AK90:$AR90,$AK$10:$AR$10)*IF($E90="CABA",'Parametros'!G$7,IF($E90="PBA",1-'Parametros'!G$7,1)) | L90: =SUMPRODUCT($AK90:$AR90,$AK$11:$AR$11)*IF($E90="CABA",'Parametros'!H$7,IF($E90="PBA",1-'Parametros'!H$7,1)) | M90: =SUMPRODUCT($AK90:$AR90,$AK$12:$AR$12)*IF($E90="CABA",'Parametros'!I$7,IF($E90="PBA",1-'Parametros'!I$7,1)) | N90: =SUMPRODUCT($AK90:$AR90,$AK$13:$AR$13)*IF($E90="CABA",'Parametros'!J$7,IF($E90="PBA",1-'Parametros'!J$7,1)) | O90: =SUMPRODUCT($AK90:$AR90,$AK$14:$AR$14)*IF($E90="CABA",'Parametros'!K$7,IF($E90="PBA",1-'Parametros'!K$7,1)) | AN90: 1
A91: Etiqueta / placa de características — 522 × 208 (desarrollo × alto: panel central 108° + 2 alas laterales), e ≈ 0,3, laminado UV | B91: u | C91: Identificación | D91: Astuprint | E91: Todos | F91: =SUMPRODUCT($AK91:$AR91,$AK$5:$AR$5)*IF($E91="CABA",'Parametros'!B$7,IF($E91="PBA",1-'Parametros'!B$7,1)) | G91: =SUMPRODUCT($AK91:$AR91,$AK$6:$AR$6)*IF($E91="CABA",'Parametros'!C$7,IF($E91="PBA",1-'Parametros'!C$7,1)) | H91: =SUMPRODUCT($AK91:$AR91,$AK$7:$AR$7)*IF($E91="CABA",'Parametros'!D$7,IF($E91="PBA",1-'Parametros'!D$7,1)) | I91: =SUMPRODUCT($AK91:$AR91,$AK$8:$AR$8)*IF($E91="CABA",'Parametros'!E$7,IF($E91="PBA",1-'Parametros'!E$7,1)) | J91: =SUMPRODUCT($AK91:$AR91,$AK$9:$AR$9)*IF($E91="CABA",'Parametros'!F$7,IF($E91="PBA",1-'Parametros'!F$7,1)) | K91: =SUMPRODUCT($AK91:$AR91,$AK$10:$AR$10)*IF($E91="CABA",'Parametros'!G$7,IF($E91="PBA",1-'Parametros'!G$7,1)) | L91: =SUMPRODUCT($AK91:$AR91,$AK$11:$AR$11)*IF($E91="CABA",'Parametros'!H$7,IF($E91="PBA",1-'Parametros'!H$7,1)) | M91: =SUMPRODUCT($AK91:$AR91,$AK$12:$AR$12)*IF($E91="CABA",'Parametros'!I$7,IF($E91="PBA",1-'Parametros'!I$7,1)) | N91: =SUMPRODUCT($AK91:$AR91,$AK$13:$AR$13)*IF($E91="CABA",'Parametros'!J$7,IF($E91="PBA",1-'Parametros'!J$7,1)) | O91: =SUMPRODUCT($AK91:$AR91,$AK$14:$AR$14)*IF($E91="CABA",'Parametros'!K$7,IF($E91="PBA",1-'Parametros'!K$7,1)) | AO91: 1
A92: Etiqueta / placa de características — 604 × 204 (desarrollo × alto: panel central 108° + 2 alas laterales), e ≈ 0,3, laminado UV | B92: u | C92: Identificación | D92: Astuprint | E92: Todos | F92: =SUMPRODUCT($AK92:$AR92,$AK$5:$AR$5)*IF($E92="CABA",'Parametros'!B$7,IF($E92="PBA",1-'Parametros'!B$7,1)) | G92: =SUMPRODUCT($AK92:$AR92,$AK$6:$AR$6)*IF($E92="CABA",'Parametros'!C$7,IF($E92="PBA",1-'Parametros'!C$7,1)) | H92: =SUMPRODUCT($AK92:$AR92,$AK$7:$AR$7)*IF($E92="CABA",'Parametros'!D$7,IF($E92="PBA",1-'Parametros'!D$7,1)) | I92: =SUMPRODUCT($AK92:$AR92,$AK$8:$AR$8)*IF($E92="CABA",'Parametros'!E$7,IF($E92="PBA",1-'Parametros'!E$7,1)) | J92: =SUMPRODUCT($AK92:$AR92,$AK$9:$AR$9)*IF($E92="CABA",'Parametros'!F$7,IF($E92="PBA",1-'Parametros'!F$7,1)) | K92: =SUMPRODUCT($AK92:$AR92,$AK$10:$AR$10)*IF($E92="CABA",'Parametros'!G$7,IF($E92="PBA",1-'Parametros'!G$7,1)) | L92: =SUMPRODUCT($AK92:$AR92,$AK$11:$AR$11)*IF($E92="CABA",'Parametros'!H$7,IF($E92="PBA",1-'Parametros'!H$7,1)) | M92: =SUMPRODUCT($AK92:$AR92,$AK$12:$AR$12)*IF($E92="CABA",'Parametros'!I$7,IF($E92="PBA",1-'Parametros'!I$7,1)) | N92: =SUMPRODUCT($AK92:$AR92,$AK$13:$AR$13)*IF($E92="CABA",'Parametros'!J$7,IF($E92="PBA",1-'Parametros'!J$7,1)) | O92: =SUMPRODUCT($AK92:$AR92,$AK$14:$AR$14)*IF($E92="CABA",'Parametros'!K$7,IF($E92="PBA",1-'Parametros'!K$7,1)) | AP92: 1
A93: Etiqueta / placa de características — 736 × 211 (desarrollo × alto: panel central 108° + 2 alas laterales), e ≈ 0,3, laminado UV | B93: u | C93: Identificación | D93: Astuprint | E93: Todos | F93: =SUMPRODUCT($AK93:$AR93,$AK$5:$AR$5)*IF($E93="CABA",'Parametros'!B$7,IF($E93="PBA",1-'Parametros'!B$7,1)) | G93: =SUMPRODUCT($AK93:$AR93,$AK$6:$AR$6)*IF($E93="CABA",'Parametros'!C$7,IF($E93="PBA",1-'Parametros'!C$7,1)) | H93: =SUMPRODUCT($AK93:$AR93,$AK$7:$AR$7)*IF($E93="CABA",'Parametros'!D$7,IF($E93="PBA",1-'Parametros'!D$7,1)) | I93: =SUMPRODUCT($AK93:$AR93,$AK$8:$AR$8)*IF($E93="CABA",'Parametros'!E$7,IF($E93="PBA",1-'Parametros'!E$7,1)) | J93: =SUMPRODUCT($AK93:$AR93,$AK$9:$AR$9)*IF($E93="CABA",'Parametros'!F$7,IF($E93="PBA",1-'Parametros'!F$7,1)) | K93: =SUMPRODUCT($AK93:$AR93,$AK$10:$AR$10)*IF($E93="CABA",'Parametros'!G$7,IF($E93="PBA",1-'Parametros'!G$7,1)) | L93: =SUMPRODUCT($AK93:$AR93,$AK$11:$AR$11)*IF($E93="CABA",'Parametros'!H$7,IF($E93="PBA",1-'Parametros'!H$7,1)) | M93: =SUMPRODUCT($AK93:$AR93,$AK$12:$AR$12)*IF($E93="CABA",'Parametros'!I$7,IF($E93="PBA",1-'Parametros'!I$7,1)) | N93: =SUMPRODUCT($AK93:$AR93,$AK$13:$AR$13)*IF($E93="CABA",'Parametros'!J$7,IF($E93="PBA",1-'Parametros'!J$7,1)) | O93: =SUMPRODUCT($AK93:$AR93,$AK$14:$AR$14)*IF($E93="CABA",'Parametros'!K$7,IF($E93="PBA",1-'Parametros'!K$7,1)) | AQ93: 1 | AR93: 1
A94: Etiqueta de n° de serie GS1 — 45 × 25 | B94: u | C94: Identificación | D94: Astuprint | E94: Todos | F94: =SUMPRODUCT($AK94:$AR94,$AK$5:$AR$5)*IF($E94="CABA",'Parametros'!B$7,IF($E94="PBA",1-'Parametros'!B$7,1)) | G94: =SUMPRODUCT($AK94:$AR94,$AK$6:$AR$6)*IF($E94="CABA",'Parametros'!C$7,IF($E94="PBA",1-'Parametros'!C$7,1)) | H94: =SUMPRODUCT($AK94:$AR94,$AK$7:$AR$7)*IF($E94="CABA",'Parametros'!D$7,IF($E94="PBA",1-'Parametros'!D$7,1)) | I94: =SUMPRODUCT($AK94:$AR94,$AK$8:$AR$8)*IF($E94="CABA",'Parametros'!E$7,IF($E94="PBA",1-'Parametros'!E$7,1)) | J94: =SUMPRODUCT($AK94:$AR94,$AK$9:$AR$9)*IF($E94="CABA",'Parametros'!F$7,IF($E94="PBA",1-'Parametros'!F$7,1)) | K94: =SUMPRODUCT($AK94:$AR94,$AK$10:$AR$10)*IF($E94="CABA",'Parametros'!G$7,IF($E94="PBA",1-'Parametros'!G$7,1)) | L94: =SUMPRODUCT($AK94:$AR94,$AK$11:$AR$11)*IF($E94="CABA",'Parametros'!H$7,IF($E94="PBA",1-'Parametros'!H$7,1)) | M94: =SUMPRODUCT($AK94:$AR94,$AK$12:$AR$12)*IF($E94="CABA",'Parametros'!I$7,IF($E94="PBA",1-'Parametros'!I$7,1)) | N94: =SUMPRODUCT($AK94:$AR94,$AK$13:$AR$13)*IF($E94="CABA",'Parametros'!J$7,IF($E94="PBA",1-'Parametros'!J$7,1)) | O94: =SUMPRODUCT($AK94:$AR94,$AK$14:$AR$14)*IF($E94="CABA",'Parametros'!K$7,IF($E94="PBA",1-'Parametros'!K$7,1)) | AK94: 1 | AL94: 1 | AM94: 1 | AN94: 1 | AO94: 1 | AP94: 1 | AQ94: 1 | AR94: 1
A95: Faja de garantía válvula-cuello — 30 × 40 | B95: u | C95: Identificación | D95: Astuprint | E95: Todos | F95: =SUMPRODUCT($AK95:$AR95,$AK$5:$AR$5)*IF($E95="CABA",'Parametros'!B$7,IF($E95="PBA",1-'Parametros'!B$7,1)) | G95: =SUMPRODUCT($AK95:$AR95,$AK$6:$AR$6)*IF($E95="CABA",'Parametros'!C$7,IF($E95="PBA",1-'Parametros'!C$7,1)) | H95: =SUMPRODUCT($AK95:$AR95,$AK$7:$AR$7)*IF($E95="CABA",'Parametros'!D$7,IF($E95="PBA",1-'Parametros'!D$7,1)) | I95: =SUMPRODUCT($AK95:$AR95,$AK$8:$AR$8)*IF($E95="CABA",'Parametros'!E$7,IF($E95="PBA",1-'Parametros'!E$7,1)) | J95: =SUMPRODUCT($AK95:$AR95,$AK$9:$AR$9)*IF($E95="CABA",'Parametros'!F$7,IF($E95="PBA",1-'Parametros'!F$7,1)) | K95: =SUMPRODUCT($AK95:$AR95,$AK$10:$AR$10)*IF($E95="CABA",'Parametros'!G$7,IF($E95="PBA",1-'Parametros'!G$7,1)) | L95: =SUMPRODUCT($AK95:$AR95,$AK$11:$AR$11)*IF($E95="CABA",'Parametros'!H$7,IF($E95="PBA",1-'Parametros'!H$7,1)) | M95: =SUMPRODUCT($AK95:$AR95,$AK$12:$AR$12)*IF($E95="CABA",'Parametros'!I$7,IF($E95="PBA",1-'Parametros'!I$7,1)) | N95: =SUMPRODUCT($AK95:$AR95,$AK$13:$AR$13)*IF($E95="CABA",'Parametros'!J$7,IF($E95="PBA",1-'Parametros'!J$7,1)) | O95: =SUMPRODUCT($AK95:$AR95,$AK$14:$AR$14)*IF($E95="CABA",'Parametros'!K$7,IF($E95="PBA",1-'Parametros'!K$7,1)) | AK95: 1 | AL95: 1 | AM95: 1 | AN95: 1 | AO95: 1 | AP95: 1 | AQ95: 1 | AR95: 1
A96: Oblea de fabricación (PBA) — Ø46 (Res. OPDS 522/07), numerada, autodestructible | B96: u | C96: Identificación | D96: Ministerio de Ambiente PBA (ex OPDS) | E96: PBA | F96: =SUMPRODUCT($AK96:$AR96,$AK$5:$AR$5)*IF($E96="CABA",'Parametros'!B$7,IF($E96="PBA",1-'Parametros'!B$7,1)) | G96: =SUMPRODUCT($AK96:$AR96,$AK$6:$AR$6)*IF($E96="CABA",'Parametros'!C$7,IF($E96="PBA",1-'Parametros'!C$7,1)) | H96: =SUMPRODUCT($AK96:$AR96,$AK$7:$AR$7)*IF($E96="CABA",'Parametros'!D$7,IF($E96="PBA",1-'Parametros'!D$7,1)) | I96: =SUMPRODUCT($AK96:$AR96,$AK$8:$AR$8)*IF($E96="CABA",'Parametros'!E$7,IF($E96="PBA",1-'Parametros'!E$7,1)) | J96: =SUMPRODUCT($AK96:$AR96,$AK$9:$AR$9)*IF($E96="CABA",'Parametros'!F$7,IF($E96="PBA",1-'Parametros'!F$7,1)) | K96: =SUMPRODUCT($AK96:$AR96,$AK$10:$AR$10)*IF($E96="CABA",'Parametros'!G$7,IF($E96="PBA",1-'Parametros'!G$7,1)) | L96: =SUMPRODUCT($AK96:$AR96,$AK$11:$AR$11)*IF($E96="CABA",'Parametros'!H$7,IF($E96="PBA",1-'Parametros'!H$7,1)) | M96: =SUMPRODUCT($AK96:$AR96,$AK$12:$AR$12)*IF($E96="CABA",'Parametros'!I$7,IF($E96="PBA",1-'Parametros'!I$7,1)) | N96: =SUMPRODUCT($AK96:$AR96,$AK$13:$AR$13)*IF($E96="CABA",'Parametros'!J$7,IF($E96="PBA",1-'Parametros'!J$7,1)) | O96: =SUMPRODUCT($AK96:$AR96,$AK$14:$AR$14)*IF($E96="CABA",'Parametros'!K$7,IF($E96="PBA",1-'Parametros'!K$7,1)) | AK96: 1 | AL96: 1 | AM96: 1 | AN96: 1 | AO96: 1 | AP96: 1 | AQ96: 1 | AR96: 1
A97: Precinto de fábrica — Ø5 × 10, numerado, rotura 30-50 N | B97: u | C97: Identificación | D97: SonFuertes (vía Papelera Damián) | E97: Todos | F97: =SUMPRODUCT($AK97:$AR97,$AK$5:$AR$5)*IF($E97="CABA",'Parametros'!B$7,IF($E97="PBA",1-'Parametros'!B$7,1)) | G97: =SUMPRODUCT($AK97:$AR97,$AK$6:$AR$6)*IF($E97="CABA",'Parametros'!C$7,IF($E97="PBA",1-'Parametros'!C$7,1)) | H97: =SUMPRODUCT($AK97:$AR97,$AK$7:$AR$7)*IF($E97="CABA",'Parametros'!D$7,IF($E97="PBA",1-'Parametros'!D$7,1)) | I97: =SUMPRODUCT($AK97:$AR97,$AK$8:$AR$8)*IF($E97="CABA",'Parametros'!E$7,IF($E97="PBA",1-'Parametros'!E$7,1)) | J97: =SUMPRODUCT($AK97:$AR97,$AK$9:$AR$9)*IF($E97="CABA",'Parametros'!F$7,IF($E97="PBA",1-'Parametros'!F$7,1)) | K97: =SUMPRODUCT($AK97:$AR97,$AK$10:$AR$10)*IF($E97="CABA",'Parametros'!G$7,IF($E97="PBA",1-'Parametros'!G$7,1)) | L97: =SUMPRODUCT($AK97:$AR97,$AK$11:$AR$11)*IF($E97="CABA",'Parametros'!H$7,IF($E97="PBA",1-'Parametros'!H$7,1)) | M97: =SUMPRODUCT($AK97:$AR97,$AK$12:$AR$12)*IF($E97="CABA",'Parametros'!I$7,IF($E97="PBA",1-'Parametros'!I$7,1)) | N97: =SUMPRODUCT($AK97:$AR97,$AK$13:$AR$13)*IF($E97="CABA",'Parametros'!J$7,IF($E97="PBA",1-'Parametros'!J$7,1)) | O97: =SUMPRODUCT($AK97:$AR97,$AK$14:$AR$14)*IF($E97="CABA",'Parametros'!K$7,IF($E97="PBA",1-'Parametros'!K$7,1)) | AK97: 1 | AL97: 1 | AM97: 1 | AN97: 1 | AO97: 1 | AP97: 1 | AQ97: 1 | AR97: 1
A98: Tarjeta de identificación AGC (CABA) — 140 × 55 | B98: u | C98: Identificación | D98: Agencia Gubernamental de Control (CABA) | E98: CABA | F98: =SUMPRODUCT($AK98:$AR98,$AK$5:$AR$5)*IF($E98="CABA",'Parametros'!B$7,IF($E98="PBA",1-'Parametros'!B$7,1)) | G98: =SUMPRODUCT($AK98:$AR98,$AK$6:$AR$6)*IF($E98="CABA",'Parametros'!C$7,IF($E98="PBA",1-'Parametros'!C$7,1)) | H98: =SUMPRODUCT($AK98:$AR98,$AK$7:$AR$7)*IF($E98="CABA",'Parametros'!D$7,IF($E98="PBA",1-'Parametros'!D$7,1)) | I98: =SUMPRODUCT($AK98:$AR98,$AK$8:$AR$8)*IF($E98="CABA",'Parametros'!E$7,IF($E98="PBA",1-'Parametros'!E$7,1)) | J98: =SUMPRODUCT($AK98:$AR98,$AK$9:$AR$9)*IF($E98="CABA",'Parametros'!F$7,IF($E98="PBA",1-'Parametros'!F$7,1)) | K98: =SUMPRODUCT($AK98:$AR98,$AK$10:$AR$10)*IF($E98="CABA",'Parametros'!G$7,IF($E98="PBA",1-'Parametros'!G$7,1)) | L98: =SUMPRODUCT($AK98:$AR98,$AK$11:$AR$11)*IF($E98="CABA",'Parametros'!H$7,IF($E98="PBA",1-'Parametros'!H$7,1)) | M98: =SUMPRODUCT($AK98:$AR98,$AK$12:$AR$12)*IF($E98="CABA",'Parametros'!I$7,IF($E98="PBA",1-'Parametros'!I$7,1)) | N98: =SUMPRODUCT($AK98:$AR98,$AK$13:$AR$13)*IF($E98="CABA",'Parametros'!J$7,IF($E98="PBA",1-'Parametros'!J$7,1)) | O98: =SUMPRODUCT($AK98:$AR98,$AK$14:$AR$14)*IF($E98="CABA",'Parametros'!K$7,IF($E98="PBA",1-'Parametros'!K$7,1)) | AL98: 1 | AM98: 1 | AN98: 1 | AO98: 1 | AP98: 1 | AQ98: 1 | AR98: 1
A99: Soporte de pared (FL_ACC_01) | B99: u | C99: Soporte | D99: Maxiseguridad | E99: Todos | F99: =SUMPRODUCT($AK99:$AR99,$AK$5:$AR$5)*IF($E99="CABA",'Parametros'!B$7,IF($E99="PBA",1-'Parametros'!B$7,1)) | G99: =SUMPRODUCT($AK99:$AR99,$AK$6:$AR$6)*IF($E99="CABA",'Parametros'!C$7,IF($E99="PBA",1-'Parametros'!C$7,1)) | H99: =SUMPRODUCT($AK99:$AR99,$AK$7:$AR$7)*IF($E99="CABA",'Parametros'!D$7,IF($E99="PBA",1-'Parametros'!D$7,1)) | I99: =SUMPRODUCT($AK99:$AR99,$AK$8:$AR$8)*IF($E99="CABA",'Parametros'!E$7,IF($E99="PBA",1-'Parametros'!E$7,1)) | J99: =SUMPRODUCT($AK99:$AR99,$AK$9:$AR$9)*IF($E99="CABA",'Parametros'!F$7,IF($E99="PBA",1-'Parametros'!F$7,1)) | K99: =SUMPRODUCT($AK99:$AR99,$AK$10:$AR$10)*IF($E99="CABA",'Parametros'!G$7,IF($E99="PBA",1-'Parametros'!G$7,1)) | L99: =SUMPRODUCT($AK99:$AR99,$AK$11:$AR$11)*IF($E99="CABA",'Parametros'!H$7,IF($E99="PBA",1-'Parametros'!H$7,1)) | M99: =SUMPRODUCT($AK99:$AR99,$AK$12:$AR$12)*IF($E99="CABA",'Parametros'!I$7,IF($E99="PBA",1-'Parametros'!I$7,1)) | N99: =SUMPRODUCT($AK99:$AR99,$AK$13:$AR$13)*IF($E99="CABA",'Parametros'!J$7,IF($E99="PBA",1-'Parametros'!J$7,1)) | O99: =SUMPRODUCT($AK99:$AR99,$AK$14:$AR$14)*IF($E99="CABA",'Parametros'!K$7,IF($E99="PBA",1-'Parametros'!K$7,1)) | AL99: 1 | AM99: 1 | AN99: 1
A100: Soporte vehicular con cierre rápido (FL_ACC_02) | B100: u | C100: Soporte | D100: Maxiseguridad | E100: Todos | F100: =SUMPRODUCT($AK100:$AR100,$AK$5:$AR$5)*IF($E100="CABA",'Parametros'!B$7,IF($E100="PBA",1-'Parametros'!B$7,1)) | G100: =SUMPRODUCT($AK100:$AR100,$AK$6:$AR$6)*IF($E100="CABA",'Parametros'!C$7,IF($E100="PBA",1-'Parametros'!C$7,1)) | H100: =SUMPRODUCT($AK100:$AR100,$AK$7:$AR$7)*IF($E100="CABA",'Parametros'!D$7,IF($E100="PBA",1-'Parametros'!D$7,1)) | I100: =SUMPRODUCT($AK100:$AR100,$AK$8:$AR$8)*IF($E100="CABA",'Parametros'!E$7,IF($E100="PBA",1-'Parametros'!E$7,1)) | J100: =SUMPRODUCT($AK100:$AR100,$AK$9:$AR$9)*IF($E100="CABA",'Parametros'!F$7,IF($E100="PBA",1-'Parametros'!F$7,1)) | K100: =SUMPRODUCT($AK100:$AR100,$AK$10:$AR$10)*IF($E100="CABA",'Parametros'!G$7,IF($E100="PBA",1-'Parametros'!G$7,1)) | L100: =SUMPRODUCT($AK100:$AR100,$AK$11:$AR$11)*IF($E100="CABA",'Parametros'!H$7,IF($E100="PBA",1-'Parametros'!H$7,1)) | M100: =SUMPRODUCT($AK100:$AR100,$AK$12:$AR$12)*IF($E100="CABA",'Parametros'!I$7,IF($E100="PBA",1-'Parametros'!I$7,1)) | N100: =SUMPRODUCT($AK100:$AR100,$AK$13:$AR$13)*IF($E100="CABA",'Parametros'!J$7,IF($E100="PBA",1-'Parametros'!J$7,1)) | O100: =SUMPRODUCT($AK100:$AR100,$AK$14:$AR$14)*IF($E100="CABA",'Parametros'!K$7,IF($E100="PBA",1-'Parametros'!K$7,1)) | AK100: 1
A101: Tornillo y tarugo de fijación | B101: u | C101: Soporte | D101: Würth Argentina | E101: Todos | F101: =SUMPRODUCT($AK101:$AR101,$AK$5:$AR$5)*IF($E101="CABA",'Parametros'!B$7,IF($E101="PBA",1-'Parametros'!B$7,1)) | G101: =SUMPRODUCT($AK101:$AR101,$AK$6:$AR$6)*IF($E101="CABA",'Parametros'!C$7,IF($E101="PBA",1-'Parametros'!C$7,1)) | H101: =SUMPRODUCT($AK101:$AR101,$AK$7:$AR$7)*IF($E101="CABA",'Parametros'!D$7,IF($E101="PBA",1-'Parametros'!D$7,1)) | I101: =SUMPRODUCT($AK101:$AR101,$AK$8:$AR$8)*IF($E101="CABA",'Parametros'!E$7,IF($E101="PBA",1-'Parametros'!E$7,1)) | J101: =SUMPRODUCT($AK101:$AR101,$AK$9:$AR$9)*IF($E101="CABA",'Parametros'!F$7,IF($E101="PBA",1-'Parametros'!F$7,1)) | K101: =SUMPRODUCT($AK101:$AR101,$AK$10:$AR$10)*IF($E101="CABA",'Parametros'!G$7,IF($E101="PBA",1-'Parametros'!G$7,1)) | L101: =SUMPRODUCT($AK101:$AR101,$AK$11:$AR$11)*IF($E101="CABA",'Parametros'!H$7,IF($E101="PBA",1-'Parametros'!H$7,1)) | M101: =SUMPRODUCT($AK101:$AR101,$AK$12:$AR$12)*IF($E101="CABA",'Parametros'!I$7,IF($E101="PBA",1-'Parametros'!I$7,1)) | N101: =SUMPRODUCT($AK101:$AR101,$AK$13:$AR$13)*IF($E101="CABA",'Parametros'!J$7,IF($E101="PBA",1-'Parametros'!J$7,1)) | O101: =SUMPRODUCT($AK101:$AR101,$AK$14:$AR$14)*IF($E101="CABA",'Parametros'!K$7,IF($E101="PBA",1-'Parametros'!K$7,1)) | AL101: 2 | AM101: 2 | AN101: 2
A102: Caja de cartón corrugado doble — 261 × 214 × 628 interior (envolvente del plano + 15 por lado) | B102: u | C102: Embalaje | D102: Maxipack | E102: Todos | F102: =SUMPRODUCT($AK102:$AR102,$AK$5:$AR$5)*IF($E102="CABA",'Parametros'!B$7,IF($E102="PBA",1-'Parametros'!B$7,1)) | G102: =SUMPRODUCT($AK102:$AR102,$AK$6:$AR$6)*IF($E102="CABA",'Parametros'!C$7,IF($E102="PBA",1-'Parametros'!C$7,1)) | H102: =SUMPRODUCT($AK102:$AR102,$AK$7:$AR$7)*IF($E102="CABA",'Parametros'!D$7,IF($E102="PBA",1-'Parametros'!D$7,1)) | I102: =SUMPRODUCT($AK102:$AR102,$AK$8:$AR$8)*IF($E102="CABA",'Parametros'!E$7,IF($E102="PBA",1-'Parametros'!E$7,1)) | J102: =SUMPRODUCT($AK102:$AR102,$AK$9:$AR$9)*IF($E102="CABA",'Parametros'!F$7,IF($E102="PBA",1-'Parametros'!F$7,1)) | K102: =SUMPRODUCT($AK102:$AR102,$AK$10:$AR$10)*IF($E102="CABA",'Parametros'!G$7,IF($E102="PBA",1-'Parametros'!G$7,1)) | L102: =SUMPRODUCT($AK102:$AR102,$AK$11:$AR$11)*IF($E102="CABA",'Parametros'!H$7,IF($E102="PBA",1-'Parametros'!H$7,1)) | M102: =SUMPRODUCT($AK102:$AR102,$AK$12:$AR$12)*IF($E102="CABA",'Parametros'!I$7,IF($E102="PBA",1-'Parametros'!I$7,1)) | N102: =SUMPRODUCT($AK102:$AR102,$AK$13:$AR$13)*IF($E102="CABA",'Parametros'!J$7,IF($E102="PBA",1-'Parametros'!J$7,1)) | O102: =SUMPRODUCT($AK102:$AR102,$AK$14:$AR$14)*IF($E102="CABA",'Parametros'!K$7,IF($E102="PBA",1-'Parametros'!K$7,1)) | AN102: 1
...

Sheet MP_MATAFUEGOS_REVENDIDOS
A1: Requerimiento — matafuegos revendidos (compra del equipo terminado)
A2: Sólo se compra el equipo terminado y, si va a CABA, la tarjeta AGC.
AJ4: Demanda (u) → | AK4: AGUA_10l | AL4: AFFF_10l | AM4: AFFF_50l | AN4: BC_5kg | AO4: SALESK_6l | AP4: CO2_2kg | AQ4: CO2_5kg | AR4: HCFC-HFC_5kg | AS4: CLASED_9l
AJ5: ='Demanda'!B3 | AK5: ='Demanda'!B16 | AL5: ='Demanda'!B17 | AM5: ='Demanda'!B18 | AN5: ='Demanda'!B19 | AO5: ='Demanda'!B20 | AP5: ='Demanda'!B21 | AQ5: ='Demanda'!B22 | AR5: ='Demanda'!B23 | AS5: ='Demanda'!B24
AJ6: ='Demanda'!C3 | AK6: ='Demanda'!C16 | AL6: ='Demanda'!C17 | AM6: ='Demanda'!C18 | AN6: ='Demanda'!C19 | AO6: ='Demanda'!C20 | AP6: ='Demanda'!C21 | AQ6: ='Demanda'!C22 | AR6: ='Demanda'!C23 | AS6: ='Demanda'!C24
AJ7: ='Demanda'!D3 | AK7: ='Demanda'!D16 | AL7: ='Demanda'!D17 | AM7: ='Demanda'!D18 | AN7: ='Demanda'!D19 | AO7: ='Demanda'!D20 | AP7: ='Demanda'!D21 | AQ7: ='Demanda'!D22 | AR7: ='Demanda'!D23 | AS7: ='Demanda'!D24
AJ8: ='Demanda'!E3 | AK8: ='Demanda'!E16 | AL8: ='Demanda'!E17 | AM8: ='Demanda'!E18 | AN8: ='Demanda'!E19 | AO8: ='Demanda'!E20 | AP8: ='Demanda'!E21 | AQ8: ='Demanda'!E22 | AR8: ='Demanda'!E23 | AS8: ='Demanda'!E24
AJ9: ='Demanda'!F3 | AK9: ='Demanda'!F16 | AL9: ='Demanda'!F17 | AM9: ='Demanda'!F18 | AN9: ='Demanda'!F19 | AO9: ='Demanda'!F20 | AP9: ='Demanda'!F21 | AQ9: ='Demanda'!F22 | AR9: ='Demanda'!F23 | AS9: ='Demanda'!F24
AJ10: ='Demanda'!G3 | AK10: ='Demanda'!G16 | AL10: ='Demanda'!G17 | AM10: ='Demanda'!G18 | AN10: ='Demanda'!G19 | AO10: ='Demanda'!G20 | AP10: ='Demanda'!G21 | AQ10: ='Demanda'!G22 | AR10: ='Demanda'!G23 | AS10: ='Demanda'!G24
AJ11: ='Demanda'!H3 | AK11: ='Demanda'!H16 | AL11: ='Demanda'!H17 | AM11: ='Demanda'!H18 | AN11: ='Demanda'!H19 | AO11: ='Demanda'!H20 | AP11: ='Demanda'!H21 | AQ11: ='Demanda'!H22 | AR11: ='Demanda'!H23 | AS11: ='Demanda'!H24
AJ12: ='Demanda'!I3 | AK12: ='Demanda'!I16 | AL12: ='Demanda'!I17 | AM12: ='Demanda'!I18 | AN12: ='Demanda'!I19 | AO12: ='Demanda'!I20 | AP12: ='Demanda'!I21 | AQ12: ='Demanda'!I22 | AR12: ='Demanda'!I23 | AS12: ='Demanda'!I24
AJ13: ='Demanda'!J3 | AK13: ='Demanda'!J16 | AL13: ='Demanda'!J17 | AM13: ='Demanda'!J18 | AN13: ='Demanda'!J19 | AO13: ='Demanda'!J20 | AP13: ='Demanda'!J21 | AQ13: ='Demanda'!J22 | AR13: ='Demanda'!J23 | AS13: ='Demanda'!J24
AJ14: ='Demanda'!K3 | AK14: ='Demanda'!K16 | AL14: ='Demanda'!K17 | AM14: ='Demanda'!K18 | AN14: ='Demanda'!K19 | AO14: ='Demanda'!K20 | AP14: ='Demanda'!K21 | AQ14: ='Demanda'!K22 | AR14: ='Demanda'!K23 | AS14: ='Demanda'!K24
A16: Ítem | B16: UM | C16: Rubro | D16: Proveedor principal | E16: Destino | F16: ='Demanda'!B3 | G16: ='Demanda'!C3 | H16: ='Demanda'!D3 | I16: ='Demanda'!E3 | J16: ='Demanda'!F3 | K16: ='Demanda'!G3 | L16: ='Demanda'!H3 | M16: ='Demanda'!I3 | ... O16: ='Demanda'!K3 | AK16: coef. AGUA_10l | AL16: coef. AFFF_10l | AM16: coef. AFFF_50l | AN16: coef. BC_5kg | AO16: coef. SALESK_6l | AP16: coef. CO2_2kg | AQ16: coef. CO2_5kg | AR16: coef. HCFC-HFC_5kg | AS16: coef. CLASED_9l
A17: Tarjeta de identificación AGC (CABA) — 140 × 55 | B17: u | C17: Identificación | D17: Agencia Gubernamental de Control (CABA) | E17: CABA | F17: =SUMPRODUCT($AK17:$AS17,$AK$5:$AS$5)*IF($E17="CABA",'Parametros'!B$7,IF($E17="PBA",1-'Parametros'!B$7,1)) | G17: =SUMPRODUCT($AK17:$AS17,$AK$6:$AS$6)*IF($E17="CABA",'Parametros'!C$7,IF($E17="PBA",1-'Parametros'!C$7,1)) | H17: =SUMPRODUCT($AK17:$AS17,$AK$7:$AS$7)*IF($E17="CABA",'Parametros'!D$7,IF($E17="PBA",1-'Parametros'!D$7,1)) | I17: =SUMPRODUCT($AK17:$AS17,$AK$8:$AS$8)*IF($E17="CABA",'Parametros'!E$7,IF($E17="PBA",1-'Parametros'!E$7,1)) | J17: =SUMPRODUCT($AK17:$AS17,$AK$9:$AS$9)*IF($E17="CABA",'Parametros'!F$7,IF($E17="PBA",1-'Parametros'!F$7,1)) | K17: =SUMPRODUCT($AK17:$AS17,$AK$10:$AS$10)*IF($E17="CABA",'Parametros'!G$7,IF($E17="PBA",1-'Parametros'!G$7,1)) | L17: =SUMPRODUCT($AK17:$AS17,$AK$11:$AS$11)*IF($E17="CABA",'Parametros'!H$7,IF($E17="PBA",1-'Parametros'!H$7,1)) | M17: =SUMPRODUCT($AK17:$AS17,$AK$12:$AS$12)*IF($E17="CABA",'Parametros'!I$7,IF($E17="PBA",1-'Parametros'!I$7,1)) | N17: =SUMPRODUCT($AK17:$AS17,$AK$13:$AS$13)*IF($E17="CABA",'Parametros'!J$7,IF($E17="PBA",1-'Parametros'!J$7,1)) | O17: =SUMPRODUCT($AK17:$AS17,$AK$14:$AS$14)*IF($E17="CABA",'Parametros'!K$7,IF($E17="PBA",1-'Parametros'!K$7,1)) | AK17: 1 | AL17: 1 | AM17: 1 | AN17: 1 | AO17: 1 | AP17: 1 | AQ17: 1 | AR17: 1 | AS17: 1
A18: Equipo terminado comprado (fabricante con Sello IRAM): FL_MAT_AFFF_10l | B18: u | C18: Equipo terminado comprado | D18: Matafuegos Georgia - venta mayorista | E18: Todos | F18: =SUMPRODUCT($AK18:$AS18,$AK$5:$AS$5)*IF($E18="CABA",'Parametros'!B$7,IF($E18="PBA",1-'Parametros'!B$7,1)) | G18: =SUMPRODUCT($AK18:$AS18,$AK$6:$AS$6)*IF($E18="CABA",'Parametros'!C$7,IF($E18="PBA",1-'Parametros'!C$7,1)) | H18: =SUMPRODUCT($AK18:$AS18,$AK$7:$AS$7)*IF($E18="CABA",'Parametros'!D$7,IF($E18="PBA",1-'Parametros'!D$7,1)) | I18: =SUMPRODUCT($AK18:$AS18,$AK$8:$AS$8)*IF($E18="CABA",'Parametros'!E$7,IF($E18="PBA",1-'Parametros'!E$7,1)) | J18: =SUMPRODUCT($AK18:$AS18,$AK$9:$AS$9)*IF($E18="CABA",'Parametros'!F$7,IF($E18="PBA",1-'Parametros'!F$7,1)) | K18: =SUMPRODUCT($AK18:$AS18,$AK$10:$AS$10)*IF($E18="CABA",'Parametros'!G$7,IF($E18="PBA",1-'Parametros'!G$7,1)) | L18: =SUMPRODUCT($AK18:$AS18,$AK$11:$AS$11)*IF($E18="CABA",'Parametros'!H$7,IF($E18="PBA",1-'Parametros'!H$7,1)) | M18: =SUMPRODUCT($AK18:$AS18,$AK$12:$AS$12)*IF($E18="CABA",'Parametros'!I$7,IF($E18="PBA",1-'Parametros'!I$7,1)) | N18: =SUMPRODUCT($AK18:$AS18,$AK$13:$AS$13)*IF($E18="CABA",'Parametros'!J$7,IF($E18="PBA",1-'Parametros'!J$7,1)) | O18: =SUMPRODUCT($AK18:$AS18,$AK$14:$AS$14)*IF($E18="CABA",'Parametros'!K$7,IF($E18="PBA",1-'Parametros'!K$7,1)) | AL18: 1
A19: Equipo terminado comprado (fabricante con Sello IRAM): FL_MAT_AFFF_50l | B19: u | C19: Equipo terminado comprado | D19: Matafuegos Georgia - venta mayorista | E19: Todos | F19: =SUMPRODUCT($AK19:$AS19,$AK$5:$AS$5)*IF($E19="CABA",'Parametros'!B$7,IF($E19="PBA",1-'Parametros'!B$7,1)) | G19: =SUMPRODUCT($AK19:$AS19,$AK$6:$AS$6)*IF($E19="CABA",'Parametros'!C$7,IF($E19="PBA",1-'Parametros'!C$7,1)) | H19: =SUMPRODUCT($AK19:$AS19,$AK$7:$AS$7)*IF($E19="CABA",'Parametros'!D$7,IF($E19="PBA",1-'Parametros'!D$7,1)) | I19: =SUMPRODUCT($AK19:$AS19,$AK$8:$AS$8)*IF($E19="CABA",'Parametros'!E$7,IF($E19="PBA",1-'Parametros'!E$7,1)) | J19: =SUMPRODUCT($AK19:$AS19,$AK$9:$AS$9)*IF($E19="CABA",'Parametros'!F$7,IF($E19="PBA",1-'Parametros'!F$7,1)) | K19: =SUMPRODUCT($AK19:$AS19,$AK$10:$AS$10)*IF($E19="CABA",'Parametros'!G$7,IF($E19="PBA",1-'Parametros'!G$7,1)) | L19: =SUMPRODUCT($AK19:$AS19,$AK$11:$AS$11)*IF($E19="CABA",'Parametros'!H$7,IF($E19="PBA",1-'Parametros'!H$7,1)) | M19: =SUMPRODUCT($AK19:$AS19,$AK$12:$AS$12)*IF($E19="CABA",'Parametros'!I$7,IF($E19="PBA",1-'Parametros'!I$7,1)) | N19: =SUMPRODUCT($AK19:$AS19,$AK$13:$AS$13)*IF($E19="CABA",'Parametros'!J$7,IF($E19="PBA",1-'Parametros'!J$7,1)) | O19: =SUMPRODUCT($AK19:$AS19,$AK$14:$AS$14)*IF($E19="CABA",'Parametros'!K$7,IF($E19="PBA",1-'Parametros'!K$7,1)) | AM19: 1
A20: Equipo terminado comprado (fabricante con Sello IRAM): FL_MAT_AGUA_10l | B20: u | C20: Equipo terminado comprado | D20: Matafuegos Georgia - venta mayorista | E20: Todos | F20: =SUMPRODUCT($AK20:$AS20,$AK$5:$AS$5)*IF($E20="CABA",'Parametros'!B$7,IF($E20="PBA",1-'Parametros'!B$7,1)) | G20: =SUMPRODUCT($AK20:$AS20,$AK$6:$AS$6)*IF($E20="CABA",'Parametros'!C$7,IF($E20="PBA",1-'Parametros'!C$7,1)) | H20: =SUMPRODUCT($AK20:$AS20,$AK$7:$AS$7)*IF($E20="CABA",'Parametros'!D$7,IF($E20="PBA",1-'Parametros'!D$7,1)) | I20: =SUMPRODUCT($AK20:$AS20,$AK$8:$AS$8)*IF($E20="CABA",'Parametros'!E$7,IF($E20="PBA",1-'Parametros'!E$7,1)) | J20: =SUMPRODUCT($AK20:$AS20,$AK$9:$AS$9)*IF($E20="CABA",'Parametros'!F$7,IF($E20="PBA",1-'Parametros'!F$7,1)) | K20: =SUMPRODUCT($AK20:$AS20,$AK$10:$AS$10)*IF($E20="CABA",'Parametros'!G$7,IF($E20="PBA",1-'Parametros'!G$7,1)) | L20: =SUMPRODUCT($AK20:$AS20,$AK$11:$AS$11)*IF($E20="CABA",'Parametros'!H$7,IF($E20="PBA",1-'Parametros'!H$7,1)) | M20: =SUMPRODUCT($AK20:$AS20,$AK$12:$AS$12)*IF($E20="CABA",'Parametros'!I$7,IF($E20="PBA",1-'Parametros'!I$7,1)) | N20: =SUMPRODUCT($AK20:$AS20,$AK$13:$AS$13)*IF($E20="CABA",'Parametros'!J$7,IF($E20="PBA",1-'Parametros'!J$7,1)) | O20: =SUMPRODUCT($AK20:$AS20,$AK$14:$AS$14)*IF($E20="CABA",'Parametros'!K$7,IF($E20="PBA",1-'Parametros'!K$7,1)) | AK20: 1
A21: Equipo terminado comprado (fabricante con Sello IRAM): FL_MAT_BC_5kg | B21: u | C21: Equipo terminado comprado | D21: Matafuegos Georgia - venta mayorista | E21: Todos | F21: =SUMPRODUCT($AK21:$AS21,$AK$5:$AS$5)*IF($E21="CABA",'Parametros'!B$7,IF($E21="PBA",1-'Parametros'!B$7,1)) | G21: =SUMPRODUCT($AK21:$AS21,$AK$6:$AS$6)*IF($E21="CABA",'Parametros'!C$7,IF($E21="PBA",1-'Parametros'!C$7,1)) | H21: =SUMPRODUCT($AK21:$AS21,$AK$7:$AS$7)*IF($E21="CABA",'Parametros'!D$7,IF($E21="PBA",1-'Parametros'!D$7,1)) | I21: =SUMPRODUCT($AK21:$AS21,$AK$8:$AS$8)*IF($E21="CABA",'Parametros'!E$7,IF($E21="PBA",1-'Parametros'!E$7,1)) | J21: =SUMPRODUCT($AK21:$AS21,$AK$9:$AS$9)*IF($E21="CABA",'Parametros'!F$7,IF($E21="PBA",1-'Parametros'!F$7,1)) | K21: =SUMPRODUCT($AK21:$AS21,$AK$10:$AS$10)*IF($E21="CABA",'Parametros'!G$7,IF($E21="PBA",1-'Parametros'!G$7,1)) | L21: =SUMPRODUCT($AK21:$AS21,$AK$11:$AS$11)*IF($E21="CABA",'Parametros'!H$7,IF($E21="PBA",1-'Parametros'!H$7,1)) | M21: =SUMPRODUCT($AK21:$AS21,$AK$12:$AS$12)*IF($E21="CABA",'Parametros'!I$7,IF($E21="PBA",1-'Parametros'!I$7,1)) | N21: =SUMPRODUCT($AK21:$AS21,$AK$13:$AS$13)*IF($E21="CABA",'Parametros'!J$7,IF($E21="PBA",1-'Parametros'!J$7,1)) | O21: =SUMPRODUCT($AK21:$AS21,$AK$14:$AS$14)*IF($E21="CABA",'Parametros'!K$7,IF($E21="PBA",1-'Parametros'!K$7,1)) | AN21: 1
A22: Equipo terminado comprado (fabricante con Sello IRAM): FL_MAT_CLASED_9l | B22: u | C22: Equipo terminado comprado | D22: Matafuegos Georgia - venta mayorista | E22: Todos | F22: =SUMPRODUCT($AK22:$AS22,$AK$5:$AS$5)*IF($E22="CABA",'Parametros'!B$7,IF($E22="PBA",1-'Parametros'!B$7,1)) | G22: =SUMPRODUCT($AK22:$AS22,$AK$6:$AS$6)*IF($E22="CABA",'Parametros'!C$7,IF($E22="PBA",1-'Parametros'!C$7,1)) | H22: =SUMPRODUCT($AK22:$AS22,$AK$7:$AS$7)*IF($E22="CABA",'Parametros'!D$7,IF($E22="PBA",1-'Parametros'!D$7,1)) | I22: =SUMPRODUCT($AK22:$AS22,$AK$8:$AS$8)*IF($E22="CABA",'Parametros'!E$7,IF($E22="PBA",1-'Parametros'!E$7,1)) | J22: =SUMPRODUCT($AK22:$AS22,$AK$9:$AS$9)*IF($E22="CABA",'Parametros'!F$7,IF($E22="PBA",1-'Parametros'!F$7,1)) | K22: =SUMPRODUCT($AK22:$AS22,$AK$10:$AS$10)*IF($E22="CABA",'Parametros'!G$7,IF($E22="PBA",1-'Parametros'!G$7,1)) | L22: =SUMPRODUCT($AK22:$AS22,$AK$11:$AS$11)*IF($E22="CABA",'Parametros'!H$7,IF($E22="PBA",1-'Parametros'!H$7,1)) | M22: =SUMPRODUCT($AK22:$AS22,$AK$12:$AS$12)*IF($E22="CABA",'Parametros'!I$7,IF($E22="PBA",1-'Parametros'!I$7,1)) | N22: =SUMPRODUCT($AK22:$AS22,$AK$13:$AS$13)*IF($E22="CABA",'Parametros'!J$7,IF($E22="PBA",1-'Parametros'!J$7,1)) | O22: =SUMPRODUCT($AK22:$AS22,$AK$14:$AS$14)*IF($E22="CABA",'Parametros'!K$7,IF($E22="PBA",1-'Parametros'!K$7,1)) | AS22: 1
A23: Equipo terminado comprado (fabricante con Sello IRAM): FL_MAT_CO2_2kg | B23: u | C23: Equipo terminado comprado | D23: Mozart S.R.L. | E23: Todos | F23: =SUMPRODUCT($AK23:$AS23,$AK$5:$AS$5)*IF($E23="CABA",'Parametros'!B$7,IF($E23="PBA",1-'Parametros'!B$7,1)) | G23: =SUMPRODUCT($AK23:$AS23,$AK$6:$AS$6)*IF($E23="CABA",'Parametros'!C$7,IF($E23="PBA",1-'Parametros'!C$7,1)) | H23: =SUMPRODUCT($AK23:$AS23,$AK$7:$AS$7)*IF($E23="CABA",'Parametros'!D$7,IF($E23="PBA",1-'Parametros'!D$7,1)) | I23: =SUMPRODUCT($AK23:$AS23,$AK$8:$AS$8)*IF($E23="CABA",'Parametros'!E$7,IF($E23="PBA",1-'Parametros'!E$7,1)) | J23: =SUMPRODUCT($AK23:$AS23,$AK$9:$AS$9)*IF($E23="CABA",'Parametros'!F$7,IF($E23="PBA",1-'Parametros'!F$7,1)) | K23: =SUMPRODUCT($AK23:$AS23,$AK$10:$AS$10)*IF($E23="CABA",'Parametros'!G$7,IF($E23="PBA",1-'Parametros'!G$7,1)) | L23: =SUMPRODUCT($AK23:$AS23,$AK$11:$AS$11)*IF($E23="CABA",'Parametros'!H$7,IF($E23="PBA",1-'Parametros'!H$7,1)) | M23: =SUMPRODUCT($AK23:$AS23,$AK$12:$AS$12)*IF($E23="CABA",'Parametros'!I$7,IF($E23="PBA",1-'Parametros'!I$7,1)) | N23: =SUMPRODUCT($AK23:$AS23,$AK$13:$AS$13)*IF($E23="CABA",'Parametros'!J$7,IF($E23="PBA",1-'Parametros'!J$7,1)) | O23: =SUMPRODUCT($AK23:$AS23,$AK$14:$AS$14)*IF($E23="CABA",'Parametros'!K$7,IF($E23="PBA",1-'Parametros'!K$7,1)) | AP23: 1
A24: Equipo terminado comprado (fabricante con Sello IRAM): FL_MAT_CO2_5kg | B24: u | C24: Equipo terminado comprado | D24: Mozart S.R.L. | E24: Todos | F24: =SUMPRODUCT($AK24:$AS24,$AK$5:$AS$5)*IF($E24="CABA",'Parametros'!B$7,IF($E24="PBA",1-'Parametros'!B$7,1)) | G24: =SUMPRODUCT($AK24:$AS24,$AK$6:$AS$6)*IF($E24="CABA",'Parametros'!C$7,IF($E24="PBA",1-'Parametros'!C$7,1)) | H24: =SUMPRODUCT($AK24:$AS24,$AK$7:$AS$7)*IF($E24="CABA",'Parametros'!D$7,IF($E24="PBA",1-'Parametros'!D$7,1)) | I24: =SUMPRODUCT($AK24:$AS24,$AK$8:$AS$8)*IF($E24="CABA",'Parametros'!E$7,IF($E24="PBA",1-'Parametros'!E$7,1)) | J24: =SUMPRODUCT($AK24:$AS24,$AK$9:$AS$9)*IF($E24="CABA",'Parametros'!F$7,IF($E24="PBA",1-'Parametros'!F$7,1)) | K24: =SUMPRODUCT($AK24:$AS24,$AK$10:$AS$10)*IF($E24="CABA",'Parametros'!G$7,IF($E24="PBA",1-'Parametros'!G$7,1)) | L24: =SUMPRODUCT($AK24:$AS24,$AK$11:$AS$11)*IF($E24="CABA",'Parametros'!H$7,IF($E24="PBA",1-'Parametros'!H$7,1)) | M24: =SUMPRODUCT($AK24:$AS24,$AK$12:$AS$12)*IF($E24="CABA",'Parametros'!I$7,IF($E24="PBA",1-'Parametros'!I$7,1)) | N24: =SUMPRODUCT($AK24:$AS24,$AK$13:$AS$13)*IF($E24="CABA",'Parametros'!J$7,IF($E24="PBA",1-'Parametros'!J$7,1)) | O24: =SUMPRODUCT($AK24:$AS24,$AK$14:$AS$14)*IF($E24="CABA",'Parametros'!K$7,IF($E24="PBA",1-'Parametros'!K$7,1)) | AQ24: 1
A25: Equipo terminado comprado (fabricante con Sello IRAM): FL_MAT_HCFC-HFC_5kg | B25: u | C25: Equipo terminado comprado | D25: Matafuegos Georgia - venta mayorista | E25: Todos | F25: =SUMPRODUCT($AK25:$AS25,$AK$5:$AS$5)*IF($E25="CABA",'Parametros'!B$7,IF($E25="PBA",1-'Parametros'!B$7,1)) | G25: =SUMPRODUCT($AK25:$AS25,$AK$6:$AS$6)*IF($E25="CABA",'Parametros'!C$7,IF($E25="PBA",1-'Parametros'!C$7,1)) | H25: =SUMPRODUCT($AK25:$AS25,$AK$7:$AS$7)*IF($E25="CABA",'Parametros'!D$7,IF($E25="PBA",1-'Parametros'!D$7,1)) | I25: =SUMPRODUCT($AK25:$AS25,$AK$8:$AS$8)*IF($E25="CABA",'Parametros'!E$7,IF($E25="PBA",1-'Parametros'!E$7,1)) | J25: =SUMPRODUCT($AK25:$AS25,$AK$9:$AS$9)*IF($E25="CABA",'Parametros'!F$7,IF($E25="PBA",1-'Parametros'!F$7,1)) | K25: =SUMPRODUCT($AK25:$AS25,$AK$10:$AS$10)*IF($E25="CABA",'Parametros'!G$7,IF($E25="PBA",1-'Parametros'!G$7,1)) | L25: =SUMPRODUCT($AK25:$AS25,$AK$11:$AS$11)*IF($E25="CABA",'Parametros'!H$7,IF($E25="PBA",1-'Parametros'!H$7,1)) | M25: =SUMPRODUCT($AK25:$AS25,$AK$12:$AS$12)*IF($E25="CABA",'Parametros'!I$7,IF($E25="PBA",1-'Parametros'!I$7,1)) | N25: =SUMPRODUCT($AK25:$AS25,$AK$13:$AS$13)*IF($E25="CABA",'Parametros'!J$7,IF($E25="PBA",1-'Parametros'!J$7,1)) | O25: =SUMPRODUCT($AK25:$AS25,$AK$14:$AS$14)*IF($E25="CABA",'Parametros'!K$7,IF($E25="PBA",1-'Parametros'!K$7,1)) | AR25: 1
A26: Equipo terminado comprado (fabricante con Sello IRAM): FL_MAT_SALESK_6l | B26: u | C26: Equipo terminado comprado | D26: Matafuegos Georgia - venta mayorista | E26: Todos | F26: =SUMPRODUCT($AK26:$AS26,$AK$5:$AS$5)*IF($E26="CABA",'Parametros'!B$7,IF($E26="PBA",1-'Parametros'!B$7,1)) | G26: =SUMPRODUCT($AK26:$AS26,$AK$6:$AS$6)*IF($E26="CABA",'Parametros'!C$7,IF($E26="PBA",1-'Parametros'!C$7,1)) | H26: =SUMPRODUCT($AK26:$AS26,$AK$7:$AS$7)*IF($E26="CABA",'Parametros'!D$7,IF($E26="PBA",1-'Parametros'!D$7,1)) | I26: =SUMPRODUCT($AK26:$AS26,$AK$8:$AS$8)*IF($E26="CABA",'Parametros'!E$7,IF($E26="PBA",1-'Parametros'!E$7,1)) | J26: =SUMPRODUCT($AK26:$AS26,$AK$9:$AS$9)*IF($E26="CABA",'Parametros'!F$7,IF($E26="PBA",1-'Parametros'!F$7,1)) | K26: =SUMPRODUCT($AK26:$AS26,$AK$10:$AS$10)*IF($E26="CABA",'Parametros'!G$7,IF($E26="PBA",1-'Parametros'!G$7,1)) | L26: =SUMPRODUCT($AK26:$AS26,$AK$11:$AS$11)*IF($E26="CABA",'Parametros'!H$7,IF($E26="PBA",1-'Parametros'!H$7,1)) | M26: =SUMPRODUCT($AK26:$AS26,$AK$12:$AS$12)*IF($E26="CABA",'Parametros'!I$7,IF($E26="PBA",1-'Parametros'!I$7,1)) | N26: =SUMPRODUCT($AK26:$AS26,$AK$13:$AS$13)*IF($E26="CABA",'Parametros'!J$7,IF($E26="PBA",1-'Parametros'!J$7,1)) | O26: =SUMPRODUCT($AK26:$AS26,$AK$14:$AS$14)*IF($E26="CABA",'Parametros'!K$7,IF($E26="PBA",1-'Parametros'!K$7,1)) | AO26: 1

Sheet MP_CILINDROS
A1: Requerimiento de MP — cilindros sueltos FL_REC (venta)
A2: Recipiente, tapón, etiqueta, protocolo y embalaje.
AJ4: Demanda (u) → | AK4: REC ABC_1kg | AL4: REC ABC_2.5kg | AM4: REC ABC_5kg | AN4: REC ABC_10kg | AO4: REC ABC_25kg | AP4: REC ABC_50kg | AQ4: REC ABC_70kg | AR4: REC ABC_100kg
AJ5: ='Demanda'!B3 | AK5: ='Demanda'!B27 | AL5: ='Demanda'!B28 | AM5: ='Demanda'!B29 | AN5: ='Demanda'!B30 | AO5: ='Demanda'!B31 | AP5: ='Demanda'!B32 | AQ5: ='Demanda'!B33 | AR5: ='Demanda'!B34
AJ6: ='Demanda'!C3 | AK6: ='Demanda'!C27 | AL6: ='Demanda'!C28 | AM6: ='Demanda'!C29 | AN6: ='Demanda'!C30 | AO6: ='Demanda'!C31 | AP6: ='Demanda'!C32 | AQ6: ='Demanda'!C33 | AR6: ='Demanda'!C34
AJ7: ='Demanda'!D3 | AK7: ='Demanda'!D27 | AL7: ='Demanda'!D28 | AM7: ='Demanda'!D29 | AN7: ='Demanda'!D30 | AO7: ='Demanda'!D31 | AP7: ='Demanda'!D32 | AQ7: ='Demanda'!D33 | AR7: ='Demanda'!D34
AJ8: ='Demanda'!E3 | AK8: ='Demanda'!E27 | AL8: ='Demanda'!E28 | AM8: ='Demanda'!E29 | AN8: ='Demanda'!E30 | AO8: ='Demanda'!E31 | AP8: ='Demanda'!E32 | AQ8: ='Demanda'!E33 | AR8: ='Demanda'!E34
AJ9: ='Demanda'!F3 | AK9: ='Demanda'!F27 | AL9: ='Demanda'!F28 | AM9: ='Demanda'!F29 | AN9: ='Demanda'!F30 | AO9: ='Demanda'!F31 | AP9: ='Demanda'!F32 | AQ9: ='Demanda'!F33 | AR9: ='Demanda'!F34
AJ10: ='Demanda'!G3 | AK10: ='Demanda'!G27 | AL10: ='Demanda'!G28 | AM10: ='Demanda'!G29 | AN10: ='Demanda'!G30 | AO10: ='Demanda'!G31 | AP10: ='Demanda'!G32 | AQ10: ='Demanda'!G33 | AR10: ='Demanda'!G34
AJ11: ='Demanda'!H3 | AK11: ='Demanda'!H27 | AL11: ='Demanda'!H28 | AM11: ='Demanda'!H29 | AN11: ='Demanda'!H30 | AO11: ='Demanda'!H31 | AP11: ='Demanda'!H32 | AQ11: ='Demanda'!H33 | AR11: ='Demanda'!H34
AJ12: ='Demanda'!I3 | AK12: ='Demanda'!I27 | AL12: ='Demanda'!I28 | AM12: ='Demanda'!I29 | AN12: ='Demanda'!I30 | AO12: ='Demanda'!I31 | AP12: ='Demanda'!I32 | AQ12: ='Demanda'!I33 | AR12: ='Demanda'!I34
AJ13: ='Demanda'!J3 | AK13: ='Demanda'!J27 | AL13: ='Demanda'!J28 | AM13: ='Demanda'!J29 | AN13: ='Demanda'!J30 | AO13: ='Demanda'!J31 | AP13: ='Demanda'!J32 | AQ13: ='Demanda'!J33 | AR13: ='Demanda'!J34
AJ14: ='Demanda'!K3 | AK14: ='Demanda'!K27 | AL14: ='Demanda'!K28 | AM14: ='Demanda'!K29 | AN14: ='Demanda'!K30 | AO14: ='Demanda'!K31 | AP14: ='Demanda'!K32 | AQ14: ='Demanda'!K33 | AR14: ='Demanda'!K34
A16: Ítem | B16: UM | C16: Rubro | D16: Proveedor principal | E16: Destino | F16: ='Demanda'!B3 | G16: ='Demanda'!C3 | H16: ='Demanda'!D3 | I16: ='Demanda'!E3 | J16: ='Demanda'!F3 | K16: ='Demanda'!G3 | L16: ='Demanda'!H3 | M16: ='Demanda'!I3 | ... O16: ='Demanda'!K3 | AK16: coef. REC ABC_1kg | AL16: coef. REC ABC_2.5kg | AM16: coef. REC ABC_5kg | AN16: coef. REC ABC_10kg | AO16: coef. REC ABC_25kg | AP16: coef. REC ABC_50kg | AQ16: coef. REC ABC_70kg | AR16: coef. REC ABC_100kg
A17: Caño Ø76,2 × 1,25 | B17: barra 6 m | C17: Materia prima | D17: Metalpri / Prilux | E17: Todos | F17: =SUMPRODUCT($AK17:$AR17,$AK$5:$AR$5)*IF($E17="CABA",'Parametros'!B$7,IF($E17="PBA",1-'Parametros'!B$7,1)) | G17: =SUMPRODUCT($AK17:$AR17,$AK$6:$AR$6)*IF($E17="CABA",'Parametros'!C$7,IF($E17="PBA",1-'Parametros'!C$7,1)) | H17: =SUMPRODUCT($AK17:$AR17,$AK$7:$AR$7)*IF($E17="CABA",'Parametros'!D$7,IF($E17="PBA",1-'Parametros'!D$7,1)) | I17: =SUMPRODUCT($AK17:$AR17,$AK$8:$AR$8)*IF($E17="CABA",'Parametros'!E$7,IF($E17="PBA",1-'Parametros'!E$7,1)) | J17: =SUMPRODUCT($AK17:$AR17,$AK$9:$AR$9)*IF($E17="CABA",'Parametros'!F$7,IF($E17="PBA",1-'Parametros'!F$7,1)) | K17: =SUMPRODUCT($AK17:$AR17,$AK$10:$AR$10)*IF($E17="CABA",'Parametros'!G$7,IF($E17="PBA",1-'Parametros'!G$7,1)) | L17: =SUMPRODUCT($AK17:$AR17,$AK$11:$AR$11)*IF($E17="CABA",'Parametros'!H$7,IF($E17="PBA",1-'Parametros'!H$7,1)) | M17: =SUMPRODUCT($AK17:$AR17,$AK$12:$AR$12)*IF($E17="CABA",'Parametros'!I$7,IF($E17="PBA",1-'Parametros'!I$7,1)) | N17: =SUMPRODUCT($AK17:$AR17,$AK$13:$AR$13)*IF($E17="CABA",'Parametros'!J$7,IF($E17="PBA",1-'Parametros'!J$7,1)) | O17: =SUMPRODUCT($AK17:$AR17,$AK$14:$AR$14)*IF($E17="CABA",'Parametros'!K$7,IF($E17="PBA",1-'Parametros'!K$7,1)) | AK17: 0.0435
A18: Chapa LAC 1500 × 3000 e=3,2 | B18: kg | C18: Materia prima | D18: Pradecon S.A. | E18: Todos | F18: =SUMPRODUCT($AK18:$AR18,$AK$5:$AR$5)*IF($E18="CABA",'Parametros'!B$7,IF($E18="PBA",1-'Parametros'!B$7,1)) | G18: =SUMPRODUCT($AK18:$AR18,$AK$6:$AR$6)*IF($E18="CABA",'Parametros'!C$7,IF($E18="PBA",1-'Parametros'!C$7,1)) | H18: =SUMPRODUCT($AK18:$AR18,$AK$7:$AR$7)*IF($E18="CABA",'Parametros'!D$7,IF($E18="PBA",1-'Parametros'!D$7,1)) | I18: =SUMPRODUCT($AK18:$AR18,$AK$8:$AR$8)*IF($E18="CABA",'Parametros'!E$7,IF($E18="PBA",1-'Parametros'!E$7,1)) | J18: =SUMPRODUCT($AK18:$AR18,$AK$9:$AR$9)*IF($E18="CABA",'Parametros'!F$7,IF($E18="PBA",1-'Parametros'!F$7,1)) | K18: =SUMPRODUCT($AK18:$AR18,$AK$10:$AR$10)*IF($E18="CABA",'Parametros'!G$7,IF($E18="PBA",1-'Parametros'!G$7,1)) | L18: =SUMPRODUCT($AK18:$AR18,$AK$11:$AR$11)*IF($E18="CABA",'Parametros'!H$7,IF($E18="PBA",1-'Parametros'!H$7,1)) | M18: =SUMPRODUCT($AK18:$AR18,$AK$12:$AR$12)*IF($E18="CABA",'Parametros'!I$7,IF($E18="PBA",1-'Parametros'!I$7,1)) | N18: =SUMPRODUCT($AK18:$AR18,$AK$13:$AR$13)*IF($E18="CABA",'Parametros'!J$7,IF($E18="PBA",1-'Parametros'!J$7,1)) | O18: =SUMPRODUCT($AK18:$AR18,$AK$14:$AR$14)*IF($E18="CABA",'Parametros'!K$7,IF($E18="PBA",1-'Parametros'!K$7,1)) | AO18: 12.558 | AP18: 18.845
