Workbook

Sheet 01_Indice
A1: FLAMA S.A. - Lista de materiales (BOM) de matafuegos, cilindros, sustitutos y recargas
A3: Origen | B3: Generado por código (python generar.py --bom) a partir del mismo modelo 3D que los planos FL_MAT, FL_REC, FL_DES y FL_SUS: código, posición, denominación y material de cada pieza son los del plano; medida y peso se miden sobre el sólido.
A4: Alcance | B4: 17 matafuegos FL_MAT (8 de fabricación propia ABC y 9 revendidos), 8 cilindros sueltos FL_REC, 17 extintores sustitutos FL_SUS y los kits de recarga RK por extintor y caso.
A5: Niveles | B5: 0 producto (= plano) · 1 subconjunto · 2 pieza o insumo · 3 materia prima de la pieza fabricada (cursiva; no suma al peso porque ya está en la pieza).
A6: Subconjuntos | B6: S1 Recipiente (cilindro) · S2 Conjunto de válvula · S3 Dispositivo de descarga · S4 Carro (tren rodante soldado y ruedas) · S5 Carga: agente extintor y gas impulsor · S6 Identificación y precinto · S7 Embalaje · S8 Soporte (accesorio de montaje) · S0 Equipo terminado comprado (revendidos). En los ABC el S1 es el plano FL_REC (el mismo recipiente que se vende suelto).
A7: Entra MRP | B7: Sí = se compra (materia prima, componente, consumible, servicio, agente, gas, identificación, embalaje). No = se fabrica (se explota en su materia prima), viene dentro de un conjunto comprado o es un proceso. Revendidos: sólo S0 (y la tarjeta AGC si va a CABA). Cilindros: materia prima del recipiente, tapón, etiqueta y embalaje. Sustitutos: sólo el kit de identificación. Recargas: todo lo que se repone.
A8: Códigos | B8: ABC10-01… pieza del plano (posición 01) · ABC10-S1…S8 subconjuntos · K2 válvula HZ armada · C consumible del recipiente · V interno de válvula · A carga · I soporte · E embalaje · T cilindro suelto · MP-* materia prima · SUS-* sustituto · RK-*-A/B/C kits de recarga.
A9: Peso | B9: kg por unidad de medida. Peso total = Cant. × Peso unit. (fórmula). Subconjunto = suma de sus piezas. Componentes comprados sin ficha quedan sin peso (fila naranja).
A10: Fuente P | B10: Plano / modelo 3D (misma geometría que el plano FL_MAT / FL_REC)
A11: Fuente C | B11: Cálculo declarado con datos del plano, de la norma o de una fuente técnica (fórmula en Medida u Observaciones)
A12: Fuente N | B12: Norma IRAM o resolución (se cita el apartado; texto no transcripto por licencia)
A13: Fuente L | B13: Layout de planta FLAMA (FL_PI_04) cruzado con la cotización de chapa (Pacheco / Pradecon)
A14: Fuente Q | B14: Cotización o ficha técnica recibida del proveedor (ver 11_Validacion_MP)
... A17: Normas | B17: IRAM 3517-2:2020 y las IRAM de producto citadas; resoluciones PBA y CABA. Los PDF de las normas tienen licencia monousuario: se citan apartados, no se transcribe texto.
A19: Colores de estado
A20: Sin color | B20: Validado: especificación respaldada por plano, norma, cotización o proveedor nacional con el producto exacto (la falta de precio no cambia el color: ver 10_Proveedores)
A21: Amarillo | B21: Estimado: valor justificado con norma o fuente técnica citada, sin medición ni cotización propia (corregir con dato real)
A22: Naranja | B22: A validar: falta el dato, la cotización o la confirmación del proveedor
A23: Rojo | B23: No cumple o decisión pendiente: contradicción con la norma, con el plano o sin proveedor nacional
A25: Hojas
A26: 02_Decisiones | B26: Decisiones de diseño y abastecimiento con su fundamento
A27: 03_Resumen_Productos | B27: Una fila por matafuego: agente, carga, gas, pesos, desvío contra catálogo, ítems en MRP
A28: 04_BOM_Matafuegos | B28: BOM de los 17 matafuegos en tabla plana filtrable
A29: 05_BOM_Cilindros | B29: BOM de los 8 cilindros sueltos FL_REC
A30: 06_BOM_Sustitutos | B30: BOM unitario de los extintores sustitutos FL_SUS
A31: 07_BOM_Recargas | B31: Kits de recarga por extintor y por caso (IRAM 3517-2:2020)
A32: 08_Quimica_Agentes | B32: Química y densidades de los agentes (entrada de 09_Carga_N2)
A33: 09_Carga_N2 | B33: Volumen libre, gas impulsor y control de llenado por modelo
A34: 10_Proveedores | B34: Proveedores nacionales por ítem (principal y alternativa) y directorio
A35: 11_Validacion_MP | B35: Respaldo documental y estado de cada materia prima y componente
A36: 12_Maestro_Consolidado_MP | B36: Maestro consolidado: todo lo que lleva cada matafuego, cilindro, sustituto y kit de recarga, por unidad, más los insumos de cada proceso (base del archivo MRP_MATERIA_PRIMA)
A37: 13_Fuentes | B37: Documentos y fuentes técnicas citadas
... A40: BOM_FL_MAT_* / BOM_FL_REC_* | B40: Una hoja por plano con el BOM multinivel plegable (links en 03_Resumen_Productos y 15_Indice_Planos)

Sheet 02_Decisiones
A1: Decisiones de diseño y abastecimiento que estructuran el BOM
A2: Colores: | B2: Validado | D2: Estimado | F2: A validar | H2: No cumple o decisión pendiente
A4: N° | B4: Tema | C4: Decisión adoptada | D4: Fundamento (norma / fuente) | E4: Impacto en el BOM
A5: 1 | B5: Fabricación propia | C5: Se fabrican sólo los ABC (1 a 100 kg). BC, clase D, agua, AFFF, sales K, CO₂ y HCFC se compran terminados y se revenden. | D5: Decisión FLAMA | E5: Revendidos: BOM completo de referencia; en MRP sólo la fila S0 «Equipo terminado comprado» (más la tarjeta AGC si el destino es CABA).
A6: 2 | B6: Alcance del MRP | C6: El BOM se arma completo; la columna «Entra MRP» marca lo que se compra. Lo fabricado se explota en su materia prima; lo que viene dentro de un conjunto comprado (válvula HZ, rueda) no se pide aparte. | D6: Decisión FLAMA | E6: 12_Maestro_Consolidado_MP trae todo por producto con la marca Entra MRP. El MRP por año (MRP_MATERIA_PRIMA) va en otro archivo.
A7: 3 | B7: Polvo ABC | C7: DEMSA principal (DEM-60 / DEM-90 según modelo). Polvex / Sancibrao alternativa. | D7: IRAM 3569 (composición declarada por el fabricante del polvo); licencia IRAM 3523 Drago: potencial de referencia con DEM-60/90; Polvex: sello IRAM 3569 no confirmado | E7: Con la alternativa el potencial sale del ensayo de tipo de FLAMA (IRAM 3542 / 3543).
A8: 4 | B8: Densidad del polvo | C8: Volumen libre con densidad empacada mínima 1,10 kg/dm³; llenado controlado con aparente mínima. | D8: NOM-104-STPS-2001 (IRAM 3569 no fija densidad); criterio de aceptación: descarga ≥ 85 % (IRAM 3523 4.9.1) | E8: 09_Carga_N2 y fila A2 (N₂) en amarillo hasta el ensayo de descarga.
A9: 5 | B9: Soldadura | C9: MAG 135 con Arcal 21 / ARCAL Speed (Ar + 8 % CO₂, M20) y alambre ER70S-6. | D9: Decisión FLAMA. IRAM 3523 3.2.4.2 y 3550 3.2.2.2 nombran «atmósfera inerte»: acreditar con el certificador en el ensayo de tipo (probetas IRAM 609 y PH) | E9: Consumos C1 y C2 calculados por longitud de cordón; planos con símbolo 135.
A10: 6 | B10: Placas de refuerzo | C10: 70 y 100 kg: dos placas 200 × 100 × 4,75 curvadas a Ø380, por dentro sobre la costura longitudinal, una en cada extremo a 100 mm de la boca; salen de las orillas de 4,75. | D10: Proceso FLAMA de carros (corte, cilindrado y punteo) | E10: Pieza en S1 (planos FL_MAT, FL_REC y FL_DES 70/100).
A11: 7 | B11: Carro de rodantes | C11: Accesorios soldados al recipiente antes de la PH: dos triángulos con V (chapa 4,75) con el caño del eje 1" / 1¼" × 2,0 apoyado, manija de caño 1" × 2,0 con lengüetas aplastadas 40 × 60, dos flejes del soporte de manga y pata delantera; eje, ruedas, arandelas y pasadores al montaje final. | D11: Proceso FLAMA de carros v2 (puesto 8 y kit del 8.1, tabla de posiciones); IRAM 3550 6.1.1, 3.8.2, 3.12.3 y 4.8.2 | E11: Medidas y posiciones del proceso; kit 2,8-3,7 kg (proceso: 2,9-3,8).
A12: 8 | B12: Tapas de rodantes | C12: Casquetes de 25, 50, 70 y 100 kg embutidos por Gockel Ingeniería (Wilde, Avellaneda). | D12: IRAM 3550 3.2.1 / 4.1.3; proveedor de FLAMA | E12: Ítem comprado (semielaborado); cotizar con certificado de material.
A13: 9 | B13: Pintura | C13: Tercerizada (Prymax manuales, pintor de carros rodantes). | D13: Res. 349/07 art. 18: la cabina de pintura figura en el equipamiento del fabricante; la tercerización queda sujeta a la aceptación del Ministerio | E13: C4 servicio por unidad.
A14: 10 | B14: Granallado | C14: Manuales en Airblast G-100 (Ø80-200). | D14: Ficha del equipo | E14: 1 kg (Ø76,2) fuera de rango: fila C3 en rojo hasta definir soporte o equipo.
A15: 11 | B15: Proveedores | C15: Sólo nacionales y cercanos o razonables para Avellaneda; principal + alternativa. | D15: Decisión FLAMA | E15: Columnas Proveedor principal / Alternativa y hoja 10_Proveedores.
A16: 12 | B16: Inoxidables revendidos | C16: Agua, AFFF 10 L y sales K: recipiente inoxidable soldado (no sin costura), TIG con Ar puro. | D16: IRAM 3525 3.2.1 b) y 3.2.2 (≤ 1 longitudinal + 2 transversales, proceso automático, atmósfera inerte); IRAM 3517-2 9.4.21 (sales K en inoxidable); mercado: «recipiente inoxidable soldado, PH 100 %» | E16: Referencia (revendidos). Proceso exacto (TIG / plasma / láser) no publicado por los fabricantes.
... A18: 14 | B18: Sustitutos | C18: Extintor del stock + faja amarilla ≤ 40 mm + tarjeta DPS «sustituto habilitado» + tarjeta AGC «Es sustituto». | D18: IRAM 3517-2:2020 9.4.5; Res. 349/07 art. 32; Res. AGC 32/15 | E18: 06_BOM_Sustitutos (unitario; el tamaño del parque se dimensiona aparte).

Sheet 03_Resumen_Productos
A1: Plano | B1: Producto | C1: Familia | D1: Fabricación | E1: Norma IRAM | F1: Agente | G1: Carga | H1: UM | I1: Gas impulsor | J1: Gas (kg) | K1: Peso vacío S1-S4 (kg) | L1: Peso cargado (kg) | M1: Peso de referencia (kg) | N1: Desvío | O1: Piezas del plano | P1: Ítems BOM | Q1: Ítems que entran en MRP | R1: Recipiente suelto | S1: Hoja BOM | T1: Tara de referencia (kg) = referencia - carga - gas | U1: Desvío de tara (modelo vs referencia) | V1: Fuente del peso de referencia
A2: FL_MAT_ABC_1kg | B2: Extintor ABC 1 kg | C2: manual | D2: Propia | E2: 3523 | F2: Polvo químico seco ABC (fosfato monoamónico) | G2: 1.05 | H2: kg | I2: N₂ | J2: 0.0047 | K2: ='BOM_FL_MAT_ABC_1kg'!G3 | L2: ='BOM_FL_MAT_ABC_1kg'!G4 | M2: 1.84 | N2: =L2/M2-1 | O2: 23 | P2: 51 | Q2: 28 | R2: FL_REC_ABC_1kg | S2: ir » | T2: =M2-1.05-J2 | U2: =(L2-1.05-J2)/T2-1 | V2: Plano Fadesa «Extintor 1 kg Ø76 (válvula HZ) R1»
A3: FL_MAT_ABC_2.5kg | B3: Extintor ABC 2,5 kg | C3: manual | D3: Propia | E3: 3523 | F3: Polvo químico seco ABC (fosfato monoamónico) | G3: 2.55 | H3: kg | I3: N₂ | J3: 0.0212 | K3: ='BOM_FL_MAT_ABC_2.5kg'!G3 | L3: ='BOM_FL_MAT_ABC_2.5kg'!G4 | M3: 4.62 | N3: =L3/M3-1 | O3: 27 | P3: 57 | Q3: 34 | R3: FL_REC_ABC_2.5kg | S3: ir » | T3: =M3-2.55-J3 | U3: =(L3-2.55-J3)/T3-1 | V3: Plano Fadesa «Extintor 2,5 kg válvula HZ R1»
A4: FL_MAT_ABC_5kg | B4: Extintor ABC 5 kg | C4: manual | D4: Propia | E4: 3523 | F4: Polvo químico seco ABC (fosfato monoamónico) | G4: 5.15 | H4: kg | I4: N₂ | J4: 0.0251 | K4: ='BOM_FL_MAT_ABC_5kg'!G3 | L4: ='BOM_FL_MAT_ABC_5kg'!G4 | M4: 8.4 | N4: =L4/M4-1 | O4: 27 | P4: 57 | Q4: 34 | R4: FL_REC_ABC_5kg | S4: ir » | T4: =M4-5.15-J4 | U4: =(L4-5.15-J4)/T4-1 | V4: Plano Fadesa «Extintor 5 kg válvula HZ R1»
A5: FL_MAT_ABC_10kg | B5: Extintor ABC 10 kg | C5: manual | D5: Propia | E5: 3523 | F5: Polvo químico seco ABC (fosfato monoamónico) | G5: 10.15 | H5: kg | I5: N₂ | J5: 0.0588 | K5: ='BOM_FL_MAT_ABC_10kg'!G3 | L5: ='BOM_FL_MAT_ABC_10kg'!G4 | M5: 16.4 | N5: =L5/M5-1 | O5: 27 | P5: 57 | Q5: 34 | R5: FL_REC_ABC_10kg | S5: ir » | T5: =M5-10.15-J5 | U5: =(L5-10.15-J5)/T5-1 | V5: Plano Fadesa «Extintor 10 kg HZ R1»
A6: FL_MAT_AGUA_10l | B6: Extintor Agua 10 l | C6: inox | D6: Revendido | E6: 3525 | F6: Agua | G6: 10 | H6: L | I6: Aire comprimido | J6: 0.0427 | K6: ='BOM_FL_MAT_AGUA_10l'!G3 | L6: ='BOM_FL_MAT_AGUA_10l'!G4 | M6: 12.55 | N6: =L6/M6-1 | O6: 28 | P6: 50 | Q6: 2 | R6: - | S6: ir » | T6: =M6-10.0-J6 | U6: =(L6-10.0-J6)/T6-1 | V6: Catálogo Fadesa 3 (repite pesos entre tablas: sólo orientativo)
A7: FL_MAT_AFFF_10l | B7: Extintor AFFF 10 l | C7: inox | D7: Revendido | E7: 3527 | F7: Agua + espumígeno AFFF 3 % (DEMSA 203 MN, IRAM 3515) | G7: 10 | H7: L | I7: Aire comprimido | J7: 0.0427 | K7: ='BOM_FL_MAT_AFFF_10l'!G3 | L7: ='BOM_FL_MAT_AFFF_10l'!G4 | M7: 12.6 | N7: =L7/M7-1 | O7: 28 | P7: 51 | Q7: 2 | R7: - | S7: ir » | T7: =M7-10.0-J7 | U7: =(L7-10.0-J7)/T7-1 | V7: Catálogo Fadesa 3 (repite pesos entre tablas: sólo orientativo)
A8: FL_MAT_AFFF_50l | B8: Extintor AFFF 50 l sobre ruedas | C8: rodante | D8: Revendido | E8: 3541 | F8: Agua + espumígeno AFFF 3 % (DEMSA 203 MN, IRAM 3515) | G8: 50 | H8: L | I8: Aire comprimido | J8: 0.1265 | K8: ='BOM_FL_MAT_AFFF_50l'!G3 | L8: ='BOM_FL_MAT_AFFF_50l'!G4 | M8: 100 | N8: =L8/M8-1 | O8: 37 | P8: 55 | Q8: 2 | R8: - | S8: ir » | T8: =M8-50.0-J8 | U8: =(L8-50.0-J8)/T8-1 | V8: Catálogo Fadesa 3 (repite pesos entre tablas: sólo orientativo)
A9: FL_MAT_BC_5kg | B9: Extintor BC 5 kg | C9: manual | D9: Revendido | E9: 3523 | F9: Polvo químico seco BC (bicarbonato) | G9: 5.15 | H9: kg | I9: N₂ | J9: 0.0077 | K9: ='BOM_FL_MAT_BC_5kg'!G3 | L9: ='BOM_FL_MAT_BC_5kg'!G4 | M9: 8.5 | N9: =L9/M9-1 | O9: 27 | P9: 50 | Q9: 2 | R9: - | S9: ir » | T9: =M9-5.15-J9 | U9: =(L9-5.15-J9)/T9-1 | V9: Catálogo Fadesa 3 (repite pesos entre tablas: sólo orientativo)
A10: FL_MAT_SALESK_6l | B10: Extintor Sales K 6 l | C10: inox | D10: Revendido | E10: 3694 | F10: Acetato de potasio - DEMSA Kitchen (IRAM 3697) | G10: 6.09 | H10: L | I10: N₂ | J10: 0.0306 | K10: ='BOM_FL_MAT_SALESK_6l'!G3 | L10: ='BOM_FL_MAT_SALESK_6l'!G4 | M10: 9.5 | N10: =L10/M10-1 | O10: 28 | P10: 50 | Q10: 2 | R10: - | S10: ir » | T10: =M10-7.8-J10 | U10: =(L10-7.8-J10)/T10-1 | V10: Ficha técnica Melisam acetato 6 L
A11: FL_MAT_CO2_2kg | B11: Extintor CO₂ 2 kg | C11: co2 | D11: Revendido | E11: 3509 | F11: Dióxido de carbono (IRAM 41170) | G11: 2 | H11: kg | I11: - (autopresurizado) | K11: ='BOM_FL_MAT_CO2_2kg'!G3 | L11: ='BOM_FL_MAT_CO2_2kg'!G4 | M11: 9 | N11: =L11/M11-1 | O11: 24 | P11: 44 | Q11: 2 | R11: - | S11: ir » | T11: =M11-2.0 | U11: =(L11-2.0)/T11-1 | V11: Catálogo Fadesa 3 (repite pesos entre tablas: sólo orientativo)
A12: FL_MAT_CO2_5kg | B12: Extintor CO₂ 5 kg | C12: co2 | D12: Revendido | E12: 3509 | F12: Dióxido de carbono (IRAM 41170) | G12: 5 | H12: kg | I12: - (autopresurizado) | K12: ='BOM_FL_MAT_CO2_5kg'!G3 | L12: ='BOM_FL_MAT_CO2_5kg'!G4 | M12: 20 | N12: =L12/M12-1 | O12: 26 | P12: 46 | Q12: 2 | R12: - | S12: ir » | T12: =M12-5.0 | U12: =(L12-5.0)/T12-1 | V12: Catálogo Fadesa 3 (repite pesos entre tablas: sólo orientativo)
A13: FL_MAT_HCFC-HFC_5kg | B13: Extintor HCFC/HFC 5 kg | C13: manual | D13: Revendido | E13: 3504 | F13: HCFC 123 / HFC 236fa (agente limpio) | G13: 5 | H13: kg | I13: Argón | J13: 0.0388 | K13: ='BOM_FL_MAT_HCFC-HFC_5kg'!G3 | L13: ='BOM_FL_MAT_HCFC-HFC_5kg'!G4 | M13: 8.5 | N13: =L13/M13-1 | O13: 27 | P13: 50 | Q13: 2 | R13: - | S13: ir » | T13: =M13-5.0-J13 | U13: =(L13-5.0-J13)/T13-1 | V13: Catálogo Fadesa 3 (repite pesos entre tablas: sólo orientativo)
A14: FL_MAT_CLASED_9l | B14: Extintor Clase D 9 l | C14: manual | D14: Revendido | E14: 3523 | F14: Polvo para metales combustibles clase D | G14: 9.15 | H14: kg | I14: N₂ | J14: 0.0604 | K14: ='BOM_FL_MAT_CLASED_9l'!G3 | L14: ='BOM_FL_MAT_CLASED_9l'!G4 | M14: 16.5 | N14: =L14/M14-1 | O14: 28 | P14: 50 | Q14: 2 | R14: - | S14: ir » | T14: =M14-9.15-J14 | U14: =(L14-9.15-J14)/T14-1 | V14: Catálogo Fadesa 3 (repite pesos entre tablas: sólo orientativo)
A15: FL_MAT_ABC_25kg | B15: Extintor ABC 25 kg sobre ruedas | C15: rodante | D15: Propia | E15: 3550 | F15: Polvo químico seco ABC (fosfato monoamónico) | G15: 25 | H15: kg | I15: N₂ | J15: 0.2013 | K15: ='BOM_FL_MAT_ABC_25kg'!G3 | L15: ='BOM_FL_MAT_ABC_25kg'!G4 | M15: 53.2 | N15: =L15/M15-1 | O15: 38 | P15: 62 | Q15: 34 | R15: FL_REC_ABC_25kg | S15: ir » | T15: =M15-25.0-J15 | U15: =(L15-25.0-J15)/T15-1 | V15: Plano Fadesa «Extintor rodante 25 kg R1»
A16: FL_MAT_ABC_50kg | B16: Extintor ABC 50 kg sobre ruedas | C16: rodante | D16: Propia | E16: 3550 | F16: Polvo químico seco ABC (fosfato monoamónico) | G16: 50 | H16: kg | I16: N₂ | J16: 0.2819 | K16: ='BOM_FL_MAT_ABC_50kg'!G3 | L16: ='BOM_FL_MAT_ABC_50kg'!G4 | M16: 94 | N16: =L16/M16-1 | O16: 37 | P16: 61 | Q16: 34 | R16: FL_REC_ABC_50kg | S16: ir » | T16: =M16-50.0-J16 | U16: =(L16-50.0-J16)/T16-1 | V16: Plano Fadesa «Extintor rodante 50 kg R1»
A17: FL_MAT_ABC_70kg | B17: Extintor ABC 70 kg sobre ruedas | C17: rodante | D17: Propia | E17: 3550 | F17: Polvo químico seco ABC (fosfato monoamónico) | G17: 70 | H17: kg | I17: N₂ | J17: 0.5581 | K17: ='BOM_FL_MAT_ABC_70kg'!G3 | L17: ='BOM_FL_MAT_ABC_70kg'!G4 | M17: 140 | N17: =L17/M17-1 | O17: 38 | P17: 62 | Q17: 34 | R17: FL_REC_ABC_70kg | S17: ir » | T17: =M17-70.0-J17 | U17: =(L17-70.0-J17)/T17-1 | V17: Ficha técnica Georgia ABC 90 70 kg
A18: FL_MAT_ABC_100kg | B18: Extintor ABC 100 kg sobre ruedas | C18: rodante | D18: Propia | E18: 3550 | F18: Polvo químico seco ABC (fosfato monoamónico) | G18: 100 | H18: kg | I18: N₂ | J18: 0.5189 | K18: ='BOM_FL_MAT_ABC_100kg'!G3 | L18: ='BOM_FL_MAT_ABC_100kg'!G4 | M18: 187.6 | N18: =L18/M18-1 | O18: 38 | P18: 62 | Q18: 34 | R18: FL_REC_ABC_100kg | S18: ir » | T18: =M18-100.0-J18 | U18: =(L18-100.0-J18)/T18-1 | V18: Plano Fadesa «Extintor rodante 100 kg R1»

Sheet 04_BOM_Matafuegos
A1: BOM de matafuegos terminados FL_MAT (tabla plana filtrable)
A2: Colores: | B2: Validado | D2: Estimado | F2: A validar | H2: No cumple o decisión pendiente
A4: Producto | B4: Nivel | C4: Código | D4: Descripción | E4: Cant. | F4: UM | G4: Peso unit. (kg/UM) | H4: Peso total (kg) | I4: Material | J4: Medida (mm) | K4: Origen | L4: Entra MRP | M4: Proveedor principal | N4: Alternativa | O4: Operación / puesto (layout FLAMA) | P4: Norma / referencia | Q4: Fte. | R4: Plano | S4: Observaciones
A5: FL_MAT_ABC_1kg | B5: 0 | C5: FL_MAT_ABC_1kg | D5: Extintor ABC 1 kg | E5: 1 | F5: u | P5: IRAM 3523 | Q5: P | R5: FL_MAT_ABC_1kg | S5: Fabricación propia
A6: FL_MAT_ABC_1kg | B6: 1 | C6: FL_REC_ABC_1kg | D6: Recipiente (cilindro) | E6: 1 | F6: u | H6: =H7+H9+H11+H13+H14 | K6: Fabricación | P6: IRAM 3523 / 3550 (recipiente) | Q6: P | R6: FL_REC_ABC_1kg
A7: FL_MAT_ABC_1kg | B7: 2 | C7: ABC1-01 | D7: Cuerpo (virola) | E7: 1 | F7: u | G7: 0.6072 | H7: =E7*G7 | I7: Caño c-c LF Ø76,2 e=1,25 (SAE 1010) | J7: Ø76,2 × e1,25 × 263,4 de alto; desarrollo 235,5 × 263,4 | K7: Fabricación | L7: No | O7: 5 Corte láser de caño (M15/M16) -> 9 encastre -> 10 bordoneado (los dos extremos) | Q7: P | R7: FL_DES_ABC_1kg | S7: costura long. MAG
A8: FL_MAT_ABC_1kg | B8: 3 | C8: MP-CANO | D8: Caño Ø76,2 × 1,25 (tramo de barra de 6 m) | E8: 0.0435 | F8: barra | G8: 14.288 | H8: =E8*G8 | I8: Caño acero SAE 1010 con costura | J8: 255 mm por cuerpo; 23 cuerpos por barra (kg por barra) | K8: Compra | L8: Sí | M8: Metalpri / Prilux | N8: Comercial MID | O8: AL-1T cantiléver | Q8: L | R8: FL_PI_04 h2
A9: FL_MAT_ABC_1kg | B9: 2 | C9: ABC1-02 | D9: Cúpula | E9: 1 | F9: u | G9: 0.0335 | H9: =E9*G9 | I9: Chapa LAF IRAM-IAS U 500-05 e=0,9 | J9: Ø76,2 × e0,9 × 12,1 de alto; disco Ø108 | K9: Fabricación | L9: No | O9: 6 Desbobinado + embutido (M06-M08) -> numerado de cúpula (micropercusión, en arco junto al cuello) -> 8 soldadura de cuello | Q9: P | R9: FL_DES_ABC_1kg | S9: embutida
A10: FL_MAT_ABC_1kg | B10: 3 | C10: MP-FLEJE | D10: Fleje e=0,9 × 114 (paso 111) | E10: 0.111 | F10: m | G10: 0.805 | H10: =E10*G10 | I10: Fleje SAE 1010 | J10: disco Ø108 (kg por m de fleje) | K10: Compra | L10: Sí | M10: Pacheco Chapas | N10: Pradecon S.A. | O10: AL-1F porta-flejes | Q10: L | R10: FL_PI_04 h2
A11: FL_MAT_ABC_1kg | B11: 2 | C11: ABC1-03 | D11: Fondo | E11: 1 | F11: u | G11: 0.0662 | H11: =E11*G11 | I11: Chapa LAF IRAM-IAS U 500-05 e=1,25 | J11: Ø76,2 × e1,25 × 22 de alto; disco Ø100 | K11: Fabricación | L11: No | O11: 6 Desbobinado + embutido (M06-M08) | Q11: P | R11: FL_DES_ABC_1kg | S11: embutido
A12: FL_MAT_ABC_1kg | B12: 3 | C12: MP-FLEJE | D12: Fleje e=1,25 × 106 (paso 103) | E12: 0.103 | F12: m | G12: 1.04 | H12: =E12*G12 | I12: Fleje SAE 1010 | J12: disco Ø100 (kg por m de fleje) | K12: Compra | L12: Sí | M12: Pacheco Chapas | N12: Pradecon S.A. | O12: AL-1F porta-flejes | Q12: L | R12: FL_PI_04 h2
A13: FL_MAT_ABC_1kg | B13: 2 | C13: ABC1-04 | D13: Cuello roscado | E13: 1 | F13: u | G13: 0.0358 | H13: =E13*G13 | I13: Acero SAE 1010 | J13: Ø29 × 12,5 de alto, rosca M22x1,5, asiento Ø26 | K13: Compra (mecanizado, Eli-Met) | L13: Sí | M13: Eli-Met | N13: - | O13: Compra -> 8 soldadura de cuello | Q13: P | R13: FL_DES_ABC_1kg | S13: M22x1,5
A14: FL_MAT_ABC_1kg | B14: 2 | C14: ABC1-C1 | D14: Alambre MAG ER70S-6 Ø0,9 (AWS A5.18) | E14: 0.0146 | F14: kg | G14: 0.95 | H14: =E14*G14 | I14: ER70S-6 | J14: metal depositado de los cordones del plano 14 g / rendimiento 0,95 | K14: Compra | L14: Sí | M14: Conarco (ESAB Argentina) | N14: - | O14: 4 sold. long. / 8 cuello / 11 circunferencial | P14: IRAM 3523 3.2.4.2 · IRAM 3550 4.1.2 | Q14: C | S14: Peso unit. = fracción que queda en la pieza (el resto es salpicadura). Depositado = volumen de los cordones del modelo × 7,85. Rendimiento de deposición del alambre macizo MAG 90-97 % (ESAB): se adopta 0,95. Medir en la prueba de soldadura del equipo (Getweld)
A15: FL_MAT_ABC_1kg | B15: 2 | C15: ABC1-C2 | D15: Gas de protección MAG Arcal 21 / ARCAL Speed (Ar + 8 % CO₂, M20) | E15: 13.3 | F15: L | I15: EN ISO 14175 M20-ArC-8 | J15: 14 L/min × 0,95 min de arco (cordones 570 mm: long. 0 + circ. 479 + cuello 91, a 600 mm/min) | K15: Compra | L15: Sí | M15: Air Liquide Argentina - sucursal Piñeyro | N15: Gogniat | O15: Colector SC | P15: IRAM 3523 3.2.4.2 · IRAM 3550 3.2.2.2 | Q15: C | S15: Caudal 12-16 L/min para alambre 0,9-1,2 (Air Liquide; Ingemecánica): se adopta 14. Velocidad: Getweld 0-1500 mm/min; se adopta 600. Decisión FLAMA: MAG 135 con Arcal 21; la norma nombra «atmósfera inerte»: acreditar con el certificador en el ensayo de tipo. No incluye la soldadura del carro
A16: FL_MAT_ABC_1kg | B16: 2 | C16: ABC1-C3 | D16: Granalla de acero S330 / S390 (ISO 11124-3, SAE J444) | E16: 0.08 | F16: kg | I16: Granalla esférica alto C | J16: 0,073 m² a Sa 2½ (ISO 8501-1); 3,4 kg/h ÷ 42,5 u/h | K16: Compra | L16: Sí | M16: CyM Materiales | N16: Roca Ingeniería | O16: 14 Granallado (B08) | P16: DOC-01 | Q16: C | S16: Consumo (desgaste) por turbina ≈ HP / 2 lb/h (The Fabricator, «aspectos básicos del granallado por turbina»): G-100 con 2 × 7,5 HP = 7,5 lb/h = 3,4 kg/h; ritmo 340 u por turno (Getweld) = 42,5 u/h. OJO: Ø76,2 fuera del rango de la Airblast G-100 (Ø80-200): definir soporte o equipo
A17: FL_MAT_ABC_1kg | B17: 2 | C17: ABC1-C4 | D17: Servicio de pintura en polvo al horno, rojo 03-1-050 | E17: 1 | F17: u | I17: Servicio tercerizado | J17: superficie exterior 0,073 m² | K17: Compra (servicio) | L17: Sí | M17: Prymax | N17: Pintor de carros (cotización por mensaje) | O17: 17 Pintura tercerizada | P17: IRAM 3523 5.3 / IRAM 3550 3.11 · IRAM 121 | Q17: Q | S17: Q-PRYMAX (precio por cilindro); exigir informe de niebla salina del sistema de pintura; tercerización aceptada por el Ministerio (Res. 349/07 art. 18)
A18: FL_MAT_ABC_1kg | B18: 1 | C18: ABC1-S2 | D18: Conjunto de válvula | E18: 1 | F18: u | H18: =H19+H20+H21+H23+H24+H25+H26+H27+H28+H29+H30 | K18: Compra / armado | P18: Manómetro IRAM 3533 | Q18: P | R18: FL_DES_ABC_1kg
A19: FL_MAT_ABC_1kg | B19: 2 | C19: ABC1-05 | D19: Espiga roscada | E19: 1 | F19: u | G19: 0.0117 | H19: =E19*G19 | I19: Latón forjado | J19: 21 × 21 × 8,6 | K19: Incluido en válvula HZ | L19: No | O19: 19 Ensamblaje de válvula (T03/T04) | Q19: P | R19: FL_DES_ABC_1kg
A20: FL_MAT_ABC_1kg | B20: 2 | C20: ABC1-06 | D20: Collarín de válvula | E20: 1 | F20: u | G20: 0.0025 | H20: =E20*G20 | I20: Latón forjado | J20: 19 × 19 × 3 | K20: Incluido en válvula HZ | L20: No | O20: 19 Ensamblaje de válvula (T03/T04) | Q20: P | R20: FL_DES_ABC_1kg
A21: FL_MAT_ABC_1kg | B21: 2 | C21: ABC1-07 | D21: Cuerpo de válvula | E21: 1 | F21: u | G21: 0.0935 | H21: =E21*G21 | I21: Latón forjado | J21: 32,3 × 28 × 22,9 | K21: Incluido en válvula HZ | L21: No | O21: 19 Ensamblaje de válvula (T03/T04) | Q21: P | R21: FL_DES_ABC_1kg
A22: FL_MAT_ABC_1kg | B22: 2 | C22: ABC1-08 | D22: Manómetro | E22: 1 | F22: u | I22: Comercial | J22: Ø36 esfera, rango 0-3,5 MPa, sector verde en 1,4 | K22: Compra | L22: Sí | M22: Yukon / MatafuegosYa S.R.L. | N22: Matafuegos Iglesias | O22: 19 Ensamblaje de válvula (T03/T04) | P22: IRAM 3533 | Q22: P | R22: FL_DES_ABC_1kg | S22: Pieza comercial; sello IRAM 3533; peso: completar con la ficha del proveedor (no afecta el MRP)
A23: FL_MAT_ABC_1kg | B23: 2 | C23: ABC1-09 | D23: Vástago | E23: 1 | F23: u | G23: 0.0044 | H23: =E23*G23 | I23: Latón | J23: 22,8 × 9 × 9 | K23: Incluido en válvula HZ | L23: No | O23: 19 Ensamblaje de válvula (T03/T04) | Q23: P | R23: FL_DES_ABC_1kg | S23: con junta tórica
A24: FL_MAT_ABC_1kg | B24: 2 | C24: ABC1-10 | D24: Resorte de válvula | E24: 1 | F24: u | G24: 0.0018 | H24: =E24*G24 | I24: Alambre acero inox. AISI 302 | J24: 19,9 × 9,8 × 9,8 | K24: Incluido en válvula HZ | L24: No | O24: 19 Ensamblaje de válvula (T03/T04) | Q24: P | R24: FL_DES_ABC_1kg | S24: cierre del vástago
A25: FL_MAT_ABC_1kg | B25: 2 | C25: ABC1-11 | D25: Eje de palanca | E25: 1 | F25: u | G25: 0.0023 | H25: =E25*G25 | I25: Acero inox. AISI 304 | J25: 29 × 3,6 × 3,6 | K25: Incluido en válvula HZ | L25: No | O25: 19 Ensamblaje de válvula (T03/T04) | Q25: P | R25: FL_DES_ABC_1kg
A26: FL_MAT_ABC_1kg | B26: 2 | C26: ABC1-12 | D26: Pasador de seguridad | E26: 1 | F26: u | G26: 0.0053 | H26: =E26*G26 | I26: Alambre acero inox. AISI 304 | J26: 41,9 × 21 × 20,8 | K26: Incluido en válvula HZ | L26: No | O26: 19 Ensamblaje de válvula (T03/T04) | Q26: P | R26: FL_DES_ABC_1kg | S26: con precinto
A27: FL_MAT_ABC_1kg | B27: 2 | C27: ABC1-13 | D27: Manija de accionamiento | E27: 1 | F27: u | G27: 0.025 | H27: =E27*G27 | I27: Chapa acero SAE 1010 pintada | J27: 67,1 × 27 × 11 | K27: Incluido en válvula HZ | L27: No | O27: 19 Ensamblaje de válvula (T03/T04) | Q27: P | R27: FL_DES_ABC_1kg
A28: FL_MAT_ABC_1kg | B28: 2 | C28: ABC1-14 | D28: Manija de transporte | E28: 1 | F28: u | G28: 0.0501 | H28: =E28*G28 | I28: Chapa acero SAE 1010 pintada | J28: 91,7 × 60 × 31 | K28: Incluido en válvula HZ | L28: No | O28: 19 Ensamblaje de válvula (T03/T04) | Q28: P | R28: FL_DES_ABC_1kg
A29: FL_MAT_ABC_1kg | B29: 2 | C29: ABC1-15 | D29: Caño de pesca (sifón) | E29: 1 | F29: u | G29: 0.023 | H29: =E29*G29 | I29: Tubo PVC rígido | J29: Ø14,4 × 270,1 de largo | K29: Incluido en válvula HZ | L29: No | O29: 19 Ensamblaje de válvula (T03/T04) | Q29: P | R29: FL_DES_ABC_1kg
A30: FL_MAT_ABC_1kg | B30: 2 | C30: ABC1-21 | D30: Junta tórica de asiento | E30: 1 | F30: u | G30: 0.0007 | H30: =E30*G30 | I30: NBR 70 Shore A | J30: Ø24 ext. × cordón 3 | K30: Compra | L30: Sí | M30: Argensold | N30: Matafuegos Iglesias | O30: 19 Ensamblaje de válvula (T03/T04) | Q30: P | R30: FL_DES_ABC_1kg | S30: cambio c/recarga
A31: FL_MAT_ABC_1kg | B31: 2 | C31: ABC1-K2 | D31: Válvula HZ armada M-22 1 kg c/tubo de pesca plástico | E31: 1 | F31: u | I31: Latón forjado (HZ) | J31: rosca M22x1,5 | K31: Compra | L31: Sí | M31: Polvex S.R.L. / Sancibrao | N31: Mozart S.R.L. | O31: 19 Ensamblaje de válvula | P31: IRAM 3523 3.3 | Q31: Q | R31: FL_DES_ABC_1kg | S31: Lista de precios HZ (Q-AGENTES); plano Fadesa usa válvula HZ (R-FADESA). Trae las piezas marcadas «Incluido en válvula HZ»
A32: FL_MAT_ABC_1kg | B32: 2 | C32: ABC1-V2 | D32: Resorte de retorno del vástago | E32: 1 | F32: u | I32: Acero para resortes | J32: incluido en la válvula | K32: Incluido en válvula HZ | L32: No | O32: 19 Ensamblaje | Q32: Q | S32: Lista de precios HZ: válvula «c/resorte» (Q-AGENTES)
A33: FL_MAT_ABC_1kg | B33: 2 | C33: ABC1-V3 | D33: Junta tórica del vástago | E33: 1 | F33: u | I33: NBR 70 Shore A | J33: incluida en la válvula | K33: Incluido en válvula HZ | L33: No | O33: 19 Ensamblaje | Q33: P | S33: Figura en el plano como «vástago con junta tórica»
A34: FL_MAT_ABC_1kg | B34: 1 | C34: ABC1-S3 | D34: Dispositivo de descarga | E34: 1 | F34: u | H34: =H35 | K34: Compra / armado | Q34: P | R34: FL_DES_ABC_1kg
A35: FL_MAT_ABC_1kg | B35: 2 | C35: ABC1-16 | D35: Tobera | E35: 1 | F35: u | G35: 0.0006 | H35: =E35*G35 | I35: Polipropileno | J35: 12 × 12 × 10 | K35: Compra | L35: Sí | M35: Yukon / MatafuegosYa S.R.L. | N35: Matafuegos Iglesias | O35: 19 Ensamblaje (T03/T04) | Q35: P | R35: FL_DES_ABC_1kg
A36: FL_MAT_ABC_1kg | B36: 1 | C36: ABC1-S5 | D36: Carga: agente extintor y gas impulsor | E36: 1 | F36: u | H36: =H37+H38 | K36: Carga en planta | O36: 18 Carga de polvo (T01) / C8 (T02)
A37: FL_MAT_ABC_1kg | B37: 2 | C37: ABC1-A1 | D37: Polvo químico seco ABC 60 (Sello IRAM 3569) | E37: 1.05 | F37: kg | G37: 1 | H37: =E37*G37 | I37: Polvo químico seco ABC 60 (Sello IRAM 3569) | J37: nominal 1 kg; tolerancia 0 / +100 g (IRAM 3517-2:2020 tabla 3 · IRAM 3523 tabla II) | K37: Compra | L37: Sí | M37: DEM S.A. (DEMSA) | N37: Polvex S.R.L. / Sancibrao | O37: SP-1 almacén previo a la carga | P37: IRAM 3569 | Q37: N | S37: Composición declarada del polvo ABC 60: MAP 60 % (IRAM 3569: 57-63 %) = 0,63 kg MAP + 0,389 kg sulfato de amonio + 0,032 kg aditivos · potencial de referencia 1A-5B:C (licencia Drago con DEM-60/90, L-DRAGO) · Decisión: DEMSA principal (sello IRAM 3569 y potencial de referencia); Polvex/Sancibrao alternativa sujeta a sello IRAM 3569 y ensayo de tipo de FLAMA (IRAM 3542/3543) · Lote único por extintor; prohibido mezclar ABC con BC (3517-2 9.9.1.6)
A38: FL_MAT_ABC_1kg | B38: 2 | C38: ABC1-A2 | D38: Gas impulsor: N₂ | E38: 0.0047 | F38: kg | G38: 1 | H38: =E38*G38 | I38: N₂ | J38: 3,7 L normales para 1,4 MPa a 20 °C en 0,27 dm³ libres | K38: Compra | L38: Sí | M38: Air Liquide Argentina - sucursal Piñeyro | N38: Gogniat | O38: 20 Presurización (T05) / C10 | P38: IRAM 3517-2 9.4.9 (tabla 2) · IRAM 3523 2.3 y 3.10 | Q38: C | S38: N₂ ≥ 99,8 %, H₂O ≤ 40 ppm (Q-N2, Air Liquide) · volumen libre con ρ empacada mínima 1,1 kg/dm³ (NOM-104-STPS-2001); confirmar con descarga ≥ 85 % (IRAM 3523 4.9.1)
A39: FL_MAT_ABC_1kg | B39: 1 | C39: ABC1-S6 | D39: Identificación y precinto | E39: 1 | F39: u | H39: =H40+H41+H42+H43+H44+H45 | K39: Compra | O39: 22 Etiquetado (T07)
A40: FL_MAT_ABC_1kg | B40: 2 | C40: ABC1-17 | D40: Etiqueta / placa de características | E40: 1 | F40: u | G40: 0.0097 | H40: =E40*G40 | I40: Vinilo autoadhesivo laminado | J40: 168 × 137 (desarrollo × alto: panel central 108° + 2 alas laterales), e ≈ 0,3, laminado UV | K40: Compra | L40: Sí | M40: Astuprint | N40: Multilabel Argentina S.A. | O40: 22 Etiquetado (T07) | P40: IRAM 3534 · IRAM 3523 cap. 5 · relevamiento de mercado | Q40: P | R40: FL_DES_ABC_1kg | S40: IRAM 3534
A41: FL_MAT_ABC_1kg | B41: 2 | C41: ABC1-18 | D41: Oblea de fabricación (PBA) | E41: 1 | F41: u | G41: 0.0009 | H41: =E41*G41 | I41: Papel de seguridad autodestructible | J41: Ø46 (Res. OPDS 522/07), numerada, autodestructible | K41: Compra | L41: Sí | M41: Ministerio de Ambiente PBA (ex OPDS) | N41: - | O41: 22 Etiquetado (T07) | P41: Res. OPDS 522/07 anexos 1, 2 y 6 | Q41: P | R41: FL_DES_ABC_1kg | S41: Res. 522/07
A42: FL_MAT_ABC_1kg | B42: 2 | C42: ABC1-19 | D42: Estampilla IRAM de conformidad | E42: 1 | F42: u | G42: 0.001 | H42: =E42*G42 | I42: Provista por IRAM (Anexo R) | J42: 60 × 40 | K42: Compra | L42: Sí | M42: IRAM - Instituto Argentino de Normalización | N42: - | O42: 22 Etiquetado (T07) | P42: IRAM Anexo R (DC-PG-129) | Q42: P | R42: FL_DES_ABC_1kg | S42: numerada
A43: FL_MAT_ABC_1kg | B43: 2 | C43: ABC1-20 | D43: Etiqueta de n° de serie GS1 | E43: 1 | F43: u | G43: 0.0005 | H43: =E43*G43 | I43: Poliéster autoadhesivo impreso térmico | J43: 45 × 25 | K43: Compra | L43: Sí | M43: Astuprint | N43: GS1 Argentina | O43: 22 Etiquetado (T07) | P43: GS1 Argentina (GTIN 779) · trazabilidad IRAM 3523 5.1 | Q43: P | R43: FL_DES_ABC_1kg | S43: QR GTIN + serie
A44: FL_MAT_ABC_1kg | B44: 2 | C44: ABC1-22 | D44: Faja de garantía válvula-cuello | E44: 1 | F44: u | G44: 0.0001 | H44: =E44*G44 | I44: Vinilo destructible rayado rojo/blanco | J44: 17 × 20 (ancho × largo desarrollado), pegada sobre la unión: cuerpo de la válvula, tuerca y cuello | K44: Compra | L44: Sí | M44: Astuprint | N44: Multilabel Argentina S.A. | O44: 22 Etiquetado (T07) | P44: Sin norma: práctica de mercado (garantía de fábrica) | Q44: P | R44: FL_DES_ABC_1kg | S44: nuevo sin abrir
A45: FL_MAT_ABC_1kg | B45: 2 | C45: ABC1-23 | D45: Precinto de fábrica | E45: 1 | F45: u | G45: 0.0002 | H45: =E45*G45 | I45: Polipropileno color | J45: Ø5 × 10, numerado, rotura 30-50 N | K45: Compra | L45: Sí | M45: SonFuertes (vía Papelera Damián) | N45: Precinter S.R.L. | O45: 20 Presurización (T05) | P45: IRAM 3523 3.3.2 · IRAM 3517-2:2020 9.4.13 | Q45: P | R45: FL_DES_ABC_1kg | S45: id. FLAMA y lote
A46: FL_MAT_ABC_1kg | B46: 1 | C46: ABC1-S8 | D46: Soporte (accesorio de montaje) | E46: 1 | F46: u | H46: =H47 | K46: Compra | O46: 23 Embalaje (va dentro de la caja) | P46: IRAM 3517-2 7.4
A47: FL_MAT_ABC_1kg | B47: 2 | C47: ABC1-I7 | D47: Soporte vehicular con cierre rápido (FL_ACC_02) | E47: 1 | F47: u | G47: 0.631 | H47: =E47*G47 | I47: Chapa acero SAE 1010 e=2,5 pintada | J47: base 80 de ancho, 2 aros con hebilla | K47: Compra | L47: Sí | M47: Maxiseguridad | N47: CM Representaciones | O47: 23 Embalaje | P47: IRAM 3517-2 7.4 | Q47: P | R47: FL_ACC_02
A48: FL_MAT_ABC_1kg | B48: 1 | C48: ABC1-S7 | D48: Embalaje | E48: 1 | F48: u | H48: =H52 | K48: Compra | O48: 23 Embalaje -> 24 envolvedora (T11)
A49: FL_MAT_ABC_1kg | B49: 2 | C49: ABC1-E1 | D49: Caja de cartón corrugado simple | E49: 1 | F49: u | I49: Cartón corrugado | J49: 160 × 107 × 347 interior (envolvente del plano + 15 por lado) | K49: Compra | L49: Sí | M49: Maxipack | N49: Cartocan | O49: 23 Embalaje | Q49: P | S49: Medida del plano
A50: FL_MAT_ABC_1kg | B50: 2 | C50: ABC1-E2 | D50: Instructivo de uso y mantenimiento | E50: 1 | F50: u | I50: Papel | J50: A5 | K50: Compra | L50: Sí | M50: Astuprint | N50: - | O50: 23 Embalaje | Q50: I | S50: Decisión comercial de FLAMA (las instrucciones de uso obligatorias van en la etiqueta, IRAM 3534)
A51: FL_MAT_ABC_1kg | B51: 2 | C51: ABC1-E3 | D51: Pallet 1200 × 1000 (fracción) | E51: 0.0038 | F51: u | I51: Madera | J51: 264 u por pallet | K51: Compra | L51: Sí | M51: IndusPallets | N51: - | O51: 23 Embalaje | Q51: C | S51: u por pallet = acomodo de la caja (plano) en 1200 × 1000 × 1450 de alto
A52: FL_MAT_ABC_1kg | B52: 2 | C52: ABC1-E4 | D52: Film stretch (fracción del pallet) | E52: 0.0005 | F52: kg | G52: 1 | H52: =E52*G52 | I52: PE lineal 23 µm | J52: 0,12 kg por pallet / 264 u | K52: Compra | L52: Sí | M52: MV Embalajes | N52: Embalpack | O52: 24 Envolvedora (T11) | Q52: C | S52: Perímetro del pallet 4,4 m × 9 vueltas = 40 m aplicados; con pre-estirado 250 % (1 m de bobina = 3,5 m aplicados) = 11,4 m de bobina × 0,5 m × 23 µm × 0,92 g/cm³ = 0,12 kg. Fuentes: fichas de film 23 µm × 500 mm (MV Embalajes / Embalpack) y pre-estirado de la envolvedora. Medir en la puesta en marcha
A53: FL_MAT_ABC_1kg | B53: 2 | C53: ABC1-E5 | D53: Etiqueta de pallet (lote y destino, fracción) | E53: 0.0038 | F53: u | I53: Papel térmico | J53: 100 × 150 | K53: Compra | L53: Sí | M53: Astuprint | N53: Multilabel Argentina S.A. | O53: 24 Envolvedora | Q53: C
A54: FL_MAT_ABC_1kg | B54: 2 | C54: ABC1-E6 | D54: Cinta de embalaje PP 48 mm (cierre de la caja) | E54: 0.6 | F54: m | I54: Polipropileno con adhesivo acrílico | J54: cierre en I arriba y abajo: 2 × (160 + 2 × 70 de solapa) | K54: Compra | L54: Sí | M54: MV Embalajes | N54: Embalpack | O54: 23 Embalaje | Q54: C | S54: Solapa de 70 mm por lado: práctica de cierre de cajas (medir en la línea)
A55: FL_MAT_ABC_1kg | B55: 2 | C55: ABC1-E7 | D55: Esquineros de cartón 50 × 50 × 1200 (fracción del pallet) | E55: 0.0152 | F55: u | I55: Cartón | J55: 4 por pallet / 264 u | K55: Compra | L55: Sí | M55: Maxipack | N55: Cartocan | O55: 24 Envolvedora (T11) | Q55: C | S55: Planilla MP-64
A56: FL_MAT_ABC_2.5kg | B56: 0 | C56: FL_MAT_ABC_2.5kg | D56: Extintor ABC 2,5 kg | E56: 1 | F56: u | P56: IRAM 3523 | Q56: P | R56: FL_MAT_ABC_2.5kg | S56: Fabricación propia
A57: FL_MAT_ABC_2.5kg | B57: 1 | C57: FL_REC_ABC_2.5kg | D57: Recipiente (cilindro) | E57: 1 | F57: u | H57: =H58+H60+H62+H64+H65 | K57: Fabricación | P57: IRAM 3523 / 3550 (recipiente) | Q57: P | R57: FL_REC_ABC_2.5kg
A58: FL_MAT_ABC_2.5kg | B58: 2 | C58: ABC2.5-01 | D58: Cuerpo (virola) | E58: 1 | F58: u | G58: 1.011 | H58: =E58*G58 | I58: Chapa LAF IRAM-IAS U 500-05 e=1,25 | J58: Ø124 × e1,25 × 267,4 de alto; desarrollo 385,6 × 267,4 | K58: Fabricación | L58: No | O58: 1 Guillotina -> 3 cilindrado -> 4 soldadura longitudinal -> 9 encastre del fondo -> 10 bordoneado | Q58: P | R58: FL_DES_ABC_2.5kg | S58: costura long. MAG
A59: FL_MAT_ABC_2.5kg | B59: 3 | C59: MP-HOJA | D59: Recorte de hoja LAF 1220 × 2440 e=1,25 | E59: 1 | F59: u | G59: 1.082 | H59: =E59*G59 | I59: Chapa LAF IRAM-IAS U 500-05 LAF | J59: 385,5 × 269,5 (aprovech. 94,2 %) | K59: Compra | L59: Sí | M59: Pradecon S.A. | N59: Pacheco Chapas | O59: AL-1H paquetes de hojas | Q59: L | R59: FL_PI_04 h2
A60: FL_MAT_ABC_2.5kg | B60: 2 | C60: ABC2.5-02 | D60: Cúpula | E60: 1 | F60: u | G60: 0.1734 | H60: =E60*G60 | I60: Chapa LAF IRAM-IAS U 500-05 e=1,25 | J60: Ø124 × e1,25 × 38,1 de alto; disco Ø179 | K60: Fabricación | L60: No | O60: 6 Desbobinado + embutido (M06-M08) -> numerado de cúpula (micropercusión, en arco junto al cuello) -> 8 soldadura de cuello | Q60: P | R60: FL_DES_ABC_2.5kg | S60: embutida
A61: FL_MAT_ABC_2.5kg | B61: 3 | C61: MP-FLEJE | D61: Fleje e=1,25 × 200 (paso 182) | E61: 0.182 | F61: m | G61: 1.962 | H61: =E61*G61 | I61: Fleje SAE 1010 | J61: disco Ø179 (kg por m de fleje) | K61: Compra | L61: Sí | M61: Pacheco Chapas | N61: Pradecon S.A. | O61: AL-1F porta-flejes | Q61: L | R61: FL_PI_04 h2
A62: FL_MAT_ABC_2.5kg | B62: 2 | C62: ABC2.5-03 | D62: Fondo | E62: 1 | F62: u | G62: 0.1657 | H62: =E62*G62 | I62: Chapa LAF IRAM-IAS U 500-05 e=1,25 | J62: Ø124 × e1,25 × 20,5 de alto; disco Ø148 | K62: Fabricación | L62: No | O62: 6 Desbobinado + embutido (M06-M08) | Q62: P | R62: FL_DES_ABC_2.5kg | S62: embutido
A63: FL_MAT_ABC_2.5kg | B63: 3 | C63: MP-FLEJE | D63: Fleje e=1,25 × 200 (paso 151) | E63: 0.151 | F63: m | G63: 1.962 | H63: =E63*G63 | I63: Fleje SAE 1010 | J63: disco Ø148 (kg por m de fleje) | K63: Compra | L63: Sí | M63: Pacheco Chapas | N63: Pradecon S.A. | O63: AL-1F porta-flejes | Q63: L | R63: FL_PI_04 h2
A64: FL_MAT_ABC_2.5kg | B64: 2 | C64: ABC2.5-04 | D64: Cuello roscado | E64: 1 | F64: u | G64: 0.0545 | H64: =E64*G64 | I64: Acero SAE 1010 | J64: Ø37 × 14 de alto, rosca M30x1,5, asiento Ø35 | K64: Compra (mecanizado, Eli-Met) | L64: Sí | M64: Eli-Met | N64: - | O64: Compra -> 8 soldadura de cuello | Q64: P | R64: FL_DES_ABC_2.5kg | S64: M30x1,5
A65: FL_MAT_ABC_2.5kg | B65: 2 | C65: ABC2.5-C1 | D65: Alambre MAG ER70S-6 Ø0,9 (AWS A5.18) | E65: 0.0292 | F65: kg | G65: 0.95 | H65: =E65*G65 | I65: ER70S-6 | J65: metal depositado de los cordones del plano 28 g / rendimiento 0,95 | K65: Compra | L65: Sí | M65: Conarco (ESAB Argentina) | N65: - | O65: 4 sold. long. / 8 cuello / 11 circunferencial | P65: IRAM 3523 3.2.4.2 · IRAM 3550 4.1.2 | Q65: C | S65: Peso unit. = fracción que queda en la pieza (el resto es salpicadura). Depositado = volumen de los cordones del modelo × 7,85. Rendimiento de deposición del alambre macizo MAG 90-97 % (ESAB): se adopta 0,95. Medir en la prueba de soldadura del equipo (Getweld)
A66: FL_MAT_ABC_2.5kg | B66: 2 | C66: ABC2.5-C2 | D66: Gas de protección MAG Arcal 21 / ARCAL Speed (Ar + 8 % CO₂, M20) | E66: 27.1 | F66: L | I66: EN ISO 14175 M20-ArC-8 | J66: 14 L/min × 1,94 min de arco (cordones 1.163 mm: long. 267 + circ. 779 + cuello 116, a 600 mm/min) | K66: Compra | L66: Sí | M66: Air Liquide Argentina - sucursal Piñeyro | N66: Gogniat | O66: Colector SC | P66: IRAM 3523 3.2.4.2 · IRAM 3550 3.2.2.2 | Q66: C | S66: Caudal 12-16 L/min para alambre 0,9-1,2 (Air Liquide; Ingemecánica): se adopta 14. Velocidad: Getweld 0-1500 mm/min; se adopta 600. Decisión FLAMA: MAG 135 con Arcal 21; la norma nombra «atmósfera inerte»: acreditar con el certificador en el ensayo de tipo. No incluye la soldadura del carro
A67: FL_MAT_ABC_2.5kg | B67: 2 | C67: ABC2.5-C3 | D67: Granalla de acero S330 / S390 (ISO 11124-3, SAE J444) | E67: 0.08 | F67: kg | I67: Granalla esférica alto C | J67: 0,138 m² a Sa 2½ (ISO 8501-1); 3,4 kg/h ÷ 42,5 u/h | K67: Compra | L67: Sí | M67: CyM Materiales | N67: Roca Ingeniería | O67: 14 Granallado (B08) | P67: DOC-01 | Q67: C | S67: Consumo (desgaste) por turbina ≈ HP / 2 lb/h (The Fabricator, «aspectos básicos del granallado por turbina»): G-100 con 2 × 7,5 HP = 7,5 lb/h = 3,4 kg/h; ritmo 340 u por turno (Getweld) = 42,5 u/h.
A68: FL_MAT_ABC_2.5kg | B68: 2 | C68: ABC2.5-C4 | D68: Servicio de pintura en polvo al horno, rojo 03-1-050 | E68: 1 | F68: u | I68: Servicio tercerizado | J68: superficie exterior 0,138 m² | K68: Compra (servicio) | L68: Sí | M68: Prymax | N68: Pintor de carros (cotización por mensaje) | O68: 17 Pintura tercerizada | P68: IRAM 3523 5.3 / IRAM 3550 3.11 · IRAM 121 | Q68: Q | S68: Q-PRYMAX (precio por cilindro); exigir informe de niebla salina del sistema de pintura; tercerización aceptada por el Ministerio (Res. 349/07 art. 18)
A69: FL_MAT_ABC_2.5kg | B69: 1 | C69: ABC2.5-S2 | D69: Conjunto de válvula | E69: 1 | F69: u | H69: =H70+H71+H72+H74+H75+H76+H77+H78+H79+H80+H81 | K69: Compra / armado | P69: Manómetro IRAM 3533 | Q69: P | R69: FL_DES_ABC_2.5kg
A70: FL_MAT_ABC_2.5kg | B70: 2 | C70: ABC2.5-05 | D70: Espiga roscada | E70: 1 | F70: u | G70: 0.0245 | H70: =E70*G70 | I70: Latón forjado | J70: 29,8 × 29,8 × 10,8 | K70: Incluido en válvula HZ | L70: No | O70: 19 Ensamblaje de válvula (T03/T04) | Q70: P | R70: FL_DES_ABC_2.5kg
A71: FL_MAT_ABC_2.5kg | B71: 2 | C71: ABC2.5-06 | D71: Collarín de válvula | E71: 1 | F71: u | G71: 0.0053 | H71: =E71*G71 | I71: Latón forjado | J71: 27,2 × 27,2 × 4,1 | K71: Incluido en válvula HZ | L71: No | O71: 19 Ensamblaje de válvula (T03/T04) | Q71: P | R71: FL_DES_ABC_2.5kg
A72: FL_MAT_ABC_2.5kg | B72: 2 | C72: ABC2.5-07 | D72: Cuerpo de válvula | E72: 1 | F72: u | G72: 0.1328 | H72: =E72*G72 | I72: Latón forjado | J72: 43,9 × 32 × 24,5 | K72: Incluido en válvula HZ | L72: No | O72: 19 Ensamblaje de válvula (T03/T04) | Q72: P | R72: FL_DES_ABC_2.5kg
A73: FL_MAT_ABC_2.5kg | B73: 2 | C73: ABC2.5-08 | D73: Manómetro | E73: 1 | F73: u | I73: Comercial | J73: Ø36 esfera, rango 0-3,5 MPa, sector verde en 1,4 | K73: Compra | L73: Sí | M73: Yukon / MatafuegosYa S.R.L. | N73: Matafuegos Iglesias | O73: 19 Ensamblaje de válvula (T03/T04) | P73: IRAM 3533 | Q73: P | R73: FL_DES_ABC_2.5kg | S73: Pieza comercial; sello IRAM 3533; peso: completar con la ficha del proveedor (no afecta el MRP)
A74: FL_MAT_ABC_2.5kg | B74: 2 | C74: ABC2.5-09 | D74: Vástago | E74: 1 | F74: u | G74: 0.0137 | H74: =E74*G74 | I74: Latón | J74: 35,6 × 14 × 14 | K74: Incluido en válvula HZ | L74: No | O74: 19 Ensamblaje de válvula (T03/T04) | Q74: P | R74: FL_DES_ABC_2.5kg | S74: con junta tórica
A75: FL_MAT_ABC_2.5kg | B75: 2 | C75: ABC2.5-10 | D75: Resorte de válvula | E75: 1 | F75: u | G75: 0.0049 | H75: =E75*G75 | I75: Alambre acero inox. AISI 302 | J75: 28,8 × 17,3 × 17,3 | K75: Incluido en válvula HZ | L75: No | O75: 19 Ensamblaje de válvula (T03/T04) | Q75: P | R75: FL_DES_ABC_2.5kg | S75: cierre del vástago
A76: FL_MAT_ABC_2.5kg | B76: 2 | C76: ABC2.5-11 | D76: Eje de palanca | E76: 1 | F76: u | G76: 0.0033 | H76: =E76*G76 | I76: Acero inox. AISI 304 | J76: 33 × 4 × 4 | K76: Incluido en válvula HZ | L76: No | O76: 19 Ensamblaje de válvula (T03/T04) | Q76: P | R76: FL_DES_ABC_2.5kg
A77: FL_MAT_ABC_2.5kg | B77: 2 | C77: ABC2.5-12 | D77: Pasador de seguridad | E77: 1 | F77: u | G77: 0.0055 | H77: =E77*G77 | I77: Alambre acero inox. AISI 304 | J77: 45,9 × 21 × 20,8 | K77: Incluido en válvula HZ | L77: No | O77: 19 Ensamblaje de válvula (T03/T04) | Q77: P | R77: FL_DES_ABC_2.5kg | S77: con precinto
A78: FL_MAT_ABC_2.5kg | B78: 2 | C78: ABC2.5-13 | D78: Manija de accionamiento | E78: 1 | F78: u | G78: 0.0959 | H78: =E78*G78 | I78: Chapa acero SAE 1010 pintada | J78: 124,6 × 31 × 29,3 | K78: Incluido en válvula HZ | L78: No | O78: 19 Ensamblaje de válvula (T03/T04) | Q78: P | R78: FL_DES_ABC_2.5kg
A79: FL_MAT_ABC_2.5kg | B79: 2 | C79: ABC2.5-14 | D79: Manija de transporte | E79: 1 | F79: u | G79: 0.0757 | H79: =E79*G79 | I79: Chapa acero SAE 1010 pintada | J79: 102,6 × 35 × 25,4 | K79: Incluido en válvula HZ | L79: No | O79: 19 Ensamblaje de válvula (T03/T04) | Q79: P | R79: FL_DES_ABC_2.5kg
A80: FL_MAT_ABC_2.5kg | B80: 2 | C80: ABC2.5-15 | D80: Caño de pesca (sifón) | E80: 1 | F80: u | G80: 0.0363 | H80: =E80*G80 | I80: Tubo PVC rígido | J80: Ø21,3 × 277,9 de largo | K80: Incluido en válvula HZ | L80: No | O80: 19 Ensamblaje de válvula (T03/T04) | Q80: P | R80: FL_DES_ABC_2.5kg
A81: FL_MAT_ABC_2.5kg | B81: 2 | C81: ABC2.5-25 | D81: Junta tórica de asiento | E81: 1 | F81: u | G81: 0.001 | H81: =E81*G81 | I81: NBR 70 Shore A | J81: Ø32,8 ext. × cordón 3 | K81: Compra | L81: Sí | M81: Argensold | N81: Matafuegos Iglesias | O81: 19 Ensamblaje de válvula (T03/T04) | Q81: P | R81: FL_DES_ABC_2.5kg | S81: cambio c/recarga
A82: FL_MAT_ABC_2.5kg | B82: 2 | C82: ABC2.5-K2 | D82: Válvula HZ armada M-30 c/resorte y tubo 7/8 | E82: 1 | F82: u | I82: Latón forjado (HZ) | J82: rosca M30x1,5 | K82: Compra | L82: Sí | M82: Polvex S.R.L. / Sancibrao | N82: Mozart S.R.L. | O82: 19 Ensamblaje de válvula | P82: IRAM 3523 3.3 | Q82: Q | R82: FL_DES_ABC_2.5kg | S82: Lista de precios HZ (Q-AGENTES); plano Fadesa usa válvula HZ (R-FADESA). Trae las piezas marcadas «Incluido en válvula HZ»
A83: FL_MAT_ABC_2.5kg | B83: 2 | C83: ABC2.5-V2 | D83: Resorte de retorno del vástago | E83: 1 | F83: u | I83: Acero para resortes | J83: incluido en la válvula | K83: Incluido en válvula HZ | L83: No | O83: 19 Ensamblaje | Q83: Q | S83: Lista de precios HZ: válvula «c/resorte» (Q-AGENTES)
A84: FL_MAT_ABC_2.5kg | B84: 2 | C84: ABC2.5-V3 | D84: Junta tórica del vástago | E84: 1 | F84: u | I84: NBR 70 Shore A | J84: incluida en la válvula | K84: Incluido en válvula HZ | L84: No | O84: 19 Ensamblaje | Q84: P | S84: Figura en el plano como «vástago con junta tórica»
A85: FL_MAT_ABC_2.5kg | B85: 1 | C85: ABC2.5-S3 | D85: Dispositivo de descarga | E85: 1 | F85: u | H85: =H86+H87+H88+H89 | K85: Compra / armado | Q85: P | R85: FL_DES_ABC_2.5kg
A86: FL_MAT_ABC_2.5kg | B86: 2 | C86: ABC2.5-16 | D86: Racor de manguera | E86: 1 | F86: u | G86: 0.0394 | H86: =E86*G86 | I86: Latón | J86: 19,4 × 18,8 × 18,8 | K86: Compra | L86: Sí | M86: Yukon / MatafuegosYa S.R.L. | N86: Matafuegos Iglesias | O86: 19 Ensamblaje (T03/T04) | Q86: P | R86: FL_DES_ABC_2.5kg
A87: FL_MAT_ABC_2.5kg | B87: 2 | C87: ABC2.5-17 | D87: Manguera | E87: 1 | F87: u | G87: 0.0368 | H87: =E87*G87 | I87: Caucho sintético | J87: Ø16 × 238 de largo desarrollado | K87: Compra | L87: Sí | M87: Yukon / MatafuegosYa S.R.L. | N87: Matafuegos Iglesias | O87: 19 Ensamblaje (T03/T04) | Q87: P | R87: FL_DES_ABC_2.5kg
A88: FL_MAT_ABC_2.5kg | B88: 2 | C88: ABC2.5-18 | D88: Tobera con portatobera | E88: 1 | F88: u | G88: 0.0168 | H88: =E88*G88 | I88: Polipropileno | J88: 73,5 × 19,9 × 19,9 | K88: Compra | L88: Sí | M88: Yukon / MatafuegosYa S.R.L. | N88: Matafuegos Iglesias | O88: 19 Ensamblaje (T03/T04) | Q88: P | R88: FL_DES_ABC_2.5kg
A89: FL_MAT_ABC_2.5kg | B89: 2 | C89: ABC2.5-19 | D89: Suncho portatobera | E89: 1 | F89: u | G89: 0.0791 | H89: =E89*G89 | I89: Fleje acero SAE 1010 pintado | J89: 137,6 × 127,6 × 14,4 | K89: Compra (estructura) | L89: Sí | M89: Yukon / MatafuegosYa S.R.L. | N89: Matafuegos Iglesias | O89: 19 Ensamblaje (T03/T04) | Q89: P | R89: FL_DES_ABC_2.5kg
A90: FL_MAT_ABC_2.5kg | B90: 1 | C90: ABC2.5-S5 | D90: Carga: agente extintor y gas impulsor | E90: 1 | F90: u | H90: =H91+H92 | K90: Carga en planta | O90: 18 Carga de polvo (T01) / C8 (T02)
A91: FL_MAT_ABC_2.5kg | B91: 2 | C91: ABC2.5-A1 | D91: Polvo químico seco ABC 60 (Sello IRAM 3569) | E91: 2.55 | F91: kg | G91: 1 | H91: =E91*G91 | I91: Polvo químico seco ABC 60 (Sello IRAM 3569) | J91: nominal 2,5 kg; tolerancia 0 / +100 g (IRAM 3517-2:2020 tabla 3 · IRAM 3523 tabla II) | K91: Compra | L91: Sí | M91: DEM S.A. (DEMSA) | N91: Polvex S.R.L. / Sancibrao | O91: SP-1 almacén previo a la carga | P91: IRAM 3569 | Q91: N | S91: Composición declarada del polvo ABC 60: MAP 60 % (IRAM 3569: 57-63 %) = 1,53 kg MAP + 0,943 kg sulfato de amonio + 0,076 kg aditivos · potencial de referencia 3A-20B:C (licencia Drago con DEM-60/90, L-DRAGO) · Decisión: DEMSA principal (sello IRAM 3569 y potencial de referencia); Polvex/Sancibrao alternativa sujeta a sello IRAM 3569 y ensayo de tipo de FLAMA (IRAM 3542/3543) · Lote único por extintor; prohibido mezclar ABC con BC (3517-2 9.9.1.6)
A92: FL_MAT_ABC_2.5kg | B92: 2 | C92: ABC2.5-A2 | D92: Gas impulsor: N₂ | E92: 0.0212 | F92: kg | G92: 1 | H92: =E92*G92 | I92: N₂ | J92: 16,9 L normales para 1,4 MPa a 20 °C en 1,23 dm³ libres | K92: Compra | L92: Sí | M92: Air Liquide Argentina - sucursal Piñeyro | N92: Gogniat | O92: 20 Presurización (T05) / C10 | P92: IRAM 3517-2 9.4.9 (tabla 2) · IRAM 3523 2.3 y 3.10 | Q92: C | S92: N₂ ≥ 99,8 %, H₂O ≤ 40 ppm (Q-N2, Air Liquide) · volumen libre con ρ empacada mínima 1,1 kg/dm³ (NOM-104-STPS-2001); confirmar con descarga ≥ 85 % (IRAM 3523 4.9.1)
A93: FL_MAT_ABC_2.5kg | B93: 1 | C93: ABC2.5-S6 | D93: Identificación y precinto | E93: 1 | F93: u | H93: =H94+H95+H96+H97+H98+H99+H100 | K93: Compra | O93: 22 Etiquetado (T07)
A94: FL_MAT_ABC_2.5kg | B94: 2 | C94: ABC2.5-20 | D94: Etiqueta / placa de características | E94: 1 | F94: u | G94: 0.0149 | H94: =E94*G94 | I94: Vinilo autoadhesivo laminado | J94: 234 × 152 (desarrollo × alto: panel central 108° + 2 alas laterales), e ≈ 0,3, laminado UV | K94: Compra | L94: Sí | M94: Astuprint | N94: Multilabel Argentina S.A. | O94: 22 Etiquetado (T07) | P94: IRAM 3534 · IRAM 3523 cap. 5 · relevamiento de mercado | Q94: P | R94: FL_DES_ABC_2.5kg | S94: IRAM 3534
A95: FL_MAT_ABC_2.5kg | B95: 2 | C95: ABC2.5-21 | D95: Oblea de fabricación (PBA) | E95: 1 | F95: u | G95: 0.0009 | H95: =E95*G95 | I95: Papel de seguridad autodestructible | J95: Ø46 (Res. OPDS 522/07), numerada, autodestructible | K95: Compra | L95: Sí | M95: Ministerio de Ambiente PBA (ex OPDS) | N95: - | O95: 22 Etiquetado (T07) | P95: Res. OPDS 522/07 anexos 1, 2 y 6 | Q95: P | R95: FL_DES_ABC_2.5kg | S95: Res. 522/07
A96: FL_MAT_ABC_2.5kg | B96: 2 | C96: ABC2.5-22 | D96: Estampilla IRAM de conformidad | E96: 1 | F96: u | G96: 0.001 | H96: =E96*G96 | I96: Provista por IRAM (Anexo R) | J96: 60 × 40 | K96: Compra | L96: Sí | M96: IRAM - Instituto Argentino de Normalización | N96: - | O96: 22 Etiquetado (T07) | P96: IRAM Anexo R (DC-PG-129) | Q96: P | R96: FL_DES_ABC_2.5kg | S96: numerada
A97: FL_MAT_ABC_2.5kg | B97: 2 | C97: ABC2.5-23 | D97: Tarjeta de identificación AGC (CABA) | E97: 1 | F97: u | G97: 0.0032 | H97: =E97*G97 | I97: Etiqueta autoadhesiva emitida por la AGC | J97: 140 × 55 | K97: Compra | L97: Sí | M97: Agencia Gubernamental de Control (CABA) | N97: - | O97: 22 Etiquetado (T07) | P97: Ordenanza 40.473 art. 6 · Res. AGC 32/15 | Q97: P | R97: FL_DES_ABC_2.5kg | S97: sólo destino CABA
A98: FL_MAT_ABC_2.5kg | B98: 2 | C98: ABC2.5-24 | D98: Etiqueta de n° de serie GS1 | E98: 1 | F98: u | G98: 0.0005 | H98: =E98*G98 | I98: Poliéster autoadhesivo impreso térmico | J98: 45 × 25 | K98: Compra | L98: Sí | M98: Astuprint | N98: GS1 Argentina | O98: 22 Etiquetado (T07) | P98: GS1 Argentina (GTIN 779) · trazabilidad IRAM 3523 5.1 | Q98: P | R98: FL_DES_ABC_2.5kg | S98: QR GTIN + serie
A99: FL_MAT_ABC_2.5kg | B99: 2 | C99: ABC2.5-26 | D99: Faja de garantía válvula-cuello | E99: 1 | F99: u | G99: 0.0001 | H99: =E99*G99 | I99: Vinilo destructible rayado rojo/blanco | J99: 22 × 22 (ancho × largo desarrollado), pegada sobre la unión: cuerpo de la válvula, tuerca y cuello | K99: Compra | L99: Sí | M99: Astuprint | N99: Multilabel Argentina S.A. | O99: 22 Etiquetado (T07) | P99: Sin norma: práctica de mercado (garantía de fábrica) | Q99: P | R99: FL_DES_ABC_2.5kg | S99: nuevo sin abrir
A100: FL_MAT_ABC_2.5kg | B100: 2 | C100: ABC2.5-27 | D100: Precinto de fábrica | E100: 1 | F100: u | G100: 0.0002 | H100: =E100*G100 | I100: Polipropileno color | J100: Ø5 × 10, numerado, rotura 30-50 N | K100: Compra | L100: Sí | M100: SonFuertes (vía Papelera Damián) | N100: Precinter S.R.L. | O100: 20 Presurización (T05) | P100: IRAM 3523 3.3.2 · IRAM 3517-2:2020 9.4.13 | Q100: P | R100: FL_DES_ABC_2.5kg | S100: id. FLAMA y lote
A101: FL_MAT_ABC_2.5kg | B101: 1 | C101: ABC2.5-S8 | D101: Soporte (accesorio de montaje) | E101: 1 | F101: u | H101: =H102 | K101: Compra | O101: 23 Embalaje (va dentro de la caja) | P101: IRAM 3517-2 7.4
...

Sheet 05_BOM_Cilindros
A1: BOM de cilindros sueltos FL_REC
A2: Colores: | B2: Validado | D2: Estimado | F2: A validar | H2: No cumple o decisión pendiente
A4: Producto | B4: Nivel | C4: Código | D4: Descripción | E4: Cant. | F4: UM | G4: Peso unit. (kg/UM) | H4: Peso total (kg) | I4: Material | J4: Medida (mm) | K4: Origen | L4: Entra MRP | M4: Proveedor principal | N4: Alternativa | O4: Operación / puesto (layout FLAMA) | P4: Norma / referencia | Q4: Fte. | R4: Plano | S4: Observaciones
A5: FL_REC_ABC_1kg | B5: 0 | C5: FL_REC_ABC_1kg | D5: Cilindro (recipiente) ABC 1 kg - repuesto vacío sin válvula | E5: 1 | F5: u | P5: IRAM 3523 | Q5: P | R5: FL_REC_ABC_1kg | S5: Fabricación propia
A6: FL_REC_ABC_1kg | B6: 1 | C6: ABC1-S1 | D6: Recipiente (cilindro) | E6: 1 | F6: u | H6: =H7+H9+H11+H13+H14+H21 | K6: Fabricación | P6: IRAM 3523 / 3550 (recipiente) | Q6: P | R6: FL_DES_ABC_1kg
A7: FL_REC_ABC_1kg | B7: 2 | C7: ABC1-01 | D7: Cuerpo (virola) | E7: 1 | F7: u | G7: 0.6072 | H7: =E7*G7 | I7: Caño c-c LF Ø76,2 e=1,25 (SAE 1010) | J7: Ø76,2 × e1,25 × 263,4 de alto; desarrollo 235,5 × 263,4 | K7: Fabricación | L7: No | O7: 5 Corte láser de caño (M15/M16) -> 9 encastre -> 10 bordoneado (los dos extremos) | Q7: P | R7: FL_DES_ABC_1kg | S7: costura long. MAG
A8: FL_REC_ABC_1kg | B8: 3 | C8: MP-CANO | D8: Caño Ø76,2 × 1,25 (tramo de barra de 6 m) | E8: 0.0435 | F8: barra | G8: 14.288 | H8: =E8*G8 | I8: Caño acero SAE 1010 con costura | J8: 255 mm por cuerpo; 23 cuerpos por barra (kg por barra) | K8: Compra | L8: Sí | M8: Metalpri / Prilux | N8: Comercial MID | O8: AL-1T cantiléver | Q8: L | R8: FL_PI_04 h2
A9: FL_REC_ABC_1kg | B9: 2 | C9: ABC1-02 | D9: Cúpula | E9: 1 | F9: u | G9: 0.0335 | H9: =E9*G9 | I9: Chapa LAF IRAM-IAS U 500-05 e=0,9 | J9: Ø76,2 × e0,9 × 12,1 de alto; disco Ø108 | K9: Fabricación | L9: No | O9: 6 Desbobinado + embutido (M06-M08) -> numerado de cúpula (micropercusión, en arco junto al cuello) -> 8 soldadura de cuello | Q9: P | R9: FL_DES_ABC_1kg | S9: embutida
A10: FL_REC_ABC_1kg | B10: 3 | C10: MP-FLEJE | D10: Fleje e=0,9 × 114 (paso 111) | E10: 0.111 | F10: m | G10: 0.805 | H10: =E10*G10 | I10: Fleje SAE 1010 | J10: disco Ø108 (kg por m de fleje) | K10: Compra | L10: Sí | M10: Pacheco Chapas | N10: Pradecon S.A. | O10: AL-1F porta-flejes | Q10: L | R10: FL_PI_04 h2
A11: FL_REC_ABC_1kg | B11: 2 | C11: ABC1-03 | D11: Fondo | E11: 1 | F11: u | G11: 0.0662 | H11: =E11*G11 | I11: Chapa LAF IRAM-IAS U 500-05 e=1,25 | J11: Ø76,2 × e1,25 × 22 de alto; disco Ø100 | K11: Fabricación | L11: No | O11: 6 Desbobinado + embutido (M06-M08) | Q11: P | R11: FL_DES_ABC_1kg | S11: embutido
A12: FL_REC_ABC_1kg | B12: 3 | C12: MP-FLEJE | D12: Fleje e=1,25 × 106 (paso 103) | E12: 0.103 | F12: m | G12: 1.04 | H12: =E12*G12 | I12: Fleje SAE 1010 | J12: disco Ø100 (kg por m de fleje) | K12: Compra | L12: Sí | M12: Pacheco Chapas | N12: Pradecon S.A. | O12: AL-1F porta-flejes | Q12: L | R12: FL_PI_04 h2
A13: FL_REC_ABC_1kg | B13: 2 | C13: ABC1-04 | D13: Cuello roscado | E13: 1 | F13: u | G13: 0.0358 | H13: =E13*G13 | I13: Acero SAE 1010 | J13: Ø29 × 12,5 de alto, rosca M22x1,5, asiento Ø26 | K13: Compra (mecanizado, Eli-Met) | L13: Sí | M13: Eli-Met | N13: - | O13: Compra -> 8 soldadura de cuello | Q13: P | R13: FL_DES_ABC_1kg | S13: M22x1,5
A14: FL_REC_ABC_1kg | B14: 2 | C14: ABC1-C1 | D14: Alambre MAG ER70S-6 Ø0,9 (AWS A5.18) | E14: 0.0146 | F14: kg | G14: 0.95 | H14: =E14*G14 | I14: ER70S-6 | J14: metal depositado de los cordones del plano 14 g / rendimiento 0,95 | K14: Compra | L14: Sí | M14: Conarco (ESAB Argentina) | N14: - | O14: 4 sold. long. / 8 cuello / 11 circunferencial | P14: IRAM 3523 3.2.4.2 · IRAM 3550 4.1.2 | Q14: C | S14: Peso unit. = fracción que queda en la pieza (el resto es salpicadura). Depositado = volumen de los cordones del modelo × 7,85. Rendimiento de deposición del alambre macizo MAG 90-97 % (ESAB): se adopta 0,95. Medir en la prueba de soldadura del equipo (Getweld)
A15: FL_REC_ABC_1kg | B15: 2 | C15: ABC1-C2 | D15: Gas de protección MAG Arcal 21 / ARCAL Speed (Ar + 8 % CO₂, M20) | E15: 13.3 | F15: L | I15: EN ISO 14175 M20-ArC-8 | J15: 14 L/min × 0,95 min de arco (cordones 570 mm: long. 0 + circ. 479 + cuello 91, a 600 mm/min) | K15: Compra | L15: Sí | M15: Air Liquide Argentina - sucursal Piñeyro | N15: Gogniat | O15: Colector SC | P15: IRAM 3523 3.2.4.2 · IRAM 3550 3.2.2.2 | Q15: C | S15: Caudal 12-16 L/min para alambre 0,9-1,2 (Air Liquide; Ingemecánica): se adopta 14. Velocidad: Getweld 0-1500 mm/min; se adopta 600. Decisión FLAMA: MAG 135 con Arcal 21; la norma nombra «atmósfera inerte»: acreditar con el certificador en el ensayo de tipo. No incluye la soldadura del carro
A16: FL_REC_ABC_1kg | B16: 2 | C16: ABC1-C3 | D16: Granalla de acero S330 / S390 (ISO 11124-3, SAE J444) | E16: 0.08 | F16: kg | I16: Granalla esférica alto C | J16: 0,073 m² a Sa 2½ (ISO 8501-1); 3,4 kg/h ÷ 42,5 u/h | K16: Compra | L16: Sí | M16: CyM Materiales | N16: Roca Ingeniería | O16: 14 Granallado (B08) | P16: DOC-01 | Q16: C | S16: Consumo (desgaste) por turbina ≈ HP / 2 lb/h (The Fabricator, «aspectos básicos del granallado por turbina»): G-100 con 2 × 7,5 HP = 7,5 lb/h = 3,4 kg/h; ritmo 340 u por turno (Getweld) = 42,5 u/h. OJO: Ø76,2 fuera del rango de la Airblast G-100 (Ø80-200): definir soporte o equipo
A17: FL_REC_ABC_1kg | B17: 2 | C17: ABC1-C4 | D17: Servicio de pintura en polvo al horno, rojo 03-1-050 | E17: 1 | F17: u | I17: Servicio tercerizado | J17: superficie exterior 0,073 m² | K17: Compra (servicio) | L17: Sí | M17: Prymax | N17: Pintor de carros (cotización por mensaje) | O17: 17 Pintura tercerizada | P17: IRAM 3523 5.3 / IRAM 3550 3.11 · IRAM 121 | Q17: Q | S17: Q-PRYMAX (precio por cilindro); exigir informe de niebla salina del sistema de pintura; tercerización aceptada por el Ministerio (Res. 349/07 art. 18)
A18: FL_REC_ABC_1kg | B18: 2 | C18: ABC1-T1 | D18: Tapón protector de rosca del cuello | E18: 1 | F18: u | I18: Polietileno | J18: para rosca M22x1,5 (plano FL_REC_ABC_1kg hoja 3, R4) | K18: Compra | L18: Sí | M18: - | N18: - | O18: Embalaje | Q18: P
A19: FL_REC_ABC_1kg | B19: 2 | C19: ABC1-T2 | D19: Marcado del recipiente: estampado en la cúpula, en arco junto al cuello (puesto de numerado de cúpula) | E19: 1 | F19: u | I19: - | J19: Fabricante, n° de serie, año; en arco junto al cuello, letra 5 mm; cuño DPS 15 × 7 junto al n° | K19: Proceso | L19: No | O19: Marcado | P19: IRAM 3523 5.1 · Res. 349/07 anexo IV | Q19: N
A20: FL_REC_ABC_1kg | B20: 2 | C20: ABC1-T3 | D20: Etiqueta de identificación del cilindro suelto | E20: 1 | F20: u | I20: Poliéster autoadhesivo removible | J20: 100 × 60, impresión térmica, QR GS1 | K20: Compra | L20: Sí | M20: Astuprint | N20: GS1 Argentina | O20: Etiquetado | Q20: P | R20: FL_REC_ABC_1kg hoja 3
A21: FL_REC_ABC_1kg | B21: 2 | C21: ABC1-T4 | D21: Protocolo de ensayo hidrostático (certificado que acompaña) | E21: 1 | F21: u | G21: 0.005 | H21: =E21*G21 | I21: Papel | J21: A5 | K21: Proceso | L21: No | O21: Control de calidad | P21: IRAM 3523 4.1 y cap. 6 · IRAM 2587 | Q21: N | R21: FL_REC_ABC_1kg hoja 3
A22: FL_REC_ABC_1kg | B22: 1 | C22: ABC1-S7 | D22: Embalaje | E22: 1 | F22: u | H22: =H25 | K22: Compra | O22: 23 Embalaje -> 24 envolvedora (T11)
A23: FL_REC_ABC_1kg | B23: 2 | C23: ABC1-E1 | D23: Caja de cartón corrugado simple | E23: 1 | F23: u | I23: Cartón corrugado | J23: 106 × 106 × 318 interior (envolvente del plano + 15 por lado) | K23: Compra | L23: Sí | M23: Maxipack | N23: Cartocan | O23: 23 Embalaje | Q23: P | S23: Medida del plano
A24: FL_REC_ABC_1kg | B24: 2 | C24: ABC1-E3 | D24: Pallet 1200 × 1000 (fracción) | E24: 0.0025 | F24: u | I24: Madera | J24: 396 u por pallet | K24: Compra | L24: Sí | M24: IndusPallets | N24: - | O24: 23 Embalaje | Q24: C | S24: u por pallet = acomodo de la caja (plano) en 1200 × 1000 × 1450 de alto
A25: FL_REC_ABC_1kg | B25: 2 | C25: ABC1-E4 | D25: Film stretch (fracción del pallet) | E25: 0.0003 | F25: kg | G25: 1 | H25: =E25*G25 | I25: PE lineal 23 µm | J25: 0,12 kg por pallet / 396 u | K25: Compra | L25: Sí | M25: MV Embalajes | N25: Embalpack | O25: 24 Envolvedora (T11) | Q25: C | S25: Perímetro del pallet 4,4 m × 9 vueltas = 40 m aplicados; con pre-estirado 250 % (1 m de bobina = 3,5 m aplicados) = 11,4 m de bobina × 0,5 m × 23 µm × 0,92 g/cm³ = 0,12 kg. Fuentes: fichas de film 23 µm × 500 mm (MV Embalajes / Embalpack) y pre-estirado de la envolvedora. Medir en la puesta en marcha
A26: FL_REC_ABC_1kg | B26: 2 | C26: ABC1-E5 | D26: Etiqueta de pallet (lote y destino, fracción) | E26: 0.0025 | F26: u | I26: Papel térmico | J26: 100 × 150 | K26: Compra | L26: Sí | M26: Astuprint | N26: Multilabel Argentina S.A. | O26: 24 Envolvedora | Q26: C
A27: FL_REC_ABC_1kg | B27: 2 | C27: ABC1-E6 | D27: Cinta de embalaje PP 48 mm (cierre de la caja) | E27: 0.492 | F27: m | I27: Polipropileno con adhesivo acrílico | J27: cierre en I arriba y abajo: 2 × (106 + 2 × 70 de solapa) | K27: Compra | L27: Sí | M27: MV Embalajes | N27: Embalpack | O27: 23 Embalaje | Q27: C | S27: Solapa de 70 mm por lado: práctica de cierre de cajas (medir en la línea)
A28: FL_REC_ABC_1kg | B28: 2 | C28: ABC1-E7 | D28: Esquineros de cartón 50 × 50 × 1200 (fracción del pallet) | E28: 0.0101 | F28: u | I28: Cartón | J28: 4 por pallet / 396 u | K28: Compra | L28: Sí | M28: Maxipack | N28: Cartocan | O28: 24 Envolvedora (T11) | Q28: C | S28: Planilla MP-64
A29: FL_REC_ABC_1kg | B29: 2 | C29: ABC1-E8 | D29: Separador de capa de cartón 1200 × 1000 (fracción del pallet) | E29: 0.0076 | F29: u | I29: Cartón | J29: 4 capas → 3 separadores por pallet / 396 u | K29: Compra | L29: Sí | M29: Maxipack | N29: Cartocan | O29: 23 Embalaje | Q29: C | S29: Planilla MP-61
A30: FL_REC_ABC_2.5kg | B30: 0 | C30: FL_REC_ABC_2.5kg | D30: Cilindro (recipiente) ABC 2,5 kg - repuesto vacío sin válvula | E30: 1 | F30: u | P30: IRAM 3523 | Q30: P | R30: FL_REC_ABC_2.5kg | S30: Fabricación propia
A31: FL_REC_ABC_2.5kg | B31: 1 | C31: ABC2.5-S1 | D31: Recipiente (cilindro) | E31: 1 | F31: u | H31: =H32+H34+H36+H38+H39+H46 | K31: Fabricación | P31: IRAM 3523 / 3550 (recipiente) | Q31: P | R31: FL_DES_ABC_2.5kg
A32: FL_REC_ABC_2.5kg | B32: 2 | C32: ABC2.5-01 | D32: Cuerpo (virola) | E32: 1 | F32: u | G32: 1.011 | H32: =E32*G32 | I32: Chapa LAF IRAM-IAS U 500-05 e=1,25 | J32: Ø124 × e1,25 × 267,4 de alto; desarrollo 385,6 × 267,4 | K32: Fabricación | L32: No | O32: 1 Guillotina -> 3 cilindrado -> 4 soldadura longitudinal -> 9 encastre del fondo -> 10 bordoneado | Q32: P | R32: FL_DES_ABC_2.5kg | S32: costura long. MAG
A33: FL_REC_ABC_2.5kg | B33: 3 | C33: MP-HOJA | D33: Recorte de hoja LAF 1220 × 2440 e=1,25 | E33: 1 | F33: u | G33: 1.082 | H33: =E33*G33 | I33: Chapa LAF IRAM-IAS U 500-05 LAF | J33: 385,5 × 269,5 (aprovech. 94,2 %) | K33: Compra | L33: Sí | M33: Pradecon S.A. | N33: Pacheco Chapas | O33: AL-1H paquetes de hojas | Q33: L | R33: FL_PI_04 h2
A34: FL_REC_ABC_2.5kg | B34: 2 | C34: ABC2.5-02 | D34: Cúpula | E34: 1 | F34: u | G34: 0.1734 | H34: =E34*G34 | I34: Chapa LAF IRAM-IAS U 500-05 e=1,25 | J34: Ø124 × e1,25 × 38,1 de alto; disco Ø179 | K34: Fabricación | L34: No | O34: 6 Desbobinado + embutido (M06-M08) -> numerado de cúpula (micropercusión, en arco junto al cuello) -> 8 soldadura de cuello | Q34: P | R34: FL_DES_ABC_2.5kg | S34: embutida
A35: FL_REC_ABC_2.5kg | B35: 3 | C35: MP-FLEJE | D35: Fleje e=1,25 × 200 (paso 182) | E35: 0.182 | F35: m | G35: 1.962 | H35: =E35*G35 | I35: Fleje SAE 1010 | J35: disco Ø179 (kg por m de fleje) | K35: Compra | L35: Sí | M35: Pacheco Chapas | N35: Pradecon S.A. | O35: AL-1F porta-flejes | Q35: L | R35: FL_PI_04 h2
A36: FL_REC_ABC_2.5kg | B36: 2 | C36: ABC2.5-03 | D36: Fondo | E36: 1 | F36: u | G36: 0.1657 | H36: =E36*G36 | I36: Chapa LAF IRAM-IAS U 500-05 e=1,25 | J36: Ø124 × e1,25 × 20,5 de alto; disco Ø148 | K36: Fabricación | L36: No | O36: 6 Desbobinado + embutido (M06-M08) | Q36: P | R36: FL_DES_ABC_2.5kg | S36: embutido
A37: FL_REC_ABC_2.5kg | B37: 3 | C37: MP-FLEJE | D37: Fleje e=1,25 × 200 (paso 151) | E37: 0.151 | F37: m | G37: 1.962 | H37: =E37*G37 | I37: Fleje SAE 1010 | J37: disco Ø148 (kg por m de fleje) | K37: Compra | L37: Sí | M37: Pacheco Chapas | N37: Pradecon S.A. | O37: AL-1F porta-flejes | Q37: L | R37: FL_PI_04 h2
A38: FL_REC_ABC_2.5kg | B38: 2 | C38: ABC2.5-04 | D38: Cuello roscado | E38: 1 | F38: u | G38: 0.0545 | H38: =E38*G38 | I38: Acero SAE 1010 | J38: Ø37 × 14 de alto, rosca M30x1,5, asiento Ø35 | K38: Compra (mecanizado, Eli-Met) | L38: Sí | M38: Eli-Met | N38: - | O38: Compra -> 8 soldadura de cuello | Q38: P | R38: FL_DES_ABC_2.5kg | S38: M30x1,5
A39: FL_REC_ABC_2.5kg | B39: 2 | C39: ABC2.5-C1 | D39: Alambre MAG ER70S-6 Ø0,9 (AWS A5.18) | E39: 0.0292 | F39: kg | G39: 0.95 | H39: =E39*G39 | I39: ER70S-6 | J39: metal depositado de los cordones del plano 28 g / rendimiento 0,95 | K39: Compra | L39: Sí | M39: Conarco (ESAB Argentina) | N39: - | O39: 4 sold. long. / 8 cuello / 11 circunferencial | P39: IRAM 3523 3.2.4.2 · IRAM 3550 4.1.2 | Q39: C | S39: Peso unit. = fracción que queda en la pieza (el resto es salpicadura). Depositado = volumen de los cordones del modelo × 7,85. Rendimiento de deposición del alambre macizo MAG 90-97 % (ESAB): se adopta 0,95. Medir en la prueba de soldadura del equipo (Getweld)
A40: FL_REC_ABC_2.5kg | B40: 2 | C40: ABC2.5-C2 | D40: Gas de protección MAG Arcal 21 / ARCAL Speed (Ar + 8 % CO₂, M20) | E40: 27.1 | F40: L | I40: EN ISO 14175 M20-ArC-8 | J40: 14 L/min × 1,94 min de arco (cordones 1.163 mm: long. 267 + circ. 779 + cuello 116, a 600 mm/min) | K40: Compra | L40: Sí | M40: Air Liquide Argentina - sucursal Piñeyro | N40: Gogniat | O40: Colector SC | P40: IRAM 3523 3.2.4.2 · IRAM 3550 3.2.2.2 | Q40: C | S40: Caudal 12-16 L/min para alambre 0,9-1,2 (Air Liquide; Ingemecánica): se adopta 14. Velocidad: Getweld 0-1500 mm/min; se adopta 600. Decisión FLAMA: MAG 135 con Arcal 21; la norma nombra «atmósfera inerte»: acreditar con el certificador en el ensayo de tipo. No incluye la soldadura del carro
A41: FL_REC_ABC_2.5kg | B41: 2 | C41: ABC2.5-C3 | D41: Granalla de acero S330 / S390 (ISO 11124-3, SAE J444) | E41: 0.08 | F41: kg | I41: Granalla esférica alto C | J41: 0,138 m² a Sa 2½ (ISO 8501-1); 3,4 kg/h ÷ 42,5 u/h | K41: Compra | L41: Sí | M41: CyM Materiales | N41: Roca Ingeniería | O41: 14 Granallado (B08) | P41: DOC-01 | Q41: C | S41: Consumo (desgaste) por turbina ≈ HP / 2 lb/h (The Fabricator, «aspectos básicos del granallado por turbina»): G-100 con 2 × 7,5 HP = 7,5 lb/h = 3,4 kg/h; ritmo 340 u por turno (Getweld) = 42,5 u/h.
A42: FL_REC_ABC_2.5kg | B42: 2 | C42: ABC2.5-C4 | D42: Servicio de pintura en polvo al horno, rojo 03-1-050 | E42: 1 | F42: u | I42: Servicio tercerizado | J42: superficie exterior 0,138 m² | K42: Compra (servicio) | L42: Sí | M42: Prymax | N42: Pintor de carros (cotización por mensaje) | O42: 17 Pintura tercerizada | P42: IRAM 3523 5.3 / IRAM 3550 3.11 · IRAM 121 | Q42: Q | S42: Q-PRYMAX (precio por cilindro); exigir informe de niebla salina del sistema de pintura; tercerización aceptada por el Ministerio (Res. 349/07 art. 18)
A43: FL_REC_ABC_2.5kg | B43: 2 | C43: ABC2.5-T1 | D43: Tapón protector de rosca del cuello | E43: 1 | F43: u | I43: Polietileno | J43: para rosca M30x1,5 (plano FL_REC_ABC_2.5kg hoja 3, R4) | K43: Compra | L43: Sí | M43: - | N43: - | O43: Embalaje | Q43: P
A44: FL_REC_ABC_2.5kg | B44: 2 | C44: ABC2.5-T2 | D44: Marcado del recipiente: estampado en la cúpula, en arco junto al cuello (puesto de numerado de cúpula) | E44: 1 | F44: u | I44: - | J44: Fabricante, n° de serie, año; en arco junto al cuello, letra 5 mm; cuño DPS 15 × 7 junto al n° | K44: Proceso | L44: No | O44: Marcado | P44: IRAM 3523 5.1 · Res. 349/07 anexo IV | Q44: N
A45: FL_REC_ABC_2.5kg | B45: 2 | C45: ABC2.5-T3 | D45: Etiqueta de identificación del cilindro suelto | E45: 1 | F45: u | I45: Poliéster autoadhesivo removible | J45: 100 × 60, impresión térmica, QR GS1 | K45: Compra | L45: Sí | M45: Astuprint | N45: GS1 Argentina | O45: Etiquetado | Q45: P | R45: FL_REC_ABC_2.5kg hoja 3
A46: FL_REC_ABC_2.5kg | B46: 2 | C46: ABC2.5-T4 | D46: Protocolo de ensayo hidrostático (certificado que acompaña) | E46: 1 | F46: u | G46: 0.005 | H46: =E46*G46 | I46: Papel | J46: A5 | K46: Proceso | L46: No | O46: Control de calidad | P46: IRAM 3523 4.1 y cap. 6 · IRAM 2587 | Q46: N | R46: FL_REC_ABC_2.5kg hoja 3
A47: FL_REC_ABC_2.5kg | B47: 1 | C47: ABC2.5-S7 | D47: Embalaje | E47: 1 | F47: u | H47: =H50 | K47: Compra | O47: 23 Embalaje -> 24 envolvedora (T11)
A48: FL_REC_ABC_2.5kg | B48: 2 | C48: ABC2.5-E1 | D48: Caja de cartón corrugado simple | E48: 1 | F48: u | I48: Cartón corrugado | J48: 154 × 154 × 334 interior (envolvente del plano + 15 por lado) | K48: Compra | L48: Sí | M48: Maxipack | N48: Cartocan | O48: 23 Embalaje | Q48: P | S48: Medida del plano
A49: FL_REC_ABC_2.5kg | B49: 2 | C49: ABC2.5-E3 | D49: Pallet 1200 × 1000 (fracción) | E49: 0.006 | F49: u | I49: Madera | J49: 168 u por pallet | K49: Compra | L49: Sí | M49: IndusPallets | N49: - | O49: 23 Embalaje | Q49: C | S49: u por pallet = acomodo de la caja (plano) en 1200 × 1000 × 1450 de alto
A50: FL_REC_ABC_2.5kg | B50: 2 | C50: ABC2.5-E4 | D50: Film stretch (fracción del pallet) | E50: 0.0007 | F50: kg | G50: 1 | H50: =E50*G50 | I50: PE lineal 23 µm | J50: 0,12 kg por pallet / 168 u | K50: Compra | L50: Sí | M50: MV Embalajes | N50: Embalpack | O50: 24 Envolvedora (T11) | Q50: C | S50: Perímetro del pallet 4,4 m × 9 vueltas = 40 m aplicados; con pre-estirado 250 % (1 m de bobina = 3,5 m aplicados) = 11,4 m de bobina × 0,5 m × 23 µm × 0,92 g/cm³ = 0,12 kg. Fuentes: fichas de film 23 µm × 500 mm (MV Embalajes / Embalpack) y pre-estirado de la envolvedora. Medir en la puesta en marcha
A51: FL_REC_ABC_2.5kg | B51: 2 | C51: ABC2.5-E5 | D51: Etiqueta de pallet (lote y destino, fracción) | E51: 0.006 | F51: u | I51: Papel térmico | J51: 100 × 150 | K51: Compra | L51: Sí | M51: Astuprint | N51: Multilabel Argentina S.A. | O51: 24 Envolvedora | Q51: C
A52: FL_REC_ABC_2.5kg | B52: 2 | C52: ABC2.5-E6 | D52: Cinta de embalaje PP 48 mm (cierre de la caja) | E52: 0.588 | F52: m | I52: Polipropileno con adhesivo acrílico | J52: cierre en I arriba y abajo: 2 × (154 + 2 × 70 de solapa) | K52: Compra | L52: Sí | M52: MV Embalajes | N52: Embalpack | O52: 23 Embalaje | Q52: C | S52: Solapa de 70 mm por lado: práctica de cierre de cajas (medir en la línea)
A53: FL_REC_ABC_2.5kg | B53: 2 | C53: ABC2.5-E7 | D53: Esquineros de cartón 50 × 50 × 1200 (fracción del pallet) | E53: 0.0238 | F53: u | I53: Cartón | J53: 4 por pallet / 168 u | K53: Compra | L53: Sí | M53: Maxipack | N53: Cartocan | O53: 24 Envolvedora (T11) | Q53: C | S53: Planilla MP-64
A54: FL_REC_ABC_2.5kg | B54: 2 | C54: ABC2.5-E8 | D54: Separador de capa de cartón 1200 × 1000 (fracción del pallet) | E54: 0.0179 | F54: u | I54: Cartón | J54: 4 capas → 3 separadores por pallet / 168 u | K54: Compra | L54: Sí | M54: Maxipack | N54: Cartocan | O54: 23 Embalaje | Q54: C | S54: Planilla MP-61
A55: FL_REC_ABC_5kg | B55: 0 | C55: FL_REC_ABC_5kg | D55: Cilindro (recipiente) ABC 5 kg - repuesto vacío sin válvula | E55: 1 | F55: u | P55: IRAM 3523 | Q55: P | R55: FL_REC_ABC_5kg | S55: Fabricación propia
A56: FL_REC_ABC_5kg | B56: 1 | C56: ABC5-S1 | D56: Recipiente (cilindro) | E56: 1 | F56: u | H56: =H57+H59+H61+H63+H64+H71 | K56: Fabricación | P56: IRAM 3523 / 3550 (recipiente) | Q56: P | R56: FL_DES_ABC_5kg
A57: FL_REC_ABC_5kg | B57: 2 | C57: ABC5-01 | D57: Cuerpo (virola) | E57: 1 | F57: u | G57: 1.9541 | H57: =E57*G57 | I57: Chapa LAF IRAM-IAS U 500-05 e=1,6 | J57: Ø153 × e1,6 × 327,3 de alto; desarrollo 475,6 × 327,3 | K57: Fabricación | L57: No | O57: 1 Guillotina -> 3 cilindrado -> 4 soldadura longitudinal -> 9 encastre del fondo -> 10 bordoneado | Q57: P | R57: FL_DES_ABC_5kg | S57: costura long. MAG
A58: FL_REC_ABC_5kg | B58: 3 | C58: MP-HOJA | D58: Recorte de hoja LAF 1000 × 2000 e=1,6 | E58: 1 | F58: u | G58: 2.092 | H58: =E58*G58 | I58: Chapa LAF IRAM-IAS U 500-05 LAF | J58: 330 × 474,5 (aprovech. 94 %) | K58: Compra | L58: Sí | M58: Pradecon S.A. | N58: Pacheco Chapas | O58: AL-1H paquetes de hojas | Q58: L | R58: FL_PI_04 h2
A59: FL_REC_ABC_5kg | B59: 2 | C59: ABC5-02 | D59: Cúpula | E59: 1 | F59: u | G59: 0.3608 | H59: =E59*G59 | I59: Chapa LAF IRAM-IAS U 500-05 e=1,6 | J59: Ø153 × e1,6 × 53,2 de alto; disco Ø221 | K59: Fabricación | L59: No | O59: 6 Desbobinado + embutido (M06-M08) -> numerado de cúpula (micropercusión, en arco junto al cuello) -> 8 soldadura de cuello | Q59: P | R59: FL_DES_ABC_5kg | S59: embutida
A60: FL_REC_ABC_5kg | B60: 3 | C60: MP-FLEJE | D60: Fleje e=1,6 × 250 (paso 224) | E60: 0.224 | F60: m | G60: 3.14 | H60: =E60*G60 | I60: Fleje SAE 1010 | J60: disco Ø221 (kg por m de fleje) | K60: Compra | L60: Sí | M60: Pacheco Chapas | N60: Pradecon S.A. | O60: AL-1F porta-flejes | Q60: L | R60: FL_PI_04 h2
A61: FL_REC_ABC_5kg | B61: 2 | C61: ABC5-03 | D61: Fondo | E61: 1 | F61: u | G61: 0.3173 | H61: =E61*G61 | I61: Chapa LAF IRAM-IAS U 500-05 e=1,6 | J61: Ø153 × e1,6 × 26 de alto; disco Ø177 | K61: Fabricación | L61: No | O61: 6 Desbobinado + embutido (M06-M08) | Q61: P | R61: FL_DES_ABC_5kg | S61: embutido
A62: FL_REC_ABC_5kg | B62: 3 | C62: MP-FLEJE | D62: Fleje e=1,6 × 200 (paso 180) | E62: 0.18 | F62: m | G62: 2.512 | H62: =E62*G62 | I62: Fleje SAE 1010 | J62: disco Ø177 (kg por m de fleje) | K62: Compra | L62: Sí | M62: Pacheco Chapas | N62: Pradecon S.A. | O62: AL-1F porta-flejes | Q62: L | R62: FL_PI_04 h2
A63: FL_REC_ABC_5kg | B63: 2 | C63: ABC5-04 | D63: Cuello roscado | E63: 1 | F63: u | G63: 0.0589 | H63: =E63*G63 | I63: Acero SAE 1010 | J63: Ø37 × 15 de alto, rosca M30x1,5, asiento Ø35 | K63: Compra (mecanizado, Eli-Met) | L63: Sí | M63: Eli-Met | N63: - | O63: Compra -> 8 soldadura de cuello | Q63: P | R63: FL_DES_ABC_5kg | S63: M30x1,5
A64: FL_REC_ABC_5kg | B64: 2 | C64: ABC5-C1 | D64: Alambre MAG ER70S-6 Ø0,9 (AWS A5.18) | E64: 0.0551 | F64: kg | G64: 0.95 | H64: =E64*G64 | I64: ER70S-6 | J64: metal depositado de los cordones del plano 52 g / rendimiento 0,95 | K64: Compra | L64: Sí | M64: Conarco (ESAB Argentina) | N64: - | O64: 4 sold. long. / 8 cuello / 11 circunferencial | P64: IRAM 3523 3.2.4.2 · IRAM 3550 4.1.2 | Q64: C | S64: Peso unit. = fracción que queda en la pieza (el resto es salpicadura). Depositado = volumen de los cordones del modelo × 7,85. Rendimiento de deposición del alambre macizo MAG 90-97 % (ESAB): se adopta 0,95. Medir en la prueba de soldadura del equipo (Getweld)
A65: FL_REC_ABC_5kg | B65: 2 | C65: ABC5-C2 | D65: Gas de protección MAG Arcal 21 / ARCAL Speed (Ar + 8 % CO₂, M20) | E65: 32.8 | F65: L | I65: EN ISO 14175 M20-ArC-8 | J65: 14 L/min × 2,34 min de arco (cordones 1.405 mm: long. 327 + circ. 961 + cuello 116, a 600 mm/min) | K65: Compra | L65: Sí | M65: Air Liquide Argentina - sucursal Piñeyro | N65: Gogniat | O65: Colector SC | P65: IRAM 3523 3.2.4.2 · IRAM 3550 3.2.2.2 | Q65: C | S65: Caudal 12-16 L/min para alambre 0,9-1,2 (Air Liquide; Ingemecánica): se adopta 14. Velocidad: Getweld 0-1500 mm/min; se adopta 600. Decisión FLAMA: MAG 135 con Arcal 21; la norma nombra «atmósfera inerte»: acreditar con el certificador en el ensayo de tipo. No incluye la soldadura del carro
A66: FL_REC_ABC_5kg | B66: 2 | C66: ABC5-C3 | D66: Granalla de acero S330 / S390 (ISO 11124-3, SAE J444) | E66: 0.08 | F66: kg | I66: Granalla esférica alto C | J66: 0,21 m² a Sa 2½ (ISO 8501-1); 3,4 kg/h ÷ 42,5 u/h | K66: Compra | L66: Sí | M66: CyM Materiales | N66: Roca Ingeniería | O66: 14 Granallado (B08) | P66: DOC-01 | Q66: C | S66: Consumo (desgaste) por turbina ≈ HP / 2 lb/h (The Fabricator, «aspectos básicos del granallado por turbina»): G-100 con 2 × 7,5 HP = 7,5 lb/h = 3,4 kg/h; ritmo 340 u por turno (Getweld) = 42,5 u/h.
A67: FL_REC_ABC_5kg | B67: 2 | C67: ABC5-C4 | D67: Servicio de pintura en polvo al horno, rojo 03-1-050 | E67: 1 | F67: u | I67: Servicio tercerizado | J67: superficie exterior 0,21 m² | K67: Compra (servicio) | L67: Sí | M67: Prymax | N67: Pintor de carros (cotización por mensaje) | O67: 17 Pintura tercerizada | P67: IRAM 3523 5.3 / IRAM 3550 3.11 · IRAM 121 | Q67: Q | S67: Q-PRYMAX (precio por cilindro); exigir informe de niebla salina del sistema de pintura; tercerización aceptada por el Ministerio (Res. 349/07 art. 18)
A68: FL_REC_ABC_5kg | B68: 2 | C68: ABC5-T1 | D68: Tapón protector de rosca del cuello | E68: 1 | F68: u | I68: Polietileno | J68: para rosca M30x1,5 (plano FL_REC_ABC_5kg hoja 3, R4) | K68: Compra | L68: Sí | M68: - | N68: - | O68: Embalaje | Q68: P
A69: FL_REC_ABC_5kg | B69: 2 | C69: ABC5-T2 | D69: Marcado del recipiente: estampado en la cúpula, en arco junto al cuello (puesto de numerado de cúpula) | E69: 1 | F69: u | I69: - | J69: Fabricante, n° de serie, año; en arco junto al cuello, letra 5 mm; cuño DPS 15 × 7 junto al n° | K69: Proceso | L69: No | O69: Marcado | P69: IRAM 3523 5.1 · Res. 349/07 anexo IV | Q69: N
A70: FL_REC_ABC_5kg | B70: 2 | C70: ABC5-T3 | D70: Etiqueta de identificación del cilindro suelto | E70: 1 | F70: u | I70: Poliéster autoadhesivo removible | J70: 100 × 60, impresión térmica, QR GS1 | K70: Compra | L70: Sí | M70: Astuprint | N70: GS1 Argentina | O70: Etiquetado | Q70: P | R70: FL_REC_ABC_5kg hoja 3
A71: FL_REC_ABC_5kg | B71: 2 | C71: ABC5-T4 | D71: Protocolo de ensayo hidrostático (certificado que acompaña) | E71: 1 | F71: u | G71: 0.005 | H71: =E71*G71 | I71: Papel | J71: A5 | K71: Proceso | L71: No | O71: Control de calidad | P71: IRAM 3523 4.1 y cap. 6 · IRAM 2587 | Q71: N | R71: FL_REC_ABC_5kg hoja 3
A72: FL_REC_ABC_5kg | B72: 1 | C72: ABC5-S7 | D72: Embalaje | E72: 1 | F72: u | H72: =H75 | K72: Compra | O72: 23 Embalaje -> 24 envolvedora (T11)
A73: FL_REC_ABC_5kg | B73: 2 | C73: ABC5-E1 | D73: Caja de cartón corrugado simple | E73: 1 | F73: u | I73: Cartón corrugado | J73: 183 × 183 × 410 interior (envolvente del plano + 15 por lado) | K73: Compra | L73: Sí | M73: Maxipack | N73: Cartocan | O73: 23 Embalaje | Q73: P | S73: Medida del plano
A74: FL_REC_ABC_5kg | B74: 2 | C74: ABC5-E3 | D74: Pallet 1200 × 1000 (fracción) | E74: 0.0111 | F74: u | I74: Madera | J74: 90 u por pallet | K74: Compra | L74: Sí | M74: IndusPallets | N74: - | O74: 23 Embalaje | Q74: C | S74: u por pallet = acomodo de la caja (plano) en 1200 × 1000 × 1450 de alto
A75: FL_REC_ABC_5kg | B75: 2 | C75: ABC5-E4 | D75: Film stretch (fracción del pallet) | E75: 0.0013 | F75: kg | G75: 1 | H75: =E75*G75 | I75: PE lineal 23 µm | J75: 0,12 kg por pallet / 90 u | K75: Compra | L75: Sí | M75: MV Embalajes | N75: Embalpack | O75: 24 Envolvedora (T11) | Q75: C | S75: Perímetro del pallet 4,4 m × 9 vueltas = 40 m aplicados; con pre-estirado 250 % (1 m de bobina = 3,5 m aplicados) = 11,4 m de bobina × 0,5 m × 23 µm × 0,92 g/cm³ = 0,12 kg. Fuentes: fichas de film 23 µm × 500 mm (MV Embalajes / Embalpack) y pre-estirado de la envolvedora. Medir en la puesta en marcha
A76: FL_REC_ABC_5kg | B76: 2 | C76: ABC5-E5 | D76: Etiqueta de pallet (lote y destino, fracción) | E76: 0.0111 | F76: u | I76: Papel térmico | J76: 100 × 150 | K76: Compra | L76: Sí | M76: Astuprint | N76: Multilabel Argentina S.A. | O76: 24 Envolvedora | Q76: C
A77: FL_REC_ABC_5kg | B77: 2 | C77: ABC5-E6 | D77: Cinta de embalaje PP 48 mm (cierre de la caja) | E77: 0.646 | F77: m | I77: Polipropileno con adhesivo acrílico | J77: cierre en I arriba y abajo: 2 × (183 + 2 × 70 de solapa) | K77: Compra | L77: Sí | M77: MV Embalajes | N77: Embalpack | O77: 23 Embalaje | Q77: C | S77: Solapa de 70 mm por lado: práctica de cierre de cajas (medir en la línea)
A78: FL_REC_ABC_5kg | B78: 2 | C78: ABC5-E7 | D78: Esquineros de cartón 50 × 50 × 1200 (fracción del pallet) | E78: 0.0444 | F78: u | I78: Cartón | J78: 4 por pallet / 90 u | K78: Compra | L78: Sí | M78: Maxipack | N78: Cartocan | O78: 24 Envolvedora (T11) | Q78: C | S78: Planilla MP-64
A79: FL_REC_ABC_5kg | B79: 2 | C79: ABC5-E8 | D79: Separador de capa de cartón 1200 × 1000 (fracción del pallet) | E79: 0.0222 | F79: u | I79: Cartón | J79: 3 capas → 2 separadores por pallet / 90 u | K79: Compra | L79: Sí | M79: Maxipack | N79: Cartocan | O79: 23 Embalaje | Q79: C | S79: Planilla MP-61
A80: FL_REC_ABC_10kg | B80: 0 | C80: FL_REC_ABC_10kg | D80: Cilindro (recipiente) ABC 10 kg - repuesto vacío sin válvula | E80: 1 | F80: u | P80: IRAM 3523 | Q80: P | R80: FL_REC_ABC_10kg | S80: Fabricación propia
A81: FL_REC_ABC_10kg | B81: 1 | C81: ABC10-S1 | D81: Recipiente (cilindro) | E81: 1 | F81: u | H81: =H82+H84+H86+H88+H89+H96 | K81: Fabricación | P81: IRAM 3523 / 3550 (recipiente) | Q81: P | R81: FL_DES_ABC_10kg
A82: FL_REC_ABC_10kg | B82: 2 | C82: ABC10-01 | D82: Cuerpo (virola) | E82: 1 | F82: u | G82: 4.3636 | H82: =E82*G82 | I82: Chapa LAF IRAM-IAS U 500-05 e=2 | J82: Ø181,5 × e2 × 493,1 de alto; desarrollo 563,9 × 493,1 | K82: Fabricación | L82: No | O82: 1 Guillotina -> 3 cilindrado -> 4 soldadura longitudinal -> 9 encastre del fondo -> 10 bordoneado | Q82: P | R82: FL_DES_ABC_10kg | S82: costura long. MAG
A83: FL_REC_ABC_10kg | B83: 3 | C83: MP-HOJA | D83: Recorte de hoja LAF 1500 × 3000 e=2 | E83: 1 | F83: u | G83: 4.71 | H83: =E83*G83 | I83: Chapa LAF IRAM-IAS U 500-05 LAF | J83: 495 × 563 (aprovech. 92,9 %) | K83: Compra | L83: Sí | M83: Pradecon S.A. | N83: Pacheco Chapas | O83: AL-1H paquetes de hojas | Q83: L | R83: FL_PI_04 h2
A84: FL_REC_ABC_10kg | B84: 2 | C84: ABC10-02 | D84: Cúpula | E84: 1 | F84: u | G84: 0.501 | H84: =E84*G84 | I84: Chapa LAF IRAM-IAS U 500-05 e=1,6 | J84: Ø181,5 × e1,6 × 61,4 de alto; disco Ø258 | K84: Fabricación | L84: No | O84: 6 Desbobinado + embutido (M06-M08) -> numerado de cúpula (micropercusión, en arco junto al cuello) -> 8 soldadura de cuello | Q84: P | R84: FL_DES_ABC_10kg | S84: embutida
A85: FL_REC_ABC_10kg | B85: 3 | C85: MP-FLEJE | D85: Fleje e=1,6 × 300 (paso 261) | E85: 0.261 | F85: m | G85: 3.768 | H85: =E85*G85 | I85: Fleje SAE 1010 | J85: disco Ø258 (kg por m de fleje) | K85: Compra | L85: Sí | M85: Pacheco Chapas | N85: Pradecon S.A. | O85: AL-1F porta-flejes | Q85: L | R85: FL_PI_04 h2
A86: FL_REC_ABC_10kg | B86: 2 | C86: ABC10-03 | D86: Fondo | E86: 1 | F86: u | G86: 0.5084 | H86: =E86*G86 | I86: Chapa LAF IRAM-IAS U 500-05 e=2 | J86: Ø181,5 × e2 × 21,7 de alto; disco Ø205 | K86: Fabricación | L86: No | O86: 6 Desbobinado + embutido (M06-M08) | Q86: P | R86: FL_DES_ABC_10kg | S86: embutido
A87: FL_REC_ABC_10kg | B87: 3 | C87: MP-FLEJE | D87: Fleje e=2 × 249 (paso 208) | E87: 0.208 | F87: m | G87: 3.909 | H87: =E87*G87 | I87: Fleje SAE 1010 | J87: disco Ø205 (kg por m de fleje) | K87: Compra | L87: Sí | M87: Pacheco Chapas | N87: Pradecon S.A. | O87: AL-1F porta-flejes | Q87: L | R87: FL_PI_04 h2
A88: FL_REC_ABC_10kg | B88: 2 | C88: ABC10-04 | D88: Cuello roscado | E88: 1 | F88: u | G88: 0.0541 | H88: =E88*G88 | I88: Acero SAE 1010 | J88: Ø36,8 × 14 de alto, rosca M30x1,5, asiento Ø35 | K88: Compra (mecanizado, Eli-Met) | L88: Sí | M88: Eli-Met | N88: - | O88: Compra -> 8 soldadura de cuello | Q88: P | R88: FL_DES_ABC_10kg | S88: M30x1,5
A89: FL_REC_ABC_10kg | B89: 2 | C89: ABC10-C1 | D89: Alambre MAG ER70S-6 Ø0,9 (AWS A5.18) | E89: 0.0985 | F89: kg | G89: 0.95 | H89: =E89*G89 | I89: ER70S-6 | J89: metal depositado de los cordones del plano 94 g / rendimiento 0,95 | K89: Compra | L89: Sí | M89: Conarco (ESAB Argentina) | N89: - | O89: 4 sold. long. / 8 cuello / 11 circunferencial | P89: IRAM 3523 3.2.4.2 · IRAM 3550 4.1.2 | Q89: C | S89: Peso unit. = fracción que queda en la pieza (el resto es salpicadura). Depositado = volumen de los cordones del modelo × 7,85. Rendimiento de deposición del alambre macizo MAG 90-97 % (ESAB): se adopta 0,95. Medir en la prueba de soldadura del equipo (Getweld)
A90: FL_REC_ABC_10kg | B90: 2 | C90: ABC10-C2 | D90: Gas de protección MAG Arcal 21 / ARCAL Speed (Ar + 8 % CO₂, M20) | E90: 40.8 | F90: L | I90: EN ISO 14175 M20-ArC-8 | J90: 14 L/min × 2,92 min de arco (cordones 1.749 mm: long. 493 + circ. 1.140 + cuello 116, a 600 mm/min) | K90: Compra | L90: Sí | M90: Air Liquide Argentina - sucursal Piñeyro | N90: Gogniat | O90: Colector SC | P90: IRAM 3523 3.2.4.2 · IRAM 3550 3.2.2.2 | Q90: C | S90: Caudal 12-16 L/min para alambre 0,9-1,2 (Air Liquide; Ingemecánica): se adopta 14. Velocidad: Getweld 0-1500 mm/min; se adopta 600. Decisión FLAMA: MAG 135 con Arcal 21; la norma nombra «atmósfera inerte»: acreditar con el certificador en el ensayo de tipo. No incluye la soldadura del carro
A91: FL_REC_ABC_10kg | B91: 2 | C91: ABC10-C3 | D91: Granalla de acero S330 / S390 (ISO 11124-3, SAE J444) | E91: 0.08 | F91: kg | I91: Granalla esférica alto C | J91: 0,35 m² a Sa 2½ (ISO 8501-1); 3,4 kg/h ÷ 42,5 u/h | K91: Compra | L91: Sí | M91: CyM Materiales | N91: Roca Ingeniería | O91: 14 Granallado (B08) | P91: DOC-01 | Q91: C | S91: Consumo (desgaste) por turbina ≈ HP / 2 lb/h (The Fabricator, «aspectos básicos del granallado por turbina»): G-100 con 2 × 7,5 HP = 7,5 lb/h = 3,4 kg/h; ritmo 340 u por turno (Getweld) = 42,5 u/h.
A92: FL_REC_ABC_10kg | B92: 2 | C92: ABC10-C4 | D92: Servicio de pintura en polvo al horno, rojo 03-1-050 | E92: 1 | F92: u | I92: Servicio tercerizado | J92: superficie exterior 0,35 m² | K92: Compra (servicio) | L92: Sí | M92: Prymax | N92: Pintor de carros (cotización por mensaje) | O92: 17 Pintura tercerizada | P92: IRAM 3523 5.3 / IRAM 3550 3.11 · IRAM 121 | Q92: Q | S92: Q-PRYMAX (precio por cilindro); exigir informe de niebla salina del sistema de pintura; tercerización aceptada por el Ministerio (Res. 349/07 art. 18)
A93: FL_REC_ABC_10kg | B93: 2 | C93: ABC10-T1 | D93: Tapón protector de rosca del cuello | E93: 1 | F93: u | I93: Polietileno | J93: para rosca M30x1,5 (plano FL_REC_ABC_10kg hoja 3, R4) | K93: Compra | L93: Sí | M93: - | N93: - | O93: Embalaje | Q93: P
A94: FL_REC_ABC_10kg | B94: 2 | C94: ABC10-T2 | D94: Marcado del recipiente: estampado en la cúpula, en arco junto al cuello (puesto de numerado de cúpula) | E94: 1 | F94: u | I94: - | J94: Fabricante, n° de serie, año; en arco junto al cuello, letra 5 mm; cuño DPS 15 × 7 junto al n° | K94: Proceso | L94: No | O94: Marcado | P94: IRAM 3523 5.1 · Res. 349/07 anexo IV | Q94: N
A95: FL_REC_ABC_10kg | B95: 2 | C95: ABC10-T3 | D95: Etiqueta de identificación del cilindro suelto | E95: 1 | F95: u | I95: Poliéster autoadhesivo removible | J95: 100 × 60, impresión térmica, QR GS1 | K95: Compra | L95: Sí | M95: Astuprint | N95: GS1 Argentina | O95: Etiquetado | Q95: P | R95: FL_REC_ABC_10kg hoja 3
A96: FL_REC_ABC_10kg | B96: 2 | C96: ABC10-T4 | D96: Protocolo de ensayo hidrostático (certificado que acompaña) | E96: 1 | F96: u | G96: 0.005 | H96: =E96*G96 | I96: Papel | J96: A5 | K96: Proceso | L96: No | O96: Control de calidad | P96: IRAM 3523 4.1 y cap. 6 · IRAM 2587 | Q96: N | R96: FL_REC_ABC_10kg hoja 3
A97: FL_REC_ABC_10kg | B97: 1 | C97: ABC10-S7 | D97: Embalaje | E97: 1 | F97: u | H97: =H100 | K97: Compra | O97: 23 Embalaje -> 24 envolvedora (T11)
A98: FL_REC_ABC_10kg | B98: 2 | C98: ABC10-E1 | D98: Caja de cartón corrugado doble | E98: 1 | F98: u | I98: Cartón corrugado | J98: 212 × 212 × 582 interior (envolvente del plano + 15 por lado) | K98: Compra | L98: Sí | M98: Maxipack | N98: Cartocan | O98: 23 Embalaje | Q98: P | S98: Medida del plano
A99: FL_REC_ABC_10kg | B99: 2 | C99: ABC10-E3 | D99: Pallet 1200 × 1000 (fracción) | E99: 0.025 | F99: u | I99: Madera | J99: 40 u por pallet | K99: Compra | L99: Sí | M99: IndusPallets | N99: - | O99: 23 Embalaje | Q99: C | S99: u por pallet = acomodo de la caja (plano) en 1200 × 1000 × 1450 de alto
A100: FL_REC_ABC_10kg | B100: 2 | C100: ABC10-E4 | D100: Film stretch (fracción del pallet) | E100: 0.003 | F100: kg | G100: 1 | H100: =E100*G100 | I100: PE lineal 23 µm | J100: 0,12 kg por pallet / 40 u | K100: Compra | L100: Sí | M100: MV Embalajes | N100: Embalpack | O100: 24 Envolvedora (T11) | Q100: C | S100: Perímetro del pallet 4,4 m × 9 vueltas = 40 m aplicados; con pre-estirado 250 % (1 m de bobina = 3,5 m aplicados) = 11,4 m de bobina × 0,5 m × 23 µm × 0,92 g/cm³ = 0,12 kg. Fuentes: fichas de film 23 µm × 500 mm (MV Embalajes / Embalpack) y pre-estirado de la envolvedora. Medir en la puesta en marcha
A101: FL_REC_ABC_10kg | B101: 2 | C101: ABC10-E5 | D101: Etiqueta de pallet (lote y destino, fracción) | E101: 0.025 | F101: u | I101: Papel térmico | J101: 100 × 150 | K101: Compra | L101: Sí | M101: Astuprint | N101: Multilabel Argentina S.A. | O101: 24 Envolvedora | Q101: C
...

Sheet 06_BOM_Sustitutos
A1: BOM unitario de extintores sustitutos FL_SUS (IRAM 3517-2:2020 9.4.5)
A2: Colores: | B2: Validado | D2: Estimado | F2: A validar | H2: No cumple o decisión pendiente
A4: Producto | B4: Nivel | C4: Código | D4: Descripción | E4: Cant. | F4: UM | G4: Peso unit. (kg/UM) | H4: Peso total (kg) | I4: Material | J4: Medida (mm) | K4: Origen | L4: Entra MRP | M4: Proveedor principal | N4: Alternativa | O4: Operación / puesto (layout FLAMA) | P4: Norma / referencia | Q4: Fte. | R4: Plano | S4: Observaciones
A5: FL_SUS_ABC_1kg | B5: 0 | C5: FL_SUS_ABC_1kg | D5: Extintor sustituto para Extintor ABC 1 kg | E5: 1 | F5: u | P5: IRAM 3517-2:2020 9.4.5 | Q5: N | R5: FL_SUS_ABC_1kg | S5: Unitario: el tamaño del parque de sustitutos se dimensiona aparte
A6: FL_SUS_ABC_1kg | B6: 1 | C6: FL_MAT_ABC_1kg | D6: Extintor base: Extintor ABC 1 kg (mismo modelo) | E6: 1 | F6: u | K6: Stock FLAMA (fabricación propia) | L6: No | P6: IRAM 3517-2:2020 9.4.5 | Q6: N | R6: FL_SUS_ABC_1kg | S6: Igual clasificación y capacidad; mantenimiento vigente. BOM: hoja FL_MAT_ABC_1kg · No entra en MRP del kit: es demanda del producto FL_MAT (stock)
A7: FL_SUS_ABC_1kg | B7: 1 | C7: SUS-ABC_1kg-K | D7: Identificación de extintor sustituto | E7: 1 | F7: u | K7: Compra | Q7: N | R7: FL_SUS_ABC_1kg
A8: FL_SUS_ABC_1kg | B8: 2 | C8: SUS-ABC_1kg-01 | D8: Faja amarilla de sustituto en la pollera (3 leyendas) | E8: 1 | F8: u | I8: Cinta vinílica autoadhesiva amarilla | J8: 36 × 259 (alto ≤ 40; perímetro + 20 de solape) | K8: Compra | L8: Sí | M8: Astuprint | N8: Multilabel Argentina S.A. | P8: IRAM 3517-2:2020 9.4.5 b) | Q8: N | R8: FL_SUS_ABC_1kg | S8: Leyendas: extintor sustituto / reemplaza al equipo de este puesto en mantenimiento o recarga / FLAMA S.A. (datos y logo). Proveedor a cotizar
A9: FL_SUS_ABC_1kg | B9: 2 | C9: SUS-ABC_1kg-02 | D9: Tarjeta de identificación DPS con sello «SUSTITUTO HABILITADO» | E9: 1 | F9: u | I9: Tarjeta oficial DPS (PBA) | J9: formato oficial | K9: Compra (organismo) | L9: Sí | M9: Ministerio de Ambiente PBA (ex OPDS) | N9: - | P9: Res. 349/07 art. 32 | Q9: N | R9: FL_SUS_ABC_1kg | S9: Sólo PBA; reutilizable en cada revisión de carga; n° del extintor asentado en el libro de actas
A10: FL_SUS_ABC_1kg | B10: 2 | C10: SUS-ABC_1kg-03 | D10: Tarjeta AGC con «Es sustituto» (sin domicilio de instalación) | E10: 1 | F10: u | I10: Etiqueta autoadhesiva AGC | J10: formato oficial | K10: Compra (organismo) | L10: Sí | M10: Agencia Gubernamental de Control (CABA) | N10: - | P10: Res. AGC 32/15 anexo II | Q10: N | R10: FL_SUS_ABC_1kg | S10: Sólo CABA
A11: FL_SUS_ABC_1kg | B11: 2 | C11: SUS-ABC_1kg-04 | D11: Remito de préstamo con membrete (n° de extintor, puesto, equipo retirado, fechas) | E11: 1 | F11: u/préstamo | I11: Papel | J11: A5 duplicado | K11: Compra | L11: Sí | M11: Astuprint | N11: - | Q11: I | R11: FL_SUS_ABC_1kg | S11: Práctica de mercado relevada (Fullmat, Rodo, Eversafe)
A12: FL_SUS_ABC_2.5kg | B12: 0 | C12: FL_SUS_ABC_2.5kg | D12: Extintor sustituto para Extintor ABC 2,5 kg | E12: 1 | F12: u | P12: IRAM 3517-2:2020 9.4.5 | Q12: N | R12: FL_SUS_ABC_2.5kg | S12: Unitario: el tamaño del parque de sustitutos se dimensiona aparte
A13: FL_SUS_ABC_2.5kg | B13: 1 | C13: FL_MAT_ABC_2.5kg | D13: Extintor base: Extintor ABC 2,5 kg (mismo modelo) | E13: 1 | F13: u | K13: Stock FLAMA (fabricación propia) | L13: No | P13: IRAM 3517-2:2020 9.4.5 | Q13: N | R13: FL_SUS_ABC_2.5kg | S13: Igual clasificación y capacidad; mantenimiento vigente. BOM: hoja FL_MAT_ABC_2.5kg · No entra en MRP del kit: es demanda del producto FL_MAT (stock)
A14: FL_SUS_ABC_2.5kg | B14: 1 | C14: SUS-ABC_2.5kg-K | D14: Identificación de extintor sustituto | E14: 1 | F14: u | K14: Compra | Q14: N | R14: FL_SUS_ABC_2.5kg
A15: FL_SUS_ABC_2.5kg | B15: 2 | C15: SUS-ABC_2.5kg-01 | D15: Faja amarilla de sustituto en la pollera (3 leyendas) | E15: 1 | F15: u | I15: Cinta vinílica autoadhesiva amarilla | J15: 30 × 410 (alto ≤ 40; perímetro + 20 de solape) | K15: Compra | L15: Sí | M15: Astuprint | N15: Multilabel Argentina S.A. | P15: IRAM 3517-2:2020 9.4.5 b) | Q15: N | R15: FL_SUS_ABC_2.5kg | S15: Leyendas: extintor sustituto / reemplaza al equipo de este puesto en mantenimiento o recarga / FLAMA S.A. (datos y logo). Proveedor a cotizar
A16: FL_SUS_ABC_2.5kg | B16: 2 | C16: SUS-ABC_2.5kg-02 | D16: Tarjeta de identificación DPS con sello «SUSTITUTO HABILITADO» | E16: 1 | F16: u | I16: Tarjeta oficial DPS (PBA) | J16: formato oficial | K16: Compra (organismo) | L16: Sí | M16: Ministerio de Ambiente PBA (ex OPDS) | N16: - | P16: Res. 349/07 art. 32 | Q16: N | R16: FL_SUS_ABC_2.5kg | S16: Sólo PBA; reutilizable en cada revisión de carga; n° del extintor asentado en el libro de actas
A17: FL_SUS_ABC_2.5kg | B17: 2 | C17: SUS-ABC_2.5kg-03 | D17: Tarjeta AGC con «Es sustituto» (sin domicilio de instalación) | E17: 1 | F17: u | I17: Etiqueta autoadhesiva AGC | J17: formato oficial | K17: Compra (organismo) | L17: Sí | M17: Agencia Gubernamental de Control (CABA) | N17: - | P17: Res. AGC 32/15 anexo II | Q17: N | R17: FL_SUS_ABC_2.5kg | S17: Sólo CABA
A18: FL_SUS_ABC_2.5kg | B18: 2 | C18: SUS-ABC_2.5kg-04 | D18: Remito de préstamo con membrete (n° de extintor, puesto, equipo retirado, fechas) | E18: 1 | F18: u/préstamo | I18: Papel | J18: A5 duplicado | K18: Compra | L18: Sí | M18: Astuprint | N18: - | Q18: I | R18: FL_SUS_ABC_2.5kg | S18: Práctica de mercado relevada (Fullmat, Rodo, Eversafe)
A19: FL_SUS_ABC_5kg | B19: 0 | C19: FL_SUS_ABC_5kg | D19: Extintor sustituto para Extintor ABC 5 kg | E19: 1 | F19: u | P19: IRAM 3517-2:2020 9.4.5 | Q19: N | R19: FL_SUS_ABC_5kg | S19: Unitario: el tamaño del parque de sustitutos se dimensiona aparte
A20: FL_SUS_ABC_5kg | B20: 1 | C20: FL_MAT_ABC_5kg | D20: Extintor base: Extintor ABC 5 kg (mismo modelo) | E20: 1 | F20: u | K20: Stock FLAMA (fabricación propia) | L20: No | P20: IRAM 3517-2:2020 9.4.5 | Q20: N | R20: FL_SUS_ABC_5kg | S20: Igual clasificación y capacidad; mantenimiento vigente. BOM: hoja FL_MAT_ABC_5kg · No entra en MRP del kit: es demanda del producto FL_MAT (stock)
A21: FL_SUS_ABC_5kg | B21: 1 | C21: SUS-ABC_5kg-K | D21: Identificación de extintor sustituto | E21: 1 | F21: u | K21: Compra | Q21: N | R21: FL_SUS_ABC_5kg
A22: FL_SUS_ABC_5kg | B22: 2 | C22: SUS-ABC_5kg-01 | D22: Faja amarilla de sustituto en la pollera (3 leyendas) | E22: 1 | F22: u | I22: Cinta vinílica autoadhesiva amarilla | J22: 40 × 501 (alto ≤ 40; perímetro + 20 de solape) | K22: Compra | L22: Sí | M22: Astuprint | N22: Multilabel Argentina S.A. | P22: IRAM 3517-2:2020 9.4.5 b) | Q22: N | R22: FL_SUS_ABC_5kg | S22: Leyendas: extintor sustituto / reemplaza al equipo de este puesto en mantenimiento o recarga / FLAMA S.A. (datos y logo). Proveedor a cotizar
A23: FL_SUS_ABC_5kg | B23: 2 | C23: SUS-ABC_5kg-02 | D23: Tarjeta de identificación DPS con sello «SUSTITUTO HABILITADO» | E23: 1 | F23: u | I23: Tarjeta oficial DPS (PBA) | J23: formato oficial | K23: Compra (organismo) | L23: Sí | M23: Ministerio de Ambiente PBA (ex OPDS) | N23: - | P23: Res. 349/07 art. 32 | Q23: N | R23: FL_SUS_ABC_5kg | S23: Sólo PBA; reutilizable en cada revisión de carga; n° del extintor asentado en el libro de actas
A24: FL_SUS_ABC_5kg | B24: 2 | C24: SUS-ABC_5kg-03 | D24: Tarjeta AGC con «Es sustituto» (sin domicilio de instalación) | E24: 1 | F24: u | I24: Etiqueta autoadhesiva AGC | J24: formato oficial | K24: Compra (organismo) | L24: Sí | M24: Agencia Gubernamental de Control (CABA) | N24: - | P24: Res. AGC 32/15 anexo II | Q24: N | R24: FL_SUS_ABC_5kg | S24: Sólo CABA
A25: FL_SUS_ABC_5kg | B25: 2 | C25: SUS-ABC_5kg-04 | D25: Remito de préstamo con membrete (n° de extintor, puesto, equipo retirado, fechas) | E25: 1 | F25: u/préstamo | I25: Papel | J25: A5 duplicado | K25: Compra | L25: Sí | M25: Astuprint | N25: - | Q25: I | R25: FL_SUS_ABC_5kg | S25: Práctica de mercado relevada (Fullmat, Rodo, Eversafe)
A26: FL_SUS_ABC_10kg | B26: 0 | C26: FL_SUS_ABC_10kg | D26: Extintor sustituto para Extintor ABC 10 kg | E26: 1 | F26: u | P26: IRAM 3517-2:2020 9.4.5 | Q26: N | R26: FL_SUS_ABC_10kg | S26: Unitario: el tamaño del parque de sustitutos se dimensiona aparte
A27: FL_SUS_ABC_10kg | B27: 1 | C27: FL_MAT_ABC_10kg | D27: Extintor base: Extintor ABC 10 kg (mismo modelo) | E27: 1 | F27: u | K27: Stock FLAMA (fabricación propia) | L27: No | P27: IRAM 3517-2:2020 9.4.5 | Q27: N | R27: FL_SUS_ABC_10kg | S27: Igual clasificación y capacidad; mantenimiento vigente. BOM: hoja FL_MAT_ABC_10kg · No entra en MRP del kit: es demanda del producto FL_MAT (stock)
A28: FL_SUS_ABC_10kg | B28: 1 | C28: SUS-ABC_10kg-K | D28: Identificación de extintor sustituto | E28: 1 | F28: u | K28: Compra | Q28: N | R28: FL_SUS_ABC_10kg
A29: FL_SUS_ABC_10kg | B29: 2 | C29: SUS-ABC_10kg-01 | D29: Faja amarilla de sustituto en la pollera (3 leyendas) | E29: 1 | F29: u | I29: Cinta vinílica autoadhesiva amarilla | J29: 40 × 590 (alto ≤ 40; perímetro + 20 de solape) | K29: Compra | L29: Sí | M29: Astuprint | N29: Multilabel Argentina S.A. | P29: IRAM 3517-2:2020 9.4.5 b) | Q29: N | R29: FL_SUS_ABC_10kg | S29: Leyendas: extintor sustituto / reemplaza al equipo de este puesto en mantenimiento o recarga / FLAMA S.A. (datos y logo). Proveedor a cotizar
A30: FL_SUS_ABC_10kg | B30: 2 | C30: SUS-ABC_10kg-02 | D30: Tarjeta de identificación DPS con sello «SUSTITUTO HABILITADO» | E30: 1 | F30: u | I30: Tarjeta oficial DPS (PBA) | J30: formato oficial | K30: Compra (organismo) | L30: Sí | M30: Ministerio de Ambiente PBA (ex OPDS) | N30: - | P30: Res. 349/07 art. 32 | Q30: N | R30: FL_SUS_ABC_10kg | S30: Sólo PBA; reutilizable en cada revisión de carga; n° del extintor asentado en el libro de actas
A31: FL_SUS_ABC_10kg | B31: 2 | C31: SUS-ABC_10kg-03 | D31: Tarjeta AGC con «Es sustituto» (sin domicilio de instalación) | E31: 1 | F31: u | I31: Etiqueta autoadhesiva AGC | J31: formato oficial | K31: Compra (organismo) | L31: Sí | M31: Agencia Gubernamental de Control (CABA) | N31: - | P31: Res. AGC 32/15 anexo II | Q31: N | R31: FL_SUS_ABC_10kg | S31: Sólo CABA
A32: FL_SUS_ABC_10kg | B32: 2 | C32: SUS-ABC_10kg-04 | D32: Remito de préstamo con membrete (n° de extintor, puesto, equipo retirado, fechas) | E32: 1 | F32: u/préstamo | I32: Papel | J32: A5 duplicado | K32: Compra | L32: Sí | M32: Astuprint | N32: - | Q32: I | R32: FL_SUS_ABC_10kg | S32: Práctica de mercado relevada (Fullmat, Rodo, Eversafe)
A33: FL_SUS_AGUA_10l | B33: 0 | C33: FL_SUS_AGUA_10l | D33: Extintor sustituto para Extintor Agua 10 l | E33: 1 | F33: u | P33: IRAM 3517-2:2020 9.4.5 | Q33: N | R33: FL_SUS_AGUA_10l | S33: Unitario: el tamaño del parque de sustitutos se dimensiona aparte
A34: FL_SUS_AGUA_10l | B34: 1 | C34: FL_MAT_AGUA_10l | D34: Extintor base: Extintor Agua 10 l (mismo modelo) | E34: 1 | F34: u | K34: Stock FLAMA (comprado terminado) | L34: No | P34: IRAM 3517-2:2020 9.4.5 | Q34: N | R34: FL_SUS_AGUA_10l | S34: Igual clasificación y capacidad; mantenimiento vigente. BOM: hoja FL_MAT_AGUA_10l · No entra en MRP del kit: es demanda del producto FL_MAT (stock)
A35: FL_SUS_AGUA_10l | B35: 1 | C35: SUS-AGUA_10l-K | D35: Identificación de extintor sustituto | E35: 1 | F35: u | K35: Compra | Q35: N | R35: FL_SUS_AGUA_10l
A36: FL_SUS_AGUA_10l | B36: 2 | C36: SUS-AGUA_10l-01 | D36: Faja amarilla de sustituto en la pollera (3 leyendas) | E36: 1 | F36: u | I36: Cinta vinílica autoadhesiva amarilla | J36: 40 × 617 (alto ≤ 40; perímetro + 20 de solape) | K36: Compra | L36: Sí | M36: Astuprint | N36: Multilabel Argentina S.A. | P36: IRAM 3517-2:2020 9.4.5 b) | Q36: N | R36: FL_SUS_AGUA_10l | S36: Leyendas: extintor sustituto / reemplaza al equipo de este puesto en mantenimiento o recarga / FLAMA S.A. (datos y logo). Proveedor a cotizar
A37: FL_SUS_AGUA_10l | B37: 2 | C37: SUS-AGUA_10l-02 | D37: Tarjeta de identificación DPS con sello «SUSTITUTO HABILITADO» | E37: 1 | F37: u | I37: Tarjeta oficial DPS (PBA) | J37: formato oficial | K37: Compra (organismo) | L37: Sí | M37: Ministerio de Ambiente PBA (ex OPDS) | N37: - | P37: Res. 349/07 art. 32 | Q37: N | R37: FL_SUS_AGUA_10l | S37: Sólo PBA; reutilizable en cada revisión de carga; n° del extintor asentado en el libro de actas
A38: FL_SUS_AGUA_10l | B38: 2 | C38: SUS-AGUA_10l-03 | D38: Tarjeta AGC con «Es sustituto» (sin domicilio de instalación) | E38: 1 | F38: u | I38: Etiqueta autoadhesiva AGC | J38: formato oficial | K38: Compra (organismo) | L38: Sí | M38: Agencia Gubernamental de Control (CABA) | N38: - | P38: Res. AGC 32/15 anexo II | Q38: N | R38: FL_SUS_AGUA_10l | S38: Sólo CABA
A39: FL_SUS_AGUA_10l | B39: 2 | C39: SUS-AGUA_10l-04 | D39: Remito de préstamo con membrete (n° de extintor, puesto, equipo retirado, fechas) | E39: 1 | F39: u/préstamo | I39: Papel | J39: A5 duplicado | K39: Compra | L39: Sí | M39: Astuprint | N39: - | Q39: I | R39: FL_SUS_AGUA_10l | S39: Práctica de mercado relevada (Fullmat, Rodo, Eversafe)
A40: FL_SUS_AFFF_10l | B40: 0 | C40: FL_SUS_AFFF_10l | D40: Extintor sustituto para Extintor AFFF 10 l | E40: 1 | F40: u | P40: IRAM 3517-2:2020 9.4.5 | Q40: N | R40: FL_SUS_AFFF_10l | S40: Unitario: el tamaño del parque de sustitutos se dimensiona aparte
A41: FL_SUS_AFFF_10l | B41: 1 | C41: FL_MAT_AFFF_10l | D41: Extintor base: Extintor AFFF 10 l (mismo modelo) | E41: 1 | F41: u | K41: Stock FLAMA (comprado terminado) | L41: No | P41: IRAM 3517-2:2020 9.4.5 | Q41: N | R41: FL_SUS_AFFF_10l | S41: Igual clasificación y capacidad; mantenimiento vigente. BOM: hoja FL_MAT_AFFF_10l · No entra en MRP del kit: es demanda del producto FL_MAT (stock)
A42: FL_SUS_AFFF_10l | B42: 1 | C42: SUS-AFFF_10l-K | D42: Identificación de extintor sustituto | E42: 1 | F42: u | K42: Compra | Q42: N | R42: FL_SUS_AFFF_10l
A43: FL_SUS_AFFF_10l | B43: 2 | C43: SUS-AFFF_10l-01 | D43: Faja amarilla de sustituto en la pollera (3 leyendas) | E43: 1 | F43: u | I43: Cinta vinílica autoadhesiva amarilla | J43: 40 × 617 (alto ≤ 40; perímetro + 20 de solape) | K43: Compra | L43: Sí | M43: Astuprint | N43: Multilabel Argentina S.A. | P43: IRAM 3517-2:2020 9.4.5 b) | Q43: N | R43: FL_SUS_AFFF_10l | S43: Leyendas: extintor sustituto / reemplaza al equipo de este puesto en mantenimiento o recarga / FLAMA S.A. (datos y logo). Proveedor a cotizar
A44: FL_SUS_AFFF_10l | B44: 2 | C44: SUS-AFFF_10l-02 | D44: Tarjeta de identificación DPS con sello «SUSTITUTO HABILITADO» | E44: 1 | F44: u | I44: Tarjeta oficial DPS (PBA) | J44: formato oficial | K44: Compra (organismo) | L44: Sí | M44: Ministerio de Ambiente PBA (ex OPDS) | N44: - | P44: Res. 349/07 art. 32 | Q44: N | R44: FL_SUS_AFFF_10l | S44: Sólo PBA; reutilizable en cada revisión de carga; n° del extintor asentado en el libro de actas
A45: FL_SUS_AFFF_10l | B45: 2 | C45: SUS-AFFF_10l-03 | D45: Tarjeta AGC con «Es sustituto» (sin domicilio de instalación) | E45: 1 | F45: u | I45: Etiqueta autoadhesiva AGC | J45: formato oficial | K45: Compra (organismo) | L45: Sí | M45: Agencia Gubernamental de Control (CABA) | N45: - | P45: Res. AGC 32/15 anexo II | Q45: N | R45: FL_SUS_AFFF_10l | S45: Sólo CABA
A46: FL_SUS_AFFF_10l | B46: 2 | C46: SUS-AFFF_10l-04 | D46: Remito de préstamo con membrete (n° de extintor, puesto, equipo retirado, fechas) | E46: 1 | F46: u/préstamo | I46: Papel | J46: A5 duplicado | K46: Compra | L46: Sí | M46: Astuprint | N46: - | Q46: I | R46: FL_SUS_AFFF_10l | S46: Práctica de mercado relevada (Fullmat, Rodo, Eversafe)
A47: FL_SUS_AFFF_50l | B47: 0 | C47: FL_SUS_AFFF_50l | D47: Extintor sustituto para Extintor AFFF 50 l sobre ruedas | E47: 1 | F47: u | P47: IRAM 3517-2:2020 9.4.5 | Q47: N | R47: FL_SUS_AFFF_50l | S47: Unitario: el tamaño del parque de sustitutos se dimensiona aparte
A48: FL_SUS_AFFF_50l | B48: 1 | C48: FL_MAT_AFFF_50l | D48: Extintor base: Extintor AFFF 50 l sobre ruedas (mismo modelo) | E48: 1 | F48: u | K48: Stock FLAMA (comprado terminado) | L48: No | P48: IRAM 3517-2:2020 9.4.5 | Q48: N | R48: FL_SUS_AFFF_50l | S48: Igual clasificación y capacidad; mantenimiento vigente. BOM: hoja FL_MAT_AFFF_50l · No entra en MRP del kit: es demanda del producto FL_MAT (stock)
A49: FL_SUS_AFFF_50l | B49: 1 | C49: SUS-AFFF_50l-K | D49: Identificación de extintor sustituto | E49: 1 | F49: u | K49: Compra | Q49: N | R49: FL_SUS_AFFF_50l
A50: FL_SUS_AFFF_50l | B50: 2 | C50: SUS-AFFF_50l-01 | D50: Faja amarilla de sustituto en la pollera (3 leyendas) | E50: 1 | F50: u | I50: Cinta vinílica autoadhesiva amarilla | J50: 40 × 1025 (alto ≤ 40; perímetro + 20 de solape) | K50: Compra | L50: Sí | M50: Astuprint | N50: Multilabel Argentina S.A. | P50: IRAM 3517-2:2020 9.4.5 b) | Q50: N | R50: FL_SUS_AFFF_50l | S50: Leyendas: extintor sustituto / reemplaza al equipo de este puesto en mantenimiento o recarga / FLAMA S.A. (datos y logo). Proveedor a cotizar
A51: FL_SUS_AFFF_50l | B51: 2 | C51: SUS-AFFF_50l-02 | D51: Tarjeta de identificación DPS con sello «SUSTITUTO HABILITADO» | E51: 1 | F51: u | I51: Tarjeta oficial DPS (PBA) | J51: formato oficial | K51: Compra (organismo) | L51: Sí | M51: Ministerio de Ambiente PBA (ex OPDS) | N51: - | P51: Res. 349/07 art. 32 | Q51: N | R51: FL_SUS_AFFF_50l | S51: Sólo PBA; reutilizable en cada revisión de carga; n° del extintor asentado en el libro de actas
A52: FL_SUS_AFFF_50l | B52: 2 | C52: SUS-AFFF_50l-03 | D52: Tarjeta AGC con «Es sustituto» (sin domicilio de instalación) | E52: 1 | F52: u | I52: Etiqueta autoadhesiva AGC | J52: formato oficial | K52: Compra (organismo) | L52: Sí | M52: Agencia Gubernamental de Control (CABA) | N52: - | P52: Res. AGC 32/15 anexo II | Q52: N | R52: FL_SUS_AFFF_50l | S52: Sólo CABA
A53: FL_SUS_AFFF_50l | B53: 2 | C53: SUS-AFFF_50l-04 | D53: Remito de préstamo con membrete (n° de extintor, puesto, equipo retirado, fechas) | E53: 1 | F53: u/préstamo | I53: Papel | J53: A5 duplicado | K53: Compra | L53: Sí | M53: Astuprint | N53: - | Q53: I | R53: FL_SUS_AFFF_50l | S53: Práctica de mercado relevada (Fullmat, Rodo, Eversafe)
A54: FL_SUS_BC_5kg | B54: 0 | C54: FL_SUS_BC_5kg | D54: Extintor sustituto para Extintor BC 5 kg | E54: 1 | F54: u | P54: IRAM 3517-2:2020 9.4.5 | Q54: N | R54: FL_SUS_BC_5kg | S54: Unitario: el tamaño del parque de sustitutos se dimensiona aparte
A55: FL_SUS_BC_5kg | B55: 1 | C55: FL_MAT_BC_5kg | D55: Extintor base: Extintor BC 5 kg (mismo modelo) | E55: 1 | F55: u | K55: Stock FLAMA (comprado terminado) | L55: No | P55: IRAM 3517-2:2020 9.4.5 | Q55: N | R55: FL_SUS_BC_5kg | S55: Igual clasificación y capacidad; mantenimiento vigente. BOM: hoja FL_MAT_BC_5kg · No entra en MRP del kit: es demanda del producto FL_MAT (stock)
A56: FL_SUS_BC_5kg | B56: 1 | C56: SUS-BC_5kg-K | D56: Identificación de extintor sustituto | E56: 1 | F56: u | K56: Compra | Q56: N | R56: FL_SUS_BC_5kg
A57: FL_SUS_BC_5kg | B57: 2 | C57: SUS-BC_5kg-01 | D57: Faja amarilla de sustituto en la pollera (3 leyendas) | E57: 1 | F57: u | I57: Cinta vinílica autoadhesiva amarilla | J57: 40 × 501 (alto ≤ 40; perímetro + 20 de solape) | K57: Compra | L57: Sí | M57: Astuprint | N57: Multilabel Argentina S.A. | P57: IRAM 3517-2:2020 9.4.5 b) | Q57: N | R57: FL_SUS_BC_5kg | S57: Leyendas: extintor sustituto / reemplaza al equipo de este puesto en mantenimiento o recarga / FLAMA S.A. (datos y logo). Proveedor a cotizar
A58: FL_SUS_BC_5kg | B58: 2 | C58: SUS-BC_5kg-02 | D58: Tarjeta de identificación DPS con sello «SUSTITUTO HABILITADO» | E58: 1 | F58: u | I58: Tarjeta oficial DPS (PBA) | J58: formato oficial | K58: Compra (organismo) | L58: Sí | M58: Ministerio de Ambiente PBA (ex OPDS) | N58: - | P58: Res. 349/07 art. 32 | Q58: N | R58: FL_SUS_BC_5kg | S58: Sólo PBA; reutilizable en cada revisión de carga; n° del extintor asentado en el libro de actas
A59: FL_SUS_BC_5kg | B59: 2 | C59: SUS-BC_5kg-03 | D59: Tarjeta AGC con «Es sustituto» (sin domicilio de instalación) | E59: 1 | F59: u | I59: Etiqueta autoadhesiva AGC | J59: formato oficial | K59: Compra (organismo) | L59: Sí | M59: Agencia Gubernamental de Control (CABA) | N59: - | P59: Res. AGC 32/15 anexo II | Q59: N | R59: FL_SUS_BC_5kg | S59: Sólo CABA
A60: FL_SUS_BC_5kg | B60: 2 | C60: SUS-BC_5kg-04 | D60: Remito de préstamo con membrete (n° de extintor, puesto, equipo retirado, fechas) | E60: 1 | F60: u/préstamo | I60: Papel | J60: A5 duplicado | K60: Compra | L60: Sí | M60: Astuprint | N60: - | Q60: I | R60: FL_SUS_BC_5kg | S60: Práctica de mercado relevada (Fullmat, Rodo, Eversafe)
A61: FL_SUS_SALESK_6l | B61: 0 | C61: FL_SUS_SALESK_6l | D61: Extintor sustituto para Extintor Sales K 6 l | E61: 1 | F61: u | P61: IRAM 3517-2:2020 9.4.5 | Q61: N | R61: FL_SUS_SALESK_6l | S61: Unitario: el tamaño del parque de sustitutos se dimensiona aparte
A62: FL_SUS_SALESK_6l | B62: 1 | C62: FL_MAT_SALESK_6l | D62: Extintor base: Extintor Sales K 6 l (mismo modelo) | E62: 1 | F62: u | K62: Stock FLAMA (comprado terminado) | L62: No | P62: IRAM 3517-2:2020 9.4.5 | Q62: N | R62: FL_SUS_SALESK_6l | S62: Igual clasificación y capacidad; mantenimiento vigente. BOM: hoja FL_MAT_SALESK_6l · No entra en MRP del kit: es demanda del producto FL_MAT (stock)
A63: FL_SUS_SALESK_6l | B63: 1 | C63: SUS-SALESK_6l-K | D63: Identificación de extintor sustituto | E63: 1 | F63: u | K63: Compra | Q63: N | R63: FL_SUS_SALESK_6l
A64: FL_SUS_SALESK_6l | B64: 2 | C64: SUS-SALESK_6l-01 | D64: Faja amarilla de sustituto en la pollera (3 leyendas) | E64: 1 | F64: u | I64: Cinta vinílica autoadhesiva amarilla | J64: 40 × 617 (alto ≤ 40; perímetro + 20 de solape) | K64: Compra | L64: Sí | M64: Astuprint | N64: Multilabel Argentina S.A. | P64: IRAM 3517-2:2020 9.4.5 b) | Q64: N | R64: FL_SUS_SALESK_6l | S64: Leyendas: extintor sustituto / reemplaza al equipo de este puesto en mantenimiento o recarga / FLAMA S.A. (datos y logo). Proveedor a cotizar
A65: FL_SUS_SALESK_6l | B65: 2 | C65: SUS-SALESK_6l-02 | D65: Tarjeta de identificación DPS con sello «SUSTITUTO HABILITADO» | E65: 1 | F65: u | I65: Tarjeta oficial DPS (PBA) | J65: formato oficial | K65: Compra (organismo) | L65: Sí | M65: Ministerio de Ambiente PBA (ex OPDS) | N65: - | P65: Res. 349/07 art. 32 | Q65: N | R65: FL_SUS_SALESK_6l | S65: Sólo PBA; reutilizable en cada revisión de carga; n° del extintor asentado en el libro de actas
A66: FL_SUS_SALESK_6l | B66: 2 | C66: SUS-SALESK_6l-03 | D66: Tarjeta AGC con «Es sustituto» (sin domicilio de instalación) | E66: 1 | F66: u | I66: Etiqueta autoadhesiva AGC | J66: formato oficial | K66: Compra (organismo) | L66: Sí | M66: Agencia Gubernamental de Control (CABA) | N66: - | P66: Res. AGC 32/15 anexo II | Q66: N | R66: FL_SUS_SALESK_6l | S66: Sólo CABA
A67: FL_SUS_SALESK_6l | B67: 2 | C67: SUS-SALESK_6l-04 | D67: Remito de préstamo con membrete (n° de extintor, puesto, equipo retirado, fechas) | E67: 1 | F67: u/préstamo | I67: Papel | J67: A5 duplicado | K67: Compra | L67: Sí | M67: Astuprint | N67: - | Q67: I | R67: FL_SUS_SALESK_6l | S67: Práctica de mercado relevada (Fullmat, Rodo, Eversafe)
A68: FL_SUS_CO2_2kg | B68: 0 | C68: FL_SUS_CO2_2kg | D68: Extintor sustituto para Extintor CO₂ 2 kg | E68: 1 | F68: u | P68: IRAM 3517-2:2020 9.4.5 | Q68: N | R68: FL_SUS_CO2_2kg | S68: Unitario: el tamaño del parque de sustitutos se dimensiona aparte
A69: FL_SUS_CO2_2kg | B69: 1 | C69: FL_MAT_CO2_2kg | D69: Extintor base: Extintor CO₂ 2 kg (mismo modelo) | E69: 1 | F69: u | K69: Stock FLAMA (comprado terminado) | L69: No | P69: IRAM 3517-2:2020 9.4.5 | Q69: N | R69: FL_SUS_CO2_2kg | S69: Igual clasificación y capacidad; mantenimiento vigente. BOM: hoja FL_MAT_CO2_2kg · No entra en MRP del kit: es demanda del producto FL_MAT (stock)
A70: FL_SUS_CO2_2kg | B70: 1 | C70: SUS-CO2_2kg-K | D70: Identificación de extintor sustituto | E70: 1 | F70: u | K70: Compra | Q70: N | R70: FL_SUS_CO2_2kg
A71: FL_SUS_CO2_2kg | B71: 2 | C71: SUS-CO2_2kg-01 | D71: Faja amarilla de sustituto en la pollera (3 leyendas) | E71: 1 | F71: u | I71: Cinta vinílica autoadhesiva amarilla | J71: 33 × 378 (alto ≤ 40; perímetro + 20 de solape) | K71: Compra | L71: Sí | M71: Astuprint | N71: Multilabel Argentina S.A. | P71: IRAM 3517-2:2020 9.4.5 b) | Q71: N | R71: FL_SUS_CO2_2kg | S71: Leyendas: extintor sustituto / reemplaza al equipo de este puesto en mantenimiento o recarga / FLAMA S.A. (datos y logo). Proveedor a cotizar
A72: FL_SUS_CO2_2kg | B72: 2 | C72: SUS-CO2_2kg-02 | D72: Tarjeta de identificación DPS con sello «SUSTITUTO HABILITADO» | E72: 1 | F72: u | I72: Tarjeta oficial DPS (PBA) | J72: formato oficial | K72: Compra (organismo) | L72: Sí | M72: Ministerio de Ambiente PBA (ex OPDS) | N72: - | P72: Res. 349/07 art. 32 | Q72: N | R72: FL_SUS_CO2_2kg | S72: Sólo PBA; reutilizable en cada revisión de carga; n° del extintor asentado en el libro de actas
A73: FL_SUS_CO2_2kg | B73: 2 | C73: SUS-CO2_2kg-03 | D73: Tarjeta AGC con «Es sustituto» (sin domicilio de instalación) | E73: 1 | F73: u | I73: Etiqueta autoadhesiva AGC | J73: formato oficial | K73: Compra (organismo) | L73: Sí | M73: Agencia Gubernamental de Control (CABA) | N73: - | P73: Res. AGC 32/15 anexo II | Q73: N | R73: FL_SUS_CO2_2kg | S73: Sólo CABA
A74: FL_SUS_CO2_2kg | B74: 2 | C74: SUS-CO2_2kg-04 | D74: Remito de préstamo con membrete (n° de extintor, puesto, equipo retirado, fechas) | E74: 1 | F74: u/préstamo | I74: Papel | J74: A5 duplicado | K74: Compra | L74: Sí | M74: Astuprint | N74: - | Q74: I | R74: FL_SUS_CO2_2kg | S74: Práctica de mercado relevada (Fullmat, Rodo, Eversafe)
A75: FL_SUS_CO2_5kg | B75: 0 | C75: FL_SUS_CO2_5kg | D75: Extintor sustituto para Extintor CO₂ 5 kg | E75: 1 | F75: u | P75: IRAM 3517-2:2020 9.4.5 | Q75: N | R75: FL_SUS_CO2_5kg | S75: Unitario: el tamaño del parque de sustitutos se dimensiona aparte
A76: FL_SUS_CO2_5kg | B76: 1 | C76: FL_MAT_CO2_5kg | D76: Extintor base: Extintor CO₂ 5 kg (mismo modelo) | E76: 1 | F76: u | K76: Stock FLAMA (comprado terminado) | L76: No | P76: IRAM 3517-2:2020 9.4.5 | Q76: N | R76: FL_SUS_CO2_5kg | S76: Igual clasificación y capacidad; mantenimiento vigente. BOM: hoja FL_MAT_CO2_5kg · No entra en MRP del kit: es demanda del producto FL_MAT (stock)
A77: FL_SUS_CO2_5kg | B77: 1 | C77: SUS-CO2_5kg-K | D77: Identificación de extintor sustituto | E77: 1 | F77: u | K77: Compra | Q77: N | R77: FL_SUS_CO2_5kg
A78: FL_SUS_CO2_5kg | B78: 2 | C78: SUS-CO2_5kg-01 | D78: Faja amarilla de sustituto en la pollera (3 leyendas) | E78: 1 | F78: u | I78: Cinta vinílica autoadhesiva amarilla | J78: 40 × 460 (alto ≤ 40; perímetro + 20 de solape) | K78: Compra | L78: Sí | M78: Astuprint | N78: Multilabel Argentina S.A. | P78: IRAM 3517-2:2020 9.4.5 b) | Q78: N | R78: FL_SUS_CO2_5kg | S78: Leyendas: extintor sustituto / reemplaza al equipo de este puesto en mantenimiento o recarga / FLAMA S.A. (datos y logo). Proveedor a cotizar
A79: FL_SUS_CO2_5kg | B79: 2 | C79: SUS-CO2_5kg-02 | D79: Tarjeta de identificación DPS con sello «SUSTITUTO HABILITADO» | E79: 1 | F79: u | I79: Tarjeta oficial DPS (PBA) | J79: formato oficial | K79: Compra (organismo) | L79: Sí | M79: Ministerio de Ambiente PBA (ex OPDS) | N79: - | P79: Res. 349/07 art. 32 | Q79: N | R79: FL_SUS_CO2_5kg | S79: Sólo PBA; reutilizable en cada revisión de carga; n° del extintor asentado en el libro de actas
A80: FL_SUS_CO2_5kg | B80: 2 | C80: SUS-CO2_5kg-03 | D80: Tarjeta AGC con «Es sustituto» (sin domicilio de instalación) | E80: 1 | F80: u | I80: Etiqueta autoadhesiva AGC | J80: formato oficial | K80: Compra (organismo) | L80: Sí | M80: Agencia Gubernamental de Control (CABA) | N80: - | P80: Res. AGC 32/15 anexo II | Q80: N | R80: FL_SUS_CO2_5kg | S80: Sólo CABA
A81: FL_SUS_CO2_5kg | B81: 2 | C81: SUS-CO2_5kg-04 | D81: Remito de préstamo con membrete (n° de extintor, puesto, equipo retirado, fechas) | E81: 1 | F81: u/préstamo | I81: Papel | J81: A5 duplicado | K81: Compra | L81: Sí | M81: Astuprint | N81: - | Q81: I | R81: FL_SUS_CO2_5kg | S81: Práctica de mercado relevada (Fullmat, Rodo, Eversafe)
A82: FL_SUS_HCFC-HFC_5kg | B82: 0 | C82: FL_SUS_HCFC-HFC_5kg | D82: Extintor sustituto para Extintor HCFC/HFC 5 kg | E82: 1 | F82: u | P82: IRAM 3517-2:2020 9.4.5 | Q82: N | R82: FL_SUS_HCFC-HFC_5kg | S82: Unitario: el tamaño del parque de sustitutos se dimensiona aparte
A83: FL_SUS_HCFC-HFC_5kg | B83: 1 | C83: FL_MAT_HCFC-HFC_5kg | D83: Extintor base: Extintor HCFC/HFC 5 kg (mismo modelo) | E83: 1 | F83: u | K83: Stock FLAMA (comprado terminado) | L83: No | P83: IRAM 3517-2:2020 9.4.5 | Q83: N | R83: FL_SUS_HCFC-HFC_5kg | S83: Igual clasificación y capacidad; mantenimiento vigente. BOM: hoja FL_MAT_HCFC-HFC_5kg · No entra en MRP del kit: es demanda del producto FL_MAT (stock)
A84: FL_SUS_HCFC-HFC_5kg | B84: 1 | C84: SUS-HCFC-HFC_5kg-K | D84: Identificación de extintor sustituto | E84: 1 | F84: u | K84: Compra | Q84: N | R84: FL_SUS_HCFC-HFC_5kg
A85: FL_SUS_HCFC-HFC_5kg | B85: 2 | C85: SUS-HCFC-HFC_5kg-01 | D85: Faja amarilla de sustituto en la pollera (3 leyendas) | E85: 1 | F85: u | I85: Cinta vinílica autoadhesiva amarilla | J85: 40 × 501 (alto ≤ 40; perímetro + 20 de solape) | K85: Compra | L85: Sí | M85: Astuprint | N85: Multilabel Argentina S.A. | P85: IRAM 3517-2:2020 9.4.5 b) | Q85: N | R85: FL_SUS_HCFC-HFC_5kg | S85: Leyendas: extintor sustituto / reemplaza al equipo de este puesto en mantenimiento o recarga / FLAMA S.A. (datos y logo). Proveedor a cotizar
A86: FL_SUS_HCFC-HFC_5kg | B86: 2 | C86: SUS-HCFC-HFC_5kg-02 | D86: Tarjeta de identificación DPS con sello «SUSTITUTO HABILITADO» | E86: 1 | F86: u | I86: Tarjeta oficial DPS (PBA) | J86: formato oficial | K86: Compra (organismo) | L86: Sí | M86: Ministerio de Ambiente PBA (ex OPDS) | N86: - | P86: Res. 349/07 art. 32 | Q86: N | R86: FL_SUS_HCFC-HFC_5kg | S86: Sólo PBA; reutilizable en cada revisión de carga; n° del extintor asentado en el libro de actas
A87: FL_SUS_HCFC-HFC_5kg | B87: 2 | C87: SUS-HCFC-HFC_5kg-03 | D87: Tarjeta AGC con «Es sustituto» (sin domicilio de instalación) | E87: 1 | F87: u | I87: Etiqueta autoadhesiva AGC | J87: formato oficial | K87: Compra (organismo) | L87: Sí | M87: Agencia Gubernamental de Control (CABA) | N87: - | P87: Res. AGC 32/15 anexo II | Q87: N | R87: FL_SUS_HCFC-HFC_5kg | S87: Sólo CABA
A88: FL_SUS_HCFC-HFC_5kg | B88: 2 | C88: SUS-HCFC-HFC_5kg-04 | D88: Remito de préstamo con membrete (n° de extintor, puesto, equipo retirado, fechas) | E88: 1 | F88: u/préstamo | I88: Papel | J88: A5 duplicado | K88: Compra | L88: Sí | M88: Astuprint | N88: - | Q88: I | R88: FL_SUS_HCFC-HFC_5kg | S88: Práctica de mercado relevada (Fullmat, Rodo, Eversafe)
A89: FL_SUS_CLASED_9l | B89: 0 | C89: FL_SUS_CLASED_9l | D89: Extintor sustituto para Extintor Clase D 9 l | E89: 1 | F89: u | P89: IRAM 3517-2:2020 9.4.5 | Q89: N | R89: FL_SUS_CLASED_9l | S89: Unitario: el tamaño del parque de sustitutos se dimensiona aparte
A90: FL_SUS_CLASED_9l | B90: 1 | C90: FL_MAT_CLASED_9l | D90: Extintor base: Extintor Clase D 9 l (mismo modelo) | E90: 1 | F90: u | K90: Stock FLAMA (comprado terminado) | L90: No | P90: IRAM 3517-2:2020 9.4.5 | Q90: N | R90: FL_SUS_CLASED_9l | S90: Igual clasificación y capacidad; mantenimiento vigente. BOM: hoja FL_MAT_CLASED_9l · No entra en MRP del kit: es demanda del producto FL_MAT (stock)
A91: FL_SUS_CLASED_9l | B91: 1 | C91: SUS-CLASED_9l-K | D91: Identificación de extintor sustituto | E91: 1 | F91: u | K91: Compra | Q91: N | R91: FL_SUS_CLASED_9l
A92: FL_SUS_CLASED_9l | B92: 2 | C92: SUS-CLASED_9l-01 | D92: Faja amarilla de sustituto en la pollera (3 leyendas) | E92: 1 | F92: u | I92: Cinta vinílica autoadhesiva amarilla | J92: 40 × 590 (alto ≤ 40; perímetro + 20 de solape) | K92: Compra | L92: Sí | M92: Astuprint | N92: Multilabel Argentina S.A. | P92: IRAM 3517-2:2020 9.4.5 b) | Q92: N | R92: FL_SUS_CLASED_9l | S92: Leyendas: extintor sustituto / reemplaza al equipo de este puesto en mantenimiento o recarga / FLAMA S.A. (datos y logo). Proveedor a cotizar
A93: FL_SUS_CLASED_9l | B93: 2 | C93: SUS-CLASED_9l-02 | D93: Tarjeta de identificación DPS con sello «SUSTITUTO HABILITADO» | E93: 1 | F93: u | I93: Tarjeta oficial DPS (PBA) | J93: formato oficial | K93: Compra (organismo) | L93: Sí | M93: Ministerio de Ambiente PBA (ex OPDS) | N93: - | P93: Res. 349/07 art. 32 | Q93: N | R93: FL_SUS_CLASED_9l | S93: Sólo PBA; reutilizable en cada revisión de carga; n° del extintor asentado en el libro de actas
A94: FL_SUS_CLASED_9l | B94: 2 | C94: SUS-CLASED_9l-03 | D94: Tarjeta AGC con «Es sustituto» (sin domicilio de instalación) | E94: 1 | F94: u | I94: Etiqueta autoadhesiva AGC | J94: formato oficial | K94: Compra (organismo) | L94: Sí | M94: Agencia Gubernamental de Control (CABA) | N94: - | P94: Res. AGC 32/15 anexo II | Q94: N | R94: FL_SUS_CLASED_9l | S94: Sólo CABA
A95: FL_SUS_CLASED_9l | B95: 2 | C95: SUS-CLASED_9l-04 | D95: Remito de préstamo con membrete (n° de extintor, puesto, equipo retirado, fechas) | E95: 1 | F95: u/préstamo | I95: Papel | J95: A5 duplicado | K95: Compra | L95: Sí | M95: Astuprint | N95: - | Q95: I | R95: FL_SUS_CLASED_9l | S95: Práctica de mercado relevada (Fullmat, Rodo, Eversafe)
A96: FL_SUS_ABC_25kg | B96: 0 | C96: FL_SUS_ABC_25kg | D96: Extintor sustituto para Extintor ABC 25 kg sobre ruedas | E96: 1 | F96: u | P96: IRAM 3517-2:2020 9.4.5 | Q96: N | R96: FL_SUS_ABC_25kg | S96: Unitario: el tamaño del parque de sustitutos se dimensiona aparte
A97: FL_SUS_ABC_25kg | B97: 1 | C97: FL_MAT_ABC_25kg | D97: Extintor base: Extintor ABC 25 kg sobre ruedas (mismo modelo) | E97: 1 | F97: u | K97: Stock FLAMA (fabricación propia) | L97: No | P97: IRAM 3517-2:2020 9.4.5 | Q97: N | R97: FL_SUS_ABC_25kg | S97: Igual clasificación y capacidad; mantenimiento vigente. BOM: hoja FL_MAT_ABC_25kg · No entra en MRP del kit: es demanda del producto FL_MAT (stock)
A98: FL_SUS_ABC_25kg | B98: 1 | C98: SUS-ABC_25kg-K | D98: Identificación de extintor sustituto | E98: 1 | F98: u | K98: Compra | Q98: N | R98: FL_SUS_ABC_25kg
A99: FL_SUS_ABC_25kg | B99: 2 | C99: SUS-ABC_25kg-01 | D99: Faja amarilla de sustituto en la pollera (3 leyendas) | E99: 1 | F99: u | I99: Cinta vinílica autoadhesiva amarilla | J99: 40 × 889 (alto ≤ 40; perímetro + 20 de solape) | K99: Compra | L99: Sí | M99: Astuprint | N99: Multilabel Argentina S.A. | P99: IRAM 3517-2:2020 9.4.5 b) | Q99: N | R99: FL_SUS_ABC_25kg | S99: Leyendas: extintor sustituto / reemplaza al equipo de este puesto en mantenimiento o recarga / FLAMA S.A. (datos y logo). Proveedor a cotizar
A100: FL_SUS_ABC_25kg | B100: 2 | C100: SUS-ABC_25kg-02 | D100: Tarjeta de identificación DPS con sello «SUSTITUTO HABILITADO» | E100: 1 | F100: u | I100: Tarjeta oficial DPS (PBA) | J100: formato oficial | K100: Compra (organismo) | L100: Sí | M100: Ministerio de Ambiente PBA (ex OPDS) | N100: - | P100: Res. 349/07 art. 32 | Q100: N | R100: FL_SUS_ABC_25kg | S100: Sólo PBA; reutilizable en cada revisión de carga; n° del extintor asentado en el libro de actas
A101: FL_SUS_ABC_25kg | B101: 2 | C101: SUS-ABC_25kg-03 | D101: Tarjeta AGC con «Es sustituto» (sin domicilio de instalación) | E101: 1 | F101: u | I101: Etiqueta autoadhesiva AGC | J101: formato oficial | K101: Compra (organismo) | L101: Sí | M101: Agencia Gubernamental de Control (CABA) | N101: - | P101: Res. AGC 32/15 anexo II | Q101: N | R101: FL_SUS_ABC_25kg | S101: Sólo CABA
...

Sheet 07_BOM_Recargas
A1: BOM de servicio de recarga y mantenimiento por extintor y por caso (IRAM 3517-2:2020)
A2: • Polvo: un extintor ACCIONADO (aunque sea parcialmente) se recarga con polvo NUEVO; el polvo de ese extintor no se reutiliza (9.9.1.4). El polvo de un extintor que se abre SIN haber sido accionado (control interior, prueba hidráulica) puede volver al mismo equipo si se trata en el sistema cerrado de recuperación del recinto y pasa el control de 9.9.3 (4.4.1 y). Nunca se mezcla ABC con BC (9.9.1.6).
A3: • Polvo de la versión anterior de la IRAM 3569 → reemplazo total obligatorio (9.9.4); el retirado es residuo.
A4: • HCFC / gases limpios: el agente se trasvasa y RECUPERA en circuito cerrado, nunca se ventea (4.4.1 z). Se repone sólo la pérdida. El recuperado fuera de especificación va a regeneración por gestor habilitado.
A5: • CO₂: carga por trasvase (4.4.1 l); recuperación recomendada en vaciados (9.4.18).
A6: • Mermas de 3 % (polvo) y 2 % (HCFC): valores estimados (amarillo) a medir en planta con la balanza de RC-CQ.
A7: • Entra MRP: todo lo que se repone; lo recuperado, los grabados y el aire comprimido de planta no se compran.
A8: Colores: | B8: Validado | D8: Estimado | F8: A validar | H8: No cumple o decisión pendiente
A9: Código kit | B9: Plano | C9: Extintor | D9: Caso | E9: Ítem | F9: Cant. | G9: UM | H9: Estado / origen | I9: Referencia | J9: Entra MRP | K9: Proveedor principal | L9: Alternativa
A10: RK-ABC1-A | B10: FL_MAT_ABC_1kg | C10: Extintor ABC 1 kg | D10: A - Extintor descargado (uso o descarga parcial) | E10: Polvo químico seco ABC 60 (Sello IRAM 3569) | F10: 1.05 | G10: kg | H10: Nuevo 100 % | I10: IRAM 3517-2:2020 9.9.1.4: el polvo de un extintor accionado no se reutiliza | J10: Sí | K10: DEM S.A. (DEMSA) | L10: Polvex S.R.L. / Sancibrao
A11: RK-ABC1-A | B11: FL_MAT_ABC_1kg | C11: Extintor ABC 1 kg | D11: A - Extintor descargado (uso o descarga parcial) | E11: Precinto plástico numerado, color, con nombre del recargador | F11: 1 | G11: u | H11: Nuevo | I11: IRAM 3517-2:2020 9.4.13 | J11: Sí | K11: SonFuertes (vía Papelera Damián) | L11: Precinter S.R.L.
A12: RK-ABC1-A | B12: FL_MAT_ABC_1kg | C12: Extintor ABC 1 kg | D12: A - Extintor descargado (uso o descarga parcial) | E12: Marbete (anillo, color del año) | F12: 1 | G12: u | H12: Nuevo | I12: IRAM 3517-2:2020 9.6 · anexo E | J12: Sí | K12: Astuprint | L12: Multilabel Argentina S.A.
A13: RK-ABC1-A | B13: FL_MAT_ABC_1kg | C13: Extintor ABC 1 kg | D13: A - Extintor descargado (uso o descarga parcial) | E13: Etiqueta de servicio del recargador (extintor n°, serie, próxima recarga y PH) | F13: 1 | G13: u | H13: Nuevo | I13: IRAM 3517-2:2020 9.4.14 · relevado Suyai/Firegram | J13: Sí | K13: Astuprint | L13: Multilabel Argentina S.A.
A14: RK-ABC1-A | B14: FL_MAT_ABC_1kg | C14: Extintor ABC 1 kg | D14: A - Extintor descargado (uso o descarga parcial) | E14: Oblea PBA de recarga Ø46 + estampilla precinto 1" × 200 mm válvula-cuerpo | F14: 1 | G14: u | H14: Nuevo (venta en PBA) | I14: IRAM 3517-2:2020 Res. OPDS 522/07 | J14: Sí | K14: Ministerio de Ambiente PBA (ex OPDS) | L14: -
A15: RK-ABC1-A | B15: FL_MAT_ABC_1kg | C15: Extintor ABC 1 kg | D15: A - Extintor descargado (uso o descarga parcial) | E15: Tarjeta de identificación AGC (módulo papel con QR + etiqueta AGC) | F15: 1 | G15: u | H15: Nuevo (destino CABA) | I15: IRAM 3517-2:2020 Ord. 40.473 art. 6 · Res. AGC 32/15 | J15: Sí | K15: Agencia Gubernamental de Control (CABA) | L15: -
A16: RK-ABC1-A | B16: FL_MAT_ABC_1kg | C16: Extintor ABC 1 kg | D16: A - Extintor descargado (uso o descarga parcial) | E16: Tarjeta de identificación DPS de revisión / recarga | F16: 1 | G16: u | H16: Nuevo (PBA) | I16: IRAM 3517-2:2020 Res. 349/07 art. 21 | J16: Sí | K16: Ministerio de Ambiente PBA (ex OPDS) | L16: -
A17: RK-ABC1-A | B17: FL_MAT_ABC_1kg | C17: Extintor ABC 1 kg | D17: A - Extintor descargado (uso o descarga parcial) | E17: Grabado de la fecha del servicio en el tubo de pesca (lápiz vibratorio; en polvo, marcador indeleble) | F17: 1 | G17: u | H17: Proceso | I17: IRAM 3517-2:2020 Res. 349/07 art. 28 | J17: No
A18: RK-ABC1-A | B18: FL_MAT_ABC_1kg | C18: Extintor ABC 1 kg | D18: A - Extintor descargado (uso o descarga parcial) | E18: Si hubo PH: oblea de vencimiento de PH + «PH» y fecha grabados en el tubo de pesca (CO₂: fecha y logo estampados en la ojiva) | F18: 1 | G18: u | H18: Proceso | I18: IRAM 3517-2:2020 Res. 349/07 art. 29 · IRAM 3517-2 | J18: No
A19: RK-ABC1-A | B19: FL_MAT_ABC_1kg | C19: Extintor ABC 1 kg | D19: A - Extintor descargado (uso o descarga parcial) | E19: Junta tórica de asiento del cuello | F19: 1 | G19: u | H19: Nuevo (R: cambio sistemático) | J19: Sí | K19: Argensold | L19: Matafuegos Iglesias
A20: RK-ABC1-A | B20: FL_MAT_ABC_1kg | C20: Extintor ABC 1 kg | D20: A - Extintor descargado (uso o descarga parcial) | E20: Gas impulsor: N₂ | F20: 0.0047 | G20: kg | H20: Nuevo | I20: IRAM 3517-2:2020 9.4.9 tabla 2 | J20: Sí | K20: Air Liquide Argentina - sucursal Piñeyro | L20: Gogniat
A21: RK-ABC1-B | B21: FL_MAT_ABC_1kg | C21: Extintor ABC 1 kg | D21: B - Mantenimiento con apertura sin descarga (control interior, PH) | E21: Polvo químico seco ABC 60 (Sello IRAM 3569) recuperado | F21: 1 | G21: kg | H21: Recuperado en sistema cerrado | I21: IRAM 3517-2:2020 4.4.1 y) sistema cerrado de recuperación con inspección; 9.9.3 control (puffer IRAM 3672, fusión IRAM 3569 en ABC) | J21: No
A22: RK-ABC1-B | B22: FL_MAT_ABC_1kg | C22: Extintor ABC 1 kg | D22: B - Mantenimiento con apertura sin descarga (control interior, PH) | E22: Polvo químico seco ABC 60 (Sello IRAM 3569) | F22: 0.05 | G22: kg | H22: Nuevo: reposición = carga objetivo − límite inferior de 0 / +100 g (cota superior) | I22: IRAM 3517-2:2020 9.4.12 tabla 3 · anexo F; mismo tipo y marca (prohibido mezclar ABC con BC, 9.9.1.6) | J22: Sí | K22: DEM S.A. (DEMSA) | L22: Polvex S.R.L. / Sancibrao
A23: RK-ABC1-B | B23: FL_MAT_ABC_1kg | C23: Extintor ABC 1 kg | D23: B - Mantenimiento con apertura sin descarga (control interior, PH) | E23: Precinto plástico numerado, color, con nombre del recargador | F23: 1 | G23: u | H23: Nuevo | I23: IRAM 3517-2:2020 9.4.13 | J23: Sí | K23: SonFuertes (vía Papelera Damián) | L23: Precinter S.R.L.
A24: RK-ABC1-B | B24: FL_MAT_ABC_1kg | C24: Extintor ABC 1 kg | D24: B - Mantenimiento con apertura sin descarga (control interior, PH) | E24: Marbete (anillo, color del año) | F24: 1 | G24: u | H24: Nuevo | I24: IRAM 3517-2:2020 9.6 · anexo E | J24: Sí | K24: Astuprint | L24: Multilabel Argentina S.A.
A25: RK-ABC1-B | B25: FL_MAT_ABC_1kg | C25: Extintor ABC 1 kg | D25: B - Mantenimiento con apertura sin descarga (control interior, PH) | E25: Etiqueta de servicio del recargador (extintor n°, serie, próxima recarga y PH) | F25: 1 | G25: u | H25: Nuevo | I25: IRAM 3517-2:2020 9.4.14 · relevado Suyai/Firegram | J25: Sí | K25: Astuprint | L25: Multilabel Argentina S.A.
A26: RK-ABC1-B | B26: FL_MAT_ABC_1kg | C26: Extintor ABC 1 kg | D26: B - Mantenimiento con apertura sin descarga (control interior, PH) | E26: Oblea PBA de recarga Ø46 + estampilla precinto 1" × 200 mm válvula-cuerpo | F26: 1 | G26: u | H26: Nuevo (venta en PBA) | I26: IRAM 3517-2:2020 Res. OPDS 522/07 | J26: Sí | K26: Ministerio de Ambiente PBA (ex OPDS) | L26: -
A27: RK-ABC1-B | B27: FL_MAT_ABC_1kg | C27: Extintor ABC 1 kg | D27: B - Mantenimiento con apertura sin descarga (control interior, PH) | E27: Tarjeta de identificación AGC (módulo papel con QR + etiqueta AGC) | F27: 1 | G27: u | H27: Nuevo (destino CABA) | I27: IRAM 3517-2:2020 Ord. 40.473 art. 6 · Res. AGC 32/15 | J27: Sí | K27: Agencia Gubernamental de Control (CABA) | L27: -
A28: RK-ABC1-B | B28: FL_MAT_ABC_1kg | C28: Extintor ABC 1 kg | D28: B - Mantenimiento con apertura sin descarga (control interior, PH) | E28: Tarjeta de identificación DPS de revisión / recarga | F28: 1 | G28: u | H28: Nuevo (PBA) | I28: IRAM 3517-2:2020 Res. 349/07 art. 21 | J28: Sí | K28: Ministerio de Ambiente PBA (ex OPDS) | L28: -
A29: RK-ABC1-B | B29: FL_MAT_ABC_1kg | C29: Extintor ABC 1 kg | D29: B - Mantenimiento con apertura sin descarga (control interior, PH) | E29: Grabado de la fecha del servicio en el tubo de pesca (lápiz vibratorio; en polvo, marcador indeleble) | F29: 1 | G29: u | H29: Proceso | I29: IRAM 3517-2:2020 Res. 349/07 art. 28 | J29: No
A30: RK-ABC1-B | B30: FL_MAT_ABC_1kg | C30: Extintor ABC 1 kg | D30: B - Mantenimiento con apertura sin descarga (control interior, PH) | E30: Si hubo PH: oblea de vencimiento de PH + «PH» y fecha grabados en el tubo de pesca (CO₂: fecha y logo estampados en la ojiva) | F30: 1 | G30: u | H30: Proceso | I30: IRAM 3517-2:2020 Res. 349/07 art. 29 · IRAM 3517-2 | J30: No
A31: RK-ABC1-B | B31: FL_MAT_ABC_1kg | C31: Extintor ABC 1 kg | D31: B - Mantenimiento con apertura sin descarga (control interior, PH) | E31: Junta tórica de asiento del cuello | F31: 1 | G31: u | H31: Nuevo (R: cambio sistemático) | J31: Sí | K31: Argensold | L31: Matafuegos Iglesias
A32: RK-ABC1-B | B32: FL_MAT_ABC_1kg | C32: Extintor ABC 1 kg | D32: B - Mantenimiento con apertura sin descarga (control interior, PH) | E32: Gas impulsor: N₂ | F32: 0.0047 | G32: kg | H32: Nuevo | I32: IRAM 3517-2:2020 9.4.9 tabla 2 | J32: Sí | K32: Air Liquide Argentina - sucursal Piñeyro | L32: Gogniat
A33: RK-ABC1-C | B33: FL_MAT_ABC_1kg | C33: Extintor ABC 1 kg | D33: C - Cambio obligatorio de polvo (versión anterior de la IRAM 3569) | E33: Polvo químico seco ABC 60 (Sello IRAM 3569) | F33: 1.05 | G33: kg | H33: Nuevo 100 %; el viejo va a residuos (RC-IR) | I33: IRAM 3517-2:2020 9.9.4 | J33: Sí | K33: DEM S.A. (DEMSA) | L33: Polvex S.R.L. / Sancibrao
A34: RK-ABC1-C | B34: FL_MAT_ABC_1kg | C34: Extintor ABC 1 kg | D34: C - Cambio obligatorio de polvo (versión anterior de la IRAM 3569) | E34: Precinto plástico numerado, color, con nombre del recargador | F34: 1 | G34: u | H34: Nuevo | I34: IRAM 3517-2:2020 9.4.13 | J34: Sí | K34: SonFuertes (vía Papelera Damián) | L34: Precinter S.R.L.
A35: RK-ABC1-C | B35: FL_MAT_ABC_1kg | C35: Extintor ABC 1 kg | D35: C - Cambio obligatorio de polvo (versión anterior de la IRAM 3569) | E35: Marbete (anillo, color del año) | F35: 1 | G35: u | H35: Nuevo | I35: IRAM 3517-2:2020 9.6 · anexo E | J35: Sí | K35: Astuprint | L35: Multilabel Argentina S.A.
A36: RK-ABC1-C | B36: FL_MAT_ABC_1kg | C36: Extintor ABC 1 kg | D36: C - Cambio obligatorio de polvo (versión anterior de la IRAM 3569) | E36: Etiqueta de servicio del recargador (extintor n°, serie, próxima recarga y PH) | F36: 1 | G36: u | H36: Nuevo | I36: IRAM 3517-2:2020 9.4.14 · relevado Suyai/Firegram | J36: Sí | K36: Astuprint | L36: Multilabel Argentina S.A.
A37: RK-ABC1-C | B37: FL_MAT_ABC_1kg | C37: Extintor ABC 1 kg | D37: C - Cambio obligatorio de polvo (versión anterior de la IRAM 3569) | E37: Oblea PBA de recarga Ø46 + estampilla precinto 1" × 200 mm válvula-cuerpo | F37: 1 | G37: u | H37: Nuevo (venta en PBA) | I37: IRAM 3517-2:2020 Res. OPDS 522/07 | J37: Sí | K37: Ministerio de Ambiente PBA (ex OPDS) | L37: -
A38: RK-ABC1-C | B38: FL_MAT_ABC_1kg | C38: Extintor ABC 1 kg | D38: C - Cambio obligatorio de polvo (versión anterior de la IRAM 3569) | E38: Tarjeta de identificación AGC (módulo papel con QR + etiqueta AGC) | F38: 1 | G38: u | H38: Nuevo (destino CABA) | I38: IRAM 3517-2:2020 Ord. 40.473 art. 6 · Res. AGC 32/15 | J38: Sí | K38: Agencia Gubernamental de Control (CABA) | L38: -
A39: RK-ABC1-C | B39: FL_MAT_ABC_1kg | C39: Extintor ABC 1 kg | D39: C - Cambio obligatorio de polvo (versión anterior de la IRAM 3569) | E39: Tarjeta de identificación DPS de revisión / recarga | F39: 1 | G39: u | H39: Nuevo (PBA) | I39: IRAM 3517-2:2020 Res. 349/07 art. 21 | J39: Sí | K39: Ministerio de Ambiente PBA (ex OPDS) | L39: -
A40: RK-ABC1-C | B40: FL_MAT_ABC_1kg | C40: Extintor ABC 1 kg | D40: C - Cambio obligatorio de polvo (versión anterior de la IRAM 3569) | E40: Grabado de la fecha del servicio en el tubo de pesca (lápiz vibratorio; en polvo, marcador indeleble) | F40: 1 | G40: u | H40: Proceso | I40: IRAM 3517-2:2020 Res. 349/07 art. 28 | J40: No
A41: RK-ABC1-C | B41: FL_MAT_ABC_1kg | C41: Extintor ABC 1 kg | D41: C - Cambio obligatorio de polvo (versión anterior de la IRAM 3569) | E41: Si hubo PH: oblea de vencimiento de PH + «PH» y fecha grabados en el tubo de pesca (CO₂: fecha y logo estampados en la ojiva) | F41: 1 | G41: u | H41: Proceso | I41: IRAM 3517-2:2020 Res. 349/07 art. 29 · IRAM 3517-2 | J41: No
A42: RK-ABC1-C | B42: FL_MAT_ABC_1kg | C42: Extintor ABC 1 kg | D42: C - Cambio obligatorio de polvo (versión anterior de la IRAM 3569) | E42: Junta tórica de asiento del cuello | F42: 1 | G42: u | H42: Nuevo (R: cambio sistemático) | J42: Sí | K42: Argensold | L42: Matafuegos Iglesias
A43: RK-ABC1-C | B43: FL_MAT_ABC_1kg | C43: Extintor ABC 1 kg | D43: C - Cambio obligatorio de polvo (versión anterior de la IRAM 3569) | E43: Gas impulsor: N₂ | F43: 0.0047 | G43: kg | H43: Nuevo | I43: IRAM 3517-2:2020 9.4.9 tabla 2 | J43: Sí | K43: Air Liquide Argentina - sucursal Piñeyro | L43: Gogniat
A44: RK-ABC1-I | B44: FL_MAT_ABC_1kg | C44: Extintor ABC 1 kg | D44: Según inspección (consumo estadístico a definir) | E44: Manómetro / manguera / tobera / kit de válvula | F44: - | G44: u | H44: Recambio sólo si falla | I44: IRAM 3517-2:2020 9.4.11 (cada manguera vuelve a su extintor) | J44: Sí | K44: Polvex S.R.L. / Sancibrao | L44: Yukon / MatafuegosYa S.R.L.
A45: RK-ABC2.5-A | B45: FL_MAT_ABC_2.5kg | C45: Extintor ABC 2,5 kg | D45: A - Extintor descargado (uso o descarga parcial) | E45: Polvo químico seco ABC 60 (Sello IRAM 3569) | F45: 2.55 | G45: kg | H45: Nuevo 100 % | I45: IRAM 3517-2:2020 9.9.1.4: el polvo de un extintor accionado no se reutiliza | J45: Sí | K45: DEM S.A. (DEMSA) | L45: Polvex S.R.L. / Sancibrao
A46: RK-ABC2.5-A | B46: FL_MAT_ABC_2.5kg | C46: Extintor ABC 2,5 kg | D46: A - Extintor descargado (uso o descarga parcial) | E46: Precinto plástico numerado, color, con nombre del recargador | F46: 1 | G46: u | H46: Nuevo | I46: IRAM 3517-2:2020 9.4.13 | J46: Sí | K46: SonFuertes (vía Papelera Damián) | L46: Precinter S.R.L.
A47: RK-ABC2.5-A | B47: FL_MAT_ABC_2.5kg | C47: Extintor ABC 2,5 kg | D47: A - Extintor descargado (uso o descarga parcial) | E47: Marbete (anillo, color del año) | F47: 1 | G47: u | H47: Nuevo | I47: IRAM 3517-2:2020 9.6 · anexo E | J47: Sí | K47: Astuprint | L47: Multilabel Argentina S.A.
A48: RK-ABC2.5-A | B48: FL_MAT_ABC_2.5kg | C48: Extintor ABC 2,5 kg | D48: A - Extintor descargado (uso o descarga parcial) | E48: Etiqueta de servicio del recargador (extintor n°, serie, próxima recarga y PH) | F48: 1 | G48: u | H48: Nuevo | I48: IRAM 3517-2:2020 9.4.14 · relevado Suyai/Firegram | J48: Sí | K48: Astuprint | L48: Multilabel Argentina S.A.
A49: RK-ABC2.5-A | B49: FL_MAT_ABC_2.5kg | C49: Extintor ABC 2,5 kg | D49: A - Extintor descargado (uso o descarga parcial) | E49: Oblea PBA de recarga Ø46 + estampilla precinto 1" × 200 mm válvula-cuerpo | F49: 1 | G49: u | H49: Nuevo (venta en PBA) | I49: IRAM 3517-2:2020 Res. OPDS 522/07 | J49: Sí | K49: Ministerio de Ambiente PBA (ex OPDS) | L49: -
A50: RK-ABC2.5-A | B50: FL_MAT_ABC_2.5kg | C50: Extintor ABC 2,5 kg | D50: A - Extintor descargado (uso o descarga parcial) | E50: Tarjeta de identificación AGC (módulo papel con QR + etiqueta AGC) | F50: 1 | G50: u | H50: Nuevo (destino CABA) | I50: IRAM 3517-2:2020 Ord. 40.473 art. 6 · Res. AGC 32/15 | J50: Sí | K50: Agencia Gubernamental de Control (CABA) | L50: -
A51: RK-ABC2.5-A | B51: FL_MAT_ABC_2.5kg | C51: Extintor ABC 2,5 kg | D51: A - Extintor descargado (uso o descarga parcial) | E51: Tarjeta de identificación DPS de revisión / recarga | F51: 1 | G51: u | H51: Nuevo (PBA) | I51: IRAM 3517-2:2020 Res. 349/07 art. 21 | J51: Sí | K51: Ministerio de Ambiente PBA (ex OPDS) | L51: -
A52: RK-ABC2.5-A | B52: FL_MAT_ABC_2.5kg | C52: Extintor ABC 2,5 kg | D52: A - Extintor descargado (uso o descarga parcial) | E52: Grabado de la fecha del servicio en el tubo de pesca (lápiz vibratorio; en polvo, marcador indeleble) | F52: 1 | G52: u | H52: Proceso | I52: IRAM 3517-2:2020 Res. 349/07 art. 28 | J52: No
A53: RK-ABC2.5-A | B53: FL_MAT_ABC_2.5kg | C53: Extintor ABC 2,5 kg | D53: A - Extintor descargado (uso o descarga parcial) | E53: Si hubo PH: oblea de vencimiento de PH + «PH» y fecha grabados en el tubo de pesca (CO₂: fecha y logo estampados en la ojiva) | F53: 1 | G53: u | H53: Proceso | I53: IRAM 3517-2:2020 Res. 349/07 art. 29 · IRAM 3517-2 | J53: No
A54: RK-ABC2.5-A | B54: FL_MAT_ABC_2.5kg | C54: Extintor ABC 2,5 kg | D54: A - Extintor descargado (uso o descarga parcial) | E54: Junta tórica de asiento del cuello | F54: 1 | G54: u | H54: Nuevo (R: cambio sistemático) | J54: Sí | K54: Argensold | L54: Matafuegos Iglesias
A55: RK-ABC2.5-A | B55: FL_MAT_ABC_2.5kg | C55: Extintor ABC 2,5 kg | D55: A - Extintor descargado (uso o descarga parcial) | E55: Gas impulsor: N₂ | F55: 0.0212 | G55: kg | H55: Nuevo | I55: IRAM 3517-2:2020 9.4.9 tabla 2 | J55: Sí | K55: Air Liquide Argentina - sucursal Piñeyro | L55: Gogniat
A56: RK-ABC2.5-B | B56: FL_MAT_ABC_2.5kg | C56: Extintor ABC 2,5 kg | D56: B - Mantenimiento con apertura sin descarga (control interior, PH) | E56: Polvo químico seco ABC 60 (Sello IRAM 3569) recuperado | F56: 2.5 | G56: kg | H56: Recuperado en sistema cerrado | I56: IRAM 3517-2:2020 4.4.1 y) sistema cerrado de recuperación con inspección; 9.9.3 control (puffer IRAM 3672, fusión IRAM 3569 en ABC) | J56: No
A57: RK-ABC2.5-B | B57: FL_MAT_ABC_2.5kg | C57: Extintor ABC 2,5 kg | D57: B - Mantenimiento con apertura sin descarga (control interior, PH) | E57: Polvo químico seco ABC 60 (Sello IRAM 3569) | F57: 0.05 | G57: kg | H57: Nuevo: reposición = carga objetivo − límite inferior de 0 / +100 g (cota superior) | I57: IRAM 3517-2:2020 9.4.12 tabla 3 · anexo F; mismo tipo y marca (prohibido mezclar ABC con BC, 9.9.1.6) | J57: Sí | K57: DEM S.A. (DEMSA) | L57: Polvex S.R.L. / Sancibrao
A58: RK-ABC2.5-B | B58: FL_MAT_ABC_2.5kg | C58: Extintor ABC 2,5 kg | D58: B - Mantenimiento con apertura sin descarga (control interior, PH) | E58: Precinto plástico numerado, color, con nombre del recargador | F58: 1 | G58: u | H58: Nuevo | I58: IRAM 3517-2:2020 9.4.13 | J58: Sí | K58: SonFuertes (vía Papelera Damián) | L58: Precinter S.R.L.
A59: RK-ABC2.5-B | B59: FL_MAT_ABC_2.5kg | C59: Extintor ABC 2,5 kg | D59: B - Mantenimiento con apertura sin descarga (control interior, PH) | E59: Marbete (anillo, color del año) | F59: 1 | G59: u | H59: Nuevo | I59: IRAM 3517-2:2020 9.6 · anexo E | J59: Sí | K59: Astuprint | L59: Multilabel Argentina S.A.
A60: RK-ABC2.5-B | B60: FL_MAT_ABC_2.5kg | C60: Extintor ABC 2,5 kg | D60: B - Mantenimiento con apertura sin descarga (control interior, PH) | E60: Etiqueta de servicio del recargador (extintor n°, serie, próxima recarga y PH) | F60: 1 | G60: u | H60: Nuevo | I60: IRAM 3517-2:2020 9.4.14 · relevado Suyai/Firegram | J60: Sí | K60: Astuprint | L60: Multilabel Argentina S.A.
A61: RK-ABC2.5-B | B61: FL_MAT_ABC_2.5kg | C61: Extintor ABC 2,5 kg | D61: B - Mantenimiento con apertura sin descarga (control interior, PH) | E61: Oblea PBA de recarga Ø46 + estampilla precinto 1" × 200 mm válvula-cuerpo | F61: 1 | G61: u | H61: Nuevo (venta en PBA) | I61: IRAM 3517-2:2020 Res. OPDS 522/07 | J61: Sí | K61: Ministerio de Ambiente PBA (ex OPDS) | L61: -
A62: RK-ABC2.5-B | B62: FL_MAT_ABC_2.5kg | C62: Extintor ABC 2,5 kg | D62: B - Mantenimiento con apertura sin descarga (control interior, PH) | E62: Tarjeta de identificación AGC (módulo papel con QR + etiqueta AGC) | F62: 1 | G62: u | H62: Nuevo (destino CABA) | I62: IRAM 3517-2:2020 Ord. 40.473 art. 6 · Res. AGC 32/15 | J62: Sí | K62: Agencia Gubernamental de Control (CABA) | L62: -
A63: RK-ABC2.5-B | B63: FL_MAT_ABC_2.5kg | C63: Extintor ABC 2,5 kg | D63: B - Mantenimiento con apertura sin descarga (control interior, PH) | E63: Tarjeta de identificación DPS de revisión / recarga | F63: 1 | G63: u | H63: Nuevo (PBA) | I63: IRAM 3517-2:2020 Res. 349/07 art. 21 | J63: Sí | K63: Ministerio de Ambiente PBA (ex OPDS) | L63: -
A64: RK-ABC2.5-B | B64: FL_MAT_ABC_2.5kg | C64: Extintor ABC 2,5 kg | D64: B - Mantenimiento con apertura sin descarga (control interior, PH) | E64: Grabado de la fecha del servicio en el tubo de pesca (lápiz vibratorio; en polvo, marcador indeleble) | F64: 1 | G64: u | H64: Proceso | I64: IRAM 3517-2:2020 Res. 349/07 art. 28 | J64: No
A65: RK-ABC2.5-B | B65: FL_MAT_ABC_2.5kg | C65: Extintor ABC 2,5 kg | D65: B - Mantenimiento con apertura sin descarga (control interior, PH) | E65: Si hubo PH: oblea de vencimiento de PH + «PH» y fecha grabados en el tubo de pesca (CO₂: fecha y logo estampados en la ojiva) | F65: 1 | G65: u | H65: Proceso | I65: IRAM 3517-2:2020 Res. 349/07 art. 29 · IRAM 3517-2 | J65: No
A66: RK-ABC2.5-B | B66: FL_MAT_ABC_2.5kg | C66: Extintor ABC 2,5 kg | D66: B - Mantenimiento con apertura sin descarga (control interior, PH) | E66: Junta tórica de asiento del cuello | F66: 1 | G66: u | H66: Nuevo (R: cambio sistemático) | J66: Sí | K66: Argensold | L66: Matafuegos Iglesias
A67: RK-ABC2.5-B | B67: FL_MAT_ABC_2.5kg | C67: Extintor ABC 2,5 kg | D67: B - Mantenimiento con apertura sin descarga (control interior, PH) | E67: Gas impulsor: N₂ | F67: 0.0212 | G67: kg | H67: Nuevo | I67: IRAM 3517-2:2020 9.4.9 tabla 2 | J67: Sí | K67: Air Liquide Argentina - sucursal Piñeyro | L67: Gogniat
A68: RK-ABC2.5-C | B68: FL_MAT_ABC_2.5kg | C68: Extintor ABC 2,5 kg | D68: C - Cambio obligatorio de polvo (versión anterior de la IRAM 3569) | E68: Polvo químico seco ABC 60 (Sello IRAM 3569) | F68: 2.55 | G68: kg | H68: Nuevo 100 %; el viejo va a residuos (RC-IR) | I68: IRAM 3517-2:2020 9.9.4 | J68: Sí | K68: DEM S.A. (DEMSA) | L68: Polvex S.R.L. / Sancibrao
A69: RK-ABC2.5-C | B69: FL_MAT_ABC_2.5kg | C69: Extintor ABC 2,5 kg | D69: C - Cambio obligatorio de polvo (versión anterior de la IRAM 3569) | E69: Precinto plástico numerado, color, con nombre del recargador | F69: 1 | G69: u | H69: Nuevo | I69: IRAM 3517-2:2020 9.4.13 | J69: Sí | K69: SonFuertes (vía Papelera Damián) | L69: Precinter S.R.L.
A70: RK-ABC2.5-C | B70: FL_MAT_ABC_2.5kg | C70: Extintor ABC 2,5 kg | D70: C - Cambio obligatorio de polvo (versión anterior de la IRAM 3569) | E70: Marbete (anillo, color del año) | F70: 1 | G70: u | H70: Nuevo | I70: IRAM 3517-2:2020 9.6 · anexo E | J70: Sí | K70: Astuprint | L70: Multilabel Argentina S.A.
A71: RK-ABC2.5-C | B71: FL_MAT_ABC_2.5kg | C71: Extintor ABC 2,5 kg | D71: C - Cambio obligatorio de polvo (versión anterior de la IRAM 3569) | E71: Etiqueta de servicio del recargador (extintor n°, serie, próxima recarga y PH) | F71: 1 | G71: u | H71: Nuevo | I71: IRAM 3517-2:2020 9.4.14 · relevado Suyai/Firegram | J71: Sí | K71: Astuprint | L71: Multilabel Argentina S.A.
A72: RK-ABC2.5-C | B72: FL_MAT_ABC_2.5kg | C72: Extintor ABC 2,5 kg | D72: C - Cambio obligatorio de polvo (versión anterior de la IRAM 3569) | E72: Oblea PBA de recarga Ø46 + estampilla precinto 1" × 200 mm válvula-cuerpo | F72: 1 | G72: u | H72: Nuevo (venta en PBA) | I72: IRAM 3517-2:2020 Res. OPDS 522/07 | J72: Sí | K72: Ministerio de Ambiente PBA (ex OPDS) | L72: -
A73: RK-ABC2.5-C | B73: FL_MAT_ABC_2.5kg | C73: Extintor ABC 2,5 kg | D73: C - Cambio obligatorio de polvo (versión anterior de la IRAM 3569) | E73: Tarjeta de identificación AGC (módulo papel con QR + etiqueta AGC) | F73: 1 | G73: u | H73: Nuevo (destino CABA) | I73: IRAM 3517-2:2020 Ord. 40.473 art. 6 · Res. AGC 32/15 | J73: Sí | K73: Agencia Gubernamental de Control (CABA) | L73: -
A74: RK-ABC2.5-C | B74: FL_MAT_ABC_2.5kg | C74: Extintor ABC 2,5 kg | D74: C - Cambio obligatorio de polvo (versión anterior de la IRAM 3569) | E74: Tarjeta de identificación DPS de revisión / recarga | F74: 1 | G74: u | H74: Nuevo (PBA) | I74: IRAM 3517-2:2020 Res. 349/07 art. 21 | J74: Sí | K74: Ministerio de Ambiente PBA (ex OPDS) | L74: -
A75: RK-ABC2.5-C | B75: FL_MAT_ABC_2.5kg | C75: Extintor ABC 2,5 kg | D75: C - Cambio obligatorio de polvo (versión anterior de la IRAM 3569) | E75: Grabado de la fecha del servicio en el tubo de pesca (lápiz vibratorio; en polvo, marcador indeleble) | F75: 1 | G75: u | H75: Proceso | I75: IRAM 3517-2:2020 Res. 349/07 art. 28 | J75: No
A76: RK-ABC2.5-C | B76: FL_MAT_ABC_2.5kg | C76: Extintor ABC 2,5 kg | D76: C - Cambio obligatorio de polvo (versión anterior de la IRAM 3569) | E76: Si hubo PH: oblea de vencimiento de PH + «PH» y fecha grabados en el tubo de pesca (CO₂: fecha y logo estampados en la ojiva) | F76: 1 | G76: u | H76: Proceso | I76: IRAM 3517-2:2020 Res. 349/07 art. 29 · IRAM 3517-2 | J76: No
A77: RK-ABC2.5-C | B77: FL_MAT_ABC_2.5kg | C77: Extintor ABC 2,5 kg | D77: C - Cambio obligatorio de polvo (versión anterior de la IRAM 3569) | E77: Junta tórica de asiento del cuello | F77: 1 | G77: u | H77: Nuevo (R: cambio sistemático) | J77: Sí | K77: Argensold | L77: Matafuegos Iglesias
A78: RK-ABC2.5-C | B78: FL_MAT_ABC_2.5kg | C78: Extintor ABC 2,5 kg | D78: C - Cambio obligatorio de polvo (versión anterior de la IRAM 3569) | E78: Gas impulsor: N₂ | F78: 0.0212 | G78: kg | H78: Nuevo | I78: IRAM 3517-2:2020 9.4.9 tabla 2 | J78: Sí | K78: Air Liquide Argentina - sucursal Piñeyro | L78: Gogniat
A79: RK-ABC2.5-I | B79: FL_MAT_ABC_2.5kg | C79: Extintor ABC 2,5 kg | D79: Según inspección (consumo estadístico a definir) | E79: Manómetro / manguera / tobera / kit de válvula | F79: - | G79: u | H79: Recambio sólo si falla | I79: IRAM 3517-2:2020 9.4.11 (cada manguera vuelve a su extintor) | J79: Sí | K79: Polvex S.R.L. / Sancibrao | L79: Yukon / MatafuegosYa S.R.L.
A80: RK-ABC5-A | B80: FL_MAT_ABC_5kg | C80: Extintor ABC 5 kg | D80: A - Extintor descargado (uso o descarga parcial) | E80: Polvo químico seco ABC 60 (Sello IRAM 3569) | F80: 5.15 | G80: kg | H80: Nuevo 100 % | I80: IRAM 3517-2:2020 9.9.1.4: el polvo de un extintor accionado no se reutiliza | J80: Sí | K80: DEM S.A. (DEMSA) | L80: Polvex S.R.L. / Sancibrao
A81: RK-ABC5-A | B81: FL_MAT_ABC_5kg | C81: Extintor ABC 5 kg | D81: A - Extintor descargado (uso o descarga parcial) | E81: Precinto plástico numerado, color, con nombre del recargador | F81: 1 | G81: u | H81: Nuevo | I81: IRAM 3517-2:2020 9.4.13 | J81: Sí | K81: SonFuertes (vía Papelera Damián) | L81: Precinter S.R.L.
A82: RK-ABC5-A | B82: FL_MAT_ABC_5kg | C82: Extintor ABC 5 kg | D82: A - Extintor descargado (uso o descarga parcial) | E82: Marbete (anillo, color del año) | F82: 1 | G82: u | H82: Nuevo | I82: IRAM 3517-2:2020 9.6 · anexo E | J82: Sí | K82: Astuprint | L82: Multilabel Argentina S.A.
A83: RK-ABC5-A | B83: FL_MAT_ABC_5kg | C83: Extintor ABC 5 kg | D83: A - Extintor descargado (uso o descarga parcial) | E83: Etiqueta de servicio del recargador (extintor n°, serie, próxima recarga y PH) | F83: 1 | G83: u | H83: Nuevo | I83: IRAM 3517-2:2020 9.4.14 · relevado Suyai/Firegram | J83: Sí | K83: Astuprint | L83: Multilabel Argentina S.A.
A84: RK-ABC5-A | B84: FL_MAT_ABC_5kg | C84: Extintor ABC 5 kg | D84: A - Extintor descargado (uso o descarga parcial) | E84: Oblea PBA de recarga Ø46 + estampilla precinto 1" × 200 mm válvula-cuerpo | F84: 1 | G84: u | H84: Nuevo (venta en PBA) | I84: IRAM 3517-2:2020 Res. OPDS 522/07 | J84: Sí | K84: Ministerio de Ambiente PBA (ex OPDS) | L84: -
A85: RK-ABC5-A | B85: FL_MAT_ABC_5kg | C85: Extintor ABC 5 kg | D85: A - Extintor descargado (uso o descarga parcial) | E85: Tarjeta de identificación AGC (módulo papel con QR + etiqueta AGC) | F85: 1 | G85: u | H85: Nuevo (destino CABA) | I85: IRAM 3517-2:2020 Ord. 40.473 art. 6 · Res. AGC 32/15 | J85: Sí | K85: Agencia Gubernamental de Control (CABA) | L85: -
A86: RK-ABC5-A | B86: FL_MAT_ABC_5kg | C86: Extintor ABC 5 kg | D86: A - Extintor descargado (uso o descarga parcial) | E86: Tarjeta de identificación DPS de revisión / recarga | F86: 1 | G86: u | H86: Nuevo (PBA) | I86: IRAM 3517-2:2020 Res. 349/07 art. 21 | J86: Sí | K86: Ministerio de Ambiente PBA (ex OPDS) | L86: -
A87: RK-ABC5-A | B87: FL_MAT_ABC_5kg | C87: Extintor ABC 5 kg | D87: A - Extintor descargado (uso o descarga parcial) | E87: Grabado de la fecha del servicio en el tubo de pesca (lápiz vibratorio; en polvo, marcador indeleble) | F87: 1 | G87: u | H87: Proceso | I87: IRAM 3517-2:2020 Res. 349/07 art. 28 | J87: No
A88: RK-ABC5-A | B88: FL_MAT_ABC_5kg | C88: Extintor ABC 5 kg | D88: A - Extintor descargado (uso o descarga parcial) | E88: Si hubo PH: oblea de vencimiento de PH + «PH» y fecha grabados en el tubo de pesca (CO₂: fecha y logo estampados en la ojiva) | F88: 1 | G88: u | H88: Proceso | I88: IRAM 3517-2:2020 Res. 349/07 art. 29 · IRAM 3517-2 | J88: No
A89: RK-ABC5-A | B89: FL_MAT_ABC_5kg | C89: Extintor ABC 5 kg | D89: A - Extintor descargado (uso o descarga parcial) | E89: Junta tórica de asiento del cuello | F89: 1 | G89: u | H89: Nuevo (R: cambio sistemático) | J89: Sí | K89: Argensold | L89: Matafuegos Iglesias
A90: RK-ABC5-A | B90: FL_MAT_ABC_5kg | C90: Extintor ABC 5 kg | D90: A - Extintor descargado (uso o descarga parcial) | E90: Gas impulsor: N₂ | F90: 0.0251 | G90: kg | H90: Nuevo | I90: IRAM 3517-2:2020 9.4.9 tabla 2 | J90: Sí | K90: Air Liquide Argentina - sucursal Piñeyro | L90: Gogniat
A91: RK-ABC5-B | B91: FL_MAT_ABC_5kg | C91: Extintor ABC 5 kg | D91: B - Mantenimiento con apertura sin descarga (control interior, PH) | E91: Polvo químico seco ABC 60 (Sello IRAM 3569) recuperado | F91: 5 | G91: kg | H91: Recuperado en sistema cerrado | I91: IRAM 3517-2:2020 4.4.1 y) sistema cerrado de recuperación con inspección; 9.9.3 control (puffer IRAM 3672, fusión IRAM 3569 en ABC) | J91: No
A92: RK-ABC5-B | B92: FL_MAT_ABC_5kg | C92: Extintor ABC 5 kg | D92: B - Mantenimiento con apertura sin descarga (control interior, PH) | E92: Polvo químico seco ABC 60 (Sello IRAM 3569) | F92: 0.15 | G92: kg | H92: Nuevo: reposición = carga objetivo − límite inferior de 0 / +300 g (cota superior) | I92: IRAM 3517-2:2020 9.4.12 tabla 3 · anexo F; mismo tipo y marca (prohibido mezclar ABC con BC, 9.9.1.6) | J92: Sí | K92: DEM S.A. (DEMSA) | L92: Polvex S.R.L. / Sancibrao
A93: RK-ABC5-B | B93: FL_MAT_ABC_5kg | C93: Extintor ABC 5 kg | D93: B - Mantenimiento con apertura sin descarga (control interior, PH) | E93: Precinto plástico numerado, color, con nombre del recargador | F93: 1 | G93: u | H93: Nuevo | I93: IRAM 3517-2:2020 9.4.13 | J93: Sí | K93: SonFuertes (vía Papelera Damián) | L93: Precinter S.R.L.
A94: RK-ABC5-B | B94: FL_MAT_ABC_5kg | C94: Extintor ABC 5 kg | D94: B - Mantenimiento con apertura sin descarga (control interior, PH) | E94: Marbete (anillo, color del año) | F94: 1 | G94: u | H94: Nuevo | I94: IRAM 3517-2:2020 9.6 · anexo E | J94: Sí | K94: Astuprint | L94: Multilabel Argentina S.A.
A95: RK-ABC5-B | B95: FL_MAT_ABC_5kg | C95: Extintor ABC 5 kg | D95: B - Mantenimiento con apertura sin descarga (control interior, PH) | E95: Etiqueta de servicio del recargador (extintor n°, serie, próxima recarga y PH) | F95: 1 | G95: u | H95: Nuevo | I95: IRAM 3517-2:2020 9.4.14 · relevado Suyai/Firegram | J95: Sí | K95: Astuprint | L95: Multilabel Argentina S.A.
A96: RK-ABC5-B | B96: FL_MAT_ABC_5kg | C96: Extintor ABC 5 kg | D96: B - Mantenimiento con apertura sin descarga (control interior, PH) | E96: Oblea PBA de recarga Ø46 + estampilla precinto 1" × 200 mm válvula-cuerpo | F96: 1 | G96: u | H96: Nuevo (venta en PBA) | I96: IRAM 3517-2:2020 Res. OPDS 522/07 | J96: Sí | K96: Ministerio de Ambiente PBA (ex OPDS) | L96: -
A97: RK-ABC5-B | B97: FL_MAT_ABC_5kg | C97: Extintor ABC 5 kg | D97: B - Mantenimiento con apertura sin descarga (control interior, PH) | E97: Tarjeta de identificación AGC (módulo papel con QR + etiqueta AGC) | F97: 1 | G97: u | H97: Nuevo (destino CABA) | I97: IRAM 3517-2:2020 Ord. 40.473 art. 6 · Res. AGC 32/15 | J97: Sí | K97: Agencia Gubernamental de Control (CABA) | L97: -
A98: RK-ABC5-B | B98: FL_MAT_ABC_5kg | C98: Extintor ABC 5 kg | D98: B - Mantenimiento con apertura sin descarga (control interior, PH) | E98: Tarjeta de identificación DPS de revisión / recarga | F98: 1 | G98: u | H98: Nuevo (PBA) | I98: IRAM 3517-2:2020 Res. 349/07 art. 21 | J98: Sí | K98: Ministerio de Ambiente PBA (ex OPDS) | L98: -
A99: RK-ABC5-B | B99: FL_MAT_ABC_5kg | C99: Extintor ABC 5 kg | D99: B - Mantenimiento con apertura sin descarga (control interior, PH) | E99: Grabado de la fecha del servicio en el tubo de pesca (lápiz vibratorio; en polvo, marcador indeleble) | F99: 1 | G99: u | H99: Proceso | I99: IRAM 3517-2:2020 Res. 349/07 art. 28 | J99: No
A100: RK-ABC5-B | B100: FL_MAT_ABC_5kg | C100: Extintor ABC 5 kg | D100: B - Mantenimiento con apertura sin descarga (control interior, PH) | E100: Si hubo PH: oblea de vencimiento de PH + «PH» y fecha grabados en el tubo de pesca (CO₂: fecha y logo estampados en la ojiva) | F100: 1 | G100: u | H100: Proceso | I100: IRAM 3517-2:2020 Res. 349/07 art. 29 · IRAM 3517-2 | J100: No
...

Sheet 08_Quimica_Agentes
A1: Química de los agentes extintores - datos de entrada (celdas celestes)
A2: Si cambia la formulación (% de MAP, tipo de bicarbonato, concentración del acetato o del AFFF) cambia la densidad, y con ella el volumen que ocupa la carga, el volumen libre, el N₂ y si el recipiente alcanza. Cambie la densidad acá y mire 09_Carga_N2.
A4: Clave | B4: Agente | C4: Composición | D4: Mecanismo de extinción | E4: ¿Saponifica? | F4: Gas impulsor | G4: ρ aparente mín (kg/dm³) | H4: ρ aparente típica (kg/dm³) | I4: ρ aparente máx (kg/dm³) | J4: Masa molar gas (kg/mol) | K4: Fuente ρ aparente | L4: ρ empacada mín (kg/dm³) | M4: Fuente ρ empacada
A5: ABC | B5: Polvo ABC (fosfato monoamónico) con Sello IRAM 3569 - DEMSA | C5: MAP 40-90 % según grado (nominal ± 5 %) + sulfato de amonio 5-55 % + mica, sílice y silicona | D5: Captura de radicales; en clase A el MAP funde (≈177-190 °C) y cubre las brasas con una capa vítrea: el potencial A depende del grado (licencias IRAM 3523: 5 kg DEM-60 = 6A, DEM-90 = 10A) | E5: No. Ácido (pH 6-7,5 al 1 % según DEMSA; 4-5 otras fichas): no saponifica, no apto clase K; con BC reacciona (CO₂ + apelmazamiento) | F5: N₂ | G5: 0.85 | H5: 0.9 | I5: 0.98 | J5: 0.028 | K5: DEMSA HDS ABC: densidad aparente > 0,85 (piso garantizado) · típica 0,90 (ficha IZ; Corponor 0,85-0,98) · IRAM 3569 no fija densidad: exigirla en la orden de compra | L5: 1.1 | M5: NOM-104-STPS-2001 (México): polvo ABC, densidad empacada ≥ 1,10 g/cm³ (aparente ≥ 0,82). IRAM 3569 no fija densidad: exigir el valor en la OC y verificar con descarga ≥ 85 % (IRAM 3523 4.9.1)
A6: BC | B6: Polvo BC sódico con Sello IRAM 3566 - DEMSA | C6: NaHCO₃ ≥ 85,5 % (85,5-94,5) + estearatos, sílice, silicona (Púrpura K: KHCO₃ 92 ± 5 %) | D6: Captura de radicales y descomposición endotérmica (CO₂ + H₂O) | E6: Leve: alcalino (pH 8-9), saponifica superficialmente aceites; no reemplaza clase K | F6: N₂ | G6: 0.85 | H6: 0.9 | I6: 1 | J6: 0.028 | K6: DEMSA HDS Púrpura K: > 0,85 · Buckeye estándar 0,90 · Purple K aireado 0,88 | L6: 0.9 | M6: Revendido: lo carga el fabricante (se usa la típica)
A7: D | B7: Polvo clase D (cloruro de sodio) - DEMSA | C7: NaCl > 90 % + aditivos siliconados | D7: Forma costra sobre el metal fundido y lo aísla del aire | E7: No (pH 6-7,5) | F7: N₂ | G7: 0.85 | H7: 1 | I7: 1.2 | J7: 0.028 | K7: DEMSA HDS polvo D: > 0,85 · típica R (pedir valor garantizado) | L7: 1 | M7: Revendido: lo carga el fabricante (se usa la típica)
A8: HCFC | B8: HCFC Mezcla B (HCFC-123 base) | C8: HCFC-123 > 93 % + mezcla de gases < 7 % | D8: Enfriamiento y captura de radicales; no deja residuo | E8: No | F8: Argón | G8: 1.47 | H8: 1.48 | I8: 1.48 | J8: 0.04 | K8: Halotron I HDS: 1,48 kg/L a 25 °C; 655 kPa a 20 °C (IRAM 3526-1: pedir ficha local) | L8: 1.48 | M8: Líquido: densidad del agente
A9: AGUA | B9: Agua | C9: Agua potable | D9: Enfriamiento | E9: No | F9: Aire comprimido | G9: 1 | H9: 1 | I9: 1 | J9: 0.029 | K9: Catálogo de referencia: aire comprimido | L9: 1 | M9: Líquido: densidad del agente
A10: AFFF | B10: Agua + espumígeno AFFF 3 % (DEMSA 203 MN, IRAM 3515) | C10: 97 % agua + 3 % concentrado (1,025 g/cm³) | D10: Película acuosa que sella vapores + enfriamiento | E10: No | F10: Aire comprimido | G10: 1 | H10: 1 | I10: 1 | J10: 0.029 | K10: DEMSA 203 MN: concentrado 1,025 g/cm³ → premezcla ≈ 1,001 | L10: 1 | M10: Líquido: densidad del agente
A11: K | B11: Acetato de potasio - DEMSA Kitchen (IRAM 3697) | C11: Sales orgánicas de potasio + aditivos en agua | D11: SAPONIFICACIÓN y enfriamiento: el agente alcalino reacciona con los ácidos grasos del aceite caliente y forma una espuma jabonosa que sella la superficie y evita la reignición | E11: Sí: mecanismo principal (pH 8,5) | F11: N₂ | G11: 1.3 | H11: 1.3 | I11: 1.3 | J11: 0.028 | K11: DEMSA Kitchen: 1,300 g/ml a 20 °C, pH 8,5; agente certificado en las licencias IRAM 3694 de Drago y Georgia/Fadesa | L11: 1.3 | M11: Líquido: densidad del agente
A13: Criterio de aceptación del volumen libre: descarga continua ≥ 85 % de la masa de agente en el ensayo de tipo (IRAM 3523 4.9.1). Reemplaza al antiguo «volumen libre mínimo» supuesto.
A15: Grado del polvo ABC: la masa la fija la norma; el % de MAP fija el potencial A (licencias IRAM 3523 Drago y Georgia/Fadesa)
A16: Grado | B16: MAP nominal % | C16: Banda IRAM % | D16: Relleno | E16: 1 kg | F16: 2,5 kg | G16: 5 kg | H16: 10 kg | I16: Hoja técnica
A17: ABC 40 | B17: 40 | C17: 36 - 44 | D17: sulfato de amonio + 3 % aditivos | E17: sin licencia relevada | F17: sin licencia relevada | G17: sin licencia relevada | H17: sin licencia relevada | I17: DEMSA ABC 40 (Rev 02, 2019)
A18: ABC 55 | B18: 55 | C18: 52,25 - 57,75 | D18: sulfato de amonio + 3 % aditivos | E18: sin licencia relevada | F18: sin licencia relevada | G18: sin licencia relevada | H18: sin licencia relevada | I18: DEMSA ABC 55 (Rev 02, 2019)
A19: ABC 60 | B19: 60 | C19: 57 - 63 | D19: sulfato de amonio + 3 % aditivos | E19: 1A-5B:C | F19: 3A-20B:C | G19: 6A-40B:C | H19: 6A-60B:C | I19: DEMSA catálogo (ABC 60)
A20: ABC 75 | B20: 75 | C20: 71,25 - 78,75 | D20: sulfato de amonio + 3 % aditivos | E20: sin licencia relevada | F20: sin licencia relevada | G20: sin licencia relevada | H20: sin licencia relevada | I20: DEMSA catálogo (ABC 75)
A21: ABC 90 | B21: 90 | C21: 85,5 - 94,5 | D21: sulfato de amonio + 3 % aditivos | E21: - | F21: 3A-20B:C | G21: 10A-40B:C | H21: 10A-60B:C | I21: DEMSA ABC 90 (Rev 02, 2019)
A23: Agente y grado adoptado por modelo (DEMSA principal; Polvex / Sancibrao alternativa)
A24: Plano | B24: Agente / grado | C24: Norma agente | D24: Gas | E24: Potencial | F24: Alternativa
A25: FL_MAT_ABC_1kg | B25: ABC 60 | C25: IRAM 3569 | D25: N₂ seco | E25: 1A-5B:C
A26: FL_MAT_ABC_2.5kg | B26: ABC 60 | C26: IRAM 3569 | D26: N₂ seco | E26: 3A-20B:C
A27: FL_MAT_ABC_5kg | B27: ABC 60 | C27: IRAM 3569 | D27: N₂ seco | E27: 6A-40B:C | F27: ABC 90: 10A-40B:C
A28: FL_MAT_ABC_10kg | B28: ABC 60 | C28: IRAM 3569 | D28: N₂ seco | E28: 6A-60B:C | F28: ABC 90: 10A-60B:C
A29: FL_MAT_AGUA_10l | B29: Agua potable | C29: - | D29: Aire comprimido | E29: 1A
A30: FL_MAT_AFFF_10l | B30: Premezcla AFFF 3 % (DEMSA 203 MN, IRAM 3515) | C30: IRAM 3515 | D30: Aire comprimido | E30: 3A-10B
A31: FL_MAT_AFFF_50l | B31: Premezcla AFFF 3 % (DEMSA 203 MN, IRAM 3515) | C31: IRAM 3515 | D31: Aire comprimido | E31: -
A32: FL_MAT_BC_5kg | B32: BC sódico (NaHCO₃ ≥ 85,5 %) | C32: IRAM 3566 | D32: N₂ seco | E32: - | F32: BC Púrpura K (KHCO₃ 92 ± 5 %): 40B
A33: FL_MAT_SALESK_6l | B33: Acetato de potasio (DEMSA Kitchen, 1,300 g/ml, pH 8,5) | C33: IRAM 3697 | D33: N₂ seco | E33: 1A-K
A34: FL_MAT_CO2_2kg | B34: CO₂ ≥ 99,5 % | C34: IRAM 41170 | D34: autopresurizado | E34: -
A35: FL_MAT_CO2_5kg | B35: CO₂ ≥ 99,5 % | C35: IRAM 41170 | D35: autopresurizado | E35: -
A36: FL_MAT_HCFC-HFC_5kg | B36: HCFC-123 (Mezcla B) > 93 % | C36: IRAM 3526-1 | D36: Argón | E36: -
A37: FL_MAT_CLASED_9l | B37: Clase D (NaCl > 90 %) | C37: sin norma IRAM de agente (DEMSA ISO 9001) | D37: N₂ seco | E37: -
A38: FL_MAT_ABC_25kg | B38: ABC 90 | C38: IRAM 3569 | D38: N₂ seco | E38: -
A39: FL_MAT_ABC_50kg | B39: ABC 90 | C39: IRAM 3569 | D39: N₂ seco | E39: -
A40: FL_MAT_ABC_70kg | B40: ABC 90 | C40: IRAM 3569 | D40: N₂ seco | E40: -
A41: FL_MAT_ABC_100kg | B41: ABC 90 | C41: IRAM 3569 | D41: N₂ seco | E41: -

Sheet 09_Carga_N2
A1: Carga de agente y gas impulsor por extintor (fórmulas ligadas a 08_Quimica_Agentes) - la capacidad es la MASA de agente (IRAM 3523 2.2); el gas es la masa que da Ps a 20 °C en el volumen libre
A2: • Carga: nominal con la tolerancia de IRAM 3517-2:2020 tabla 3 / IRAM 3523 tabla II; si la tolerancia es sólo positiva se carga al centro de la banda.
A3: • Volumen que ocupa el polvo en servicio = masa / densidad EMPACADA (asentada después del vibrado de la carga). ABC: ≥ 1,10 kg/dm³ (NOM-104-STPS-2001; IRAM 3569 no la fija) - valor ESTIMADO (amarillo): exigirlo en la OC y confirmar con descarga ≥ 85 % (IRAM 3523 4.9.1).
A4: • Llenado: con la densidad aparente mínima (polvo suelto) se controla si el polvo entra sin vibrar; si no, la carga T01 debe vibrar el recipiente.
A5: • Gas: m = (Ps + 0,101 MPa) × V libre / (8,314 × 293,15 K) × M. N₂ seco en polvos, argón en HCFC, aire comprimido en agua, AFFF y acetato (IRAM 3517-2 tabla 2).
A7: Plano | B7: Clave agente | C7: Carga objetivo | D7: UM | E7: Tolerancia | F7: V recipiente (dm³) | G7: Ps (MPa) | H7: Gas | I7: ρ aparente mín (suelta) | J7: ρ empacada mín (asentada) | K7: V agente asentado (dm³) | L7: V libre (dm³) | M7: V libre (%) | N7: Gas impulsor (g) | O7: V agente suelto con ρ aparente mín (dm³) | P7: Control | Q7: Observaciones
A8: FL_MAT_ABC_1kg | B8: ABC | C8: 1.05 | D8: kg | E8: 0 / +100 g | F8: 1.18 | G8: 1.4 | H8: N₂ | I8: ='08_Quimica_Agentes'!$G$5 | J8: ='08_Quimica_Agentes'!$L$5 | K8: =C8/J8 | L8: =F8-K8 | M8: =L8/F8 | N8: =(G8+0.101)*1000000*MAX(0,L8)/1000/(8.314*293.15)*'08_Quimica_Agentes'!$J$5*1000 | O8: =C8/I8 | P8: =IF(L8<0,"NO ENTRA",IF(O8>F8,"VIBRAR EN EL LLENADO","OK")) | Q8: ρ empacada estimada (NOM-104): confirmar con descarga ≥ 85 % en el ensayo de tipo
A9: FL_MAT_ABC_2.5kg | B9: ABC | C9: 2.55 | D9: kg | E9: 0 / +100 g | F9: 3.5 | G9: 1.4 | H9: N₂ | I9: ='08_Quimica_Agentes'!$G$5 | J9: ='08_Quimica_Agentes'!$L$5 | K9: =C9/J9 | L9: =F9-K9 | M9: =L9/F9 | N9: =(G9+0.101)*1000000*MAX(0,L9)/1000/(8.314*293.15)*'08_Quimica_Agentes'!$J$5*1000 | O9: =C9/I9 | P9: =IF(L9<0,"NO ENTRA",IF(O9>F9,"VIBRAR EN EL LLENADO","OK")) | Q9: ρ empacada estimada (NOM-104): confirmar con descarga ≥ 85 % en el ensayo de tipo
A10: FL_MAT_ABC_5kg | B10: ABC | C10: 5.15 | D10: kg | E10: 0 / +300 g | F10: 6 | G10: 1.4 | H10: N₂ | I10: ='08_Quimica_Agentes'!$G$5 | J10: ='08_Quimica_Agentes'!$L$5 | K10: =C10/J10 | L10: =F10-K10 | M10: =L10/F10 | N10: =(G10+0.101)*1000000*MAX(0,L10)/1000/(8.314*293.15)*'08_Quimica_Agentes'!$J$5*1000 | O10: =C10/I10 | P10: =IF(L10<0,"NO ENTRA",IF(O10>F10,"VIBRAR EN EL LLENADO","OK")) | Q10: ρ empacada estimada (NOM-104): confirmar con descarga ≥ 85 % en el ensayo de tipo
A11: FL_MAT_ABC_10kg | B11: ABC | C11: 10.15 | D11: kg | E11: 0 / +300 g | F11: 12.5 | G11: 1.4 | H11: N₂ | I11: ='08_Quimica_Agentes'!$G$5 | J11: ='08_Quimica_Agentes'!$L$5 | K11: =C11/J11 | L11: =F11-K11 | M11: =L11/F11 | N11: =(G11+0.101)*1000000*MAX(0,L11)/1000/(8.314*293.15)*'08_Quimica_Agentes'!$J$5*1000 | O11: =C11/I11 | P11: =IF(L11<0,"NO ENTRA",IF(O11>F11,"VIBRAR EN EL LLENADO","OK")) | Q11: ρ empacada estimada (NOM-104): confirmar con descarga ≥ 85 % en el ensayo de tipo
A12: FL_MAT_AGUA_10l | B12: AGUA | C12: 10 | D12: L | E12: ± 3 % | F12: 13.98 | G12: 0.8 | H12: Aire comprimido | I12: ='08_Quimica_Agentes'!$G$9 | J12: ='08_Quimica_Agentes'!$L$9 | K12: =C12 | L12: =F12-K12 | M12: =L12/F12 | N12: =(G12+0.101)*1000000*MAX(0,L12)/1000/(8.314*293.15)*'08_Quimica_Agentes'!$J$9*1000 | O12: =C12 | P12: =IF(L12<0,"NO ENTRA",IF(O12>F12,"VIBRAR EN EL LLENADO","OK")) | Q12: Revendido: carga y gas del fabricante (referencia)
A13: FL_MAT_AFFF_10l | B13: AFFF | C13: 10 | D13: L | E13: ± 3 % | F13: 13.98 | G13: 0.8 | H13: Aire comprimido | I13: ='08_Quimica_Agentes'!$G$10 | J13: ='08_Quimica_Agentes'!$L$10 | K13: =C13 | L13: =F13-K13 | M13: =L13/F13 | N13: =(G13+0.101)*1000000*MAX(0,L13)/1000/(8.314*293.15)*'08_Quimica_Agentes'!$J$10*1000 | O13: =C13 | P13: =IF(L13<0,"NO ENTRA",IF(O13>F13,"VIBRAR EN EL LLENADO","OK")) | Q13: Revendido: carga y gas del fabricante (referencia)
A14: FL_MAT_AFFF_50l | B14: AFFF | C14: 50 | D14: L | E14: ± 3 % | F14: 61.8 | G14: 0.8 | H14: Aire comprimido | I14: ='08_Quimica_Agentes'!$G$10 | J14: ='08_Quimica_Agentes'!$L$10 | K14: =C14 | L14: =F14-K14 | M14: =L14/F14 | N14: =(G14+0.101)*1000000*MAX(0,L14)/1000/(8.314*293.15)*'08_Quimica_Agentes'!$J$10*1000 | O14: =C14 | P14: =IF(L14<0,"NO ENTRA",IF(O14>F14,"VIBRAR EN EL LLENADO","OK")) | Q14: Revendido: carga y gas del fabricante (referencia)
A15: FL_MAT_BC_5kg | B15: BC | C15: 5.15 | D15: kg | E15: 0 / +300 g | F15: 6 | G15: 1.4 | H15: N₂ | I15: ='08_Quimica_Agentes'!$G$6 | J15: ='08_Quimica_Agentes'!$L$6 | K15: =C15/J15 | L15: =F15-K15 | M15: =L15/F15 | N15: =(G15+0.101)*1000000*MAX(0,L15)/1000/(8.314*293.15)*'08_Quimica_Agentes'!$J$6*1000 | O15: =C15/I15 | P15: =IF(L15<0,"NO ENTRA",IF(O15>F15,"VIBRAR EN EL LLENADO","OK")) | Q15: Revendido: carga y gas del fabricante (referencia)
A16: FL_MAT_SALESK_6l | B16: K | C16: 6.09 | D16: L | E16: 0 / +3 % | F16: 8.96 | G16: 0.8 | H16: N₂ | I16: ='08_Quimica_Agentes'!$G$11 | J16: ='08_Quimica_Agentes'!$L$11 | K16: =C16 | L16: =F16-K16 | M16: =L16/F16 | N16: =(G16+0.101)*1000000*MAX(0,L16)/1000/(8.314*293.15)*'08_Quimica_Agentes'!$J$11*1000 | O16: =C16 | P16: =IF(L16<0,"NO ENTRA",IF(O16>F16,"VIBRAR EN EL LLENADO","OK")) | Q16: Revendido: carga y gas del fabricante (referencia)
A17: FL_MAT_CO2_2kg | B17: CO2 | C17: 2 | D17: kg | E17: 0 / -5 % | F17: 2.96 | G17: 15 | H17: - (autopresurizado) | P17: OK | Q17: Grado de llenado 0,676 kg/dm³ (máx. 0,75 kg/dm³, IRAM 2533 / ADR P200)
A18: FL_MAT_CO2_5kg | B18: CO2 | C18: 5 | D18: kg | E18: 0 / -5 % | F18: 7.92 | G18: 15 | H18: - (autopresurizado) | P18: OK | Q18: Grado de llenado 0,631 kg/dm³ (máx. 0,75 kg/dm³, IRAM 2533 / ADR P200)
A19: FL_MAT_HCFC-HFC_5kg | B19: HCFC | C19: 5 | D19: kg | E19: 0 / -3 % | F19: 6 | G19: 0.8 | H19: Argón | I19: ='08_Quimica_Agentes'!$G$8 | J19: ='08_Quimica_Agentes'!$L$8 | K19: =C19/J19 | L19: =F19-K19 | M19: =L19/F19 | N19: =(G19+0.101)*1000000*MAX(0,L19)/1000/(8.314*293.15)*'08_Quimica_Agentes'!$J$8*1000 | O19: =C19/I19 | P19: =IF(L19<0,"NO ENTRA",IF(O19>F19,"VIBRAR EN EL LLENADO","OK")) | Q19: Revendido: carga y gas del fabricante (referencia)
A20: FL_MAT_CLASED_9l | B20: D | C20: 9.15 | D20: kg | E20: 0 / +300 g | F20: 12.5 | G20: 1.4 | H20: N₂ | I20: ='08_Quimica_Agentes'!$G$7 | J20: ='08_Quimica_Agentes'!$L$7 | K20: =C20/J20 | L20: =F20-K20 | M20: =L20/F20 | N20: =(G20+0.101)*1000000*MAX(0,L20)/1000/(8.314*293.15)*'08_Quimica_Agentes'!$J$7*1000 | O20: =C20/I20 | P20: =IF(L20<0,"NO ENTRA",IF(O20>F20,"VIBRAR EN EL LLENADO","OK")) | Q20: Revendido: carga y gas del fabricante (referencia) · Capacidad en dm³ en el catálogo; IRAM 3523 la define en kg: definir 9 o 10 kg
A21: FL_MAT_ABC_25kg | B21: ABC | C21: 25 | D21: kg | E21: ± 3 % | F21: 34.4 | G21: 1.4 | H21: N₂ | I21: ='08_Quimica_Agentes'!$G$5 | J21: ='08_Quimica_Agentes'!$L$5 | K21: =C21/J21 | L21: =F21-K21 | M21: =L21/F21 | N21: =(G21+0.101)*1000000*MAX(0,L21)/1000/(8.314*293.15)*'08_Quimica_Agentes'!$J$5*1000 | O21: =C21/I21 | P21: =IF(L21<0,"NO ENTRA",IF(O21>F21,"VIBRAR EN EL LLENADO","OK")) | Q21: ρ empacada estimada (NOM-104): confirmar con descarga ≥ 85 % en el ensayo de tipo
A22: FL_MAT_ABC_50kg | B22: ABC | C22: 50 | D22: kg | E22: ± 3 % | F22: 61.8 | G22: 1.4 | H22: N₂ | I22: ='08_Quimica_Agentes'!$G$5 | J22: ='08_Quimica_Agentes'!$L$5 | K22: =C22/J22 | L22: =F22-K22 | M22: =L22/F22 | N22: =(G22+0.101)*1000000*MAX(0,L22)/1000/(8.314*293.15)*'08_Quimica_Agentes'!$J$5*1000 | O22: =C22/I22 | P22: =IF(L22<0,"NO ENTRA",IF(O22>F22,"VIBRAR EN EL LLENADO","OK")) | Q22: ρ empacada estimada (NOM-104): confirmar con descarga ≥ 85 % en el ensayo de tipo
A23: FL_MAT_ABC_70kg | B23: ABC | C23: 70 | D23: kg | E23: ± 3 % | F23: 96 | G23: 1.4 | H23: N₂ | I23: ='08_Quimica_Agentes'!$G$5 | J23: ='08_Quimica_Agentes'!$L$5 | K23: =C23/J23 | L23: =F23-K23 | M23: =L23/F23 | N23: =(G23+0.101)*1000000*MAX(0,L23)/1000/(8.314*293.15)*'08_Quimica_Agentes'!$J$5*1000 | O23: =C23/I23 | P23: =IF(L23<0,"NO ENTRA",IF(O23>F23,"VIBRAR EN EL LLENADO","OK")) | Q23: ρ empacada estimada (NOM-104): confirmar con descarga ≥ 85 % en el ensayo de tipo
A24: FL_MAT_ABC_100kg | B24: ABC | C24: 100 | D24: kg | E24: ± 3 % | F24: 121 | G24: 1.4 | H24: N₂ | I24: ='08_Quimica_Agentes'!$G$5 | J24: ='08_Quimica_Agentes'!$L$5 | K24: =C24/J24 | L24: =F24-K24 | M24: =L24/F24 | N24: =(G24+0.101)*1000000*MAX(0,L24)/1000/(8.314*293.15)*'08_Quimica_Agentes'!$J$5*1000 | O24: =C24/I24 | P24: =IF(L24<0,"NO ENTRA",IF(O24>F24,"VIBRAR EN EL LLENADO","OK")) | Q24: ρ empacada estimada (NOM-104): confirmar con descarga ≥ 85 % en el ensayo de tipo

Sheet 10_Proveedores
A1: Proveedores nacionales por ítem de compra (principal y alternativa) - criterio: argentinos, cercanos o razonables para Avellaneda, que vendan exactamente lo que pide el plano y cumplan la norma
A2: Distancias por ruta desde Avellaneda, aproximadas. Precios: los de la planilla de materias primas de FLAMA (MP-xx) y las cotizaciones recibidas (ver 11_Validacion_MP).
A3: Colores: | B3: Validado | D3: Estimado | F3: A validar | H3: No cumple o decisión pendiente
A5: Ítem | B5: Descripción | C5: Producto exacto que se pide | D5: Proveedor principal | E5: Domicilio | F5: Distancia | G5: Contacto | H5: Alternativa | I5: Domicilio alternativa | J5: Distancia alt. | K5: Precio / cotización de referencia | L5: Certificación / norma del principal | M5: Respaldo | N5: Estado | O5: Observaciones
A6: MP-HOJA-LAF | B6: Chapa LAF del cuerpo 2,5 / 5 / 10 kg | C6: Recorte LAF IRAM-IAS U 500-05 e=1,25/1,6/2,0 a medida de la hoja de corte | D6: Pradecon S.A. | E6: Garín, Escobar (PBA) | F6: ≈ 55 km (aprox.) | H6: Pacheco Chapas | I6: El Talar, Tigre (PBA) | J6: ≈ 40 km (aprox.) | K6: Planilla MP-02/03/04: USD 1,29 / 1,33 / 1,28 por kg (Pradecon) | L6: Bobinas de origen Ternium | M6: Q-PRADECON (173170 / 173195) | N6: Cotizado | O6: Exigir certificado de colada en la OC
A7: MP-HOJA-LAC | B7: Chapa LAC del cuerpo rodantes | C7: Recorte LAC IRAM-IAS U 500-04 e=3,2 / 4,75, σf ≥ 265 MPa | D7: Pradecon S.A. | E7: Garín, Escobar (PBA) | F7: ≈ 55 km (aprox.) | H7: Pacheco Chapas | I7: El Talar, Tigre (PBA) | J7: ≈ 40 km (aprox.) | K7: Planilla MP-11/12: USD 1,10 / 1,09 por kg (Pradecon) | L7: Bobinas de origen Ternium | M7: Q-PRADECON (173170 / 173195) | N7: Cotizado | O7: σf ≥ 265 MPa en el certificado (IRAM 3550 4.1.3.1)
A8: MP-FLEJE | B8: Fleje LAF de cúpula y fondo 1 a 10 kg | C8: Bobina flejada LAF e=0,9/1,25/1,6/2,0, ancho del plano | D8: Pacheco Chapas | E8: El Talar, Tigre (PBA) | F8: ≈ 40 km (aprox.) | H8: Pradecon S.A. | I8: Garín, Escobar (PBA) | J8: ≈ 55 km (aprox.) | K8: Planilla MP-05 a 10 y 13: USD 1,19-1,26 por kg | L8: Origen Ternium; certificado de colada a pedido | M8: Q-PACHECO (PR-42021 / PR-42024) | N8: Cotizado | O8: Pacheco flejes ≥ 1,25; Pradecon fleje 0,9 (1 kg)
A9: MP-CANO | B9: Caño del cuerpo 1 kg | C9: Caño c/costura ERW SAE 1010 Ø76,2 × 1,25, barra 6 m | D9: Metalpri / Prilux | E9: Nueva Pompeya, CABA | F9: ≈ 8 km (aprox.) | H9: Comercial MID | I9: Don Torcuato, Tigre (PBA) | J9: ≈ 40 km (aprox.) | K9: Planilla MP-01 (Metalprisa) | L9: - | M9: Q-METALPRI (mail 09/09/2026) | N9: Cotizado | O9: MID cotizó 2½" × 2,6 (más pesado): alternativa con reserva; confirmar costura por resistencia (IRAM 3523 3.2.4.2 b)
A10: MP-CUELLO | B10: Cuello roscado de manuales | C10: Asiento roscado SAE 1020 M22 (1 kg) / M30 × 1,5 (2,5-10 kg), mecanizado bajo plano | D10: Eli-Met | E10: Albariño 2047, Mataderos, CABA | F10: ≈ 15 km (aprox.) | K10: Planilla MP-18/19: sin cotizar (Eli-Met cotizó la cupla M30 de carros) | L10: - | M10: Planilla MP-20/21 (cupla M30 $5.261; cupla 2½" $13.479 + IVA; 35-40 días) | N10: A cotizar | O10: Segundo tornero CNC a relevar
A11: MP-CUPLA | B11: Cupla soldable de rodantes | C11: Cupla SAE 1020 M30 × 1,5 (25/50 kg) / RBSP 2½" (70/100 kg) | D11: Eli-Met | E11: Albariño 2047, Mataderos, CABA | F11: ≈ 15 km (aprox.) | K11: Planilla MP-20/21: $5.261 / $13.479 c/u + IVA | L11: - | M11: Planilla MP-20/21 (cupla M30 $5.261; cupla 2½" $13.479 + IVA; 35-40 días) | N11: Cotizado | O11: 35-40 días
A12: TAPA-ROD-G | B12: Tapas (cúpula y fondo) 70 / 100 kg | C12: Casquete embutido toriesférico Ø390 × 4,75 LAC (15", 70 y 100 kg) | D12: Gockel Ingeniería S.R.L. | E12: San Carlos 755, Wilde, Avellaneda | F12: ≈ 5 km (aprox.) | G12: 011-7713-5110 · gockelingenieria@gmail.com | K12: Sin cotizar (la planilla MP-17 lo daba importado) | L12: Matrices de corte, punzonado, plegado y embutido en frío y en caliente | M12: Proveedor de FLAMA · gockelingenieria.com.ar | N12: A cotizar | O12: Embutido con matriz propia de Gockel (Wilde); cotizar con certificado de material de la chapa
A13: TAPA-ROD-C | B13: Tapas (cúpula y fondo) 25 / 50 kg | C13: Casquete embutido Ø276 / Ø320 × 3,2 LAC | D13: Gockel Ingeniería S.R.L. | E13: San Carlos 755, Wilde, Avellaneda | F13: ≈ 5 km (aprox.) | G13: 011-7713-5110 · gockelingenieria@gmail.com | K13: Sin cotizar (la planilla MP-15/16 lo daba importado) | L13: Matrices de corte, punzonado, plegado y embutido en frío y en caliente | M13: Proveedor de FLAMA · gockelingenieria.com.ar | N13: A cotizar | O13: Embutido con matriz propia de Gockel (Wilde); cotizar con certificado de material de la chapa
A14: C1 | B14: Alambre MAG | C14: ER70S-6 (AWS A5.18) Ø0,9 manuales / Ø1,2 rodantes, carrete 15 kg | D14: Conarco (ESAB Argentina) | E14: Venta por distribuidores de soldadura | F14: a confirmar | K14: Planilla MP-23/24: sin cotizar | L14: AWS A5.18 ER70S-6 | M14: Planilla MP-23/24 (sin cotizar) | N14: A cotizar | O14: Comprar al distribuidor de soldadura de zona sur
A15: C2 | B15: Gas de protección MAG | C15: Arcal 21 / ARCAL Speed: Ar + 8 % CO₂ (EN ISO 14175 M20-ArC-8) | D15: Air Liquide Argentina - sucursal Piñeyro | E15: Tte. Cnel. Guiffra 799, Piñeyro, Avellaneda | F15: ≈ 3 km (aprox.) | G15: 0810-222-5272 | H15: Gogniat | I15: GBA (gogniat.com.ar) | J15: a confirmar | K15: Planilla MP-25: $8.800/m³ + $1.000/m³ acarreo (batería 11 × 50 L) | L15: ARCAL 21 / ARCAL Speed EN ISO 14175 M20-ArC-8; N₂ ≥ 99,8 % | M15: Q-ARCAL · Q-N2 · planilla MP-25 ($8.800/m³ + acarreo) y MP-34 ($1.800/m³ + acarreo) | N15: Cotizado | O15: Decisión FLAMA: MAG 135; acreditar con el certificador (IRAM 3523 3.2.4.2 c)
A16: C3 | B16: Granalla de acero | C16: S330 / S390 esférica alto C (SAE J444 / ISO 11124-3), bolsa 25 kg | D16: CyM Materiales | E16: GBA (cymba@cym.com.ar) | F16: a confirmar | G16: cymba@cym.com.ar | H16: Roca Ingeniería | I16: San Justo, La Matanza (PBA) | J16: ≈ 20 km (aprox.) | K16: Planilla MP-28: $2.000/kg | L16: SAE J444 / ISO 11124-3 | M16: Planilla MP-28 ($2.000/kg) | N16: Cotizado
A17: C4M | B17: Pintura de manuales (servicio) | C17: Pintura en polvo poliéster al horno, rojo 03-1-050, por cilindro | D17: Prymax | E17: Según presupuesto S00469 | F17: a confirmar | H17: Pintor de carros (cotización por mensaje) | I17: Según cotización | J17: a confirmar | K17: Q-PRYMAX (S00469, por unidad) | L17: Pedir informe de niebla salina IRAM 121 | M17: Q-PRYMAX (S00469) | N17: Cotizado | O17: Tercerización sujeta a aceptación del Ministerio (Res. 349/07 art. 18)
A18: C4R | B18: Pintura de rodantes (servicio) | C18: Preparación por quemado + pintura en polvo rojo 03-1-050, por carro | D18: Pintor de carros (cotización por mensaje) | E18: Según cotización | F18: a confirmar | H18: Prymax | I18: Según presupuesto S00469 | J18: a confirmar | K18: Q-CARROS (por carro) | L18: Pedir informe de niebla salina IRAM 121 (3550 4.5: 240 h) | M18: Q-CARROS | N18: Cotizado | O18: Tercerización sujeta a aceptación del Ministerio (Res. 349/07 art. 18)
A19: VALV-1 | B19: Válvula 1 kg | C19: Válvula HZ M-22 con tubo de pesca plástico | D19: Polvex S.R.L. / Sancibrao | E19: Boulogne Sur Mer 1813, Villa Maipú, San Martín (PBA) | F19: ≈ 25 km (aprox.) | G19: 11 4405-3382 | H19: Mozart S.R.L. | I19: Ucrania 1564, Valentín Alsina, Lanús (PBA) | J19: ≈ 9 km (aprox.) | K19: Planilla MP-42: $4.200 c/u | L19: Polvo «según IRAM 3569» (sello no confirmado); válvulas HZ | M19: Q-AGENTES (lista de precios) | N19: Cotizado | O19: Mozart fabrica válvulas (licencias IRAM 3509 / 3565): cotizar
A20: VALV-M30 | B20: Válvula 2,5 a 10 kg | C20: Válvula HZ M-30 × 1,5 con resorte y tubo 7/8 | D20: Polvex S.R.L. / Sancibrao | E20: Boulogne Sur Mer 1813, Villa Maipú, San Martín (PBA) | F20: ≈ 25 km (aprox.) | G20: 11 4405-3382 | H20: Mozart S.R.L. | I20: Ucrania 1564, Valentín Alsina, Lanús (PBA) | J20: ≈ 9 km (aprox.) | K20: Planilla MP-43: $6.800 c/u | L20: Polvo «según IRAM 3569» (sello no confirmado); válvulas HZ | M20: Q-AGENTES (lista de precios) | N20: Cotizado
A21: VALV-CARRO | B21: Válvula de carro | C21: Válvula HZ de carro 25 kg (traba, manija, resorte) / 50-70-100 kg | D21: Polvex S.R.L. / Sancibrao | E21: Boulogne Sur Mer 1813, Villa Maipú, San Martín (PBA) | F21: ≈ 25 km (aprox.) | G21: 11 4405-3382 | H21: Mozart S.R.L. | I21: Ucrania 1564, Valentín Alsina, Lanús (PBA) | J21: ≈ 9 km (aprox.) | K21: Planilla MP-44: $7.500 c/u | L21: Polvo «según IRAM 3569» (sello no confirmado); válvulas HZ | M21: Q-AGENTES (lista de precios) | N21: Cotizado
A22: MANOMETRO | B22: Manómetro | C22: Manómetro con sello IRAM 3533, 1,4 MPa (rosca de la válvula) | D22: Yukon / MatafuegosYa S.R.L. | E22: Estomba 954, CABA | F22: ≈ 12 km (aprox.) | G22: 4555-5100 | H22: Matafuegos Iglesias | I22: Av. Entre Ríos 1127, CABA | J22: ≈ 7 km (aprox.) | K22: Planilla MP-45: sin cotizar | L22: Vástagos, manómetros, etiquetas, mangueras, toberas y válvulas | M22: Registro de proveedores PJN · Q-YUKON (equipos) | N22: A validar | O22: Ambos venden manómetros sueltos: confirmar sello IRAM 3533 en la cotización
A23: REP-VALV | B23: Repuestos de válvula | C23: Manijas, eje, pasador, disco de seguridad de la válvula HZ | D23: Polvex S.R.L. / Sancibrao | E23: Boulogne Sur Mer 1813, Villa Maipú, San Martín (PBA) | F23: ≈ 25 km (aprox.) | G23: 11 4405-3382 | H23: Yukon / MatafuegosYa S.R.L. | I23: Estomba 954, CABA | J23: ≈ 12 km (aprox.) | K23: Q-AGENTES (válvula armada) | L23: Polvo «según IRAM 3569» (sello no confirmado); válvulas HZ | M23: Q-AGENTES (lista de precios) | N23: A cotizar | O23: Vienen con la válvula armada; sueltos sólo para recarga
A24: DESC-MAN | B24: Manga y tobera de manuales | C24: Manguera EPDM/NBR trenzada ≥ 350 mm con racor + tobera (PH 2 × Ps) | D24: Yukon / MatafuegosYa S.R.L. | E24: Estomba 954, CABA | F24: ≈ 12 km (aprox.) | G24: 4555-5100 | H24: Matafuegos Iglesias | I24: Av. Entre Ríos 1127, CABA | J24: ≈ 7 km (aprox.) | K24: Planilla MP-48: sin cotizar | L24: Vástagos, manómetros, etiquetas, mangueras, toberas y válvulas | M24: Registro de proveedores PJN · Q-YUKON (equipos) | N24: A cotizar | O24: Pedir ensayo de PH de la manga (IRAM 3523 4.2)
A25: DESC-ROD | B25: Manga, lanza y válvula de rodantes | C25: Manguera armada 5 / 12 m + lanza o válvula esférica + tobera campana | D25: Yukon / MatafuegosYa S.R.L. | E25: Estomba 954, CABA | F25: ≈ 12 km (aprox.) | G25: 4555-5100 | H25: Matafuegos Iglesias | I25: Av. Entre Ríos 1127, CABA | J25: ≈ 7 km (aprox.) | K25: Planilla MP-49: sin cotizar | L25: Vástagos, manómetros, etiquetas, mangueras, toberas y válvulas | M25: Registro de proveedores PJN · Q-YUKON (equipos) | N25: A cotizar
A26: ORING | B26: Junta tórica | C26: O-ring NBR 70 Shore A, medida del cuello | D26: Argensold | E26: Av. J. M. de Rosas 698, Lomas del Mirador (PBA) | F26: ≈ 20 km (aprox.) | G26: 4699-3788 | H26: Matafuegos Iglesias | I26: Av. Entre Ríos 1127, CABA | J26: ≈ 7 km (aprox.) | K26: Planilla MP-50: sin cotizar | L26: O-rings AS-568 en NBR | M26: Web o-ring.com.ar (producto verificado) | N26: A cotizar
A27: RUEDA-300 | B27: Rueda Ø300 (carro 25 kg) | C27: Rueda de chapa y goma Ø300 × 50, buje liso para eje 3/4" | D27: Ruedar | E27: Gral. Paunero 557, Ciudad Madero, La Matanza (PBA) | F27: ≈ 20 km (aprox.) | G27: 4442-4752 | K27: Planilla MP-54: sin cotizar | L27: Goma maciza vulcanizada: Ø300 × 60 (M-1509, buje 20, 250 kg); Ø350 × 60 (buje 20/25/28, 150 kg) | M27: Catálogo web ruedar.com.ar (sin cotización) | N27: A validar | O27: Proceso de carros final (8.1): Ø300 × 50, agujero 3/4"
A28: RUEDA-350 | B28: Rueda Ø350 (carro 50 kg) | C28: Rueda de chapa y goma Ø350 × 60, buje liso para eje 1" | D28: Ruedar | E28: Gral. Paunero 557, Ciudad Madero, La Matanza (PBA) | F28: ≈ 20 km (aprox.) | G28: 4442-4752 | H28: Escanort S.A. | I28: San Martín 1930, Florida, Vicente López (PBA) | J28: ≈ 22 km (aprox.) | K28: Planilla MP-54: sin cotizar | L28: Goma maciza vulcanizada: Ø300 × 60 (M-1509, buje 20, 250 kg); Ø350 × 60 (buje 20/25/28, 150 kg) | M28: Catálogo web ruedar.com.ar (sin cotización) | N28: A cotizar | O28: Proceso de carros final (8.1): Ø350 × 60, agujero 1"
A29: RUEDA-400 | B29: Rueda Ø400 (carros 70 / 100 kg) | C29: Rueda de chapa y goma Ø400 × 60, buje liso para eje 1" | D29: Escanort S.A. | E29: San Martín 1930, Florida, Vicente López (PBA) | F29: ≈ 22 km (aprox.) | G29: 4795-0943 | H29: Ruedar | I29: Gral. Paunero 557, Ciudad Madero, La Matanza (PBA) | J29: ≈ 20 km (aprox.) | K29: Sin cotizar | L29: Ø400 × 100 neumática, rodamiento para eje 25, 200 kg (no maciza) | M29: Web escanort.com.ar | N29: A cotizar | O29: Proceso de carros final (8.1): Ø400 × 60, agujero 1"
A30: MP-EJE | B30: Eje de ruedas | C30: Barra trefilada SAE 1045 3/4" (25 kg, barra 4 m) o 1" (50 a 100 kg, barra 6 m) | D30: Vladimirsky | E30: - | F30: a confirmar | H30: Hierros Parrotta | I30: Av. Debenedetti 2851, Avellaneda | J30: ≈ 3 km (aprox.) | K30: Sin cotizar | L30: Barras de 4 m hasta Ø20 y de 6 m de 21 a 30 mm; demora a confirmar | M30: Proceso de carros final (8.1) | N30: A cotizar | O30: Proceso de carros final (8.1): corte 490 / 510 / 590; va al montaje final con ruedas, arandelas y pasadores
A31: MP-CANO-CARRO | B31: Caño de la manija del carro | C31: Caño SAE 1010 1" × 2,0, barra 6 m | D31: Metalpri / Prilux | E31: Nueva Pompeya, CABA | F31: ≈ 8 km (aprox.) | H31: Comercial MID | I31: Don Torcuato, Tigre (PBA) | J31: ≈ 40 km (aprox.) | K31: Sin cotizar (mismo proveedor que el caño del 1 kg) | L31: - | M31: Q-METALPRI (mail 09/09/2026) | N31: A cotizar | O31: Corte 1440 / 1520 / 1590 (proceso, kit 8.1)
A32: MP-PORTAEJE | B32: Caño del eje del carro | C32: Caño SAE 1010 1¼" × 2,0 (1" × 2,0 en 25 kg), barra 6 m | D32: Metalpri / Prilux | E32: Nueva Pompeya, CABA | F32: ≈ 8 km (aprox.) | H32: Comercial MID | I32: Don Torcuato, Tigre (PBA) | J32: ≈ 40 km (aprox.) | K32: Sin cotizar (mismo proveedor que el caño de la manija) | L32: - | M32: Q-METALPRI (mail 09/09/2026) | N32: A cotizar | O32: Largo 354 / 354 / 434 con marca de la mitad (proceso, kit 8.1)
A33: ARANDELA-TOPE | B33: Arandela de tope del eje de carro | C33: Arandela SAE 1010 Ø40 × 4 (Ø int. eje + 1) | D33: Hierros Parrotta | E33: Av. Debenedetti 2851, Avellaneda | F33: ≈ 3 km (aprox.) | K33: Sin cotizar | L33: - | M33: Q-PARROTTA (00413329) | N33: A cotizar | O33: Montaje final, con las ruedas (proceso de carros, puesto 8)
A34: PASADOR-EJE | B34: Pasador del eje de carro | C34: Pasador partido acero Ø4 × 40 | D34: Hierros Parrotta | E34: Av. Debenedetti 2851, Avellaneda | F34: ≈ 3 km (aprox.) | K34: Sin cotizar | L34: - | M34: Q-PARROTTA (00413329) | N34: A cotizar | O34: Montaje final, con las ruedas (proceso de carros, puesto 8)
A35: POLVO-ABC | B35: Polvo ABC | C35: Polvo ABC con Sello IRAM 3569, grado del modelo (DEM-60 / DEM-90), bolsa 25 kg | D35: DEM S.A. (DEMSA) | E35: Ruta 9 km 79, Campana (PBA) | F35: ≈ 85 km (aprox.) | H35: Polvex S.R.L. / Sancibrao | I35: Boulogne Sur Mer 1813, Villa Maipú, San Martín (PBA) | J35: ≈ 25 km (aprox.) | K35: Lista Q-AGENTES (Sancibrao ABC 55/75/90) | L35: Sello IRAM 3569 (ABC) y BVQI | M35: L-DEMSA · L-DRAGO (potencial con DEM-60/90) | N35: Cotizado | O35: DEMSA: sello IRAM 3569 y potencial de referencia (licencia Drago). Polvex: sello no confirmado; con ese polvo el potencial sale del ensayo de tipo de FLAMA
A36: N2 | B36: Nitrógeno seco | C36: N₂ ≥ 99,8 %, H₂O ≤ 40 ppm, batería 11 × 50 L 200 bar | D36: Air Liquide Argentina - sucursal Piñeyro | E36: Tte. Cnel. Guiffra 799, Piñeyro, Avellaneda | F36: ≈ 3 km (aprox.) | G36: 0810-222-5272 | H36: Gogniat | I36: GBA (gogniat.com.ar) | J36: a confirmar | K36: Planilla MP-34: $1.800/m³ + $1.000/m³ acarreo | L36: ARCAL 21 / ARCAL Speed EN ISO 14175 M20-ArC-8; N₂ ≥ 99,8 % | M36: Q-ARCAL · Q-N2 · planilla MP-25 ($8.800/m³ + acarreo) y MP-34 ($1.800/m³ + acarreo) | N36: Cotizado
A37: ETIQUETA | B37: Etiqueta del extintor | C37: Vinilo autoadhesivo laminado UV, panel 108° + alas (hoja 4 del plano) | D37: Astuprint | E37: Tte. Cnel. Guiffra 970, Piñeyro, Avellaneda | F37: ≈ 3 km (aprox.) | H37: Multilabel Argentina S.A. | I37: Planta: Rodríguez Peña 1616 (GBA) | J37: a confirmar | K37: Planilla MP-56: sin cotizar | L37: Vinilo / PP con laminado UV | M37: Web (sin cotización) | N37: A cotizar
A38: ETIQ-SERIE | B38: Etiqueta de serie GS1 | C38: Poliéster autoadhesivo 45 × 25 con QR GS1 (GTIN 779) | D38: Astuprint | E38: Tte. Cnel. Guiffra 970, Piñeyro, Avellaneda | F38: ≈ 3 km (aprox.) | H38: GS1 Argentina | I38: CABA | J38: ≈ 10 km (aprox.) | K38: Sin cotizar | L38: Vinilo / PP con laminado UV | M38: Web (sin cotización) | N38: A cotizar | O38: GS1 asigna los códigos; la imprenta imprime
A39: FAJA | B39: Faja de garantía | C39: Vinilo destructible rayado rojo-blanco 30 × 40 | D39: Astuprint | E39: Tte. Cnel. Guiffra 970, Piñeyro, Avellaneda | F39: ≈ 3 km (aprox.) | H39: Multilabel Argentina S.A. | I39: Planta: Rodríguez Peña 1616 (GBA) | J39: a confirmar | K39: Sin cotizar | L39: Vinilo / PP con laminado UV | M39: Web (sin cotización) | N39: A cotizar
A40: FAJA-SUS | B40: Faja amarilla de sustituto | C40: Vinilo autoadhesivo amarillo, alto ≤ 40 mm, 3 leyendas | D40: Astuprint | E40: Tte. Cnel. Guiffra 970, Piñeyro, Avellaneda | F40: ≈ 3 km (aprox.) | H40: Multilabel Argentina S.A. | I40: Planta: Rodríguez Peña 1616 (GBA) | J40: a confirmar | K40: Sin cotizar | L40: Vinilo / PP con laminado UV | M40: Web (sin cotización) | N40: A cotizar | O40: IRAM 3517-2:2020 9.4.5
A41: PRECINTO | B41: Precinto de fábrica | C41: Precinto plástico numerado de color con «FLAMA» | D41: SonFuertes (vía Papelera Damián) | E41: GBA | F41: a confirmar | H41: Precinter S.R.L. | I41: Vera 518, Villa Crespo, CABA | J41: ≈ 10 km (aprox.) | K41: Planilla MP-51: sin cotizar | L41: Numeración correlativa, color a pedido | M41: Web (sin cotización) | N41: A cotizar
A42: OBLEA-PBA | B42: Oblea PBA | C42: Oblea oficial Ø46 (Res. 522/07) | D42: Ministerio de Ambiente PBA (ex OPDS) | E42: La Plata (PBA) | F42: ≈ 55 km (aprox.) | K42: Arancel oficial | L42: Res. 522/07 · Res. 349/07 | M42: N-349 | N42: Cotizado | O42: Se adquiere al organismo
A43: ESTAMPILLA | B43: Estampilla IRAM | C43: Estampilla de conformidad (Anexo R) | D43: IRAM - Instituto Argentino de Normalización | E43: Perú 552/556, CABA | F43: ≈ 6 km (aprox.) | K43: Arancel de la licencia | L43: Anexo R (DC-PG-129) | M43: N-3523 | N43: Cotizado | O43: Se adquiere al organismo
A44: TARJETA-AGC | B44: Tarjeta AGC | C44: Tarjeta de dos módulos (papel con QR + etiqueta AGC) | D44: Agencia Gubernamental de Control (CABA) | E44: CABA | F44: ≈ 6 km (aprox.) | K44: Arancel oficial | L44: Ord. 40.473 · Res. AGC 32/15 | M44: N-AGC | N44: Cotizado | O44: Sólo destino CABA
A45: TARJETA-DPS | B45: Tarjeta DPS | C45: Tarjeta oficial DPS (Res. 349/07 art. 21 / 32) | D45: Ministerio de Ambiente PBA (ex OPDS) | E45: La Plata (PBA) | F45: ≈ 55 km (aprox.) | K45: Arancel oficial | L45: Res. 522/07 · Res. 349/07 | M45: N-349 | N45: Cotizado | O45: Sólo PBA
A46: SOPORTE | B46: Soporte de pared / vehicular | C46: Soporte de chapa SAE 1010 pintado según FL_ACC_01 / 02 | D46: Maxiseguridad | E46: Vélez Sarsfield 5263, Munro (PBA) | F46: ≈ 25 km (aprox.) | G46: 4756-3979 | H46: CM Representaciones | I46: GBA | J46: a confirmar | K46: Planilla MP-52: sin cotizar | L46: Soportes de chapa para 1 kg, de pared y de piso | M46: Web catalogo.maxiseguridad.com.ar (producto verificado) | N46: A cotizar
A47: TORNILLERIA | B47: Tornillo y tarugo | C47: Tornillo M8 + tarugo nylon Ø10 | D47: Würth Argentina | E47: Sucursales GBA | F47: a confirmar | K47: Sin cotizar | L47: - | M47: Web (sin cotización) | N47: A cotizar
A48: CAJA | B48: Caja de cartón corrugado | C48: Caja a medida del modelo (medida del plano), simple o doble | D48: Maxipack | E48: Aldecoa 953, Avellaneda | F48: ≈ 3 km (aprox.) | G48: 5281-8000 | H48: Cartocan | I48: La Rioja 1642, Avellaneda | J48: ≈ 3 km (aprox.) | K48: Planilla MP-59: $1.500 por caja 2,5-10 kg (evaluación económica) | L48: Corrugado simple / doble | M48: Web (sin cotización) | N48: A cotizar | O48: Ambos en Avellaneda
A49: FUNDA | B49: Funda y esquineros de rodantes | C49: Funda de PE + esquineros de cartón | D49: MV Embalajes | E49: Zona Oeste (PBA) | F49: a confirmar | G49: 7520-0870 · ventas@mvembalajes.com.ar | H49: Embalpack | I49: Nicasio Oroño 2444, CABA | J49: ≈ 10 km (aprox.) | K49: Planilla MP-64: sin cotizar | L49: Film stretch y cinta de embalaje | M49: Web mvembalajes.com (producto verificado) | N49: A cotizar
A50: PALLET | B50: Pallet | C50: Pallet de madera 1200 × 1000 (IRAM 10016) | D50: IndusPallets | E50: Las Higueritas 548, Lanús Este (PBA) | F50: ≈ 8 km (aprox.) | G50: 4220-9600 | K50: Planilla MP-60: sin cotizar | L50: 1200 × 1000 (IRAM 10016) | M50: Web (sin cotización) | N50: A cotizar
A51: FILM | B51: Film stretch | C51: Film LLDPE 23 µm × 500 mm, pre-estirable 250 % | D51: MV Embalajes | E51: Zona Oeste (PBA) | F51: a confirmar | G51: 7520-0870 · ventas@mvembalajes.com.ar | H51: Embalpack | I51: Nicasio Oroño 2444, CABA | J51: ≈ 10 km (aprox.) | K51: Planilla MP-63: sin cotizar | L51: Film stretch y cinta de embalaje | M51: Web mvembalajes.com (producto verificado) | N51: A cotizar
A52: CINTA | B52: Cinta de embalaje | C52: Cinta PP 48 mm × 100 m, adhesivo acrílico | D52: MV Embalajes | E52: Zona Oeste (PBA) | F52: a confirmar | G52: 7520-0870 · ventas@mvembalajes.com.ar | H52: Embalpack | I52: Nicasio Oroño 2444, CABA | J52: ≈ 10 km (aprox.) | K52: Sin cotizar | L52: Film stretch y cinta de embalaje | M52: Web mvembalajes.com (producto verificado) | N52: A cotizar
A53: ESQUINERO | B53: Esquineros de cartón | C53: Esquinero 50 × 50 × 1200 | D53: Maxipack | E53: Aldecoa 953, Avellaneda | F53: ≈ 3 km (aprox.) | G53: 5281-8000 | H53: Cartocan | I53: La Rioja 1642, Avellaneda | J53: ≈ 3 km (aprox.) | K53: Planilla MP-64: sin cotizar | L53: Corrugado simple / doble | M53: Web (sin cotización) | N53: A cotizar
A54: SEPARADOR | B54: Separador de capa | C54: Plancha de cartón 1200 × 1000 | D54: Maxipack | E54: Aldecoa 953, Avellaneda | F54: ≈ 3 km (aprox.) | G54: 5281-8000 | H54: Cartocan | I54: La Rioja 1642, Avellaneda | J54: ≈ 3 km (aprox.) | K54: Planilla MP-61: sin cotizar | L54: Corrugado simple / doble | M54: Web (sin cotización) | N54: A cotizar
A55: ETIQ-PALLET | B55: Etiqueta de pallet | C55: Papel térmico 100 × 150 | D55: Astuprint | E55: Tte. Cnel. Guiffra 970, Piñeyro, Avellaneda | F55: ≈ 3 km (aprox.) | H55: Multilabel Argentina S.A. | I55: Planta: Rodríguez Peña 1616 (GBA) | J55: a confirmar | K55: Sin cotizar | L55: Vinilo / PP con laminado UV | M55: Web (sin cotización) | N55: A cotizar
A56: IMPRESOS | B56: Impresos (instructivo, protocolo, remito) | C56: Impresión offset A5 | D56: Astuprint | E56: Tte. Cnel. Guiffra 970, Piñeyro, Avellaneda | F56: ≈ 3 km (aprox.) | K56: Sin cotizar | L56: Vinilo / PP con laminado UV | M56: Web (sin cotización) | N56: A cotizar
A57: TAPON | B57: Tapón protector de rosca | C57: Tapón PE para M22 / M30 / RBSP 2½" | D57: Sin proveedor nacional identificado | K57: Planilla MP-62: inyectora local sin identificar | N57: No cumple / a definir | O57: Sin proveedor nacional identificado
A58: EQ-CO2 | B58: Extintor de CO₂ terminado | C58: Extintor CO₂ con sello IRAM 3509 (cilindro IRAM 2533) | D58: Mozart S.R.L. | E58: Ucrania 1564, Valentín Alsina, Lanús (PBA) | F58: ≈ 9 km (aprox.) | G58: 4218-3690 · info@mozartsrl.com.ar | H58: Matafuegos Georgia - venta mayorista | I58: Gral. Manuel A. Rodríguez 2838, CABA | J58: ≈ 15 km (aprox.) | K58: Sin cotizar | L58: Licencias IRAM de extintores y cilindros (2525/2526/2533, 3509, 3565) | M58: Web (sin cotización) | N58: A cotizar | O58: Mozart: licencias de cilindros y extintores de CO₂
A59: EQ-AGUA | B59: Extintor de agua terminado | C59: Extintor de agua 10 L inoxidable con sello IRAM 3525 | D59: Matafuegos Georgia - venta mayorista | E59: Gral. Manuel A. Rodríguez 2838, CABA | F59: ≈ 15 km (aprox.) | G59: 4585-4400 · ventas@matafuegosgeorgia.com | H59: Drago (Luis Pasquinelli e Hijos S.A.) | I59: Saladillo 1884, Castelar (PBA) | J59: ≈ 30 km (aprox.) | K59: Sin cotizar | L59: Sello IRAM en sus extintores (fichas técnicas F1) | M59: Fichas técnicas (sin cotización de repuestos) | N59: A cotizar | O59: Drago: licencia IRAM 3525
A60: EQ-AFFF | B60: Extintor AFFF terminado | C60: Extintor AFFF con sello IRAM 3527 (manual) / 3541 (rodante) | D60: Matafuegos Georgia - venta mayorista | E60: Gral. Manuel A. Rodríguez 2838, CABA | F60: ≈ 15 km (aprox.) | G60: 4585-4400 · ventas@matafuegosgeorgia.com | H60: Drago (Luis Pasquinelli e Hijos S.A.) | I60: Saladillo 1884, Castelar (PBA) | J60: ≈ 30 km (aprox.) | K60: Sin cotizar | L60: Sello IRAM en sus extintores (fichas técnicas F1) | M60: Fichas técnicas (sin cotización de repuestos) | N60: A cotizar | O60: Drago: licencia IRAM 3527 (10 L)
A61: EQ-K | B61: Extintor clase K terminado | C61: Extintor de acetato de potasio con sello IRAM 3694 | D61: Matafuegos Georgia - venta mayorista | E61: Gral. Manuel A. Rodríguez 2838, CABA | F61: ≈ 15 km (aprox.) | G61: 4585-4400 · ventas@matafuegosgeorgia.com | H61: Drago (Luis Pasquinelli e Hijos S.A.) | I61: Saladillo 1884, Castelar (PBA) | J61: ≈ 30 km (aprox.) | K61: Sin cotizar | L61: Sello IRAM en sus extintores (fichas técnicas F1) | M61: Fichas técnicas (sin cotización de repuestos) | N61: A cotizar | O61: Licencias 3694 de Drago y Georgia/Fadesa
A62: EQ-HCFC | B62: Extintor HCFC / HFC terminado | C62: Extintor de agente limpio con sello IRAM 3504 | D62: Matafuegos Georgia - venta mayorista | E62: Gral. Manuel A. Rodríguez 2838, CABA | F62: ≈ 15 km (aprox.) | G62: 4585-4400 · ventas@matafuegosgeorgia.com | H62: Melisam | I62: Los Ceibos 428, San Isidro (PBA) | J62: ≈ 30 km (aprox.) | K62: Sin cotizar | L62: Sello IRAM en sus extintores (fichas técnicas F1) | M62: Fichas técnicas (sin cotización de repuestos) | N62: A cotizar | O62: Drago también tiene licencia 3504
A63: EQ-BC | B63: Extintor BC terminado | C63: Extintor de polvo BC con sello IRAM 3523 | D63: Matafuegos Georgia - venta mayorista | E63: Gral. Manuel A. Rodríguez 2838, CABA | F63: ≈ 15 km (aprox.) | G63: 4585-4400 · ventas@matafuegosgeorgia.com | H63: Melisam | I63: Los Ceibos 428, San Isidro (PBA) | J63: ≈ 30 km (aprox.) | K63: Sin cotizar | L63: Sello IRAM en sus extintores (fichas técnicas F1) | M63: Fichas técnicas (sin cotización de repuestos) | N63: A cotizar
